{
  "type": "Feature",
  "properties": {
    "iso:country":"US",
    "sg:address":"311 W Side Ave",
    "sg:city":"Jersey City",
    "sg:classifiers":[
        {
            "category":"Retail",
            "subcategory":"Auto Repair",
            "type":"Services"
        }
    ],
    "sg:phone":"+1 201 432 1800",
    "sg:postcode":"07305",
    "sg:province":"NJ",
    "wof:name":"All Aspects Automotive Inc",
    "wof:placetype":"venue"
},
  "geometry": {"coordinates":[-74.09050000000001,40.713001],"type":"Point"}
}