{
  "type": "Feature",
  "properties": {
    "iso:country":"US",
    "sg:address":"13 Gordon Ct",
    "sg:city":"Port Monmouth",
    "sg:classifiers":[
        {
            "category":"Building & Trades",
            "subcategory":"Construction",
            "type":"Services"
        }
    ],
    "sg:phone":"+1 732 787 8679",
    "sg:postcode":"07758",
    "sg:province":"NJ",
    "sg:tags":[
        "home",
        "improvement"
    ],
    "wof:name":"Scalzo Home Improvements Inc",
    "wof:placetype":"venue"
},
  "geometry": {"coordinates":[-74.102531,40.431082],"type":"Point"}
}