{
  "type": "Feature",
  "properties": {
    "addr:full":"1065 E Jersey St Elizabeth NJ 07201",
    "addr:housenumber":"1065",
    "addr:postcode":"07201",
    "addr:street":"E Jersey St",
    "iso:country":"US",
    "sg:address":"1065 E Jersey St",
    "sg:city":"Elizabeth",
    "sg:classifiers":[
        {
            "category":"Shopping",
            "type":"Retail Goods"
        }
    ],
    "sg:phone":"+1   ",
    "sg:postcode":"07201",
    "sg:province":"NJ",
    "sg:tags":[
        "merchandise"
    ],
    "wof:name":"Mitra Mdo Fire Extinguisher SE",
    "wof:placetype":"venue"
},
  "geometry": {"coordinates":[-74.210966,40.663947],"type":"Point"}
}