{
  "type": "Feature",
  "properties": {
    "iso:country":"US",
    "sg:address":"21 Patriot Xing",
    "sg:city":"Rockaway",
    "sg:classifiers":[
        {
            "category":"Building & Trades",
            "subcategory":"Construction",
            "type":"Services"
        }
    ],
    "sg:phone":"+1 973 983 7979",
    "sg:postcode":"07866",
    "sg:province":"NJ",
    "sg:tags":[
        "house"
    ],
    "wof:name":"Tqm Construction Corp",
    "wof:placetype":"venue"
},
  "geometry": {"coordinates":[-74.55265799999999,40.901779],"type":"Point"}
}