{
  "type": "Feature",
  "properties": {
    "addr:full":"3 Broadway Fair Lawn NJ 07410",
    "addr:housenumber":"3",
    "addr:postcode":"07410",
    "addr:street":"Broadway",
    "iso:country":"US",
    "sg:address":"3 Broadway",
    "sg:city":"Fair Lawn",
    "sg:classifiers":[
        {
            "category":"Wholesale",
            "subcategory":"Electrical",
            "type":"Manufacturing & Wholesale Goods"
        }
    ],
    "sg:phone":"+1 201 796 6900",
    "sg:postcode":"07410",
    "sg:province":"NJ",
    "sg:tags":[
        "shaver"
    ],
    "wof:name":"Shavers-N-More",
    "wof:placetype":"venue"
},
  "geometry": {"coordinates":[-74.107726,40.923636],"type":"Point"}
}