{
  "type": "Feature",
  "properties": {
    "iso:country":"US",
    "sg:address":"80 Prospect St",
    "sg:city":"Midland Park",
    "sg:classifiers":[
        {
            "category":"Professional",
            "type":"Services"
        }
    ],
    "sg:phone":"+1 201 493 0602",
    "sg:postcode":"07432",
    "sg:province":"NJ",
    "wof:name":"Daniel Services",
    "wof:placetype":"venue"
},
  "geometry": {"coordinates":[-74.14070599999999,40.9944],"type":"Point"}
}