{
  "type": "Feature",
  "properties": {
    "addr:full":"20 Chancellor Ave Newark NJ 07112",
    "addr:housenumber":"20",
    "addr:postcode":"07112",
    "addr:street":"Chancellor Ave",
    "iso:country":"US",
    "sg:address":"20 Chancellor Ave",
    "sg:city":"Newark",
    "sg:classifiers":[
        {
            "category":"Professional",
            "subcategory":"Business Services",
            "type":"Services"
        }
    ],
    "sg:phone":"+1   ",
    "sg:postcode":"07112",
    "sg:province":"NJ",
    "wof:name":"Lj Associates Contracting",
    "wof:placetype":"venue"
},
  "geometry": {"coordinates":[-74.211803,40.703363],"type":"Point"}
}