{
  "type": "Feature",
  "properties": {
    "iso:country":"US",
    "sg:address":"121 Stonehurst Dr",
    "sg:city":"Tenafly",
    "sg:classifiers":[
        {
            "category":"Professional",
            "subcategory":"Research",
            "type":"Services"
        }
    ],
    "sg:phone":"+1 201 871 0794",
    "sg:postcode":"07670",
    "sg:province":"NJ",
    "sg:tags":[
        "organization",
        "noncommercial"
    ],
    "wof:name":"Life Cycle Institute Corp",
    "wof:placetype":"venue"
},
  "geometry": {"coordinates":[-73.955187,40.917031],"type":"Point"}
}