{
  "type": "Feature",
  "properties": {
    "iso:country":"US",
    "sg:address":"1351 State Rte 38",
    "sg:city":"Hainesport",
    "sg:classifiers":[
        {
            "category":"Personal",
            "subcategory":"Beauty Salon",
            "type":"Services"
        }
    ],
    "sg:phone":"+1 609 267 5005",
    "sg:postcode":"08036",
    "sg:province":"NJ",
    "sg:tags":[
        "shop"
    ],
    "wof:name":"Shear Perfection LLC",
    "wof:placetype":"venue"
},
  "geometry": {"coordinates":[-74.82199,39.979812],"type":"Point"}
}