{
  "type": "Feature",
  "properties": {
    "addr:full":"200 E Chestnut St Bordentown NJ 08505",
    "addr:housenumber":"200",
    "addr:postcode":"08505",
    "addr:street":"E Chestnut St",
    "iso:country":"US",
    "sg:address":"200 E Chestnut St",
    "sg:city":"Bordentown",
    "sg:classifiers":[
        {
            "category":"Real Estate",
            "subcategory":"Real Estate Operator",
            "type":"Services"
        }
    ],
    "sg:phone":"+1 609 298 1561",
    "sg:postcode":"08505",
    "sg:province":"NJ",
    "sg:tags":[
        "apartment"
    ],
    "wof:name":"Chestnut Village Apartments",
    "wof:placetype":"venue"
},
  "geometry": {"coordinates":[-74.703626,40.144098],"type":"Point"}
}