{
  "type": "Feature",
  "properties": {
    "iso:country":"US",
    "sg:address":"224 Fairview Ave",
    "sg:city":"Westwood",
    "sg:classifiers":[
        {
            "category":"Education",
            "subcategory":"Vocational School",
            "type":"Public Place"
        }
    ],
    "sg:phone":"+1 201 664 5557",
    "sg:postcode":"07675",
    "sg:province":"NJ",
    "wof:name":"Thermo Rite Sales of N J",
    "wof:placetype":"venue"
},
  "geometry": {"coordinates":[-74.031775,40.993825],"type":"Point"}
}