{
  "type": "Feature",
  "properties": {
    "addr:full":"11 Madison St S Bound Brook NJ 08880",
    "addr:housenumber":"11",
    "addr:postcode":"08880",
    "addr:street":"Madison St S",
    "iso:country":"US",
    "sg:address":"11 Madison St",
    "sg:city":"S Bound Brook",
    "sg:classifiers":[
        {
            "category":"Government",
            "subcategory":"Post Office",
            "type":"Public Place"
        }
    ],
    "sg:phone":"+1 732 356 1255",
    "sg:postcode":"08880",
    "sg:province":"NJ",
    "sg:tags":[
        "postal",
        "us"
    ],
    "wof:name":"US Post Office",
    "wof:placetype":"venue"
},
  "geometry": {"coordinates":[-74.531792,40.558104],"type":"Point"}
}