{
  "type": "Feature",
  "properties": {
    "iso:country":"US",
    "sg:address":"2052 Morris Ave",
    "sg:city":"Union",
    "sg:classifiers":[
        {
            "category":"Health Services",
            "subcategory":"Medical Lab",
            "type":"Services"
        }
    ],
    "sg:phone":"+1 908 686 0809",
    "sg:postcode":"07083",
    "sg:province":"NJ",
    "sg:tags":[
        "laboratory"
    ],
    "wof:name":"M Joseph Feman MD",
    "wof:placetype":"venue"
},
  "geometry": {"coordinates":[-74.27252900000001,40.696911],"type":"Point"}
}