{
  "type": "Feature",
  "properties": {
    "iso:country":"US",
    "sg:address":"5 Robin Dr",
    "sg:city":"Randolph",
    "sg:classifiers":[
        {
            "category":"Farming",
            "subcategory":"Farm",
            "type":"Manufacturing & Wholesale Goods"
        }
    ],
    "sg:phone":"+1 973 361 7136",
    "sg:postcode":"07869",
    "sg:province":"NJ",
    "sg:tags":[
        "crop",
        "general"
    ],
    "wof:name":"Mineur Farm LLC",
    "wof:placetype":"venue"
},
  "geometry": {"coordinates":[-74.55924,40.860345],"type":"Point"}
}