{
  "type": "Feature",
  "properties": {
    "iso:country":"US",
    "sg:address":"799 US Highway 46 Ste 100",
    "sg:city":"Parsippany",
    "sg:classifiers":[
        {
            "category":"Food & Beverages",
            "subcategory":"Liquor & Beverages",
            "type":"Retail Goods"
        }
    ],
    "sg:phone":"+1 973 402 1300",
    "sg:postcode":"07054",
    "sg:province":"NJ",
    "sg:tags":[
        "beer",
        "spirit",
        "wine"
    ],
    "wof:name":"Bottle King Inc",
    "wof:placetype":"venue"
},
  "geometry": {"coordinates":[-74.377484,40.862105],"type":"Point"}
}