{
  "type": "Feature",
  "properties": {
    "iso:country":"US",
    "sg:address":"217 State Rte 94",
    "sg:city":"Vernon",
    "sg:classifiers":[
        {
            "category":"Travel",
            "subcategory":"Hotels & Motels",
            "type":"Entertainment"
        }
    ],
    "sg:phone":"+1 973 209 7080",
    "sg:postcode":"07462",
    "sg:province":"NJ",
    "sg:tags":[
        "breakfast",
        "accommodation",
        "bed"
    ],
    "wof:name":"Alpine Haus",
    "wof:placetype":"venue"
},
  "geometry": {"coordinates":[-74.48845900000001,41.198472],"type":"Point"}
}