{
  "type": "Feature",
  "properties": {
    "iso:country":"US",
    "sg:address":"1000 Crawford Pl",
    "sg:city":"Mount Laurel",
    "sg:classifiers":[
        {
            "category":"Retail",
            "subcategory":"Car Wash",
            "type":"Services"
        }
    ],
    "sg:phone":"+1 856 778 2300",
    "sg:postcode":"08054",
    "sg:province":"NJ",
    "sg:tags":[
        "consumer",
        "safe",
        "operates",
        "facility"
    ],
    "wof:name":"Mace Security International",
    "wof:placetype":"venue"
},
  "geometry": {"coordinates":[-74.947125,39.915658],"type":"Point"}
}