{
  "type": "Feature",
  "properties": {
    "addr:full":"205 Espanong Rd Lake Hopatcong NJ 07849",
    "addr:housenumber":"205",
    "addr:postcode":"07849",
    "addr:street":"Espanong Rd",
    "iso:country":"US",
    "sg:address":"205 Espanong Rd",
    "sg:city":"Lake Hopatcong",
    "sg:classifiers":[
        {
            "category":"Building & Trades",
            "subcategory":"Plumbing",
            "type":"Services"
        }
    ],
    "sg:phone":"+1 973 663 0357",
    "sg:postcode":"07849",
    "sg:province":"NJ",
    "sg:tags":[
        "septic"
    ],
    "wof:name":"Texagon Septic Cleaning",
    "wof:placetype":"venue"
},
  "geometry": {"coordinates":[-74.61340199999999,40.959418],"type":"Point"}
}