{
  "type": "Feature",
  "properties": {
    "iso:country":"US",
    "sg:address":"181 Broadway",
    "sg:city":"Long Branch",
    "sg:classifiers":[
        {
            "category":"Professional",
            "subcategory":"Detective & Security Services",
            "type":"Services"
        }
    ],
    "sg:phone":"+1   ",
    "sg:postcode":"07740",
    "sg:province":"NJ",
    "sg:tags":[
        "system"
    ],
    "wof:name":"Safetech International",
    "wof:placetype":"venue"
},
  "geometry": {"coordinates":[-73.98582,40.304766],"type":"Point"}
}