{
  "type": "Feature",
  "properties": {
    "iso:country":"US",
    "sg:address":"68 Linden St",
    "sg:city":"Salem",
    "sg:classifiers":[
        {
            "category":"Professional",
            "subcategory":"Detective & Security Services",
            "type":"Services"
        }
    ],
    "sg:phone":"+1 856 935 1600",
    "sg:postcode":"08079",
    "sg:province":"NJ",
    "sg:tags":[
        "investigator"
    ],
    "wof:name":"Equitable Legal Investigations",
    "wof:placetype":"venue"
},
  "geometry": {"coordinates":[-75.462031,39.564667],"type":"Point"}
}