{
  "type": "Feature",
  "properties": {
    "addr:full":"557 Bloomfield Ave Verona NJ 07044",
    "addr:housenumber":"557",
    "addr:postcode":"07044",
    "addr:street":"Bloomfield Ave",
    "iso:country":"US",
    "sg:address":"557 Bloomfield Ave",
    "sg:city":"Verona",
    "sg:classifiers":[
        {
            "category":"Restaurant",
            "type":"Food & Drink"
        }
    ],
    "sg:menulink":"http://www.allmenus.com/nj/verona/17947-verona-pizza/menu/",
    "sg:phone":"+1 973 239 4645",
    "sg:postcode":"07044",
    "sg:province":"NJ",
    "sg:tags":[
        "italian",
        "american",
        "sandwich",
        "salad",
        "pizza"
    ],
    "wof:name":"Verona Pizza",
    "wof:placetype":"venue"
},
  "geometry": {"coordinates":[-74.24540500000001,40.831611],"type":"Point"}
}