{
  "type": "Feature",
  "properties": {
    "iso:country":"US",
    "sg:address":"466 Kinderkamack Rd",
    "sg:city":"Oradell",
    "sg:classifiers":[
        {
            "category":"Professional",
            "subcategory":"Lawyer & Legal Services",
            "type":"Services"
        }
    ],
    "sg:phone":"+1 201 265 5575",
    "sg:postcode":"07649",
    "sg:province":"NJ",
    "sg:tags":[
        "attorney",
        "family",
        "divorce",
        "landlord",
        "law",
        "tenant"
    ],
    "sg:website":"http://www.ginacalogerolaw.com",
    "wof:name":"Calogero Gina A Attorney at Law",
    "wof:placetype":"venue"
},
  "geometry": {"coordinates":[-74.031082,40.956371],"type":"Point"}
}