{
  "type": "Feature",
  "properties": {
    "addr:full":"1 Truman Dr S Edison NJ 08817",
    "addr:housenumber":"1",
    "addr:postcode":"08817",
    "addr:street":"Truman Dr S",
    "iso:country":"US",
    "sg:address":"1 Truman Dr S",
    "sg:city":"Edison",
    "sg:classifiers":[
        {
            "category":"Freight",
            "type":"Transportation"
        }
    ],
    "sg:phone":"+1 732 985 4600",
    "sg:postcode":"08817",
    "sg:province":"NJ",
    "sg:tags":[
        "warehouse",
        "self",
        "storage"
    ],
    "wof:name":"Popular Club Plan-Warehouse",
    "wof:placetype":"venue"
},
  "geometry": {"coordinates":[-74.42012699999999,40.517714],"type":"Point"}
}