{
  "type": "Feature",
  "properties": {
    "iso:country":"US",
    "sg:address":"547 W Farms Rd",
    "sg:city":"Howell",
    "sg:classifiers":[
        {
            "category":"Building & Trades",
            "subcategory":"Construction",
            "type":"Services"
        }
    ],
    "sg:phone":"+1 732 938 3016",
    "sg:postcode":"07731",
    "sg:province":"NJ",
    "sg:tags":[
        "excavating",
        "contractor"
    ],
    "wof:name":"Hoe Trucking & Excavating Inc",
    "wof:placetype":"venue"
},
  "geometry": {"coordinates":[-74.228138,40.188211],"type":"Point"}
}