{
  "type": "Feature",
  "properties": {
    "addr:full":"423 Forest Ave Teaneck NJ 07666",
    "addr:housenumber":"423",
    "addr:postcode":"07666",
    "addr:street":"Forest Ave",
    "iso:country":"US",
    "sg:address":"423 Forest Ave",
    "sg:city":"Teaneck",
    "sg:classifiers":[
        {
            "category":"Professional",
            "subcategory":"Advertising",
            "type":"Services"
        }
    ],
    "sg:phone":"+1   ",
    "sg:postcode":"07666",
    "sg:province":"NJ",
    "sg:tags":[
        "real estate"
    ],
    "wof:name":"Sequitur Inc",
    "wof:placetype":"venue"
},
  "geometry": {"coordinates":[-74.016434,40.899418],"type":"Point"}
}