{
  "type": "Feature",
  "properties": {
    "iso:country":"US",
    "sg:address":"17 Hanover Rd Ste 410",
    "sg:city":"Florham Park",
    "sg:classifiers":[
        {
            "category":"Banks & Credit Unions",
            "subcategory":"Financial Services",
            "type":"Services"
        }
    ],
    "sg:phone":"+1 973 593 4959",
    "sg:postcode":"07932",
    "sg:province":"NJ",
    "sg:tags":[
        "broker",
        "mortgage"
    ],
    "wof:name":"American Mortgage Company",
    "wof:placetype":"venue"
},
  "geometry": {"coordinates":[-74.38623200000001,40.788653],"type":"Point"}
}