{
  "type": "Feature",
  "properties": {
    "addr:full":"116 Meyersville Rd Chatham NJ 07928",
    "addr:housenumber":"116",
    "addr:postcode":"07928",
    "addr:street":"Meyersville Rd",
    "iso:country":"US",
    "sg:address":"116 Meyersville Rd",
    "sg:city":"Chatham",
    "sg:classifiers":[
        {
            "category":"Professional",
            "subcategory":"Engineering",
            "type":"Services"
        }
    ],
    "sg:phone":"+1 973 635 4800",
    "sg:postcode":"07928",
    "sg:province":"NJ",
    "wof:name":"Rommech Inc",
    "wof:placetype":"venue"
},
  "geometry": {"coordinates":[-74.44014199999999,40.702152],"type":"Point"}
}