{
  "type": "Feature",
  "properties": {
    "iso:country":"US",
    "sg:address":"20 Olden Ter",
    "sg:city":"Trenton",
    "sg:classifiers":[
        {
            "category":"Wholesale",
            "subcategory":"Non-durable Goods",
            "type":"Manufacturing & Wholesale Goods"
        }
    ],
    "sg:phone":"+1 609 581 7608",
    "sg:postcode":"08610",
    "sg:province":"NJ",
    "wof:name":"Mak Distributors Inc",
    "wof:placetype":"venue"
},
  "geometry": {"coordinates":[-74.70351100000001,40.203753],"type":"Point"}
}