{
  "type": "Feature",
  "properties": {
    "iso:country":"US",
    "sg:address":"29 Edgehill Ave",
    "sg:city":"Morristown",
    "sg:classifiers":[
        {
            "category":"Communications",
            "subcategory":"Film & Video Production",
            "type":"Services"
        }
    ],
    "sg:phone":"+1 973 285 3944",
    "sg:postcode":"07960",
    "sg:province":"NJ",
    "sg:tags":[
        "motion"
    ],
    "wof:name":"Imagine If Productions Inc",
    "wof:placetype":"venue"
},
  "geometry": {"coordinates":[-74.504361,40.79636],"type":"Point"}
}