{
  "type": "Feature",
  "properties": {
    "iso:country":"US",
    "sg:address":"203 Randall Ave",
    "sg:city":"Point Pleasant",
    "sg:classifiers":[
        {
            "category":"Manufacturing",
            "subcategory":"Printing",
            "type":"Manufacturing & Wholesale Goods"
        }
    ],
    "sg:phone":"+1 732 892 8794",
    "sg:postcode":"08742",
    "sg:province":"NJ",
    "sg:tags":[
        "printer",
        "commercial"
    ],
    "wof:name":"I N Blue Printing Company Inc",
    "wof:placetype":"venue"
},
  "geometry": {"coordinates":[-74.03780399999999,40.096615],"type":"Point"}
}