{
  "type": "Feature",
  "properties": {
    "addr:full":"250 Circle Dr N Piscataway NJ 08854",
    "addr:housenumber":"250",
    "addr:postcode":"08854",
    "addr:street":"Circle Dr N",
    "iso:country":"US",
    "sg:address":"250 Circle Dr N",
    "sg:city":"Piscataway",
    "sg:classifiers":[
        {
            "category":"Freight",
            "type":"Transportation"
        }
    ],
    "sg:phone":"+1 732 356 9260",
    "sg:postcode":"08854",
    "sg:province":"NJ",
    "sg:tags":[
        "mover"
    ],
    "wof:name":"Allied Van Lines Agents",
    "wof:placetype":"venue"
},
  "geometry": {"coordinates":[-74.477295,40.559557],"type":"Point"}
}