{
  "type": "Feature",
  "properties": {
    "iso:country":"US",
    "sg:address":"574 Inman Ave",
    "sg:city":"Colonia",
    "sg:classifiers":[
        {
            "category":"Government",
            "subcategory":"Post Office",
            "type":"Public Place"
        }
    ],
    "sg:phone":"+1 732 388 3760",
    "sg:postcode":"07067",
    "sg:province":"NJ",
    "sg:tags":[
        "postal",
        "us"
    ],
    "wof:name":"Colonia Post Office",
    "wof:placetype":"venue"
},
  "geometry": {"coordinates":[-74.32814399999999,40.59869],"type":"Point"}
}