{
  "type": "Feature",
  "properties": {
    "iso:country":"US",
    "sg:address":"629 Haven Ave",
    "sg:city":"Ocean City",
    "sg:classifiers":[
        {
            "category":"Autos & Motor Vehicles",
            "subcategory":"Boat Sales",
            "type":"Retail Goods"
        },
        {
            "category":"Retail",
            "subcategory":"Repair Shop",
            "type":"Services"
        }
    ],
    "sg:phone":"+1 609 398 6286",
    "sg:postcode":"08226",
    "sg:province":"NJ",
    "sg:tags":[
        "pleasure",
        "outboard",
        "marine",
        "supply"
    ],
    "wof:name":"Corky's Marine",
    "wof:placetype":"venue"
},
  "geometry": {"coordinates":[-74.57462,39.282461],"type":"Point"}
}