{
  "type": "Feature",
  "properties": {
    "addr:full":"44 Fairway Ave Northfield NJ 08225",
    "addr:housenumber":"44",
    "addr:postcode":"08225",
    "addr:street":"Fairway Ave",
    "iso:country":"US",
    "sg:address":"44 Fairway Ave",
    "sg:city":"Northfield",
    "sg:classifiers":[
        {
            "category":"Building & Trades",
            "subcategory":"Construction",
            "type":"Services"
        }
    ],
    "sg:phone":"+1 609 485 0204",
    "sg:postcode":"08225",
    "sg:province":"NJ",
    "sg:tags":[
        "hanging"
    ],
    "wof:name":"La Rocca Contracting",
    "wof:placetype":"venue"
},
  "geometry": {"coordinates":[-74.54337200000001,39.373494],"type":"Point"}
}