{
  "type": "Feature",
  "properties": {
    "addr:full":"91 Midland Ave Wyckoff NJ 07481",
    "addr:housenumber":"91",
    "addr:postcode":"07481",
    "addr:street":"Midland Ave",
    "iso:country":"US",
    "sg:address":"91 Midland Ave",
    "sg:city":"Wyckoff",
    "sg:classifiers":[
        {
            "category":"Professional",
            "type":"Services"
        }
    ],
    "sg:phone":"+1 201 447 5856",
    "sg:postcode":"07481",
    "sg:province":"NJ",
    "sg:tags":[
        "arts",
        "artist"
    ],
    "wof:name":"Winner Anne Connors Art Studio",
    "wof:placetype":"venue"
},
  "geometry": {"coordinates":[-74.151917,41.00287],"type":"Point"}
}