{
  "type": "Feature",
  "properties": {
    "iso:country":"US",
    "sg:address":"340 Church Ln",
    "sg:city":"North Brunswick",
    "sg:classifiers":[
        {
            "category":"Building & Trades",
            "subcategory":"Construction",
            "type":"Services"
        }
    ],
    "sg:phone":"+1 732 422 8614",
    "sg:postcode":"08902",
    "sg:province":"NJ",
    "sg:tags":[
        "carpentry",
        "contractor"
    ],
    "wof:name":"Five Star Carpentry",
    "wof:placetype":"venue"
},
  "geometry": {"coordinates":[-74.48345399999999,40.429609],"type":"Point"}
}