{
  "type": "Feature",
  "properties": {
    "addr:full":"5012 Dune Dr Avalon NJ 08202",
    "addr:housenumber":"5012",
    "addr:postcode":"08202",
    "addr:street":"Dune Dr",
    "iso:country":"US",
    "sg:address":"5012 Dune Dr",
    "sg:city":"Avalon",
    "sg:classifiers":[
        {
            "category":"Organizations",
            "subcategory":"Religious Organization",
            "type":"Services"
        }
    ],
    "sg:phone":"+1 609 967 3746",
    "sg:postcode":"08202",
    "sg:province":"NJ",
    "sg:tags":[
        "church"
    ],
    "wof:name":"Maris Stella Catholic Church",
    "wof:placetype":"venue"
},
  "geometry": {"coordinates":[-74.733811,39.082958],"type":"Point"}
}