{
  "type": "Feature",
  "properties": {
    "addr:full":"389 Harding Hwy Elmer NJ 08318",
    "addr:housenumber":"389",
    "addr:postcode":"08318",
    "addr:street":"Harding Hwy",
    "iso:country":"US",
    "sg:address":"389 Harding Hwy",
    "sg:city":"Elmer",
    "sg:classifiers":[
        {
            "category":"Recreation",
            "type":"Entertainment"
        }
    ],
    "sg:phone":"+1 856 358 6600",
    "sg:postcode":"08318",
    "sg:province":"NJ",
    "sg:tags":[
        "karate",
        "judo",
        "instr"
    ],
    "wof:name":"Browns Martial Arts Academy",
    "wof:placetype":"venue"
},
  "geometry": {"coordinates":[-75.175927,39.596791],"type":"Point"}
}