{
  "type": "Feature",
  "properties": {
    "addr:full":"260 Myrtle Ave Neptune NJ 07753",
    "addr:housenumber":"260",
    "addr:postcode":"07753",
    "addr:street":"Myrtle Ave",
    "iso:country":"US",
    "sg:address":"260 Myrtle Ave",
    "sg:city":"Neptune",
    "sg:classifiers":[
        {
            "category":"Taxi",
            "type":"Transportation"
        }
    ],
    "sg:phone":"+1 732 776 5666",
    "sg:postcode":"07753",
    "sg:province":"NJ",
    "sg:tags":[
        "taxicab"
    ],
    "wof:name":"Neptune Star Cab",
    "wof:placetype":"venue"
},
  "geometry": {"coordinates":[-74.025644,40.214832],"type":"Point"}
}