{
  "type": "Feature",
  "properties": {
    "addr:full":"48 Parker Pl Shrewsbury NJ 07702",
    "addr:housenumber":"48",
    "addr:postcode":"07702",
    "addr:street":"Parker Pl",
    "iso:country":"US",
    "sg:address":"48 Parker Pl",
    "sg:city":"Shrewsbury",
    "sg:classifiers":[
        {
            "category":"Building & Trades",
            "subcategory":"Construction",
            "type":"Services"
        }
    ],
    "sg:phone":"+1 732 530 0916",
    "sg:postcode":"07702",
    "sg:province":"NJ",
    "sg:tags":[
        "contractor"
    ],
    "wof:name":"Deus Contracting Inc",
    "wof:placetype":"venue"
},
  "geometry": {"coordinates":[-74.058521,40.329471],"type":"Point"}
}