{
  "type": "Feature",
  "properties": {
    "iso:country":"US",
    "sg:address":"1403 Teresa Dr",
    "sg:city":"Fort Lee",
    "sg:classifiers":[
        {
            "category":"Social Services",
            "subcategory":"Child Care",
            "type":"Services"
        }
    ],
    "sg:phone":"+1 201 363 9207",
    "sg:postcode":"07024",
    "sg:province":"NJ",
    "sg:tags":[
        "day"
    ],
    "wof:name":"Learning Bridge",
    "wof:placetype":"venue"
},
  "geometry": {"coordinates":[-73.98366,40.849496],"type":"Point"}
}