{
  "type": "Feature",
  "properties": {
    "addr:full":"8 W Connecticut Concourse Jackson NJ 08527",
    "addr:housenumber":"8",
    "addr:postcode":"08527",
    "addr:street":"W Connecticut",
    "iso:country":"US",
    "sg:address":"8 W Connecticut Concourse",
    "sg:city":"Jackson",
    "sg:classifiers":[
        {
            "category":"Wholesale",
            "subcategory":"Machinery & Supplies",
            "type":"Manufacturing & Wholesale Goods"
        }
    ],
    "sg:phone":"+1 732 730 2850",
    "sg:postcode":"08527",
    "sg:province":"NJ",
    "sg:tags":[
        "supplier",
        "military"
    ],
    "wof:name":"Aljers LLC",
    "wof:placetype":"venue"
},
  "geometry": {"coordinates":[-74.260805,40.145714],"type":"Point"}
}