{
  "type": "Feature",
  "properties": {
    "addr:full":"7 Sherman Ct Plainsboro NJ 08536",
    "addr:housenumber":"7",
    "addr:postcode":"08536",
    "addr:street":"Sherman Ct",
    "iso:country":"US",
    "sg:address":"7 Sherman Ct",
    "sg:city":"Plainsboro",
    "sg:classifiers":[
        {
            "category":"Professional",
            "subcategory":"Management & Consulting",
            "type":"Services"
        }
    ],
    "sg:phone":"+1 609 275 9489",
    "sg:postcode":"08536",
    "sg:province":"NJ",
    "sg:website":"www.sagacitygroup.com",
    "wof:name":"Sagacity Group",
    "wof:placetype":"venue"
},
  "geometry": {"coordinates":[-74.548232,40.329579],"type":"Point"}
}