{
  "type": "Feature",
  "properties": {
    "addr:full":"1042 US Hwy 9 Howell NJ 07731",
    "addr:housenumber":"1042",
    "addr:postcode":"07731",
    "addr:street":"Us Hwy 9",
    "iso:country":"US",
    "sg:address":"1042 US Hwy 9",
    "sg:city":"Howell",
    "sg:classifiers":[
        {
            "category":"Health Services",
            "subcategory":"Clinic",
            "type":"Services"
        }
    ],
    "sg:phone":"+1   ",
    "sg:postcode":"07731",
    "sg:province":"NJ",
    "sg:tags":[
        "home",
        "care"
    ],
    "sg:website":"www.carouselofhomecare.com",
    "wof:name":"Carousel Of Home Care Inc",
    "wof:placetype":"venue"
},
  "geometry": {"coordinates":[-74.254289,40.198369],"type":"Point"}
}