{
  "type": "Feature",
  "properties": {
    "iso:country":"US",
    "sg:address":"268 Lynwood Ave",
    "sg:city":"Trenton",
    "sg:classifiers":[
        {
            "category":"Professional",
            "subcategory":"Management & Consulting",
            "type":"Services"
        }
    ],
    "sg:phone":"+1 609 586 1814",
    "sg:postcode":"08609",
    "sg:province":"NJ",
    "wof:name":"Realty & Management Group",
    "wof:placetype":"venue"
},
  "geometry": {"coordinates":[-74.73079799999999,40.228773],"type":"Point"}
}