{
  "type": "Feature",
  "properties": {
    "addr:full":"515 Amboy Ave Woodbridge NJ 07095",
    "addr:housenumber":"515",
    "addr:postcode":"07095",
    "addr:street":"Amboy Ave",
    "iso:country":"US",
    "sg:address":"515 Amboy Ave",
    "sg:city":"Woodbridge",
    "sg:classifiers":[
        {
            "category":"Banks & Credit Unions",
            "subcategory":"Bank",
            "type":"Services"
        }
    ],
    "sg:phone":"+1   ",
    "sg:postcode":"07095",
    "sg:province":"NJ",
    "sg:tags":[
        "loan",
        "broker"
    ],
    "wof:name":"Allied Home Mrtg Capitl Corp",
    "wof:placetype":"venue"
},
  "geometry": {"coordinates":[-74.28518,40.558842],"type":"Point"}
}