{
  "type": "Feature",
  "properties": {
    "addr:full":"72 Norman Rd Newark NJ 07106",
    "addr:housenumber":"72",
    "addr:postcode":"07106",
    "addr:street":"Norman Rd",
    "iso:country":"US",
    "sg:address":"72 Norman Rd",
    "sg:city":"Newark",
    "sg:classifiers":[
        {
            "category":"Building & Trades",
            "subcategory":"Cleaning & Sanitation",
            "type":"Services"
        }
    ],
    "sg:phone":"+1   ",
    "sg:postcode":"07106",
    "sg:province":"NJ",
    "sg:tags":[
        "maintenance"
    ],
    "wof:name":"Rgm Building Maintenance",
    "wof:placetype":"venue"
},
  "geometry": {"coordinates":[-74.24204400000001,40.737255],"type":"Point"}
}