{
  "type": "Feature",
  "properties": {
    "addr:full":"7918 Kennedy Blvd North Bergen NJ 07047",
    "addr:housenumber":"7918",
    "addr:postcode":"07047",
    "addr:street":"Kennedy Blvd",
    "iso:country":"US",
    "sg:address":"7918 Kennedy Blvd",
    "sg:city":"North Bergen",
    "sg:classifiers":[
        {
            "category":"Health Services",
            "subcategory":"Dentist",
            "type":"Services"
        }
    ],
    "sg:phone":"+1 201 854 1616",
    "sg:postcode":"07047",
    "sg:province":"NJ",
    "wof:name":"Ghisalberti Luciano DMD",
    "wof:placetype":"venue"
},
  "geometry": {"coordinates":[-74.0112,40.803902],"type":"Point"}
}