{
  "type": "Feature",
  "properties": {
    "iso:country":"US",
    "sg:address":"804 8th St",
    "sg:city":"Union City",
    "sg:classifiers":[
        {
            "category":"Building & Trades",
            "subcategory":"Locksmith",
            "type":"Services"
        }
    ],
    "sg:phone":"+1 201 520 7491",
    "sg:postcode":"07087",
    "sg:province":"NJ",
    "sg:tags":[
        "key"
    ],
    "wof:name":"A 1 A 1 Available Emergency Locksmith",
    "wof:placetype":"venue"
},
  "geometry": {"coordinates":[-74.043447,40.759035],"type":"Point"}
}