{
  "type": "Feature",
  "properties": {
    "iso:country":"US",
    "sg:address":"1438 Springfield Ave",
    "sg:city":"Irvington",
    "sg:classifiers":[
        {
            "category":"Shopping",
            "subcategory":"Clothing, Apparel, & Fashions",
            "type":"Retail Goods"
        }
    ],
    "sg:phone":"+1 973 416 8429",
    "sg:postcode":"07111",
    "sg:province":"NJ",
    "sg:tags":[
        "dressmaker"
    ],
    "wof:name":"Halo Bridal",
    "wof:placetype":"venue"
},
  "geometry": {"coordinates":[-74.24957999999999,40.723497],"type":"Point"}
}