{
  "type": "Feature",
  "properties": {
    "iso:country":"US",
    "sg:address":"205 W Sylvania Ave",
    "sg:city":"Neptune",
    "sg:classifiers":[
        {
            "category":"Food & Beverages",
            "subcategory":"Groceries & Convenience Stores",
            "type":"Retail Goods"
        }
    ],
    "sg:phone":"+1 732 775 6111",
    "sg:postcode":"07753",
    "sg:province":"NJ",
    "sg:tags":[
        "market"
    ],
    "wof:name":"Midway Food Market",
    "wof:placetype":"venue"
},
  "geometry": {"coordinates":[-74.03917300000001,40.202053],"type":"Point"}
}