{
  "type": "Feature",
  "properties": {
    "addr:full":"133 S Wood Ave Linden NJ 07036",
    "addr:housenumber":"133",
    "addr:postcode":"07036",
    "addr:street":"S Wood Ave",
    "iso:country":"US",
    "sg:address":"133 S Wood Ave",
    "sg:city":"Linden",
    "sg:classifiers":[
        {
            "category":"Personal",
            "subcategory":"Barber",
            "type":"Services"
        }
    ],
    "sg:phone":"+1 908 862 5060",
    "sg:postcode":"07036",
    "sg:province":"NJ",
    "sg:tags":[
        "shop"
    ],
    "wof:name":"Ritchs Barber Shop",
    "wof:placetype":"venue"
},
  "geometry": {"coordinates":[-74.249055,40.62929],"type":"Point"}
}