{
  "type": "Feature",
  "properties": {
    "iso:country":"US",
    "sg:address":"336 North Ave",
    "sg:city":"Dunellen",
    "sg:classifiers":[
        {
            "category":"Retail",
            "subcategory":"Repair Shop",
            "type":"Services"
        }
    ],
    "sg:phone":"+1   ",
    "sg:postcode":"08812",
    "sg:province":"NJ",
    "wof:name":"Miles Upholstery",
    "wof:placetype":"venue"
},
  "geometry": {"coordinates":[-74.463678,40.591654],"type":"Point"}
}