{
  "type": "Feature",
  "properties": {
    "addr:full":"740 Washington St Hoboken NJ 07030",
    "addr:housenumber":"740",
    "addr:postcode":"07030",
    "addr:street":"Washington St",
    "iso:country":"US",
    "sg:address":"740 Washington St",
    "sg:city":"Hoboken",
    "sg:classifiers":[
        {
            "category":"Restaurant",
            "type":"Food & Drink"
        }
    ],
    "sg:phone":"+1 201 222 2400",
    "sg:postcode":"07030",
    "sg:province":"NJ",
    "sg:tags":[
        "eating",
        "pizza"
    ],
    "wof:name":"Margherita's Pizza & Cafe",
    "wof:placetype":"venue"
},
  "geometry": {"coordinates":[-74.02873200000001,40.745947],"type":"Point"}
}