{
  "type": "Feature",
  "properties": {
    "addr:full":"301 N Main St Manville NJ 08835",
    "addr:housenumber":"301",
    "addr:postcode":"08835",
    "addr:street":"N Main St",
    "iso:country":"US",
    "sg:address":"301 N Main St",
    "sg:city":"Manville",
    "sg:classifiers":[
        {
            "category":"Insurance",
            "subcategory":"Insurance Agent",
            "type":"Services"
        }
    ],
    "sg:phone":"+1   ",
    "sg:postcode":"08835",
    "sg:province":"NJ",
    "wof:name":"Monteroso Agency",
    "wof:placetype":"venue"
},
  "geometry": {"coordinates":[-74.58625000000001,40.54902],"type":"Point"}
}