{
  "type": "Feature",
  "properties": {
    "addr:full":"3141 Woodbridge Ave Edison NJ 08837",
    "addr:housenumber":"3141",
    "addr:postcode":"08837",
    "addr:street":"Woodbridge Ave",
    "iso:country":"US",
    "sg:address":"3141 Woodbridge Ave",
    "sg:city":"Edison",
    "sg:classifiers":[
        {
            "category":"Retail",
            "subcategory":"Auto Repair",
            "type":"Services"
        }
    ],
    "sg:phone":"+1 732 738 6960",
    "sg:postcode":"08837",
    "sg:province":"NJ",
    "sg:tags":[
        "repairing",
        "automobile"
    ],
    "sg:website":"www.meineke.com",
    "wof:name":"Meineke Car Care Ctr",
    "wof:placetype":"venue"
},
  "geometry": {"coordinates":[-74.327281,40.530317],"type":"Point"}
}