{
  "type": "Feature",
  "properties": {
    "iso:country":"US",
    "sg:address":"57 Paterson St",
    "sg:city":"New Brunswick",
    "sg:classifiers":[
        {
            "category":"Home & Garden",
            "subcategory":"Furniture",
            "type":"Retail Goods"
        }
    ],
    "sg:phone":"+1   ",
    "sg:postcode":"08901",
    "sg:province":"NJ",
    "sg:tags":[
        "showroom"
    ],
    "wof:name":"Broadspan Commerce LLC",
    "wof:placetype":"venue"
},
  "geometry": {"coordinates":[-74.443862,40.495179],"type":"Point"}
}