{
  "type": "Feature",
  "properties": {
    "iso:country":"US",
    "sg:address":"12 Holly Dr",
    "sg:city":"Saddle River",
    "sg:classifiers":[
        {
            "category":"Professional",
            "type":"Services"
        }
    ],
    "sg:phone":"+1   ",
    "sg:postcode":"07458",
    "sg:province":"NJ",
    "wof:name":"Swankcom Inc",
    "wof:placetype":"venue"
},
  "geometry": {"coordinates":[-74.101067,41.060656],"type":"Point"}
}