{
  "type": "Feature",
  "properties": {
    "addr:full":"29 Kiser Ln Bridgewater NJ 08807",
    "addr:housenumber":"29",
    "addr:postcode":"08807",
    "addr:street":"Kiser Ln",
    "iso:country":"US",
    "sg:address":"29 Kiser Ln",
    "sg:city":"Bridgewater",
    "sg:classifiers":[
        {
            "category":"Professional",
            "subcategory":"Computer Services",
            "type":"Services"
        }
    ],
    "sg:phone":"+1 908 392 6150",
    "sg:postcode":"08807",
    "sg:province":"NJ",
    "sg:tags":[
        "programing",
        "custom"
    ],
    "wof:name":"Bright Future Learning Center",
    "wof:placetype":"venue"
},
  "geometry": {"coordinates":[-74.66118299999999,40.59258],"type":"Point"}
}