{
  "type": "Feature",
  "properties": {
    "iso:country":"US",
    "sg:address":"18 Arbor Rd",
    "sg:city":"Wayne",
    "sg:classifiers":[
        {
            "category":"Building & Trades",
            "subcategory":"Landscaping Services",
            "type":"Services"
        }
    ],
    "sg:phone":"+1 973 835 1992",
    "sg:postcode":"07470",
    "sg:province":"NJ",
    "sg:tags":[
        "heavy",
        "construction"
    ],
    "wof:name":"Red Cedar Tree Experts",
    "wof:placetype":"venue"
},
  "geometry": {"coordinates":[-74.273507,40.99265],"type":"Point"}
}