{
  "type": "Feature",
  "properties": {
    "iso:country":"US",
    "sg:address":"19 Longview Ln",
    "sg:city":"Hamburg",
    "sg:classifiers":[
        {
            "category":"Professional",
            "type":"Services"
        }
    ],
    "sg:phone":"+1 973 209 7310",
    "sg:postcode":"07419",
    "sg:province":"NJ",
    "sg:tags":[
        "establishment"
    ],
    "wof:name":"Dauson Inc",
    "wof:placetype":"venue"
},
  "geometry": {"coordinates":[-74.560847,41.186651],"type":"Point"}
}