{
  "type": "Feature",
  "properties": {
    "addr:full":"614 Hanford Pl Westfield NJ 07090",
    "addr:housenumber":"614",
    "addr:postcode":"07090",
    "addr:street":"Hanford Pl",
    "iso:country":"US",
    "sg:address":"614 Hanford Pl",
    "sg:city":"Westfield",
    "sg:classifiers":[
        {
            "category":"Building & Trades",
            "subcategory":"Construction",
            "type":"Services"
        }
    ],
    "sg:phone":"+1 908 789 0215",
    "sg:postcode":"07090",
    "sg:province":"NJ",
    "sg:tags":[
        "carpentry",
        "contractor"
    ],
    "wof:name":"Fine Design Carpentry Inc",
    "wof:placetype":"venue"
},
  "geometry": {"coordinates":[-74.362156,40.652492],"type":"Point"}
}