{
  "type": "Feature",
  "properties": {
    "addr:full":"Wiley Publishing 111 River St Hoboken NJ 07030",
    "addr:housenumber":"111",
    "addr:postcode":"07030",
    "addr:street":"River St",
    "iso:country":"US",
    "sg:address":"Wiley Publishing 111 River St",
    "sg:city":"Hoboken",
    "sg:classifiers":[
        {
            "category":"Communications",
            "subcategory":"Newspaper",
            "type":"Services"
        }
    ],
    "sg:postcode":"07030",
    "sg:province":"NJ",
    "sg:tags":[
        "print",
        "medium"
    ],
    "sg:website":"www.frommers.com",
    "wof:name":"Frommer's",
    "wof:placetype":"venue"
},
  "geometry": {"coordinates":[-74.028683,40.737582],"type":"Point"}
}