{
  "type": "Feature",
  "properties": {
    "addr:full":"18 Vista Rd Trenton NJ 08690",
    "addr:housenumber":"18",
    "addr:postcode":"08690",
    "addr:street":"Vista Rd",
    "iso:country":"US",
    "sg:address":"18 Vista Rd",
    "sg:city":"Trenton",
    "sg:classifiers":[
        {
            "category":"Personal",
            "type":"Services"
        }
    ],
    "sg:phone":"+1 609 631 9775",
    "sg:postcode":"08690",
    "sg:province":"NJ",
    "sg:tags":[
        "credit",
        "debt",
        "counseling"
    ],
    "wof:name":"Creditek",
    "wof:placetype":"venue"
},
  "geometry": {"coordinates":[-74.651518,40.220234],"type":"Point"}
}