{
  "type": "Feature",
  "properties": {
    "addr:full":"12 E 11th St Lakewood NJ 08701",
    "addr:housenumber":"12",
    "addr:postcode":"08701",
    "addr:street":"E 11Th St",
    "iso:country":"US",
    "sg:address":"12 E 11th St",
    "sg:city":"Lakewood",
    "sg:classifiers":[
        {
            "category":"Shopping",
            "subcategory":"Clothing, Apparel, & Fashions",
            "type":"Retail Goods"
        }
    ],
    "sg:phone":"+1   ",
    "sg:postcode":"08701",
    "sg:province":"NJ",
    "sg:tags":[
        "family"
    ],
    "wof:name":"Canadian Children",
    "wof:placetype":"venue"
},
  "geometry": {"coordinates":[-74.208443,40.101589],"type":"Point"}
}