{
  "type": "Feature",
  "properties": {
    "iso:country":"US",
    "sg:address":"1715 Greenwood Ave",
    "sg:city":"Trenton",
    "sg:classifiers":[
        {
            "category":"Ice Cream",
            "type":"Food & Drink"
        }
    ],
    "sg:menulink":"http://www.allmenus.com/nj/hamilton/234639-ritas-ice-custard-happiness/menu/",
    "sg:phone":"+1 609 587 3777",
    "sg:postcode":"08609",
    "sg:province":"NJ",
    "sg:tags":[
        "american"
    ],
    "wof:name":"Rita's Ice Custard Happiness",
    "wof:placetype":"venue"
},
  "geometry": {"coordinates":[-74.732052,40.226504],"type":"Point"}
}