{
  "type": "Feature",
  "properties": {
    "iso:country":"US",
    "sg:address":"3306 Boardwalk",
    "sg:city":"Wildwood",
    "sg:classifiers":[
        {
            "category":"Shopping",
            "subcategory":"Gifts & Souvenirs",
            "type":"Retail Goods"
        }
    ],
    "sg:phone":"+1 609 729 6906",
    "sg:postcode":"08260",
    "sg:province":"NJ",
    "sg:tags":[
        "shop"
    ],
    "wof:name":"Captain Deckens Inc",
    "wof:placetype":"venue"
},
  "geometry": {"coordinates":[-74.80919799999999,38.987849],"type":"Point"}
}