{
  "type": "Feature",
  "properties": {
    "iso:country":"US",
    "sg:address":"531 US Hwy 22 E",
    "sg:city":"Whitehouse Sta",
    "sg:classifiers":[
        {
            "category":"Shopping",
            "subcategory":"Gifts & Souvenirs",
            "type":"Retail Goods"
        }
    ],
    "sg:phone":"+1 908 534 4191",
    "sg:postcode":"08889",
    "sg:province":"NJ",
    "sg:tags":[
        "shop"
    ],
    "wof:name":"Huggables Card & Gift",
    "wof:placetype":"venue"
},
  "geometry": {"coordinates":[-74.753877,40.618652],"type":"Point"}
}