{
  "type": "Feature",
  "properties": {
    "addr:full":"784 Franklin Ave Franklin Lakes NJ 07417",
    "addr:housenumber":"784",
    "addr:postcode":"07417",
    "addr:street":"Franklin Ave",
    "iso:country":"US",
    "sg:address":"784 Franklin Ave",
    "sg:city":"Franklin Lakes",
    "sg:classifiers":[
        {
            "category":"Building & Trades",
            "subcategory":"Construction",
            "type":"Services"
        }
    ],
    "sg:phone":"+1 201 848 0881",
    "sg:postcode":"07417",
    "sg:province":"NJ",
    "sg:tags":[
        "house"
    ],
    "wof:name":"Mowery D Construction",
    "wof:placetype":"venue"
},
  "geometry": {"coordinates":[-74.20588100000001,41.021389],"type":"Point"}
}