{
  "type": "Feature",
  "properties": {
    "iso:country":"US",
    "sg:address":"10 Corporate Pl S",
    "sg:city":"Piscataway",
    "sg:classifiers":[
        {
            "category":"Professional",
            "subcategory":"Employment Agencies",
            "type":"Services"
        }
    ],
    "sg:phone":"+1 732 981 8008",
    "sg:postcode":"08854",
    "sg:province":"NJ",
    "sg:tags":[
        "recruitment",
        "executive"
    ],
    "wof:name":"Management Recruiters Intl",
    "wof:placetype":"venue"
},
  "geometry": {"coordinates":[-74.45430500000001,40.550051],"type":"Point"}
}