{
  "type": "Feature",
  "properties": {
    "addr:full":"199 Whitehead Rd Trenton NJ 08619",
    "addr:housenumber":"199",
    "addr:postcode":"08619",
    "addr:street":"Whitehead Rd",
    "iso:country":"US",
    "sg:address":"199 Whitehead Rd",
    "sg:city":"Trenton",
    "sg:classifiers":[
        {
            "category":"Wholesale",
            "subcategory":"Metals & Minerals",
            "type":"Manufacturing & Wholesale Goods"
        }
    ],
    "sg:phone":"+1 609 890 7000",
    "sg:postcode":"08619",
    "sg:province":"NJ",
    "sg:tags":[
        "steel",
        "warehouse",
        "center"
    ],
    "sg:website":"www.certifiedsteel.com",
    "wof:name":"Certified Steel Hamilton Wrhse",
    "wof:placetype":"venue"
},
  "geometry": {"coordinates":[-74.727918,40.239496],"type":"Point"}
}