{
  "type": "Feature",
  "properties": {
    "iso:country":"US",
    "sg:address":"8 E Frederick Pl Ste 101B",
    "sg:city":"Cedar Knolls",
    "sg:classifiers":[
        {
            "category":"Education",
            "subcategory":"Music School",
            "type":"Public Place"
        }
    ],
    "sg:phone":"+1 973 290 9355",
    "sg:postcode":"07927",
    "sg:province":"NJ",
    "sg:tags":[
        "instrument",
        "teacher",
        "musical"
    ],
    "sg:website":"www.originalmusicschool.com",
    "wof:name":"Original Music School",
    "wof:placetype":"venue"
},
  "geometry": {"coordinates":[-74.454904,40.813318],"type":"Point"}
}