{
  "type": "Feature",
  "properties": {
    "iso:country":"US",
    "sg:address":"497 Morris St",
    "sg:city":"Woodbury",
    "sg:classifiers":[
        {
            "category":"Professional",
            "type":"Services"
        },
        {
            "category":"Professional",
            "subcategory":"Business Services",
            "type":"Services"
        }
    ],
    "sg:phone":"+1 856 251 0921",
    "sg:postcode":"08096",
    "sg:province":"NJ",
    "sg:tags":[
        "shop",
        "gift",
        "consultant",
        "design",
        "interior",
        "decorator"
    ],
    "wof:name":"Kelley Bird Design",
    "wof:placetype":"venue"
},
  "geometry": {"coordinates":[-75.161264,39.831246],"type":"Point"}
}