{
  "type": "Feature",
  "properties": {
    "addr:full":"257 Monmouth Rd Oakhurst NJ 07755",
    "addr:housenumber":"257",
    "addr:postcode":"07755",
    "addr:street":"Monmouth Rd",
    "iso:country":"US",
    "sg:address":"257 Monmouth Rd",
    "sg:city":"Oakhurst",
    "sg:classifiers":[
        {
            "category":"Banks & Credit Unions",
            "subcategory":"Investment Brokerage",
            "type":"Services"
        }
    ],
    "sg:phone":"+1 732 531 4111",
    "sg:postcode":"07755",
    "sg:province":"NJ",
    "sg:tags":[
        "consultant",
        "planning",
        "financial"
    ],
    "wof:name":"Grande Financial Svc Raymond",
    "wof:placetype":"venue"
},
  "geometry": {"coordinates":[-74.011201,40.257],"type":"Point"}
}