{
  "type": "Feature",
  "properties": {
    "iso:country":"US",
    "sg:address":"210 North Ave",
    "sg:city":"Dunellen",
    "sg:classifiers":[
        {
            "category":"Retail",
            "subcategory":"Self-service Laundry",
            "type":"Services"
        }
    ],
    "sg:phone":"+1 732 752 1411",
    "sg:postcode":"08812",
    "sg:province":"NJ",
    "wof:name":"Diane's O'Matic Wash-Dunellen",
    "wof:placetype":"venue"
},
  "geometry": {"coordinates":[-74.46287599999999,40.592104],"type":"Point"}
}