{
  "type": "Feature",
  "properties": {
    "addr:full":"21 Arch St Ramsey NJ 07446",
    "addr:housenumber":"21",
    "addr:postcode":"07446",
    "addr:street":"Arch St",
    "iso:country":"US",
    "sg:address":"21 Arch St",
    "sg:city":"Ramsey",
    "sg:classifiers":[
        {
            "category":"Professional",
            "type":"Services"
        }
    ],
    "sg:phone":"+1   ",
    "sg:postcode":"07446",
    "sg:province":"NJ",
    "wof:name":"Gonnagetchacom Inc",
    "wof:placetype":"venue"
},
  "geometry": {"coordinates":[-74.13903000000001,41.058335],"type":"Point"}
}