{
  "type": "Feature",
  "properties": {
    "addr:full":"794 Hamilton St Somerset NJ 08873",
    "addr:housenumber":"794",
    "addr:postcode":"08873",
    "addr:street":"Hamilton St",
    "iso:country":"US",
    "sg:address":"794 Hamilton St",
    "sg:city":"Somerset",
    "sg:classifiers":[
        {
            "category":"Professional",
            "subcategory":"Art Services",
            "type":"Services"
        }
    ],
    "sg:phone":"+1 732 846 7577",
    "sg:postcode":"08873",
    "sg:province":"NJ",
    "sg:tags":[
        "artist"
    ],
    "wof:name":"Murphy Anderson Visual Concept",
    "wof:placetype":"venue"
},
  "geometry": {"coordinates":[-74.47617700000001,40.490161],"type":"Point"}
}