{
  "type": "Feature",
  "properties": {
    "addr:full":"346 Elm Ave Maple Shade NJ 08052",
    "addr:housenumber":"346",
    "addr:postcode":"08052",
    "addr:street":"Elm Ave",
    "iso:country":"US",
    "sg:address":"346 Elm Ave",
    "sg:city":"Maple Shade",
    "sg:classifiers":[
        {
            "category":"Manufacturing",
            "subcategory":"Tools & Machinery",
            "type":"Manufacturing & Wholesale Goods"
        }
    ],
    "sg:phone":"+1 856 779 6367",
    "sg:postcode":"08052",
    "sg:province":"NJ",
    "sg:tags":[
        "food",
        "product",
        "mfg"
    ],
    "wof:name":"Precision Food Machinery",
    "wof:placetype":"venue"
},
  "geometry": {"coordinates":[-74.996802,39.950391],"type":"Point"}
}