{
  "type": "Feature",
  "properties": {
    "iso:country":"US",
    "sg:address":"1130 E Broad St",
    "sg:city":"Elizabeth",
    "sg:classifiers":[
        {
            "category":"Shopping",
            "type":"Retail Goods"
        }
    ],
    "sg:phone":"+1   ",
    "sg:postcode":"07201",
    "sg:province":"NJ",
    "sg:tags":[
        "merchandise"
    ],
    "wof:name":"Timeless Wireless",
    "wof:placetype":"venue"
},
  "geometry": {"coordinates":[-74.21185699999999,40.668726],"type":"Point"}
}