{
  "type": "Feature",
  "properties": {
    "addr:full":"459 Gorge Rd Cliffside Park NJ 07010",
    "addr:housenumber":"459",
    "addr:postcode":"07010",
    "addr:street":"Gorge Rd",
    "iso:country":"US",
    "sg:address":"459 Gorge Rd",
    "sg:city":"Cliffside Park",
    "sg:classifiers":[
        {
            "category":"Building & Trades",
            "subcategory":"Locksmith",
            "type":"Services"
        }
    ],
    "sg:phone":"+1 888 228 0553",
    "sg:postcode":"07010",
    "sg:province":"NJ",
    "sg:tags":[
        "key"
    ],
    "wof:name":"24 Hour 7 Day Emergency Locksmith",
    "wof:placetype":"venue"
},
  "geometry": {"coordinates":[-73.988316,40.819741],"type":"Point"}
}