{
  "type": "Feature",
  "properties": {
    "iso:country":"US",
    "sg:address":"47 Beaver Ave",
    "sg:city":"Edison",
    "sg:classifiers":[
        {
            "category":"Organizations",
            "subcategory":"Religious Organization",
            "type":"Services"
        }
    ],
    "sg:phone":"+1 908 755 4983",
    "sg:postcode":"08820",
    "sg:province":"NJ",
    "sg:tags":[
        "church"
    ],
    "wof:name":"Mount Zion Free Will Baptist",
    "wof:placetype":"venue"
},
  "geometry": {"coordinates":[-74.36487,40.593098],"type":"Point"}
}