{
  "type": "Feature",
  "properties": {
    "addr:full":"181 Lefante Way Bayonne NJ 07002",
    "addr:housenumber":"181",
    "addr:postcode":"07002",
    "addr:street":"Lefante Way",
    "iso:country":"US",
    "sg:address":"181 Lefante Way",
    "sg:city":"Bayonne",
    "sg:classifiers":[
        {
            "category":"Restaurant",
            "type":"Food & Drink"
        }
    ],
    "sg:menulink":"http://www.allmenus.com/nj/bayonne/181643-wendys/menu/",
    "sg:phone":"+1 201 339 8470",
    "sg:postcode":"07002",
    "sg:province":"NJ",
    "sg:tags":[
        "burger",
        "american",
        "soup"
    ],
    "wof:name":"Wendy's",
    "wof:placetype":"venue"
},
  "geometry": {"coordinates":[-74.102604,40.664499],"type":"Point"}
}