{
  "type": "Feature",
  "properties": {
    "iso:country":"US",
    "sg:address":"99 Bridge St",
    "sg:city":"Sewaren",
    "sg:classifiers":[
        {
            "category":"Building & Trades",
            "subcategory":"Plumbing",
            "type":"Services"
        }
    ],
    "sg:phone":"+1 732 636 7756",
    "sg:postcode":"07077",
    "sg:province":"NJ",
    "sg:tags":[
        "contractor"
    ],
    "wof:name":"Residential Plumbing & Heating",
    "wof:placetype":"venue"
},
  "geometry": {"coordinates":[-74.26361199999999,40.554656],"type":"Point"}
}