{
  "type": "Feature",
  "properties": {
    "addr:full":"892 US Hwy 22 Somerville NJ 08876",
    "addr:housenumber":"892",
    "addr:postcode":"08876",
    "addr:street":"Us Hwy 22",
    "iso:country":"US",
    "sg:address":"892 US Hwy 22",
    "sg:city":"Somerville",
    "sg:classifiers":[
        {
            "category":"Professional",
            "subcategory":"Business Services",
            "type":"Services"
        }
    ],
    "sg:phone":"+1 908 253 9103",
    "sg:postcode":"08876",
    "sg:province":"NJ",
    "wof:name":"Jackson National Life Insur Co",
    "wof:placetype":"venue"
},
  "geometry": {"coordinates":[-74.67894200000001,40.598102],"type":"Point"}
}