{
  "type": "Feature",
  "properties": {
    "addr:full":"74 Averell Dr Morris Plains NJ 07950",
    "addr:housenumber":"74",
    "addr:postcode":"07950",
    "addr:street":"Averell Dr",
    "iso:country":"US",
    "sg:address":"74 Averell Dr",
    "sg:city":"Morris Plains",
    "sg:classifiers":[
        {
            "category":"Building & Trades",
            "subcategory":"Cleaning & Sanitation",
            "type":"Services"
        }
    ],
    "sg:phone":"+1   ",
    "sg:postcode":"07950",
    "sg:province":"NJ",
    "wof:name":"Bnd Service",
    "wof:placetype":"venue"
},
  "geometry": {"coordinates":[-74.497586,40.83837],"type":"Point"}
}