{
  "type": "Feature",
  "properties": {
    "addr:full":"50 Washington Ave Dumont NJ 07628",
    "addr:housenumber":"50",
    "addr:postcode":"07628",
    "addr:street":"Washington Ave",
    "iso:country":"US",
    "sg:address":"50 Washington Ave",
    "sg:city":"Dumont",
    "sg:classifiers":[
        {
            "category":"Government",
            "subcategory":"Office",
            "type":"Public Place"
        }
    ],
    "sg:phone":"+1 201 387 5062",
    "sg:postcode":"07628",
    "sg:province":"NJ",
    "sg:tags":[
        "city",
        "resource",
        "human"
    ],
    "wof:name":"Dumont Social Svc Dept",
    "wof:placetype":"venue"
},
  "geometry": {"coordinates":[-73.994418,40.93819],"type":"Point"}
}