{
  "type": "Feature",
  "properties": {
    "addr:full":"96 S Finley Ave Basking Ridge NJ 07920",
    "addr:housenumber":"96",
    "addr:postcode":"07920",
    "addr:street":"S Finley Ave",
    "iso:country":"US",
    "sg:address":"96 S Finley Ave",
    "sg:city":"Basking Ridge",
    "sg:classifiers":[
        {
            "category":"Organizations",
            "subcategory":"Non-profit Organization",
            "type":"Services"
        }
    ],
    "sg:phone":"+1 908 766 1221",
    "sg:postcode":"07920",
    "sg:province":"NJ",
    "sg:tags":[
        "information",
        "alcoholism",
        "treatment"
    ],
    "wof:name":"Ellen R Dahlquist",
    "wof:placetype":"venue"
},
  "geometry": {"coordinates":[-74.54862799999999,40.704365],"type":"Point"}
}