{
  "type": "Feature",
  "properties": {
    "addr:full":"712 Broadway Tpke Camden NJ 08103",
    "addr:housenumber":"712",
    "addr:postcode":"08103",
    "addr:street":"Broadway Tpke",
    "iso:country":"US",
    "sg:address":"712 Broadway Tpke",
    "sg:city":"Camden",
    "sg:classifiers":[
        {
            "category":"Real Estate",
            "subcategory":"Real Estate Operator",
            "type":"Services"
        }
    ],
    "sg:phone":"+1   ",
    "sg:postcode":"08103",
    "sg:province":"NJ",
    "sg:tags":[
        "building",
        "apartment"
    ],
    "wof:name":"West Wynne Apts",
    "wof:placetype":"venue"
},
  "geometry": {"coordinates":[-75.11935099999999,39.936571],"type":"Point"}
}