{
  "type": "Feature",
  "properties": {
    "addr:full":"32 Lake Dr W Wayne NJ 07470",
    "addr:housenumber":"32",
    "addr:postcode":"07470",
    "addr:street":"Lake Dr W",
    "iso:country":"US",
    "sg:address":"32 Lake Dr W",
    "sg:city":"Wayne",
    "sg:classifiers":[
        {
            "category":"Local Transit",
            "type":"Transportation"
        }
    ],
    "sg:phone":"+1 973 696 5123",
    "sg:postcode":"07470",
    "sg:province":"NJ",
    "sg:tags":[
        "passenger"
    ],
    "wof:name":"Amcare Inc",
    "wof:placetype":"venue"
},
  "geometry": {"coordinates":[-74.256765,40.936597],"type":"Point"}
}