{
  "type": "Feature",
  "properties": {
    "addr:full":"36 Lincoln Ave Monroe Township NJ 08831",
    "addr:housenumber":"36",
    "addr:postcode":"08831",
    "addr:street":"Lincoln Ave",
    "iso:country":"US",
    "sg:address":"36 Lincoln Ave",
    "sg:city":"Monroe Township",
    "sg:classifiers":[
        {
            "category":"Organizations",
            "subcategory":"Religious Organization",
            "type":"Services"
        }
    ],
    "sg:phone":"+1   ",
    "sg:postcode":"08831",
    "sg:province":"NJ",
    "wof:name":"St James",
    "wof:placetype":"venue"
},
  "geometry": {"coordinates":[-74.438667,40.355485],"type":"Point"}
}