{
  "type": "Feature",
  "properties": {
    "iso:country":"US",
    "sg:address":"616 US Hwy 30",
    "sg:city":"Cologne",
    "sg:classifiers":[
        {
            "category":"Travel",
            "subcategory":"Hotels & Motels",
            "type":"Entertainment"
        }
    ],
    "sg:phone":"+1 609 965 5141",
    "sg:postcode":"08201",
    "sg:province":"NJ",
    "wof:name":"A-1 Motel",
    "wof:placetype":"venue"
},
  "geometry": {"coordinates":[-74.49179599999999,39.408344],"type":"Point"}
}