{
  "type": "Feature",
  "properties": {
    "iso:country":"US",
    "sg:address":"33 Willis Ave",
    "sg:city":"Cherry Hill",
    "sg:classifiers":[
        {
            "category":"Personal",
            "subcategory":"Beauty Salon",
            "type":"Services"
        }
    ],
    "sg:phone":"+1   ",
    "sg:postcode":"08002",
    "sg:province":"NJ",
    "sg:tags":[
        "shop"
    ],
    "wof:name":"Salon On Maple LLC",
    "wof:placetype":"venue"
},
  "geometry": {"coordinates":[-75.030297,39.950612],"type":"Point"}
}