{
  "type": "Feature",
  "properties": {
    "iso:country":"US",
    "sg:address":"21 Mill St",
    "sg:city":"Paterson",
    "sg:classifiers":[
        {
            "category":"Building & Trades",
            "subcategory":"Locksmith",
            "type":"Services"
        }
    ],
    "sg:phone":"+1 973 689 0487",
    "sg:postcode":"07501",
    "sg:province":"NJ",
    "sg:tags":[
        "key"
    ],
    "wof:name":"0 0 0 0 24 Hour 1 Emergency Locksmith",
    "wof:placetype":"venue"
},
  "geometry": {"coordinates":[-74.177463,40.9163],"type":"Point"}
}