{
  "type": "Feature",
  "properties": {
    "addr:full":"1214 Aldrich Rd Jackson NJ 08527",
    "addr:housenumber":"1214",
    "addr:postcode":"08527",
    "addr:street":"Aldrich Rd",
    "iso:country":"US",
    "sg:address":"1214 Aldrich Rd",
    "sg:city":"Jackson",
    "sg:classifiers":[
        {
            "category":"Retail",
            "subcategory":"Auto Repair",
            "type":"Services"
        }
    ],
    "sg:phone":"+1   ",
    "sg:postcode":"08527",
    "sg:province":"NJ",
    "sg:tags":[
        "general"
    ],
    "wof:name":"Mobile Auto Repair",
    "wof:placetype":"venue"
},
  "geometry": {"coordinates":[-74.260694,40.144513],"type":"Point"}
}