{
  "type": "Feature",
  "properties": {
    "addr:full":"322 Central Ave Jersey City NJ 07307",
    "addr:housenumber":"322",
    "addr:postcode":"07307",
    "addr:street":"Central Ave",
    "iso:country":"US",
    "sg:address":"322 Central Ave",
    "sg:city":"Jersey City",
    "sg:classifiers":[
        {
            "category":"Insurance",
            "subcategory":"Health Insurance",
            "type":"Services"
        }
    ],
    "sg:phone":"+1 201 963 7044",
    "sg:postcode":"07307",
    "sg:province":"NJ",
    "sg:tags":[
        "market"
    ],
    "wof:name":"Be-VI Natural Food Center",
    "wof:placetype":"venue"
},
  "geometry": {"coordinates":[-74.049301,40.7458],"type":"Point"}
}