{
  "type": "Feature",
  "properties": {
    "iso:country":"US",
    "sg:address":"900 Holmdel Rd",
    "sg:city":"Holmdel",
    "sg:classifiers":[
        {
            "category":"Professional",
            "subcategory":"Management & Consulting",
            "type":"Services"
        }
    ],
    "sg:phone":"+1 732 817 1000",
    "sg:postcode":"07733",
    "sg:province":"NJ",
    "sg:tags":[
        "consultant",
        "security",
        "system"
    ],
    "wof:name":"Home Watch",
    "wof:placetype":"venue"
},
  "geometry": {"coordinates":[-74.189364,40.366535],"type":"Point"}
}