{
  "type": "Feature",
  "properties": {
    "addr:full":"145 Hopper Ave Waldwick NJ 07463",
    "addr:housenumber":"145",
    "addr:postcode":"07463",
    "addr:street":"Hopper Ave",
    "iso:country":"US",
    "sg:address":"145 Hopper Ave",
    "sg:city":"Waldwick",
    "sg:classifiers":[
        {
            "category":"Retail",
            "subcategory":"Auto Repair",
            "type":"Services"
        }
    ],
    "sg:phone":"+1 201 444 0601",
    "sg:postcode":"07463",
    "sg:province":"NJ",
    "sg:tags":[
        "body",
        "automobile",
        "painting"
    ],
    "wof:name":"J & J Auto Maintenance",
    "wof:placetype":"venue"
},
  "geometry": {"coordinates":[-74.12608299999999,41.020838],"type":"Point"}
}