{
  "type": "Feature",
  "properties": {
    "iso:country":"US",
    "sg:address":"301 N Harrison St",
    "sg:city":"Princeton",
    "sg:classifiers":[
        {
            "category":"Professional",
            "subcategory":"Computer Services",
            "type":"Services"
        }
    ],
    "sg:phone":"+1 609 683 4545",
    "sg:postcode":"08540",
    "sg:province":"NJ",
    "sg:tags":[
        "consultant",
        "designer",
        "programing",
        "custom"
    ],
    "wof:name":"Princeton Commercial Systems",
    "wof:placetype":"venue"
},
  "geometry": {"coordinates":[-74.654293,40.365845],"type":"Point"}
}