{
  "type": "Feature",
  "properties": {
    "addr:full":"90 W Peddie St Newark NJ 07112",
    "addr:housenumber":"90",
    "addr:postcode":"07112",
    "addr:street":"W Peddie St",
    "iso:country":"US",
    "sg:address":"90 W Peddie St",
    "sg:city":"Newark",
    "sg:classifiers":[
        {
            "category":"Education",
            "subcategory":"School",
            "type":"Public Place"
        }
    ],
    "sg:phone":"+1 973 623 5395",
    "sg:postcode":"07112",
    "sg:province":"NJ",
    "wof:name":"Newark Pre School Council",
    "wof:placetype":"venue"
},
  "geometry": {"coordinates":[-74.196586,40.713987],"type":"Point"}
}