{
  "type": "Feature",
  "properties": {
    "addr:full":"2320 E State St Exd Trenton NJ 08619",
    "addr:housenumber":"2320",
    "addr:postcode":"08619",
    "addr:street":"E State St Exd",
    "iso:country":"US",
    "sg:address":"2320 E State St Exd",
    "sg:city":"Trenton",
    "sg:classifiers":[
        {
            "category":"Manufacturing",
            "subcategory":"Rubber & Plastics",
            "type":"Manufacturing & Wholesale Goods"
        }
    ],
    "sg:phone":"+1 609 890 1212",
    "sg:postcode":"08619",
    "sg:province":"NJ",
    "wof:name":"Polystar",
    "wof:placetype":"venue"
},
  "geometry": {"coordinates":[-74.716077,40.244893],"type":"Point"}
}