{
  "type": "Feature",
  "properties": {
    "addr:full":"102 W Broad St Bridgeton NJ 08302",
    "addr:housenumber":"102",
    "addr:postcode":"08302",
    "addr:street":"W Broad St",
    "iso:country":"US",
    "sg:address":"102 W Broad St",
    "sg:city":"Bridgeton",
    "sg:classifiers":[
        {
            "category":"Government",
            "subcategory":"Post Office",
            "type":"Public Place"
        }
    ],
    "sg:phone":"+1 856 451 6100",
    "sg:postcode":"08302",
    "sg:province":"NJ",
    "wof:name":"US Post Office",
    "wof:placetype":"venue"
},
  "geometry": {"coordinates":[-75.24091,39.428244],"type":"Point"}
}