{
  "type": "Feature",
  "properties": {
    "iso:country":"US",
    "sg:address":"440 Market St",
    "sg:city":"Elmwood Park",
    "sg:classifiers":[
        {
            "category":"Banks & Credit Unions",
            "subcategory":"Financial Services",
            "type":"Services"
        }
    ],
    "sg:phone":"+1 201 398 1333",
    "sg:postcode":"07407",
    "sg:province":"NJ",
    "sg:tags":[
        "broker",
        "mortgage"
    ],
    "wof:name":"Ams Mortgage Services",
    "wof:placetype":"venue"
},
  "geometry": {"coordinates":[-74.111587,40.898936],"type":"Point"}
}