{
  "type": "Feature",
  "properties": {
    "addr:full":"555 18th Ave Newark NJ 07103",
    "addr:housenumber":"555",
    "addr:postcode":"07103",
    "addr:street":"18Th Ave",
    "iso:country":"US",
    "sg:address":"555 18th Ave",
    "sg:city":"Newark",
    "sg:classifiers":[
        {
            "category":"Taxi",
            "type":"Transportation"
        }
    ],
    "sg:phone":"+1 973 374 2446",
    "sg:postcode":"07103",
    "sg:province":"NJ",
    "wof:name":"Diane Dell Corp",
    "wof:placetype":"venue"
},
  "geometry": {"coordinates":[-74.20909899999999,40.7328],"type":"Point"}
}