{
  "type": "Feature",
  "properties": {
    "addr:full":"910 Delancey St Newark NJ 07105",
    "addr:housenumber":"910",
    "addr:postcode":"07105",
    "addr:street":"Delancey St",
    "iso:country":"US",
    "sg:address":"910 Delancey St",
    "sg:city":"Newark",
    "sg:classifiers":[
        {
            "category":"Wholesale",
            "subcategory":"Petroleum",
            "type":"Manufacturing & Wholesale Goods"
        }
    ],
    "sg:phone":"+1 973 344 4461",
    "sg:postcode":"07105",
    "sg:province":"NJ",
    "sg:tags":[
        "bulk",
        "station"
    ],
    "wof:name":"Motiva Enterprises LLC",
    "wof:placetype":"venue"
},
  "geometry": {"coordinates":[-74.130763,40.70995],"type":"Point"}
}