{
  "type": "Feature",
  "properties": {
    "addr:full":"513 W Broadway Paterson NJ 07522",
    "addr:housenumber":"513",
    "addr:postcode":"07522",
    "addr:street":"W Broadway",
    "iso:country":"US",
    "sg:address":"513 W Broadway",
    "sg:city":"Paterson",
    "sg:classifiers":[
        {
            "category":"Building & Trades",
            "subcategory":"Construction",
            "type":"Services"
        }
    ],
    "sg:phone":"+1 973 720 6995",
    "sg:postcode":"07522",
    "sg:province":"NJ",
    "sg:tags":[
        "house"
    ],
    "wof:name":"SM First Impression Inc",
    "wof:placetype":"venue"
},
  "geometry": {"coordinates":[-74.190394,40.930198],"type":"Point"}
}