{
  "type": "Feature",
  "properties": {
    "addr:full":"1902 Atlantic Ave Manasquan NJ 08736",
    "addr:housenumber":"1902",
    "addr:postcode":"08736",
    "addr:street":"Atlantic Ave",
    "iso:country":"US",
    "sg:address":"1902 Atlantic Ave",
    "sg:city":"Manasquan",
    "sg:classifiers":[
        {
            "category":"Social Services",
            "subcategory":"Child Care",
            "type":"Services"
        }
    ],
    "sg:phone":"+1 732 528 5437",
    "sg:postcode":"08736",
    "sg:province":"NJ",
    "sg:tags":[
        "kindergarten",
        "academic",
        "school"
    ],
    "wof:name":"Atlantis Preparatory School",
    "wof:placetype":"venue"
},
  "geometry": {"coordinates":[-74.070679,40.13367],"type":"Point"}
}