{
  "type": "Feature",
  "properties": {
    "addr:full":"112 Nassau St Princeton NJ 08542",
    "addr:housenumber":"112",
    "addr:postcode":"08542",
    "addr:street":"Nassau St",
    "iso:country":"US",
    "sg:address":"112 Nassau St",
    "sg:city":"Princeton",
    "sg:classifiers":[
        {
            "category":"Professional",
            "subcategory":"Management & Consulting",
            "type":"Services"
        }
    ],
    "sg:phone":"+1   ",
    "sg:postcode":"08542",
    "sg:province":"NJ",
    "wof:name":"Betterbranding LLC",
    "wof:placetype":"venue"
},
  "geometry": {"coordinates":[-74.659171,40.349876],"type":"Point"}
}