{
  "type": "Feature",
  "properties": {
    "addr:full":"94 Tallowood Dr Medford NJ 08055",
    "addr:housenumber":"94",
    "addr:postcode":"08055",
    "addr:street":"Tallowood Dr",
    "iso:country":"US",
    "sg:address":"94 Tallowood Dr",
    "sg:city":"Medford",
    "sg:classifiers":[
        {
            "category":"Shopping",
            "subcategory":"Computers & Home Electronics",
            "type":"Retail Goods"
        }
    ],
    "sg:phone":"+1 609 654 7672",
    "sg:postcode":"08055",
    "sg:province":"NJ",
    "sg:tags":[
        "software"
    ],
    "wof:name":"Stafford Systems",
    "wof:placetype":"venue"
},
  "geometry": {"coordinates":[-74.831428,39.85495],"type":"Point"}
}