{
  "type": "Feature",
  "properties": {
    "addr:full":"80 E 5th St Paterson NJ 07524",
    "addr:housenumber":"80",
    "addr:postcode":"07524",
    "addr:street":"E 5Th St",
    "iso:country":"US",
    "sg:address":"80 E 5th St",
    "sg:city":"Paterson",
    "sg:classifiers":[
        {
            "category":"Professional",
            "subcategory":"Business Services",
            "type":"Services"
        }
    ],
    "sg:phone":"+1   ",
    "sg:postcode":"07524",
    "sg:province":"NJ",
    "sg:tags":[
        "packaging",
        "contract"
    ],
    "wof:name":"Gomez Packaging Corp",
    "wof:placetype":"venue"
},
  "geometry": {"coordinates":[-74.1639,40.933617],"type":"Point"}
}