{
  "type": "Feature",
  "properties": {
    "iso:country":"US",
    "sg:address":"1609 Cherry Blossom Ln",
    "sg:city":"Point Pleasant Beach",
    "sg:classifiers":[
        {
            "category":"Manufacturing",
            "subcategory":"Furniture",
            "type":"Manufacturing & Wholesale Goods"
        }
    ],
    "sg:phone":"+1 732 295 3781",
    "sg:postcode":"08742",
    "sg:province":"NJ",
    "sg:tags":[
        "distributor",
        "hospital",
        "business"
    ],
    "wof:name":"Inge Interiors Inc",
    "wof:placetype":"venue"
},
  "geometry": {"coordinates":[-74.080951,40.068239],"type":"Point"}
}