{
  "type": "Feature",
  "properties": {
    "addr:full":"26 Hill Rd Parsippany NJ 07054",
    "addr:housenumber":"26",
    "addr:postcode":"07054",
    "addr:street":"Hill Rd",
    "iso:country":"US",
    "sg:address":"26 Hill Rd",
    "sg:city":"Parsippany",
    "sg:classifiers":[
        {
            "category":"Insurance",
            "subcategory":"Insurance Agent",
            "type":"Services"
        }
    ],
    "sg:phone":"+1 973 257 5558",
    "sg:postcode":"07054",
    "sg:province":"NJ",
    "sg:tags":[
        "consultant"
    ],
    "wof:name":"First National Administrators",
    "wof:placetype":"venue"
},
  "geometry": {"coordinates":[-74.443918,40.876909],"type":"Point"}
}