{
  "type": "Feature",
  "properties": {
    "addr:full":"525 Newton Lake Dr Oaklyn NJ 08107",
    "addr:housenumber":"525",
    "addr:postcode":"08107",
    "addr:street":"Newton Lake Dr",
    "iso:country":"US",
    "sg:address":"525 Newton Lake Dr",
    "sg:city":"Oaklyn",
    "sg:classifiers":[
        {
            "category":"Real Estate",
            "subcategory":"Real Estate Operator",
            "type":"Services"
        }
    ],
    "sg:phone":"+1 856 858 5974",
    "sg:postcode":"08107",
    "sg:province":"NJ",
    "sg:tags":[
        "apartment"
    ],
    "wof:name":"Parkview At Collingswood",
    "wof:placetype":"venue"
},
  "geometry": {"coordinates":[-75.080229,39.909816],"type":"Point"}
}