{
  "type": "Feature",
  "properties": {
    "addr:full":"38 Lake Trl W Morristown NJ 07960",
    "addr:housenumber":"38",
    "addr:postcode":"07960",
    "addr:street":"Lake Trl W",
    "iso:country":"US",
    "sg:address":"38 Lake Trl W",
    "sg:city":"Morristown",
    "sg:classifiers":[
        {
            "category":"Professional",
            "subcategory":"Computer Services",
            "type":"Services"
        }
    ],
    "sg:phone":"+1   ",
    "sg:postcode":"07960",
    "sg:province":"NJ",
    "sg:tags":[
        "development",
        "software"
    ],
    "wof:name":"New Development Solutions",
    "wof:placetype":"venue"
},
  "geometry": {"coordinates":[-74.522862,40.74584],"type":"Point"}
}