{
  "type": "Feature",
  "properties": {
    "addr:full":"16 Half Moon Isle Jersey City NJ 07305",
    "addr:housenumber":"16",
    "addr:postcode":"07305",
    "addr:street":"Half Moon Isle",
    "iso:country":"US",
    "sg:address":"16 Half Moon Isle",
    "sg:city":"Jersey City",
    "sg:classifiers":[
        {
            "category":"Professional",
            "type":"Services"
        }
    ],
    "sg:phone":"+1   ",
    "sg:postcode":"07305",
    "sg:province":"NJ",
    "wof:name":"Medisaver Inc",
    "wof:placetype":"venue"
},
  "geometry": {"coordinates":[-74.071845,40.687379],"type":"Point"}
}