{
  "type": "Feature",
  "properties": {
    "iso:country":"US",
    "sg:address":"140 Mountainside Dr",
    "sg:city":"Randolph",
    "sg:classifiers":[
        {
            "category":"Professional",
            "type":"Services"
        }
    ],
    "sg:phone":"+1 973 361 4324",
    "sg:postcode":"07869",
    "sg:province":"NJ",
    "sg:tags":[
        "establishment"
    ],
    "wof:name":"Ciottariello G",
    "wof:placetype":"venue"
},
  "geometry": {"coordinates":[-74.53389799999999,40.858647],"type":"Point"}
}