{
  "type": "Feature",
  "properties": {
    "addr:full":"55 Brick Blvd Brick NJ 08723",
    "addr:housenumber":"55",
    "addr:postcode":"08723",
    "addr:street":"Brick Blvd",
    "iso:country":"US",
    "sg:address":"55 Brick Blvd",
    "sg:city":"Brick",
    "sg:classifiers":[
        {
            "category":"Shopping",
            "subcategory":"Clothing, Apparel, & Fashions",
            "type":"Retail Goods"
        }
    ],
    "sg:phone":"+1   ",
    "sg:postcode":"08723",
    "sg:province":"NJ",
    "sg:tags":[
        "r",
        "shoes",
        "family",
        "accessory"
    ],
    "sg:website":"www.burlingtoncoatfactory.com",
    "wof:name":"Burlington Coat Factory",
    "wof:placetype":"venue"
},
  "geometry": {"coordinates":[-74.143871,40.025086],"type":"Point"}
}