{
  "type": "Feature",
  "properties": {
    "iso:country":"US",
    "sg:address":"2460 Lemoine Ave",
    "sg:city":"Fort Lee",
    "sg:classifiers":[
        {
            "category":"Professional",
            "subcategory":"Accounting & Tax Preparation",
            "type":"Services"
        }
    ],
    "sg:phone":"+1 201 947 3570",
    "sg:postcode":"07024",
    "sg:province":"NJ",
    "sg:tags":[
        "accountant"
    ],
    "wof:name":"Fried & Fried LLP",
    "wof:placetype":"venue"
},
  "geometry": {"coordinates":[-73.96102500000001,40.865092],"type":"Point"}
}