{
  "type": "Feature",
  "properties": {
    "addr:full":"3021 5th St Voorhees NJ 08043",
    "addr:housenumber":"3021",
    "addr:postcode":"08043",
    "addr:street":"5Th St",
    "iso:country":"US",
    "sg:address":"3021 5th St",
    "sg:city":"Voorhees",
    "sg:classifiers":[
        {
            "category":"Wholesale",
            "subcategory":"Jewelry",
            "type":"Manufacturing & Wholesale Goods"
        }
    ],
    "sg:phone":"+1 856 782 1561",
    "sg:postcode":"08043",
    "sg:province":"NJ",
    "sg:tags":[
        "stone"
    ],
    "wof:name":"Daniel Aloyss Jewelry",
    "wof:placetype":"venue"
},
  "geometry": {"coordinates":[-74.988738,39.83837],"type":"Point"}
}