{
  "type": "Feature",
  "properties": {
    "iso:country":"US",
    "sg:address":"2441 US Hwy 22",
    "sg:city":"Union",
    "sg:classifiers":[
        {
            "category":"Banks & Credit Unions",
            "subcategory":"Bank",
            "type":"Services"
        }
    ],
    "sg:phone":"+1 908 686 4442",
    "sg:postcode":"07083",
    "sg:province":"NJ",
    "sg:tags":[
        "federal",
        "savings",
        "institution"
    ],
    "sg:website":"www.isbnj.com",
    "wof:name":"Investors Savings Bank",
    "wof:placetype":"venue"
},
  "geometry": {"coordinates":[-74.29849400000001,40.689581],"type":"Point"}
}