{
  "type": "Feature",
  "properties": {
    "iso:country":"US",
    "sg:address":"1229 Madison Ave",
    "sg:city":"Lakewood",
    "sg:classifiers":[
        {
            "category":"Health Services",
            "subcategory":"Doctor",
            "type":"Services"
        }
    ],
    "sg:phone":"+1 732 363 2126",
    "sg:postcode":"08701",
    "sg:province":"NJ",
    "wof:name":"Edwyn M Smith DDS",
    "wof:placetype":"venue"
},
  "geometry": {"coordinates":[-74.218597,40.102794],"type":"Point"}
}