{
  "type": "Feature",
  "properties": {
    "iso:country":"US",
    "sg:address":"5 Columbia Rd",
    "sg:city":"Branchburg",
    "sg:classifiers":[
        {
            "category":"Manufacturing",
            "subcategory":"Electronics",
            "type":"Manufacturing & Wholesale Goods"
        }
    ],
    "sg:phone":"+1 908 722 8081",
    "sg:postcode":"08876",
    "sg:province":"NJ",
    "sg:tags":[
        "equipment",
        "electronic",
        "supply"
    ],
    "sg:website":"www.conolog.com",
    "wof:name":"Conolog Corp",
    "wof:placetype":"venue"
},
  "geometry": {"coordinates":[-74.68963599999999,40.597699],"type":"Point"}
}