{
  "type": "Feature",
  "properties": {
    "iso:country":"US",
    "sg:address":"29 Phyllis Ln",
    "sg:city":"Fairfield",
    "sg:classifiers":[
        {
            "category":"Professional",
            "type":"Services"
        }
    ],
    "sg:phone":"+1   ",
    "sg:postcode":"07004",
    "sg:province":"NJ",
    "wof:name":"B A M Points Inc",
    "wof:placetype":"venue"
},
  "geometry": {"coordinates":[-74.31132599999999,40.873654],"type":"Point"}
}