{
  "type": "Feature",
  "properties": {
    "addr:full":"289 S Shore Rd Marmora NJ 08223",
    "addr:housenumber":"289",
    "addr:postcode":"08223",
    "addr:street":"S Shore Rd",
    "iso:country":"US",
    "sg:address":"289 S Shore Rd",
    "sg:city":"Marmora",
    "sg:classifiers":[
        {
            "category":"Building & Trades",
            "subcategory":"Construction",
            "type":"Services"
        }
    ],
    "sg:phone":"+1 609 261 2268",
    "sg:postcode":"08223",
    "sg:province":"NJ",
    "sg:tags":[
        "designer",
        "marine",
        "contractor"
    ],
    "sg:website":"www.wjcastlegroup.com",
    "wof:name":"W J Castle & Assoc",
    "wof:placetype":"venue"
},
  "geometry": {"coordinates":[-74.654661,39.258081],"type":"Point"}
}