{
  "type": "Feature",
  "properties": {
    "addr:full":"3 Hill Hollow Dr Pittstown NJ 08867",
    "addr:housenumber":"3",
    "addr:postcode":"08867",
    "addr:street":"Hill Hollow Dr",
    "iso:country":"US",
    "sg:address":"3 Hill Hollow Dr",
    "sg:city":"Pittstown",
    "sg:classifiers":[
        {
            "category":"Wholesale",
            "subcategory":"Construction Materials",
            "type":"Manufacturing & Wholesale Goods"
        }
    ],
    "sg:phone":"+1 908 735 8879",
    "sg:postcode":"08867",
    "sg:province":"NJ",
    "sg:tags":[
        "fence"
    ],
    "wof:name":"Fence Co",
    "wof:placetype":"venue"
},
  "geometry": {"coordinates":[-74.993295,40.598844],"type":"Point"}
}