{
  "type": "Feature",
  "properties": {
    "addr:full":"105 Main St Millburn NJ 07041",
    "addr:housenumber":"105",
    "addr:postcode":"07041",
    "addr:street":"Main St",
    "iso:country":"US",
    "sg:address":"105 Main St",
    "sg:city":"Millburn",
    "sg:classifiers":[
        {
            "category":"Personal",
            "type":"Services"
        }
    ],
    "sg:phone":"+1 973 379 5355",
    "sg:postcode":"07041",
    "sg:province":"NJ",
    "sg:tags":[
        "costume"
    ],
    "wof:name":"Junior League of Summit Costume Shop",
    "wof:placetype":"venue"
},
  "geometry": {"coordinates":[-74.3069,40.722301],"type":"Point"}
}