{
  "type": "Feature",
  "properties": {
    "iso:country":"US",
    "sg:address":"264 Ramblewood Pkwy",
    "sg:city":"Mount Laurel",
    "sg:classifiers":[
        {
            "category":"Banks & Credit Unions",
            "subcategory":"Investment Brokerage",
            "type":"Services"
        }
    ],
    "sg:phone":"+1   ",
    "sg:postcode":"08054",
    "sg:province":"NJ",
    "sg:tags":[
        "security"
    ],
    "wof:name":"Baytree Investors Inc",
    "wof:placetype":"venue"
},
  "geometry": {"coordinates":[-74.938379,39.940573],"type":"Point"}
}