{
  "type": "Feature",
  "properties": {
    "addr:full":"140 Hanover Rd East Hanover NJ 07936",
    "addr:housenumber":"140",
    "addr:postcode":"07936",
    "addr:street":"Hanover Rd",
    "iso:country":"US",
    "sg:address":"140 Hanover Rd",
    "sg:city":"East Hanover",
    "sg:classifiers":[
        {
            "category":"Building & Trades",
            "subcategory":"Electrical",
            "type":"Services"
        },
        {
            "category":"Retail",
            "subcategory":"Repair Shop",
            "type":"Services"
        }
    ],
    "sg:phone":"+1 973 884 1199",
    "sg:postcode":"07936",
    "sg:province":"NJ",
    "sg:tags":[
        "installation",
        "alarm",
        "wiring",
        "system",
        "telephone",
        "equipment"
    ],
    "wof:name":"Nobel Telephone Installation",
    "wof:placetype":"venue"
},
  "geometry": {"coordinates":[-74.372986,40.797744],"type":"Point"}
}