{
  "type": "Feature",
  "properties": {
    "iso:country":"US",
    "sg:address":"11 Skyline Dr",
    "sg:city":"Caldwell",
    "sg:classifiers":[
        {
            "category":"Real Estate",
            "subcategory":"Real Estate Agent",
            "type":"Services"
        }
    ],
    "sg:phone":"+1   ",
    "sg:postcode":"07006",
    "sg:province":"NJ",
    "wof:name":"Garden Apartments",
    "wof:placetype":"venue"
},
  "geometry": {"coordinates":[-74.244928,40.865767],"type":"Point"}
}