{
  "type": "Feature",
  "properties": {
    "iso:country":"US",
    "sg:address":"5 Shore Dr",
    "sg:city":"Newton",
    "sg:classifiers":[
        {
            "category":"Place Of Worship",
            "type":"Public Place"
        }
    ],
    "sg:phone":"+1 973 383 6468",
    "sg:postcode":"07860",
    "sg:province":"NJ",
    "sg:tags":[
        "church"
    ],
    "wof:name":"Covenant Advent Church",
    "wof:placetype":"venue"
},
  "geometry": {"coordinates":[-74.82078,41.106054],"type":"Point"}
}