{
  "type": "Feature",
  "properties": {
    "iso:country":"US",
    "sg:address":"56 Ferry St",
    "sg:city":"Newark",
    "sg:classifiers":[
        {
            "category":"Professional",
            "subcategory":"Lawyer & Legal Services",
            "type":"Services"
        }
    ],
    "sg:phone":"+1 973 344 1621",
    "sg:postcode":"07105",
    "sg:province":"NJ",
    "sg:tags":[
        "attorney"
    ],
    "wof:name":"James V Scarlata",
    "wof:placetype":"venue"
},
  "geometry": {"coordinates":[-74.163056,40.732332],"type":"Point"}
}