{
  "type": "Feature",
  "properties": {
    "addr:full":"3718 John F Kennedy Blvd Jersey City NJ 07307",
    "addr:housenumber":"3718",
    "addr:postcode":"07307",
    "addr:street":"John F Kennedy Blvd",
    "iso:country":"US",
    "sg:address":"3718 John F Kennedy Blvd",
    "sg:city":"Jersey City",
    "sg:classifiers":[
        {
            "category":"Personal",
            "subcategory":"Beauty Salon",
            "type":"Services"
        }
    ],
    "sg:phone":"+1 201 653 6859",
    "sg:postcode":"07307",
    "sg:province":"NJ",
    "sg:tags":[
        "hair"
    ],
    "wof:name":"Jenny Ubri Beauty Salon",
    "wof:placetype":"venue"
},
  "geometry": {"coordinates":[-74.045799,40.757198],"type":"Point"}
}