{
  "type": "Feature",
  "properties": {
    "addr:full":"25 Millbrook Dr Middletown NJ 07748",
    "addr:housenumber":"25",
    "addr:postcode":"07748",
    "addr:street":"Millbrook Dr",
    "iso:country":"US",
    "sg:address":"25 Millbrook Dr",
    "sg:city":"Middletown",
    "sg:classifiers":[
        {
            "category":"Manufacturing",
            "subcategory":"Paper Products",
            "type":"Manufacturing & Wholesale Goods"
        }
    ],
    "sg:phone":"+1 732 671 2938",
    "sg:postcode":"07748",
    "sg:province":"NJ",
    "sg:tags":[
        "die",
        "mfg"
    ],
    "wof:name":"Total View Systems Corp",
    "wof:placetype":"venue"
},
  "geometry": {"coordinates":[-74.110865,40.409837],"type":"Point"}
}