{
  "type": "Feature",
  "properties": {
    "addr:full":"3 Tiffany Pl Brigantine NJ 08203",
    "addr:housenumber":"3",
    "addr:postcode":"08203",
    "addr:street":"Tiffany Pl",
    "iso:country":"US",
    "sg:address":"3 Tiffany Pl",
    "sg:city":"Brigantine",
    "sg:classifiers":[
        {
            "category":"Professional",
            "type":"Services"
        }
    ],
    "sg:phone":"+1   ",
    "sg:postcode":"08203",
    "sg:province":"NJ",
    "wof:name":"Bret Bergman",
    "wof:placetype":"venue"
},
  "geometry": {"coordinates":[-74.406387,39.382353],"type":"Point"}
}