{
  "type": "Feature",
  "properties": {
    "iso:country":"US",
    "sg:address":"722 McCormack Dr",
    "sg:city":"Toms River",
    "sg:classifiers":[
        {
            "category":"Manufacturing",
            "subcategory":"Furniture",
            "type":"Manufacturing & Wholesale Goods"
        }
    ],
    "sg:phone":"+1 732 286 6366",
    "sg:postcode":"08753",
    "sg:province":"NJ",
    "sg:tags":[
        "wood",
        "mfg"
    ],
    "wof:name":"A P Kitchen Cabinets Inc",
    "wof:placetype":"venue"
},
  "geometry": {"coordinates":[-74.17228799999999,39.967098],"type":"Point"}
}