{
  "type": "Feature",
  "properties": {
    "addr:full":"68 Schraalenburgh Rd Harrington Park NJ 07640",
    "addr:housenumber":"68",
    "addr:postcode":"07640",
    "addr:street":"Schraalenburgh Rd",
    "iso:country":"US",
    "sg:address":"68 Schraalenburgh Rd",
    "sg:city":"Harrington Park",
    "sg:classifiers":[
        {
            "category":"Building & Trades",
            "subcategory":"Plumbing",
            "type":"Services"
        }
    ],
    "sg:phone":"+1 201 567 5967",
    "sg:postcode":"07640",
    "sg:province":"NJ",
    "sg:tags":[
        "plumbing",
        "contractor"
    ],
    "wof:name":"Hofmeister & Co Plumbing & Htg",
    "wof:placetype":"venue"
},
  "geometry": {"coordinates":[-73.97813600000001,40.982271],"type":"Point"}
}