{
  "type": "Feature",
  "properties": {
    "iso:country":"US",
    "sg:address":"29 Stonehedge Rd",
    "sg:city":"Millington",
    "sg:classifiers":[
        {
            "category":"Shopping",
            "subcategory":"Computers & Home Electronics",
            "type":"Retail Goods"
        }
    ],
    "sg:phone":"+1   ",
    "sg:postcode":"07946",
    "sg:province":"NJ",
    "wof:name":"Debugg Inc",
    "wof:placetype":"venue"
},
  "geometry": {"coordinates":[-74.500327,40.66625],"type":"Point"}
}