{
  "type": "Feature",
  "properties": {
    "addr:full":"60 Essex St Rochelle Park NJ 07662",
    "addr:housenumber":"60",
    "addr:postcode":"07662",
    "addr:street":"Essex St",
    "iso:country":"US",
    "sg:address":"60 Essex St",
    "sg:city":"Rochelle Park",
    "sg:classifiers":[
        {
            "category":"Manufacturing",
            "subcategory":"Metals",
            "type":"Manufacturing & Wholesale Goods"
        },
        {
            "category":"Manufacturing",
            "subcategory":"Printing",
            "type":"Manufacturing & Wholesale Goods"
        }
    ],
    "sg:phone":"+1 201 845 8555",
    "sg:postcode":"07662",
    "sg:province":"NJ",
    "sg:tags":[
        "engraver",
        "commercial"
    ],
    "wof:name":"Multitone Engraving Co Inc",
    "wof:placetype":"venue"
},
  "geometry": {"coordinates":[-74.077612,40.894815],"type":"Point"}
}