{
  "type": "Feature",
  "properties": {
    "addr:full":"63 Belmont Ave Garfield NJ 07026",
    "addr:housenumber":"63",
    "addr:postcode":"07026",
    "addr:street":"Belmont Ave",
    "iso:country":"US",
    "sg:address":"63 Belmont Ave",
    "sg:city":"Garfield",
    "sg:classifiers":[
        {
            "category":"Building & Trades",
            "subcategory":"Locksmith",
            "type":"Services"
        }
    ],
    "sg:phone":"+1 888 228 0813",
    "sg:postcode":"07026",
    "sg:province":"NJ",
    "sg:tags":[
        "key"
    ],
    "wof:name":"A 1 Emergency Locksmith",
    "wof:placetype":"venue"
},
  "geometry": {"coordinates":[-74.11042999999999,40.875184],"type":"Point"}
}