{
  "type": "Feature",
  "properties": {
    "iso:country":"US",
    "sg:address":"1 Scout Ave",
    "sg:city":"Kearny",
    "sg:classifiers":[
        {
            "category":"Retail",
            "subcategory":"Repair Shop",
            "type":"Services"
        }
    ],
    "sg:phone":"+1 973 854 5740",
    "sg:postcode":"07032",
    "sg:province":"NJ",
    "sg:tags":[
        "lock",
        "key",
        "locksmith"
    ],
    "wof:name":"1 24 Hour 7 Day Emerg A Lock A Locksmith",
    "wof:placetype":"venue"
},
  "geometry": {"coordinates":[-74.102017,40.729001],"type":"Point"}
}