{
  "type": "Feature",
  "properties": {
    "addr:full":"21 Mountain Ave Maplewood NJ 07040",
    "addr:housenumber":"21",
    "addr:postcode":"07040",
    "addr:street":"Mountain Ave",
    "iso:country":"US",
    "sg:address":"21 Mountain Ave",
    "sg:city":"Maplewood",
    "sg:classifiers":[
        {
            "category":"Professional",
            "type":"Services"
        }
    ],
    "sg:phone":"+1   ",
    "sg:postcode":"07040",
    "sg:province":"NJ",
    "wof:name":"Lisa M Trusiani",
    "wof:placetype":"venue"
},
  "geometry": {"coordinates":[-74.286801,40.730732],"type":"Point"}
}