{
  "type": "Feature",
  "properties": {
    "addr:full":"506 Millburn Ave Short Hills NJ 07078",
    "addr:housenumber":"506",
    "addr:postcode":"07078",
    "addr:street":"Millburn Ave",
    "iso:country":"US",
    "sg:address":"506 Millburn Ave",
    "sg:city":"Short Hills",
    "sg:classifiers":[
        {
            "category":"Personal",
            "subcategory":"Beauty Salon",
            "type":"Services"
        }
    ],
    "sg:phone":"+1 973 467 0170",
    "sg:postcode":"07078",
    "sg:province":"NJ",
    "sg:tags":[
        "manicuring"
    ],
    "wof:name":"Ven Nail",
    "wof:placetype":"venue"
},
  "geometry": {"coordinates":[-74.31908900000001,40.720149],"type":"Point"}
}