{
  "type": "Feature",
  "properties": {
    "iso:country":"US",
    "sg:address":"20 Broad St",
    "sg:city":"Red Bank",
    "sg:classifiers":[
        {
            "category":"Manufacturing",
            "subcategory":"Printing",
            "type":"Manufacturing & Wholesale Goods"
        }
    ],
    "sg:phone":"+1 732 933 4767",
    "sg:postcode":"07701",
    "sg:province":"NJ",
    "sg:tags":[
        "newspaper"
    ],
    "wof:name":"Ansorge Unlimited",
    "wof:placetype":"venue"
},
  "geometry": {"coordinates":[-74.06549099999999,40.352193],"type":"Point"}
}