{
  "type": "Feature",
  "properties": {
    "addr:full":"9614 Ventnor Ave Margate City NJ 08402",
    "addr:housenumber":"9614",
    "addr:postcode":"08402",
    "addr:street":"Ventnor Ave Margate",
    "iso:country":"US",
    "sg:address":"9614 Ventnor Ave",
    "sg:city":"Margate City",
    "sg:classifiers":[
        {
            "category":"Retail",
            "subcategory":"Auto Rental",
            "type":"Services"
        }
    ],
    "sg:phone":"+1 609 487 2295",
    "sg:postcode":"08402",
    "sg:province":"NJ",
    "sg:tags":[
        "renting",
        "truck",
        "leasing"
    ],
    "wof:name":"U-Haul Co",
    "wof:placetype":"venue"
},
  "geometry": {"coordinates":[-74.517168,39.320421],"type":"Point"}
}