{
  "type": "Feature",
  "properties": {
    "iso:country":"US",
    "sg:address":"181 The Plz",
    "sg:city":"Teaneck",
    "sg:classifiers":[
        {
            "category":"Organizations",
            "subcategory":"Non-profit Organization",
            "type":"Services"
        }
    ],
    "sg:phone":"+1 201 833 5040",
    "sg:postcode":"07666",
    "sg:province":"NJ",
    "sg:tags":[
        "service/non-profit",
        "community"
    ],
    "wof:name":"American Friends of the Ghetto Fighter's House",
    "wof:placetype":"venue"
},
  "geometry": {"coordinates":[-74.005501,40.902401],"type":"Point"}
}