{
  "type": "Feature",
  "properties": {
    "iso:country":"US",
    "sg:address":"269 Hayward Pl",
    "sg:city":"Wallington",
    "sg:classifiers":[
        {
            "category":"Professional",
            "subcategory":"Management & Consulting",
            "type":"Services"
        }
    ],
    "sg:phone":"+1 973 473 2880",
    "sg:postcode":"07057",
    "sg:province":"NJ",
    "sg:tags":[
        "medical",
        "administration",
        "business"
    ],
    "wof:name":"Ent Med Consultants",
    "wof:placetype":"venue"
},
  "geometry": {"coordinates":[-74.111672,40.851435],"type":"Point"}
}