{
  "type": "Feature",
  "properties": {
    "iso:country":"US",
    "sg:address":"18 Grant Ave",
    "sg:city":"Highland Park",
    "sg:classifiers":[
        {
            "category":"Professional",
            "subcategory":"Management & Consulting",
            "type":"Services"
        }
    ],
    "sg:phone":"+1   ",
    "sg:postcode":"08904",
    "sg:province":"NJ",
    "sg:tags":[
        "business"
    ],
    "wof:name":"Borgida Consulting",
    "wof:placetype":"venue"
},
  "geometry": {"coordinates":[-74.43404700000001,40.501748],"type":"Point"}
}