{
  "type": "Feature",
  "properties": {
    "addr:full":"220 Monmouth Rd Oakhurst NJ 07755",
    "addr:housenumber":"220",
    "addr:postcode":"07755",
    "addr:street":"Monmouth Rd",
    "iso:country":"US",
    "sg:address":"220 Monmouth Rd",
    "sg:city":"Oakhurst",
    "sg:classifiers":[
        {
            "category":"Health Services",
            "subcategory":"Doctor",
            "type":"Services"
        }
    ],
    "sg:phone":"+1   ",
    "sg:postcode":"07755",
    "sg:province":"NJ",
    "sg:tags":[
        "physician",
        "pediatric"
    ],
    "wof:name":"Ocean Pediatric Group PA",
    "wof:placetype":"venue"
},
  "geometry": {"coordinates":[-74.011589,40.259489],"type":"Point"}
}