{
  "type": "Feature",
  "properties": {
    "addr:full":"35 N Main St Wharton NJ 07885",
    "addr:housenumber":"35",
    "addr:postcode":"07885",
    "addr:street":"N Main St",
    "iso:country":"US",
    "sg:address":"35 N Main St",
    "sg:city":"Wharton",
    "sg:classifiers":[
        {
            "category":"Personal",
            "subcategory":"Beauty Salon",
            "type":"Services"
        }
    ],
    "sg:phone":"+1 973 361 2330",
    "sg:postcode":"07885",
    "sg:province":"NJ",
    "sg:tags":[
        "shop"
    ],
    "wof:name":"Crosstown Beauty Supply",
    "wof:placetype":"venue"
},
  "geometry": {"coordinates":[-74.58266999999999,40.899753],"type":"Point"}
}