{
  "type": "Feature",
  "properties": {
    "iso:country":"US",
    "sg:address":"6416 Ventnor Ave",
    "sg:city":"Ventnor City",
    "sg:classifiers":[
        {
            "category":"Airline",
            "type":"Transportation"
        }
    ],
    "sg:phone":"+1 609 487 9444",
    "sg:postcode":"08406",
    "sg:province":"NJ",
    "sg:tags":[
        "scheduled",
        "air"
    ],
    "wof:name":"Delta Airlines",
    "wof:placetype":"venue"
},
  "geometry": {"coordinates":[-74.48289699999999,39.337825],"type":"Point"}
}