{
  "type": "Feature",
  "properties": {
    "iso:country":"US",
    "sg:address":"140 Mount Vernon St",
    "sg:city":"Ridgefield Park",
    "sg:classifiers":[
        {
            "category":"Building & Trades",
            "subcategory":"Construction",
            "type":"Services"
        }
    ],
    "sg:phone":"+1 201 807 1083",
    "sg:postcode":"07660",
    "sg:province":"NJ",
    "sg:tags":[
        "house"
    ],
    "wof:name":"Petes General Renovations",
    "wof:placetype":"venue"
},
  "geometry": {"coordinates":[-74.02157699999999,40.855936],"type":"Point"}
}