{
  "type": "Feature",
  "properties": {
    "iso:country":"US",
    "sg:address":"326 Essex Ave",
    "sg:city":"Boonton",
    "sg:classifiers":[
        {
            "category":"Manufacturing",
            "subcategory":"Paper Products",
            "type":"Manufacturing & Wholesale Goods"
        }
    ],
    "sg:phone":"+1 973 334 0065",
    "sg:postcode":"07005",
    "sg:province":"NJ",
    "sg:tags":[
        "die",
        "mfg"
    ],
    "wof:name":"Uhimate Coatings",
    "wof:placetype":"venue"
},
  "geometry": {"coordinates":[-74.420547,40.904615],"type":"Point"}
}