{
  "type": "Feature",
  "properties": {
    "addr:full":"2087 Shore Rd Ocean View NJ 08230",
    "addr:housenumber":"2087",
    "addr:postcode":"08230",
    "addr:street":"Shore Rd",
    "iso:country":"US",
    "sg:address":"2087 Shore Rd",
    "sg:city":"Ocean View",
    "sg:classifiers":[
        {
            "category":"Food & Beverages",
            "subcategory":"Specialty",
            "type":"Retail Goods"
        }
    ],
    "sg:phone":"+1 609 624 7977",
    "sg:postcode":"08230",
    "sg:province":"NJ",
    "sg:tags":[
        "health",
        "diet"
    ],
    "wof:name":"GNC",
    "wof:placetype":"venue"
},
  "geometry": {"coordinates":[-74.703546,39.209157],"type":"Point"}
}