{
  "type": "Feature",
  "properties": {
    "addr:full":"10 Driftwood Dr Parlin NJ 08859",
    "addr:housenumber":"10",
    "addr:postcode":"08859",
    "addr:street":"Driftwood Dr",
    "iso:country":"US",
    "sg:address":"10 Driftwood Dr",
    "sg:city":"Parlin",
    "sg:classifiers":[
        {
            "category":"Manufacturing",
            "subcategory":"Tools & Machinery",
            "type":"Manufacturing & Wholesale Goods"
        }
    ],
    "sg:phone":"+1 732 727 0032",
    "sg:postcode":"08859",
    "sg:province":"NJ",
    "sg:tags":[
        "roofing"
    ],
    "wof:name":"D & J Roofing",
    "wof:placetype":"venue"
},
  "geometry": {"coordinates":[-74.29302800000001,40.460718],"type":"Point"}
}