{
  "type": "Feature",
  "properties": {
    "iso:country":"US",
    "sg:address":"150 Clove Rd",
    "sg:city":"Little Falls",
    "sg:classifiers":[
        {
            "category":"Insurance",
            "subcategory":"Insurance Agent",
            "type":"Services"
        }
    ],
    "sg:phone":"+1 973 237 1544",
    "sg:postcode":"07424",
    "sg:province":"NJ",
    "wof:name":"Sidney Gottlieb",
    "wof:placetype":"venue"
},
  "geometry": {"coordinates":[-74.196275,40.873035],"type":"Point"}
}