{
  "type": "Feature",
  "properties": {
    "iso:country":"US",
    "sg:address":"14 Main St",
    "sg:city":"Sparta",
    "sg:classifiers":[
        {
            "category":"Shopping",
            "subcategory":"Florist",
            "type":"Retail Goods"
        }
    ],
    "sg:phone":"+1 973 729 4044",
    "sg:postcode":"07871",
    "sg:province":"NJ",
    "wof:name":"Flower Box III",
    "wof:placetype":"venue"
},
  "geometry": {"coordinates":[-74.635763,41.037041],"type":"Point"}
}