{
  "type": "Feature",
  "properties": {
    "addr:full":"12 W Main St Marlton NJ 08053",
    "addr:housenumber":"12",
    "addr:postcode":"08053",
    "addr:street":"W Main St",
    "iso:country":"US",
    "sg:address":"12 W Main St",
    "sg:city":"Marlton",
    "sg:classifiers":[
        {
            "category":"Personal",
            "subcategory":"Beauty Salon",
            "type":"Services"
        }
    ],
    "sg:phone":"+1   ",
    "sg:postcode":"08053",
    "sg:province":"NJ",
    "sg:tags":[
        "shop"
    ],
    "wof:name":"Beauty By Tiki",
    "wof:placetype":"venue"
},
  "geometry": {"coordinates":[-74.926225,39.892105],"type":"Point"}
}