{
  "type": "Feature",
  "properties": {
    "iso:country":"US",
    "sg:address":"3273 Evergreen Ln",
    "sg:city":"South Plainfield",
    "sg:classifiers":[
        {
            "category":"Retail",
            "subcategory":"Portrait Studio",
            "type":"Services"
        }
    ],
    "sg:phone":"+1   ",
    "sg:postcode":"07080",
    "sg:province":"NJ",
    "sg:tags":[
        "photo"
    ],
    "wof:name":"Photography By Tim Sexton",
    "wof:placetype":"venue"
},
  "geometry": {"coordinates":[-74.390146,40.582951],"type":"Point"}
}