{
  "type": "Feature",
  "properties": {
    "iso:country":"US",
    "sg:address":"690 Lawrenceville Rd",
    "sg:city":"Trenton",
    "sg:classifiers":[
        {
            "category":"Personal",
            "subcategory":"Beauty Salon",
            "type":"Services"
        }
    ],
    "sg:phone":"+1 609 882 4092",
    "sg:postcode":"08648",
    "sg:province":"NJ",
    "wof:name":"Francis William & Co",
    "wof:placetype":"venue"
},
  "geometry": {"coordinates":[-74.741827,40.255354],"type":"Point"}
}