{
  "type": "Feature",
  "properties": {
    "addr:full":"1429 Pacific Ave Atlantic City NJ 08401",
    "addr:housenumber":"1429",
    "addr:postcode":"08401",
    "addr:street":"Pacific Ave",
    "iso:country":"US",
    "sg:address":"1429 Pacific Ave",
    "sg:city":"Atlantic City",
    "sg:classifiers":[
        {
            "category":"Banks & Credit Unions",
            "subcategory":"Bank",
            "type":"Services"
        }
    ],
    "sg:phone":"+1   ",
    "sg:postcode":"08401",
    "sg:province":"NJ",
    "sg:tags":[
        "depository",
        "banking"
    ],
    "wof:name":"Checcs",
    "wof:placetype":"venue"
},
  "geometry": {"coordinates":[-74.427407,39.360541],"type":"Point"}
}