{
  "type": "Feature",
  "properties": {
    "iso:country":"US",
    "sg:address":"415 Baldwin Ave",
    "sg:city":"Jersey City",
    "sg:classifiers":[
        {
            "category":"Shopping",
            "subcategory":"Pharmacy",
            "type":"Retail Goods"
        }
    ],
    "sg:phone":"+1 201 653 1683",
    "sg:postcode":"07306",
    "sg:province":"NJ",
    "wof:name":"Donato Di Paola Pharmacy",
    "wof:placetype":"venue"
},
  "geometry": {"coordinates":[-74.053134,40.734945],"type":"Point"}
}