{
  "type": "Feature",
  "properties": {
    "addr:full":"716 Hessian Ave National Park NJ 08063",
    "addr:housenumber":"716",
    "addr:postcode":"08063",
    "addr:street":"Hessian Ave",
    "iso:country":"US",
    "sg:address":"716 Hessian Ave",
    "sg:city":"National Park",
    "sg:classifiers":[
        {
            "category":"Arts & Performance",
            "subcategory":"Theater",
            "type":"Entertainment"
        }
    ],
    "sg:phone":"+1   ",
    "sg:postcode":"08063",
    "sg:province":"NJ",
    "sg:tags":[
        "group"
    ],
    "wof:name":"Peter A Broomall Stringback",
    "wof:placetype":"venue"
},
  "geometry": {"coordinates":[-75.176417,39.864808],"type":"Point"}
}