{
  "type": "Feature",
  "properties": {
    "addr:full":"1000 Rahway Rd Plainfield NJ 07060",
    "addr:housenumber":"1000",
    "addr:postcode":"07060",
    "addr:street":"Rahway Rd",
    "iso:country":"US",
    "sg:address":"1000 Rahway Rd",
    "sg:city":"Plainfield",
    "sg:classifiers":[
        {
            "category":"Health Services",
            "subcategory":"Doctor",
            "type":"Services"
        }
    ],
    "sg:phone":"+1 908 753 2043",
    "sg:postcode":"07060",
    "sg:province":"NJ",
    "sg:tags":[
        "female",
        "care"
    ],
    "wof:name":"Female Health Associates Inc",
    "wof:placetype":"venue"
},
  "geometry": {"coordinates":[-74.394858,40.61352],"type":"Point"}
}