{
  "type": "Feature",
  "properties": {
    "addr:full":"5 Marathon St Toms River NJ 08757",
    "addr:housenumber":"5",
    "addr:postcode":"08757",
    "addr:street":"Marathon St",
    "iso:country":"US",
    "sg:address":"5 Marathon St",
    "sg:city":"Toms River",
    "sg:classifiers":[
        {
            "category":"Organizations",
            "subcategory":"Non-profit Organization",
            "type":"Services"
        }
    ],
    "sg:phone":"+1 732 797 2566",
    "sg:postcode":"08757",
    "sg:province":"NJ",
    "sg:tags":[
        "disability"
    ],
    "sg:website":"www.iacea.org",
    "wof:name":"Iacea Inc",
    "wof:placetype":"venue"
},
  "geometry": {"coordinates":[-74.26047699999999,39.981791],"type":"Point"}
}