{
  "type": "Feature",
  "properties": {
    "iso:country":"US",
    "sg:address":"1103 Sunset Rd Ste 3",
    "sg:city":"Burlington",
    "sg:classifiers":[
        {
            "category":"Cinema",
            "subcategory":"Movie Rental",
            "type":"Entertainment"
        }
    ],
    "sg:phone":"+1 609 871 6070",
    "sg:postcode":"08016",
    "sg:province":"NJ",
    "sg:tags":[
        "game",
        "video"
    ],
    "wof:name":"Palace Video",
    "wof:placetype":"venue"
},
  "geometry": {"coordinates":[-74.84410099999999,40.050598],"type":"Point"}
}