{
  "type": "Feature",
  "properties": {
    "iso:country":"US",
    "sg:address":"795 S Springfield Ave",
    "sg:city":"Springfield",
    "sg:classifiers":[
        {
            "category":"Professional",
            "type":"Services"
        }
    ],
    "sg:phone":"+1 973 467 1050",
    "sg:postcode":"07081",
    "sg:province":"NJ",
    "sg:tags":[
        "management",
        "property"
    ],
    "wof:name":"Mountainview Gardens",
    "wof:placetype":"venue"
},
  "geometry": {"coordinates":[-74.325041,40.687624],"type":"Point"}
}