{
  "type": "Feature",
  "properties": {
    "iso:country":"US",
    "sg:address":"512 Back Neck Rd",
    "sg:city":"Bridgeton",
    "sg:classifiers":[
        {
            "category":"Building & Trades",
            "subcategory":"Construction",
            "type":"Services"
        }
    ],
    "sg:phone":"+1 856 453 4213",
    "sg:postcode":"08302",
    "sg:province":"NJ",
    "sg:tags":[
        "house"
    ],
    "wof:name":"Jjr Construction",
    "wof:placetype":"venue"
},
  "geometry": {"coordinates":[-75.27325999999999,39.369552],"type":"Point"}
}