{
  "type": "Feature",
  "properties": {
    "addr:full":"319 State Route 10 Ste 2 East Hanover NJ 07936",
    "addr:housenumber":"319",
    "addr:postcode":"07936",
    "addr:street":"State Route 10 Ste 2",
    "iso:country":"US",
    "sg:address":"319 State Route 10 Ste 2",
    "sg:city":"East Hanover",
    "sg:classifiers":[
        {
            "category":"Arts & Performance",
            "subcategory":"Art Gallery",
            "type":"Entertainment"
        }
    ],
    "sg:phone":"+1 973 884 9145",
    "sg:postcode":"07936",
    "sg:province":"NJ",
    "sg:website":"www.gatehousegalleries.com",
    "wof:name":"Gate House Frame Co",
    "wof:placetype":"venue"
},
  "geometry": {"coordinates":[-74.367706,40.804847],"type":"Point"}
}