{
  "type": "Feature",
  "properties": {
    "iso:country":"US",
    "sg:address":"430 Greenwich St",
    "sg:city":"Belvidere",
    "sg:classifiers":[
        {
            "category":"Professional",
            "subcategory":"Lawyer & Legal Services",
            "type":"Services"
        }
    ],
    "sg:phone":"+1 908 475 3382",
    "sg:postcode":"07823",
    "sg:province":"NJ",
    "wof:name":"Hampshire Thomas R Atty",
    "wof:placetype":"venue"
},
  "geometry": {"coordinates":[-75.07862799999999,40.823999],"type":"Point"}
}