{
  "type": "Feature",
  "properties": {
    "iso:country":"US",
    "sg:address":"860 US Hwy 206",
    "sg:city":"Bordentown",
    "sg:classifiers":[
        {
            "category":"Autos & Motor Vehicles",
            "subcategory":"Automobile Sales",
            "type":"Retail Goods"
        }
    ],
    "sg:phone":"+1 609 298 4990",
    "sg:postcode":"08505",
    "sg:province":"NJ",
    "sg:tags":[
        "body",
        "repair",
        "general"
    ],
    "sg:website":"www.townford.net",
    "wof:name":"Town Ford Inc",
    "wof:placetype":"venue"
},
  "geometry": {"coordinates":[-74.699787,40.166561],"type":"Point"}
}