{
  "type": "Feature",
  "properties": {
    "iso:country":"US",
    "sg:address":"275 Linden Ave",
    "sg:city":"Jersey City",
    "sg:classifiers":[
        {
            "category":"Professional",
            "subcategory":"Art Services",
            "type":"Services"
        }
    ],
    "sg:phone":"+1   ",
    "sg:postcode":"07305",
    "sg:province":"NJ",
    "sg:tags":[
        "commercial",
        "design"
    ],
    "wof:name":"A&J Graphics Liability Company",
    "wof:placetype":"venue"
},
  "geometry": {"coordinates":[-74.096497,40.700879],"type":"Point"}
}