{
  "type": "Feature",
  "properties": {
    "iso:country":"US",
    "sg:address":"100 US Hwy 46",
    "sg:city":"Hackettstown",
    "sg:classifiers":[
        {
            "category":"Professional",
            "subcategory":"Business Services",
            "type":"Services"
        }
    ],
    "sg:phone":"+1   ",
    "sg:postcode":"07840",
    "sg:province":"NJ",
    "wof:name":"Tricounty Answering Service",
    "wof:placetype":"venue"
},
  "geometry": {"coordinates":[-74.830975,40.854545],"type":"Point"}
}