{
  "type": "Feature",
  "properties": {
    "addr:full":"141 S Black Horse Pike Blackwood NJ 08012",
    "addr:housenumber":"141",
    "addr:postcode":"08012",
    "addr:street":"S Black Horse Pike",
    "iso:country":"US",
    "sg:address":"141 S Black Horse Pike",
    "sg:city":"Blackwood",
    "sg:classifiers":[
        {
            "category":"Utilities",
            "subcategory":"Telephone",
            "type":"Services"
        }
    ],
    "sg:phone":"+1 856 401 9430",
    "sg:postcode":"08012",
    "sg:province":"NJ",
    "sg:tags":[
        "telecommunication"
    ],
    "wof:name":"WFI",
    "wof:placetype":"venue"
},
  "geometry": {"coordinates":[-75.066114,39.800791],"type":"Point"}
}