{
  "type": "Feature",
  "properties": {
    "addr:full":"126 E River Rd Rumson NJ 07760",
    "addr:housenumber":"126",
    "addr:postcode":"07760",
    "addr:street":"E River Rd",
    "iso:country":"US",
    "sg:address":"126 E River Rd",
    "sg:city":"Rumson",
    "sg:classifiers":[
        {
            "category":"Personal",
            "subcategory":"Beauty Salon",
            "type":"Services"
        }
    ],
    "sg:phone":"+1 732 450 0351",
    "sg:postcode":"07760",
    "sg:province":"NJ",
    "sg:tags":[
        "shop"
    ],
    "wof:name":"Reve Inc",
    "wof:placetype":"venue"
},
  "geometry": {"coordinates":[-73.999661,40.372292],"type":"Point"}
}