{
  "type": "Feature",
  "properties": {
    "iso:country":"US",
    "sg:address":"133 Village Dr",
    "sg:city":"Barnegat",
    "sg:classifiers":[
        {
            "category":"Building & Trades",
            "subcategory":"Construction",
            "type":"Services"
        }
    ],
    "sg:phone":"+1 609 698 0427",
    "sg:postcode":"08005",
    "sg:province":"NJ",
    "sg:tags":[
        "carpet",
        "contractor"
    ],
    "wof:name":"Robert J Heimall Carpet Contrs",
    "wof:placetype":"venue"
},
  "geometry": {"coordinates":[-74.245073,39.741515],"type":"Point"}
}