{
  "type": "Feature",
  "properties": {
    "iso:country":"US",
    "sg:address":"1090 Pompton Ave",
    "sg:city":"Cedar Grove",
    "sg:classifiers":[
        {
            "category":"Education",
            "subcategory":"Preschool",
            "type":"Public Place"
        },
        {
            "category":"Education",
            "subcategory":"School",
            "type":"Public Place"
        }
    ],
    "sg:phone":"+1 973 837 9180",
    "sg:postcode":"07009",
    "sg:province":"NJ",
    "sg:tags":[
        "elementary"
    ],
    "wof:name":"The Learning Experience At Cedar Grove",
    "wof:placetype":"venue"
},
  "geometry": {"coordinates":[-74.23617900000001,40.869531],"type":"Point"}
}