{
  "type": "Feature",
  "properties": {
    "addr:full":"129 Melissa Ct Lakewood NJ 08701",
    "addr:housenumber":"129",
    "addr:postcode":"08701",
    "addr:street":"Melissa Ct",
    "iso:country":"US",
    "sg:address":"129 Melissa Ct",
    "sg:city":"Lakewood",
    "sg:classifiers":[
        {
            "category":"Wholesale",
            "subcategory":"Electrical",
            "type":"Manufacturing & Wholesale Goods"
        }
    ],
    "sg:phone":"+1 732 730 2113",
    "sg:postcode":"08701",
    "sg:province":"NJ",
    "sg:tags":[
        "equipment",
        "electronic",
        "supply"
    ],
    "wof:name":"Ubui",
    "wof:placetype":"venue"
},
  "geometry": {"coordinates":[-74.21716600000001,40.051318],"type":"Point"}
}