{
  "type": "Feature",
  "properties": {
    "iso:country":"US",
    "sg:address":"3 Elizabeth Pl",
    "sg:city":"Englishtown",
    "sg:classifiers":[
        {
            "category":"Real Estate",
            "subcategory":"Real Estate Operator",
            "type":"Services"
        }
    ],
    "sg:phone":"+1   ",
    "sg:postcode":"07726",
    "sg:province":"NJ",
    "sg:tags":[
        "building",
        "nonresidential"
    ],
    "wof:name":"Mw Property Assoc LLC",
    "wof:placetype":"venue"
},
  "geometry": {"coordinates":[-74.34539599999999,40.309861],"type":"Point"}
}