{
  "type": "Feature",
  "properties": {
    "addr:full":"304 Old Mill Rd Spring Lake NJ 07762",
    "addr:housenumber":"304",
    "addr:postcode":"07762",
    "addr:street":"Old Mill Rd",
    "iso:country":"US",
    "sg:address":"304 Old Mill Rd",
    "sg:city":"Spring Lake",
    "sg:classifiers":[
        {
            "category":"Building & Trades",
            "subcategory":"Construction",
            "type":"Services"
        }
    ],
    "sg:phone":"+1 732 974 1865",
    "sg:postcode":"07762",
    "sg:province":"NJ",
    "sg:tags":[
        "painter"
    ],
    "wof:name":"Justin Slattery Painting Contr",
    "wof:placetype":"venue"
},
  "geometry": {"coordinates":[-74.052418,40.146951],"type":"Point"}
}