{
  "type": "Feature",
  "properties": {
    "addr:full":"188 E Broadway Salem NJ 08079",
    "addr:housenumber":"188",
    "addr:postcode":"08079",
    "addr:street":"E Broadway",
    "iso:country":"US",
    "sg:address":"188 E Broadway",
    "sg:city":"Salem",
    "sg:classifiers":[
        {
            "category":"Restaurant",
            "type":"Food & Drink"
        }
    ],
    "sg:menulink":"http://www.allmenus.com/nj/salem/11002-pats-pizzeria/menu/",
    "sg:phone":"+1 856 935 6776",
    "sg:postcode":"08079",
    "sg:province":"NJ",
    "sg:tags":[
        "italian"
    ],
    "wof:name":"Pat's Pizzeria",
    "wof:placetype":"venue"
},
  "geometry": {"coordinates":[-75.466122,39.571494],"type":"Point"}
}