{
  "type": "Feature",
  "properties": {
    "iso:country":"US",
    "sg:address":"201 Roseld Ave",
    "sg:city":"Deal",
    "sg:classifiers":[
        {
            "category":"Education",
            "subcategory":"School",
            "type":"Public Place"
        }
    ],
    "sg:phone":"+1 732 531 0480",
    "sg:postcode":"07723",
    "sg:province":"NJ",
    "sg:website":"www.dealschool.org",
    "wof:name":"Deal Borough School District",
    "wof:placetype":"venue"
},
  "geometry": {"coordinates":[-74.007986,40.248135],"type":"Point"}
}