{
  "type": "Feature",
  "properties": {
    "iso:country":"US",
    "sg:address":"1988 US Hwy 22",
    "sg:city":"Scotch Plains",
    "sg:classifiers":[
        {
            "category":"Professional",
            "subcategory":"Detective & Security Services",
            "type":"Services"
        }
    ],
    "sg:phone":"+1   ",
    "sg:postcode":"07076",
    "sg:province":"NJ",
    "sg:tags":[
        "car"
    ],
    "wof:name":"Store 06-579-2467",
    "wof:placetype":"venue"
},
  "geometry": {"coordinates":[-74.400677,40.656315],"type":"Point"}
}