{
  "type": "Feature",
  "properties": {
    "addr:full":"1053 Oakland Ct Teaneck NJ 07666",
    "addr:housenumber":"1053",
    "addr:postcode":"07666",
    "addr:street":"Oakland Ct",
    "iso:country":"US",
    "sg:address":"1053 Oakland Ct",
    "sg:city":"Teaneck",
    "sg:classifiers":[
        {
            "category":"Professional",
            "subcategory":"Management & Consulting",
            "type":"Services"
        }
    ],
    "sg:phone":"+1 201 836 6953",
    "sg:postcode":"07666",
    "sg:province":"NJ",
    "wof:name":"Paul Wilson & Assoc Inc",
    "wof:placetype":"venue"
},
  "geometry": {"coordinates":[-74.02337900000001,40.897075],"type":"Point"}
}