{
  "type": "Feature",
  "properties": {
    "addr:full":"100 Northfield Ave Frnt 1 West Orange NJ 07052",
    "addr:housenumber":"100;1",
    "addr:postcode":"07052",
    "addr:street":"Northfield Ave Frnt",
    "iso:country":"US",
    "sg:address":"100 Northfield Ave Frnt 1",
    "sg:city":"West Orange",
    "sg:classifiers":[
        {
            "category":"Health Services",
            "subcategory":"Doctor",
            "type":"Services"
        }
    ],
    "sg:phone":"+1 973 243 7000",
    "sg:postcode":"07052",
    "sg:province":"NJ",
    "wof:name":"Wildman Joseph MD",
    "wof:placetype":"venue"
},
  "geometry": {"coordinates":[-74.24424500000001,40.775401],"type":"Point"}
}