{
  "type": "Feature",
  "properties": {
    "iso:country":"US",
    "sg:address":"329 Windsor Ct",
    "sg:city":"Cherry Hill",
    "sg:classifiers":[
        {
            "category":"Shopping",
            "type":"Retail Goods"
        }
    ],
    "sg:phone":"+1   ",
    "sg:postcode":"08002",
    "sg:province":"NJ",
    "sg:tags":[
        "merchandise"
    ],
    "wof:name":"Blitz Art Products Inc",
    "wof:placetype":"venue"
},
  "geometry": {"coordinates":[-75.00796200000001,39.923665],"type":"Point"}
}