{
  "type": "Feature",
  "properties": {
    "iso:country":"US",
    "sg:address":"405 Braun Ave",
    "sg:city":"Highland Park",
    "sg:classifiers":[
        {
            "category":"Shopping",
            "subcategory":"Clothing, Apparel, & Fashions",
            "type":"Retail Goods"
        }
    ],
    "sg:phone":"+1   ",
    "sg:postcode":"08904",
    "sg:province":"NJ",
    "sg:tags":[
        "leather",
        "coat",
        "lady"
    ],
    "wof:name":"Continental Leather Coat Co",
    "wof:placetype":"venue"
},
  "geometry": {"coordinates":[-74.42502,40.494358],"type":"Point"}
}