{
  "type": "Feature",
  "properties": {
    "addr:full":"1372 Main Ave Clifton NJ 07011",
    "addr:housenumber":"1372",
    "addr:postcode":"07011",
    "addr:street":"Main Ave",
    "iso:country":"US",
    "sg:address":"1372 Main Ave",
    "sg:city":"Clifton",
    "sg:classifiers":[
        {
            "category":"Autos & Motor Vehicles",
            "subcategory":"Auto Supplies",
            "type":"Retail Goods"
        },
        {
            "category":"Wholesale",
            "subcategory":"Auto Parts",
            "type":"Manufacturing & Wholesale Goods"
        }
    ],
    "sg:phone":"+1 973 253 3900",
    "sg:postcode":"07011",
    "sg:province":"NJ",
    "sg:tags":[
        "equipment",
        "racing",
        "automobile",
        "car",
        "accessory"
    ],
    "sg:website":"www.imp-auto.com",
    "wof:name":"I M P Intl Motorsports",
    "wof:placetype":"venue"
},
  "geometry": {"coordinates":[-74.144075,40.879676],"type":"Point"}
}