{
  "type": "Feature",
  "properties": {
    "addr:full":"432 Forest Ave Paramus NJ 07652",
    "addr:housenumber":"432",
    "addr:postcode":"07652",
    "addr:street":"Forest Ave",
    "iso:country":"US",
    "sg:address":"432 Forest Ave",
    "sg:city":"Paramus",
    "sg:classifiers":[
        {
            "category":"Shopping",
            "subcategory":"Jewelry",
            "type":"Retail Goods"
        }
    ],
    "sg:phone":"+1 201 368 0286",
    "sg:postcode":"07652",
    "sg:province":"NJ",
    "sg:tags":[
        "jeweler"
    ],
    "wof:name":"Zales The Diamond Store",
    "wof:placetype":"venue"
},
  "geometry": {"coordinates":[-74.051203,40.944061],"type":"Point"}
}