{
  "type": "Feature",
  "properties": {
    "addr:full":"826 State Rt 3 Clifton NJ 07012",
    "addr:housenumber":"826",
    "addr:postcode":"07012",
    "addr:street":"State Rt 3",
    "iso:country":"US",
    "sg:address":"826 State Rt 3",
    "sg:city":"Clifton",
    "sg:classifiers":[
        {
            "category":"Restaurant",
            "type":"Food & Drink"
        }
    ],
    "sg:phone":"+1 973 778 1828",
    "sg:postcode":"07012",
    "sg:province":"NJ",
    "sg:tags":[
        "traditional",
        "american"
    ],
    "sg:website":"www.fridays.com",
    "wof:name":"TGI Friday's",
    "wof:placetype":"venue"
},
  "geometry": {"coordinates":[-74.156994,40.838568],"type":"Point"}
}