{
  "type": "Feature",
  "properties": {
    "addr:full":"418 Monroe St Hoboken NJ 07030",
    "addr:housenumber":"418",
    "addr:postcode":"07030",
    "addr:street":"Monroe St",
    "iso:country":"US",
    "sg:address":"418 Monroe St",
    "sg:city":"Hoboken",
    "sg:classifiers":[
        {
            "category":"Organizations",
            "subcategory":"Religious Organization",
            "type":"Services"
        }
    ],
    "sg:phone":"+1   ",
    "sg:postcode":"07030",
    "sg:province":"NJ",
    "wof:name":"Rose Of Sharon Holy Church",
    "wof:placetype":"venue"
},
  "geometry": {"coordinates":[-74.038768,40.743634],"type":"Point"}
}