{
  "type": "Feature",
  "properties": {
    "addr:full":"108 Jackson Ave Rutherford NJ 07070",
    "addr:housenumber":"108",
    "addr:postcode":"07070",
    "addr:street":"Jackson Ave",
    "iso:country":"US",
    "sg:address":"108 Jackson Ave",
    "sg:city":"Rutherford",
    "sg:classifiers":[
        {
            "category":"Building & Trades",
            "subcategory":"Locksmith",
            "type":"Services"
        }
    ],
    "sg:phone":"+1 201 528 9131",
    "sg:postcode":"07070",
    "sg:province":"NJ",
    "sg:tags":[
        "key"
    ],
    "wof:name":"A-1 All Emergency Locksmith",
    "wof:placetype":"venue"
},
  "geometry": {"coordinates":[-74.116563,40.837786],"type":"Point"}
}