{
  "type": "Feature",
  "properties": {
    "iso:country":"US",
    "sg:address":"39 Ferry St",
    "sg:city":"Newark",
    "sg:classifiers":[
        {
            "category":"Freight",
            "type":"Transportation"
        }
    ],
    "sg:phone":"+1 973 589 2422",
    "sg:postcode":"07105",
    "sg:province":"NJ",
    "wof:name":"CSC Transportation",
    "wof:placetype":"venue"
},
  "geometry": {"coordinates":[-74.163354,40.732524],"type":"Point"}
}