{
  "type": "Feature",
  "properties": {
    "addr:full":"85 Grove St Montclair NJ 07042",
    "addr:housenumber":"85",
    "addr:postcode":"07042",
    "addr:street":"Grove St",
    "iso:country":"US",
    "sg:address":"85 Grove St",
    "sg:city":"Montclair",
    "sg:classifiers":[
        {
            "category":"Personal",
            "type":"Services"
        }
    ],
    "sg:phone":"+1   ",
    "sg:postcode":"07042",
    "sg:province":"NJ",
    "wof:name":"Nutri West",
    "wof:placetype":"venue"
},
  "geometry": {"coordinates":[-74.21050700000001,40.812287],"type":"Point"}
}