{
  "type": "Feature",
  "properties": {
    "iso:country":"US",
    "sg:address":"829 Fay Ct",
    "sg:city":"Point Pleasant Beach",
    "sg:classifiers":[
        {
            "category":"Building & Trades",
            "subcategory":"Construction",
            "type":"Services"
        }
    ],
    "sg:phone":"+1 732 892 2938",
    "sg:postcode":"08742",
    "sg:province":"NJ",
    "sg:tags":[
        "hanging"
    ],
    "wof:name":"Richard M Moor Painting Contr",
    "wof:placetype":"venue"
},
  "geometry": {"coordinates":[-74.05743,40.07439],"type":"Point"}
}