{
  "type": "Feature",
  "properties": {
    "addr:full":"34 Gary Dr Englishtown NJ 07726",
    "addr:housenumber":"34",
    "addr:postcode":"07726",
    "addr:street":"Gary Dr",
    "iso:country":"US",
    "sg:address":"34 Gary Dr",
    "sg:city":"Englishtown",
    "sg:classifiers":[
        {
            "category":"Professional",
            "subcategory":"Business Services",
            "type":"Services"
        }
    ],
    "sg:phone":"+1   ",
    "sg:postcode":"07726",
    "sg:province":"NJ",
    "wof:name":"Kdb Marketing Group Inc",
    "wof:placetype":"venue"
},
  "geometry": {"coordinates":[-74.29970299999999,40.334695],"type":"Point"}
}