{
  "type": "Feature",
  "properties": {
    "addr:full":"4000 Route 130 Delran NJ 08075",
    "addr:housenumber":"4000",
    "addr:postcode":"08075",
    "addr:street":"Route 130",
    "iso:country":"US",
    "sg:address":"4000 Route 130",
    "sg:city":"Delran",
    "sg:classifiers":[
        {
            "category":"Bars & Pubs",
            "type":"Food & Drink"
        },
        {
            "category":"Restaurant",
            "type":"Food & Drink"
        },
        {
            "category":"Fast Food",
            "type":"Food & Drink"
        }
    ],
    "sg:phone":"+1 856 461 1023",
    "sg:postcode":"08075",
    "sg:province":"NJ",
    "sg:tags":[
        "grill",
        "style",
        "family",
        "lunch",
        "american",
        "take",
        "brunch",
        "breakfast"
    ],
    "sg:website":"http://www.chilis.com",
    "wof:name":"Chili's Grill & Bar",
    "wof:placetype":"venue"
},
  "geometry": {"coordinates":[-74.962479,40.011799],"type":"Point"}
}