{
  "type": "Feature",
  "properties": {
    "addr:full":"1 E Park Dr Paterson NJ 07504",
    "addr:housenumber":"1",
    "addr:postcode":"07504",
    "addr:street":"E Park Dr",
    "iso:country":"US",
    "sg:address":"1 E Park Dr",
    "sg:city":"Paterson",
    "sg:classifiers":[
        {
            "category":"Health Services",
            "subcategory":"Doctor",
            "type":"Services"
        }
    ],
    "sg:phone":"+1 973 279 9063",
    "sg:postcode":"07504",
    "sg:province":"NJ",
    "sg:tags":[
        "medical"
    ],
    "wof:name":"Asher Aladjem MD",
    "wof:placetype":"venue"
},
  "geometry": {"coordinates":[-74.137046,40.914415],"type":"Point"}
}