{
  "type": "Feature",
  "properties": {
    "iso:country":"US",
    "sg:address":"102 Brighton Ave",
    "sg:city":"Kearny",
    "sg:classifiers":[
        {
            "category":"Social Services",
            "subcategory":"Child Care",
            "type":"Services"
        }
    ],
    "sg:phone":"+1 201 246 0306",
    "sg:postcode":"07032",
    "sg:province":"NJ",
    "sg:tags":[
        "day"
    ],
    "wof:name":"Cultural & Child Developm",
    "wof:placetype":"venue"
},
  "geometry": {"coordinates":[-74.15434500000001,40.761351],"type":"Point"}
}