{
  "type": "Feature",
  "properties": {
    "addr:full":"321 Broad Ave Ridgefield NJ 07657",
    "addr:housenumber":"321",
    "addr:postcode":"07657",
    "addr:street":"Broad Ave",
    "iso:country":"US",
    "sg:address":"321 Broad Ave",
    "sg:city":"Ridgefield",
    "sg:classifiers":[
        {
            "category":"Shopping",
            "subcategory":"Mobile Phones",
            "type":"Retail Goods"
        }
    ],
    "sg:phone":"+1 201 943 9051",
    "sg:postcode":"07657",
    "sg:province":"NJ",
    "wof:name":"Digitobi",
    "wof:placetype":"venue"
},
  "geometry": {"coordinates":[-74.009399,40.825199],"type":"Point"}
}