{
  "type": "Feature",
  "properties": {
    "addr:full":"1003 Main St Asbury Park NJ 07712",
    "addr:housenumber":"1003",
    "addr:postcode":"07712",
    "addr:street":"Main St Asbury",
    "iso:country":"US",
    "sg:address":"1003 Main St",
    "sg:city":"Asbury Park",
    "sg:classifiers":[
        {
            "category":"Home & Garden",
            "subcategory":"Home Furnishings",
            "type":"Retail Goods"
        }
    ],
    "sg:phone":"+1 732 897 1450",
    "sg:postcode":"07712",
    "sg:province":"NJ",
    "sg:tags":[
        "fireplace"
    ],
    "wof:name":"Alpine Fireplaces Heating",
    "wof:placetype":"venue"
},
  "geometry": {"coordinates":[-74.010739,40.223542],"type":"Point"}
}