{
  "type": "Feature",
  "properties": {
    "iso:country":"US",
    "sg:address":"11 Eton Dr",
    "sg:city":"Caldwell",
    "sg:classifiers":[
        {
            "category":"Professional",
            "subcategory":"Art Services",
            "type":"Services"
        }
    ],
    "sg:phone":"+1   ",
    "sg:postcode":"07006",
    "sg:province":"NJ",
    "sg:tags":[
        "commercial",
        "design"
    ],
    "wof:name":"C Squared Studios Inc",
    "wof:placetype":"venue"
},
  "geometry": {"coordinates":[-74.26651200000001,40.859842],"type":"Point"}
}