{
  "type": "Feature",
  "properties": {
    "iso:country":"US",
    "sg:address":"325 Columbia Tpke",
    "sg:city":"Florham Park",
    "sg:classifiers":[
        {
            "category":"Manufacturing",
            "subcategory":"Rubber & Plastics",
            "type":"Manufacturing & Wholesale Goods"
        }
    ],
    "sg:phone":"+1 973 514 2010",
    "sg:postcode":"07932",
    "sg:province":"NJ",
    "sg:tags":[
        "product",
        "sheet",
        "fabricated",
        "mfg"
    ],
    "sg:website":"www.longwood-elastomers.com",
    "wof:name":"Longwood Industries Inc",
    "wof:placetype":"venue"
},
  "geometry": {"coordinates":[-74.41770099999999,40.790989],"type":"Point"}
}