{
  "type": "Feature",
  "properties": {
    "addr:full":"14 Florister Dr Trenton NJ 08690",
    "addr:housenumber":"14",
    "addr:postcode":"08690",
    "addr:street":"Florister Dr",
    "iso:country":"US",
    "sg:address":"14 Florister Dr",
    "sg:city":"Trenton",
    "sg:classifiers":[
        {
            "category":"Insurance",
            "subcategory":"Insurance Agent",
            "type":"Services"
        }
    ],
    "sg:phone":"+1   ",
    "sg:postcode":"08690",
    "sg:province":"NJ",
    "wof:name":"Lester H Navatkoski",
    "wof:placetype":"venue"
},
  "geometry": {"coordinates":[-74.66979499999999,40.23735],"type":"Point"}
}