{
  "type": "Feature",
  "properties": {
    "addr:full":"36 Readington Rd Whitehouse Sta NJ 08889",
    "addr:housenumber":"36",
    "addr:postcode":"08889",
    "addr:street":"Readington Rd",
    "iso:country":"US",
    "sg:address":"36 Readington Rd",
    "sg:city":"Whitehouse Sta",
    "sg:classifiers":[
        {
            "category":"Building & Trades",
            "subcategory":"Construction",
            "type":"Services"
        }
    ],
    "sg:phone":"+1 908 534 4251",
    "sg:postcode":"08889",
    "sg:province":"NJ",
    "sg:tags":[
        "roofing",
        "contractor"
    ],
    "wof:name":"All Bell Enterprises Inc",
    "wof:placetype":"venue"
},
  "geometry": {"coordinates":[-74.772612,40.593137],"type":"Point"}
}