{
  "type": "Feature",
  "properties": {
    "iso:country":"US",
    "sg:address":"628 Broadway",
    "sg:city":"Paterson",
    "sg:classifiers":[
        {
            "category":"Health Services",
            "subcategory":"Doctor",
            "type":"Services"
        }
    ],
    "sg:phone":"+1 973 278 8001",
    "sg:postcode":"07514",
    "sg:province":"NJ",
    "sg:tags":[
        "podiatrist"
    ],
    "wof:name":"Foot & Ankle Institute",
    "wof:placetype":"venue"
},
  "geometry": {"coordinates":[-74.14679700000001,40.918201],"type":"Point"}
}