{
  "type": "Feature",
  "properties": {
    "iso:country":"US",
    "sg:address":"132 32nd St",
    "sg:city":"Union City",
    "sg:classifiers":[
        {
            "category":"Manufacturing",
            "subcategory":"Paper Products",
            "type":"Manufacturing & Wholesale Goods"
        }
    ],
    "sg:phone":"+1 201 864 3744",
    "sg:postcode":"07087",
    "sg:province":"NJ",
    "sg:tags":[
        "box"
    ],
    "wof:name":"Connecticut Packaging Corp",
    "wof:placetype":"venue"
},
  "geometry": {"coordinates":[-74.02672,40.769181],"type":"Point"}
}