{
  "type": "Feature",
  "properties": {
    "addr:full":"14 Madison Rd Fairfield NJ 07004",
    "addr:housenumber":"14",
    "addr:postcode":"07004",
    "addr:street":"Madison Rd",
    "iso:country":"US",
    "sg:address":"14 Madison Rd",
    "sg:city":"Fairfield",
    "sg:classifiers":[
        {
            "category":"Building & Trades",
            "subcategory":"Plumbing",
            "type":"Services"
        }
    ],
    "sg:phone":"+1 973 227 4311",
    "sg:postcode":"07004",
    "sg:province":"NJ",
    "sg:tags":[
        "conditioning",
        "air",
        "system",
        "contractor"
    ],
    "wof:name":"Carrier Building Svc",
    "wof:placetype":"venue"
},
  "geometry": {"coordinates":[-74.31028499999999,40.871643],"type":"Point"}
}