{
  "type": "Feature",
  "properties": {
    "addr:full":"700 Sylvan Ave Englewood Cliffs NJ 07632",
    "addr:housenumber":"700",
    "addr:postcode":"07632",
    "addr:street":"Sylvan Ave",
    "iso:country":"US",
    "sg:address":"700 Sylvan Ave",
    "sg:city":"Englewood Cliffs",
    "sg:classifiers":[
        {
            "category":"Food & Beverages",
            "subcategory":"Groceries & Convenience Stores",
            "type":"Retail Goods"
        }
    ],
    "sg:phone":"+1   ",
    "sg:postcode":"07632",
    "sg:province":"NJ",
    "wof:name":"Sodexho",
    "wof:placetype":"venue"
},
  "geometry": {"coordinates":[-73.94693700000001,40.885193],"type":"Point"}
}