{
  "type": "Feature",
  "properties": {
    "iso:country":"US",
    "sg:address":"330 Willow St",
    "sg:city":"Teaneck",
    "sg:classifiers":[
        {
            "category":"Professional",
            "subcategory":"Computer Services",
            "type":"Services"
        }
    ],
    "sg:phone":"+1 201 836 5268",
    "sg:postcode":"07666",
    "sg:province":"NJ",
    "sg:tags":[
        "related"
    ],
    "wof:name":"Robley Cmpter Enterprises",
    "wof:placetype":"venue"
},
  "geometry": {"coordinates":[-74.01234599999999,40.872134],"type":"Point"}
}