{
  "type": "Feature",
  "properties": {
    "iso:country":"US",
    "sg:address":"210 Closter Dock Rd",
    "sg:city":"Closter",
    "sg:classifiers":[
        {
            "category":"Shopping",
            "subcategory":"Discount & Variety Stores",
            "type":"Retail Goods"
        }
    ],
    "sg:phone":"+1 201 768 7759",
    "sg:postcode":"07624",
    "sg:province":"NJ",
    "wof:name":"Wards Stores Inc",
    "wof:placetype":"venue"
},
  "geometry": {"coordinates":[-73.961832,40.973098],"type":"Point"}
}