{
  "type": "Feature",
  "properties": {
    "iso:country":"US",
    "sg:address":"533 Northfield Ave",
    "sg:city":"West Orange",
    "sg:classifiers":[
        {
            "category":"Retail",
            "subcategory":"Laundry & Dry Cleaning",
            "type":"Services"
        }
    ],
    "sg:phone":"+1 973 736 6544",
    "sg:postcode":"07052",
    "sg:province":"NJ",
    "wof:name":"St Cloud Cleaners",
    "wof:placetype":"venue"
},
  "geometry": {"coordinates":[-74.27780199999999,40.770302],"type":"Point"}
}