{
  "type": "Feature",
  "properties": {
    "iso:country":"US",
    "sg:address":"189 Clark St",
    "sg:city":"Bloomingdale",
    "sg:classifiers":[
        {
            "category":"Manufacturing",
            "subcategory":"Tools & Machinery",
            "type":"Manufacturing & Wholesale Goods"
        }
    ],
    "sg:phone":"+1 973 492 3500",
    "sg:postcode":"07403",
    "sg:province":"NJ",
    "sg:tags":[
        "machine",
        "shop"
    ],
    "wof:name":"Automated Machine Design Inc",
    "wof:placetype":"venue"
},
  "geometry": {"coordinates":[-74.340626,41.016916],"type":"Point"}
}