{
  "type": "Feature",
  "properties": {
    "iso:country":"US",
    "sg:address":"86 N Beverwyck Rd",
    "sg:city":"Lake Hiawatha",
    "sg:classifiers":[
        {
            "category":"Real Estate",
            "subcategory":"Real Estate Agent",
            "type":"Services"
        }
    ],
    "sg:phone":"+1 973 394 0344",
    "sg:postcode":"07034",
    "sg:province":"NJ",
    "sg:tags":[
        "agency",
        "rental"
    ],
    "wof:name":"Metro Apartment Rentals Ntwrk",
    "wof:placetype":"venue"
},
  "geometry": {"coordinates":[-74.38209999999999,40.881016],"type":"Point"}
}