{
  "type": "Feature",
  "properties": {
    "iso:country":"US",
    "sg:address":"1692 State Rte 88",
    "sg:city":"Brick",
    "sg:classifiers":[
        {
            "category":"Wholesale",
            "subcategory":"Groceries",
            "type":"Manufacturing & Wholesale Goods"
        }
    ],
    "sg:phone":"+1 732 684 9016",
    "sg:postcode":"08724",
    "sg:province":"NJ",
    "sg:tags":[
        "general"
    ],
    "wof:name":"SMS Unlimited Inc",
    "wof:placetype":"venue"
},
  "geometry": {"coordinates":[-74.13312999999999,40.072503],"type":"Point"}
}