{
  "type": "Feature",
  "properties": {
    "iso:country":"US",
    "sg:address":"151 Fresh Ponds Rd",
    "sg:city":"Monroe Township",
    "sg:classifiers":[
        {
            "category":"Professional",
            "subcategory":"Detective & Security Services",
            "type":"Services"
        }
    ],
    "sg:phone":"+1 732 297 6438",
    "sg:postcode":"08831",
    "sg:province":"NJ",
    "sg:tags":[
        "car"
    ],
    "wof:name":"Jn D Security",
    "wof:placetype":"venue"
},
  "geometry": {"coordinates":[-74.47085300000001,40.401948],"type":"Point"}
}