{
  "type": "Feature",
  "properties": {
    "iso:country":"US",
    "sg:address":"900 State Rte 33",
    "sg:city":"Freehold",
    "sg:classifiers":[
        {
            "category":"Local Transit",
            "type":"Transportation"
        }
    ],
    "sg:phone":"+1 732 577 0023",
    "sg:postcode":"07728",
    "sg:province":"NJ",
    "sg:tags":[
        "limousine"
    ],
    "wof:name":"Concorde Limousine Inc",
    "wof:placetype":"venue"
},
  "geometry": {"coordinates":[-74.210444,40.231177],"type":"Point"}
}