{
  "type": "Feature",
  "properties": {
    "iso:country":"US",
    "sg:address":"549 Lydia Ln",
    "sg:city":"Wyckoff",
    "sg:classifiers":[
        {
            "category":"Professional",
            "type":"Services"
        }
    ],
    "sg:phone":"+1   ",
    "sg:postcode":"07481",
    "sg:province":"NJ",
    "wof:name":"Sugimoto & Co LLC",
    "wof:placetype":"venue"
},
  "geometry": {"coordinates":[-74.18015699999999,40.992722],"type":"Point"}
}