{
  "type": "Feature",
  "properties": {
    "addr:full":"770 Woodlane Rd Mount Holly NJ 08060",
    "addr:housenumber":"770",
    "addr:postcode":"08060",
    "addr:street":"Woodlane Rd",
    "iso:country":"US",
    "sg:address":"770 Woodlane Rd",
    "sg:city":"Mount Holly",
    "sg:classifiers":[
        {
            "category":"Social Services",
            "type":"Services"
        }
    ],
    "sg:phone":"+1 609 267 0932",
    "sg:postcode":"08060",
    "sg:province":"NJ",
    "wof:name":"New Jersey Assoc of Mental Hea",
    "wof:placetype":"venue"
},
  "geometry": {"coordinates":[-74.80973299999999,40.012389],"type":"Point"}
}