{
  "type": "Feature",
  "properties": {
    "addr:full":"155 Park Ave Lyndhurst NJ 07071",
    "addr:housenumber":"155",
    "addr:postcode":"07071",
    "addr:street":"Park Ave",
    "iso:country":"US",
    "sg:address":"155 Park Ave",
    "sg:city":"Lyndhurst",
    "sg:classifiers":[
        {
            "category":"Manufacturing",
            "subcategory":"Tools & Machinery",
            "type":"Manufacturing & Wholesale Goods"
        }
    ],
    "sg:phone":"+1 201 842 2130",
    "sg:postcode":"07071",
    "sg:province":"NJ",
    "sg:tags":[
        "equipment",
        "peripheral",
        "computer",
        "mfg"
    ],
    "wof:name":"Riverknoll",
    "wof:placetype":"venue"
},
  "geometry": {"coordinates":[-74.12740700000001,40.818428],"type":"Point"}
}