{
  "type": "Feature",
  "properties": {
    "addr:full":"697 Bloomfield Ave West Caldwell NJ 07006",
    "addr:housenumber":"697",
    "addr:postcode":"07006",
    "addr:street":"Bloomfield Ave",
    "iso:country":"US",
    "sg:address":"697 Bloomfield Ave",
    "sg:city":"West Caldwell",
    "sg:classifiers":[
        {
            "category":"Real Estate",
            "subcategory":"Architect",
            "type":"Services"
        }
    ],
    "sg:phone":"+1 973 228 2208",
    "sg:postcode":"07006",
    "sg:province":"NJ",
    "sg:website":"www.arkitectureplus.com",
    "wof:name":"Arkitecture Plus",
    "wof:placetype":"venue"
},
  "geometry": {"coordinates":[-74.29180100000001,40.848801],"type":"Point"}
}