{
  "type": "Feature",
  "properties": {
    "iso:country":"US",
    "sg:address":"530 US Hwy 130",
    "sg:city":"Hightstown",
    "sg:classifiers":[
        {
            "category":"Retail",
            "subcategory":"Auto Repair",
            "type":"Services"
        }
    ],
    "sg:phone":"+1 609 443 4443",
    "sg:postcode":"08520",
    "sg:province":"NJ",
    "wof:name":"Johns Auto Repair",
    "wof:placetype":"venue"
},
  "geometry": {"coordinates":[-74.543251,40.267552],"type":"Point"}
}