{
  "type": "Feature",
  "properties": {
    "addr:full":"295 Main St Matawan NJ 07747",
    "addr:housenumber":"295",
    "addr:postcode":"07747",
    "addr:street":"Main St",
    "iso:country":"US",
    "sg:address":"295 Main St",
    "sg:city":"Matawan",
    "sg:classifiers":[
        {
            "category":"Professional",
            "subcategory":"Accounting & Tax Preparation",
            "type":"Services"
        }
    ],
    "sg:phone":"+1 732 566 0900",
    "sg:postcode":"07747",
    "sg:province":"NJ",
    "sg:tags":[
        "return",
        "filing"
    ],
    "wof:name":"Jo Ann Spinelli",
    "wof:placetype":"venue"
},
  "geometry": {"coordinates":[-74.234223,40.409459],"type":"Point"}
}