{
  "type": "Feature",
  "properties": {
    "iso:country":"US",
    "sg:address":"250 Half Mile Rd",
    "sg:city":"Red Bank",
    "sg:classifiers":[
        {
            "category":"Health Services",
            "subcategory":"Chiropractor",
            "type":"Services"
        }
    ],
    "sg:phone":"+1 732 747 8461",
    "sg:postcode":"07701",
    "sg:province":"NJ",
    "wof:name":"Acute & Chronic Back Care",
    "wof:placetype":"venue"
},
  "geometry": {"coordinates":[-74.096369,40.339287],"type":"Point"}
}