{
  "type": "Feature",
  "properties": {
    "iso:country":"US",
    "sg:address":"473 Broadway Ste 409",
    "sg:city":"Bayonne",
    "sg:classifiers":[
        {
            "category":"Autos & Motor Vehicles",
            "subcategory":"Automobile Sales",
            "type":"Retail Goods"
        },
        {
            "category":"Taxi",
            "type":"Transportation"
        }
    ],
    "sg:phone":"+1 201 243 9100",
    "sg:postcode":"07002",
    "sg:province":"NJ",
    "sg:tags":[
        "limo"
    ],
    "wof:name":"Jersey One Car and Limo Service",
    "wof:placetype":"venue"
},
  "geometry": {"coordinates":[-74.118978,40.663219],"type":"Point"}
}