{
  "type": "Feature",
  "properties": {
    "iso:country":"US",
    "sg:address":"3 Hillside Ave",
    "sg:city":"Suffern",
    "sg:classifiers":[
        {
            "category":"Building & Trades",
            "subcategory":"Construction",
            "type":"Services"
        }
    ],
    "sg:phone":"+1 845 357 5473",
    "sg:postcode":"10901",
    "sg:province":"NY",
    "sg:tags":[
        "excavating",
        "contractor"
    ],
    "wof:name":"Rino Paving & Construction Inc",
    "wof:placetype":"venue"
},
  "geometry": {"coordinates":[-74.144342,41.10998],"type":"Point"}
}