{
  "type": "Feature",
  "properties": {
    "addr:full":"3098 Pleasant St Camden NJ 08105",
    "addr:housenumber":"3098",
    "addr:postcode":"08105",
    "addr:street":"Pleasant St",
    "iso:country":"US",
    "sg:address":"3098 Pleasant St",
    "sg:city":"Camden",
    "sg:classifiers":[
        {
            "category":"Education",
            "subcategory":"Preschool",
            "type":"Public Place"
        },
        {
            "category":"Education",
            "subcategory":"School",
            "type":"Public Place"
        }
    ],
    "sg:phone":"+1 856 966 8840",
    "sg:postcode":"08105",
    "sg:province":"NJ",
    "sg:tags":[
        "elementary"
    ],
    "wof:name":"Step by Step",
    "wof:placetype":"venue"
},
  "geometry": {"coordinates":[-75.08339700000001,39.953999],"type":"Point"}
}