{
  "type": "Feature",
  "properties": {
    "iso:country":"US",
    "sg:address":"5 Shippen St",
    "sg:city":"Weehawken",
    "sg:classifiers":[
        {
            "category":"Manufacturing",
            "subcategory":"Printing",
            "type":"Manufacturing & Wholesale Goods"
        }
    ],
    "sg:phone":"+1 201 865 3976",
    "sg:postcode":"07086",
    "sg:province":"NJ",
    "sg:tags":[
        "publishing"
    ],
    "wof:name":"Punchline Publishing Co Inc",
    "wof:placetype":"venue"
},
  "geometry": {"coordinates":[-74.02635600000001,40.765154],"type":"Point"}
}