{
  "type": "Feature",
  "properties": {
    "addr:full":"77 Frederick St Hackensack NJ 07601",
    "addr:housenumber":"77",
    "addr:postcode":"07601",
    "addr:street":"Frederick St",
    "iso:country":"US",
    "sg:address":"77 Frederick St",
    "sg:city":"Hackensack",
    "sg:classifiers":[
        {
            "category":"Utilities",
            "subcategory":"Refuse",
            "type":"Services"
        }
    ],
    "sg:phone":"+1 201 489 6066",
    "sg:postcode":"07601",
    "sg:province":"NJ",
    "sg:tags":[
        "system"
    ],
    "wof:name":"North Bergen Recycling  Inc",
    "wof:placetype":"venue"
},
  "geometry": {"coordinates":[-74.045428,40.870627],"type":"Point"}
}