{
  "type": "Feature",
  "properties": {
    "addr:full":"20 S Centre St Merchantville NJ 08109",
    "addr:housenumber":"20",
    "addr:postcode":"08109",
    "addr:street":"S Centre St",
    "iso:country":"US",
    "sg:address":"20 S Centre St",
    "sg:city":"Merchantville",
    "sg:classifiers":[
        {
            "category":"Building & Trades",
            "subcategory":"Construction",
            "type":"Services"
        }
    ],
    "sg:phone":"+1 856 663 8001",
    "sg:postcode":"08109",
    "sg:province":"NJ",
    "sg:tags":[
        "contractor"
    ],
    "wof:name":"Irwin Inc James M",
    "wof:placetype":"venue"
},
  "geometry": {"coordinates":[-75.048987,39.951768],"type":"Point"}
}