{
  "type": "Feature",
  "properties": {
    "iso:country":"US",
    "sg:address":"3 Hewitt Ct",
    "sg:city":"Clayton",
    "sg:classifiers":[
        {
            "category":"Personal",
            "subcategory":"Beauty Salon",
            "type":"Services"
        }
    ],
    "sg:phone":"+1 856 307 9922",
    "sg:postcode":"08312",
    "sg:province":"NJ",
    "sg:tags":[
        "shop"
    ],
    "wof:name":"Nice Nails Inc",
    "wof:placetype":"venue"
},
  "geometry": {"coordinates":[-75.05139699999999,39.674577],"type":"Point"}
}