{
  "type": "Feature",
  "properties": {
    "iso:country":"US",
    "sg:address":"50 Walker Ave",
    "sg:city":"Closter",
    "sg:classifiers":[
        {
            "category":"Real Estate",
            "subcategory":"Real Estate Agent",
            "type":"Services"
        }
    ],
    "sg:phone":"+1   ",
    "sg:postcode":"07624",
    "sg:province":"NJ",
    "wof:name":"2465 Grand Concourse",
    "wof:placetype":"venue"
},
  "geometry": {"coordinates":[-73.94423500000001,40.971129],"type":"Point"}
}