{
  "type": "Feature",
  "properties": {
    "iso:country":"US",
    "sg:address":"525 Washington Blvd",
    "sg:city":"Jersey City",
    "sg:classifiers":[
        {
            "category":"Real Estate",
            "subcategory":"Architect",
            "type":"Services"
        }
    ],
    "sg:phone":"+1 201 792 8960",
    "sg:postcode":"07310",
    "sg:province":"NJ",
    "sg:tags":[
        "builder",
        "architectural"
    ],
    "wof:name":"C H C Construction Group Inc",
    "wof:placetype":"venue"
},
  "geometry": {"coordinates":[-74.034564,40.729988],"type":"Point"}
}