{
  "type": "Feature",
  "properties": {
    "iso:country":"US",
    "sg:address":"39 Berdan Ave",
    "sg:city":"Fair Lawn",
    "sg:classifiers":[
        {
            "category":"Home & Garden",
            "subcategory":"Carpets & Floor Coverings",
            "type":"Retail Goods"
        }
    ],
    "sg:phone":"+1   ",
    "sg:postcode":"07410",
    "sg:province":"NJ",
    "wof:name":"Budget Discount Carpets",
    "wof:placetype":"venue"
},
  "geometry": {"coordinates":[-74.105547,40.937985],"type":"Point"}
}