{
  "type": "Feature",
  "properties": {
    "addr:full":"541 Frank Applegate Rd Jackson NJ 08527",
    "addr:housenumber":"541",
    "addr:postcode":"08527",
    "addr:street":"Frank Applegate Rd",
    "iso:country":"US",
    "sg:address":"541 Frank Applegate Rd",
    "sg:city":"Jackson",
    "sg:classifiers":[
        {
            "category":"Banks & Credit Unions",
            "subcategory":"Bank",
            "type":"Services"
        }
    ],
    "sg:phone":"+1   ",
    "sg:postcode":"08527",
    "sg:province":"NJ",
    "sg:tags":[
        "national",
        "commercial"
    ],
    "wof:name":"Midlantic Management Inc",
    "wof:placetype":"venue"
},
  "geometry": {"coordinates":[-74.333029,40.139657],"type":"Point"}
}