{
  "type": "Feature",
  "properties": {
    "iso:country":"US",
    "sg:address":"5401 State Rte 42",
    "sg:city":"Blackwood",
    "sg:classifiers":[
        {
            "category":"Home & Garden",
            "subcategory":"Furniture",
            "type":"Retail Goods"
        }
    ],
    "sg:phone":"+1 856 227 0600",
    "sg:postcode":"08012",
    "sg:province":"NJ",
    "wof:name":"Diamond Furniture Inc",
    "wof:placetype":"venue"
},
  "geometry": {"coordinates":[-75.04686,39.754362],"type":"Point"}
}