{
  "type": "Feature",
  "properties": {
    "iso:country":"US",
    "sg:address":"6 Gordon Ave",
    "sg:city":"Old Bridge",
    "sg:classifiers":[
        {
            "category":"Building & Trades",
            "subcategory":"Construction",
            "type":"Services"
        }
    ],
    "sg:phone":"+1 732 251 5980",
    "sg:postcode":"08857",
    "sg:province":"NJ",
    "sg:tags":[
        "house"
    ],
    "wof:name":"Ed Home Improvement LLC",
    "wof:placetype":"venue"
},
  "geometry": {"coordinates":[-74.35957500000001,40.40235],"type":"Point"}
}