{
  "type": "Feature",
  "properties": {
    "addr:full":"1036 Falls Ter Union NJ 07083",
    "addr:housenumber":"1036",
    "addr:postcode":"07083",
    "addr:street":"Falls Ter",
    "iso:country":"US",
    "sg:address":"1036 Falls Ter",
    "sg:city":"Union",
    "sg:classifiers":[
        {
            "category":"Building & Trades",
            "subcategory":"Equipment Rental",
            "type":"Services"
        }
    ],
    "sg:phone":"+1 908 964 8181",
    "sg:postcode":"07083",
    "sg:province":"NJ",
    "sg:tags":[
        "audio",
        "supply"
    ],
    "wof:name":"Wwwparagon-Avpccom",
    "wof:placetype":"venue"
},
  "geometry": {"coordinates":[-74.27502699999999,40.697939],"type":"Point"}
}