{
  "type": "Feature",
  "properties": {
    "iso:country":"US",
    "sg:address":"901 State Rt 23",
    "sg:city":"Pompton Plains",
    "sg:classifiers":[
        {
            "category":"Health Services",
            "subcategory":"Hospital",
            "type":"Services"
        }
    ],
    "sg:phone":"+1 973 839 8444",
    "sg:postcode":"07444",
    "sg:province":"NJ",
    "wof:name":"Pompton Plains Surgical Center",
    "wof:placetype":"venue"
},
  "geometry": {"coordinates":[-74.29969800000001,40.980301],"type":"Point"}
}