{
  "type": "Feature",
  "properties": {
    "addr:full":"207 Copley Ave Teaneck NJ 07666",
    "addr:housenumber":"207",
    "addr:postcode":"07666",
    "addr:street":"Copley Ave",
    "iso:country":"US",
    "sg:address":"207 Copley Ave",
    "sg:city":"Teaneck",
    "sg:classifiers":[
        {
            "category":"Building & Trades",
            "subcategory":"Construction",
            "type":"Services"
        }
    ],
    "sg:phone":"+1 201 692 9890",
    "sg:postcode":"07666",
    "sg:province":"NJ",
    "sg:tags":[
        "house"
    ],
    "wof:name":"North Jersey Home Improvements",
    "wof:placetype":"venue"
},
  "geometry": {"coordinates":[-74.01378099999999,40.876367],"type":"Point"}
}