{
  "type": "Feature",
  "properties": {
    "addr:full":"218 Linden Ave Irvington NJ 07111",
    "addr:housenumber":"218",
    "addr:postcode":"07111",
    "addr:street":"Linden Ave",
    "iso:country":"US",
    "sg:address":"218 Linden Ave",
    "sg:city":"Irvington",
    "sg:classifiers":[
        {
            "category":"Building & Trades",
            "subcategory":"Construction",
            "type":"Services"
        }
    ],
    "sg:phone":"+1 973 416 5418",
    "sg:postcode":"07111",
    "sg:province":"NJ",
    "sg:tags":[
        "house"
    ],
    "wof:name":"Arty Construction Inc",
    "wof:placetype":"venue"
},
  "geometry": {"coordinates":[-74.224192,40.733618],"type":"Point"}
}