{
  "type": "Feature",
  "properties": {
    "addr:full":"882 Amboy Ave Edison NJ 08837",
    "addr:housenumber":"882",
    "addr:postcode":"08837",
    "addr:street":"Amboy Ave",
    "iso:country":"US",
    "sg:address":"882 Amboy Ave",
    "sg:city":"Edison",
    "sg:classifiers":[
        {
            "category":"Social Services",
            "subcategory":"Child Care",
            "type":"Services"
        },
        {
            "category":"Education",
            "subcategory":"Preschool",
            "type":"Public Place"
        },
        {
            "category":"Education",
            "subcategory":"School",
            "type":"Public Place"
        }
    ],
    "sg:phone":"+1 732 709 3324",
    "sg:postcode":"08837",
    "sg:province":"NJ",
    "sg:tags":[
        "elementary",
        "day"
    ],
    "sg:website":"www.happychilddaycare.com",
    "wof:name":"Happy Child Day Care",
    "wof:placetype":"venue"
},
  "geometry": {"coordinates":[-74.330044,40.532452],"type":"Point"}
}