{
  "type": "Feature",
  "properties": {
    "addr:full":"14 Shawmont Ln Willingboro NJ 08046",
    "addr:housenumber":"14",
    "addr:postcode":"08046",
    "addr:street":"Shawmont Ln",
    "iso:country":"US",
    "sg:address":"14 Shawmont Ln",
    "sg:city":"Willingboro",
    "sg:classifiers":[
        {
            "category":"Professional",
            "type":"Services"
        }
    ],
    "sg:phone":"+1   ",
    "sg:postcode":"08046",
    "sg:province":"NJ",
    "wof:name":"Arbor View Tree Co Inc",
    "wof:placetype":"venue"
},
  "geometry": {"coordinates":[-74.891105,40.048964],"type":"Point"}
}