{
  "type": "Feature",
  "properties": {
    "iso:country":"US",
    "sg:address":"119 Franklin St",
    "sg:city":"Belleville",
    "sg:classifiers":[
        {
            "category":"Retail",
            "subcategory":"Repair Shop",
            "type":"Services"
        }
    ],
    "sg:phone":"+1 973 854 5436",
    "sg:postcode":"07109",
    "sg:province":"NJ",
    "sg:tags":[
        "lock",
        "locksmith"
    ],
    "wof:name":"A 24 7 Emergency Locksmith",
    "wof:placetype":"venue"
},
  "geometry": {"coordinates":[-74.180837,40.780873],"type":"Point"}
}