{
  "type": "Feature",
  "properties": {
    "addr:full":"121 Meadowlark Dr Trenton NJ 08690",
    "addr:housenumber":"121",
    "addr:postcode":"08690",
    "addr:street":"Meadowlark Dr",
    "iso:country":"US",
    "sg:address":"121 Meadowlark Dr",
    "sg:city":"Trenton",
    "sg:classifiers":[
        {
            "category":"Building & Trades",
            "subcategory":"Construction",
            "type":"Services"
        }
    ],
    "sg:phone":"+1 609 581 5799",
    "sg:postcode":"08690",
    "sg:province":"NJ",
    "sg:tags":[
        "general",
        "contractor"
    ],
    "wof:name":"Bob Seeds Construction Inc",
    "wof:placetype":"venue"
},
  "geometry": {"coordinates":[-74.678155,40.216968],"type":"Point"}
}