{
  "type": "Feature",
  "properties": {
    "iso:country":"US",
    "sg:address":"4507 Park Ave Ste A",
    "sg:city":"Union City",
    "sg:classifiers":[
        {
            "category":"Restaurant",
            "type":"Food & Drink"
        }
    ],
    "sg:phone":"+1 201 866 8008",
    "sg:postcode":"07087",
    "sg:province":"NJ",
    "sg:tags":[
        "chinese"
    ],
    "wof:name":"Xin Lin Chinese Restaurant",
    "wof:placetype":"venue"
},
  "geometry": {"coordinates":[-74.018621,40.777314],"type":"Point"}
}