{
  "type": "Feature",
  "properties": {
    "addr:full":"382 US Hwy 46 Parsippany NJ 07054",
    "addr:housenumber":"382",
    "addr:postcode":"07054",
    "addr:street":"Us Hwy 46",
    "iso:country":"US",
    "sg:address":"382 US Hwy 46",
    "sg:city":"Parsippany",
    "sg:classifiers":[
        {
            "category":"Personal",
            "subcategory":"Beauty Salon",
            "type":"Services"
        }
    ],
    "sg:phone":"+1 973 227 5515",
    "sg:postcode":"07054",
    "sg:province":"NJ",
    "sg:tags":[
        "manicuring"
    ],
    "wof:name":"Tip Top Nails",
    "wof:placetype":"venue"
},
  "geometry": {"coordinates":[-74.357732,40.85905],"type":"Point"}
}