{
  "type": "Feature",
  "properties": {
    "addr:full":"471 Seabreeze Rd Bridgeton NJ 08302",
    "addr:housenumber":"471",
    "addr:postcode":"08302",
    "addr:street":"Seabreeze Rd",
    "iso:country":"US",
    "sg:address":"471 Seabreeze Rd",
    "sg:city":"Bridgeton",
    "sg:classifiers":[
        {
            "category":"Organizations",
            "subcategory":"Professional Association",
            "type":"Services"
        }
    ],
    "sg:phone":"+1   ",
    "sg:postcode":"08302",
    "sg:province":"NJ",
    "sg:tags":[
        "business"
    ],
    "wof:name":"South Jersey Nurserymans",
    "wof:placetype":"venue"
},
  "geometry": {"coordinates":[-75.298354,39.342701],"type":"Point"}
}