{
  "type": "Feature",
  "properties": {
    "addr:full":"3 Mott Pl Toms River NJ 08753",
    "addr:housenumber":"3",
    "addr:postcode":"08753",
    "addr:street":"Mott Pl",
    "iso:country":"US",
    "sg:address":"3 Mott Pl",
    "sg:city":"Toms River",
    "sg:classifiers":[
        {
            "category":"Government",
            "subcategory":"Office",
            "type":"Public Place"
        }
    ],
    "sg:phone":"+1 732 363 1317",
    "sg:postcode":"08753",
    "sg:province":"NJ",
    "wof:name":"Ocean County Security-Office",
    "wof:placetype":"venue"
},
  "geometry": {"coordinates":[-74.18990700000001,39.952605],"type":"Point"}
}