{
  "type": "Feature",
  "properties": {
    "addr:full":"760 Rattling Run Rd Mickleton NJ 08056",
    "addr:housenumber":"760",
    "addr:postcode":"08056",
    "addr:street":"Rattling Run Rd",
    "iso:country":"US",
    "sg:address":"760 Rattling Run Rd",
    "sg:city":"Mickleton",
    "sg:classifiers":[
        {
            "category":"Organizations",
            "subcategory":"Labor Organization",
            "type":"Services"
        }
    ],
    "sg:phone":"+1 856 467 1463",
    "sg:postcode":"08056",
    "sg:province":"NJ",
    "wof:name":"Richard Gregorio",
    "wof:placetype":"venue"
},
  "geometry": {"coordinates":[-75.25809700000001,39.776858],"type":"Point"}
}