{
  "type": "Feature",
  "properties": {
    "iso:country":"US",
    "sg:address":"231 Stuyvesant Ave",
    "sg:city":"Lyndhurst",
    "sg:classifiers":[
        {
            "category":"Bars & Pubs",
            "type":"Food & Drink"
        }
    ],
    "sg:phone":"+1 201 438 0187",
    "sg:postcode":"07071",
    "sg:province":"NJ",
    "wof:name":"Jerry's Tavern",
    "wof:placetype":"venue"
},
  "geometry": {"coordinates":[-74.12554299999999,40.815068],"type":"Point"}
}