{
  "type": "Feature",
  "properties": {
    "addr:full":"171 Pennsylvania Ave Flemington NJ 08822",
    "addr:housenumber":"171",
    "addr:postcode":"08822",
    "addr:street":"Pennsylvania Ave",
    "iso:country":"US",
    "sg:address":"171 Pennsylvania Ave",
    "sg:city":"Flemington",
    "sg:classifiers":[
        {
            "category":"Retail",
            "subcategory":"Repair Shop",
            "type":"Services"
        }
    ],
    "sg:phone":"+1 908 782 2689",
    "sg:postcode":"08822",
    "sg:province":"NJ",
    "sg:tags":[
        "repairing",
        "lawn",
        "mower"
    ],
    "wof:name":"Van Fleet's Mower Shop",
    "wof:placetype":"venue"
},
  "geometry": {"coordinates":[-74.838954,40.517003],"type":"Point"}
}