{
  "type": "Feature",
  "properties": {
    "iso:country":"US",
    "sg:address":"230 Clems Run",
    "sg:city":"Mullica Hill",
    "sg:classifiers":[
        {
            "category":"Home & Garden",
            "subcategory":"Garden Supply",
            "type":"Retail Goods"
        }
    ],
    "sg:phone":"+1 856 478 6305",
    "sg:postcode":"08062",
    "sg:province":"NJ",
    "sg:tags":[
        "nurseryman"
    ],
    "wof:name":"Cedar Ridge",
    "wof:placetype":"venue"
},
  "geometry": {"coordinates":[-75.199769,39.723383],"type":"Point"}
}