{
  "type": "Feature",
  "properties": {
    "addr:full":"71 Hurst Ter Wayne NJ 07470",
    "addr:housenumber":"71",
    "addr:postcode":"07470",
    "addr:street":"Hurst Ter",
    "iso:country":"US",
    "sg:address":"71 Hurst Ter",
    "sg:city":"Wayne",
    "sg:classifiers":[
        {
            "category":"Autos & Motor Vehicles",
            "subcategory":"Auto Supplies",
            "type":"Retail Goods"
        }
    ],
    "sg:phone":"+1   ",
    "sg:postcode":"07470",
    "sg:province":"NJ",
    "wof:name":"Auto Parts Source LLC",
    "wof:placetype":"venue"
},
  "geometry": {"coordinates":[-74.26300999999999,40.957676],"type":"Point"}
}