{
  "type": "Feature",
  "properties": {
    "addr:full":"98 William St Monroe Township NJ 08831",
    "addr:housenumber":"98",
    "addr:postcode":"08831",
    "addr:street":"William St",
    "iso:country":"US",
    "sg:address":"98 William St",
    "sg:city":"Monroe Township",
    "sg:classifiers":[
        {
            "category":"Manufacturing",
            "subcategory":"Metals",
            "type":"Manufacturing & Wholesale Goods"
        }
    ],
    "sg:phone":"+1 732 521 0866",
    "sg:postcode":"08831",
    "sg:province":"NJ",
    "sg:tags":[
        "structural",
        "fabrication",
        "motor",
        "mfg"
    ],
    "wof:name":"Coast Chassis Design",
    "wof:placetype":"venue"
},
  "geometry": {"coordinates":[-74.426661,40.345194],"type":"Point"}
}