{
  "type": "Feature",
  "properties": {
    "addr:full":"254 Witherspoon St Princeton NJ 08542",
    "addr:housenumber":"254",
    "addr:postcode":"08542",
    "addr:street":"Witherspoon St",
    "iso:country":"US",
    "sg:address":"254 Witherspoon St",
    "sg:city":"Princeton",
    "sg:classifiers":[
        {
            "category":"Health Services",
            "subcategory":"Doctor",
            "type":"Services"
        }
    ],
    "sg:phone":"+1 609 430 8484",
    "sg:postcode":"08542",
    "sg:province":"NJ",
    "sg:tags":[
        "physician",
        "surgeon"
    ],
    "wof:name":"Louis Berrizbeitia MD",
    "wof:placetype":"venue"
},
  "geometry": {"coordinates":[-74.662981,40.357153],"type":"Point"}
}