{
  "type": "Feature",
  "properties": {
    "addr:full":"1034 Sawmill Rd Brick NJ 08724",
    "addr:housenumber":"1034",
    "addr:postcode":"08724",
    "addr:street":"Sawmill Rd",
    "iso:country":"US",
    "sg:address":"1034 Sawmill Rd",
    "sg:city":"Brick",
    "sg:classifiers":[
        {
            "category":"Building & Trades",
            "subcategory":"Construction",
            "type":"Services"
        }
    ],
    "sg:phone":"+1 732 330 8932",
    "sg:postcode":"08724",
    "sg:province":"NJ",
    "sg:tags":[
        "tile",
        "install"
    ],
    "wof:name":"Billthetileguy",
    "wof:placetype":"venue"
},
  "geometry": {"coordinates":[-74.112582,40.108424],"type":"Point"}
}