{
  "type": "Feature",
  "properties": {
    "iso:country":"US",
    "sg:address":"861 Broad St",
    "sg:city":"Newark",
    "sg:classifiers":[
        {
            "category":"Professional",
            "subcategory":"Business Services",
            "type":"Services"
        }
    ],
    "sg:phone":"+1 973 623 4777",
    "sg:postcode":"07102",
    "sg:province":"NJ",
    "sg:tags":[
        "auctioneer"
    ],
    "wof:name":"Auction II",
    "wof:placetype":"venue"
},
  "geometry": {"coordinates":[-74.172965,40.734597],"type":"Point"}
}