{
  "type": "Feature",
  "properties": {
    "addr:full":"210 State Rte 4 Paramus NJ 07652",
    "addr:housenumber":"210",
    "addr:postcode":"07652",
    "addr:street":"State Rte 4",
    "iso:country":"US",
    "sg:address":"210 State Rte 4",
    "sg:city":"Paramus",
    "sg:classifiers":[
        {
            "category":"Shopping",
            "subcategory":"Shoes",
            "type":"Retail Goods"
        }
    ],
    "sg:phone":"+1 201 712 9511",
    "sg:postcode":"07652",
    "sg:province":"NJ",
    "wof:name":"Payless Shoe Source",
    "wof:placetype":"venue"
},
  "geometry": {"coordinates":[-74.054793,40.916142],"type":"Point"}
}