{
  "type": "Feature",
  "properties": {
    "iso:country":"US",
    "sg:address":"1386 Alps Rd",
    "sg:city":"Wayne",
    "sg:classifiers":[
        {
            "category":"Health Services",
            "subcategory":"Optometrist",
            "type":"Services"
        }
    ],
    "sg:phone":"+1 973 628 0100",
    "sg:postcode":"07470",
    "sg:province":"NJ",
    "wof:name":"Morillo-Kersulec Yvonne OD",
    "wof:placetype":"venue"
},
  "geometry": {"coordinates":[-74.245502,40.954048],"type":"Point"}
}