{
  "type": "Feature",
  "properties": {
    "iso:country":"US",
    "sg:address":"110 Madison Pl",
    "sg:city":"Ridgewood",
    "sg:classifiers":[
        {
            "category":"Professional",
            "subcategory":"Business Services",
            "type":"Services"
        }
    ],
    "sg:phone":"+1   ",
    "sg:postcode":"07450",
    "sg:province":"NJ",
    "wof:name":"Marcorp Sales Inc",
    "wof:placetype":"venue"
},
  "geometry": {"coordinates":[-74.123884,40.982377],"type":"Point"}
}