{
  "type": "Feature",
  "properties": {
    "iso:country":"US",
    "sg:address":"314 57th St",
    "sg:city":"West New York",
    "sg:classifiers":[
        {
            "category":"Autos & Motor Vehicles",
            "subcategory":"Auto Supplies",
            "type":"Retail Goods"
        }
    ],
    "sg:phone":"+1 201 867 4330",
    "sg:postcode":"07093",
    "sg:province":"NJ",
    "sg:tags":[
        "automobile",
        "parts"
    ],
    "wof:name":"Prieto's Auto Parts LLC",
    "wof:placetype":"venue"
},
  "geometry": {"coordinates":[-74.01537999999999,40.785956],"type":"Point"}
}