{
  "type": "Feature",
  "properties": {
    "iso:country":"US",
    "sg:address":"615 W Mount Pleasant Ave",
    "sg:city":"Livingston",
    "sg:classifiers":[
        {
            "category":"Professional",
            "subcategory":"Accounting & Tax Preparation",
            "type":"Services"
        }
    ],
    "sg:phone":"+1 973 994 9122",
    "sg:postcode":"07039",
    "sg:province":"NJ",
    "sg:tags":[
        "accountant"
    ],
    "wof:name":"Michael Cappicille CPA Llc",
    "wof:placetype":"venue"
},
  "geometry": {"coordinates":[-74.35520200000001,40.798401],"type":"Point"}
}