{
  "type": "Feature",
  "properties": {
    "iso:country":"US",
    "sg:address":"876 Centerton Rd",
    "sg:city":"Mount Laurel",
    "sg:classifiers":[
        {
            "category":"Restaurant",
            "type":"Food & Drink"
        }
    ],
    "sg:menulink":"http://www.allmenus.com/nj/mount-laurel/269499-carluccis-waterfront/menu/",
    "sg:phone":"+1 856 235 5737",
    "sg:postcode":"08054",
    "sg:province":"NJ",
    "sg:tags":[
        "italian"
    ],
    "wof:name":"Carlucci's Waterfront",
    "wof:placetype":"venue"
},
  "geometry": {"coordinates":[-74.87572,39.994982],"type":"Point"}
}