{
  "type": "Feature",
  "properties": {
    "iso:country":"US",
    "sg:address":"1074 State Rte 173",
    "sg:city":"Asbury",
    "sg:classifiers":[
        {
            "category":"Professional",
            "type":"Services"
        },
        {
            "category":"Autos & Motor Vehicles",
            "subcategory":"Recreational Vehicle Sales",
            "type":"Retail Goods"
        }
    ],
    "sg:phone":"+1 908 735 5995",
    "sg:postcode":"08802",
    "sg:province":"NJ",
    "sg:tags":[
        "canopy",
        "shell",
        "truck",
        "cap"
    ],
    "sg:website":"www.campoutinc.com",
    "wof:name":"Camp Out Inc",
    "wof:placetype":"venue"
},
  "geometry": {"coordinates":[-75.02455500000001,40.655918],"type":"Point"}
}