{
  "type": "Feature",
  "properties": {
    "addr:full":"225 Basin Rd Hammonton NJ 08037",
    "addr:housenumber":"225",
    "addr:postcode":"08037",
    "addr:street":"Basin Rd",
    "iso:country":"US",
    "sg:address":"225 Basin Rd",
    "sg:city":"Hammonton",
    "sg:classifiers":[
        {
            "category":"Freight",
            "type":"Transportation"
        }
    ],
    "sg:phone":"+1 609 561 8572",
    "sg:postcode":"08037",
    "sg:province":"NJ",
    "sg:tags":[
        "local",
        "without",
        "storage",
        "trucking"
    ],
    "wof:name":"Di Bona F & M Trucking Inc",
    "wof:placetype":"venue"
},
  "geometry": {"coordinates":[-74.787628,39.658688],"type":"Point"}
}