{
  "type": "Feature",
  "properties": {
    "iso:country":"US",
    "sg:address":"131 Newark Pompton Tpke",
    "sg:city":"Little Falls",
    "sg:classifiers":[
        {
            "category":"Bars & Pubs",
            "type":"Food & Drink"
        }
    ],
    "sg:phone":"+1   ",
    "sg:postcode":"07424",
    "sg:province":"NJ",
    "sg:tags":[
        "tavern"
    ],
    "wof:name":"Mahoneys",
    "wof:placetype":"venue"
},
  "geometry": {"coordinates":[-74.244146,40.883624],"type":"Point"}
}