{
  "type": "Feature",
  "properties": {
    "iso:country":"US",
    "sg:address":"160 Greene St",
    "sg:city":"Jersey City",
    "sg:classifiers":[
        {
            "category":"Professional",
            "type":"Services"
        }
    ],
    "sg:phone":"+1   ",
    "sg:postcode":"07302",
    "sg:province":"NJ",
    "wof:name":"Porto Leggore",
    "wof:placetype":"venue"
},
  "geometry": {"coordinates":[-74.034784,40.720579],"type":"Point"}
}