{
  "type": "Feature",
  "properties": {
    "addr:full":"45 Coles St Jersey City NJ 07302",
    "addr:housenumber":"45",
    "addr:postcode":"07302",
    "addr:street":"Coles St",
    "iso:country":"US",
    "sg:address":"45 Coles St",
    "sg:city":"Jersey City",
    "sg:classifiers":[
        {
            "category":"Restaurant",
            "type":"Food & Drink"
        }
    ],
    "sg:phone":"+1 201 222 9544",
    "sg:postcode":"07302",
    "sg:province":"NJ",
    "sg:tags":[
        "eating"
    ],
    "wof:name":"Yuly's Place",
    "wof:placetype":"venue"
},
  "geometry": {"coordinates":[-74.04758,40.723104],"type":"Point"}
}