{
  "type": "Feature",
  "properties": {
    "iso:country":"US",
    "sg:address":"1 Baltic St",
    "sg:city":"Edison",
    "sg:classifiers":[
        {
            "category":"Education",
            "subcategory":"Special Training",
            "type":"Public Place"
        }
    ],
    "sg:phone":"+1 732 494 3434",
    "sg:postcode":"08820",
    "sg:province":"NJ",
    "sg:tags":[
        "instruction",
        "driving"
    ],
    "wof:name":"Ace & Bharat Driving School",
    "wof:placetype":"venue"
},
  "geometry": {"coordinates":[-74.35785,40.571168],"type":"Point"}
}