{
  "type": "Feature",
  "properties": {
    "iso:country":"US",
    "sg:address":"276 Willow Ave",
    "sg:city":"Lyndhurst",
    "sg:classifiers":[
        {
            "category":"Real Estate",
            "subcategory":"Real Estate Agent",
            "type":"Services"
        }
    ],
    "sg:phone":"+1 201 933 2232",
    "sg:postcode":"07071",
    "sg:province":"NJ",
    "wof:name":"Cross Country Realtors",
    "wof:placetype":"venue"
},
  "geometry": {"coordinates":[-74.128636,40.815011],"type":"Point"}
}