{
  "type": "Feature",
  "properties": {
    "addr:full":"77 Tuttle Rd Watchung NJ 07069",
    "addr:housenumber":"77",
    "addr:postcode":"07069",
    "addr:street":"Tuttle Rd",
    "iso:country":"US",
    "sg:address":"77 Tuttle Rd",
    "sg:city":"Watchung",
    "sg:classifiers":[
        {
            "category":"Wholesale",
            "subcategory":"Durable Goods & Equipment",
            "type":"Manufacturing & Wholesale Goods"
        }
    ],
    "sg:phone":"+1 908 757 8798",
    "sg:postcode":"07069",
    "sg:province":"NJ",
    "wof:name":"J & J Industrial Supply",
    "wof:placetype":"venue"
},
  "geometry": {"coordinates":[-74.428636,40.655057],"type":"Point"}
}