{
  "type": "Feature",
  "properties": {
    "iso:country":"US",
    "sg:address":"59 Flaming Arrow Rd",
    "sg:city":"Mahwah",
    "sg:classifiers":[
        {
            "category":"Wholesale",
            "subcategory":"Durable Goods & Equipment",
            "type":"Manufacturing & Wholesale Goods"
        }
    ],
    "sg:phone":"+1 201 828 9492",
    "sg:postcode":"07430",
    "sg:province":"NJ",
    "sg:tags":[
        "representative",
        "manufacturer"
    ],
    "wof:name":"K Iv Enterprises",
    "wof:placetype":"venue"
},
  "geometry": {"coordinates":[-74.136329,41.096975],"type":"Point"}
}