{
  "type": "Feature",
  "properties": {
    "iso:country":"US",
    "sg:address":"493 Cherry St",
    "sg:city":"Franklin Lakes",
    "sg:classifiers":[
        {
            "category":"Personal",
            "type":"Services"
        }
    ],
    "sg:phone":"+1 201 891 4725",
    "sg:postcode":"07417",
    "sg:province":"NJ",
    "sg:tags":[
        "custom"
    ],
    "wof:name":"Branding Time",
    "wof:placetype":"venue"
},
  "geometry": {"coordinates":[-74.20127599999999,41.019271],"type":"Point"}
}