{
  "type": "Feature",
  "properties": {
    "iso:country":"US",
    "sg:address":"6 Tucker Dr",
    "sg:city":"Neptune",
    "sg:classifiers":[
        {
            "category":"Shopping",
            "type":"Retail Goods"
        }
    ],
    "sg:phone":"+1   ",
    "sg:postcode":"07753",
    "sg:province":"NJ",
    "sg:tags":[
        "merchandise"
    ],
    "wof:name":"F Stop Shop",
    "wof:placetype":"venue"
},
  "geometry": {"coordinates":[-74.036199,40.200278],"type":"Point"}
}