{
  "type": "Feature",
  "properties": {
    "iso:country":"US",
    "sg:address":"34 Langon Hollow Rd",
    "sg:city":"Bridgewater",
    "sg:classifiers":[
        {
            "category":"Professional",
            "subcategory":"Computer Services",
            "type":"Services"
        }
    ],
    "sg:phone":"+1   ",
    "sg:postcode":"08807",
    "sg:province":"NJ",
    "sg:tags":[
        "outsource",
        "it"
    ],
    "wof:name":"Partner Resource LLC",
    "wof:placetype":"venue"
},
  "geometry": {"coordinates":[-74.660849,40.586987],"type":"Point"}
}