{
  "type": "Feature",
  "properties": {
    "addr:full":"211 Cox Ave Tuckerton NJ 08087",
    "addr:housenumber":"211",
    "addr:postcode":"08087",
    "addr:street":"Cox Ave",
    "iso:country":"US",
    "sg:address":"211 Cox Ave",
    "sg:city":"Tuckerton",
    "sg:classifiers":[
        {
            "category":"Manufacturing",
            "subcategory":"Textiles",
            "type":"Manufacturing & Wholesale Goods"
        }
    ],
    "sg:phone":"+1 609 296 0856",
    "sg:postcode":"08087",
    "sg:province":"NJ",
    "sg:tags":[
        "mill",
        "cotton",
        "fabric",
        "mfg"
    ],
    "wof:name":"North Bay Canvas",
    "wof:placetype":"venue"
},
  "geometry": {"coordinates":[-74.334599,39.596433],"type":"Point"}
}