{
  "type": "Feature",
  "properties": {
    "iso:country":"US",
    "sg:address":"45 Ocean Dr W",
    "sg:city":"Brigantine",
    "sg:classifiers":[
        {
            "category":"Shopping",
            "subcategory":"Clothing, Apparel, & Fashions",
            "type":"Retail Goods"
        }
    ],
    "sg:phone":"+1 609 264 0957",
    "sg:postcode":"08203",
    "sg:province":"NJ",
    "wof:name":"King Of Jeans",
    "wof:placetype":"venue"
},
  "geometry": {"coordinates":[-74.40783,39.378229],"type":"Point"}
}