{
  "type": "Feature",
  "properties": {
    "iso:country":"US",
    "sg:address":"95 Beekman Ln",
    "sg:city":"Somerville",
    "sg:classifiers":[
        {
            "category":"Building & Trades",
            "subcategory":"Cleaning & Sanitation",
            "type":"Services"
        }
    ],
    "sg:phone":"+1   ",
    "sg:postcode":"08844",
    "sg:province":"NJ",
    "sg:tags":[
        "maintenance"
    ],
    "wof:name":"Jam Cleaning Services",
    "wof:placetype":"venue"
},
  "geometry": {"coordinates":[-74.669928,40.537574],"type":"Point"}
}