{
  "type": "Feature",
  "properties": {
    "addr:full":"87 County Rd Cliffwood NJ 07721",
    "addr:housenumber":"87",
    "addr:postcode":"07721",
    "addr:street":"County Rd",
    "iso:country":"US",
    "sg:address":"87 County Rd",
    "sg:city":"Cliffwood",
    "sg:classifiers":[
        {
            "category":"Professional",
            "type":"Services"
        }
    ],
    "sg:phone":"+1   ",
    "sg:postcode":"07721",
    "sg:province":"NJ",
    "wof:name":"Takata",
    "wof:placetype":"venue"
},
  "geometry": {"coordinates":[-74.244134,40.433097],"type":"Point"}
}