{
  "type": "Feature",
  "properties": {
    "iso:country":"US",
    "sg:address":"60 Prince St",
    "sg:city":"Elizabeth",
    "sg:classifiers":[
        {
            "category":"Health Services",
            "subcategory":"Clinic",
            "type":"Services"
        },
        {
            "category":"Health Services",
            "subcategory":"Hospital",
            "type":"Services"
        }
    ],
    "sg:phone":"+1 908 352 7830",
    "sg:postcode":"07208",
    "sg:province":"NJ",
    "sg:tags":[
        "mental",
        "outpatient",
        "specialty"
    ],
    "wof:name":"Spirit of Dawn",
    "wof:placetype":"venue"
},
  "geometry": {"coordinates":[-74.218598,40.671449],"type":"Point"}
}