{
  "type": "Feature",
  "properties": {
    "addr:full":"5 New Turkey Island Rd Monmouth Junction NJ 08852",
    "addr:housenumber":"5",
    "addr:postcode":"08852",
    "addr:street":"New Turkey Island Rd",
    "iso:country":"US",
    "sg:address":"5 New Turkey Island Rd",
    "sg:city":"Monmouth Junction",
    "sg:classifiers":[
        {
            "category":"Wholesale",
            "subcategory":"Petroleum",
            "type":"Manufacturing & Wholesale Goods"
        }
    ],
    "sg:phone":"+1 732 438 6777",
    "sg:postcode":"08852",
    "sg:province":"NJ",
    "sg:tags":[
        "product"
    ],
    "wof:name":"Chemoil Corporation",
    "wof:placetype":"venue"
},
  "geometry": {"coordinates":[-74.57254,40.36343],"type":"Point"}
}