{
  "type": "Feature",
  "properties": {
    "iso:country":"US",
    "sg:address":"64 Canal St",
    "sg:city":"South Bound Brook",
    "sg:classifiers":[
        {
            "category":"Freight",
            "type":"Transportation"
        }
    ],
    "sg:phone":"+1 732 469 0120",
    "sg:postcode":"08880",
    "sg:province":"NJ",
    "sg:tags":[
        "operator",
        "trucking"
    ],
    "wof:name":"J Burke Trucking",
    "wof:placetype":"venue"
},
  "geometry": {"coordinates":[-74.521475,40.553084],"type":"Point"}
}