{
  "type": "Feature",
  "properties": {
    "iso:country":"US",
    "sg:address":"186 Main St",
    "sg:city":"Chatham",
    "sg:classifiers":[
        {
            "category":"Professional",
            "subcategory":"Lawyer & Legal Services",
            "type":"Services"
        }
    ],
    "sg:phone":"+1 973 635 1141",
    "sg:postcode":"07928",
    "sg:province":"NJ",
    "sg:tags":[
        "attorney"
    ],
    "wof:name":"Barnes & Barnes",
    "wof:placetype":"venue"
},
  "geometry": {"coordinates":[-74.379997,40.740002],"type":"Point"}
}