{
  "type": "Feature",
  "properties": {
    "iso:country":"US",
    "sg:address":"1719 State Rte 27",
    "sg:city":"Somerset",
    "sg:classifiers":[
        {
            "category":"Retail",
            "subcategory":"Laundry & Dry Cleaning",
            "type":"Services"
        }
    ],
    "sg:phone":"+1 732 745 7744",
    "sg:postcode":"08873",
    "sg:province":"NJ",
    "sg:tags":[
        "cleaners"
    ],
    "wof:name":"Hempstead Dry Cleaners Inc",
    "wof:placetype":"venue"
},
  "geometry": {"coordinates":[-74.512207,40.456952],"type":"Point"}
}