{
  "type": "Feature",
  "properties": {
    "iso:country":"US",
    "sg:address":"256 Mercer St",
    "sg:city":"Stirling",
    "sg:classifiers":[
        {
            "category":"Manufacturing",
            "subcategory":"Printing",
            "type":"Manufacturing & Wholesale Goods"
        }
    ],
    "sg:phone":"+1 908 647 0412",
    "sg:postcode":"07980",
    "sg:province":"NJ",
    "sg:tags":[
        "newspaper"
    ],
    "wof:name":"Echoes-Sentinel",
    "wof:placetype":"venue"
},
  "geometry": {"coordinates":[-74.49406999999999,40.669061],"type":"Point"}
}