{
  "type": "Feature",
  "properties": {
    "addr:full":"971 Memorial Pkwy Phillipsburg NJ 08865",
    "addr:housenumber":"971",
    "addr:postcode":"08865",
    "addr:street":"Memorial Pkwy",
    "iso:country":"US",
    "sg:address":"971 Memorial Pkwy",
    "sg:city":"Phillipsburg",
    "sg:classifiers":[
        {
            "category":"Food & Beverages",
            "subcategory":"Liquor & Beverages",
            "type":"Retail Goods"
        }
    ],
    "sg:phone":"+1   ",
    "sg:postcode":"08865",
    "sg:province":"NJ",
    "sg:tags":[
        "eating",
        "alcoholic"
    ],
    "wof:name":"Parkway Liquor and Deli",
    "wof:placetype":"venue"
},
  "geometry": {"coordinates":[-75.16763,40.698608],"type":"Point"}
}