{
  "type": "Feature",
  "properties": {
    "iso:country":"US",
    "sg:address":"330 New Brunswick Ave",
    "sg:city":"Fords",
    "sg:classifiers":[
        {
            "category":"Professional",
            "subcategory":"Computer Services",
            "type":"Services"
        }
    ],
    "sg:phone":"+1   ",
    "sg:postcode":"08863",
    "sg:province":"NJ",
    "sg:tags":[
        "programming",
        "m",
        "related",
        "custom"
    ],
    "wof:name":"DATAMATICS",
    "wof:placetype":"venue"
},
  "geometry": {"coordinates":[-74.30344700000001,40.525911],"type":"Point"}
}