{
  "type": "Feature",
  "properties": {
    "addr:full":"416 38th St Union City NJ 07087",
    "addr:housenumber":"416",
    "addr:postcode":"07087",
    "addr:street":"38Th St",
    "iso:country":"US",
    "sg:address":"416 38th St",
    "sg:city":"Union City",
    "sg:classifiers":[
        {
            "category":"Personal",
            "subcategory":"Beauty Salon",
            "type":"Services"
        }
    ],
    "sg:phone":"+1 201 863 1333",
    "sg:postcode":"07087",
    "sg:province":"NJ",
    "sg:tags":[
        "shop",
        "barber"
    ],
    "wof:name":"Dominic Lanni Hair Stylist",
    "wof:placetype":"venue"
},
  "geometry": {"coordinates":[-74.02619900000001,40.775101],"type":"Point"}
}