{
  "type": "Feature",
  "properties": {
    "addr:full":"331 Stokes Ave Trenton NJ 08638",
    "addr:housenumber":"331",
    "addr:postcode":"08638",
    "addr:street":"Stokes Ave",
    "iso:country":"US",
    "sg:address":"331 Stokes Ave",
    "sg:city":"Trenton",
    "sg:classifiers":[
        {
            "category":"Building & Trades",
            "subcategory":"Plumbing",
            "type":"Services"
        }
    ],
    "sg:phone":"+1 609 882 2102",
    "sg:postcode":"08638",
    "sg:province":"NJ",
    "sg:tags":[
        "heating",
        "contractor"
    ],
    "wof:name":"Home Comfort Systems",
    "wof:placetype":"venue"
},
  "geometry": {"coordinates":[-74.76461500000001,40.241428],"type":"Point"}
}