{
  "type": "Feature",
  "properties": {
    "addr:full":"2500 Hooper Ave Brick NJ 08723",
    "addr:housenumber":"2500",
    "addr:postcode":"08723",
    "addr:street":"Hooper Ave",
    "iso:country":"US",
    "sg:address":"2500 Hooper Ave",
    "sg:city":"Brick",
    "sg:classifiers":[
        {
            "category":"Manufacturing",
            "subcategory":"Signs",
            "type":"Manufacturing & Wholesale Goods"
        }
    ],
    "sg:phone":"+1 732 920 7551",
    "sg:postcode":"08723",
    "sg:province":"NJ",
    "sg:tags":[
        "body",
        "auto",
        "specialty",
        "mfg"
    ],
    "wof:name":"Dang Signs",
    "wof:placetype":"venue"
},
  "geometry": {"coordinates":[-74.129974,40.041993],"type":"Point"}
}