{
  "type": "Feature",
  "properties": {
    "iso:country":"US",
    "sg:address":"416 Clinton Ave",
    "sg:city":"Plainfield",
    "sg:classifiers":[
        {
            "category":"Organizations",
            "subcategory":"Religious Organization",
            "type":"Services"
        }
    ],
    "sg:phone":"+1 908 668 8111",
    "sg:postcode":"07063",
    "sg:province":"NJ",
    "sg:tags":[
        "church"
    ],
    "wof:name":"God's Assembly In Christ",
    "wof:placetype":"venue"
},
  "geometry": {"coordinates":[-74.440157,40.598594],"type":"Point"}
}