{
  "type": "Feature",
  "properties": {
    "iso:country":"US",
    "sg:address":"315 S Orange Ave",
    "sg:city":"South Orange",
    "sg:classifiers":[
        {
            "category":"Health Services",
            "subcategory":"Hospital",
            "type":"Services"
        }
    ],
    "sg:phone":"+1 973 763 7979",
    "sg:postcode":"07079",
    "sg:province":"NJ",
    "sg:tags":[
        "mental"
    ],
    "wof:name":"Village",
    "wof:placetype":"venue"
},
  "geometry": {"coordinates":[-74.24969900000001,40.744826],"type":"Point"}
}