{
  "type": "Feature",
  "properties": {
    "addr:full":"32 Red Bank Dr Sicklerville NJ 08081",
    "addr:housenumber":"32",
    "addr:postcode":"08081",
    "addr:street":"Red Bank Dr",
    "iso:country":"US",
    "sg:address":"32 Red Bank Dr",
    "sg:city":"Sicklerville",
    "sg:classifiers":[
        {
            "category":"Professional",
            "type":"Services"
        }
    ],
    "sg:phone":"+1   ",
    "sg:postcode":"08081",
    "sg:province":"NJ",
    "wof:name":"Country Cupboard",
    "wof:placetype":"venue"
},
  "geometry": {"coordinates":[-75.03816500000001,39.768713],"type":"Point"}
}