{
  "type": "Feature",
  "properties": {
    "iso:country":"US",
    "sg:address":"2 Changebridge Rd",
    "sg:city":"Montville",
    "sg:classifiers":[
        {
            "category":"Recreation",
            "type":"Entertainment"
        }
    ],
    "sg:phone":"+1 973 316 2507",
    "sg:postcode":"07045",
    "sg:province":"NJ",
    "sg:tags":[
        "instruction",
        "gymnastic"
    ],
    "wof:name":"North Stars Gymnastics Academy",
    "wof:placetype":"venue"
},
  "geometry": {"coordinates":[-74.36233799999999,40.915265],"type":"Point"}
}