{
  "type": "Feature",
  "properties": {
    "addr:full":"600 Laurel Oak Rd Voorhees NJ 08043",
    "addr:housenumber":"600",
    "addr:postcode":"08043",
    "addr:street":"Laurel Oak Rd",
    "iso:country":"US",
    "sg:address":"600 Laurel Oak Rd",
    "sg:city":"Voorhees",
    "sg:classifiers":[
        {
            "category":"Professional",
            "subcategory":"Advertising",
            "type":"Services"
        }
    ],
    "sg:phone":"+1   ",
    "sg:postcode":"08043",
    "sg:province":"NJ",
    "wof:name":"Strategic Distribution",
    "wof:placetype":"venue"
},
  "geometry": {"coordinates":[-74.98527199999999,39.845289],"type":"Point"}
}