{
  "type": "Feature",
  "properties": {
    "addr:full":"944 Garfield Ave Jersey City NJ 07304",
    "addr:housenumber":"944",
    "addr:postcode":"07304",
    "addr:street":"Garfield Ave",
    "iso:country":"US",
    "sg:address":"944 Garfield Ave",
    "sg:city":"Jersey City",
    "sg:classifiers":[
        {
            "category":"Wholesale",
            "subcategory":"Scrap",
            "type":"Manufacturing & Wholesale Goods"
        }
    ],
    "sg:phone":"+1 201 333 4800",
    "sg:postcode":"07304",
    "sg:province":"NJ",
    "sg:tags":[
        "material"
    ],
    "wof:name":"Tri Auto Center",
    "wof:placetype":"venue"
},
  "geometry": {"coordinates":[-74.068884,40.712117],"type":"Point"}
}