{
  "type": "Feature",
  "properties": {
    "iso:country":"US",
    "sg:address":"404 N Dudley St",
    "sg:city":"Camden",
    "sg:classifiers":[
        {
            "category":"Real Estate",
            "subcategory":"Real Estate Operator",
            "type":"Services"
        }
    ],
    "sg:phone":"+1 856 969 9050",
    "sg:postcode":"08105",
    "sg:province":"NJ",
    "sg:tags":[
        "apartment"
    ],
    "wof:name":"Pennrose Baldwin Run 8",
    "wof:placetype":"venue"
},
  "geometry": {"coordinates":[-75.083168,39.95224],"type":"Point"}
}