{
  "type": "Feature",
  "properties": {
    "iso:country":"US",
    "sg:address":"16 Brookvale Rd",
    "sg:city":"Butler",
    "sg:classifiers":[
        {
            "category":"Retail",
            "subcategory":"Repair Shop",
            "type":"Services"
        }
    ],
    "sg:phone":"+1 973 263 0730",
    "sg:postcode":"07405",
    "sg:province":"NJ",
    "wof:name":"Big K Supply & Tool Service",
    "wof:placetype":"venue"
},
  "geometry": {"coordinates":[-74.399787,41.009119],"type":"Point"}
}