{
  "type": "Feature",
  "properties": {
    "iso:country":"US",
    "sg:address":"Preaness Shopping Ct",
    "sg:city":"Wayne",
    "sg:classifiers":[
        {
            "category":"Shopping",
            "subcategory":"Mobile Phones",
            "type":"Retail Goods"
        }
    ],
    "sg:phone":"+1 973 633 7373",
    "sg:postcode":"07470",
    "sg:province":"NJ",
    "wof:name":"At & T Wireless",
    "wof:placetype":"venue"
},
  "geometry": {"coordinates":[-74.2388,40.9487],"type":"Point"}
}