{
  "type": "Feature",
  "properties": {
    "addr:full":"3 Werner Way Ste 300 Lebanon NJ 08833",
    "addr:housenumber":"3",
    "addr:postcode":"08833",
    "addr:street":"Werner Way Ste 300",
    "iso:country":"US",
    "sg:address":"3 Werner Way Ste 300",
    "sg:city":"Lebanon",
    "sg:classifiers":[
        {
            "category":"Health Services",
            "subcategory":"Health Practitioner",
            "type":"Services"
        }
    ],
    "sg:phone":"+1 908 849 4830",
    "sg:postcode":"08833",
    "sg:province":"NJ",
    "sg:tags":[
        "therapy",
        "physical"
    ],
    "wof:name":"Providence Therapy Services",
    "wof:placetype":"venue"
},
  "geometry": {"coordinates":[-74.84293700000001,40.645763],"type":"Point"}
}