{
  "type": "Feature",
  "properties": {
    "addr:full":"6214 Monroe Pl West New York NJ 07093",
    "addr:housenumber":"6214",
    "addr:postcode":"07093",
    "addr:street":"Monroe Pl West",
    "iso:country":"US",
    "sg:address":"6214 Monroe Pl",
    "sg:city":"West New York",
    "sg:classifiers":[
        {
            "category":"Wholesale",
            "subcategory":"Apparel",
            "type":"Manufacturing & Wholesale Goods"
        }
    ],
    "sg:phone":"+1 201 453 1000",
    "sg:postcode":"07093",
    "sg:province":"NJ",
    "sg:tags":[
        "thread"
    ],
    "wof:name":"Pan America Thread & Inc",
    "wof:placetype":"venue"
},
  "geometry": {"coordinates":[-74.010976,40.790272],"type":"Point"}
}