{
  "type": "Feature",
  "properties": {
    "iso:country":"US",
    "sg:address":"434 Liberty Ln",
    "sg:city":"Marlton",
    "sg:classifiers":[
        {
            "category":"Building & Trades",
            "subcategory":"Cleaning & Sanitation",
            "type":"Services"
        }
    ],
    "sg:phone":"+1 856 985 7969",
    "sg:postcode":"08053",
    "sg:province":"NJ",
    "sg:tags":[
        "janitor"
    ],
    "wof:name":"Crystal Clean Cans",
    "wof:placetype":"venue"
},
  "geometry": {"coordinates":[-74.900735,39.916211],"type":"Point"}
}