{
  "type": "Feature",
  "properties": {
    "iso:country":"US",
    "sg:address":"67 Wyandemere Dr",
    "sg:city":"Woodcliff Lake",
    "sg:classifiers":[
        {
            "category":"Professional",
            "subcategory":"Management & Consulting",
            "type":"Services"
        }
    ],
    "sg:phone":"+1   ",
    "sg:postcode":"07677",
    "sg:province":"NJ",
    "wof:name":"David Rifkin",
    "wof:placetype":"venue"
},
  "geometry": {"coordinates":[-74.065825,41.03743],"type":"Point"}
}