{
  "type": "Feature",
  "properties": {
    "iso:country":"US",
    "sg:address":"54 Hollywood Ave",
    "sg:city":"Somerset",
    "sg:classifiers":[
        {
            "category":"Government",
            "subcategory":"Office",
            "type":"Public Place"
        }
    ],
    "sg:phone":"+1 732 828 9390",
    "sg:postcode":"08873",
    "sg:province":"NJ",
    "sg:tags":[
        "broadcast",
        "stat",
        "conservation",
        "radio"
    ],
    "wof:name":"Colonial Waterbird Group",
    "wof:placetype":"venue"
},
  "geometry": {"coordinates":[-74.50005299999999,40.524677],"type":"Point"}
}