{
  "type": "Feature",
  "properties": {
    "addr:full":"27 Ocean Ave Jersey City NJ 07305",
    "addr:housenumber":"27",
    "addr:postcode":"07305",
    "addr:street":"Ocean Ave",
    "iso:country":"US",
    "sg:address":"27 Ocean Ave",
    "sg:city":"Jersey City",
    "sg:classifiers":[
        {
            "category":"Wholesale",
            "subcategory":"Machinery & Supplies",
            "type":"Manufacturing & Wholesale Goods"
        }
    ],
    "sg:phone":"+1 201 435 2000",
    "sg:postcode":"07305",
    "sg:province":"NJ",
    "sg:tags":[
        "engine"
    ],
    "wof:name":"Diesel Distributors Co",
    "wof:placetype":"venue"
},
  "geometry": {"coordinates":[-74.09704000000001,40.690296],"type":"Point"}
}