{
  "type": "Feature",
  "properties": {
    "iso:country":"US",
    "sg:address":"8 Lougheed Ave",
    "sg:city":"Caldwell",
    "sg:classifiers":[
        {
            "category":"Building & Trades",
            "subcategory":"Construction",
            "type":"Services"
        }
    ],
    "sg:phone":"+1 973 228 1624",
    "sg:postcode":"07006",
    "sg:province":"NJ",
    "sg:tags":[
        "house"
    ],
    "wof:name":"Allam Construction Inc",
    "wof:placetype":"venue"
},
  "geometry": {"coordinates":[-74.289743,40.845959],"type":"Point"}
}