{
  "type": "Feature",
  "properties": {
    "addr:full":"511 3rd St Belvidere NJ 07823",
    "addr:housenumber":"511",
    "addr:postcode":"07823",
    "addr:street":"3Rd St",
    "iso:country":"US",
    "sg:address":"511 3rd St",
    "sg:city":"Belvidere",
    "sg:classifiers":[
        {
            "category":"Freight",
            "type":"Transportation"
        }
    ],
    "sg:phone":"+1 908 475 4996",
    "sg:postcode":"07823",
    "sg:province":"NJ",
    "sg:tags":[
        "operator",
        "local",
        "trucking"
    ],
    "wof:name":"Camel Piano Moving Co",
    "wof:placetype":"venue"
},
  "geometry": {"coordinates":[-75.075058,40.826157],"type":"Point"}
}