{
  "type": "Feature",
  "properties": {
    "addr:full":"583 Industrial Rd Carlstadt NJ 07072",
    "addr:housenumber":"583",
    "addr:postcode":"07072",
    "addr:street":"Industrial Rd",
    "iso:country":"US",
    "sg:address":"583 Industrial Rd",
    "sg:city":"Carlstadt",
    "sg:classifiers":[
        {
            "category":"Freight",
            "type":"Transportation"
        }
    ],
    "sg:phone":"+1 201 933 9999",
    "sg:postcode":"07072",
    "sg:province":"NJ",
    "sg:tags":[
        "petroleum"
    ],
    "wof:name":"Prospect Transportation Inc",
    "wof:placetype":"venue"
},
  "geometry": {"coordinates":[-74.099962,40.84464],"type":"Point"}
}