{
  "type": "Feature",
  "properties": {
    "iso:country":"US",
    "sg:address":"181 Millburn Ave",
    "sg:city":"Millburn",
    "sg:classifiers":[
        {
            "category":"Professional",
            "subcategory":"Employment Agencies",
            "type":"Services"
        }
    ],
    "sg:phone":"+1 973 379 4020",
    "sg:postcode":"07041",
    "sg:province":"NJ",
    "sg:tags":[
        "executive",
        "placement",
        "help",
        "contractor"
    ],
    "sg:website":"www.mrishorthills.com",
    "wof:name":"Management Recruiters Intl",
    "wof:placetype":"venue"
},
  "geometry": {"coordinates":[-74.294203,40.722095],"type":"Point"}
}