{
  "type": "Feature",
  "properties": {
    "iso:country":"US",
    "sg:address":"814 Green Ave",
    "sg:city":"Mount Ephraim",
    "sg:classifiers":[
        {
            "category":"Building & Trades",
            "subcategory":"Construction",
            "type":"Services"
        }
    ],
    "sg:phone":"+1 856 933 4520",
    "sg:postcode":"08059",
    "sg:province":"NJ",
    "sg:tags":[
        "carpentry",
        "contractor"
    ],
    "wof:name":"Miremax Carpentry",
    "wof:placetype":"venue"
},
  "geometry": {"coordinates":[-75.09813800000001,39.882513],"type":"Point"}
}