{
  "type": "Feature",
  "properties": {
    "addr:full":"210 Main St Fort Lee NJ 07024",
    "addr:housenumber":"210",
    "addr:postcode":"07024",
    "addr:street":"Main St",
    "iso:country":"US",
    "sg:address":"210 Main St",
    "sg:city":"Fort Lee",
    "sg:classifiers":[
        {
            "category":"Restaurant",
            "type":"Food & Drink"
        }
    ],
    "sg:phone":"+1 201 585 7979",
    "sg:postcode":"07024",
    "sg:province":"NJ",
    "sg:tags":[
        "eating",
        "pizza"
    ],
    "sg:website":"www.baggiospizza.com",
    "wof:name":"Baggios Restaurant & Pizzeria",
    "wof:placetype":"venue"
},
  "geometry": {"coordinates":[-73.97067800000001,40.851025],"type":"Point"}
}