{
  "type": "Feature",
  "properties": {
    "iso:country":"US",
    "sg:address":"200 Stratford Dr",
    "sg:city":"Nutley",
    "sg:classifiers":[
        {
            "category":"Professional",
            "subcategory":"Business Services",
            "type":"Services"
        }
    ],
    "sg:phone":"+1   ",
    "sg:postcode":"07110",
    "sg:province":"NJ",
    "sg:tags":[
        "computer",
        "related"
    ],
    "wof:name":"EZ Solution 4u Corp",
    "wof:placetype":"venue"
},
  "geometry": {"coordinates":[-74.137311,40.821419],"type":"Point"}
}