{
  "type": "Feature",
  "properties": {
    "addr:full":"410 Ogden Ave Jersey City NJ 07307",
    "addr:housenumber":"410",
    "addr:postcode":"07307",
    "addr:street":"Ogden Ave",
    "iso:country":"US",
    "sg:address":"410 Ogden Ave",
    "sg:city":"Jersey City",
    "sg:classifiers":[
        {
            "category":"Building & Trades",
            "subcategory":"Construction",
            "type":"Services"
        }
    ],
    "sg:phone":"+1 201 420 5050",
    "sg:postcode":"07307",
    "sg:province":"NJ",
    "sg:tags":[
        "nonresidential",
        "general",
        "contractor"
    ],
    "wof:name":"Callico Construction Corp",
    "wof:placetype":"venue"
},
  "geometry": {"coordinates":[-74.04140599999999,40.746718],"type":"Point"}
}