{
  "type": "Feature",
  "properties": {
    "iso:country":"US",
    "sg:address":"5378 State Rte 49",
    "sg:city":"Millville",
    "sg:classifiers":[
        {
            "category":"Recreation",
            "type":"Entertainment"
        }
    ],
    "sg:phone":"+1 856 327 6365",
    "sg:postcode":"08332",
    "sg:province":"NJ",
    "sg:tags":[
        "paint",
        "ball",
        "sport"
    ],
    "sg:website":"www.countrypaintball.com",
    "wof:name":"Cumberland County Paintball",
    "wof:placetype":"venue"
},
  "geometry": {"coordinates":[-74.919482,39.357145],"type":"Point"}
}