{
  "type": "Feature",
  "properties": {
    "addr:full":"1617 Bergenline Ave Union City NJ 07087",
    "addr:housenumber":"1617",
    "addr:postcode":"07087",
    "addr:street":"Bergenline Ave",
    "iso:country":"US",
    "sg:address":"1617 Bergenline Ave",
    "sg:city":"Union City",
    "sg:classifiers":[
        {
            "category":"Building & Trades",
            "subcategory":"Construction",
            "type":"Services"
        }
    ],
    "sg:phone":"+1 201 330 8894",
    "sg:postcode":"07087",
    "sg:province":"NJ",
    "sg:tags":[
        "contractor"
    ],
    "wof:name":"Rocha Construction Inc",
    "wof:placetype":"venue"
},
  "geometry": {"coordinates":[-74.035988,40.762502],"type":"Point"}
}