{
  "type": "Feature",
  "properties": {
    "iso:country":"US",
    "sg:address":"900 Sylvan Ave",
    "sg:city":"Englewood Cliffs",
    "sg:classifiers":[
        {
            "category":"Communications",
            "subcategory":"Television Station",
            "type":"Services"
        }
    ],
    "sg:phone":"+1 201 735 5151",
    "sg:postcode":"07632",
    "sg:province":"NJ",
    "sg:tags":[
        "cable"
    ],
    "wof:name":"CNBC",
    "wof:placetype":"venue"
},
  "geometry": {"coordinates":[-73.938385,40.899763],"type":"Point"}
}