{
  "type": "Feature",
  "properties": {
    "addr:full":"110 White Horse Pike Oaklyn NJ 08107",
    "addr:housenumber":"110",
    "addr:postcode":"08107",
    "addr:street":"White Horse Pike",
    "iso:country":"US",
    "sg:address":"110 White Horse Pike",
    "sg:city":"Oaklyn",
    "sg:classifiers":[
        {
            "category":"Restaurant",
            "type":"Food & Drink"
        }
    ],
    "sg:phone":"+1 856 854 9204",
    "sg:postcode":"08107",
    "sg:province":"NJ",
    "wof:name":"Time Out Sports Bar & Grill",
    "wof:placetype":"venue"
},
  "geometry": {"coordinates":[-75.0886,39.918301],"type":"Point"}
}