{
  "type": "Feature",
  "properties": {
    "addr:full":"1350 Asbury Ave Ocean City NJ 08226",
    "addr:housenumber":"1350",
    "addr:postcode":"08226",
    "addr:street":"Asbury Ave",
    "iso:country":"US",
    "sg:address":"1350 Asbury Ave",
    "sg:city":"Ocean City",
    "sg:classifiers":[
        {
            "category":"Retail",
            "subcategory":"Portrait Studio",
            "type":"Services"
        },
        {
            "category":"Retail",
            "subcategory":"Photofinishing",
            "type":"Services"
        }
    ],
    "sg:phone":"+1 609 398 4242",
    "sg:postcode":"08226",
    "sg:province":"NJ",
    "sg:tags":[
        "laboratory",
        "photo",
        "finishing",
        "photographer"
    ],
    "wof:name":"Perfect Exposure The",
    "wof:placetype":"venue"
},
  "geometry": {"coordinates":[-74.582984,39.2741],"type":"Point"}
}