{
  "type": "Feature",
  "properties": {
    "iso:country":"US",
    "sg:address":"4 Revere Rd",
    "sg:city":"Basking Ridge",
    "sg:classifiers":[
        {
            "category":"Professional",
            "subcategory":"Management & Consulting",
            "type":"Services"
        }
    ],
    "sg:phone":"+1   ",
    "sg:postcode":"07920",
    "sg:province":"NJ",
    "wof:name":"Siprian Consultants Inc",
    "wof:placetype":"venue"
},
  "geometry": {"coordinates":[-74.624516,40.651399],"type":"Point"}
}