{
  "type": "Feature",
  "properties": {
    "iso:country":"US",
    "sg:address":"2330 Marlton Pike W",
    "sg:city":"Cherry Hill",
    "sg:classifiers":[
        {
            "category":"Retail",
            "subcategory":"Auto Repair",
            "type":"Services"
        }
    ],
    "sg:phone":"+1 856 665 0320",
    "sg:postcode":"08002",
    "sg:province":"NJ",
    "sg:tags":[
        "body",
        "shop"
    ],
    "wof:name":"The Body Shop by Di Eva",
    "wof:placetype":"venue"
},
  "geometry": {"coordinates":[-75.049301,39.925598],"type":"Point"}
}