{
  "type": "Feature",
  "properties": {
    "addr:full":"10 E 21st St Bayonne NJ 07002",
    "addr:housenumber":"10",
    "addr:postcode":"07002",
    "addr:street":"E 21St St",
    "iso:country":"US",
    "sg:address":"10 E 21st St",
    "sg:city":"Bayonne",
    "sg:classifiers":[
        {
            "category":"Personal",
            "type":"Services"
        }
    ],
    "sg:phone":"+1 201 339 1790",
    "sg:postcode":"07002",
    "sg:province":"NJ",
    "sg:tags":[
        "sewing",
        "alteration"
    ],
    "wof:name":"Saint George Tailor",
    "wof:placetype":"venue"
},
  "geometry": {"coordinates":[-74.119125,40.661933],"type":"Point"}
}