{
  "type": "Feature",
  "properties": {
    "iso:country":"US",
    "sg:address":"800 New York Ave",
    "sg:city":"Union City",
    "sg:classifiers":[
        {
            "category":"Food & Beverages",
            "subcategory":"Groceries & Convenience Stores",
            "type":"Retail Goods"
        }
    ],
    "sg:phone":"+1 973 458 1809",
    "sg:postcode":"07087",
    "sg:province":"NJ",
    "wof:name":"La Esperanza Grocery Store",
    "wof:placetype":"venue"
},
  "geometry": {"coordinates":[-74.03769699999999,40.756802],"type":"Point"}
}