{
  "type": "Feature",
  "properties": {
    "iso:country":"US",
    "sg:address":"7312 Bergenline Ave",
    "sg:city":"North Bergen",
    "sg:classifiers":[
        {
            "category":"Health Services",
            "subcategory":"Doctor",
            "type":"Services"
        }
    ],
    "sg:phone":"+1 201 861 9422",
    "sg:postcode":"07047",
    "sg:province":"NJ",
    "wof:name":"Ricciardi Ralph E Jr MD",
    "wof:placetype":"venue"
},
  "geometry": {"coordinates":[-74.009102,40.798199],"type":"Point"}
}