{
  "type": "Feature",
  "properties": {
    "iso:country":"US",
    "sg:address":"2 Winant Ave",
    "sg:city":"Ridgefield Park",
    "sg:classifiers":[
        {
            "category":"Autos & Motor Vehicles",
            "subcategory":"Fuel & Gas Station",
            "type":"Retail Goods"
        }
    ],
    "sg:phone":"+1 201 641 5977",
    "sg:postcode":"07660",
    "sg:province":"NJ",
    "wof:name":"Marwah Projects Inc",
    "wof:placetype":"venue"
},
  "geometry": {"coordinates":[-74.025837,40.850385],"type":"Point"}
}