{
  "type": "Feature",
  "properties": {
    "iso:country":"US",
    "sg:address":"28 Chestnut Ridge Rd",
    "sg:city":"Montvale",
    "sg:classifiers":[
        {
            "category":"Autos & Motor Vehicles",
            "subcategory":"Fuel & Gas Station",
            "type":"Retail Goods"
        }
    ],
    "sg:phone":"+1 201 391 1236",
    "sg:postcode":"07645",
    "sg:province":"NJ",
    "sg:tags":[
        "oil"
    ],
    "wof:name":"Middle Ridge Exxon",
    "wof:placetype":"venue"
},
  "geometry": {"coordinates":[-74.069638,41.050699],"type":"Point"}
}