{
  "type": "Feature",
  "properties": {
    "addr:full":"1223 Blackwood Clementon Rd Clementon NJ 08021",
    "addr:housenumber":"1223",
    "addr:postcode":"08021",
    "addr:street":"Blackwood Clementon Rd",
    "iso:country":"US",
    "sg:address":"1223 Blackwood Clementon Rd",
    "sg:city":"Clementon",
    "sg:classifiers":[
        {
            "category":"Food & Beverages",
            "subcategory":"Bakery",
            "type":"Retail Goods"
        }
    ],
    "sg:phone":"+1 856 627 9355",
    "sg:postcode":"08021",
    "sg:province":"NJ",
    "sg:tags":[
        "doughnut"
    ],
    "wof:name":"Dunkin' Donuts",
    "wof:placetype":"venue"
},
  "geometry": {"coordinates":[-75.025471,39.80424],"type":"Point"}
}