{
  "type": "Feature",
  "properties": {
    "iso:country":"US",
    "sg:address":"7350 Maple Ave",
    "sg:city":"Merchantville",
    "sg:classifiers":[
        {
            "category":"Banks & Credit Unions",
            "subcategory":"Bank",
            "type":"Services"
        }
    ],
    "sg:phone":"+1 856 665 8000",
    "sg:postcode":"08109",
    "sg:province":"NJ",
    "sg:tags":[
        "national",
        "commercial"
    ],
    "wof:name":"Susquehanna Patriot Bank",
    "wof:placetype":"venue"
},
  "geometry": {"coordinates":[-75.032257,39.952119],"type":"Point"}
}