{
  "type": "Feature",
  "properties": {
    "iso:country":"US",
    "sg:address":"231 Bennington Rd",
    "sg:city":"Freehold",
    "sg:classifiers":[
        {
            "category":"Manufacturing",
            "subcategory":"Tools & Machinery",
            "type":"Manufacturing & Wholesale Goods"
        }
    ],
    "sg:phone":"+1 732 866 0017",
    "sg:postcode":"07728",
    "sg:province":"NJ",
    "sg:tags":[
        "mfg"
    ],
    "wof:name":"Twin City Fan Co",
    "wof:placetype":"venue"
},
  "geometry": {"coordinates":[-74.23944400000001,40.273963],"type":"Point"}
}