{
  "type": "Feature",
  "properties": {
    "addr:full":"135 Columbia Tpke Ste 201 Florham Park NJ 07932",
    "addr:housenumber":"135",
    "addr:postcode":"07932",
    "addr:street":"Columbia Tpke Ste 201",
    "iso:country":"US",
    "sg:address":"135 Columbia Tpke Ste 201",
    "sg:city":"Florham Park",
    "sg:classifiers":[
        {
            "category":"Health Services",
            "subcategory":"Doctor",
            "type":"Services"
        }
    ],
    "sg:phone":"+1 973 660 0430",
    "sg:postcode":"07932",
    "sg:province":"NJ",
    "sg:tags":[
        "psychiatrist"
    ],
    "wof:name":"Weisberg Lynne W MD PC",
    "wof:placetype":"venue"
},
  "geometry": {"coordinates":[-74.386398,40.786301],"type":"Point"}
}