{
  "type": "Feature",
  "properties": {
    "iso:country":"US",
    "sg:address":"1800 Chapel Ave W Ste 360",
    "sg:city":"Cherry Hill",
    "sg:classifiers":[
        {
            "category":"Professional",
            "subcategory":"Lawyer & Legal Services",
            "type":"Services"
        }
    ],
    "sg:phone":"+1 856 854 3636",
    "sg:postcode":"08002",
    "sg:province":"NJ",
    "sg:website":"www.litchfieldcavo.com",
    "wof:name":"Litchfield Cavo Llp",
    "wof:placetype":"venue"
},
  "geometry": {"coordinates":[-75.030776,39.934887],"type":"Point"}
}