{
  "type": "Feature",
  "properties": {
    "iso:country":"US",
    "sg:address":"1077 Elizabeth Ave",
    "sg:city":"Elizabeth",
    "sg:classifiers":[
        {
            "category":"Shopping",
            "subcategory":"Department Store",
            "type":"Retail Goods"
        }
    ],
    "sg:phone":"+1   ",
    "sg:postcode":"07201",
    "sg:province":"NJ",
    "wof:name":"My Ninety Nine Cent Paradise",
    "wof:placetype":"venue"
},
  "geometry": {"coordinates":[-74.209889,40.661372],"type":"Point"}
}