{
  "type": "Feature",
  "properties": {
    "iso:country":"US",
    "sg:address":"1250 State Rte 73",
    "sg:city":"Palmyra",
    "sg:classifiers":[
        {
            "category":"Autos & Motor Vehicles",
            "subcategory":"Automobile Sales",
            "type":"Retail Goods"
        }
    ],
    "sg:phone":"+1 856 303 2400",
    "sg:postcode":"08065",
    "sg:province":"NJ",
    "sg:tags":[
        "car",
        "dealer"
    ],
    "wof:name":"Good Carma Auto Group",
    "wof:placetype":"venue"
},
  "geometry": {"coordinates":[-75.039329,40.007533],"type":"Point"}
}