{
  "type": "Feature",
  "properties": {
    "iso:country":"US",
    "sg:address":"24 Walnut Pl",
    "sg:city":"West Long Branch",
    "sg:classifiers":[
        {
            "category":"Social Services",
            "type":"Services"
        }
    ],
    "sg:phone":"+1 732 870 9500",
    "sg:postcode":"07764",
    "sg:province":"NJ",
    "sg:tags":[
        "worker"
    ],
    "wof:name":"Alexander La Salle",
    "wof:placetype":"venue"
},
  "geometry": {"coordinates":[-74.016598,40.296628],"type":"Point"}
}