{
  "type": "Feature",
  "properties": {
    "iso:country":"US",
    "sg:address":"460 Ludlow Ave",
    "sg:city":"Cranford",
    "sg:classifiers":[
        {
            "category":"Building & Trades",
            "subcategory":"Plumbing",
            "type":"Services"
        }
    ],
    "sg:phone":"+1 908 272 7510",
    "sg:postcode":"07016",
    "sg:province":"NJ",
    "sg:tags":[
        "air",
        "ventilation",
        "heating",
        "conditioning",
        "contractor"
    ],
    "sg:website":"www.ajceliano.com",
    "wof:name":"A J Celiano Inc",
    "wof:placetype":"venue"
},
  "geometry": {"coordinates":[-74.283382,40.652702],"type":"Point"}
}