{
  "type": "Feature",
  "properties": {
    "iso:country":"US",
    "sg:address":"20 Mount Vernon Rd",
    "sg:city":"Columbia",
    "sg:classifiers":[
        {
            "category":"Wholesale",
            "subcategory":"Home Furnishings",
            "type":"Manufacturing & Wholesale Goods"
        }
    ],
    "sg:phone":"+1 908 362 1101",
    "sg:postcode":"07832",
    "sg:province":"NJ",
    "sg:tags":[
        "glassware",
        "chinaware"
    ],
    "wof:name":"American Atlantic-Salhoff",
    "wof:placetype":"venue"
},
  "geometry": {"coordinates":[-75.010059,40.987017],"type":"Point"}
}