{
  "type": "Feature",
  "properties": {
    "addr:full":"160 Broadway Hillsdale NJ 07642",
    "addr:housenumber":"160",
    "addr:postcode":"07642",
    "addr:street":"Broadway",
    "iso:country":"US",
    "sg:address":"160 Broadway",
    "sg:city":"Hillsdale",
    "sg:classifiers":[
        {
            "category":"Retail",
            "subcategory":"Repair Shop",
            "type":"Services"
        }
    ],
    "sg:phone":"+1 201 328 0491",
    "sg:postcode":"07642",
    "sg:province":"NJ",
    "sg:tags":[
        "lock",
        "locksmith"
    ],
    "wof:name":"A 1 24 Hour A Emerg Locksmith",
    "wof:placetype":"venue"
},
  "geometry": {"coordinates":[-74.04101799999999,41.005576],"type":"Point"}
}