{
  "type": "Feature",
  "properties": {
    "iso:country":"US",
    "sg:address":"20 Bowling Green Pkwy",
    "sg:city":"Lake Hopatcong",
    "sg:classifiers":[
        {
            "category":"Home & Garden",
            "subcategory":"Hardware",
            "type":"Retail Goods"
        }
    ],
    "sg:phone":"+1   ",
    "sg:postcode":"07849",
    "sg:province":"NJ",
    "wof:name":"American Hardware Of Lakeside",
    "wof:placetype":"venue"
},
  "geometry": {"coordinates":[-74.598646,40.962065],"type":"Point"}
}