{
  "type": "Feature",
  "properties": {
    "addr:full":"68 Loyola Pl Oakland NJ 07436",
    "addr:housenumber":"68",
    "addr:postcode":"07436",
    "addr:street":"Loyola Pl",
    "iso:country":"US",
    "sg:address":"68 Loyola Pl",
    "sg:city":"Oakland",
    "sg:classifiers":[
        {
            "category":"Insurance",
            "subcategory":"Life Insurance",
            "type":"Services"
        }
    ],
    "sg:phone":"+1   ",
    "sg:postcode":"07436",
    "sg:province":"NJ",
    "sg:tags":[
        "carrier"
    ],
    "wof:name":"Northwestern Mutual Life",
    "wof:placetype":"venue"
},
  "geometry": {"coordinates":[-74.22736399999999,41.031251],"type":"Point"}
}