{
  "type": "Feature",
  "properties": {
    "addr:full":"1017 Boulevard E Weehawken NJ 07086",
    "addr:housenumber":"1017;e",
    "addr:postcode":"07086",
    "addr:street":"Boulevard",
    "iso:country":"US",
    "sg:address":"1017 Boulevard E",
    "sg:city":"Weehawken",
    "sg:classifiers":[
        {
            "category":"Organizations",
            "subcategory":"Community Association",
            "type":"Services"
        }
    ],
    "sg:phone":"+1 201 863 0296",
    "sg:postcode":"07086",
    "sg:province":"NJ",
    "sg:tags":[
        "military"
    ],
    "wof:name":"American Legion",
    "wof:placetype":"venue"
},
  "geometry": {"coordinates":[-74.012349,40.779015],"type":"Point"}
}