{
  "type": "Feature",
  "properties": {
    "addr:full":"91 Bernard Ave Edison NJ 08837",
    "addr:housenumber":"91",
    "addr:postcode":"08837",
    "addr:street":"Bernard Ave",
    "iso:country":"US",
    "sg:address":"91 Bernard Ave",
    "sg:city":"Edison",
    "sg:classifiers":[
        {
            "category":"Building & Trades",
            "subcategory":"Construction",
            "type":"Services"
        }
    ],
    "sg:phone":"+1 732 516 0055",
    "sg:postcode":"08837",
    "sg:province":"NJ",
    "sg:tags":[
        "house"
    ],
    "wof:name":"MJL Interiors",
    "wof:placetype":"venue"
},
  "geometry": {"coordinates":[-74.354839,40.522413],"type":"Point"}
}