{
  "type": "Feature",
  "properties": {
    "addr:full":"346 Main St Woodbridge NJ 07095",
    "addr:housenumber":"346",
    "addr:postcode":"07095",
    "addr:street":"Main St",
    "iso:country":"US",
    "sg:address":"346 Main St",
    "sg:city":"Woodbridge",
    "sg:classifiers":[
        {
            "category":"Sports & Exercise",
            "subcategory":"Bowling",
            "type":"Entertainment"
        }
    ],
    "sg:phone":"+1 732 750 4552",
    "sg:postcode":"07095",
    "sg:province":"NJ",
    "sg:tags":[
        "center"
    ],
    "wof:name":"Ed Walsh's Pro Shop",
    "wof:placetype":"venue"
},
  "geometry": {"coordinates":[-74.291397,40.5499],"type":"Point"}
}