{
  "type": "Feature",
  "properties": {
    "iso:country":"US",
    "sg:address":"11 Gordon Ave",
    "sg:city":"Trenton",
    "sg:classifiers":[
        {
            "category":"Education",
            "subcategory":"Special Training",
            "type":"Public Place"
        }
    ],
    "sg:phone":"+1 609 896 2200",
    "sg:postcode":"08648",
    "sg:province":"NJ",
    "sg:tags":[
        "school",
        "instruction",
        "art"
    ],
    "wof:name":"Maidenhead Studio",
    "wof:placetype":"venue"
},
  "geometry": {"coordinates":[-74.729933,40.29825],"type":"Point"}
}