{
  "type": "Feature",
  "properties": {
    "addr:full":"600 S Livingston Ave Livingston NJ 07039",
    "addr:housenumber":"600",
    "addr:postcode":"07039",
    "addr:street":"S Livingston Ave",
    "iso:country":"US",
    "sg:address":"600 S Livingston Ave",
    "sg:city":"Livingston",
    "sg:classifiers":[
        {
            "category":"Professional",
            "subcategory":"Employment Agencies",
            "type":"Services"
        }
    ],
    "sg:phone":"+1 973 740 9001",
    "sg:postcode":"07039",
    "sg:province":"NJ",
    "wof:name":"Health Staff Professional",
    "wof:placetype":"venue"
},
  "geometry": {"coordinates":[-74.32706399999999,40.772742],"type":"Point"}
}