{
  "type": "Feature",
  "properties": {
    "iso:country":"US",
    "sg:address":"162 Pine Brook Rd",
    "sg:city":"Montville",
    "sg:classifiers":[
        {
            "category":"Recreation",
            "type":"Entertainment"
        }
    ],
    "sg:phone":"+1 973 575 1525",
    "sg:postcode":"07045",
    "sg:province":"NJ",
    "sg:tags":[
        "stable"
    ],
    "wof:name":"Pine Brook Stables",
    "wof:placetype":"venue"
},
  "geometry": {"coordinates":[-74.340971,40.89275],"type":"Point"}
}