{
  "type": "Feature",
  "properties": {
    "addr:full":"209 Bogert St Totowa NJ 07512",
    "addr:housenumber":"209",
    "addr:postcode":"07512",
    "addr:street":"Bogert St",
    "iso:country":"US",
    "sg:address":"209 Bogert St",
    "sg:city":"Totowa",
    "sg:classifiers":[
        {
            "category":"Wholesale",
            "subcategory":"Vending Machines",
            "type":"Manufacturing & Wholesale Goods"
        }
    ],
    "sg:phone":"+1   ",
    "sg:postcode":"07512",
    "sg:province":"NJ",
    "sg:tags":[
        "operator"
    ],
    "wof:name":"Big Cap Vending Corp",
    "wof:placetype":"venue"
},
  "geometry": {"coordinates":[-74.22065600000001,40.903161],"type":"Point"}
}