{
  "type": "Feature",
  "properties": {
    "iso:country":"US",
    "sg:address":"77 Sussex Rd",
    "sg:city":"Washington Twp",
    "sg:classifiers":[
        {
            "category":"Wholesale",
            "subcategory":"Medical Equipment & Supplies",
            "type":"Manufacturing & Wholesale Goods"
        }
    ],
    "sg:phone":"+1 201 666 6434",
    "sg:postcode":"07676",
    "sg:province":"NJ",
    "sg:tags":[
        "optical"
    ],
    "wof:name":"Smilen International Eyewear",
    "wof:placetype":"venue"
},
  "geometry": {"coordinates":[-74.0575,40.985329],"type":"Point"}
}