{
  "type": "Feature",
  "properties": {
    "iso:country":"US",
    "sg:address":"100 Heritage Valley Dr",
    "sg:city":"Sewell",
    "sg:classifiers":[
        {
            "category":"Health Services",
            "subcategory":"Doctor",
            "type":"Services"
        }
    ],
    "sg:phone":"+1 856 582 6100",
    "sg:postcode":"08080",
    "sg:province":"NJ",
    "sg:tags":[
        "physician",
        "surgeon"
    ],
    "wof:name":"Washington Medical",
    "wof:placetype":"venue"
},
  "geometry": {"coordinates":[-75.08558499999999,39.749659],"type":"Point"}
}