{
  "type": "Feature",
  "properties": {
    "iso:country":"US",
    "sg:address":"11 Desai Ct",
    "sg:city":"Eatontown",
    "sg:classifiers":[
        {
            "category":"Professional",
            "subcategory":"Art Services",
            "type":"Services"
        }
    ],
    "sg:phone":"+1   ",
    "sg:postcode":"07728",
    "sg:province":"NJ",
    "sg:tags":[
        "graphic",
        "design"
    ],
    "wof:name":"Regan Graphic Design",
    "wof:placetype":"venue"
},
  "geometry": {"coordinates":[-74.21761600000001,40.239938],"type":"Point"}
}