{
  "type": "Feature",
  "properties": {
    "addr:full":"41 Romeo St Moonachie NJ 07074",
    "addr:housenumber":"41",
    "addr:postcode":"07074",
    "addr:street":"Romeo St",
    "iso:country":"US",
    "sg:address":"41 Romeo St",
    "sg:city":"Moonachie",
    "sg:classifiers":[
        {
            "category":"Building & Trades",
            "subcategory":"Plumbing",
            "type":"Services"
        }
    ],
    "sg:phone":"+1 201 262 4491",
    "sg:postcode":"07074",
    "sg:province":"NJ",
    "sg:tags":[
        "conditioning",
        "air",
        "system",
        "contractor"
    ],
    "wof:name":"Air Conditioning & Heating",
    "wof:placetype":"venue"
},
  "geometry": {"coordinates":[-74.07221,40.839975],"type":"Point"}
}