{
  "type": "Feature",
  "properties": {
    "iso:country":"US",
    "sg:address":"141 S Black Horse Pike",
    "sg:city":"Blackwood",
    "sg:classifiers":[
        {
            "category":"Health Services",
            "subcategory":"Doctor",
            "type":"Services"
        }
    ],
    "sg:phone":"+1 856 931 6868",
    "sg:postcode":"08012",
    "sg:province":"NJ",
    "sg:tags":[
        "medical"
    ],
    "wof:name":"Joseph Marchetta MD",
    "wof:placetype":"venue"
},
  "geometry": {"coordinates":[-75.066114,39.800791],"type":"Point"}
}