{
  "type": "Feature",
  "properties": {
    "iso:country":"US",
    "sg:address":"177 Main St",
    "sg:city":"East Brunswick",
    "sg:classifiers":[
        {
            "category":"Recreation",
            "type":"Entertainment"
        }
    ],
    "sg:phone":"+1 732 238 1414",
    "sg:postcode":"08816",
    "sg:province":"NJ",
    "sg:tags":[
        "karate",
        "judo",
        "instr"
    ],
    "sg:website":"www.taijiusa.com",
    "wof:name":"Andy Lee's Tai Chi Chuan Ctr",
    "wof:placetype":"venue"
},
  "geometry": {"coordinates":[-74.362527,40.415939],"type":"Point"}
}