{
  "type": "Feature",
  "properties": {
    "iso:country":"US",
    "sg:address":"134 Colonial Dr",
    "sg:city":"Lakewood",
    "sg:classifiers":[
        {
            "category":"Freight",
            "type":"Transportation"
        }
    ],
    "sg:phone":"+1 732 364 3528",
    "sg:postcode":"08701",
    "sg:province":"NJ",
    "sg:tags":[
        "operator",
        "local",
        "trucking"
    ],
    "wof:name":"Grimaldi Trucking Inc",
    "wof:placetype":"venue"
},
  "geometry": {"coordinates":[-74.214123,40.051051],"type":"Point"}
}