{
  "type": "Feature",
  "properties": {
    "addr:full":"623 Westfield Ave Elizabeth NJ 07208",
    "addr:housenumber":"623",
    "addr:postcode":"07208",
    "addr:street":"Westfield Ave",
    "iso:country":"US",
    "sg:address":"623 Westfield Ave",
    "sg:city":"Elizabeth",
    "sg:classifiers":[
        {
            "category":"Insurance",
            "subcategory":"Insurance Agent",
            "type":"Services"
        }
    ],
    "sg:phone":"+1 908 355 8765",
    "sg:postcode":"07208",
    "sg:province":"NJ",
    "wof:name":"Omega's Insurance",
    "wof:placetype":"venue"
},
  "geometry": {"coordinates":[-74.23687200000001,40.665419],"type":"Point"}
}