{
  "type": "Feature",
  "properties": {
    "addr:full":"79 Sky Manor Rd Pittstown NJ 08867",
    "addr:housenumber":"79",
    "addr:postcode":"08867",
    "addr:street":"Sky Manor Rd",
    "iso:country":"US",
    "sg:address":"79 Sky Manor Rd",
    "sg:city":"Pittstown",
    "sg:classifiers":[
        {
            "category":"Building & Trades",
            "subcategory":"Construction",
            "type":"Services"
        }
    ],
    "sg:phone":"+1 908 996 3298",
    "sg:postcode":"08867",
    "sg:province":"NJ",
    "sg:tags":[
        "house"
    ],
    "wof:name":"Razz Construction",
    "wof:placetype":"venue"
},
  "geometry": {"coordinates":[-74.982376,40.56279],"type":"Point"}
}