{
  "type": "Feature",
  "properties": {
    "addr:full":"24 Durham Ave Metuchen NJ 08840",
    "addr:housenumber":"24",
    "addr:postcode":"08840",
    "addr:street":"Durham Ave",
    "iso:country":"US",
    "sg:address":"24 Durham Ave",
    "sg:city":"Metuchen",
    "sg:classifiers":[
        {
            "category":"Wholesale",
            "subcategory":"Electrical",
            "type":"Manufacturing & Wholesale Goods"
        }
    ],
    "sg:phone":"+1 732 906 9649",
    "sg:postcode":"08840",
    "sg:province":"NJ",
    "sg:tags":[
        "control"
    ],
    "wof:name":"Jersey State Energy Controls",
    "wof:placetype":"venue"
},
  "geometry": {"coordinates":[-74.363798,40.544659],"type":"Point"}
}