{
  "type": "Feature",
  "properties": {
    "addr:full":"100 Oak St East Rutherford NJ 07073",
    "addr:housenumber":"100",
    "addr:postcode":"07073",
    "addr:street":"Oak St",
    "iso:country":"US",
    "sg:address":"100 Oak St",
    "sg:city":"East Rutherford",
    "sg:classifiers":[
        {
            "category":"Manufacturing",
            "subcategory":"Chemicals & Compounds",
            "type":"Manufacturing & Wholesale Goods"
        }
    ],
    "sg:phone":"+1 201 935 5045",
    "sg:postcode":"07073",
    "sg:province":"NJ",
    "sg:tags":[
        "inorganic",
        "industrial",
        "mfg"
    ],
    "wof:name":"Absco Products LTD",
    "wof:placetype":"venue"
},
  "geometry": {"coordinates":[-74.10623699999999,40.839359],"type":"Point"}
}