{
  "type": "Feature",
  "properties": {
    "addr:full":"4 Delaware Ave Trenton NJ 08628",
    "addr:housenumber":"4",
    "addr:postcode":"08628",
    "addr:street":"Delaware Ave",
    "iso:country":"US",
    "sg:address":"4 Delaware Ave",
    "sg:city":"Trenton",
    "sg:classifiers":[
        {
            "category":"Shopping",
            "subcategory":"Used Merchandise",
            "type":"Retail Goods"
        }
    ],
    "sg:phone":"+1   ",
    "sg:postcode":"08628",
    "sg:province":"NJ",
    "wof:name":"Lifetime Treasures",
    "wof:placetype":"venue"
},
  "geometry": {"coordinates":[-74.850979,40.272982],"type":"Point"}
}