{
  "type": "Feature",
  "properties": {
    "addr:full":"6 Old Milford Ln West Milford NJ 07480",
    "addr:housenumber":"6",
    "addr:postcode":"07480",
    "addr:street":"Old Milford Ln",
    "iso:country":"US",
    "sg:address":"6 Old Milford Ln",
    "sg:city":"West Milford",
    "sg:classifiers":[
        {
            "category":"Real Estate",
            "subcategory":"Real Estate Services",
            "type":"Services"
        }
    ],
    "sg:phone":"+1   ",
    "sg:postcode":"07480",
    "sg:province":"NJ",
    "sg:tags":[
        "searching",
        "title"
    ],
    "wof:name":"Precision Title Searching",
    "wof:placetype":"venue"
},
  "geometry": {"coordinates":[-74.406285,41.102821],"type":"Point"}
}