{
  "type": "Feature",
  "properties": {
    "addr:full":"22 South St Morristown NJ 07960",
    "addr:housenumber":"22",
    "addr:postcode":"07960",
    "addr:street":"South St",
    "iso:country":"US",
    "sg:address":"22 South St",
    "sg:city":"Morristown",
    "sg:classifiers":[
        {
            "category":"Professional",
            "subcategory":"Management & Consulting",
            "type":"Services"
        }
    ],
    "sg:phone":"+1 973 292 1220",
    "sg:postcode":"07960",
    "sg:province":"NJ",
    "sg:tags":[
        "investing",
        "fuel"
    ],
    "wof:name":"Penn Phoenix Asset Management",
    "wof:placetype":"venue"
},
  "geometry": {"coordinates":[-74.480598,40.795799],"type":"Point"}
}