{
  "type": "Feature",
  "properties": {
    "iso:country":"US",
    "sg:address":"73 Catherine Ct",
    "sg:city":"Ringwood",
    "sg:classifiers":[
        {
            "category":"Organizations",
            "subcategory":"Membership Organization",
            "type":"Services"
        }
    ],
    "sg:phone":"+1 973 962 4889",
    "sg:postcode":"07456",
    "sg:province":"NJ",
    "wof:name":"Desimone Christn L Foundation",
    "wof:placetype":"venue"
},
  "geometry": {"coordinates":[-74.256215,41.120217],"type":"Point"}
}