{
  "type": "Feature",
  "properties": {
    "addr:full":"1100 E State St Camden NJ 08105",
    "addr:housenumber":"1100",
    "addr:postcode":"08105",
    "addr:street":"E State St",
    "iso:country":"US",
    "sg:address":"1100 E State St",
    "sg:city":"Camden",
    "sg:classifiers":[
        {
            "category":"Manufacturing",
            "subcategory":"Buildings",
            "type":"Manufacturing & Wholesale Goods"
        },
        {
            "category":"Building & Trades",
            "subcategory":"Construction",
            "type":"Services"
        }
    ],
    "sg:phone":"+1 856 963 2113",
    "sg:postcode":"08105",
    "sg:province":"NJ",
    "sg:tags":[
        "home",
        "builder",
        "road",
        "contractor"
    ],
    "wof:name":"Arline",
    "wof:placetype":"venue"
},
  "geometry": {"coordinates":[-75.102158,39.949661],"type":"Point"}
}