{
  "type": "Feature",
  "properties": {
    "addr:full":"45 N Gaston Ave Somerville NJ 08876",
    "addr:housenumber":"45",
    "addr:postcode":"08876",
    "addr:street":"N Gaston Ave",
    "iso:country":"US",
    "sg:address":"45 N Gaston Ave",
    "sg:city":"Somerville",
    "sg:classifiers":[
        {
            "category":"Building & Trades",
            "subcategory":"Construction",
            "type":"Services"
        }
    ],
    "sg:phone":"+1 973 624 8100",
    "sg:postcode":"08876",
    "sg:province":"NJ",
    "sg:tags":[
        "general",
        "contractor"
    ],
    "sg:website":"www.blackstonegroupllc.com",
    "wof:name":"Blackstone Group",
    "wof:placetype":"venue"
},
  "geometry": {"coordinates":[-74.60370899999999,40.566144],"type":"Point"}
}