{
  "type": "Feature",
  "properties": {
    "iso:country":"US",
    "sg:address":"440 State Rte 36",
    "sg:city":"Highlands",
    "sg:classifiers":[
        {
            "category":"Shopping",
            "subcategory":"Computers & Home Electronics",
            "type":"Retail Goods"
        }
    ],
    "sg:phone":"+1   ",
    "sg:postcode":"07732",
    "sg:province":"NJ",
    "wof:name":"Sounds Impossible Mobile Elec",
    "wof:placetype":"venue"
},
  "geometry": {"coordinates":[-73.998245,40.402921],"type":"Point"}
}