{
  "type": "Feature",
  "properties": {
    "addr:full":"225 River Rd Edgewater NJ 07020",
    "addr:housenumber":"225",
    "addr:postcode":"07020",
    "addr:street":"River Rd",
    "iso:country":"US",
    "sg:address":"225 River Rd",
    "sg:city":"Edgewater",
    "sg:classifiers":[
        {
            "category":"Sports & Exercise",
            "subcategory":"Bicycle Rental",
            "type":"Entertainment"
        }
    ],
    "sg:phone":"+1 201 313 4956",
    "sg:postcode":"07020",
    "sg:province":"NJ",
    "sg:tags":[
        "wear"
    ],
    "sg:website":"www.gap.com",
    "wof:name":"The Gap",
    "wof:placetype":"venue"
},
  "geometry": {"coordinates":[-73.99065,40.806823],"type":"Point"}
}