{
  "type": "Feature",
  "properties": {
    "addr:full":"15 N Montpelier Ave Atlantic City NJ 08401",
    "addr:housenumber":"15",
    "addr:postcode":"08401",
    "addr:street":"N Montpelier Ave",
    "iso:country":"US",
    "sg:address":"15 N Montpelier Ave",
    "sg:city":"Atlantic City",
    "sg:classifiers":[
        {
            "category":"Restaurant",
            "type":"Food & Drink"
        }
    ],
    "sg:phone":"+1 609 344 1402",
    "sg:postcode":"08401",
    "sg:province":"NJ",
    "sg:tags":[
        "parlor",
        "ice",
        "cream"
    ],
    "wof:name":"Ice Cream Corner",
    "wof:placetype":"venue"
},
  "geometry": {"coordinates":[-74.450754,39.354633],"type":"Point"}
}