{
  "type": "Feature",
  "properties": {
    "addr:full":"105 Crusher Rd Hopewell NJ 08525",
    "addr:housenumber":"105",
    "addr:postcode":"08525",
    "addr:street":"Crusher Rd",
    "iso:country":"US",
    "sg:address":"105 Crusher Rd",
    "sg:city":"Hopewell",
    "sg:classifiers":[
        {
            "category":"Professional",
            "subcategory":"Management & Consulting",
            "type":"Services"
        }
    ],
    "sg:phone":"+1 609 466 3377",
    "sg:postcode":"08525",
    "sg:province":"NJ",
    "sg:tags":[
        "marketing",
        "publishing",
        "desktop"
    ],
    "wof:name":"Stout Associates",
    "wof:placetype":"venue"
},
  "geometry": {"coordinates":[-74.76049399999999,40.373985],"type":"Point"}
}