{
  "type": "Feature",
  "properties": {
    "addr:full":"322 Park Ave Newark NJ 07107",
    "addr:housenumber":"322",
    "addr:postcode":"07107",
    "addr:street":"Park Ave",
    "iso:country":"US",
    "sg:address":"322 Park Ave",
    "sg:city":"Newark",
    "sg:classifiers":[
        {
            "category":"Building & Trades",
            "subcategory":"Electrical",
            "type":"Services"
        }
    ],
    "sg:phone":"+1 973 432 0782",
    "sg:postcode":"07107",
    "sg:province":"NJ",
    "sg:tags":[
        "contracting"
    ],
    "wof:name":"Atashi Communications LLC",
    "wof:placetype":"venue"
},
  "geometry": {"coordinates":[-74.190417,40.760204],"type":"Point"}
}