{
  "type": "Feature",
  "properties": {
    "addr:full":"91 High St Newton NJ 07869",
    "addr:housenumber":"91",
    "addr:postcode":"07869",
    "addr:street":"High St",
    "iso:country":"US",
    "sg:address":"91 High St",
    "sg:city":"Newton",
    "sg:classifiers":[
        {
            "category":"Arts & Performance",
            "subcategory":"Theater",
            "type":"Entertainment"
        }
    ],
    "sg:phone":"+1 973 300 9123",
    "sg:postcode":"07869",
    "sg:province":"NJ",
    "sg:tags":[
        "entertainer",
        "group"
    ],
    "wof:name":"Stars Entertainment & Producti",
    "wof:placetype":"venue"
},
  "geometry": {"coordinates":[-74.553602,40.864856],"type":"Point"}
}