{
  "type": "Feature",
  "properties": {
    "iso:country":"US",
    "sg:address":"212 43rd St",
    "sg:city":"Union City",
    "sg:classifiers":[
        {
            "category":"Retail",
            "subcategory":"Car Wash",
            "type":"Services"
        }
    ],
    "sg:phone":"+1 201 864 2626",
    "sg:postcode":"07087",
    "sg:province":"NJ",
    "sg:tags":[
        "automobile",
        "detail",
        "clean"
    ],
    "wof:name":"Exculsive Auto Detailing",
    "wof:placetype":"venue"
},
  "geometry": {"coordinates":[-74.022087,40.776987],"type":"Point"}
}