{
  "type": "Feature",
  "properties": {
    "addr:full":"929 S Clinton Ave Trenton NJ 08611",
    "addr:housenumber":"929",
    "addr:postcode":"08611",
    "addr:street":"S Clinton Ave",
    "iso:country":"US",
    "sg:address":"929 S Clinton Ave",
    "sg:city":"Trenton",
    "sg:classifiers":[
        {
            "category":"Retail",
            "subcategory":"Funeral Services",
            "type":"Services"
        }
    ],
    "sg:phone":"+1 609 393 6385",
    "sg:postcode":"08611",
    "sg:province":"NJ",
    "sg:tags":[
        "director"
    ],
    "wof:name":"Rogers Funeral Home Inc",
    "wof:placetype":"venue"
},
  "geometry": {"coordinates":[-74.748643,40.208151],"type":"Point"}
}