{
  "type": "Feature",
  "properties": {
    "addr:full":"26 Cory Rd Flanders NJ 07836",
    "addr:housenumber":"26",
    "addr:postcode":"07836",
    "addr:street":"Cory Rd",
    "iso:country":"US",
    "sg:address":"26 Cory Rd",
    "sg:city":"Flanders",
    "sg:classifiers":[
        {
            "category":"Health Services",
            "subcategory":"Doctor",
            "type":"Services"
        }
    ],
    "sg:phone":"+1 973 584 8090",
    "sg:postcode":"07836",
    "sg:province":"NJ",
    "sg:tags":[
        "dentist"
    ],
    "wof:name":"Roger M Casulli DDS",
    "wof:placetype":"venue"
},
  "geometry": {"coordinates":[-74.713487,40.85544],"type":"Point"}
}