{
  "type": "Feature",
  "properties": {
    "iso:country":"US",
    "sg:address":"7 Seneca Trl",
    "sg:city":"Oak Ridge",
    "sg:classifiers":[
        {
            "category":"Building & Trades",
            "subcategory":"Construction",
            "type":"Services"
        }
    ],
    "sg:phone":"+1 973 697 1997",
    "sg:postcode":"07438",
    "sg:province":"NJ",
    "sg:tags":[
        "house"
    ],
    "wof:name":"Chet K General Contracting",
    "wof:placetype":"venue"
},
  "geometry": {"coordinates":[-74.522137,41.004936],"type":"Point"}
}