{
  "type": "Feature",
  "properties": {
    "iso:country":"US",
    "sg:address":"6137 Bergenline Ave",
    "sg:city":"West New York",
    "sg:classifiers":[
        {
            "category":"Banks & Credit Unions",
            "subcategory":"Bank",
            "type":"Services"
        }
    ],
    "sg:phone":"+1 201 295 5381",
    "sg:postcode":"07093",
    "sg:province":"NJ",
    "wof:name":"Td Bank",
    "wof:placetype":"venue"
},
  "geometry": {"coordinates":[-74.015308,40.790461],"type":"Point"}
}