{
  "type": "Feature",
  "properties": {
    "addr:full":"25 Frances Rd Pequannock NJ 07440",
    "addr:housenumber":"25",
    "addr:postcode":"07440",
    "addr:street":"Frances Rd",
    "iso:country":"US",
    "sg:address":"25 Frances Rd",
    "sg:city":"Pequannock",
    "sg:classifiers":[
        {
            "category":"Building & Trades",
            "subcategory":"Landscaping Services",
            "type":"Services"
        }
    ],
    "sg:phone":"+1 973 696 8582",
    "sg:postcode":"07440",
    "sg:province":"NJ",
    "sg:tags":[
        "landscape"
    ],
    "wof:name":"Creative Design Landscaping",
    "wof:placetype":"venue"
},
  "geometry": {"coordinates":[-74.30024,40.941561],"type":"Point"}
}