{
  "type": "Feature",
  "properties": {
    "addr:full":"770 State Hwy 40 Monroeville NJ 08343",
    "addr:housenumber":"770",
    "addr:postcode":"08343",
    "addr:street":"State Hwy 40",
    "iso:country":"US",
    "sg:address":"770 State Hwy 40",
    "sg:city":"Monroeville",
    "sg:classifiers":[
        {
            "category":"Retail",
            "subcategory":"Auto Rental",
            "type":"Services"
        }
    ],
    "sg:phone":"+1 856 358 4895",
    "sg:postcode":"08343",
    "sg:province":"NJ",
    "sg:tags":[
        "renting",
        "truck",
        "leasing"
    ],
    "wof:name":"U-Haul Co",
    "wof:placetype":"venue"
},
  "geometry": {"coordinates":[-75.229761,39.617258],"type":"Point"}
}