{
  "type": "Feature",
  "properties": {
    "addr:full":"41 Bethany Cir Closter NJ 07624",
    "addr:housenumber":"41",
    "addr:postcode":"07624",
    "addr:street":"Bethany Cir",
    "iso:country":"US",
    "sg:address":"41 Bethany Cir",
    "sg:city":"Closter",
    "sg:classifiers":[
        {
            "category":"Building & Trades",
            "subcategory":"Construction",
            "type":"Services"
        }
    ],
    "sg:phone":"+1 201 750 2161",
    "sg:postcode":"07624",
    "sg:province":"NJ",
    "sg:tags":[
        "house"
    ],
    "wof:name":"Bluestone Construction Corp",
    "wof:placetype":"venue"
},
  "geometry": {"coordinates":[-73.983976,40.971043],"type":"Point"}
}