{
  "type": "Feature",
  "properties": {
    "addr:full":"213 Euclid Ave Allenhurst NJ 07711",
    "addr:housenumber":"213",
    "addr:postcode":"07711",
    "addr:street":"Euclid Ave",
    "iso:country":"US",
    "sg:address":"213 Euclid Ave",
    "sg:city":"Allenhurst",
    "sg:classifiers":[
        {
            "category":"Professional",
            "subcategory":"Business Services",
            "type":"Services"
        }
    ],
    "sg:phone":"+1   ",
    "sg:postcode":"07711",
    "sg:province":"NJ",
    "wof:name":"English Speak",
    "wof:placetype":"venue"
},
  "geometry": {"coordinates":[-74.000687,40.233027],"type":"Point"}
}