{
  "type": "Feature",
  "properties": {
    "iso:country":"US",
    "sg:address":"1943 Sawmill Ct",
    "sg:city":"Toms River",
    "sg:classifiers":[
        {
            "category":"Wholesale",
            "subcategory":"Computers",
            "type":"Manufacturing & Wholesale Goods"
        }
    ],
    "sg:phone":"+1 732 240 1122",
    "sg:postcode":"08755",
    "sg:province":"NJ",
    "wof:name":"Joel Mennie",
    "wof:placetype":"venue"
},
  "geometry": {"coordinates":[-74.232613,40.024659],"type":"Point"}
}