{
  "type": "Feature",
  "properties": {
    "iso:country":"US",
    "sg:address":"406 Kings Hwy S",
    "sg:city":"Cherry Hill",
    "sg:classifiers":[
        {
            "category":"Health Services",
            "subcategory":"Doctor",
            "type":"Services"
        }
    ],
    "sg:phone":"+1 856 429 6462",
    "sg:postcode":"08034",
    "sg:province":"NJ",
    "sg:tags":[
        "dentist"
    ],
    "wof:name":"Robert M Carroll DDS",
    "wof:placetype":"venue"
},
  "geometry": {"coordinates":[-75.01376999999999,39.911001],"type":"Point"}
}