{
  "type": "Feature",
  "properties": {
    "iso:country":"US",
    "sg:address":"44 High St",
    "sg:city":"Passaic",
    "sg:classifiers":[
        {
            "category":"Manufacturing",
            "subcategory":"Textiles",
            "type":"Manufacturing & Wholesale Goods"
        }
    ],
    "sg:phone":"+1 973 710 2530",
    "sg:postcode":"07055",
    "sg:province":"NJ",
    "wof:name":"Samuel Hirsch",
    "wof:placetype":"venue"
},
  "geometry": {"coordinates":[-74.12505299999999,40.853194],"type":"Point"}
}