{
  "type": "Feature",
  "properties": {
    "iso:country":"US",
    "sg:address":"1328 S Black Horse Pike",
    "sg:city":"Williamstown",
    "sg:classifiers":[
        {
            "category":"Health Services",
            "subcategory":"Health Practitioner",
            "type":"Services"
        }
    ],
    "sg:phone":"+1 856 740 9471",
    "sg:postcode":"08094",
    "sg:province":"NJ",
    "wof:name":"Paragon Rehabilitation",
    "wof:placetype":"venue"
},
  "geometry": {"coordinates":[-74.97358199999999,39.66912],"type":"Point"}
}