{
  "type": "Feature",
  "properties": {
    "iso:country":"US",
    "sg:address":"31 South St",
    "sg:city":"Morristown",
    "sg:classifiers":[
        {
            "category":"Banks & Credit Unions",
            "subcategory":"Financial Services",
            "type":"Services"
        }
    ],
    "sg:phone":"+1 973 889 0099",
    "sg:postcode":"07960",
    "sg:province":"NJ",
    "sg:tags":[
        "broker",
        "mortgage"
    ],
    "wof:name":"Wall Street Financial Llc",
    "wof:placetype":"venue"
},
  "geometry": {"coordinates":[-74.480103,40.795502],"type":"Point"}
}