{
  "type": "Feature",
  "properties": {
    "addr:full":"141 Mountain Ave Hackettstown NJ 07840",
    "addr:housenumber":"141",
    "addr:postcode":"07840",
    "addr:street":"Mountain Ave",
    "iso:country":"US",
    "sg:address":"141 Mountain Ave",
    "sg:city":"Hackettstown",
    "sg:classifiers":[
        {
            "category":"Autos & Motor Vehicles",
            "subcategory":"Auto Supplies",
            "type":"Retail Goods"
        }
    ],
    "sg:phone":"+1 908 684 0567",
    "sg:postcode":"07840",
    "sg:province":"NJ",
    "sg:tags":[
        "tire"
    ],
    "wof:name":"Discount Tire Co",
    "wof:placetype":"venue"
},
  "geometry": {"coordinates":[-74.82396,40.846305],"type":"Point"}
}