{
  "type": "Feature",
  "properties": {
    "iso:country":"US",
    "sg:address":"345 W Absecon Blvd",
    "sg:city":"Absecon",
    "sg:classifiers":[
        {
            "category":"Autos & Motor Vehicles",
            "subcategory":"Fuel & Gas Station",
            "type":"Retail Goods"
        }
    ],
    "sg:phone":"+1 609 646 5405",
    "sg:postcode":"08201",
    "sg:province":"NJ",
    "sg:tags":[
        "oil"
    ],
    "wof:name":"Atlantic Fuels",
    "wof:placetype":"venue"
},
  "geometry": {"coordinates":[-74.503153,39.425997],"type":"Point"}
}