{
  "type": "Feature",
  "properties": {
    "addr:full":"5122 John F Kennedy Blvd W West New York NJ 07093",
    "addr:housenumber":"5122",
    "addr:postcode":"07093",
    "addr:street":"John F Kennedy Blvd W West",
    "iso:country":"US",
    "sg:address":"5122 John F Kennedy Blvd W",
    "sg:city":"West New York",
    "sg:classifiers":[
        {
            "category":"Restaurant",
            "type":"Food & Drink"
        }
    ],
    "sg:phone":"+1 201 553 2979",
    "sg:postcode":"07093",
    "sg:province":"NJ",
    "sg:tags":[
        "mediterranean",
        "spanish"
    ],
    "sg:website":"www.zietuna.com",
    "wof:name":"Zietuna Grill & Cafe",
    "wof:placetype":"venue"
},
  "geometry": {"coordinates":[-74.022885,40.784894],"type":"Point"}
}