{
  "type": "Feature",
  "properties": {
    "addr:full":"20 Waterview Blvd Parsippany NJ 07054",
    "addr:housenumber":"20",
    "addr:postcode":"07054",
    "addr:street":"Waterview Blvd",
    "iso:country":"US",
    "sg:address":"20 Waterview Blvd",
    "sg:city":"Parsippany",
    "sg:classifiers":[
        {
            "category":"Professional",
            "subcategory":"Accounting & Tax Preparation",
            "type":"Services"
        }
    ],
    "sg:phone":"+1 973 334 1445",
    "sg:postcode":"07054",
    "sg:province":"NJ",
    "sg:tags":[
        "payroll"
    ],
    "wof:name":"Paychex Inc",
    "wof:placetype":"venue"
},
  "geometry": {"coordinates":[-74.42299199999999,40.874978],"type":"Point"}
}