{
  "type": "Feature",
  "properties": {
    "addr:full":"100 Baker St Maplewood NJ 07040",
    "addr:housenumber":"100",
    "addr:postcode":"07040",
    "addr:street":"Baker St",
    "iso:country":"US",
    "sg:address":"100 Baker St",
    "sg:city":"Maplewood",
    "sg:classifiers":[
        {
            "category":"Shopping",
            "subcategory":"Clothing, Apparel, & Fashions",
            "type":"Retail Goods"
        }
    ],
    "sg:phone":"+1 973 761 4881",
    "sg:postcode":"07040",
    "sg:province":"NJ",
    "sg:tags":[
        "tailor"
    ],
    "wof:name":"Francesca's European Tailoring",
    "wof:placetype":"venue"
},
  "geometry": {"coordinates":[-74.279606,40.730326],"type":"Point"}
}