{
  "type": "Feature",
  "properties": {
    "addr:full":"78 Johnson Ave Hackensack NJ 07601",
    "addr:housenumber":"78",
    "addr:postcode":"07601",
    "addr:street":"Johnson Ave",
    "iso:country":"US",
    "sg:address":"78 Johnson Ave",
    "sg:city":"Hackensack",
    "sg:classifiers":[
        {
            "category":"Professional",
            "subcategory":"Art Services",
            "type":"Services"
        }
    ],
    "sg:phone":"+1 201 343 1233",
    "sg:postcode":"07601",
    "sg:province":"NJ",
    "sg:tags":[
        "photography",
        "commercial"
    ],
    "wof:name":"Freeze Frame Studios Inc",
    "wof:placetype":"venue"
},
  "geometry": {"coordinates":[-74.040952,40.904607],"type":"Point"}
}