{
  "type": "Feature",
  "properties": {
    "addr:full":"42 Carrie Ct Nutley NJ 07110",
    "addr:housenumber":"42",
    "addr:postcode":"07110",
    "addr:street":"Carrie Ct",
    "iso:country":"US",
    "sg:address":"42 Carrie Ct",
    "sg:city":"Nutley",
    "sg:classifiers":[
        {
            "category":"Professional",
            "subcategory":"Business Services",
            "type":"Services"
        }
    ],
    "sg:phone":"+1   ",
    "sg:postcode":"07110",
    "sg:province":"NJ",
    "wof:name":"Avish Enterprises Inc",
    "wof:placetype":"venue"
},
  "geometry": {"coordinates":[-74.17643099999999,40.811497],"type":"Point"}
}