{
  "type": "Feature",
  "properties": {
    "iso:country":"US",
    "sg:address":"52 Tennyson St",
    "sg:city":"Carteret",
    "sg:classifiers":[
        {
            "category":"Banks & Credit Unions",
            "subcategory":"Investment Brokerage",
            "type":"Services"
        }
    ],
    "sg:phone":"+1   ",
    "sg:postcode":"07008",
    "sg:province":"NJ",
    "sg:tags":[
        "security"
    ],
    "wof:name":"Alarm",
    "wof:placetype":"venue"
},
  "geometry": {"coordinates":[-74.232288,40.586101],"type":"Point"}
}