{
  "type": "Feature",
  "properties": {
    "iso:country":"US",
    "sg:address":"9 Olde Woods Ln",
    "sg:city":"Montvale",
    "sg:classifiers":[
        {
            "category":"Shopping",
            "subcategory":"Stationery & Office Supplies",
            "type":"Retail Goods"
        }
    ],
    "sg:phone":"+1   ",
    "sg:postcode":"07645",
    "sg:province":"NJ",
    "wof:name":"Pearl River Stationers",
    "wof:placetype":"venue"
},
  "geometry": {"coordinates":[-74.05453199999999,41.060612],"type":"Point"}
}