{
  "type": "Feature",
  "properties": {
    "iso:country":"US",
    "sg:address":"7 Hadley Ave",
    "sg:city":"Toms River",
    "sg:classifiers":[
        {
            "category":"Real Estate",
            "subcategory":"Real Estate Agent",
            "type":"Services"
        }
    ],
    "sg:phone":"+1 732 255 5846",
    "sg:postcode":"08753",
    "sg:province":"NJ",
    "wof:name":"Silver Bay Camelot Realty Inc",
    "wof:placetype":"venue"
},
  "geometry": {"coordinates":[-74.19059799999999,39.95283],"type":"Point"}
}