{
  "type": "Feature",
  "properties": {
    "iso:country":"US",
    "sg:address":"207 E Willow St",
    "sg:city":"Wenonah",
    "sg:classifiers":[
        {
            "category":"Professional",
            "type":"Services"
        }
    ],
    "sg:phone":"+1   ",
    "sg:postcode":"08090",
    "sg:province":"NJ",
    "wof:name":"Linda Ramsay",
    "wof:placetype":"venue"
},
  "geometry": {"coordinates":[-75.14619999999999,39.788506],"type":"Point"}
}