{
  "type": "Feature",
  "properties": {
    "iso:country":"US",
    "sg:address":"414 62nd St",
    "sg:city":"West New York",
    "sg:classifiers":[
        {
            "category":"Social Services",
            "subcategory":"Child Care",
            "type":"Services"
        }
    ],
    "sg:phone":"+1 201 662 8877",
    "sg:postcode":"07093",
    "sg:province":"NJ",
    "sg:tags":[
        "day"
    ],
    "wof:name":"Izabela Daycare",
    "wof:placetype":"venue"
},
  "geometry": {"coordinates":[-74.012398,40.790298],"type":"Point"}
}