{
  "type": "Feature",
  "properties": {
    "iso:country":"US",
    "sg:address":"1202 Bridgeboro Rd",
    "sg:city":"Beverly",
    "sg:classifiers":[
        {
            "category":"Building & Trades",
            "subcategory":"Plumbing",
            "type":"Services"
        }
    ],
    "sg:phone":"+1 609 877 5234",
    "sg:postcode":"08010",
    "sg:province":"NJ",
    "sg:tags":[
        "conditioning",
        "air",
        "system",
        "contractor"
    ],
    "wof:name":"Kane's Refrigeration Air Cond",
    "wof:placetype":"venue"
},
  "geometry": {"coordinates":[-74.921913,40.048015],"type":"Point"}
}