{
  "type": "Feature",
  "properties": {
    "addr:full":"4064 US Hwy 9 Howell NJ 07731",
    "addr:housenumber":"4064",
    "addr:postcode":"07731",
    "addr:street":"Us Hwy 9",
    "iso:country":"US",
    "sg:address":"4064 US Hwy 9",
    "sg:city":"Howell",
    "sg:classifiers":[
        {
            "category":"Home & Garden",
            "subcategory":"Household Appliances",
            "type":"Retail Goods"
        }
    ],
    "sg:phone":"+1 732 364 8888",
    "sg:postcode":"07731",
    "sg:province":"NJ",
    "sg:tags":[
        "cleaners",
        "vacuum"
    ],
    "wof:name":"A-1 Factory Sewing Ctr",
    "wof:placetype":"venue"
},
  "geometry": {"coordinates":[-74.228927,40.153358],"type":"Point"}
}