{
  "type": "Feature",
  "properties": {
    "iso:country":"US",
    "sg:address":"12 Hartley St",
    "sg:city":"Montclair",
    "sg:classifiers":[
        {
            "category":"Personal",
            "subcategory":"Beauty Salon",
            "type":"Services"
        }
    ],
    "sg:phone":"+1 973 744 3330",
    "sg:postcode":"07042",
    "sg:province":"NJ",
    "sg:tags":[
        "shop"
    ],
    "wof:name":"Beauty Biz",
    "wof:placetype":"venue"
},
  "geometry": {"coordinates":[-74.21233599999999,40.808017],"type":"Point"}
}