{
  "type": "Feature",
  "properties": {
    "addr:full":"66 W Jimmie Leeds Rd Absecon NJ 08205",
    "addr:housenumber":"66",
    "addr:postcode":"08205",
    "addr:street":"W Jimmie Leeds Rd",
    "iso:country":"US",
    "sg:address":"66 W Jimmie Leeds Rd",
    "sg:city":"Absecon",
    "sg:classifiers":[
        {
            "category":"Health Services",
            "subcategory":"Nursing And Care Facility",
            "type":"Services"
        },
        {
            "category":"Professional",
            "subcategory":"Business Services",
            "type":"Services"
        }
    ],
    "sg:phone":"+1 609 748 9100",
    "sg:postcode":"08205",
    "sg:province":"NJ",
    "sg:tags":[
        "home",
        "skilled",
        "convalescent"
    ],
    "wof:name":"Health Center At Galloway Inc",
    "wof:placetype":"venue"
},
  "geometry": {"coordinates":[-74.539416,39.476261],"type":"Point"}
}