{
  "type": "Feature",
  "properties": {
    "iso:country":"US",
    "sg:address":"3641 Route 42",
    "sg:city":"Blackwood",
    "sg:classifiers":[
        {
            "category":"Autos & Motor Vehicles",
            "subcategory":"Automobile Sales",
            "type":"Retail Goods"
        },
        {
            "category":"Autos & Motor Vehicles",
            "subcategory":"Auto Supplies",
            "type":"Retail Goods"
        },
        {
            "category":"Retail",
            "subcategory":"Auto Repair",
            "type":"Services"
        }
    ],
    "sg:phone":"+1 856 629 4500",
    "sg:postcode":"08012",
    "sg:province":"NJ",
    "sg:tags":[
        "new",
        "part",
        "car",
        "accessory"
    ],
    "sg:website":"http://www.turnersvilleauto.com",
    "wof:name":"Hyundai Of Turnersville",
    "wof:placetype":"venue"
},
  "geometry": {"coordinates":[-75.035492,39.732052],"type":"Point"}
}