{
  "type": "Feature",
  "properties": {
    "addr:full":"70 Bloomfield Ave Pine Brook NJ 07058",
    "addr:housenumber":"70",
    "addr:postcode":"07058",
    "addr:street":"Bloomfield Ave",
    "iso:country":"US",
    "sg:address":"70 Bloomfield Ave",
    "sg:city":"Pine Brook",
    "sg:classifiers":[
        {
            "category":"Professional",
            "subcategory":"Lawyer & Legal Services",
            "type":"Services"
        }
    ],
    "sg:phone":"+1 973 227 2777",
    "sg:postcode":"07058",
    "sg:province":"NJ",
    "sg:tags":[
        "attorney"
    ],
    "wof:name":"Larson Litigation Law Firm Law",
    "wof:placetype":"venue"
},
  "geometry": {"coordinates":[-74.33046400000001,40.85989],"type":"Point"}
}