{
  "type": "Feature",
  "properties": {
    "iso:country":"US",
    "sg:address":"159 Main St",
    "sg:city":"Chatham",
    "sg:classifiers":[
        {
            "category":"Insurance",
            "subcategory":"Insurance Agent",
            "type":"Services"
        }
    ],
    "sg:phone":"+1 973 635 1800",
    "sg:postcode":"07928",
    "sg:province":"NJ",
    "sg:website":"www.ogy-grmurray.com",
    "wof:name":"O'Gorman & Young",
    "wof:placetype":"venue"
},
  "geometry": {"coordinates":[-74.37924599999999,40.739528],"type":"Point"}
}