{
  "type": "Feature",
  "properties": {
    "iso:country":"US",
    "sg:address":"6 Independence Ct",
    "sg:city":"Madison",
    "sg:classifiers":[
        {
            "category":"Health Services",
            "subcategory":"Doctor",
            "type":"Services"
        }
    ],
    "sg:phone":"+1 973 377 7234",
    "sg:postcode":"07940",
    "sg:province":"NJ",
    "sg:tags":[
        "dentist"
    ],
    "wof:name":"George Kryzaniwsky DDS",
    "wof:placetype":"venue"
},
  "geometry": {"coordinates":[-74.40144100000001,40.742908],"type":"Point"}
}