{
  "type": "Feature",
  "properties": {
    "iso:country":"US",
    "sg:address":"174 Homans Ave",
    "sg:city":"Closter",
    "sg:classifiers":[
        {
            "category":"Restaurant",
            "type":"Food & Drink"
        }
    ],
    "sg:menulink":"http://www.allmenus.com/nj/closter/191375-burger-king/menu/",
    "sg:phone":"+1 201 768 9793",
    "sg:postcode":"07624",
    "sg:province":"NJ",
    "sg:tags":[
        "burger",
        "american"
    ],
    "wof:name":"Burger King",
    "wof:placetype":"venue"
},
  "geometry": {"coordinates":[-73.954037,40.969986],"type":"Point"}
}