{
  "type": "Feature",
  "properties": {
    "addr:full":"1060 Stuyvesant Ave Irvington NJ 07111",
    "addr:housenumber":"1060",
    "addr:postcode":"07111",
    "addr:street":"Stuyvesant Ave",
    "iso:country":"US",
    "sg:address":"1060 Stuyvesant Ave",
    "sg:city":"Irvington",
    "sg:classifiers":[
        {
            "category":"Autos & Motor Vehicles",
            "subcategory":"Fuel & Gas Station",
            "type":"Retail Goods"
        }
    ],
    "sg:phone":"+1   ",
    "sg:postcode":"07111",
    "sg:province":"NJ",
    "sg:tags":[
        "station",
        "gasoline"
    ],
    "wof:name":"Getty",
    "wof:placetype":"venue"
},
  "geometry": {"coordinates":[-74.250658,40.714174],"type":"Point"}
}