{
  "type": "Feature",
  "properties": {
    "addr:full":"318 Washington St Cape May NJ 08204",
    "addr:housenumber":"318",
    "addr:postcode":"08204",
    "addr:street":"Washington St",
    "iso:country":"US",
    "sg:address":"318 Washington St",
    "sg:city":"Cape May",
    "sg:classifiers":[
        {
            "category":"Shopping",
            "type":"Retail Goods"
        }
    ],
    "sg:phone":"+1 609 898 8886",
    "sg:postcode":"08204",
    "sg:province":"NJ",
    "sg:tags":[
        "art",
        "gallery",
        "dealer"
    ],
    "wof:name":"Inspiration Gallery",
    "wof:placetype":"venue"
},
  "geometry": {"coordinates":[-74.923492,38.932297],"type":"Point"}
}