{
  "type": "Feature",
  "properties": {
    "addr:full":"1225 Madison Ave Paterson NJ 07503",
    "addr:housenumber":"1225",
    "addr:postcode":"07503",
    "addr:street":"Madison Ave",
    "iso:country":"US",
    "sg:address":"1225 Madison Ave",
    "sg:city":"Paterson",
    "sg:classifiers":[
        {
            "category":"Building & Trades",
            "subcategory":"Electrical",
            "type":"Services"
        }
    ],
    "sg:phone":"+1 973 977 9778",
    "sg:postcode":"07503",
    "sg:province":"NJ",
    "sg:tags":[
        "electrician"
    ],
    "wof:name":"Justan Electrical Contracting",
    "wof:placetype":"venue"
},
  "geometry": {"coordinates":[-74.1605,40.900299],"type":"Point"}
}