{
  "type": "Feature",
  "properties": {
    "addr:full":"14 Main St Montvale NJ 07645",
    "addr:housenumber":"14",
    "addr:postcode":"07645",
    "addr:street":"Main St",
    "iso:country":"US",
    "sg:address":"14 Main St",
    "sg:city":"Montvale",
    "sg:classifiers":[
        {
            "category":"Professional",
            "subcategory":"Business Services",
            "type":"Services"
        }
    ],
    "sg:phone":"+1   ",
    "sg:postcode":"07645",
    "sg:province":"NJ",
    "wof:name":"Koushi-Dojo Inc",
    "wof:placetype":"venue"
},
  "geometry": {"coordinates":[-74.02243199999999,41.045567],"type":"Point"}
}