{
  "type": "Feature",
  "properties": {
    "addr:full":"27 Van Doren Way Belle Mead NJ 08502",
    "addr:housenumber":"27",
    "addr:postcode":"08502",
    "addr:street":"Van Doren Way Belle Mead",
    "iso:country":"US",
    "sg:address":"27 Van Doren Way",
    "sg:city":"Belle Mead",
    "sg:classifiers":[
        {
            "category":"Professional",
            "subcategory":"Detective & Security Services",
            "type":"Services"
        }
    ],
    "sg:phone":"+1   ",
    "sg:postcode":"08502",
    "sg:province":"NJ",
    "sg:tags":[
        "car"
    ],
    "wof:name":"James Dowd",
    "wof:placetype":"venue"
},
  "geometry": {"coordinates":[-74.62352199999999,40.437867],"type":"Point"}
}