{
  "type": "Feature",
  "properties": {
    "addr:full":"105 Curtis Ave Manasquan NJ 08736",
    "addr:housenumber":"105",
    "addr:postcode":"08736",
    "addr:street":"Curtis Ave",
    "iso:country":"US",
    "sg:address":"105 Curtis Ave",
    "sg:city":"Manasquan",
    "sg:classifiers":[
        {
            "category":"Building & Trades",
            "subcategory":"Construction",
            "type":"Services"
        }
    ],
    "sg:phone":"+1 732 223 5774",
    "sg:postcode":"08736",
    "sg:province":"NJ",
    "sg:tags":[
        "contractor"
    ],
    "wof:name":"Oceanside Construction Inc",
    "wof:placetype":"venue"
},
  "geometry": {"coordinates":[-74.05023199999999,40.120312],"type":"Point"}
}