{
  "type": "Feature",
  "properties": {
    "addr:full":"6579 Delilah Rd Egg Harbor Twp NJ 08234",
    "addr:housenumber":"6579",
    "addr:postcode":"08234",
    "addr:street":"Delilah Rd",
    "iso:country":"US",
    "sg:address":"6579 Delilah Rd",
    "sg:city":"Egg Harbor Twp",
    "sg:classifiers":[
        {
            "category":"Shopping",
            "subcategory":"Hobbies, Toys, & Games",
            "type":"Retail Goods"
        }
    ],
    "sg:phone":"+1 609 646 8817",
    "sg:postcode":"08234",
    "sg:province":"NJ",
    "sg:tags":[
        "supply"
    ],
    "wof:name":"M 3 Gaming",
    "wof:placetype":"venue"
},
  "geometry": {"coordinates":[-74.557575,39.423874],"type":"Point"}
}