{
  "type": "Feature",
  "properties": {
    "iso:country":"US",
    "sg:address":"27 Justine Pl",
    "sg:city":"Succasunna",
    "sg:classifiers":[
        {
            "category":"Professional",
            "subcategory":"Computer Services",
            "type":"Services"
        }
    ],
    "sg:phone":"+1 973 945 9512",
    "sg:postcode":"07876",
    "sg:province":"NJ",
    "sg:tags":[
        "design",
        "system"
    ],
    "wof:name":"Rentronics Services LLC",
    "wof:placetype":"venue"
},
  "geometry": {"coordinates":[-74.640148,40.848145],"type":"Point"}
}