{
  "type": "Feature",
  "properties": {
    "iso:country":"US",
    "sg:address":"2 Doctors Park",
    "sg:city":"Hackettstown",
    "sg:classifiers":[
        {
            "category":"Health Services",
            "subcategory":"Health Practitioner",
            "type":"Services"
        }
    ],
    "sg:phone":"+1 908 850 8050",
    "sg:postcode":"07840",
    "sg:province":"NJ",
    "sg:tags":[
        "therapist",
        "physical"
    ],
    "wof:name":"Hackettstown Rehab Clinic",
    "wof:placetype":"venue"
},
  "geometry": {"coordinates":[-74.818969,40.857864],"type":"Point"}
}