{
  "type": "Feature",
  "properties": {
    "iso:country":"US",
    "sg:address":"160 First St",
    "sg:city":"Jersey City",
    "sg:classifiers":[
        {
            "category":"Building & Trades",
            "subcategory":"Cleaning & Sanitation",
            "type":"Services"
        },
        {
            "category":"Building & Trades",
            "subcategory":"Construction",
            "type":"Services"
        }
    ],
    "sg:phone":"+1 201 798 8160",
    "sg:postcode":"07302",
    "sg:province":"NJ",
    "sg:tags":[
        "home",
        "conditioning/hvac",
        "heating",
        "air"
    ],
    "wof:name":"Dunwell Environmental",
    "wof:placetype":"venue"
},
  "geometry": {"coordinates":[-74.03985900000001,40.721417],"type":"Point"}
}