{
  "type": "Feature",
  "properties": {
    "iso:country":"US",
    "sg:address":"1731 Main St",
    "sg:city":"Belmar",
    "sg:classifiers":[
        {
            "category":"Professional",
            "subcategory":"Advertising",
            "type":"Services"
        }
    ],
    "sg:phone":"+1 732 892 4300",
    "sg:postcode":"07719",
    "sg:province":"NJ",
    "sg:tags":[
        "representative"
    ],
    "wof:name":"Pleasant Broadcasters Inc",
    "wof:placetype":"venue"
},
  "geometry": {"coordinates":[-74.0275,40.17089],"type":"Point"}
}