{
  "type": "Feature",
  "properties": {
    "addr:full":"1250 Collings Rd Camden NJ 08104",
    "addr:housenumber":"1250",
    "addr:postcode":"08104",
    "addr:street":"Collings Rd",
    "iso:country":"US",
    "sg:address":"1250 Collings Rd",
    "sg:city":"Camden",
    "sg:classifiers":[
        {
            "category":"Community Center",
            "subcategory":"Senior",
            "type":"Public Place"
        },
        {
            "category":"Social Services",
            "subcategory":"Adult Care",
            "type":"Services"
        }
    ],
    "sg:phone":"+1 856 962 0426",
    "sg:postcode":"08104",
    "sg:province":"NJ",
    "sg:tags":[
        "counseling",
        "citizen"
    ],
    "wof:name":"Market Fair Ura Lp",
    "wof:placetype":"venue"
},
  "geometry": {"coordinates":[-75.104561,39.904049],"type":"Point"}
}