{
  "type": "Feature",
  "properties": {
    "addr:full":"390 Kinderkamack Rd Oradell NJ 07649",
    "addr:housenumber":"390",
    "addr:postcode":"07649",
    "addr:street":"Kinderkamack Rd",
    "iso:country":"US",
    "sg:address":"390 Kinderkamack Rd",
    "sg:city":"Oradell",
    "sg:classifiers":[
        {
            "category":"Shopping",
            "subcategory":"Jewelry",
            "type":"Retail Goods"
        }
    ],
    "sg:phone":"+1 201 261 7161",
    "sg:postcode":"07649",
    "sg:province":"NJ",
    "sg:tags":[
        "jeweler"
    ],
    "wof:name":"Oradell Jewelers",
    "wof:placetype":"venue"
},
  "geometry": {"coordinates":[-74.03159100000001,40.953608],"type":"Point"}
}