{
  "type": "Feature",
  "properties": {
    "addr:full":"1 Mayfair Ct Belle Mead NJ 08527",
    "addr:housenumber":"1",
    "addr:postcode":"08527",
    "addr:street":"Mayfair Ct Belle Mead",
    "iso:country":"US",
    "sg:address":"1 Mayfair Ct",
    "sg:city":"Belle Mead",
    "sg:classifiers":[
        {
            "category":"Organizations",
            "subcategory":"Community Association",
            "type":"Services"
        }
    ],
    "sg:phone":"+1 908 874 6032",
    "sg:postcode":"08527",
    "sg:province":"NJ",
    "wof:name":"Huntington Pk Homeowners Assoc",
    "wof:placetype":"venue"
},
  "geometry": {"coordinates":[-74.381395,40.156721],"type":"Point"}
}