{
  "type": "Feature",
  "properties": {
    "iso:country":"US",
    "sg:address":"1012 Cox Cro Rd",
    "sg:city":"Toms River",
    "sg:classifiers":[
        {
            "category":"Restaurant",
            "type":"Food & Drink"
        }
    ],
    "sg:menulink":"http://www.allmenus.com/nj/toms-river/28138-brunello/menu/",
    "sg:phone":"+1 732 281 0255",
    "sg:postcode":"08755",
    "sg:province":"NJ",
    "sg:tags":[
        "italian"
    ],
    "wof:name":"Brunello",
    "wof:placetype":"venue"
},
  "geometry": {"coordinates":[-74.22301400000001,40.02984],"type":"Point"}
}