{
  "type": "Feature",
  "properties": {
    "iso:country":"US",
    "sg:address":"1 Bella Vista Ct",
    "sg:city":"Colts Neck",
    "sg:classifiers":[
        {
            "category":"Shopping",
            "subcategory":"Used Merchandise",
            "type":"Retail Goods"
        }
    ],
    "sg:phone":"+1   ",
    "sg:postcode":"07722",
    "sg:province":"NJ",
    "wof:name":"Angelicas",
    "wof:placetype":"venue"
},
  "geometry": {"coordinates":[-74.211007,40.306317],"type":"Point"}
}