{
  "type": "Feature",
  "properties": {
    "iso:country":"US",
    "sg:address":"700 US Hwy 130",
    "sg:city":"Cinnaminson",
    "sg:classifiers":[
        {
            "category":"Insurance",
            "subcategory":"Insurance Agent",
            "type":"Services"
        }
    ],
    "sg:phone":"+1 856 786 3857",
    "sg:postcode":"08077",
    "sg:province":"NJ",
    "sg:tags":[
        "adjuster"
    ],
    "wof:name":"Mc Shea Assoc Inc",
    "wof:placetype":"venue"
},
  "geometry": {"coordinates":[-74.994461,39.995988],"type":"Point"}
}