{
  "type": "Feature",
  "properties": {
    "iso:country":"US",
    "sg:address":"470 Mine Brook Rd",
    "sg:city":"Bernardsville",
    "sg:classifiers":[
        {
            "category":"Wholesale",
            "subcategory":"Construction Materials",
            "type":"Manufacturing & Wholesale Goods"
        }
    ],
    "sg:phone":"+1 908 221 9000",
    "sg:postcode":"07924",
    "sg:province":"NJ",
    "sg:tags":[
        "fence"
    ],
    "wof:name":"Dingus Roycroft Fence & Deck",
    "wof:placetype":"venue"
},
  "geometry": {"coordinates":[-74.60442999999999,40.699942],"type":"Point"}
}