{
  "type": "Feature",
  "properties": {
    "addr:full":"243 Hamburg Tpke Pompton Lakes NJ 07442",
    "addr:housenumber":"243",
    "addr:postcode":"07442",
    "addr:street":"Hamburg Tpke",
    "iso:country":"US",
    "sg:address":"243 Hamburg Tpke",
    "sg:city":"Pompton Lakes",
    "sg:classifiers":[
        {
            "category":"Organizations",
            "subcategory":"Religious Organization",
            "type":"Services"
        }
    ],
    "sg:phone":"+1 973 835 2125",
    "sg:postcode":"07442",
    "sg:province":"NJ",
    "sg:tags":[
        "church"
    ],
    "wof:name":"Christian Science Church",
    "wof:placetype":"venue"
},
  "geometry": {"coordinates":[-74.286587,40.998127],"type":"Point"}
}