{
  "type": "Feature",
  "properties": {
    "addr:full":"1024 Elizabeth Ave Elizabeth NJ 07201",
    "addr:housenumber":"1024",
    "addr:postcode":"07201",
    "addr:street":"Elizabeth Ave",
    "iso:country":"US",
    "sg:address":"1024 Elizabeth Ave",
    "sg:city":"Elizabeth",
    "sg:classifiers":[
        {
            "category":"Home & Garden",
            "subcategory":"Hardware",
            "type":"Retail Goods"
        }
    ],
    "sg:phone":"+1 908 354 2646",
    "sg:postcode":"07201",
    "sg:province":"NJ",
    "wof:name":"Standard True Value Home Ctr",
    "wof:placetype":"venue"
},
  "geometry": {"coordinates":[-74.208263,40.660645],"type":"Point"}
}