{
  "type": "Feature",
  "properties": {
    "addr:full":"10 E Brinkerhoff Ave Palisades Park NJ 07650",
    "addr:housenumber":"10",
    "addr:postcode":"07650",
    "addr:street":"E Brinkerhoff Ave",
    "iso:country":"US",
    "sg:address":"10 E Brinkerhoff Ave",
    "sg:city":"Palisades Park",
    "sg:classifiers":[
        {
            "category":"Wholesale",
            "subcategory":"Stationery",
            "type":"Manufacturing & Wholesale Goods"
        }
    ],
    "sg:phone":"+1 201 944 4856",
    "sg:postcode":"07650",
    "sg:province":"NJ",
    "sg:tags":[
        "product",
        "paper"
    ],
    "wof:name":"Pal Park Paper Store",
    "wof:placetype":"venue"
},
  "geometry": {"coordinates":[-73.99833700000001,40.846787],"type":"Point"}
}