{
  "type": "Feature",
  "properties": {
    "iso:country":"US",
    "sg:address":"101 Interchange Plz",
    "sg:city":"Cranbury",
    "sg:classifiers":[
        {
            "category":"Banks & Credit Unions",
            "subcategory":"Investment Brokerage",
            "type":"Services"
        }
    ],
    "sg:phone":"+1 609 395 9933",
    "sg:postcode":"08512",
    "sg:province":"NJ",
    "sg:tags":[
        "consultant",
        "financing"
    ],
    "wof:name":"Rinaldi Enterprises",
    "wof:placetype":"venue"
},
  "geometry": {"coordinates":[-74.48285799999999,40.343942],"type":"Point"}
}