{
  "type": "Feature",
  "properties": {
    "addr:full":"15 James St Ste 7 Florham Park NJ 07932",
    "addr:housenumber":"15",
    "addr:postcode":"07932",
    "addr:street":"James St Ste 7",
    "iso:country":"US",
    "sg:address":"15 James St Ste 7",
    "sg:city":"Florham Park",
    "sg:classifiers":[
        {
            "category":"Health Services",
            "subcategory":"Doctor",
            "type":"Services"
        }
    ],
    "sg:phone":"+1 973 822 9019",
    "sg:postcode":"07932",
    "sg:province":"NJ",
    "wof:name":"Nash Lillian MD",
    "wof:placetype":"venue"
},
  "geometry": {"coordinates":[-74.388802,40.789799],"type":"Point"}
}