{
  "type": "Feature",
  "properties": {
    "addr:full":"700 Huyler St Teterboro NJ 07608",
    "addr:housenumber":"700",
    "addr:postcode":"07608",
    "addr:street":"Huyler St",
    "iso:country":"US",
    "sg:address":"700 Huyler St",
    "sg:city":"Teterboro",
    "sg:classifiers":[
        {
            "category":"Professional",
            "subcategory":"Lawyer & Legal Services",
            "type":"Services"
        }
    ],
    "sg:phone":"+1 201 288 2236",
    "sg:postcode":"07608",
    "sg:province":"NJ",
    "wof:name":"Allu Group Attorney",
    "wof:placetype":"venue"
},
  "geometry": {"coordinates":[-74.04958600000001,40.861141],"type":"Point"}
}