{
  "type": "Feature",
  "properties": {
    "iso:country":"US",
    "sg:address":"842 River Rd",
    "sg:city":"Trenton",
    "sg:classifiers":[
        {
            "category":"Professional",
            "subcategory":"Lawyer & Legal Services",
            "type":"Services"
        }
    ],
    "sg:phone":"+1 856 931 2260",
    "sg:postcode":"08628",
    "sg:province":"NJ",
    "sg:tags":[
        "attorney"
    ],
    "wof:name":"Ali & Aldi",
    "wof:placetype":"venue"
},
  "geometry": {"coordinates":[-74.839899,40.250331],"type":"Point"}
}