{
  "type": "Feature",
  "properties": {
    "iso:country":"US",
    "sg:address":"996 S Shore Dr",
    "sg:city":"Basking Ridge",
    "sg:classifiers":[
        {
            "category":"Building & Trades",
            "subcategory":"Electrical",
            "type":"Services"
        }
    ],
    "sg:phone":"+1 908 658 4816",
    "sg:postcode":"07920",
    "sg:province":"NJ",
    "sg:tags":[
        "electrical",
        "contractor"
    ],
    "wof:name":"Automatic Alarms Inc",
    "wof:placetype":"venue"
},
  "geometry": {"coordinates":[-74.62824000000001,40.640541],"type":"Point"}
}