{
  "type": "Feature",
  "properties": {
    "iso:country":"US",
    "sg:address":"5804 Ravens Crest Dr",
    "sg:city":"Plainsboro",
    "sg:classifiers":[
        {
            "category":"Professional",
            "type":"Services"
        }
    ],
    "sg:phone":"+1   ",
    "sg:postcode":"08536",
    "sg:province":"NJ",
    "wof:name":"Relge Corp",
    "wof:placetype":"venue"
},
  "geometry": {"coordinates":[-74.555082,40.326543],"type":"Point"}
}