{
  "type": "Feature",
  "properties": {
    "addr:full":"1 Newark St Newark NJ 07103",
    "addr:housenumber":"1",
    "addr:postcode":"07103",
    "addr:street":"Newark St",
    "iso:country":"US",
    "sg:address":"1 Newark St",
    "sg:city":"Newark",
    "sg:classifiers":[
        {
            "category":"Professional",
            "type":"Services"
        }
    ],
    "sg:phone":"+1 973 792 9099",
    "sg:postcode":"07103",
    "sg:province":"NJ",
    "sg:tags":[
        "establishment"
    ],
    "wof:name":"Holiday Treasures",
    "wof:placetype":"venue"
},
  "geometry": {"coordinates":[-74.18125999999999,40.747003],"type":"Point"}
}