{
  "type": "Feature",
  "properties": {
    "addr:full":"439 Oakshade Rd Shamong NJ 08088",
    "addr:housenumber":"439",
    "addr:postcode":"08088",
    "addr:street":"Oakshade Rd",
    "iso:country":"US",
    "sg:address":"439 Oakshade Rd",
    "sg:city":"Shamong",
    "sg:classifiers":[
        {
            "category":"Professional",
            "type":"Services"
        },
        {
            "category":"Restaurant",
            "type":"Food & Drink"
        },
        {
            "category":"Retail",
            "subcategory":"Event Space",
            "type":"Services"
        }
    ],
    "sg:phone":"+1 609 755 4128",
    "sg:postcode":"08088",
    "sg:province":"NJ",
    "sg:tags":[
        "facility",
        "banquet",
        "reception",
        "caterer",
        "hall",
        "italian"
    ],
    "sg:website":"http://www.la-campagnola.com",
    "wof:name":"La Campagnola",
    "wof:placetype":"venue"
},
  "geometry": {"coordinates":[-74.760925,39.816799],"type":"Point"}
}