{
  "type": "Feature",
  "properties": {
    "addr:full":"108 Brick Rd Marlton NJ 08053",
    "addr:housenumber":"108",
    "addr:postcode":"08053",
    "addr:street":"Brick Rd",
    "iso:country":"US",
    "sg:address":"108 Brick Rd",
    "sg:city":"Marlton",
    "sg:classifiers":[
        {
            "category":"Real Estate",
            "subcategory":"Real Estate Operator",
            "type":"Services"
        }
    ],
    "sg:phone":"+1   ",
    "sg:postcode":"08053",
    "sg:province":"NJ",
    "sg:tags":[
        "building",
        "apartment"
    ],
    "wof:name":"Brook View Apartments",
    "wof:placetype":"venue"
},
  "geometry": {"coordinates":[-74.92482699999999,39.880509],"type":"Point"}
}