{
  "type": "Feature",
  "properties": {
    "addr:full":"2900 Route 130 N  Riverton NJ 08077",
    "addr:housenumber":"2900",
    "addr:postcode":"08077",
    "addr:street":"Route 130 N",
    "iso:country":"US",
    "sg:address":"2900 Route 130 N ",
    "sg:city":"Riverton",
    "sg:classifiers":[
        {
            "category":"Restaurant",
            "type":"Food & Drink"
        }
    ],
    "sg:menulink":"http://www.allmenus.com/nj/riverton/80589-papa-johns-pizza/menu/",
    "sg:phone":"+1 856 303 9300",
    "sg:postcode":"08077",
    "sg:province":"NJ",
    "sg:tags":[
        "american",
        "pizza"
    ],
    "wof:name":"Papa John's Pizza",
    "wof:placetype":"venue"
},
  "geometry": {"coordinates":[-74.9696,40.0081],"type":"Point"}
}