{
  "type": "Feature",
  "properties": {
    "iso:country":"US",
    "sg:address":"1171 Liberty Ave",
    "sg:city":"Hillside",
    "sg:classifiers":[
        {
            "category":"Food & Beverages",
            "subcategory":"Bakery",
            "type":"Retail Goods"
        }
    ],
    "sg:phone":"+1 908 289 1144",
    "sg:postcode":"07205",
    "sg:province":"NJ",
    "sg:tags":[
        "shop",
        "doughnut"
    ],
    "sg:website":"www.dunkindonuts.com",
    "wof:name":"Dunkin' Donuts",
    "wof:placetype":"venue"
},
  "geometry": {"coordinates":[-74.23581299999999,40.694466],"type":"Point"}
}