{
  "type": "Feature",
  "properties": {
    "addr:full":"1037 US Hwy 206 Bordentown NJ 08505",
    "addr:housenumber":"1037",
    "addr:postcode":"08505",
    "addr:street":"Us Hwy 206",
    "iso:country":"US",
    "sg:address":"1037 US Hwy 206",
    "sg:city":"Bordentown",
    "sg:classifiers":[
        {
            "category":"Retail",
            "subcategory":"Auto Rental",
            "type":"Services"
        }
    ],
    "sg:phone":"+1   ",
    "sg:postcode":"08505",
    "sg:province":"NJ",
    "sg:tags":[
        "passenger",
        "car"
    ],
    "wof:name":"Hertz",
    "wof:placetype":"venue"
},
  "geometry": {"coordinates":[-74.70455699999999,40.132521],"type":"Point"}
}