{
  "type": "Feature",
  "properties": {
    "addr:full":"2 Edinburgh Ct Englishtown NJ 07726",
    "addr:housenumber":"2",
    "addr:postcode":"07726",
    "addr:street":"Edinburgh Ct",
    "iso:country":"US",
    "sg:address":"2 Edinburgh Ct",
    "sg:city":"Englishtown",
    "sg:classifiers":[
        {
            "category":"Professional",
            "subcategory":"Management & Consulting",
            "type":"Services"
        }
    ],
    "sg:phone":"+1 732 727 4300",
    "sg:postcode":"07726",
    "sg:province":"NJ",
    "sg:tags":[
        "training",
        "computer"
    ],
    "wof:name":"Iconsys Entertainment",
    "wof:placetype":"venue"
},
  "geometry": {"coordinates":[-74.374528,40.245273],"type":"Point"}
}