{
  "type": "Feature",
  "properties": {
    "iso:country":"US",
    "sg:address":"105 Union St",
    "sg:city":"Newark",
    "sg:classifiers":[
        {
            "category":"Food & Beverages",
            "subcategory":"Groceries & Convenience Stores",
            "type":"Retail Goods"
        },
        {
            "category":"Food & Beverages",
            "subcategory":"Specialty",
            "type":"Retail Goods"
        }
    ],
    "sg:phone":"+1 973 589 2435",
    "sg:postcode":"07105",
    "sg:province":"NJ",
    "sg:tags":[
        "poultry"
    ],
    "wof:name":"Union Poultry Co Inc",
    "wof:placetype":"venue"
},
  "geometry": {"coordinates":[-74.16458299999999,40.730775],"type":"Point"}
}