{
  "type": "Feature",
  "properties": {
    "iso:country":"US",
    "sg:address":"369 Broad Ave",
    "sg:city":"Leonia",
    "sg:classifiers":[
        {
            "category":"Restaurant",
            "type":"Food & Drink"
        }
    ],
    "sg:phone":"+1 201 944 0181",
    "sg:postcode":"07605",
    "sg:province":"NJ",
    "sg:tags":[
        "eating",
        "caterer"
    ],
    "wof:name":"Convenience Food Mart",
    "wof:placetype":"venue"
},
  "geometry": {"coordinates":[-73.98699999999999,40.8633],"type":"Point"}
}