{
  "type": "Feature",
  "properties": {
    "addr:full":"25 Hanover Rd Florham Park NJ 07932",
    "addr:housenumber":"25",
    "addr:postcode":"07932",
    "addr:street":"Hanover Rd",
    "iso:country":"US",
    "sg:address":"25 Hanover Rd",
    "sg:city":"Florham Park",
    "sg:classifiers":[
        {
            "category":"Insurance",
            "subcategory":"Insurance Agent",
            "type":"Services"
        }
    ],
    "sg:phone":"+1   ",
    "sg:postcode":"07932",
    "sg:province":"NJ",
    "wof:name":"Provident",
    "wof:placetype":"venue"
},
  "geometry": {"coordinates":[-74.383087,40.789518],"type":"Point"}
}