{
  "type": "Feature",
  "properties": {
    "iso:country":"US",
    "sg:address":"265 1st St",
    "sg:city":"Hoboken",
    "sg:classifiers":[
        {
            "category":"Shopping",
            "subcategory":"Tobacco",
            "type":"Retail Goods"
        }
    ],
    "sg:phone":"+1   ",
    "sg:postcode":"07030",
    "sg:province":"NJ",
    "sg:tags":[
        "product"
    ],
    "wof:name":"Hit It Big Outfitters",
    "wof:placetype":"venue"
},
  "geometry": {"coordinates":[-74.034302,40.737945],"type":"Point"}
}