{
  "type": "Feature",
  "properties": {
    "addr:full":"433 Pine Ave Woodbury NJ 08096",
    "addr:housenumber":"433",
    "addr:postcode":"08096",
    "addr:street":"Pine Ave",
    "iso:country":"US",
    "sg:address":"433 Pine Ave",
    "sg:city":"Woodbury",
    "sg:phone":"+1 856 228 5471",
    "sg:postcode":"08096",
    "sg:province":"NJ",
    "sg:tags":[
        "equipment",
        "commercial"
    ],
    "wof:name":"Jt Dental Equipment Company",
    "wof:placetype":"venue"
},
  "geometry": {"coordinates":[-75.08881100000001,39.808212],"type":"Point"}
}