{
  "type": "Feature",
  "properties": {
    "addr:full":"508 Bridge St Trenton NJ 08611",
    "addr:housenumber":"508",
    "addr:postcode":"08611",
    "addr:street":"Bridge St",
    "iso:country":"US",
    "sg:address":"508 Bridge St",
    "sg:city":"Trenton",
    "sg:classifiers":[
        {
            "category":"Wholesale",
            "subcategory":"Hardware",
            "type":"Manufacturing & Wholesale Goods"
        }
    ],
    "sg:phone":"+1 609 695 5256",
    "sg:postcode":"08611",
    "sg:province":"NJ",
    "sg:tags":[
        "refrigerating"
    ],
    "wof:name":"American Refrig Engineering",
    "wof:placetype":"venue"
},
  "geometry": {"coordinates":[-74.760791,40.21129],"type":"Point"}
}