{
  "type": "Feature",
  "properties": {
    "iso:country":"US",
    "sg:address":"1255 Caldwell Rd",
    "sg:city":"Cherry Hill",
    "sg:classifiers":[
        {
            "category":"Insurance",
            "subcategory":"Insurance Agent",
            "type":"Services"
        }
    ],
    "sg:phone":"+1 856 429 9200",
    "sg:postcode":"08034",
    "sg:province":"NJ",
    "sg:website":"www.admiralins.com",
    "wof:name":"Admiral Insurance Co",
    "wof:placetype":"venue"
},
  "geometry": {"coordinates":[-75.015868,39.89787],"type":"Point"}
}