{
  "type": "Feature",
  "properties": {
    "addr:full":"2502 Boardwalk Wildwood NJ 08260",
    "addr:housenumber":"2502",
    "addr:postcode":"08260",
    "addr:street":"Boardwalk",
    "iso:country":"US",
    "sg:address":"2502 Boardwalk",
    "sg:city":"Wildwood",
    "sg:classifiers":[
        {
            "category":"Recreation",
            "subcategory":"Amusement Park",
            "type":"Entertainment"
        }
    ],
    "sg:phone":"+1 609 522 6045",
    "sg:postcode":"08260",
    "sg:province":"NJ",
    "wof:name":"Elbee Variety",
    "wof:placetype":"venue"
},
  "geometry": {"coordinates":[-74.80349699999999,38.990398],"type":"Point"}
}