{
  "type": "Feature",
  "properties": {
    "iso:country":"US",
    "sg:address":"2986 John F Kennedy Blvd",
    "sg:city":"Jersey City",
    "sg:classifiers":[
        {
            "category":"Restaurant",
            "type":"Food & Drink"
        }
    ],
    "sg:phone":"+1 201 798 1600",
    "sg:postcode":"07306",
    "sg:province":"NJ",
    "sg:tags":[
        "halal"
    ],
    "wof:name":"Salt & Pepper Grill",
    "wof:placetype":"venue"
},
  "geometry": {"coordinates":[-74.06306600000001,40.734716],"type":"Point"}
}