{
  "type": "Feature",
  "properties": {
    "iso:country":"US",
    "sg:address":"82 1st Ave",
    "sg:city":"Atlantic Highlands",
    "sg:classifiers":[
        {
            "category":"Cinema",
            "subcategory":"Movie Theater",
            "type":"Entertainment"
        }
    ],
    "sg:phone":"+1 732 291 0148",
    "sg:postcode":"07716",
    "sg:province":"NJ",
    "sg:tags":[
        "motion",
        "picture"
    ],
    "wof:name":"Atlantic Theatre",
    "wof:placetype":"venue"
},
  "geometry": {"coordinates":[-74.03772499999999,40.413735],"type":"Point"}
}