{
  "type": "Feature",
  "properties": {
    "iso:country":"US",
    "sg:address":"629 US Hwy 130",
    "sg:city":"Burlington",
    "sg:classifiers":[
        {
            "category":"Autos & Motor Vehicles",
            "subcategory":"Fuel & Gas Station",
            "type":"Retail Goods"
        }
    ],
    "sg:phone":"+1 609 387 8810",
    "sg:postcode":"08016",
    "sg:province":"NJ",
    "sg:tags":[
        "oil"
    ],
    "wof:name":"Burlington Amoco",
    "wof:placetype":"venue"
},
  "geometry": {"coordinates":[-74.86565899999999,40.070776],"type":"Point"}
}