{
  "type": "Feature",
  "properties": {
    "iso:country":"US",
    "sg:address":"600 Palisade Ave",
    "sg:city":"Union City",
    "sg:classifiers":[
        {
            "category":"Shopping",
            "type":"Retail Goods"
        }
    ],
    "sg:phone":"+1 201 617 8840",
    "sg:postcode":"07087",
    "sg:province":"NJ",
    "sg:tags":[
        "art",
        "gallery",
        "dealer"
    ],
    "wof:name":"J K Fine Arts Editions Co",
    "wof:placetype":"venue"
},
  "geometry": {"coordinates":[-74.03710599999999,40.75522],"type":"Point"}
}