{
  "type": "Feature",
  "properties": {
    "iso:country":"US",
    "sg:address":"415 High St",
    "sg:city":"Burlington",
    "sg:classifiers":[
        {
            "category":"Professional",
            "subcategory":"Lawyer & Legal Services",
            "type":"Services"
        }
    ],
    "sg:phone":"+1 609 386 2633",
    "sg:postcode":"08016",
    "sg:province":"NJ",
    "wof:name":"Berenato Elizabeth D Lawyer",
    "wof:placetype":"venue"
},
  "geometry": {"coordinates":[-74.857597,40.0769],"type":"Point"}
}