{
  "type": "Feature",
  "properties": {
    "addr:full":"30 Walnut St Ramsey NJ 07446",
    "addr:housenumber":"30",
    "addr:postcode":"07446",
    "addr:street":"Walnut St",
    "iso:country":"US",
    "sg:address":"30 Walnut St",
    "sg:city":"Ramsey",
    "sg:classifiers":[
        {
            "category":"Manufacturing",
            "subcategory":"Pottery",
            "type":"Manufacturing & Wholesale Goods"
        }
    ],
    "sg:phone":"+1 201 327 3452",
    "sg:postcode":"07446",
    "sg:province":"NJ",
    "sg:tags":[
        "product",
        "mfg"
    ],
    "wof:name":"Silver Rose",
    "wof:placetype":"venue"
},
  "geometry": {"coordinates":[-74.139712,41.063302],"type":"Point"}
}