{
  "type": "Feature",
  "properties": {
    "iso:country":"US",
    "sg:address":"453 Martin Luther King Dr",
    "sg:city":"Jersey City",
    "sg:classifiers":[
        {
            "category":"Travel",
            "subcategory":"Campground",
            "type":"Entertainment"
        },
        {
            "category":"Social Services",
            "type":"Services"
        }
    ],
    "sg:phone":"+1 201 333 7837",
    "sg:postcode":"07304",
    "sg:province":"NJ",
    "sg:tags":[
        "organization",
        "camp",
        "welfare"
    ],
    "wof:name":"Remarkable Mossi Youth Council",
    "wof:placetype":"venue"
},
  "geometry": {"coordinates":[-74.076059,40.714119],"type":"Point"}
}