{
  "type": "Feature",
  "properties": {
    "addr:full":"2 Garfield Ter Long Branch NJ 07740",
    "addr:housenumber":"2",
    "addr:postcode":"07740",
    "addr:street":"Garfield Ter",
    "iso:country":"US",
    "sg:address":"2 Garfield Ter",
    "sg:city":"Long Branch",
    "sg:classifiers":[
        {
            "category":"Health Services",
            "subcategory":"Doctor",
            "type":"Services"
        }
    ],
    "sg:phone":"+1 732 222 9024",
    "sg:postcode":"07740",
    "sg:province":"NJ",
    "sg:tags":[
        "dentist"
    ],
    "wof:name":"John Ritota DDS",
    "wof:placetype":"venue"
},
  "geometry": {"coordinates":[-73.98901499999999,40.264452],"type":"Point"}
}