{
  "type": "Feature",
  "properties": {
    "iso:country":"US",
    "sg:address":"2475 McClellan Ave",
    "sg:city":"Pennsauken",
    "sg:classifiers":[
        {
            "category":"Community Center",
            "type":"Public Place"
        }
    ],
    "sg:phone":"+1 856 675 3355",
    "sg:postcode":"08109",
    "sg:province":"NJ",
    "sg:tags":[
        "medical"
    ],
    "wof:name":"Our Lady of Lourdes Medical Center - Life At Lourdes",
    "wof:placetype":"venue"
},
  "geometry": {"coordinates":[-75.06804700000001,39.929726],"type":"Point"}
}