{
  "type": "Feature",
  "properties": {
    "addr:full":"80 Union Blvd Wallington NJ 07057",
    "addr:housenumber":"80",
    "addr:postcode":"07057",
    "addr:street":"Union Blvd",
    "iso:country":"US",
    "sg:address":"80 Union Blvd",
    "sg:city":"Wallington",
    "sg:classifiers":[
        {
            "category":"Building & Trades",
            "subcategory":"Locksmith",
            "type":"Services"
        }
    ],
    "sg:phone":"+1 877 898 9283",
    "sg:postcode":"07057",
    "sg:province":"NJ",
    "sg:tags":[
        "key"
    ],
    "wof:name":"Emergency 24 Hour 7 Day Locksmith",
    "wof:placetype":"venue"
},
  "geometry": {"coordinates":[-74.11339700000001,40.853772],"type":"Point"}
}