{
  "type": "Feature",
  "properties": {
    "addr:full":"280 Closter Dock Rd Closter NJ 07624",
    "addr:housenumber":"280",
    "addr:postcode":"07624",
    "addr:street":"Closter Dock Rd",
    "iso:country":"US",
    "sg:address":"280 Closter Dock Rd",
    "sg:city":"Closter",
    "sg:classifiers":[
        {
            "category":"Restaurant",
            "type":"Food & Drink"
        }
    ],
    "sg:phone":"+1   ",
    "sg:postcode":"07624",
    "sg:province":"NJ",
    "sg:tags":[
        "eating"
    ],
    "wof:name":"Takei Sushi",
    "wof:placetype":"venue"
},
  "geometry": {"coordinates":[-73.95974,40.971237],"type":"Point"}
}