{
  "type": "Feature",
  "properties": {
    "addr:full":"1140 State Rte 72 Manahawkin NJ 08050",
    "addr:housenumber":"1140",
    "addr:postcode":"08050",
    "addr:street":"State Rte 72",
    "iso:country":"US",
    "sg:address":"1140 State Rte 72",
    "sg:city":"Manahawkin",
    "sg:classifiers":[
        {
            "category":"Health Services",
            "subcategory":"Medical Lab",
            "type":"Services"
        }
    ],
    "sg:phone":"+1 609 978 8932",
    "sg:postcode":"08050",
    "sg:province":"NJ",
    "sg:tags":[
        "x"
    ],
    "wof:name":"Radiology Dept Sthrn Cnty Hosp",
    "wof:placetype":"venue"
},
  "geometry": {"coordinates":[-74.28235599999999,39.715342],"type":"Point"}
}