{
  "type": "Feature",
  "properties": {
    "addr:full":"165 Sweetmans Ln Englishtown NJ 07726",
    "addr:housenumber":"165",
    "addr:postcode":"07726",
    "addr:street":"Sweetmans Ln",
    "iso:country":"US",
    "sg:address":"165 Sweetmans Ln",
    "sg:city":"Englishtown",
    "sg:classifiers":[
        {
            "category":"Building & Trades",
            "subcategory":"Landscaping Services",
            "type":"Services"
        }
    ],
    "sg:phone":"+1 732 625 1808",
    "sg:postcode":"07726",
    "sg:province":"NJ",
    "sg:tags":[
        "landscape"
    ],
    "wof:name":"Topshelf Landscaping",
    "wof:placetype":"venue"
},
  "geometry": {"coordinates":[-74.36685799999999,40.236081],"type":"Point"}
}