{
  "type": "Feature",
  "properties": {
    "iso:country":"US",
    "sg:address":"631 Elizabeth Ave",
    "sg:city":"Elizabeth",
    "sg:phone":"+1 908 351 1870",
    "sg:postcode":"07206",
    "sg:province":"NJ",
    "sg:tags":[
        "equipment",
        "commercial"
    ],
    "wof:name":"Alban Supply Co Inc",
    "wof:placetype":"venue"
},
  "geometry": {"coordinates":[-74.20106,40.657366],"type":"Point"}
}