{
  "type": "Feature",
  "properties": {
    "addr:full":"14 Mapleton Rd Old Bridge NJ 08857",
    "addr:housenumber":"14",
    "addr:postcode":"08857",
    "addr:street":"Mapleton Rd",
    "iso:country":"US",
    "sg:address":"14 Mapleton Rd",
    "sg:city":"Old Bridge",
    "sg:classifiers":[
        {
            "category":"Professional",
            "type":"Services"
        }
    ],
    "sg:phone":"+1 732 521 3500",
    "sg:postcode":"08857",
    "sg:province":"NJ",
    "sg:tags":[
        "establishment"
    ],
    "wof:name":"Woodhaven Village",
    "wof:placetype":"venue"
},
  "geometry": {"coordinates":[-74.35297300000001,40.350088],"type":"Point"}
}