{
  "type": "Feature",
  "properties": {
    "addr:full":"110 Barclay Walk Cherry Hill NJ 08034",
    "addr:housenumber":"110",
    "addr:postcode":"08034",
    "addr:street":"Barclay Walk",
    "iso:country":"US",
    "sg:address":"110 Barclay Walk",
    "sg:city":"Cherry Hill",
    "sg:classifiers":[
        {
            "category":"Real Estate",
            "subcategory":"Real Estate Services",
            "type":"Services"
        }
    ],
    "sg:phone":"+1 609 261 0484",
    "sg:postcode":"08034",
    "sg:province":"NJ",
    "sg:tags":[
        "company",
        "title"
    ],
    "sg:website":"www.congresstitle.com",
    "wof:name":"Congress Title",
    "wof:placetype":"venue"
},
  "geometry": {"coordinates":[-74.996313,39.911493],"type":"Point"}
}