{
  "type": "Feature",
  "properties": {
    "iso:country":"US",
    "sg:address":"211 Mountain Ave",
    "sg:city":"Springfield",
    "sg:classifiers":[
        {
            "category":"Shopping",
            "subcategory":"Pharmacy",
            "type":"Retail Goods"
        }
    ],
    "sg:phone":"+1 973 376 7724",
    "sg:postcode":"07081",
    "sg:province":"NJ",
    "sg:website":"www.walgreens.com",
    "wof:name":"Walgreen's District Office",
    "wof:placetype":"venue"
},
  "geometry": {"coordinates":[-74.316968,40.70508],"type":"Point"}
}