{
  "type": "Feature",
  "properties": {
    "addr:full":"3 Sommers Ave Somers Point NJ 08244",
    "addr:housenumber":"3",
    "addr:postcode":"08244",
    "addr:street":"Sommers Ave",
    "iso:country":"US",
    "sg:address":"3 Sommers Ave",
    "sg:city":"Somers Point",
    "sg:classifiers":[
        {
            "category":"Personal",
            "subcategory":"Beauty Salon",
            "type":"Services"
        }
    ],
    "sg:phone":"+1 609 814 1696",
    "sg:postcode":"08244",
    "sg:province":"NJ",
    "sg:tags":[
        "shop"
    ],
    "wof:name":"Yankee Clipper Landscapin",
    "wof:placetype":"venue"
},
  "geometry": {"coordinates":[-74.59563900000001,39.309896],"type":"Point"}
}