{
  "type": "Feature",
  "properties": {
    "iso:country":"US",
    "sg:address":"10 Kimberly Ct",
    "sg:city":"Red Bank",
    "sg:classifiers":[
        {
            "category":"Building & Trades",
            "subcategory":"Construction",
            "type":"Services"
        }
    ],
    "sg:phone":"+1 732 741 0923",
    "sg:postcode":"07747",
    "sg:province":"NJ",
    "sg:tags":[
        "masonry",
        "contractor"
    ],
    "wof:name":"S & N Concrete & Asphalt",
    "wof:placetype":"venue"
},
  "geometry": {"coordinates":[-74.239906,40.405597],"type":"Point"}
}