{
  "type": "Feature",
  "properties": {
    "addr:full":"420 Totowa Rd Totowa NJ 07512",
    "addr:housenumber":"420",
    "addr:postcode":"07512",
    "addr:street":"Totowa Rd",
    "iso:country":"US",
    "sg:address":"420 Totowa Rd",
    "sg:city":"Totowa",
    "sg:classifiers":[
        {
            "category":"Real Estate",
            "subcategory":"Real Estate Agent",
            "type":"Services"
        }
    ],
    "sg:phone":"+1   ",
    "sg:postcode":"07512",
    "sg:province":"NJ",
    "wof:name":"Century 21",
    "wof:placetype":"venue"
},
  "geometry": {"coordinates":[-74.21344999999999,40.904489],"type":"Point"}
}