{
  "type": "Feature",
  "properties": {
    "addr:full":"235 Ellison St Paterson NJ 07501",
    "addr:housenumber":"235",
    "addr:postcode":"07501",
    "addr:street":"Ellison St",
    "iso:country":"US",
    "sg:address":"235 Ellison St",
    "sg:city":"Paterson",
    "sg:classifiers":[
        {
            "category":"Wholesale",
            "subcategory":"Scrap",
            "type":"Manufacturing & Wholesale Goods"
        }
    ],
    "sg:phone":"+1 973 279 4190",
    "sg:postcode":"07501",
    "sg:province":"NJ",
    "sg:tags":[
        "cloth",
        "wiping"
    ],
    "sg:website":"www.ndiproducts.com",
    "wof:name":"Nosaj Disposables Inc",
    "wof:placetype":"venue"
},
  "geometry": {"coordinates":[-74.166387,40.917189],"type":"Point"}
}