{
  "type": "Feature",
  "properties": {
    "iso:country":"US",
    "sg:address":"2 Walpack Flatbrook Rd",
    "sg:city":"Layton",
    "sg:classifiers":[
        {
            "category":"Government",
            "subcategory":"Office",
            "type":"Public Place"
        }
    ],
    "sg:phone":"+1   ",
    "sg:postcode":"07851",
    "sg:province":"NJ",
    "sg:tags":[
        "national",
        "security"
    ],
    "wof:name":"National Park Service",
    "wof:placetype":"venue"
},
  "geometry": {"coordinates":[-74.89503499999999,41.146555],"type":"Point"}
}