{
  "type": "Feature",
  "properties": {
    "iso:country":"US",
    "sg:address":"339 Valley Rd",
    "sg:city":"Hillsborough",
    "sg:classifiers":[
        {
            "category":"Home & Garden",
            "subcategory":"Garden Supply",
            "type":"Retail Goods"
        }
    ],
    "sg:phone":"+1 908 369 1003",
    "sg:postcode":"08844",
    "sg:province":"NJ",
    "sg:tags":[
        "sprinkler"
    ],
    "wof:name":"Jaynes Landscaping & Irrgtn",
    "wof:placetype":"venue"
},
  "geometry": {"coordinates":[-74.65298199999999,40.527442],"type":"Point"}
}