{
  "type": "Feature",
  "properties": {
    "addr:full":"231 Lucas Ln Voorhees NJ 08043",
    "addr:housenumber":"231",
    "addr:postcode":"08043",
    "addr:street":"Lucas Ln",
    "iso:country":"US",
    "sg:address":"231 Lucas Ln",
    "sg:city":"Voorhees",
    "sg:classifiers":[
        {
            "category":"Sports & Exercise",
            "subcategory":"Gym",
            "type":"Entertainment"
        }
    ],
    "sg:phone":"+1 856 772 1957",
    "sg:postcode":"08043",
    "sg:province":"NJ",
    "sg:tags":[
        "fitness",
        "physical",
        "facility"
    ],
    "wof:name":"Dynasty Fitness Corp",
    "wof:placetype":"venue"
},
  "geometry": {"coordinates":[-74.999138,39.844566],"type":"Point"}
}