{
  "type": "Feature",
  "properties": {
    "addr:full":"183 Garfield Ave Kearny NJ 07032",
    "addr:housenumber":"183",
    "addr:postcode":"07032",
    "addr:street":"Garfield Ave",
    "iso:country":"US",
    "sg:address":"183 Garfield Ave",
    "sg:city":"Kearny",
    "sg:classifiers":[
        {
            "category":"Manufacturing",
            "subcategory":"Metals",
            "type":"Manufacturing & Wholesale Goods"
        }
    ],
    "sg:phone":"+1 201 997 7744",
    "sg:postcode":"07032",
    "sg:province":"NJ",
    "sg:tags":[
        "polishing",
        "finisher"
    ],
    "wof:name":"Dynasty Metals Inc",
    "wof:placetype":"venue"
},
  "geometry": {"coordinates":[-74.141064,40.758316],"type":"Point"}
}