{
  "type": "Feature",
  "properties": {
    "iso:country":"US",
    "sg:address":"14 Julian Pl",
    "sg:city":"Elizabeth",
    "sg:classifiers":[
        {
            "category":"Restaurant",
            "type":"Food & Drink"
        }
    ],
    "sg:phone":"+1 908 353 3733",
    "sg:postcode":"07208",
    "sg:province":"NJ",
    "wof:name":"Michelino's Midtown Cafe",
    "wof:placetype":"venue"
},
  "geometry": {"coordinates":[-74.217332,40.66752],"type":"Point"}
}