{
  "type": "Feature",
  "properties": {
    "addr:full":"411 Jerusalem Rd Scotch Plains NJ 07076",
    "addr:housenumber":"411",
    "addr:postcode":"07076",
    "addr:street":"Jerusalem Rd",
    "iso:country":"US",
    "sg:address":"411 Jerusalem Rd",
    "sg:city":"Scotch Plains",
    "sg:classifiers":[
        {
            "category":"Professional",
            "subcategory":"Business Services",
            "type":"Services"
        }
    ],
    "sg:phone":"+1   ",
    "sg:postcode":"07076",
    "sg:province":"NJ",
    "wof:name":"Rivex Group Inc",
    "wof:placetype":"venue"
},
  "geometry": {"coordinates":[-74.38321500000001,40.661945],"type":"Point"}
}