{
  "type": "Feature",
  "properties": {
    "iso:country":"US",
    "sg:address":"36 Nesbitt St",
    "sg:city":"Newark",
    "sg:classifiers":[
        {
            "category":"Autos & Motor Vehicles",
            "subcategory":"Fuel & Gas Station",
            "type":"Retail Goods"
        }
    ],
    "sg:phone":"+1 973 624 7333",
    "sg:postcode":"07103",
    "sg:province":"NJ",
    "sg:tags":[
        "repair",
        "oil"
    ],
    "wof:name":"Nesbitt Auto & Truck Repair",
    "wof:placetype":"venue"
},
  "geometry": {"coordinates":[-74.17890199999999,40.747101],"type":"Point"}
}