{
  "type": "Feature",
  "properties": {
    "iso:country":"US",
    "sg:address":"31 Fine Rd",
    "sg:city":"High Bridge",
    "sg:classifiers":[
        {
            "category":"Home & Garden",
            "subcategory":"Carpets & Floor Coverings",
            "type":"Retail Goods"
        }
    ],
    "sg:phone":"+1   ",
    "sg:postcode":"08829",
    "sg:province":"NJ",
    "wof:name":"Carpets By Bob",
    "wof:placetype":"venue"
},
  "geometry": {"coordinates":[-74.898668,40.676511],"type":"Point"}
}