{
  "type": "Feature",
  "properties": {
    "addr:full":"510 US Hwy 9 Waretown NJ 08758",
    "addr:housenumber":"510",
    "addr:postcode":"08758",
    "addr:street":"Us Hwy 9",
    "iso:country":"US",
    "sg:address":"510 US Hwy 9",
    "sg:city":"Waretown",
    "sg:classifiers":[
        {
            "category":"Building & Trades",
            "subcategory":"Plumbing",
            "type":"Services"
        }
    ],
    "sg:phone":"+1 609 242 0900",
    "sg:postcode":"08758",
    "sg:province":"NJ",
    "sg:tags":[
        "heating",
        "contractor"
    ],
    "wof:name":"Weather Watch Heating Cooling",
    "wof:placetype":"venue"
},
  "geometry": {"coordinates":[-74.196186,39.793701],"type":"Point"}
}