{
  "type": "Feature",
  "properties": {
    "addr:full":"233 N Main St Cape May Court House NJ 08210",
    "addr:housenumber":"233",
    "addr:postcode":"08210",
    "addr:street":"N Main St Cape May",
    "iso:country":"US",
    "sg:address":"233 N Main St",
    "sg:city":"Cape May Court House",
    "sg:classifiers":[
        {
            "category":"Autos & Motor Vehicles",
            "subcategory":"Fuel & Gas Station",
            "type":"Retail Goods"
        }
    ],
    "sg:phone":"+1 609 465 2880",
    "sg:postcode":"08210",
    "sg:province":"NJ",
    "wof:name":"Courthouse Shell",
    "wof:placetype":"venue"
},
  "geometry": {"coordinates":[-74.819801,39.086601],"type":"Point"}
}