{
  "type": "Feature",
  "properties": {
    "iso:country":"US",
    "sg:address":"Jfk Way",
    "sg:city":"Willingboro",
    "sg:classifiers":[
        {
            "category":"Shopping",
            "subcategory":"Music",
            "type":"Retail Goods"
        }
    ],
    "sg:phone":"+1 609 871 6927",
    "sg:postcode":"08046",
    "sg:province":"NJ",
    "sg:tags":[
        "dvd's"
    ],
    "wof:name":"Sound Express",
    "wof:placetype":"venue"
},
  "geometry": {"coordinates":[-74.885498,40.0271],"type":"Point"}
}