{
  "type": "Feature",
  "properties": {
    "addr:full":"415 Morris Ave Elizabeth NJ 07208",
    "addr:housenumber":"415",
    "addr:postcode":"07208",
    "addr:street":"Morris Ave",
    "iso:country":"US",
    "sg:address":"415 Morris Ave",
    "sg:city":"Elizabeth",
    "sg:classifiers":[
        {
            "category":"Health Services",
            "subcategory":"Doctor",
            "type":"Services"
        }
    ],
    "sg:phone":"+1   ",
    "sg:postcode":"07208",
    "sg:province":"NJ",
    "sg:tags":[
        "medical"
    ],
    "wof:name":"Physician Radiology Inc",
    "wof:placetype":"venue"
},
  "geometry": {"coordinates":[-74.221001,40.67142],"type":"Point"}
}