{
  "type": "Feature",
  "properties": {
    "addr:full":"161 Columbia Ave Jersey City NJ 07307",
    "addr:housenumber":"161",
    "addr:postcode":"07307",
    "addr:street":"Columbia Ave",
    "iso:country":"US",
    "sg:address":"161 Columbia Ave",
    "sg:city":"Jersey City",
    "sg:classifiers":[
        {
            "category":"Building & Trades",
            "subcategory":"Electrical",
            "type":"Services"
        }
    ],
    "sg:phone":"+1 201 670 8270",
    "sg:postcode":"07307",
    "sg:province":"NJ",
    "sg:tags":[
        "payphone",
        "installation"
    ],
    "wof:name":"Hts",
    "wof:placetype":"venue"
},
  "geometry": {"coordinates":[-74.052627,40.754616],"type":"Point"}
}