{
  "type": "Feature",
  "properties": {
    "addr:full":"11 Cedar Mill Ln Mount Holly NJ 08060",
    "addr:housenumber":"11",
    "addr:postcode":"08060",
    "addr:street":"Cedar Mill Ln",
    "iso:country":"US",
    "sg:address":"11 Cedar Mill Ln",
    "sg:city":"Mount Holly",
    "sg:classifiers":[
        {
            "category":"Organizations",
            "subcategory":"Religious Organization",
            "type":"Services"
        }
    ],
    "sg:phone":"+1 609 261 1711",
    "sg:postcode":"08060",
    "sg:province":"NJ",
    "wof:name":"Kraft Jas H Rev",
    "wof:placetype":"venue"
},
  "geometry": {"coordinates":[-74.769997,39.997398],"type":"Point"}
}