{
  "type": "Feature",
  "properties": {
    "addr:full":"3501 Princeton Pike Lawrenceville NJ 08648",
    "addr:housenumber":"3501",
    "addr:postcode":"08648",
    "addr:street":"Princeton Pike",
    "iso:country":"US",
    "sg:address":"3501 Princeton Pike",
    "sg:city":"Lawrenceville",
    "sg:classifiers":[
        {
            "category":"Social Services",
            "subcategory":"Child Care",
            "type":"Services"
        },
        {
            "category":"Food & Beverages",
            "subcategory":"Fruits & Vegetables",
            "type":"Retail Goods"
        }
    ],
    "sg:phone":"+1 609 896 1230",
    "sg:postcode":"08648",
    "sg:province":"NJ",
    "sg:tags":[
        "produce",
        "day"
    ],
    "wof:name":"Little Acres Too Farm Market",
    "wof:placetype":"venue"
},
  "geometry": {"coordinates":[-74.696606,40.306418],"type":"Point"}
}