{
  "type": "Feature",
  "properties": {
    "iso:country":"US",
    "sg:address":"24 Prescott Ave",
    "sg:city":"Montclair",
    "sg:classifiers":[
        {
            "category":"Restaurant",
            "type":"Food & Drink"
        }
    ],
    "sg:phone":"+1   ",
    "sg:postcode":"07042",
    "sg:province":"NJ",
    "sg:tags":[
        "eating"
    ],
    "wof:name":"In Good Taste",
    "wof:placetype":"venue"
},
  "geometry": {"coordinates":[-74.19696500000001,40.828094],"type":"Point"}
}