{
  "type": "Feature",
  "properties": {
    "addr:full":"934 Maurice River Pkwy Vineland NJ 08360",
    "addr:housenumber":"934",
    "addr:postcode":"08360",
    "addr:street":"Maurice River Pkwy",
    "iso:country":"US",
    "sg:address":"934 Maurice River Pkwy",
    "sg:city":"Vineland",
    "sg:classifiers":[
        {
            "category":"Autos & Motor Vehicles",
            "subcategory":"Motorcycle Sales",
            "type":"Retail Goods"
        }
    ],
    "sg:phone":"+1 856 692 6421",
    "sg:postcode":"08360",
    "sg:province":"NJ",
    "sg:tags":[
        "scooter"
    ],
    "wof:name":"Tuff Buff Polishing",
    "wof:placetype":"venue"
},
  "geometry": {"coordinates":[-75.071656,39.50354],"type":"Point"}
}