{
  "type": "Feature",
  "properties": {
    "addr:full":"238 Center St Elmer NJ 08318",
    "addr:housenumber":"238",
    "addr:postcode":"08318",
    "addr:street":"Center St",
    "iso:country":"US",
    "sg:address":"238 Center St",
    "sg:city":"Elmer",
    "sg:classifiers":[
        {
            "category":"Building & Trades",
            "subcategory":"Cleaning & Sanitation",
            "type":"Services"
        }
    ],
    "sg:phone":"+1   ",
    "sg:postcode":"08318",
    "sg:province":"NJ",
    "sg:tags":[
        "maintenance"
    ],
    "wof:name":"Mason Cleaning Service",
    "wof:placetype":"venue"
},
  "geometry": {"coordinates":[-75.17311100000001,39.588864],"type":"Point"}
}