{
  "type": "Feature",
  "properties": {
    "addr:full":"718 Main St Boonton NJ 07005",
    "addr:housenumber":"718",
    "addr:postcode":"07005",
    "addr:street":"Main St",
    "iso:country":"US",
    "sg:address":"718 Main St",
    "sg:city":"Boonton",
    "sg:classifiers":[
        {
            "category":"Shopping",
            "subcategory":"Musical Instruments",
            "type":"Retail Goods"
        }
    ],
    "sg:phone":"+1   ",
    "sg:postcode":"07005",
    "sg:province":"NJ",
    "sg:tags":[
        "music",
        "store"
    ],
    "wof:name":"Underground Music Store",
    "wof:placetype":"venue"
},
  "geometry": {"coordinates":[-74.41203,40.905398],"type":"Point"}
}