{
  "type": "Feature",
  "properties": {
    "addr:full":"175 Clerk St Jersey City NJ 07305",
    "addr:housenumber":"175",
    "addr:postcode":"07305",
    "addr:street":"Clerk St",
    "iso:country":"US",
    "sg:address":"175 Clerk St",
    "sg:city":"Jersey City",
    "sg:classifiers":[
        {
            "category":"Organizations",
            "subcategory":"Religious Organization",
            "type":"Services"
        }
    ],
    "sg:phone":"+1 201 324 1005",
    "sg:postcode":"07305",
    "sg:province":"NJ",
    "sg:tags":[
        "church"
    ],
    "wof:name":"Lighthouse Baptist Church",
    "wof:placetype":"venue"
},
  "geometry": {"coordinates":[-74.074153,40.711203],"type":"Point"}
}