{
  "type": "Feature",
  "properties": {
    "addr:full":"343 South St Newark NJ 07105",
    "addr:housenumber":"343",
    "addr:postcode":"07105",
    "addr:street":"South St",
    "iso:country":"US",
    "sg:address":"343 South St",
    "sg:city":"Newark",
    "sg:classifiers":[
        {
            "category":"Retail",
            "subcategory":"Auto Repair",
            "type":"Services"
        }
    ],
    "sg:phone":"+1 973 491 2872",
    "sg:postcode":"07105",
    "sg:province":"NJ",
    "sg:tags":[
        "repairing",
        "automobile"
    ],
    "wof:name":"Jefferson Auto Repair",
    "wof:placetype":"venue"
},
  "geometry": {"coordinates":[-74.162487,40.718876],"type":"Point"}
}