{
  "type": "Feature",
  "properties": {
    "addr:full":"63 Cliffwood Ave Cliffwood NJ 07721",
    "addr:housenumber":"63",
    "addr:postcode":"07721",
    "addr:street":"Cliffwood Ave",
    "iso:country":"US",
    "sg:address":"63 Cliffwood Ave",
    "sg:city":"Cliffwood",
    "sg:classifiers":[
        {
            "category":"Organizations",
            "subcategory":"Religious Organization",
            "type":"Services"
        }
    ],
    "sg:phone":"+1   ",
    "sg:postcode":"07721",
    "sg:province":"NJ",
    "wof:name":"Assembly of God",
    "wof:placetype":"venue"
},
  "geometry": {"coordinates":[-74.243488,40.431342],"type":"Point"}
}