{
  "type": "Feature",
  "properties": {
    "addr:full":"2522 45th St Pennsauken NJ 08110",
    "addr:housenumber":"2522",
    "addr:postcode":"08110",
    "addr:street":"45Th St",
    "iso:country":"US",
    "sg:address":"2522 45th St",
    "sg:city":"Pennsauken",
    "sg:classifiers":[
        {
            "category":"Wholesale",
            "subcategory":"Construction Materials",
            "type":"Manufacturing & Wholesale Goods"
        }
    ],
    "sg:phone":"+1 856 665 1231",
    "sg:postcode":"08110",
    "sg:province":"NJ",
    "wof:name":"Henry Montano",
    "wof:placetype":"venue"
},
  "geometry": {"coordinates":[-75.064804,39.951387],"type":"Point"}
}