{
  "type": "Feature",
  "properties": {
    "addr:full":"100 Race St Belvidere NJ 07823",
    "addr:housenumber":"100",
    "addr:postcode":"07823",
    "addr:street":"Race St",
    "iso:country":"US",
    "sg:address":"100 Race St",
    "sg:city":"Belvidere",
    "sg:classifiers":[
        {
            "category":"Organizations",
            "subcategory":"Community Association",
            "type":"Services"
        },
        {
            "category":"Social Services",
            "type":"Services"
        }
    ],
    "sg:phone":"+1 908 475 8186",
    "sg:postcode":"07823",
    "sg:province":"NJ",
    "sg:tags":[
        "youth",
        "center"
    ],
    "wof:name":"Boy Scout Troop 141",
    "wof:placetype":"venue"
},
  "geometry": {"coordinates":[-75.071361,40.828663],"type":"Point"}
}