{
  "type": "Feature",
  "properties": {
    "addr:full":"319 22nd St S Brigantine NJ 08203",
    "addr:housenumber":"319",
    "addr:postcode":"08203",
    "addr:street":"22Nd St S",
    "iso:country":"US",
    "sg:address":"319 22nd St S",
    "sg:city":"Brigantine",
    "sg:classifiers":[
        {
            "category":"Building & Trades",
            "subcategory":"Landscaping Services",
            "type":"Services"
        }
    ],
    "sg:phone":"+1 609 266 0449",
    "sg:postcode":"08203",
    "sg:province":"NJ",
    "wof:name":"Brigantine Island Lawn Works",
    "wof:placetype":"venue"
},
  "geometry": {"coordinates":[-74.37733,39.397181],"type":"Point"}
}