{
  "type": "Feature",
  "properties": {
    "addr:full":"735 Shunpike Rd Cape May NJ 08204",
    "addr:housenumber":"735",
    "addr:postcode":"08204",
    "addr:street":"Shunpike Rd",
    "iso:country":"US",
    "sg:address":"735 Shunpike Rd",
    "sg:city":"Cape May",
    "sg:classifiers":[
        {
            "category":"Professional",
            "subcategory":"Business Services",
            "type":"Services"
        }
    ],
    "sg:phone":"+1   ",
    "sg:postcode":"08204",
    "sg:province":"NJ",
    "wof:name":"Accu Spec",
    "wof:placetype":"venue"
},
  "geometry": {"coordinates":[-74.91637299999999,38.986153],"type":"Point"}
}