{
  "type": "Feature",
  "properties": {
    "iso:country":"US",
    "sg:address":"6 Ferruzza Dr",
    "sg:city":"Spring Valley",
    "sg:classifiers":[
        {
            "category":"Wholesale",
            "subcategory":"Durable Goods & Equipment",
            "type":"Manufacturing & Wholesale Goods"
        }
    ],
    "sg:phone":"+1 845 426 7673",
    "sg:postcode":"10977",
    "sg:province":"NY",
    "sg:tags":[
        "laser"
    ],
    "wof:name":"Green-Rose Lasers",
    "wof:placetype":"venue"
},
  "geometry": {"coordinates":[-74.061007,41.076666],"type":"Point"}
}