{
  "type": "Feature",
  "properties": {
    "iso:country":"US",
    "sg:address":"10 Continental Dr",
    "sg:city":"Sparta",
    "sg:classifiers":[
        {
            "category":"Professional",
            "subcategory":"Computer Services",
            "type":"Services"
        }
    ],
    "sg:phone":"+1 973 863 2300",
    "sg:postcode":"07871",
    "sg:province":"NJ",
    "sg:tags":[
        "related"
    ],
    "wof:name":"John M Dodge Inc",
    "wof:placetype":"venue"
},
  "geometry": {"coordinates":[-74.637556,41.000696],"type":"Point"}
}