{
  "type": "Feature",
  "properties": {
    "addr:full":"429 Wall St Princeton NJ 08540",
    "addr:housenumber":"429",
    "addr:postcode":"08540",
    "addr:street":"Wall St",
    "iso:country":"US",
    "sg:address":"429 Wall St",
    "sg:city":"Princeton",
    "sg:classifiers":[
        {
            "category":"Personal",
            "subcategory":"Beauty Salon",
            "type":"Services"
        }
    ],
    "sg:phone":"+1 609 497 4747",
    "sg:postcode":"08540",
    "sg:province":"NJ",
    "sg:tags":[
        "shop"
    ],
    "wof:name":"Radiant Image Salon",
    "wof:placetype":"venue"
},
  "geometry": {"coordinates":[-74.649761,40.397063],"type":"Point"}
}