{
  "type": "Feature",
  "properties": {
    "addr:full":"207 Monmouth Rd Oakhurst NJ 07755",
    "addr:housenumber":"207",
    "addr:postcode":"07755",
    "addr:street":"Monmouth Rd",
    "iso:country":"US",
    "sg:address":"207 Monmouth Rd",
    "sg:city":"Oakhurst",
    "sg:classifiers":[
        {
            "category":"Autos & Motor Vehicles",
            "subcategory":"Fuel & Gas Station",
            "type":"Retail Goods"
        }
    ],
    "sg:phone":"+1 732 870 1244",
    "sg:postcode":"07755",
    "sg:province":"NJ",
    "sg:tags":[
        "oil"
    ],
    "wof:name":"West End Coastal",
    "wof:placetype":"venue"
},
  "geometry": {"coordinates":[-74.011398,40.258601],"type":"Point"}
}