{
  "type": "Feature",
  "properties": {
    "iso:country":"US",
    "sg:address":"340 E Bird Village Rd",
    "sg:city":"Jackson",
    "sg:classifiers":[
        {
            "category":"Insurance",
            "subcategory":"Insurance Agent",
            "type":"Services"
        }
    ],
    "sg:phone":"+1   ",
    "sg:postcode":"08527",
    "sg:province":"NJ",
    "sg:tags":[
        "information",
        "technology",
        "placement"
    ],
    "wof:name":"Provisions Solutions Inc",
    "wof:placetype":"venue"
},
  "geometry": {"coordinates":[-74.377154,40.119152],"type":"Point"}
}