{
  "type": "Feature",
  "properties": {
    "addr:full":"77 Eddystone Way Mount Laurel NJ 08054",
    "addr:housenumber":"77",
    "addr:postcode":"08054",
    "addr:street":"Eddystone Way",
    "iso:country":"US",
    "sg:address":"77 Eddystone Way",
    "sg:city":"Mount Laurel",
    "sg:classifiers":[
        {
            "category":"Shopping",
            "subcategory":"Clothing, Apparel, & Fashions",
            "type":"Retail Goods"
        }
    ],
    "sg:phone":"+1   ",
    "sg:postcode":"08054",
    "sg:province":"NJ",
    "sg:tags":[
        "wear"
    ],
    "wof:name":"L & A Enterprises",
    "wof:placetype":"venue"
},
  "geometry": {"coordinates":[-74.913948,39.933103],"type":"Point"}
}