{
  "type": "Feature",
  "properties": {
    "addr:full":"33 Watchung Ave Montclair NJ 07043",
    "addr:housenumber":"33",
    "addr:postcode":"07043",
    "addr:street":"Watchung Ave",
    "iso:country":"US",
    "sg:address":"33 Watchung Ave",
    "sg:city":"Montclair",
    "sg:classifiers":[
        {
            "category":"Sports & Exercise",
            "subcategory":"Gym",
            "type":"Entertainment"
        }
    ],
    "sg:phone":"+1   ",
    "sg:postcode":"07043",
    "sg:province":"NJ",
    "sg:tags":[
        "fitness",
        "physical",
        "facility"
    ],
    "wof:name":"Movement Place",
    "wof:placetype":"venue"
},
  "geometry": {"coordinates":[-74.211102,40.832708],"type":"Point"}
}