{
  "type": "Feature",
  "properties": {
    "iso:country":"US",
    "sg:address":"142 Morgan Pl",
    "sg:city":"North Arlington",
    "sg:classifiers":[
        {
            "category":"Building & Trades",
            "subcategory":"Construction",
            "type":"Services"
        }
    ],
    "sg:phone":"+1 201 991 2618",
    "sg:postcode":"07031",
    "sg:province":"NJ",
    "sg:tags":[
        "stone",
        "masonry",
        "work",
        "setting",
        "other"
    ],
    "wof:name":"Dumac Inc",
    "wof:placetype":"venue"
},
  "geometry": {"coordinates":[-74.13326499999999,40.785667],"type":"Point"}
}