{
  "type": "Feature",
  "properties": {
    "iso:country":"US",
    "sg:address":"530 James St",
    "sg:city":"Lakewood",
    "sg:classifiers":[
        {
            "category":"Building & Trades",
            "subcategory":"Pest Control",
            "type":"Services"
        }
    ],
    "sg:phone":"+1 732 364 7440",
    "sg:postcode":"08701",
    "sg:province":"NJ",
    "wof:name":"A Abbott Svc Co",
    "wof:placetype":"venue"
},
  "geometry": {"coordinates":[-74.238124,40.078817],"type":"Point"}
}