{
  "type": "Feature",
  "properties": {
    "addr:full":"901 Aura Rd Monroeville NJ 08343",
    "addr:housenumber":"901",
    "addr:postcode":"08343",
    "addr:street":"Aura Rd",
    "iso:country":"US",
    "sg:address":"901 Aura Rd",
    "sg:city":"Monroeville",
    "sg:classifiers":[
        {
            "category":"Organizations",
            "subcategory":"Religious Organization",
            "type":"Services"
        }
    ],
    "sg:phone":"+1 856 881 3571",
    "sg:postcode":"08343",
    "sg:province":"NJ",
    "wof:name":"Aura United Methodist Church",
    "wof:placetype":"venue"
},
  "geometry": {"coordinates":[-75.13310799999999,39.664821],"type":"Point"}
}