{
  "type": "Feature",
  "properties": {
    "iso:country":"US",
    "sg:address":"721 Hylton Rd",
    "sg:city":"Pennsauken",
    "sg:classifiers":[
        {
            "category":"Wholesale",
            "subcategory":"Medical Equipment & Supplies",
            "type":"Manufacturing & Wholesale Goods"
        }
    ],
    "sg:phone":"+1 856 303 1880",
    "sg:postcode":"08110",
    "sg:province":"NJ",
    "sg:tags":[
        "hospital"
    ],
    "wof:name":"Recovercare Inc",
    "wof:placetype":"venue"
},
  "geometry": {"coordinates":[-75.027963,39.991941],"type":"Point"}
}