{
  "type": "Feature",
  "properties": {
    "iso:country":"US",
    "sg:address":"347 Elizabeth Ave",
    "sg:city":"Somerset",
    "sg:classifiers":[
        {
            "category":"Professional",
            "subcategory":"Computer Services",
            "type":"Services"
        }
    ],
    "sg:phone":"+1 732 302 1701",
    "sg:postcode":"08873",
    "sg:province":"NJ",
    "sg:tags":[
        "prepackaged",
        "software"
    ],
    "wof:name":"Payplus Software",
    "wof:placetype":"venue"
},
  "geometry": {"coordinates":[-74.532157,40.550325],"type":"Point"}
}