{
  "type": "Feature",
  "properties": {
    "iso:country":"US",
    "sg:address":"501 Central Ave",
    "sg:city":"Westfield",
    "sg:classifiers":[
        {
            "category":"Home & Garden",
            "subcategory":"Carpets & Floor Coverings",
            "type":"Retail Goods"
        }
    ],
    "sg:phone":"+1 908 789 9099",
    "sg:postcode":"07090",
    "sg:province":"NJ",
    "sg:tags":[
        "linoleum",
        "dealer",
        "rug"
    ],
    "wof:name":"Hansel's Carpets",
    "wof:placetype":"venue"
},
  "geometry": {"coordinates":[-74.34053,40.64778],"type":"Point"}
}