{
  "type": "Feature",
  "properties": {
    "addr:full":"2530 Plainfield Ave Scotch Plains NJ 07076",
    "addr:housenumber":"2530",
    "addr:postcode":"07076",
    "addr:street":"Plainfield Ave",
    "iso:country":"US",
    "sg:address":"2530 Plainfield Ave",
    "sg:city":"Scotch Plains",
    "sg:classifiers":[
        {
            "category":"Building & Trades",
            "subcategory":"Cleaning & Sanitation",
            "type":"Services"
        },
        {
            "category":"Building & Trades",
            "subcategory":"Landscaping Services",
            "type":"Services"
        }
    ],
    "sg:phone":"+1 908 233 0727",
    "sg:postcode":"07076",
    "sg:province":"NJ",
    "sg:tags":[
        "snow",
        "removal"
    ],
    "wof:name":"Jo-Mic Landscaping Inc",
    "wof:placetype":"venue"
},
  "geometry": {"coordinates":[-74.376085,40.656463],"type":"Point"}
}