{
  "type": "Feature",
  "properties": {
    "iso:country":"US",
    "sg:address":"12 Bridle Way",
    "sg:city":"Sussex",
    "sg:classifiers":[
        {
            "category":"Professional",
            "type":"Services"
        }
    ],
    "sg:phone":"+1   ",
    "sg:postcode":"07461",
    "sg:province":"NJ",
    "wof:name":"Greenskeeper Touch LLC",
    "wof:placetype":"venue"
},
  "geometry": {"coordinates":[-74.686273,41.201602],"type":"Point"}
}