{
  "type": "Feature",
  "properties": {
    "iso:country":"US",
    "sg:address":"701 Newark Ave",
    "sg:city":"Elizabeth",
    "sg:classifiers":[
        {
            "category":"Health Services",
            "subcategory":"Chiropractor",
            "type":"Services"
        }
    ],
    "sg:phone":"+1 908 355 6460",
    "sg:postcode":"07208",
    "sg:province":"NJ",
    "wof:name":"Spine Care Chiropractor",
    "wof:placetype":"venue"
},
  "geometry": {"coordinates":[-74.20962,40.679932],"type":"Point"}
}