{
  "type": "Feature",
  "properties": {
    "addr:full":"277 Broadway Hillsdale NJ 07642",
    "addr:housenumber":"277",
    "addr:postcode":"07642",
    "addr:street":"Broadway",
    "iso:country":"US",
    "sg:address":"277 Broadway",
    "sg:city":"Hillsdale",
    "sg:classifiers":[
        {
            "category":"Professional",
            "subcategory":"Business Services",
            "type":"Services"
        }
    ],
    "sg:phone":"+1 201 594 1200",
    "sg:postcode":"07642",
    "sg:province":"NJ",
    "sg:tags":[
        "interior",
        "consultant",
        "design",
        "decorator"
    ],
    "wof:name":"CMK Interiors",
    "wof:placetype":"venue"
},
  "geometry": {"coordinates":[-74.041956,41.008779],"type":"Point"}
}