{
  "type": "Feature",
  "properties": {
    "iso:country":"US",
    "sg:address":"123 Barclay Ln",
    "sg:city":"Cherry Hill",
    "sg:classifiers":[
        {
            "category":"Health Services",
            "subcategory":"Chiropractor",
            "type":"Services"
        }
    ],
    "sg:phone":"+1 856 795 1015",
    "sg:postcode":"08034",
    "sg:province":"NJ",
    "wof:name":"Barclay Chiropractic Ctr",
    "wof:placetype":"venue"
},
  "geometry": {"coordinates":[-74.998654,39.907594],"type":"Point"}
}