{
  "type": "Feature",
  "properties": {
    "iso:country":"US",
    "sg:address":"130 Vollers Dr",
    "sg:city":"Branchburg",
    "sg:classifiers":[
        {
            "category":"Shopping",
            "subcategory":"Gifts & Souvenirs",
            "type":"Retail Goods"
        }
    ],
    "sg:phone":"+1 908 725 4320",
    "sg:postcode":"08876",
    "sg:province":"NJ",
    "sg:tags":[
        "shop"
    ],
    "wof:name":"Country Basket",
    "wof:placetype":"venue"
},
  "geometry": {"coordinates":[-74.702333,40.58864],"type":"Point"}
}