{
  "type": "Feature",
  "properties": {
    "iso:country":"US",
    "sg:address":"153 Halsey St",
    "sg:city":"Newark",
    "sg:classifiers":[
        {
            "category":"Restaurant",
            "type":"Food & Drink"
        }
    ],
    "sg:phone":"+1 973 504 6100",
    "sg:postcode":"07102",
    "sg:province":"NJ",
    "sg:tags":[
        "kosher"
    ],
    "wof:name":"Kosher Food Inspection Section",
    "wof:placetype":"venue"
},
  "geometry": {"coordinates":[-74.173118,40.737266],"type":"Point"}
}