{
  "type": "Feature",
  "properties": {
    "addr:full":"200 International Dr Budd Lake NJ 07828",
    "addr:housenumber":"200",
    "addr:postcode":"07828",
    "addr:street":"International Dr",
    "iso:country":"US",
    "sg:address":"200 International Dr",
    "sg:city":"Budd Lake",
    "sg:classifiers":[
        {
            "category":"Wholesale",
            "subcategory":"Jewelry",
            "type":"Manufacturing & Wholesale Goods"
        }
    ],
    "sg:phone":"+1 973 691 1010",
    "sg:postcode":"07828",
    "sg:province":"NJ",
    "sg:tags":[
        "stone"
    ],
    "wof:name":"Seiko Corporation of America",
    "wof:placetype":"venue"
},
  "geometry": {"coordinates":[-74.719273,40.894244],"type":"Point"}
}