{
  "type": "Feature",
  "properties": {
    "iso:country":"US",
    "sg:address":"246 Livingston St",
    "sg:city":"Northvale",
    "sg:classifiers":[
        {
            "category":"Food & Beverages",
            "subcategory":"Specialty",
            "type":"Retail Goods"
        }
    ],
    "sg:phone":"+1 201 767 8182",
    "sg:postcode":"07647",
    "sg:province":"NJ",
    "sg:tags":[
        "vitamin"
    ],
    "sg:website":"www.organicanaturalfoods.com",
    "wof:name":"Organica Natural Foods",
    "wof:placetype":"venue"
},
  "geometry": {"coordinates":[-73.94591200000001,41.013791],"type":"Point"}
}