{
  "type": "Feature",
  "properties": {
    "addr:full":"Hickory Square Mall 641 Shunpike Rd Chatham NJ 07928",
    "addr:housenumber":"641",
    "addr:postcode":"07928",
    "addr:street":"Hickory;Shunpike Rd",
    "iso:country":"US",
    "sg:address":"Hickory Square Mall 641 Shunpike Rd",
    "sg:city":"Chatham",
    "sg:classifiers":[
        {
            "category":"Education",
            "subcategory":"Special Training",
            "type":"Public Place"
        }
    ],
    "sg:phone":"+1 973 822 3200",
    "sg:postcode":"07928",
    "sg:province":"NJ",
    "sg:tags":[
        "tutoring"
    ],
    "sg:website":"www.lilreadingscientists.com",
    "wof:name":"Lil' Reading Scientists",
    "wof:placetype":"venue"
},
  "geometry": {"coordinates":[-74.430678,40.745241],"type":"Point"}
}