{
  "type": "Feature",
  "properties": {
    "addr:full":"923 Main St Belmar NJ 07719",
    "addr:housenumber":"923",
    "addr:postcode":"07719",
    "addr:street":"Main St",
    "iso:country":"US",
    "sg:address":"923 Main St",
    "sg:city":"Belmar",
    "sg:classifiers":[
        {
            "category":"Shopping",
            "type":"Retail Goods"
        }
    ],
    "sg:phone":"+1 732 869 9114",
    "sg:postcode":"07719",
    "sg:province":"NJ",
    "sg:tags":[
        "art",
        "gallery",
        "dealer"
    ],
    "wof:name":"Freedom Pottery Studios",
    "wof:placetype":"venue"
},
  "geometry": {"coordinates":[-74.02540999999999,40.180093],"type":"Point"}
}