{
  "type": "Feature",
  "properties": {
    "addr:full":"260 Central Ave Hackensack NJ 07601",
    "addr:housenumber":"260",
    "addr:postcode":"07601",
    "addr:street":"Central Ave",
    "iso:country":"US",
    "sg:address":"260 Central Ave",
    "sg:city":"Hackensack",
    "sg:classifiers":[
        {
            "category":"Organizations",
            "subcategory":"Religious Organization",
            "type":"Services"
        }
    ],
    "sg:phone":"+1 201 489 6462",
    "sg:postcode":"07601",
    "sg:province":"NJ",
    "sg:tags":[
        "clergy"
    ],
    "sg:website":"www.mountolivebaptist.org",
    "wof:name":"Mount Olive Baptist Church",
    "wof:placetype":"venue"
},
  "geometry": {"coordinates":[-74.052476,40.889569],"type":"Point"}
}