{
  "type": "Feature",
  "properties": {
    "addr:full":"1 Garden State Plaza Paramus NJ 07652",
    "addr:housenumber":"1",
    "addr:postcode":"07652",
    "addr:street":"Garden;Plaza",
    "iso:country":"US",
    "sg:address":"1 Garden State Plaza",
    "sg:city":"Paramus",
    "sg:classifiers":[
        {
            "category":"Coffee & Tea",
            "type":"Food & Drink"
        }
    ],
    "sg:phone":"+1 201 291 1800",
    "sg:postcode":"07652",
    "sg:province":"NJ",
    "sg:website":"www.Teavana.com",
    "wof:name":"Teavana",
    "wof:placetype":"venue"
},
  "geometry": {"coordinates":[-74.073868,40.915751],"type":"Point"}
}