{
  "type": "Feature",
  "properties": {
    "iso:country":"US",
    "sg:address":"32 Wildhedge Ln",
    "sg:city":"Holmdel",
    "sg:classifiers":[
        {
            "category":"Building & Trades",
            "subcategory":"Construction",
            "type":"Services"
        }
    ],
    "sg:phone":"+1 732 834 9686",
    "sg:postcode":"07733",
    "sg:province":"NJ",
    "sg:tags":[
        "house"
    ],
    "wof:name":"Gregory Fodor LLC",
    "wof:placetype":"venue"
},
  "geometry": {"coordinates":[-74.197058,40.357843],"type":"Point"}
}