{
  "type": "Feature",
  "properties": {
    "addr:full":"16 Geneva Ct Wayne NJ 07470",
    "addr:housenumber":"16",
    "addr:postcode":"07470",
    "addr:street":"Geneva Ct",
    "iso:country":"US",
    "sg:address":"16 Geneva Ct",
    "sg:city":"Wayne",
    "sg:classifiers":[
        {
            "category":"Banks & Credit Unions",
            "subcategory":"Investment Brokerage",
            "type":"Services"
        }
    ],
    "sg:phone":"+1   ",
    "sg:postcode":"07470",
    "sg:province":"NJ",
    "sg:tags":[
        "security"
    ],
    "wof:name":"UBS Financial Services Inc",
    "wof:placetype":"venue"
},
  "geometry": {"coordinates":[-74.246439,40.940323],"type":"Point"}
}