{
  "type": "Feature",
  "properties": {
    "iso:country":"US",
    "sg:address":"11 Larchmont Pl",
    "sg:city":"Mount Laurel",
    "sg:classifiers":[
        {
            "category":"Health Services",
            "subcategory":"Doctor",
            "type":"Services"
        }
    ],
    "sg:phone":"+1 856 778 2060",
    "sg:postcode":"08054",
    "sg:province":"NJ",
    "sg:tags":[
        "clinic",
        "medical"
    ],
    "wof:name":"Burlington County Osterical An",
    "wof:placetype":"venue"
},
  "geometry": {"coordinates":[-74.88102000000001,39.976099],"type":"Point"}
}