{
  "type": "Feature",
  "properties": {
    "addr:full":"264 Colfax Ave Clifton NJ 07013",
    "addr:housenumber":"264",
    "addr:postcode":"07013",
    "addr:street":"Colfax Ave",
    "iso:country":"US",
    "sg:address":"264 Colfax Ave",
    "sg:city":"Clifton",
    "sg:classifiers":[
        {
            "category":"Wholesale",
            "subcategory":"Electrical",
            "type":"Manufacturing & Wholesale Goods"
        }
    ],
    "sg:phone":"+1 973 773 1397",
    "sg:postcode":"07013",
    "sg:province":"NJ",
    "sg:tags":[
        "fire",
        "alarm",
        "system"
    ],
    "sg:website":"www.kevsecurity.com",
    "wof:name":"KEV Security Contractors",
    "wof:placetype":"venue"
},
  "geometry": {"coordinates":[-74.160515,40.869863],"type":"Point"}
}