{
  "type": "Feature",
  "properties": {
    "addr:full":"518 Richey Ave Oaklyn NJ 08107",
    "addr:housenumber":"518",
    "addr:postcode":"08107",
    "addr:street":"Richey Ave",
    "iso:country":"US",
    "sg:address":"518 Richey Ave",
    "sg:city":"Oaklyn",
    "sg:classifiers":[
        {
            "category":"Banks & Credit Unions",
            "subcategory":"Investment Brokerage",
            "type":"Services"
        }
    ],
    "sg:phone":"+1 856 833 1008",
    "sg:postcode":"08107",
    "sg:province":"NJ",
    "sg:tags":[
        "advisory",
        "financial"
    ],
    "wof:name":"Avenue Financial LLC",
    "wof:placetype":"venue"
},
  "geometry": {"coordinates":[-75.085357,39.910849],"type":"Point"}
}