{
  "type": "Feature",
  "properties": {
    "iso:country":"US",
    "sg:address":"1904 Williamstown Rd",
    "sg:city":"Franklinville",
    "sg:classifiers":[
        {
            "category":"Building & Trades",
            "subcategory":"Cleaning & Sanitation",
            "type":"Services"
        }
    ],
    "sg:phone":"+1 856 694 3411",
    "sg:postcode":"08322",
    "sg:province":"NJ",
    "sg:tags":[
        "janitor"
    ],
    "wof:name":"Coles Cleaning Svc",
    "wof:placetype":"venue"
},
  "geometry": {"coordinates":[-75.053746,39.627882],"type":"Point"}
}