{
  "type": "Feature",
  "properties": {
    "addr:full":"500 Chandler Ave Roselle NJ 07203",
    "addr:housenumber":"500",
    "addr:postcode":"07203",
    "addr:street":"Chandler Ave",
    "iso:country":"US",
    "sg:address":"500 Chandler Ave",
    "sg:city":"Roselle",
    "sg:classifiers":[
        {
            "category":"Food & Beverages",
            "subcategory":"Groceries & Convenience Stores",
            "type":"Retail Goods"
        }
    ],
    "sg:phone":"+1   ",
    "sg:postcode":"07203",
    "sg:province":"NJ",
    "sg:tags":[
        "alcoholic"
    ],
    "wof:name":"Als Liquor Delicatessen",
    "wof:placetype":"venue"
},
  "geometry": {"coordinates":[-74.25331199999999,40.655806],"type":"Point"}
}