{
  "type": "Feature",
  "properties": {
    "iso:country":"US",
    "sg:address":"935 Washington St",
    "sg:city":"Hoboken",
    "sg:classifiers":[
        {
            "category":"Shopping",
            "subcategory":"Clothing, Apparel, & Fashions",
            "type":"Retail Goods"
        }
    ],
    "sg:phone":"+1   ",
    "sg:postcode":"07030",
    "sg:province":"NJ",
    "sg:tags":[
        "wear"
    ],
    "wof:name":"Jaggar Inc",
    "wof:placetype":"venue"
},
  "geometry": {"coordinates":[-74.027534,40.748092],"type":"Point"}
}