{
  "type": "Feature",
  "properties": {
    "addr:full":"420 43rd St Union City NJ 07087",
    "addr:housenumber":"420",
    "addr:postcode":"07087",
    "addr:street":"43Rd St",
    "iso:country":"US",
    "sg:address":"420 43rd St",
    "sg:city":"Union City",
    "sg:classifiers":[
        {
            "category":"Health Services",
            "subcategory":"Medical Lab",
            "type":"Services"
        }
    ],
    "sg:phone":"+1 201 601 0368",
    "sg:postcode":"07087",
    "sg:province":"NJ",
    "sg:tags":[
        "laboratory"
    ],
    "wof:name":"Best Quality Dental Lab",
    "wof:placetype":"venue"
},
  "geometry": {"coordinates":[-74.02437999999999,40.778025],"type":"Point"}
}