{
  "type": "Feature",
  "properties": {
    "addr:full":"1210 Corbin St Elizabeth NJ 07201",
    "addr:housenumber":"1210",
    "addr:postcode":"07201",
    "addr:street":"Corbin St",
    "iso:country":"US",
    "sg:address":"1210 Corbin St",
    "sg:city":"Elizabeth",
    "sg:classifiers":[
        {
            "category":"Recreation",
            "type":"Entertainment"
        }
    ],
    "sg:phone":"+1 908 787 1187",
    "sg:postcode":"07201",
    "sg:province":"NJ",
    "sg:tags":[
        "parks"
    ],
    "wof:name":"Usfish & Wifelife Svc",
    "wof:placetype":"venue"
},
  "geometry": {"coordinates":[-74.16306,40.684979],"type":"Point"}
}