{
  "type": "Feature",
  "properties": {
    "iso:country":"US",
    "sg:address":"240 Twin Oaks Ter",
    "sg:city":"Westfield",
    "sg:classifiers":[
        {
            "category":"Professional",
            "subcategory":"Research",
            "type":"Services"
        }
    ],
    "sg:phone":"+1   ",
    "sg:postcode":"07090",
    "sg:province":"NJ",
    "sg:tags":[
        "nonphysical",
        "commercial"
    ],
    "wof:name":"Strategic Marketing Technology",
    "wof:placetype":"venue"
},
  "geometry": {"coordinates":[-74.322821,40.641686],"type":"Point"}
}