{
  "type": "Feature",
  "properties": {
    "iso:country":"US",
    "sg:address":"620 Broad St",
    "sg:city":"Shrewsbury",
    "sg:classifiers":[
        {
            "category":"Museum",
            "type":"Entertainment"
        }
    ],
    "sg:phone":"+1   ",
    "sg:postcode":"07702",
    "sg:province":"NJ",
    "sg:tags":[
        "lesson",
        "art",
        "gallery",
        "provides"
    ],
    "sg:website":"www.guildofcreativeart.com",
    "wof:name":"Guild Of Creative Art",
    "wof:placetype":"venue"
},
  "geometry": {"coordinates":[-74.06274999999999,40.331874],"type":"Point"}
}