{
  "type": "Feature",
  "properties": {
    "iso:country":"US",
    "sg:address":"176 US Highway 46",
    "sg:city":"Parsippany",
    "sg:classifiers":[
        {
            "category":"Building & Trades",
            "subcategory":"Cleaning & Sanitation",
            "type":"Services"
        }
    ],
    "sg:phone":"+1 973 575 9000",
    "sg:postcode":"07054",
    "sg:province":"NJ",
    "sg:tags":[
        "carpet"
    ],
    "wof:name":"Sam Masse Opriental Rugs",
    "wof:placetype":"venue"
},
  "geometry": {"coordinates":[-74.35228600000001,40.858265],"type":"Point"}
}