{
  "type": "Feature",
  "properties": {
    "iso:country":"US",
    "sg:address":"310 Main St",
    "sg:city":"Orange",
    "sg:classifiers":[
        {
            "category":"Professional",
            "type":"Services"
        }
    ],
    "sg:phone":"+1 973 672 7231",
    "sg:postcode":"07050",
    "sg:province":"NJ",
    "sg:tags":[
        "establishment"
    ],
    "wof:name":"Alcoholics Families",
    "wof:placetype":"venue"
},
  "geometry": {"coordinates":[-74.23056099999999,40.772462],"type":"Point"}
}