{
  "type": "Feature",
  "properties": {
    "iso:country":"US",
    "sg:address":"302 Montgomery Ave",
    "sg:city":"Pitman",
    "sg:classifiers":[
        {
            "category":"Professional",
            "subcategory":"Lawyer & Legal Services",
            "type":"Services"
        }
    ],
    "sg:phone":"+1 856 589 4128",
    "sg:postcode":"08071",
    "sg:province":"NJ",
    "sg:tags":[
        "planning",
        "estate"
    ],
    "wof:name":"Len Eckman Insurance Svc Ctr",
    "wof:placetype":"venue"
},
  "geometry": {"coordinates":[-75.130605,39.737493],"type":"Point"}
}