{
  "type": "Feature",
  "properties": {
    "addr:full":"148 Main St Lebanon NJ 08833",
    "addr:housenumber":"148",
    "addr:postcode":"08833",
    "addr:street":"Main St",
    "iso:country":"US",
    "sg:address":"148 Main St",
    "sg:city":"Lebanon",
    "sg:classifiers":[
        {
            "category":"Personal",
            "subcategory":"Beauty Salon",
            "type":"Services"
        }
    ],
    "sg:phone":"+1 908 236 7878",
    "sg:postcode":"08833",
    "sg:province":"NJ",
    "sg:tags":[
        "shop",
        "tanning"
    ],
    "sg:website":"www.adristysalon.com",
    "wof:name":"Adristy Salon Inc",
    "wof:placetype":"venue"
},
  "geometry": {"coordinates":[-74.825996,40.641998],"type":"Point"}
}