{
  "type": "Feature",
  "properties": {
    "iso:country":"US",
    "sg:address":"226 Wall St",
    "sg:city":"Eatontown",
    "sg:classifiers":[
        {
            "category":"Building & Trades",
            "subcategory":"Construction",
            "type":"Services"
        }
    ],
    "sg:phone":"+1 732 389 1524",
    "sg:postcode":"07724",
    "sg:province":"NJ",
    "sg:tags":[
        "paper",
        "painting",
        "hanging"
    ],
    "wof:name":"Adolfos Painting",
    "wof:placetype":"venue"
},
  "geometry": {"coordinates":[-74.041375,40.283534],"type":"Point"}
}