{
  "type": "Feature",
  "properties": {
    "addr:full":"3680 E Landis Ave Vineland NJ 08361",
    "addr:housenumber":"3680",
    "addr:postcode":"08361",
    "addr:street":"E Landis Ave",
    "iso:country":"US",
    "sg:address":"3680 E Landis Ave",
    "sg:city":"Vineland",
    "sg:classifiers":[
        {
            "category":"Banks & Credit Unions",
            "subcategory":"Bank",
            "type":"Services"
        }
    ],
    "sg:phone":"+1 856 000 1111",
    "sg:postcode":"08361",
    "sg:province":"NJ",
    "wof:name":"Bank Of America",
    "wof:placetype":"venue"
},
  "geometry": {"coordinates":[-74.96632200000001,39.483444],"type":"Point"}
}