{
  "type": "Feature",
  "properties": {
    "addr:full":"246 E 2nd Ave Roselle NJ 07203",
    "addr:housenumber":"246",
    "addr:postcode":"07203",
    "addr:street":"E 2Nd Ave",
    "iso:country":"US",
    "sg:address":"246 E 2nd Ave",
    "sg:city":"Roselle",
    "sg:classifiers":[
        {
            "category":"Retail",
            "subcategory":"Repair Shop",
            "type":"Services"
        }
    ],
    "sg:phone":"+1 908 372 6726",
    "sg:postcode":"07203",
    "sg:province":"NJ",
    "sg:tags":[
        "lock",
        "locksmith"
    ],
    "wof:name":"USA Locksmith",
    "wof:placetype":"venue"
},
  "geometry": {"coordinates":[-74.256657,40.659662],"type":"Point"}
}