{
  "type": "Feature",
  "properties": {
    "iso:country":"US",
    "sg:address":"400 Franklin Tpke Ste 200",
    "sg:city":"Mahwah",
    "sg:classifiers":[
        {
            "category":"Health Services",
            "subcategory":"Clinic",
            "type":"Services"
        }
    ],
    "sg:phone":"+1 201 236 0066",
    "sg:postcode":"07430",
    "sg:province":"NJ",
    "sg:tags":[
        "information",
        "alcoholism",
        "treatment"
    ],
    "sg:website":"http://www.selectmedicalcorp.com",
    "wof:name":"Healthsouth",
    "wof:placetype":"venue"
},
  "geometry": {"coordinates":[-74.140219,41.08095],"type":"Point"}
}