{
  "type": "Feature",
  "properties": {
    "addr:full":"504 E 17th Ave North Wildwood NJ 08260",
    "addr:housenumber":"504",
    "addr:postcode":"08260",
    "addr:street":"E 17Th Ave North",
    "iso:country":"US",
    "sg:address":"504 E 17th Ave",
    "sg:city":"North Wildwood",
    "sg:classifiers":[
        {
            "category":"Real Estate",
            "subcategory":"Real Estate Agent",
            "type":"Services"
        },
        {
            "category":"Real Estate",
            "subcategory":"Real Estate Operator",
            "type":"Services"
        }
    ],
    "sg:phone":"+1 609 522 7112",
    "sg:postcode":"08260",
    "sg:province":"NJ",
    "sg:tags":[
        "condominium"
    ],
    "wof:name":"Tides Oceanview Condo Assoc",
    "wof:placetype":"venue"
},
  "geometry": {"coordinates":[-74.797083,38.993838],"type":"Point"}
}