{
  "type": "Feature",
  "properties": {
    "addr:full":"101 Dillion Ct North Brunswick NJ 08902",
    "addr:housenumber":"101",
    "addr:postcode":"08902",
    "addr:street":"Dillion Ct",
    "iso:country":"US",
    "sg:address":"101 Dillion Ct",
    "sg:city":"North Brunswick",
    "sg:classifiers":[
        {
            "category":"Retail",
            "subcategory":"Auto Repair",
            "type":"Services"
        }
    ],
    "sg:phone":"+1 732 422 7723",
    "sg:postcode":"08902",
    "sg:province":"NJ",
    "sg:tags":[
        "general"
    ],
    "wof:name":"All State Limo & Car Svc",
    "wof:placetype":"venue"
},
  "geometry": {"coordinates":[-74.482533,40.439152],"type":"Point"}
}