{
  "type": "Feature",
  "properties": {
    "iso:country":"US",
    "sg:address":"204 S Nassau Dr",
    "sg:city":"Haddonfield",
    "sg:classifiers":[
        {
            "category":"Building & Trades",
            "subcategory":"Construction",
            "type":"Services"
        }
    ],
    "sg:phone":"+1 856 546 7979",
    "sg:postcode":"08033",
    "sg:province":"NJ",
    "sg:tags":[
        "contractor"
    ],
    "wof:name":"Baptiste John Construction Co",
    "wof:placetype":"venue"
},
  "geometry": {"coordinates":[-75.047077,39.875897],"type":"Point"}
}