{
  "type": "Feature",
  "properties": {
    "iso:country":"US",
    "sg:address":"150 E Broad St",
    "sg:city":"Westfield",
    "sg:classifiers":[
        {
            "category":"Education",
            "subcategory":"Special Training",
            "type":"Public Place"
        }
    ],
    "sg:phone":"+1   ",
    "sg:postcode":"07090",
    "sg:province":"NJ",
    "sg:tags":[
        "educational",
        "performing",
        "arts",
        "for"
    ],
    "wof:name":"Westfield Summer Works Shop",
    "wof:placetype":"venue"
},
  "geometry": {"coordinates":[-74.348615,40.651131],"type":"Point"}
}