{
  "type": "Feature",
  "properties": {
    "iso:country":"US",
    "sg:address":"1 E Stuyvesant Ave",
    "sg:city":"Trenton",
    "sg:classifiers":[
        {
            "category":"Personal",
            "subcategory":"Beauty Salon",
            "type":"Services"
        }
    ],
    "sg:phone":"+1 609 695 5777",
    "sg:postcode":"08618",
    "sg:province":"NJ",
    "sg:tags":[
        "shop"
    ],
    "wof:name":"Weave Got Hair",
    "wof:placetype":"venue"
},
  "geometry": {"coordinates":[-74.774559,40.230233],"type":"Point"}
}