{
  "type": "Feature",
  "properties": {
    "iso:country":"US",
    "sg:address":"1741 State Rte 37",
    "sg:city":"Toms River",
    "sg:classifiers":[
        {
            "category":"Retail",
            "subcategory":"Auto Rental",
            "type":"Services"
        }
    ],
    "sg:phone":"+1 732 914 9366",
    "sg:postcode":"08757",
    "sg:province":"NJ",
    "sg:tags":[
        "passenger",
        "car"
    ],
    "wof:name":"A-1 Car Express",
    "wof:placetype":"venue"
},
  "geometry": {"coordinates":[-74.270681,39.992136],"type":"Point"}
}