{
  "type": "Feature",
  "properties": {
    "iso:country":"US",
    "sg:address":"15 Church St",
    "sg:city":"Mount Holly",
    "sg:classifiers":[
        {
            "category":"Manufacturing",
            "subcategory":"Furniture",
            "type":"Manufacturing & Wholesale Goods"
        }
    ],
    "sg:phone":"+1 609 587 2221",
    "sg:postcode":"08060",
    "sg:province":"NJ",
    "sg:tags":[
        "fire",
        "prefabricated",
        "wood",
        "metal",
        "mfg"
    ],
    "wof:name":"Hni Corporation",
    "wof:placetype":"venue"
},
  "geometry": {"coordinates":[-74.785698,39.992438],"type":"Point"}
}