{
  "type": "Feature",
  "properties": {
    "iso:country":"US",
    "sg:address":"464 3rd Ave",
    "sg:city":"Elizabeth",
    "sg:classifiers":[
        {
            "category":"Shopping",
            "type":"Retail Goods"
        }
    ],
    "sg:phone":"+1   ",
    "sg:postcode":"07206",
    "sg:province":"NJ",
    "sg:tags":[
        "equipment",
        "audio",
        "supply"
    ],
    "wof:name":"E S Systems",
    "wof:placetype":"venue"
},
  "geometry": {"coordinates":[-74.203104,40.651963],"type":"Point"}
}