{
  "type": "Feature",
  "properties": {
    "addr:full":"57 State Rte 5 Edgewater NJ 07020",
    "addr:housenumber":"57",
    "addr:postcode":"07020",
    "addr:street":"State Rte 5",
    "iso:country":"US",
    "sg:address":"57 State Rte 5",
    "sg:city":"Edgewater",
    "sg:classifiers":[
        {
            "category":"Professional",
            "subcategory":"Management & Consulting",
            "type":"Services"
        }
    ],
    "sg:phone":"+1 201 969 2444",
    "sg:postcode":"07020",
    "sg:province":"NJ",
    "sg:tags":[
        "consultant",
        "business"
    ],
    "wof:name":"Image Management",
    "wof:placetype":"venue"
},
  "geometry": {"coordinates":[-73.972527,40.829794],"type":"Point"}
}