{
  "type": "Feature",
  "properties": {
    "addr:full":"505 Nicholson Rd Gloucester City NJ 08030",
    "addr:housenumber":"505",
    "addr:postcode":"08030",
    "addr:street":"Nicholson Rd",
    "iso:country":"US",
    "sg:address":"505 Nicholson Rd",
    "sg:city":"Gloucester City",
    "sg:classifiers":[
        {
            "category":"Retail",
            "subcategory":"Auto Repair",
            "type":"Services"
        }
    ],
    "sg:phone":"+1 856 456 6464",
    "sg:postcode":"08030",
    "sg:province":"NJ",
    "wof:name":"Aj's Advanced Auto & Diesel SE Rvice Center",
    "wof:placetype":"venue"
},
  "geometry": {"coordinates":[-75.10995800000001,39.895601],"type":"Point"}
}