{
  "type": "Feature",
  "properties": {
    "iso:country":"US",
    "sg:address":"52 Oxford St",
    "sg:city":"Paterson",
    "sg:classifiers":[
        {
            "category":"Retail",
            "subcategory":"Repair Shop",
            "type":"Services"
        },
        {
            "category":"Home & Garden",
            "subcategory":"Furniture",
            "type":"Retail Goods"
        }
    ],
    "sg:phone":"+1 973 942 9681",
    "sg:postcode":"07522",
    "sg:province":"NJ",
    "sg:tags":[
        "antique",
        "refinishing"
    ],
    "wof:name":"Angel's Restrapping",
    "wof:placetype":"venue"
},
  "geometry": {"coordinates":[-74.179008,40.924163],"type":"Point"}
}