{
  "type": "Feature",
  "properties": {
    "iso:country":"US",
    "sg:address":"2360 Nottingham Way",
    "sg:city":"Trenton",
    "sg:classifiers":[
        {
            "category":"Building & Trades",
            "subcategory":"Plumbing",
            "type":"Services"
        }
    ],
    "sg:phone":"+1 609 392 3661",
    "sg:postcode":"08619",
    "sg:province":"NJ",
    "sg:tags":[
        "mechanical",
        "contractor"
    ],
    "wof:name":"J M Mechanical Serv",
    "wof:placetype":"venue"
},
  "geometry": {"coordinates":[-74.697988,40.2339],"type":"Point"}
}