{
  "type": "Feature",
  "properties": {
    "addr:full":"481 Rte 46 W Wayne NJ 07470",
    "addr:housenumber":"481",
    "addr:postcode":"07470",
    "addr:street":"Rte 46 W",
    "iso:country":"US",
    "sg:address":"481 Rte 46 W",
    "sg:city":"Wayne",
    "sg:classifiers":[
        {
            "category":"Government",
            "subcategory":"City Hall",
            "type":"Public Place"
        }
    ],
    "sg:postcode":"07470",
    "sg:province":"NJ",
    "sg:website":"www.state.nj.us/mvc",
    "wof:name":"Department of Motor Vehicles",
    "wof:placetype":"venue"
},
  "geometry": {"coordinates":[-74.30614199999999,40.949234],"type":"Point"}
}