{
  "type": "Feature",
  "properties": {
    "iso:country":"US",
    "sg:address":"1445 Brace Rd",
    "sg:city":"Cherry Hill",
    "sg:classifiers":[
        {
            "category":"Food & Beverages",
            "subcategory":"Groceries & Convenience Stores",
            "type":"Retail Goods"
        }
    ],
    "sg:phone":"+1 856 216 7710",
    "sg:postcode":"08034",
    "sg:province":"NJ",
    "wof:name":"Shoprite of Brace Road",
    "wof:placetype":"venue"
},
  "geometry": {"coordinates":[-75.01821700000001,39.890463],"type":"Point"}
}