{
  "type": "Feature",
  "properties": {
    "iso:country":"US",
    "sg:address":"9 Burr Dr",
    "sg:city":"Metuchen",
    "sg:classifiers":[
        {
            "category":"Organizations",
            "subcategory":"Religious Organization",
            "type":"Services"
        }
    ],
    "sg:phone":"+1   ",
    "sg:postcode":"08840",
    "sg:province":"NJ",
    "wof:name":"Faith M Murphy",
    "wof:placetype":"venue"
},
  "geometry": {"coordinates":[-74.363986,40.529385],"type":"Point"}
}