{
  "type": "Feature",
  "properties": {
    "addr:full":"159 Tracy Pl Hackensack NJ 07601",
    "addr:housenumber":"159",
    "addr:postcode":"07601",
    "addr:street":"Tracy Pl",
    "iso:country":"US",
    "sg:address":"159 Tracy Pl",
    "sg:city":"Hackensack",
    "sg:classifiers":[
        {
            "category":"Real Estate",
            "subcategory":"Real Estate Operator",
            "type":"Services"
        }
    ],
    "sg:phone":"+1 201 342 5066",
    "sg:postcode":"07601",
    "sg:province":"NJ",
    "sg:tags":[
        "apartment"
    ],
    "wof:name":"Brookdale Apartments",
    "wof:placetype":"venue"
},
  "geometry": {"coordinates":[-74.06059999999999,40.890598],"type":"Point"}
}