{
  "type": "Feature",
  "properties": {
    "addr:full":"17 W 7th St Barnegat Light NJ 08006",
    "addr:housenumber":"17",
    "addr:postcode":"08006",
    "addr:street":"W 7Th St",
    "iso:country":"US",
    "sg:address":"17 W 7th St",
    "sg:city":"Barnegat Light",
    "sg:classifiers":[
        {
            "category":"Wholesale",
            "subcategory":"Seafood",
            "type":"Manufacturing & Wholesale Goods"
        }
    ],
    "sg:phone":"+1 609 361 0402",
    "sg:postcode":"08006",
    "sg:province":"NJ",
    "sg:website":"www.hilofish.com",
    "wof:name":"Export Inc",
    "wof:placetype":"venue"
},
  "geometry": {"coordinates":[-74.108841,39.75948],"type":"Point"}
}