{
  "type": "Feature",
  "properties": {
    "addr:full":"309 W Maiden Ln Somerdale NJ 08083",
    "addr:housenumber":"309",
    "addr:postcode":"08083",
    "addr:street":"W Maiden Ln",
    "iso:country":"US",
    "sg:address":"309 W Maiden Ln",
    "sg:city":"Somerdale",
    "sg:classifiers":[
        {
            "category":"Professional",
            "subcategory":"Business Services",
            "type":"Services"
        }
    ],
    "sg:phone":"+1 856 782 3313",
    "sg:postcode":"08083",
    "sg:province":"NJ",
    "wof:name":"Men or Man & Audrey Consultant",
    "wof:placetype":"venue"
},
  "geometry": {"coordinates":[-75.023298,39.842927],"type":"Point"}
}