{
  "type": "Feature",
  "properties": {
    "addr:full":"6 N 27th St Camden NJ 08105",
    "addr:housenumber":"6",
    "addr:postcode":"08105",
    "addr:street":"N 27Th St",
    "iso:country":"US",
    "sg:address":"6 N 27th St",
    "sg:city":"Camden",
    "sg:classifiers":[
        {
            "category":"Health Services",
            "subcategory":"Podiatrist",
            "type":"Services"
        }
    ],
    "sg:phone":"+1 856 365 2313",
    "sg:postcode":"08105",
    "sg:province":"NJ",
    "wof:name":"Mirarchi Joseph DPM",
    "wof:placetype":"venue"
},
  "geometry": {"coordinates":[-75.08669999999999,39.946602],"type":"Point"}
}