{
  "type": "Feature",
  "properties": {
    "iso:country":"US",
    "sg:address":"42 Bridgeton Fairton Rd",
    "sg:city":"Bridgeton",
    "sg:classifiers":[
        {
            "category":"Building & Trades",
            "subcategory":"Construction",
            "type":"Services"
        }
    ],
    "sg:phone":"+1 856 575 0200",
    "sg:postcode":"08302",
    "sg:province":"NJ",
    "sg:tags":[
        "maker",
        "cabinet"
    ],
    "sg:website":"www.the-woodchucker.com",
    "wof:name":"Woodchucker",
    "wof:placetype":"venue"
},
  "geometry": {"coordinates":[-75.221968,39.384663],"type":"Point"}
}