{
  "type": "Feature",
  "properties": {
    "addr:full":"301 E Evesham Rd Runnemede NJ 08078",
    "addr:housenumber":"301",
    "addr:postcode":"08078",
    "addr:street":"E Evesham Rd",
    "iso:country":"US",
    "sg:address":"301 E Evesham Rd",
    "sg:city":"Runnemede",
    "sg:classifiers":[
        {
            "category":"Food & Beverages",
            "subcategory":"Groceries & Convenience Stores",
            "type":"Retail Goods"
        }
    ],
    "sg:phone":"+1 856 939 1494",
    "sg:postcode":"08078",
    "sg:province":"NJ",
    "wof:name":"One Stop Shopping",
    "wof:placetype":"venue"
},
  "geometry": {"coordinates":[-75.06178,39.847153],"type":"Point"}
}