{
  "type": "Feature",
  "properties": {
    "iso:country":"US",
    "sg:address":"16 Risler St",
    "sg:city":"Stockton",
    "sg:classifiers":[
        {
            "category":"Professional",
            "subcategory":"Management & Consulting",
            "type":"Services"
        }
    ],
    "sg:phone":"+1 609 397 4005",
    "sg:postcode":"08559",
    "sg:province":"NJ",
    "sg:tags":[
        "consultant",
        "publishing"
    ],
    "wof:name":"OTTN Publishing",
    "wof:placetype":"venue"
},
  "geometry": {"coordinates":[-74.982975,40.408395],"type":"Point"}
}