{
  "type": "Feature",
  "properties": {
    "addr:full":"328 Market St Camden NJ 08102",
    "addr:housenumber":"328",
    "addr:postcode":"08102",
    "addr:street":"Market St",
    "iso:country":"US",
    "sg:address":"328 Market St",
    "sg:city":"Camden",
    "sg:classifiers":[
        {
            "category":"Banks & Credit Unions",
            "subcategory":"Bank",
            "type":"Services"
        }
    ],
    "sg:phone":"+1   ",
    "sg:postcode":"08102",
    "sg:province":"NJ",
    "sg:tags":[
        "development",
        "fund",
        "financial",
        "community"
    ],
    "wof:name":"Cbac",
    "wof:placetype":"venue"
},
  "geometry": {"coordinates":[-75.12272400000001,39.945946],"type":"Point"}
}