{
  "type": "Feature",
  "properties": {
    "addr:full":"834 Giordano Ln Hammonton NJ 08037",
    "addr:housenumber":"834",
    "addr:postcode":"08037",
    "addr:street":"Giordano Ln",
    "iso:country":"US",
    "sg:address":"834 Giordano Ln",
    "sg:city":"Hammonton",
    "sg:classifiers":[
        {
            "category":"Building & Trades",
            "subcategory":"Plumbing",
            "type":"Services"
        }
    ],
    "sg:phone":"+1 609 704 9588",
    "sg:postcode":"08037",
    "sg:province":"NJ",
    "sg:tags":[
        "contractor"
    ],
    "wof:name":"Atlantic Heating AC & Rfrgn",
    "wof:placetype":"venue"
},
  "geometry": {"coordinates":[-74.786663,39.60992],"type":"Point"}
}