{
  "type": "Feature",
  "properties": {
    "iso:country":"US",
    "sg:address":"360 Broadway",
    "sg:city":"Keyport",
    "sg:classifiers":[
        {
            "category":"Real Estate",
            "subcategory":"Developer",
            "type":"Services"
        }
    ],
    "sg:phone":"+1 732 264 0225",
    "sg:postcode":"07735",
    "sg:province":"NJ",
    "sg:tags":[
        "cemetery"
    ],
    "wof:name":"Saint Josephs Mausoleum Office",
    "wof:placetype":"venue"
},
  "geometry": {"coordinates":[-74.211353,40.425374],"type":"Point"}
}