{
  "type": "Feature",
  "properties": {
    "iso:country":"US",
    "sg:address":"40 Washington St",
    "sg:city":"West Orange",
    "sg:classifiers":[
        {
            "category":"Restaurant",
            "type":"Food & Drink"
        }
    ],
    "sg:phone":"+1 973 731 0632",
    "sg:postcode":"07052",
    "sg:province":"NJ",
    "sg:tags":[
        "pizza"
    ],
    "wof:name":"Mamma Maria Pizza",
    "wof:placetype":"venue"
},
  "geometry": {"coordinates":[-74.228104,40.786098],"type":"Point"}
}