{
  "type": "Feature",
  "properties": {
    "iso:country":"US",
    "sg:address":"1156 Toms River Rd",
    "sg:city":"Jackson",
    "sg:classifiers":[
        {
            "category":"Retail",
            "subcategory":"Auto Repair",
            "type":"Services"
        }
    ],
    "sg:phone":"+1 732 657 9201",
    "sg:postcode":"08527",
    "sg:province":"NJ",
    "sg:tags":[
        "wrecker"
    ],
    "wof:name":"Al's Towing",
    "wof:placetype":"venue"
},
  "geometry": {"coordinates":[-74.33371099999999,40.050095],"type":"Point"}
}