{
  "type": "Feature",
  "properties": {
    "iso:country":"US",
    "sg:address":"36 Delafield St",
    "sg:city":"New Brunswick",
    "sg:classifiers":[
        {
            "category":"Professional",
            "type":"Services"
        }
    ],
    "sg:phone":"+1   ",
    "sg:postcode":"08901",
    "sg:province":"NJ",
    "sg:tags":[
        "communications"
    ],
    "wof:name":"Etechwriter Inc",
    "wof:placetype":"venue"
},
  "geometry": {"coordinates":[-74.456681,40.499089],"type":"Point"}
}