{
  "type": "Feature",
  "properties": {
    "iso:country":"US",
    "sg:address":"283 Nassau St",
    "sg:city":"Princeton",
    "sg:classifiers":[
        {
            "category":"Utilities",
            "subcategory":"Telephone",
            "type":"Services"
        }
    ],
    "sg:phone":"+1 609 497 1020",
    "sg:postcode":"08540",
    "sg:province":"NJ",
    "sg:tags":[
        "communications"
    ],
    "wof:name":"Reid Byers",
    "wof:placetype":"venue"
},
  "geometry": {"coordinates":[-74.64839000000001,40.353001],"type":"Point"}
}