{
  "type": "Feature",
  "properties": {
    "iso:country":"US",
    "sg:address":"2215 River Ave",
    "sg:city":"Camden",
    "sg:classifiers":[
        {
            "category":"Restaurant",
            "type":"Food & Drink"
        }
    ],
    "sg:phone":"+1 856 963 9000",
    "sg:postcode":"08105",
    "sg:province":"NJ",
    "sg:tags":[
        "spanish"
    ],
    "wof:name":"New Spanish Family Restaurant",
    "wof:placetype":"venue"
},
  "geometry": {"coordinates":[-75.09691599999999,39.953278],"type":"Point"}
}