{
  "type": "Feature",
  "properties": {
    "addr:full":"72 Bennett Ave Neptune City NJ 07753",
    "addr:housenumber":"72",
    "addr:postcode":"07753",
    "addr:street":"Bennett Ave",
    "iso:country":"US",
    "sg:address":"72 Bennett Ave",
    "sg:city":"Neptune City",
    "sg:classifiers":[
        {
            "category":"Building & Trades",
            "subcategory":"Construction",
            "type":"Services"
        }
    ],
    "sg:phone":"+1 732 502 3224",
    "sg:postcode":"07753",
    "sg:province":"NJ",
    "sg:tags":[
        "roofing",
        "contractor"
    ],
    "wof:name":"National Construction & Roofin",
    "wof:placetype":"venue"
},
  "geometry": {"coordinates":[-74.035572,40.202847],"type":"Point"}
}