{
  "type": "Feature",
  "properties": {
    "addr:full":"124 Maple Ave Montclair NJ 07042",
    "addr:housenumber":"124",
    "addr:postcode":"07042",
    "addr:street":"Maple Ave",
    "iso:country":"US",
    "sg:address":"124 Maple Ave",
    "sg:city":"Montclair",
    "sg:classifiers":[
        {
            "category":"Real Estate",
            "subcategory":"Real Estate Operator",
            "type":"Services"
        }
    ],
    "sg:phone":"+1   ",
    "sg:postcode":"07042",
    "sg:province":"NJ",
    "sg:tags":[
        "house",
        "apartment",
        "holding"
    ],
    "wof:name":"New Frontiers Enterprise Inc",
    "wof:placetype":"venue"
},
  "geometry": {"coordinates":[-74.214319,40.803358],"type":"Point"}
}