{
  "type": "Feature",
  "properties": {
    "addr:full":"6 Ironia Mendham Rd Chester NJ 07930",
    "addr:housenumber":"6",
    "addr:postcode":"07930",
    "addr:street":"Ironia Mendham Rd",
    "iso:country":"US",
    "sg:address":"6 Ironia Mendham Rd",
    "sg:city":"Chester",
    "sg:classifiers":[
        {
            "category":"Building & Trades",
            "subcategory":"Landscaping Services",
            "type":"Services"
        }
    ],
    "sg:phone":"+1 973 252 8843",
    "sg:postcode":"07930",
    "sg:province":"NJ",
    "sg:tags":[
        "landscape"
    ],
    "wof:name":"Elite Landscape Construction",
    "wof:placetype":"venue"
},
  "geometry": {"coordinates":[-74.62509900000001,40.820039],"type":"Point"}
}