{
  "type": "Feature",
  "properties": {
    "iso:country":"US",
    "sg:address":"3000 Hadley Rd",
    "sg:city":"South Plainfield",
    "sg:classifiers":[
        {
            "category":"Education",
            "subcategory":"Vocational School",
            "type":"Public Place"
        }
    ],
    "sg:phone":"+1 908 222 0002",
    "sg:postcode":"07080",
    "sg:province":"NJ",
    "wof:name":"American Institute-Med",
    "wof:placetype":"venue"
},
  "geometry": {"coordinates":[-74.42389300000001,40.553404],"type":"Point"}
}