{
  "type": "Feature",
  "properties": {
    "addr:full":"19 Chapin Rd Pine Brook NJ 07058",
    "addr:housenumber":"19",
    "addr:postcode":"07058",
    "addr:street":"Chapin Rd",
    "iso:country":"US",
    "sg:address":"19 Chapin Rd",
    "sg:city":"Pine Brook",
    "sg:classifiers":[
        {
            "category":"Professional",
            "subcategory":"Management & Consulting",
            "type":"Services"
        }
    ],
    "sg:phone":"+1 973 227 5844",
    "sg:postcode":"07058",
    "sg:province":"NJ",
    "sg:tags":[
        "logistics"
    ],
    "wof:name":"Brainstorm Logistics",
    "wof:placetype":"venue"
},
  "geometry": {"coordinates":[-74.338052,40.856241],"type":"Point"}
}