{
  "type": "Feature",
  "properties": {
    "iso:country":"US",
    "sg:address":"112 Featherbed Ln",
    "sg:city":"Stockton",
    "sg:classifiers":[
        {
            "category":"Building & Trades",
            "subcategory":"Plumbing",
            "type":"Services"
        }
    ],
    "sg:phone":"+1 908 996 5383",
    "sg:postcode":"08559",
    "sg:province":"NJ",
    "sg:tags":[
        "contractor"
    ],
    "wof:name":"Tin Man LLC",
    "wof:placetype":"venue"
},
  "geometry": {"coordinates":[-75.00008699999999,40.465812],"type":"Point"}
}