{
  "type": "Feature",
  "properties": {
    "iso:country":"US",
    "sg:address":"370 Howard Blvd",
    "sg:city":"Mount Arlington",
    "sg:classifiers":[
        {
            "category":"Shopping",
            "subcategory":"Gifts & Souvenirs",
            "type":"Retail Goods"
        }
    ],
    "sg:phone":"+1   ",
    "sg:postcode":"07856",
    "sg:province":"NJ",
    "wof:name":"Lee Annas Cft & Gifts Shoppe",
    "wof:placetype":"venue"
},
  "geometry": {"coordinates":[-74.634519,40.927844],"type":"Point"}
}