{
  "type": "Feature",
  "properties": {
    "addr:full":"9 Mount Pleasant Tpke Denville NJ 07834",
    "addr:housenumber":"9",
    "addr:postcode":"07834",
    "addr:street":"Mount Pleasant Tpke",
    "iso:country":"US",
    "sg:address":"9 Mount Pleasant Tpke",
    "sg:city":"Denville",
    "sg:classifiers":[
        {
            "category":"Social Services",
            "subcategory":"Child Care",
            "type":"Services"
        },
        {
            "category":"Education",
            "subcategory":"Preschool",
            "type":"Public Place"
        },
        {
            "category":"Education",
            "subcategory":"School",
            "type":"Public Place"
        }
    ],
    "sg:phone":"+1 973 537 8080",
    "sg:postcode":"07834",
    "sg:province":"NJ",
    "sg:tags":[
        "elementary",
        "day"
    ],
    "sg:website":"www.mothergoosekids.com",
    "wof:name":"Mother Goose Childcare Center",
    "wof:placetype":"venue"
},
  "geometry": {"coordinates":[-74.509012,40.865747],"type":"Point"}
}