{
  "type": "Feature",
  "properties": {
    "iso:country":"US",
    "sg:address":"661 Shunpike Rd Ste 1",
    "sg:city":"Green Village",
    "sg:classifiers":[
        {
            "category":"Health Services",
            "subcategory":"Dentist",
            "type":"Services"
        }
    ],
    "sg:phone":"+1 973 377 8811",
    "sg:postcode":"07935",
    "sg:province":"NJ",
    "wof:name":"Goodman Jeffrey A DMD",
    "wof:placetype":"venue"
},
  "geometry": {"coordinates":[-74.4328,40.746601],"type":"Point"}
}