{
  "type": "Feature",
  "properties": {
    "addr:full":"4 Hillcrest Ave Mendham NJ 07945",
    "addr:housenumber":"4",
    "addr:postcode":"07945",
    "addr:street":"Hillcrest Ave",
    "iso:country":"US",
    "sg:address":"4 Hillcrest Ave",
    "sg:city":"Mendham",
    "sg:classifiers":[
        {
            "category":"Real Estate",
            "subcategory":"Developer",
            "type":"Services"
        }
    ],
    "sg:phone":"+1 973 543 4386",
    "sg:postcode":"07945",
    "sg:province":"NJ",
    "sg:tags":[
        "cemetery"
    ],
    "wof:name":"Hilltop Cemetery",
    "wof:placetype":"venue"
},
  "geometry": {"coordinates":[-74.59604899999999,40.778536],"type":"Point"}
}