{
  "type": "Feature",
  "properties": {
    "iso:country":"US",
    "sg:address":"95 Harrison St",
    "sg:city":"Nutley",
    "sg:classifiers":[
        {
            "category":"Restaurant",
            "type":"Food & Drink"
        }
    ],
    "sg:phone":"+1 973 667 5400",
    "sg:postcode":"07110",
    "sg:province":"NJ",
    "sg:tags":[
        "deli",
        "delicatessen"
    ],
    "wof:name":"Bill-Tone's Deli & Catering",
    "wof:placetype":"venue"
},
  "geometry": {"coordinates":[-74.162498,40.809898],"type":"Point"}
}