{
  "type": "Feature",
  "properties": {
    "addr:full":"9 Raintree Ct Butler NJ 07405",
    "addr:housenumber":"9",
    "addr:postcode":"07405",
    "addr:street":"Raintree Ct",
    "iso:country":"US",
    "sg:address":"9 Raintree Ct",
    "sg:city":"Butler",
    "sg:classifiers":[
        {
            "category":"Professional",
            "subcategory":"Management & Consulting",
            "type":"Services"
        }
    ],
    "sg:phone":"+1   ",
    "sg:postcode":"07405",
    "sg:province":"NJ",
    "sg:tags":[
        "business"
    ],
    "wof:name":"Promar Consulting",
    "wof:placetype":"venue"
},
  "geometry": {"coordinates":[-74.356328,40.961128],"type":"Point"}
}