{
  "type": "Feature",
  "properties": {
    "addr:full":"37 W Broad St Paulsboro NJ 08066",
    "addr:housenumber":"37",
    "addr:postcode":"08066",
    "addr:street":"W Broad St",
    "iso:country":"US",
    "sg:address":"37 W Broad St",
    "sg:city":"Paulsboro",
    "sg:classifiers":[
        {
            "category":"Professional",
            "subcategory":"Advertising",
            "type":"Services"
        }
    ],
    "sg:phone":"+1   ",
    "sg:postcode":"08066",
    "sg:province":"NJ",
    "wof:name":"Hill Scenic",
    "wof:placetype":"venue"
},
  "geometry": {"coordinates":[-75.241574,39.830003],"type":"Point"}
}