{
  "type": "Feature",
  "properties": {
    "addr:full":"6 Vermont Dr Hazlet NJ 07730",
    "addr:housenumber":"6",
    "addr:postcode":"07730",
    "addr:street":"Vermont Dr",
    "iso:country":"US",
    "sg:address":"6 Vermont Dr",
    "sg:city":"Hazlet",
    "sg:classifiers":[
        {
            "category":"Building & Trades",
            "subcategory":"Landscaping Services",
            "type":"Services"
        }
    ],
    "sg:phone":"+1 732 739 0146",
    "sg:postcode":"07730",
    "sg:province":"NJ",
    "wof:name":"Bill Kelly Lawn Service",
    "wof:placetype":"venue"
},
  "geometry": {"coordinates":[-74.16494400000001,40.429498],"type":"Point"}
}