{
  "type": "Feature",
  "properties": {
    "addr:full":"1 Morley Rd North Brunswick NJ 08902",
    "addr:housenumber":"1",
    "addr:postcode":"08902",
    "addr:street":"Morley Rd",
    "iso:country":"US",
    "sg:address":"1 Morley Rd",
    "sg:city":"North Brunswick",
    "sg:classifiers":[
        {
            "category":"Professional",
            "type":"Services"
        }
    ],
    "sg:phone":"+1   ",
    "sg:postcode":"08902",
    "sg:province":"NJ",
    "wof:name":"Trottas Hideaway Inc",
    "wof:placetype":"venue"
},
  "geometry": {"coordinates":[-74.504167,40.419142],"type":"Point"}
}