{
  "type": "Feature",
  "properties": {
    "addr:full":"1029 Central Ave Westfield NJ 07090",
    "addr:housenumber":"1029",
    "addr:postcode":"07090",
    "addr:street":"Central Ave",
    "iso:country":"US",
    "sg:address":"1029 Central Ave",
    "sg:city":"Westfield",
    "sg:classifiers":[
        {
            "category":"Government",
            "subcategory":"Fire Station",
            "type":"Public Place"
        }
    ],
    "sg:phone":"+1 908 789 4140",
    "sg:postcode":"07090",
    "sg:province":"NJ",
    "sg:tags":[
        "department"
    ],
    "wof:name":"Westfield Fire Dept",
    "wof:placetype":"venue"
},
  "geometry": {"coordinates":[-74.330842,40.642921],"type":"Point"}
}