{
  "type": "Feature",
  "properties": {
    "iso:country":"US",
    "sg:address":"21 Nashua Dr",
    "sg:city":"Marlboro",
    "sg:classifiers":[
        {
            "category":"Professional",
            "type":"Services"
        }
    ],
    "sg:phone":"+1   ",
    "sg:postcode":"07746",
    "sg:province":"NJ",
    "wof:name":"Reed CC Inc",
    "wof:placetype":"venue"
},
  "geometry": {"coordinates":[-74.27636099999999,40.30324],"type":"Point"}
}