{
  "type": "Feature",
  "properties": {
    "iso:country":"US",
    "sg:address":"13 Johnson Rd",
    "sg:city":"Somerset",
    "sg:classifiers":[
        {
            "category":"Professional",
            "subcategory":"Engineering",
            "type":"Services"
        }
    ],
    "sg:phone":"+1 732 828 3096",
    "sg:postcode":"08873",
    "sg:province":"NJ",
    "sg:tags":[
        "business"
    ],
    "wof:name":"Lrp Engineering Inc",
    "wof:placetype":"venue"
},
  "geometry": {"coordinates":[-74.494632,40.492515],"type":"Point"}
}