{
  "type": "Feature",
  "properties": {
    "iso:country":"US",
    "sg:address":"1750 Deptford Center Rd",
    "sg:city":"Woodbury",
    "sg:classifiers":[
        {
            "category":"Wholesale",
            "subcategory":"Hardware",
            "type":"Manufacturing & Wholesale Goods"
        }
    ],
    "sg:phone":"+1 856 848 0001",
    "sg:postcode":"08096",
    "sg:province":"NJ",
    "sg:tags":[
        "refrigeration"
    ],
    "wof:name":"Soda Club USA Inc",
    "wof:placetype":"venue"
},
  "geometry": {"coordinates":[-75.097632,39.828297],"type":"Point"}
}