{
  "type": "Feature",
  "properties": {
    "iso:country":"US",
    "sg:address":"154 Marsh St",
    "sg:city":"Newark",
    "sg:classifiers":[
        {
            "category":"Freight",
            "type":"Transportation"
        }
    ],
    "sg:phone":"+1 973 589 4044",
    "sg:postcode":"07114",
    "sg:province":"NJ",
    "sg:tags":[
        "bulk",
        "storage"
    ],
    "wof:name":"Citrus Products Inc",
    "wof:placetype":"venue"
},
  "geometry": {"coordinates":[-74.14614899999999,40.69338],"type":"Point"}
}