{
  "type": "Feature",
  "properties": {
    "addr:full":"17 Sylvan St Rutherford NJ 07070",
    "addr:housenumber":"17",
    "addr:postcode":"07070",
    "addr:street":"Sylvan St",
    "iso:country":"US",
    "sg:address":"17 Sylvan St",
    "sg:city":"Rutherford",
    "sg:classifiers":[
        {
            "category":"Health Services",
            "subcategory":"Medical Lab",
            "type":"Services"
        }
    ],
    "sg:phone":"+1 201 460 0016",
    "sg:postcode":"07070",
    "sg:province":"NJ",
    "sg:tags":[
        "laboratory"
    ],
    "wof:name":"Quest Diagnostics",
    "wof:placetype":"venue"
},
  "geometry": {"coordinates":[-74.104106,40.82649],"type":"Point"}
}