{
  "type": "Feature",
  "properties": {
    "iso:country":"US",
    "sg:address":"1515 US Hwy 22",
    "sg:city":"Watchung",
    "sg:classifiers":[
        {
            "category":"Personal",
            "subcategory":"Beauty Salon",
            "type":"Services"
        }
    ],
    "sg:phone":"+1 908 791 0030",
    "sg:postcode":"07069",
    "sg:province":"NJ",
    "sg:tags":[
        "manicuring"
    ],
    "wof:name":"Nail Beauty Spa",
    "wof:placetype":"venue"
},
  "geometry": {"coordinates":[-74.415847,40.641182],"type":"Point"}
}