{
  "type": "Feature",
  "properties": {
    "iso:country":"US",
    "sg:address":"26 Main St",
    "sg:city":"Chatham",
    "sg:classifiers":[
        {
            "category":"Education",
            "subcategory":"Special Training",
            "type":"Public Place"
        },
        {
            "category":"Education",
            "subcategory":"University",
            "type":"Public Place"
        }
    ],
    "sg:phone":"+1 973 738 5800",
    "sg:postcode":"07928",
    "sg:province":"NJ",
    "sg:tags":[
        "school",
        "college",
        "specialty"
    ],
    "wof:name":"Medimedia USA-Trigenesis",
    "wof:placetype":"venue"
},
  "geometry": {"coordinates":[-74.373199,40.7393],"type":"Point"}
}