{
  "type": "Feature",
  "properties": {
    "addr:full":"1812 Front St Scotch Plains NJ 07076",
    "addr:housenumber":"1812",
    "addr:postcode":"07076",
    "addr:street":"Front St",
    "iso:country":"US",
    "sg:address":"1812 Front St",
    "sg:city":"Scotch Plains",
    "sg:classifiers":[
        {
            "category":"Professional",
            "type":"Services"
        }
    ],
    "sg:phone":"+1 908 322 9352",
    "sg:postcode":"07076",
    "sg:province":"NJ",
    "sg:tags":[
        "establishment"
    ],
    "wof:name":"Peter Thom & Assoc Inc",
    "wof:placetype":"venue"
},
  "geometry": {"coordinates":[-74.39931900000001,40.649733],"type":"Point"}
}