{
  "type": "Feature",
  "properties": {
    "iso:country":"US",
    "sg:address":"700 Chestnut St",
    "sg:city":"Secaucus",
    "sg:classifiers":[
        {
            "category":"Local Transit",
            "type":"Transportation"
        }
    ],
    "sg:phone":"+1 201 865 6607",
    "sg:postcode":"07094",
    "sg:province":"NJ",
    "sg:tags":[
        "passenger"
    ],
    "wof:name":"Tamers Limo",
    "wof:placetype":"venue"
},
  "geometry": {"coordinates":[-74.05731299999999,40.788297],"type":"Point"}
}