{
  "type": "Feature",
  "properties": {
    "iso:country":"US",
    "sg:address":"3724 S Village Dr",
    "sg:city":"Avenel",
    "sg:classifiers":[
        {
            "category":"Restaurant",
            "type":"Food & Drink"
        }
    ],
    "sg:phone":"+1   ",
    "sg:postcode":"07001",
    "sg:province":"NJ",
    "sg:tags":[
        "eating"
    ],
    "wof:name":"Dountin Donuts",
    "wof:placetype":"venue"
},
  "geometry": {"coordinates":[-74.28423600000001,40.591087],"type":"Point"}
}