{
  "type": "Feature",
  "properties": {
    "iso:country":"US",
    "sg:address":"100 United Ln",
    "sg:city":"Teterboro",
    "sg:classifiers":[
        {
            "category":"Retail",
            "subcategory":"Animal Services",
            "type":"Services"
        }
    ],
    "sg:phone":"+1 201 229 4600",
    "sg:postcode":"07608",
    "sg:province":"NJ",
    "sg:tags":[
        "shelter",
        "veterinary",
        "specialty"
    ],
    "sg:website":"http://www.bergen4business.com",
    "wof:name":"Health Services",
    "wof:placetype":"venue"
},
  "geometry": {"coordinates":[-74.070435,40.854385],"type":"Point"}
}