{
  "type": "Feature",
  "properties": {
    "iso:country":"US",
    "sg:address":"101 E Peddie St",
    "sg:city":"Newark",
    "sg:classifiers":[
        {
            "category":"Freight",
            "type":"Transportation"
        }
    ],
    "sg:phone":"+1 973 733 4990",
    "sg:postcode":"07114",
    "sg:province":"NJ",
    "sg:tags":[
        "trucking"
    ],
    "wof:name":"Container Perk Group",
    "wof:placetype":"venue"
},
  "geometry": {"coordinates":[-74.187388,40.711192],"type":"Point"}
}