{
  "type": "Feature",
  "properties": {
    "iso:country":"US",
    "sg:address":"1219 Park Ave",
    "sg:city":"Hoboken",
    "sg:classifiers":[
        {
            "category":"Building & Trades",
            "subcategory":"Plumbing",
            "type":"Services"
        }
    ],
    "sg:phone":"+1 201 656 6400",
    "sg:postcode":"07030",
    "sg:province":"NJ",
    "sg:tags":[
        "contractor"
    ],
    "wof:name":"Real Energy Inc",
    "wof:placetype":"venue"
},
  "geometry": {"coordinates":[-74.02905800000001,40.752568],"type":"Point"}
}