{
  "type": "Feature",
  "properties": {
    "addr:full":"1520 Co Rd 539 Little Egg Hbr NJ 08087",
    "addr:housenumber":"1520;539",
    "addr:postcode":"08087",
    "addr:street":"Co Rd;Little",
    "iso:country":"US",
    "sg:address":"1520 Co Rd 539",
    "sg:city":"Little Egg Hbr",
    "sg:classifiers":[
        {
            "category":"Autos & Motor Vehicles",
            "subcategory":"Fuel & Gas Station",
            "type":"Retail Goods"
        }
    ],
    "sg:phone":"+1 609 296 6806",
    "sg:postcode":"08087",
    "sg:province":"NJ",
    "sg:tags":[
        "oil"
    ],
    "wof:name":"Shell",
    "wof:placetype":"venue"
},
  "geometry": {"coordinates":[-74.343014,39.650167],"type":"Point"}
}