{
  "type": "Feature",
  "properties": {
    "addr:full":"1155 State Rte 33 Neptune NJ 07753",
    "addr:housenumber":"1155",
    "addr:postcode":"07753",
    "addr:street":"State Rte 33",
    "iso:country":"US",
    "sg:address":"1155 State Rte 33",
    "sg:city":"Neptune",
    "sg:classifiers":[
        {
            "category":"Building & Trades",
            "subcategory":"Construction",
            "type":"Services"
        }
    ],
    "sg:phone":"+1 732 775 5800",
    "sg:postcode":"07753",
    "sg:province":"NJ",
    "sg:tags":[
        "general",
        "contractor"
    ],
    "wof:name":"Turner Construction Co",
    "wof:placetype":"venue"
},
  "geometry": {"coordinates":[-74.01862800000001,40.210575],"type":"Point"}
}