{
  "type": "Feature",
  "properties": {
    "iso:country":"US",
    "sg:address":"5711 6th Ave",
    "sg:city":"Brooklyn",
    "sg:classifiers":[
        {
            "category":"Shopping",
            "subcategory":"Pharmacy",
            "type":"Retail Goods"
        }
    ],
    "sg:phone":"+1 718 680 1982",
    "sg:postcode":"11220",
    "sg:province":"NY",
    "sg:tags":[
        "drugstore"
    ],
    "wof:name":"Loving Pharmacy Inc",
    "wof:placetype":"venue"
},
  "geometry": {"coordinates":[-74.208579,40.639693],"type":"Point"}
}