{
  "type": "Feature",
  "properties": {
    "addr:full":"942 Sigsbee Ave Phillipsburg NJ 08865",
    "addr:housenumber":"942",
    "addr:postcode":"08865",
    "addr:street":"Sigsbee Ave",
    "iso:country":"US",
    "sg:address":"942 Sigsbee Ave",
    "sg:city":"Phillipsburg",
    "sg:classifiers":[
        {
            "category":"Personal",
            "subcategory":"Barber",
            "type":"Services"
        }
    ],
    "sg:phone":"+1   ",
    "sg:postcode":"08865",
    "sg:province":"NJ",
    "sg:tags":[
        "shop"
    ],
    "wof:name":"Petes Alpha Barber Shop",
    "wof:placetype":"venue"
},
  "geometry": {"coordinates":[-75.16607500000001,40.660941],"type":"Point"}
}