{
  "type": "Feature",
  "properties": {
    "addr:full":"766 School House Ln Bound Brook NJ 08805",
    "addr:housenumber":"766",
    "addr:postcode":"08805",
    "addr:street":"School House Ln",
    "iso:country":"US",
    "sg:address":"766 School House Ln",
    "sg:city":"Bound Brook",
    "sg:classifiers":[
        {
            "category":"Professional",
            "type":"Services"
        }
    ],
    "sg:phone":"+1   ",
    "sg:postcode":"08805",
    "sg:province":"NJ",
    "wof:name":"Jock Lewendon",
    "wof:placetype":"venue"
},
  "geometry": {"coordinates":[-74.53330800000001,40.577033],"type":"Point"}
}