{
  "type": "Feature",
  "properties": {
    "addr:full":"1519 Waters Edge Dr Toms River NJ 08753",
    "addr:housenumber":"1519",
    "addr:postcode":"08753",
    "addr:street":"Waters Edge Dr",
    "iso:country":"US",
    "sg:address":"1519 Waters Edge Dr",
    "sg:city":"Toms River",
    "sg:classifiers":[
        {
            "category":"Retail",
            "subcategory":"Self-service Laundry",
            "type":"Services"
        }
    ],
    "sg:phone":"+1 732 803 0164",
    "sg:postcode":"08753",
    "sg:province":"NJ",
    "sg:tags":[
        "coin"
    ],
    "wof:name":"It All Comes Out In The Wash",
    "wof:placetype":"venue"
},
  "geometry": {"coordinates":[-74.14735400000001,39.997829],"type":"Point"}
}