{
  "type": "Feature",
  "properties": {
    "iso:country":"US",
    "sg:address":"U.S. 46 and Hamilton Ave",
    "sg:city":"Lodi",
    "sg:classifiers":[
        {
            "category":"Restaurant",
            "type":"Food & Drink"
        },
        {
            "category":"Food & Beverages",
            "subcategory":"Bakery",
            "type":"Retail Goods"
        }
    ],
    "sg:phone":"+1 973 478 3306",
    "sg:postcode":"07644",
    "sg:province":"NJ",
    "sg:tags":[
        "sandwich",
        "pizza"
    ],
    "wof:name":"Lodi Pizza Restaurant",
    "wof:placetype":"venue"
},
  "geometry": {"coordinates":[-74.088662,40.885004],"type":"Point"}
}