{
  "type": "Feature",
  "properties": {
    "addr:full":"953 Clinton Ave Irvington NJ 07111",
    "addr:housenumber":"953",
    "addr:postcode":"07111",
    "addr:street":"Clinton Ave",
    "iso:country":"US",
    "sg:address":"953 Clinton Ave",
    "sg:city":"Irvington",
    "sg:classifiers":[
        {
            "category":"Wholesale",
            "subcategory":"Hardware",
            "type":"Manufacturing & Wholesale Goods"
        }
    ],
    "sg:phone":"+1 973 242 0882",
    "sg:postcode":"07111",
    "sg:province":"NJ",
    "sg:tags":[
        "refrigeration"
    ],
    "wof:name":"Freezeright Refrigeration & AC",
    "wof:placetype":"venue"
},
  "geometry": {"coordinates":[-74.24402499999999,40.730697],"type":"Point"}
}