{
  "type": "Feature",
  "properties": {
    "addr:full":"339 Pompton Ave Cedar Grove NJ 07009",
    "addr:housenumber":"339",
    "addr:postcode":"07009",
    "addr:street":"Pompton Ave",
    "iso:country":"US",
    "sg:address":"339 Pompton Ave",
    "sg:city":"Cedar Grove",
    "sg:classifiers":[
        {
            "category":"Organizations",
            "subcategory":"Religious Organization",
            "type":"Services"
        }
    ],
    "sg:phone":"+1 973 239 7960",
    "sg:postcode":"07009",
    "sg:province":"NJ",
    "sg:tags":[
        "church"
    ],
    "wof:name":"St Catherine Of Siena",
    "wof:placetype":"venue"
},
  "geometry": {"coordinates":[-74.228313,40.844445],"type":"Point"}
}