{
  "type": "Feature",
  "properties": {
    "iso:country":"US",
    "sg:address":"433 Palisade Ave",
    "sg:city":"Jersey City",
    "sg:classifiers":[
        {
            "category":"Organizations",
            "subcategory":"Political Organization",
            "type":"Services"
        }
    ],
    "sg:phone":"+1 201 963 7091",
    "sg:postcode":"07307",
    "sg:province":"NJ",
    "wof:name":"New Jersey City Democratic",
    "wof:placetype":"venue"
},
  "geometry": {"coordinates":[-74.044995,40.742844],"type":"Point"}
}