{
  "type": "Feature",
  "properties": {
    "addr:full":"1202 Main Ave Clifton NJ 07011",
    "addr:housenumber":"1202",
    "addr:postcode":"07011",
    "addr:street":"Main Ave",
    "iso:country":"US",
    "sg:address":"1202 Main Ave",
    "sg:city":"Clifton",
    "sg:classifiers":[
        {
            "category":"Food & Beverages",
            "subcategory":"Groceries & Convenience Stores",
            "type":"Retail Goods"
        }
    ],
    "sg:phone":"+1 973 546 0488",
    "sg:postcode":"07011",
    "sg:province":"NJ",
    "sg:website":"www.7-eleven.com",
    "wof:name":"7-Eleven",
    "wof:placetype":"venue"
},
  "geometry": {"coordinates":[-74.141098,40.876999],"type":"Point"}
}