{
  "type": "Feature",
  "properties": {
    "addr:full":"15 Barnet St Rockaway NJ 07866",
    "addr:housenumber":"15",
    "addr:postcode":"07866",
    "addr:street":"Barnet St",
    "iso:country":"US",
    "sg:address":"15 Barnet St",
    "sg:city":"Rockaway",
    "sg:classifiers":[
        {
            "category":"Professional",
            "subcategory":"Business Services",
            "type":"Services"
        }
    ],
    "sg:phone":"+1   ",
    "sg:postcode":"07866",
    "sg:province":"NJ",
    "wof:name":"Interiors By Sam Sapio",
    "wof:placetype":"venue"
},
  "geometry": {"coordinates":[-74.507789,40.908802],"type":"Point"}
}