{
  "type": "Feature",
  "properties": {
    "addr:full":"40 South Ave Fanwood NJ 07023",
    "addr:housenumber":"40",
    "addr:postcode":"07023",
    "addr:street":"South Ave",
    "iso:country":"US",
    "sg:address":"40 South Ave",
    "sg:city":"Fanwood",
    "sg:classifiers":[
        {
            "category":"Restaurant",
            "type":"Food & Drink"
        }
    ],
    "sg:menulink":"http://www.allmenus.com/nj/fanwood/15744-il-sogno/menu/",
    "sg:phone":"+1 908 322 6555",
    "sg:postcode":"07023",
    "sg:province":"NJ",
    "sg:tags":[
        "italian"
    ],
    "wof:name":"Il Sogno",
    "wof:placetype":"venue"
},
  "geometry": {"coordinates":[-74.391428,40.635861],"type":"Point"}
}