{
  "type": "Feature",
  "properties": {
    "iso:country":"US",
    "sg:address":"344 S Main St",
    "sg:city":"South Hackensack",
    "sg:classifiers":[
        {
            "category":"Autos & Motor Vehicles",
            "subcategory":"Automobile Sales",
            "type":"Retail Goods"
        }
    ],
    "sg:phone":"+1 201 440 1277",
    "sg:postcode":"07606",
    "sg:province":"NJ",
    "sg:tags":[
        "car",
        "dealer"
    ],
    "wof:name":"Tack Motors",
    "wof:placetype":"venue"
},
  "geometry": {"coordinates":[-74.04664200000001,40.869587],"type":"Point"}
}