{
  "type": "Feature",
  "properties": {
    "addr:full":"166 River Drive Ave Pennsville NJ 08070",
    "addr:housenumber":"166",
    "addr:postcode":"08070",
    "addr:street":"River Drive Ave",
    "iso:country":"US",
    "sg:address":"166 River Drive Ave",
    "sg:city":"Pennsville",
    "sg:classifiers":[
        {
            "category":"Organizations",
            "subcategory":"Religious Organization",
            "type":"Services"
        }
    ],
    "sg:phone":"+1   ",
    "sg:postcode":"08070",
    "sg:province":"NJ",
    "wof:name":"Trinity United Methdst Chruch",
    "wof:placetype":"venue"
},
  "geometry": {"coordinates":[-75.52067099999999,39.648769],"type":"Point"}
}