{
  "type": "Feature",
  "properties": {
    "addr:full":"395 State Rte 70 Lakewood NJ 08701",
    "addr:housenumber":"395",
    "addr:postcode":"08701",
    "addr:street":"State Rte 70",
    "iso:country":"US",
    "sg:address":"395 State Rte 70",
    "sg:city":"Lakewood",
    "sg:classifiers":[
        {
            "category":"Social Services",
            "subcategory":"Adult Care",
            "type":"Services"
        },
        {
            "category":"Social Services",
            "type":"Services"
        }
    ],
    "sg:phone":"+1 732 730 0700",
    "sg:postcode":"08701",
    "sg:province":"NJ",
    "sg:tags":[
        "organization",
        "senior",
        "citizen"
    ],
    "wof:name":"Caregivers Of Lakewood Inc",
    "wof:placetype":"venue"
},
  "geometry": {"coordinates":[-74.20804099999999,40.048966],"type":"Point"}
}