{
  "type": "Feature",
  "properties": {
    "addr:full":"1468 Blackwood Clementon Rd Clementon NJ 08021",
    "addr:housenumber":"1468",
    "addr:postcode":"08021",
    "addr:street":"Blackwood Clementon Rd",
    "iso:country":"US",
    "sg:address":"1468 Blackwood Clementon Rd",
    "sg:city":"Clementon",
    "sg:classifiers":[
        {
            "category":"Shopping",
            "subcategory":"Jewelry",
            "type":"Retail Goods"
        }
    ],
    "sg:phone":"+1 856 346 1600",
    "sg:postcode":"08021",
    "sg:province":"NJ",
    "sg:tags":[
        "repair",
        "jeweler"
    ],
    "sg:website":"www.mydiamondhunt.com/anthonysimon",
    "wof:name":"Anthony Simon Jewelers Inc",
    "wof:placetype":"venue"
},
  "geometry": {"coordinates":[-75.03898100000001,39.803408],"type":"Point"}
}