{
  "type": "Feature",
  "properties": {
    "addr:full":"725 Vasser Ave Lakewood NJ 08701",
    "addr:housenumber":"725",
    "addr:postcode":"08701",
    "addr:street":"Vasser Ave",
    "iso:country":"US",
    "sg:address":"725 Vasser Ave",
    "sg:city":"Lakewood",
    "sg:classifiers":[
        {
            "category":"Professional",
            "type":"Services"
        }
    ],
    "sg:phone":"+1 732 942 6740",
    "sg:postcode":"08701",
    "sg:province":"NJ",
    "sg:tags":[
        "establishment"
    ],
    "wof:name":"Dutch Gardens",
    "wof:placetype":"venue"
},
  "geometry": {"coordinates":[-74.18024,40.069326],"type":"Point"}
}