{
  "type": "Feature",
  "properties": {
    "iso:country":"US",
    "sg:address":"505 Main St",
    "sg:city":"Hackensack",
    "sg:classifiers":[
        {
            "category":"Professional",
            "subcategory":"Lawyer & Legal Services",
            "type":"Services"
        }
    ],
    "sg:phone":"+1 201 488 1551",
    "sg:postcode":"07601",
    "sg:province":"NJ",
    "wof:name":"Lawrence Bell Attorney",
    "wof:placetype":"venue"
},
  "geometry": {"coordinates":[-74.039609,40.894417],"type":"Point"}
}