{
  "type": "Feature",
  "properties": {
    "iso:country":"US",
    "sg:address":"24 S South Carolina Ave",
    "sg:city":"Atlantic City",
    "sg:classifiers":[
        {
            "category":"Health Services",
            "subcategory":"Doctor",
            "type":"Services"
        }
    ],
    "sg:phone":"+1 609 345 6000",
    "sg:postcode":"08401",
    "sg:province":"NJ",
    "sg:tags":[
        "physician",
        "surgeon"
    ],
    "wof:name":"Health Med Assoc PC",
    "wof:placetype":"venue"
},
  "geometry": {"coordinates":[-74.42616,39.361616],"type":"Point"}
}