{
  "type": "Feature",
  "properties": {
    "iso:country":"US",
    "sg:address":"801 Philadelphia Ave",
    "sg:city":"Egg Harbor City",
    "sg:classifiers":[
        {
            "category":"Manufacturing",
            "subcategory":"Watercraft",
            "type":"Manufacturing & Wholesale Goods"
        }
    ],
    "sg:phone":"+1 609 965 2300",
    "sg:postcode":"08215",
    "sg:province":"NJ",
    "sg:tags":[
        "boat"
    ],
    "sg:website":"www.eggharboryachts.com",
    "wof:name":"Egg Harbor Yachts",
    "wof:placetype":"venue"
},
  "geometry": {"coordinates":[-74.635633,39.539083],"type":"Point"}
}