{
  "type": "Feature",
  "properties": {
    "iso:country":"US",
    "sg:address":"2004 State Rte 31",
    "sg:city":"Clinton",
    "sg:classifiers":[
        {
            "category":"Personal",
            "subcategory":"Beauty Salon",
            "type":"Services"
        }
    ],
    "sg:phone":"+1 908 638 8101",
    "sg:postcode":"08809",
    "sg:province":"NJ",
    "wof:name":"Kerri's Klaws & Hair Boutique",
    "wof:placetype":"venue"
},
  "geometry": {"coordinates":[-74.915233,40.670702],"type":"Point"}
}