{
  "type": "Feature",
  "properties": {
    "addr:full":"5 Franklin Ave Leonardo NJ 07737",
    "addr:housenumber":"5",
    "addr:postcode":"07737",
    "addr:street":"Franklin Ave",
    "iso:country":"US",
    "sg:address":"5 Franklin Ave",
    "sg:city":"Leonardo",
    "sg:classifiers":[
        {
            "category":"Building & Trades",
            "subcategory":"Construction",
            "type":"Services"
        }
    ],
    "sg:phone":"+1 732 872 8541",
    "sg:postcode":"07737",
    "sg:province":"NJ",
    "sg:tags":[
        "concrete",
        "contractor"
    ],
    "wof:name":"B & W Services Inc",
    "wof:placetype":"venue"
},
  "geometry": {"coordinates":[-74.05748699999999,40.421179],"type":"Point"}
}