{
  "type": "Feature",
  "properties": {
    "iso:country":"US",
    "sg:address":"63 Lacey Rd",
    "sg:city":"Lakehurst",
    "sg:classifiers":[
        {
            "category":"Health Services",
            "subcategory":"Optometrist",
            "type":"Services"
        }
    ],
    "sg:phone":"+1   ",
    "sg:postcode":"08759",
    "sg:province":"NJ",
    "wof:name":"HealthSouth",
    "wof:placetype":"venue"
},
  "geometry": {"coordinates":[-74.36491599999999,39.947635],"type":"Point"}
}