{
  "type": "Feature",
  "properties": {
    "addr:full":"930 Clifton Ave Clifton NJ 07013",
    "addr:housenumber":"930",
    "addr:postcode":"07013",
    "addr:street":"Clifton Ave",
    "iso:country":"US",
    "sg:address":"930 Clifton Ave",
    "sg:city":"Clifton",
    "sg:classifiers":[
        {
            "category":"Health Services",
            "subcategory":"Doctor",
            "type":"Services"
        }
    ],
    "sg:phone":"+1 973 778 2665",
    "sg:postcode":"07013",
    "sg:province":"NJ",
    "sg:tags":[
        "medical"
    ],
    "wof:name":"Jo Young I MD",
    "wof:placetype":"venue"
},
  "geometry": {"coordinates":[-74.162003,40.864799],"type":"Point"}
}