{
  "type": "Feature",
  "properties": {
    "iso:country":"US",
    "sg:address":"26 Washington Park",
    "sg:city":"Maplewood",
    "sg:classifiers":[
        {
            "category":"Health Services",
            "subcategory":"Doctor",
            "type":"Services"
        }
    ],
    "sg:phone":"+1 973 762 8164",
    "sg:postcode":"07040",
    "sg:province":"NJ",
    "sg:tags":[
        "medical"
    ],
    "wof:name":"International Exposition Cons",
    "wof:placetype":"venue"
},
  "geometry": {"coordinates":[-74.27436899999999,40.741907],"type":"Point"}
}