{
  "type": "Feature",
  "properties": {
    "iso:country":"US",
    "sg:address":"575 Martin Luther King Jr Blvd",
    "sg:city":"Newark",
    "sg:classifiers":[
        {
            "category":"Health Services",
            "subcategory":"Optometrist",
            "type":"Services"
        }
    ],
    "sg:phone":"+1 973 622 2877",
    "sg:postcode":"07102",
    "sg:province":"NJ",
    "wof:name":"Steven Ehrenworth OD",
    "wof:placetype":"venue"
},
  "geometry": {"coordinates":[-74.18107500000001,40.73311],"type":"Point"}
}