{
  "type": "Feature",
  "properties": {
    "addr:full":"130 State St Camden NJ 08102",
    "addr:housenumber":"130",
    "addr:postcode":"08102",
    "addr:street":"State St",
    "iso:country":"US",
    "sg:address":"130 State St",
    "sg:city":"Camden",
    "sg:classifiers":[
        {
            "category":"Wholesale",
            "subcategory":"Machinery & Supplies",
            "type":"Manufacturing & Wholesale Goods"
        }
    ],
    "sg:phone":"+1 856 486 0273",
    "sg:postcode":"08102",
    "sg:province":"NJ",
    "sg:tags":[
        "equipment",
        "establishment"
    ],
    "wof:name":"Save More Beauty Supplies",
    "wof:placetype":"venue"
},
  "geometry": {"coordinates":[-75.123919,39.953758],"type":"Point"}
}