{
  "type": "Feature",
  "properties": {
    "iso:country":"US",
    "sg:address":"403 County Rd",
    "sg:city":"Cliffwood",
    "sg:classifiers":[
        {
            "category":"Manufacturing",
            "subcategory":"Tools & Machinery",
            "type":"Manufacturing & Wholesale Goods"
        }
    ],
    "sg:phone":"+1 732 441 0622",
    "sg:postcode":"07721",
    "sg:province":"NJ",
    "sg:tags":[
        "equipment",
        "electric"
    ],
    "wof:name":"Powerware",
    "wof:placetype":"venue"
},
  "geometry": {"coordinates":[-74.23105200000001,40.442127],"type":"Point"}
}