{
  "type": "Feature",
  "properties": {
    "addr:full":"80 4th Ave Trenton NJ 08619",
    "addr:housenumber":"80",
    "addr:postcode":"08619",
    "addr:street":"4Th Ave",
    "iso:country":"US",
    "sg:address":"80 4th Ave",
    "sg:city":"Trenton",
    "sg:classifiers":[
        {
            "category":"Retail",
            "subcategory":"Repair Shop",
            "type":"Services"
        }
    ],
    "sg:phone":"+1 609 586 3203",
    "sg:postcode":"08619",
    "sg:province":"NJ",
    "sg:tags":[
        "television",
        "radio-service"
    ],
    "wof:name":"Evans Tv & Electronics Service",
    "wof:placetype":"venue"
},
  "geometry": {"coordinates":[-74.728554,40.24374],"type":"Point"}
}