{
  "type": "Feature",
  "properties": {
    "iso:country":"US",
    "sg:address":"47 Newark St",
    "sg:city":"Hoboken",
    "sg:classifiers":[
        {
            "category":"Professional",
            "subcategory":"Computer Services",
            "type":"Services"
        }
    ],
    "sg:phone":"+1   ",
    "sg:postcode":"07030",
    "sg:province":"NJ",
    "sg:tags":[
        "consulting"
    ],
    "wof:name":"Mvp Specialists Inc",
    "wof:placetype":"venue"
},
  "geometry": {"coordinates":[-74.029346,40.736452],"type":"Point"}
}