{
  "type": "Feature",
  "properties": {
    "iso:country":"US",
    "sg:address":"4419 Bergenline Ave",
    "sg:city":"Union City",
    "sg:classifiers":[
        {
            "category":"Shopping",
            "subcategory":"Clothing, Apparel, & Fashions",
            "type":"Retail Goods"
        }
    ],
    "sg:phone":"+1 201 866 2212",
    "sg:postcode":"07087",
    "sg:province":"NJ",
    "sg:tags":[
        "furnishing"
    ],
    "wof:name":"Milano",
    "wof:placetype":"venue"
},
  "geometry": {"coordinates":[-74.023685,40.779344],"type":"Point"}
}