{
  "type": "Feature",
  "properties": {
    "iso:country":"US",
    "sg:address":"195 Changebridge Rd",
    "sg:city":"Montville",
    "sg:classifiers":[
        {
            "category":"Government",
            "subcategory":"Office",
            "type":"Public Place"
        }
    ],
    "sg:phone":"+1 973 331 3319",
    "sg:postcode":"07045",
    "sg:province":"NJ",
    "sg:tags":[
        "village"
    ],
    "wof:name":"Montville Planning Bd-Land Use",
    "wof:placetype":"venue"
},
  "geometry": {"coordinates":[-74.364853,40.884107],"type":"Point"}
}