{
  "type": "Feature",
  "properties": {
    "addr:full":"525 3rd Ave North Brunswick NJ 08902",
    "addr:housenumber":"525",
    "addr:postcode":"08902",
    "addr:street":"3Rd Ave",
    "iso:country":"US",
    "sg:address":"525 3rd Ave",
    "sg:city":"North Brunswick",
    "sg:classifiers":[
        {
            "category":"Travel",
            "subcategory":"Hotels & Motels",
            "type":"Entertainment"
        }
    ],
    "sg:phone":"+1 732 545 7099",
    "sg:postcode":"08902",
    "sg:province":"NJ",
    "sg:tags":[
        "operation"
    ],
    "wof:name":"Holiday Inn",
    "wof:placetype":"venue"
},
  "geometry": {"coordinates":[-74.44865900000001,40.46852],"type":"Point"}
}