{
  "type": "Feature",
  "properties": {
    "addr:full":"299 Kings Rd Madison NJ 07940",
    "addr:housenumber":"299",
    "addr:postcode":"07940",
    "addr:street":"Kings Rd",
    "iso:country":"US",
    "sg:address":"299 Kings Rd",
    "sg:city":"Madison",
    "sg:classifiers":[
        {
            "category":"Professional",
            "subcategory":"Business Services",
            "type":"Services"
        }
    ],
    "sg:phone":"+1   ",
    "sg:postcode":"07940",
    "sg:province":"NJ",
    "wof:name":"Integrated Telecom Corp",
    "wof:placetype":"venue"
},
  "geometry": {"coordinates":[-74.398571,40.745457],"type":"Point"}
}