{
  "type": "Feature",
  "properties": {
    "iso:country":"US",
    "sg:address":"310 Paterson Plank Rd",
    "sg:city":"Carlstadt",
    "sg:classifiers":[
        {
            "category":"Freight",
            "type":"Transportation"
        }
    ],
    "sg:phone":"+1 732 882 1800",
    "sg:postcode":"07072",
    "sg:province":"NJ",
    "sg:tags":[
        "trucking"
    ],
    "wof:name":"International Transport Sltns",
    "wof:placetype":"venue"
},
  "geometry": {"coordinates":[-74.088336,40.833039],"type":"Point"}
}