{
  "type": "Feature",
  "properties": {
    "addr:full":"2 Green St Somerville NJ 08876",
    "addr:housenumber":"2",
    "addr:postcode":"08876",
    "addr:street":"Green St",
    "iso:country":"US",
    "sg:address":"2 Green St",
    "sg:city":"Somerville",
    "sg:classifiers":[
        {
            "category":"Social Services",
            "subcategory":"Child Care",
            "type":"Services"
        }
    ],
    "sg:phone":"+1 908 231 0956",
    "sg:postcode":"08876",
    "sg:province":"NJ",
    "sg:tags":[
        "day"
    ],
    "wof:name":"Kiddie Cornr Dy Care CT Somers",
    "wof:placetype":"venue"
},
  "geometry": {"coordinates":[-74.614307,40.574572],"type":"Point"}
}