{
  "type": "Feature",
  "properties": {
    "addr:full":"31 Madison Plz Madison NJ 07940",
    "addr:housenumber":"31",
    "addr:postcode":"07940",
    "addr:street":"Madison Plz",
    "iso:country":"US",
    "sg:address":"31 Madison Plz",
    "sg:city":"Madison",
    "sg:classifiers":[
        {
            "category":"Shopping",
            "subcategory":"Computers & Home Electronics",
            "type":"Retail Goods"
        }
    ],
    "sg:phone":"+1 973 822 0461",
    "sg:postcode":"07940",
    "sg:province":"NJ",
    "sg:tags":[
        "equipment",
        "electronic",
        "supply"
    ],
    "sg:website":"www.radioshack.com",
    "wof:name":"Radio Shack",
    "wof:placetype":"venue"
},
  "geometry": {"coordinates":[-74.422624,40.763403],"type":"Point"}
}