{
  "type": "Feature",
  "properties": {
    "addr:full":"1340 Fairview Blvd Delran NJ 08075",
    "addr:housenumber":"1340",
    "addr:postcode":"08075",
    "addr:street":"Fairview Blvd",
    "iso:country":"US",
    "sg:address":"1340 Fairview Blvd",
    "sg:city":"Delran",
    "sg:phone":"+1 856 764 0375",
    "sg:postcode":"08075",
    "sg:province":"NJ",
    "sg:website":"http://www.starbuckscoffee.com",
    "wof:name":"Starbucks Coffee",
    "wof:placetype":"venue"
},
  "geometry": {"coordinates":[-74.94394800000001,40.018808],"type":"Point"}
}