{
  "type": "Feature",
  "properties": {
    "iso:country":"US",
    "sg:address":"249 Monmouth St",
    "sg:city":"Jersey City",
    "sg:classifiers":[
        {
            "category":"Wholesale",
            "subcategory":"Non-durable Goods",
            "type":"Manufacturing & Wholesale Goods"
        }
    ],
    "sg:phone":"+1 201 433 7188",
    "sg:postcode":"07302",
    "sg:province":"NJ",
    "sg:tags":[
        "marketing"
    ],
    "wof:name":"Keyes Marketing",
    "wof:placetype":"venue"
},
  "geometry": {"coordinates":[-74.05217500000001,40.717181],"type":"Point"}
}