{
  "type": "Feature",
  "properties": {
    "addr:full":"600 Delsea Dr Sewell NJ 08080",
    "addr:housenumber":"600",
    "addr:postcode":"08080",
    "addr:street":"Delsea Dr",
    "iso:country":"US",
    "sg:address":"600 Delsea Dr",
    "sg:city":"Sewell",
    "sg:classifiers":[
        {
            "category":"Coffee & Tea",
            "type":"Food & Drink"
        },
        {
            "category":"Donuts",
            "subcategory":"None",
            "type":"Food & Drink"
        }
    ],
    "sg:phone":"+1 856 582 4418",
    "sg:postcode":"08080",
    "sg:province":"NJ",
    "sg:tags":[
        "shop",
        "espresso",
        "restaurant"
    ],
    "sg:website":"http://www.dunkindonuts.com",
    "wof:name":"Dunkin' Donuts",
    "wof:placetype":"venue"
},
  "geometry": {"coordinates":[-75.113281,39.747501],"type":"Point"}
}