{
  "type": "Feature",
  "properties": {
    "iso:country":"US",
    "sg:address":"704 Billings Ave",
    "sg:city":"Paulsboro",
    "sg:classifiers":[
        {
            "category":"Retail",
            "subcategory":"Repair Shop",
            "type":"Services"
        }
    ],
    "sg:phone":"+1   ",
    "sg:postcode":"08066",
    "sg:province":"NJ",
    "wof:name":"S J P Drain Cleaning",
    "wof:placetype":"venue"
},
  "geometry": {"coordinates":[-75.24254000000001,39.835133],"type":"Point"}
}