{
  "type": "Feature",
  "properties": {
    "addr:full":"400 Cranford Rd Cherry Hill NJ 08003",
    "addr:housenumber":"400",
    "addr:postcode":"08003",
    "addr:street":"Cranford Rd",
    "iso:country":"US",
    "sg:address":"400 Cranford Rd",
    "sg:city":"Cherry Hill",
    "sg:classifiers":[
        {
            "category":"Education",
            "subcategory":"School",
            "type":"Public Place"
        }
    ],
    "sg:phone":"+1 856 429 2058",
    "sg:postcode":"08003",
    "sg:province":"NJ",
    "wof:name":"Woodcrest Elementary School",
    "wof:placetype":"venue"
},
  "geometry": {"coordinates":[-74.99394100000001,39.87497],"type":"Point"}
}