{
  "type": "Feature",
  "properties": {
    "addr:full":"349 Bergen Blvd Fairview NJ 07022",
    "addr:housenumber":"349",
    "addr:postcode":"07022",
    "addr:street":"Bergen Blvd",
    "iso:country":"US",
    "sg:address":"349 Bergen Blvd",
    "sg:city":"Fairview",
    "sg:classifiers":[
        {
            "category":"Travel",
            "subcategory":"Travel Agent",
            "type":"Entertainment"
        }
    ],
    "sg:phone":"+1 201 943 4735",
    "sg:postcode":"07022",
    "sg:province":"NJ",
    "sg:tags":[
        "passenger",
        "transportation",
        "arrangement"
    ],
    "wof:name":"Gateway Travel Inc",
    "wof:placetype":"venue"
},
  "geometry": {"coordinates":[-73.999765,40.820855],"type":"Point"}
}