{
  "type": "Feature",
  "properties": {
    "iso:country":"US",
    "sg:address":"116 Park St",
    "sg:city":"Montclair",
    "sg:classifiers":[
        {
            "category":"Health Services",
            "subcategory":"Doctor",
            "type":"Services"
        }
    ],
    "sg:phone":"+1 973 746 2525",
    "sg:postcode":"07042",
    "sg:province":"NJ",
    "wof:name":"Meritz Keith A MD",
    "wof:placetype":"venue"
},
  "geometry": {"coordinates":[-74.212997,40.821602],"type":"Point"}
}