{
  "type": "Feature",
  "properties": {
    "iso:country":"US",
    "sg:address":"1565 State Rte 37",
    "sg:city":"Toms River",
    "sg:classifiers":[
        {
            "category":"Building & Trades",
            "subcategory":"Construction",
            "type":"Services"
        }
    ],
    "sg:phone":"+1 732 657 0344",
    "sg:postcode":"08755",
    "sg:province":"NJ",
    "sg:tags":[
        "downspouts",
        "home",
        "gutter",
        "improvement"
    ],
    "wof:name":"Hart Two Hart Seamless Gutters",
    "wof:placetype":"venue"
},
  "geometry": {"coordinates":[-74.263902,39.988609],"type":"Point"}
}