{
  "type": "Feature",
  "properties": {
    "addr:full":"114 W Mount Pleasant Ave Livingston NJ 07039",
    "addr:housenumber":"114",
    "addr:postcode":"07039",
    "addr:street":"W Mount Pleasant Ave",
    "iso:country":"US",
    "sg:address":"114 W Mount Pleasant Ave",
    "sg:city":"Livingston",
    "sg:classifiers":[
        {
            "category":"Wholesale",
            "subcategory":"Durable Goods & Equipment",
            "type":"Manufacturing & Wholesale Goods"
        }
    ],
    "sg:phone":"+1 973 992 0850",
    "sg:postcode":"07039",
    "sg:province":"NJ",
    "sg:tags":[
        "professional"
    ],
    "wof:name":"New Jersey Lab & Glove Supply",
    "wof:placetype":"venue"
},
  "geometry": {"coordinates":[-74.318433,40.795448],"type":"Point"}
}