{
  "type": "Feature",
  "properties": {
    "addr:full":"8 Walnut Ct Cranbury NJ 08512",
    "addr:housenumber":"8",
    "addr:postcode":"08512",
    "addr:street":"Walnut Ct",
    "iso:country":"US",
    "sg:address":"8 Walnut Ct",
    "sg:city":"Cranbury",
    "sg:classifiers":[
        {
            "category":"Professional",
            "type":"Services"
        }
    ],
    "sg:phone":"+1   ",
    "sg:postcode":"08512",
    "sg:province":"NJ",
    "wof:name":"Rnr Services",
    "wof:placetype":"venue"
},
  "geometry": {"coordinates":[-74.556583,40.342692],"type":"Point"}
}