{
  "type": "Feature",
  "properties": {
    "addr:full":"26 Homestead Cir Marlboro NJ 07746",
    "addr:housenumber":"26",
    "addr:postcode":"07746",
    "addr:street":"Homestead Cir",
    "iso:country":"US",
    "sg:address":"26 Homestead Cir",
    "sg:city":"Marlboro",
    "sg:classifiers":[
        {
            "category":"Professional",
            "subcategory":"Computer Services",
            "type":"Services"
        }
    ],
    "sg:phone":"+1 732 536 7410",
    "sg:postcode":"07746",
    "sg:province":"NJ",
    "sg:tags":[
        "prepackaged",
        "software"
    ],
    "wof:name":"K&J Software Inc",
    "wof:placetype":"venue"
},
  "geometry": {"coordinates":[-74.27430099999999,40.312467],"type":"Point"}
}