{
  "type": "Feature",
  "properties": {
    "addr:full":"244 S Charles St Perth Amboy NJ 08861",
    "addr:housenumber":"244",
    "addr:postcode":"08861",
    "addr:street":"S Charles St",
    "iso:country":"US",
    "sg:address":"244 S Charles St",
    "sg:city":"Perth Amboy",
    "sg:classifiers":[
        {
            "category":"Social Services",
            "type":"Services"
        }
    ],
    "sg:phone":"+1   ",
    "sg:postcode":"08861",
    "sg:province":"NJ",
    "wof:name":"Hopelawn First Aid Squad",
    "wof:placetype":"venue"
},
  "geometry": {"coordinates":[-74.290774,40.527376],"type":"Point"}
}