{
  "type": "Feature",
  "properties": {
    "iso:country":"US",
    "sg:address":"31 Church Rd",
    "sg:city":"Morganville",
    "sg:classifiers":[
        {
            "category":"Building & Trades",
            "subcategory":"Construction",
            "type":"Services"
        }
    ],
    "sg:phone":"+1 732 972 9012",
    "sg:postcode":"07751",
    "sg:province":"NJ",
    "sg:tags":[
        "house",
        "contractor"
    ],
    "wof:name":"Kwiatkowski Builders LLC",
    "wof:placetype":"venue"
},
  "geometry": {"coordinates":[-74.288633,40.33905],"type":"Point"}
}