{
  "type": "Feature",
  "properties": {
    "addr:full":"26 Brookwood Dr Voorhees NJ 08043",
    "addr:housenumber":"26",
    "addr:postcode":"08043",
    "addr:street":"Brookwood Dr",
    "iso:country":"US",
    "sg:address":"26 Brookwood Dr",
    "sg:city":"Voorhees",
    "sg:classifiers":[
        {
            "category":"Health Services",
            "subcategory":"Chiropractor",
            "type":"Services"
        }
    ],
    "sg:phone":"+1   ",
    "sg:postcode":"08043",
    "sg:province":"NJ",
    "wof:name":"Alternative Healing Center",
    "wof:placetype":"venue"
},
  "geometry": {"coordinates":[-74.94036199999999,39.833843],"type":"Point"}
}