{
  "type": "Feature",
  "properties": {
    "iso:country":"US",
    "sg:address":"203 Ferry St",
    "sg:city":"Newark",
    "sg:classifiers":[
        {
            "category":"Shopping",
            "subcategory":"Shoes",
            "type":"Retail Goods"
        }
    ],
    "sg:phone":"+1   ",
    "sg:postcode":"07105",
    "sg:province":"NJ",
    "wof:name":"Capitol Shoe Shoppe",
    "wof:placetype":"venue"
},
  "geometry": {"coordinates":[-74.155796,40.728003],"type":"Point"}
}