{
  "type": "Feature",
  "properties": {
    "addr:full":"223 S Park Dr Woodbridge NJ 07095",
    "addr:housenumber":"223",
    "addr:postcode":"07095",
    "addr:street":"S Park Dr",
    "iso:country":"US",
    "sg:address":"223 S Park Dr",
    "sg:city":"Woodbridge",
    "sg:classifiers":[
        {
            "category":"Manufacturing",
            "subcategory":"Apparel",
            "type":"Manufacturing & Wholesale Goods"
        }
    ],
    "sg:phone":"+1 732 636 6859",
    "sg:postcode":"07095",
    "sg:province":"NJ",
    "sg:tags":[
        "household",
        "furnishing",
        "mfg"
    ],
    "wof:name":"Kittrich Corporation",
    "wof:placetype":"venue"
},
  "geometry": {"coordinates":[-74.28746099999999,40.554867],"type":"Point"}
}