{
  "type": "Feature",
  "properties": {
    "addr:full":"4223 S Black Horse Pike Williamstown NJ 08094",
    "addr:housenumber":"4223",
    "addr:postcode":"08094",
    "addr:street":"S Black Horse Pike",
    "iso:country":"US",
    "sg:address":"4223 S Black Horse Pike",
    "sg:city":"Williamstown",
    "sg:classifiers":[
        {
            "category":"Farming",
            "subcategory":"Nursery",
            "type":"Manufacturing & Wholesale Goods"
        }
    ],
    "sg:phone":"+1 856 629 7160",
    "sg:postcode":"08094",
    "sg:province":"NJ",
    "sg:tags":[
        "ornamental"
    ],
    "wof:name":"Harvey Jones Nursery",
    "wof:placetype":"venue"
},
  "geometry": {"coordinates":[-74.911106,39.614234],"type":"Point"}
}