{
  "type": "Feature",
  "properties": {
    "addr:full":"155 New Jersey Ave Collingswood NJ 08108",
    "addr:housenumber":"155",
    "addr:postcode":"08108",
    "addr:street":"New Jersey Ave",
    "iso:country":"US",
    "sg:address":"155 New Jersey Ave",
    "sg:city":"Collingswood",
    "sg:classifiers":[
        {
            "category":"Professional",
            "subcategory":"Computer Services",
            "type":"Services"
        }
    ],
    "sg:phone":"+1   ",
    "sg:postcode":"08108",
    "sg:province":"NJ",
    "sg:tags":[
        "datum"
    ],
    "wof:name":"Envoy Inc",
    "wof:placetype":"venue"
},
  "geometry": {"coordinates":[-75.064609,39.918265],"type":"Point"}
}