{
  "type": "Feature",
  "properties": {
    "addr:full":"255 Main Ave Passaic NJ 07055",
    "addr:housenumber":"255",
    "addr:postcode":"07055",
    "addr:street":"Main Ave",
    "iso:country":"US",
    "sg:address":"255 Main Ave",
    "sg:city":"Passaic",
    "sg:classifiers":[
        {
            "category":"Retail",
            "subcategory":"Veterinary Services",
            "type":"Services"
        }
    ],
    "sg:phone":"+1 973 777 4833",
    "sg:postcode":"07055",
    "sg:province":"NJ",
    "sg:tags":[
        "veterinarian"
    ],
    "wof:name":"Animal Hospital of Passaic Park",
    "wof:placetype":"venue"
},
  "geometry": {"coordinates":[-74.12599899999999,40.847599],"type":"Point"}
}