{
  "type": "Feature",
  "properties": {
    "addr:full":"406 Coit St Irvington NJ 07111",
    "addr:housenumber":"406",
    "addr:postcode":"07111",
    "addr:street":"Coit St",
    "iso:country":"US",
    "sg:address":"406 Coit St",
    "sg:city":"Irvington",
    "sg:classifiers":[
        {
            "category":"Government",
            "subcategory":"Office",
            "type":"Public Place"
        }
    ],
    "sg:phone":"+1 973 399 6701",
    "sg:postcode":"07111",
    "sg:province":"NJ",
    "sg:tags":[
        "village"
    ],
    "wof:name":"Irvington Street & Sewer",
    "wof:placetype":"venue"
},
  "geometry": {"coordinates":[-74.23161899999999,40.710784],"type":"Point"}
}