{
  "type": "Feature",
  "properties": {
    "iso:country":"US",
    "sg:address":"509 Rehill Ct",
    "sg:city":"Westwood",
    "sg:classifiers":[
        {
            "category":"Retail",
            "subcategory":"Repair Shop",
            "type":"Services"
        }
    ],
    "sg:phone":"+1 201 594 1248",
    "sg:postcode":"07675",
    "sg:province":"NJ",
    "wof:name":"Equipment Repair",
    "wof:placetype":"venue"
},
  "geometry": {"coordinates":[-74.008267,41.013912],"type":"Point"}
}