{
  "type": "Feature",
  "properties": {
    "addr:full":"4 Calais Rd Mendham NJ 07945",
    "addr:housenumber":"4",
    "addr:postcode":"07945",
    "addr:street":"Calais Rd",
    "iso:country":"US",
    "sg:address":"4 Calais Rd",
    "sg:city":"Mendham",
    "sg:classifiers":[
        {
            "category":"Professional",
            "subcategory":"Business Services",
            "type":"Services"
        }
    ],
    "sg:phone":"+1 973 543 2046",
    "sg:postcode":"07945",
    "sg:province":"NJ",
    "sg:tags":[
        "interior",
        "consultant",
        "design",
        "decorator"
    ],
    "wof:name":"Old Elm Interiors",
    "wof:placetype":"venue"
},
  "geometry": {"coordinates":[-74.610829,40.790346],"type":"Point"}
}