{
  "type": "Feature",
  "properties": {
    "addr:full":"903 E Grand St Elizabeth NJ 07201",
    "addr:housenumber":"903",
    "addr:postcode":"07201",
    "addr:street":"E Grand St",
    "iso:country":"US",
    "sg:address":"903 E Grand St",
    "sg:city":"Elizabeth",
    "sg:classifiers":[
        {
            "category":"Retail",
            "subcategory":"Auto Repair",
            "type":"Services"
        }
    ],
    "sg:phone":"+1 908 352 2451",
    "sg:postcode":"07201",
    "sg:province":"NJ",
    "sg:tags":[
        "automotive",
        "towing",
        "painting"
    ],
    "wof:name":"Tecnaut Auto Body Repair Inc",
    "wof:placetype":"venue"
},
  "geometry": {"coordinates":[-74.202904,40.6647],"type":"Point"}
}