{
  "type": "Feature",
  "properties": {
    "addr:full":"603 Bloomfield Ave Verona NJ 07044",
    "addr:housenumber":"603",
    "addr:postcode":"07044",
    "addr:street":"Bloomfield Ave",
    "iso:country":"US",
    "sg:address":"603 Bloomfield Ave",
    "sg:city":"Verona",
    "sg:classifiers":[
        {
            "category":"Professional",
            "subcategory":"Lawyer & Legal Services",
            "type":"Services"
        }
    ],
    "sg:phone":"+1 973 239 3003",
    "sg:postcode":"07044",
    "sg:province":"NJ",
    "wof:name":"Law Offices of Sebastian M Bio",
    "wof:placetype":"venue"
},
  "geometry": {"coordinates":[-74.246803,40.832298],"type":"Point"}
}