{
  "type": "Feature",
  "properties": {
    "addr:full":"17 Glenbrook Rd Morris Plains NJ 07950",
    "addr:housenumber":"17",
    "addr:postcode":"07950",
    "addr:street":"Glenbrook Rd",
    "iso:country":"US",
    "sg:address":"17 Glenbrook Rd",
    "sg:city":"Morris Plains",
    "sg:classifiers":[
        {
            "category":"Real Estate",
            "subcategory":"Real Estate Agent",
            "type":"Services"
        }
    ],
    "sg:phone":"+1 973 538 0245",
    "sg:postcode":"07950",
    "sg:province":"NJ",
    "sg:tags":[
        "inspection"
    ],
    "wof:name":"Educated Home Inspections",
    "wof:placetype":"venue"
},
  "geometry": {"coordinates":[-74.481269,40.827239],"type":"Point"}
}