{
  "type": "Feature",
  "properties": {
    "addr:full":"138 Harmon Cove Tower Secaucus NJ 07094",
    "addr:housenumber":"138",
    "addr:postcode":"07094",
    "addr:street":"Harmon Cove",
    "iso:country":"US",
    "sg:address":"138 Harmon Cove Tower",
    "sg:city":"Secaucus",
    "sg:classifiers":[
        {
            "category":"Building & Trades",
            "subcategory":"Construction",
            "type":"Services"
        }
    ],
    "sg:phone":"+1 201 617 1687",
    "sg:postcode":"07094",
    "sg:province":"NJ",
    "sg:tags":[
        "contractor"
    ],
    "wof:name":"Improvements Unlimited",
    "wof:placetype":"venue"
},
  "geometry": {"coordinates":[-74.079049,40.783003],"type":"Point"}
}