{
  "type": "Feature",
  "properties": {
    "addr:full":"1217 Teaneck Rd Teaneck NJ 07666",
    "addr:housenumber":"1217",
    "addr:postcode":"07666",
    "addr:street":"Teaneck Rd",
    "iso:country":"US",
    "sg:address":"1217 Teaneck Rd",
    "sg:city":"Teaneck",
    "sg:classifiers":[
        {
            "category":"Shopping",
            "subcategory":"Jewelry",
            "type":"Retail Goods"
        }
    ],
    "sg:phone":"+1 201 837 5991",
    "sg:postcode":"07666",
    "sg:province":"NJ",
    "wof:name":"Gold Run Jewlers",
    "wof:placetype":"venue"
},
  "geometry": {"coordinates":[-74.001454,40.894329],"type":"Point"}
}