{
  "type": "Feature",
  "properties": {
    "iso:country":"US",
    "sg:address":"42 Okner Pkwy",
    "sg:city":"Livingston",
    "sg:classifiers":[
        {
            "category":"Personal",
            "type":"Services"
        },
        {
            "category":"Social Services",
            "subcategory":"Child Care",
            "type":"Services"
        }
    ],
    "sg:phone":"+1 973 533 1000",
    "sg:postcode":"07039",
    "sg:province":"NJ",
    "sg:tags":[
        "party",
        "planning",
        "day",
        "event"
    ],
    "wof:name":"Jellybean Junction Llc",
    "wof:placetype":"venue"
},
  "geometry": {"coordinates":[-74.355396,40.800489],"type":"Point"}
}