{
  "type": "Feature",
  "properties": {
    "iso:country":"US",
    "sg:address":"8 Cold Hill Rd",
    "sg:city":"Mendham",
    "sg:classifiers":[
        {
            "category":"Retail",
            "subcategory":"Auto Repair",
            "type":"Services"
        }
    ],
    "sg:phone":"+1   ",
    "sg:postcode":"07945",
    "sg:province":"NJ",
    "sg:tags":[
        "automobile",
        "station",
        "general"
    ],
    "wof:name":"Moros Automotive Service Inc",
    "wof:placetype":"venue"
},
  "geometry": {"coordinates":[-74.585476,40.785879],"type":"Point"}
}