{
  "type": "Feature",
  "properties": {
    "addr:full":"5 Glen St Cliffside Park NJ 07010",
    "addr:housenumber":"5",
    "addr:postcode":"07010",
    "addr:street":"Glen St",
    "iso:country":"US",
    "sg:address":"5 Glen St",
    "sg:city":"Cliffside Park",
    "sg:classifiers":[
        {
            "category":"Professional",
            "type":"Services"
        }
    ],
    "sg:phone":"+1   ",
    "sg:postcode":"07010",
    "sg:province":"NJ",
    "wof:name":"Eclaire Advisor Ltd",
    "wof:placetype":"venue"
},
  "geometry": {"coordinates":[-73.98693799999999,40.830173],"type":"Point"}
}