{
  "type": "Feature",
  "properties": {
    "addr:full":"792 Green St Phillipsburg NJ 08865",
    "addr:housenumber":"792",
    "addr:postcode":"08865",
    "addr:street":"Green St",
    "iso:country":"US",
    "sg:address":"792 Green St",
    "sg:city":"Phillipsburg",
    "sg:classifiers":[
        {
            "category":"Professional",
            "subcategory":"Business Services",
            "type":"Services"
        }
    ],
    "sg:phone":"+1   ",
    "sg:postcode":"08865",
    "sg:province":"NJ",
    "wof:name":"Environmental Assay Inc",
    "wof:placetype":"venue"
},
  "geometry": {"coordinates":[-75.169185,40.684266],"type":"Point"}
}