{
  "type": "Feature",
  "properties": {
    "addr:full":"177 Broad St Red Bank NJ 07701",
    "addr:housenumber":"177",
    "addr:postcode":"07701",
    "addr:street":"Broad St",
    "iso:country":"US",
    "sg:address":"177 Broad St",
    "sg:city":"Red Bank",
    "sg:classifiers":[
        {
            "category":"Retail",
            "subcategory":"Photofinishing",
            "type":"Services"
        }
    ],
    "sg:phone":"+1   ",
    "sg:postcode":"07701",
    "sg:province":"NJ",
    "sg:tags":[
        "photographer",
        "laboratory"
    ],
    "wof:name":"Foto Works Inc",
    "wof:placetype":"venue"
},
  "geometry": {"coordinates":[-74.064789,40.346505],"type":"Point"}
}