{
  "type": "Feature",
  "properties": {
    "addr:full":"821 Belmar Plz Belmar NJ 07719",
    "addr:housenumber":"821",
    "addr:postcode":"07719",
    "addr:street":"Belmar Plz",
    "iso:country":"US",
    "sg:address":"821 Belmar Plz",
    "sg:city":"Belmar",
    "sg:classifiers":[
        {
            "category":"Professional",
            "type":"Services"
        }
    ],
    "sg:phone":"+1   ",
    "sg:postcode":"07719",
    "sg:province":"NJ",
    "wof:name":"Sun Suite Tanning",
    "wof:placetype":"venue"
},
  "geometry": {"coordinates":[-74.025386,40.180605],"type":"Point"}
}