{
  "type": "Feature",
  "properties": {
    "addr:full":"358 7th St Jersey City NJ 07302",
    "addr:housenumber":"358",
    "addr:postcode":"07302",
    "addr:street":"7Th St",
    "iso:country":"US",
    "sg:address":"358 7th St",
    "sg:city":"Jersey City",
    "sg:classifiers":[
        {
            "category":"Personal",
            "type":"Services"
        }
    ],
    "sg:phone":"+1 201 418 9008",
    "sg:postcode":"07302",
    "sg:province":"NJ",
    "sg:tags":[
        "sewing",
        "alteration"
    ],
    "wof:name":"Tailors Touch",
    "wof:placetype":"venue"
},
  "geometry": {"coordinates":[-74.05036200000001,40.726669],"type":"Point"}
}