{
  "type": "Feature",
  "properties": {
    "addr:full":"177 Leghorn Ave Bridgewater NJ 08807",
    "addr:housenumber":"177",
    "addr:postcode":"08807",
    "addr:street":"Leghorn Ave",
    "iso:country":"US",
    "sg:address":"177 Leghorn Ave",
    "sg:city":"Bridgewater",
    "sg:classifiers":[
        {
            "category":"Building & Trades",
            "subcategory":"Construction",
            "type":"Services"
        }
    ],
    "sg:phone":"+1 908 526 7371",
    "sg:postcode":"08807",
    "sg:province":"NJ",
    "sg:tags":[
        "residential",
        "general",
        "commercial",
        "contractor"
    ],
    "wof:name":"R V C Inc",
    "wof:placetype":"venue"
},
  "geometry": {"coordinates":[-74.657954,40.563997],"type":"Point"}
}