{
  "type": "Feature",
  "properties": {
    "iso:country":"US",
    "sg:address":"21 Heritage Dr",
    "sg:city":"South River",
    "sg:classifiers":[
        {
            "category":"Building & Trades",
            "subcategory":"Landscaping Services",
            "type":"Services"
        }
    ],
    "sg:phone":"+1 732 257 6588",
    "sg:postcode":"08882",
    "sg:province":"NJ",
    "wof:name":"Obal Landscaping",
    "wof:placetype":"venue"
},
  "geometry": {"coordinates":[-74.366395,40.440107],"type":"Point"}
}