{
  "type": "Feature",
  "properties": {
    "iso:country":"US",
    "sg:address":"1500 Mainline Dr",
    "sg:city":"Cinnaminson",
    "sg:classifiers":[
        {
            "category":"Building & Trades",
            "subcategory":"Construction",
            "type":"Services"
        }
    ],
    "sg:phone":"+1 856 629 1605",
    "sg:postcode":"08077",
    "sg:province":"NJ",
    "sg:tags":[
        "concrete",
        "contractor"
    ],
    "wof:name":"Quality Concrete LLC",
    "wof:placetype":"venue"
},
  "geometry": {"coordinates":[-74.98163,40.007757],"type":"Point"}
}