{
  "type": "Feature",
  "properties": {
    "addr:full":"1742 Prospect St Trenton NJ 08638",
    "addr:housenumber":"1742",
    "addr:postcode":"08638",
    "addr:street":"Prospect St",
    "iso:country":"US",
    "sg:address":"1742 Prospect St",
    "sg:city":"Trenton",
    "sg:classifiers":[
        {
            "category":"Health Services",
            "subcategory":"Clinic",
            "type":"Services"
        }
    ],
    "sg:phone":"+1 609 883 2971",
    "sg:postcode":"08638",
    "sg:province":"NJ",
    "sg:tags":[
        "home"
    ],
    "wof:name":"Marie Home Care Provider",
    "wof:placetype":"venue"
},
  "geometry": {"coordinates":[-74.760761,40.251168],"type":"Point"}
}