{
  "type": "Feature",
  "properties": {
    "addr:full":"1400 Crescent Blvd Ofc Gloucester Cy NJ 08030",
    "addr:housenumber":"1400",
    "addr:postcode":"08030",
    "addr:street":"Crescent Blvd",
    "iso:country":"US",
    "sg:address":"1400 Crescent Blvd Ofc",
    "sg:city":"Gloucester Cy",
    "sg:classifiers":[
        {
            "category":"Travel",
            "subcategory":"Hotels & Motels",
            "type":"Entertainment"
        }
    ],
    "sg:phone":"+1 856 456 6000",
    "sg:postcode":"08030",
    "sg:province":"NJ",
    "wof:name":"Budget Inn",
    "wof:placetype":"venue"
},
  "geometry": {"coordinates":[-75.109398,39.883701],"type":"Point"}
}