{
  "type": "Feature",
  "properties": {
    "iso:country":"US",
    "sg:address":"75 Spring Valley Rd",
    "sg:city":"Montvale",
    "sg:classifiers":[
        {
            "category":"Professional",
            "subcategory":"Management & Consulting",
            "type":"Services"
        }
    ],
    "sg:phone":"+1 201 248 4969",
    "sg:postcode":"07645",
    "sg:province":"NJ",
    "sg:tags":[
        "accounting"
    ],
    "wof:name":"A/P Review Inc",
    "wof:placetype":"venue"
},
  "geometry": {"coordinates":[-74.052009,41.056527],"type":"Point"}
}