{
  "type": "Feature",
  "properties": {
    "addr:full":"581 Northumberland Rd Teaneck NJ 07666",
    "addr:housenumber":"581",
    "addr:postcode":"07666",
    "addr:street":"Northumberland Rd",
    "iso:country":"US",
    "sg:address":"581 Northumberland Rd",
    "sg:city":"Teaneck",
    "sg:classifiers":[
        {
            "category":"Wholesale",
            "subcategory":"Toys & Hobbies",
            "type":"Manufacturing & Wholesale Goods"
        }
    ],
    "sg:phone":"+1 201 836 5370",
    "sg:postcode":"07666",
    "sg:province":"NJ",
    "wof:name":"Teenok Designs L L C",
    "wof:placetype":"venue"
},
  "geometry": {"coordinates":[-74.02043500000001,40.898581],"type":"Point"}
}