{
  "type": "Feature",
  "properties": {
    "iso:country":"US",
    "sg:address":"34 Exchange Pl",
    "sg:city":"Jersey City",
    "sg:classifiers":[
        {
            "category":"Shopping",
            "subcategory":"Computers & Home Electronics",
            "type":"Retail Goods"
        }
    ],
    "sg:phone":"+1 201 451 2700",
    "sg:postcode":"07302",
    "sg:province":"NJ",
    "sg:tags":[
        "software"
    ],
    "wof:name":"Financial Science",
    "wof:placetype":"venue"
},
  "geometry": {"coordinates":[-74.033086,40.716212],"type":"Point"}
}