{
  "type": "Feature",
  "properties": {
    "iso:country":"US",
    "sg:address":"41 E Cheryl Rd",
    "sg:city":"Pine Brook",
    "sg:classifiers":[
        {
            "category":"Professional",
            "type":"Services"
        }
    ],
    "sg:phone":"+1 973 575 0889",
    "sg:postcode":"07058",
    "sg:province":"NJ",
    "sg:tags":[
        "establishment"
    ],
    "wof:name":"Gail S Rempell Ms Ccc Slp",
    "wof:placetype":"venue"
},
  "geometry": {"coordinates":[-74.348707,40.88206],"type":"Point"}
}