{
  "type": "Feature",
  "properties": {
    "addr:full":"11 Plymouth Ave Port Monmouth NJ 07758",
    "addr:housenumber":"11",
    "addr:postcode":"07758",
    "addr:street":"Plymouth Ave",
    "iso:country":"US",
    "sg:address":"11 Plymouth Ave",
    "sg:city":"Port Monmouth",
    "sg:classifiers":[
        {
            "category":"Building & Trades",
            "subcategory":"Landscaping Services",
            "type":"Services"
        }
    ],
    "sg:phone":"+1 732 787 8131",
    "sg:postcode":"07758",
    "sg:province":"NJ",
    "wof:name":"NA Roman Landscaping",
    "wof:placetype":"venue"
},
  "geometry": {"coordinates":[-74.100765,40.430559],"type":"Point"}
}