{
  "type": "Feature",
  "properties": {
    "addr:full":"546 W Side Ave Jersey City NJ 07304",
    "addr:housenumber":"546",
    "addr:postcode":"07304",
    "addr:street":"W Side Ave",
    "iso:country":"US",
    "sg:address":"546 W Side Ave",
    "sg:city":"Jersey City",
    "sg:classifiers":[
        {
            "category":"Shopping",
            "subcategory":"Pharmacy",
            "type":"Retail Goods"
        }
    ],
    "sg:phone":"+1 201 434 7870",
    "sg:postcode":"07304",
    "sg:province":"NJ",
    "wof:name":"Underwood Pharmacy",
    "wof:placetype":"venue"
},
  "geometry": {"coordinates":[-74.082966,40.718996],"type":"Point"}
}