{
  "type": "Feature",
  "properties": {
    "addr:full":"3730 Lawrenceville Rd Princeton NJ 08540",
    "addr:housenumber":"3730",
    "addr:postcode":"08540",
    "addr:street":"Lawrenceville Rd",
    "iso:country":"US",
    "sg:address":"3730 Lawrenceville Rd",
    "sg:city":"Princeton",
    "sg:classifiers":[
        {
            "category":"Home & Garden",
            "subcategory":"Garden Supply",
            "type":"Retail Goods"
        }
    ],
    "sg:phone":"+1 609 924 5770",
    "sg:postcode":"08540",
    "sg:province":"NJ",
    "sg:tags":[
        "nurseryman"
    ],
    "wof:name":"Peterson's Nursery Garden Ctr",
    "wof:placetype":"venue"
},
  "geometry": {"coordinates":[-74.69656500000001,40.323092],"type":"Point"}
}