{
  "type": "Feature",
  "properties": {
    "addr:full":"5 Becker Farm Rd Roseland NJ 07068",
    "addr:housenumber":"5",
    "addr:postcode":"07068",
    "addr:street":"Becker Farm Rd",
    "iso:country":"US",
    "sg:address":"5 Becker Farm Rd",
    "sg:city":"Roseland",
    "sg:classifiers":[
        {
            "category":"Sports & Exercise",
            "subcategory":"Gym",
            "type":"Entertainment"
        }
    ],
    "sg:phone":"+1 973 535 1177",
    "sg:postcode":"07068",
    "sg:province":"NJ",
    "wof:name":"Fitness 1-2-1",
    "wof:placetype":"venue"
},
  "geometry": {"coordinates":[-74.306878,40.817977],"type":"Point"}
}