{
  "type": "Feature",
  "properties": {
    "iso:country":"US",
    "sg:address":"131 Mine Mount Rd",
    "sg:city":"Bernardsville",
    "sg:classifiers":[
        {
            "category":"Manufacturing",
            "subcategory":"Printing",
            "type":"Manufacturing & Wholesale Goods"
        }
    ],
    "sg:phone":"+1 908 696 0477",
    "sg:postcode":"07924",
    "sg:province":"NJ",
    "sg:tags":[
        "publisher"
    ],
    "wof:name":"C & P Publications",
    "wof:placetype":"venue"
},
  "geometry": {"coordinates":[-74.58256900000001,40.725094],"type":"Point"}
}