{
  "type": "Feature",
  "properties": {
    "iso:country":"US",
    "sg:address":"203 Nassau St",
    "sg:city":"Princeton",
    "sg:classifiers":[
        {
            "category":"Shopping",
            "type":"Retail Goods"
        }
    ],
    "sg:phone":"+1 609 430 0700",
    "sg:postcode":"08542",
    "sg:province":"NJ",
    "sg:tags":[
        "wedding",
        "supply"
    ],
    "wof:name":"Flower Station",
    "wof:placetype":"venue"
},
  "geometry": {"coordinates":[-74.652856,40.351748],"type":"Point"}
}