{
  "type": "Feature",
  "properties": {
    "iso:country":"US",
    "sg:address":"735 Lawlins Rd",
    "sg:city":"Franklin Lakes",
    "sg:classifiers":[
        {
            "category":"Wholesale",
            "subcategory":"Non-durable Goods",
            "type":"Manufacturing & Wholesale Goods"
        }
    ],
    "sg:phone":"+1 201 847 7577",
    "sg:postcode":"07417",
    "sg:province":"NJ",
    "sg:tags":[
        "advertising"
    ],
    "sg:website":"www.cambridgemarketing.com",
    "wof:name":"Cambridge Marketing Group",
    "wof:placetype":"venue"
},
  "geometry": {"coordinates":[-74.18676600000001,41.018076],"type":"Point"}
}