{
  "type": "Feature",
  "properties": {
    "addr:full":"4316 New York Ave Union City NJ 07087",
    "addr:housenumber":"4316",
    "addr:postcode":"07087",
    "addr:street":"New York Ave",
    "iso:country":"US",
    "sg:address":"4316 New York Ave",
    "sg:city":"Union City",
    "sg:classifiers":[
        {
            "category":"Retail",
            "subcategory":"Laundry & Dry Cleaning",
            "type":"Services"
        }
    ],
    "sg:phone":"+1   ",
    "sg:postcode":"07087",
    "sg:province":"NJ",
    "sg:tags":[
        "garment",
        "agent"
    ],
    "wof:name":"La Moderna",
    "wof:placetype":"venue"
},
  "geometry": {"coordinates":[-74.022971,40.778014],"type":"Point"}
}