{
  "type": "Feature",
  "properties": {
    "addr:full":"90 Revere Dr Dumont NJ 07628",
    "addr:housenumber":"90",
    "addr:postcode":"07628",
    "addr:street":"Revere Dr",
    "iso:country":"US",
    "sg:address":"90 Revere Dr",
    "sg:city":"Dumont",
    "sg:classifiers":[
        {
            "category":"Shopping",
            "subcategory":"Catalog Store",
            "type":"Retail Goods"
        }
    ],
    "sg:phone":"+1   ",
    "sg:postcode":"07628",
    "sg:province":"NJ",
    "sg:tags":[
        "developmental",
        "educational",
        "toy"
    ],
    "wof:name":"Brighter Starts LLC",
    "wof:placetype":"venue"
},
  "geometry": {"coordinates":[-73.97954,40.948409],"type":"Point"}
}