{
  "type": "Feature",
  "properties": {
    "addr:full":"1121 Edgewater Ave Ridgefield NJ 07657",
    "addr:housenumber":"1121",
    "addr:postcode":"07657",
    "addr:street":"Edgewater Ave",
    "iso:country":"US",
    "sg:address":"1121 Edgewater Ave",
    "sg:city":"Ridgefield",
    "sg:classifiers":[
        {
            "category":"Home & Garden",
            "subcategory":"Building Materials",
            "type":"Retail Goods"
        },
        {
            "category":"Wholesale",
            "subcategory":"Electrical",
            "type":"Manufacturing & Wholesale Goods"
        }
    ],
    "sg:phone":"+1 201 941 7091",
    "sg:postcode":"07657",
    "sg:province":"NJ",
    "sg:tags":[
        "equipment",
        "electric",
        "supply"
    ],
    "wof:name":"Innovative Sound Concepts",
    "wof:placetype":"venue"
},
  "geometry": {"coordinates":[-74.01413599999999,40.835297],"type":"Point"}
}