{
  "type": "Feature",
  "properties": {
    "addr:full":"285 Adams St Newark NJ 07105",
    "addr:housenumber":"285",
    "addr:postcode":"07105",
    "addr:street":"Adams St",
    "iso:country":"US",
    "sg:address":"285 Adams St",
    "sg:city":"Newark",
    "sg:classifiers":[
        {
            "category":"Autos & Motor Vehicles",
            "subcategory":"Auto Supplies",
            "type":"Retail Goods"
        }
    ],
    "sg:phone":"+1   ",
    "sg:postcode":"07105",
    "sg:province":"NJ",
    "sg:tags":[
        "tire"
    ],
    "wof:name":"ADT Tire Inc",
    "wof:placetype":"venue"
},
  "geometry": {"coordinates":[-74.16245499999999,40.722765],"type":"Point"}
}