{
  "type": "Feature",
  "properties": {
    "addr:full":"788 W Montgomery Ave Wildwood NJ 08260",
    "addr:housenumber":"788",
    "addr:postcode":"08260",
    "addr:street":"W Montgomery Ave",
    "iso:country":"US",
    "sg:address":"788 W Montgomery Ave",
    "sg:city":"Wildwood",
    "sg:classifiers":[
        {
            "category":"Recreation",
            "subcategory":"Boat Charter",
            "type":"Entertainment"
        }
    ],
    "sg:phone":"+1 609 522 2300",
    "sg:postcode":"08260",
    "sg:province":"NJ",
    "sg:tags":[
        "boating"
    ],
    "wof:name":"Ottens Harbor Marine Service",
    "wof:placetype":"venue"
},
  "geometry": {"coordinates":[-74.830399,38.994301],"type":"Point"}
}