{
  "type": "Feature",
  "properties": {
    "iso:country":"US",
    "sg:address":"72 Smull Ave",
    "sg:city":"Caldwell",
    "sg:classifiers":[
        {
            "category":"Professional",
            "subcategory":"Management & Consulting",
            "type":"Services"
        }
    ],
    "sg:phone":"+1   ",
    "sg:postcode":"07006",
    "sg:province":"NJ",
    "sg:tags":[
        "public",
        "relations"
    ],
    "wof:name":"Cdc Public Relations & Writing",
    "wof:placetype":"venue"
},
  "geometry": {"coordinates":[-74.27137,40.843215],"type":"Point"}
}