{
  "type": "Feature",
  "properties": {
    "iso:country":"US",
    "sg:address":"80 Legion Dr",
    "sg:city":"Cresskill",
    "sg:classifiers":[
        {
            "category":"Real Estate",
            "subcategory":"Real Estate Operator",
            "type":"Services"
        }
    ],
    "sg:phone":"+1   ",
    "sg:postcode":"07626",
    "sg:province":"NJ",
    "sg:tags":[
        "building",
        "residential",
        "manager",
        "commercial"
    ],
    "wof:name":"Legion Drive Associates",
    "wof:placetype":"venue"
},
  "geometry": {"coordinates":[-73.95960599999999,40.939683],"type":"Point"}
}