{
  "type": "Feature",
  "properties": {
    "iso:country":"US",
    "sg:address":"33 Station Rd",
    "sg:city":"Budd Lake",
    "sg:classifiers":[
        {
            "category":"Building & Trades",
            "subcategory":"Landscaping Services",
            "type":"Services"
        }
    ],
    "sg:phone":"+1 973 691 2699",
    "sg:postcode":"07828",
    "sg:province":"NJ",
    "sg:tags":[
        "landscape",
        "contractor"
    ],
    "wof:name":"Ignacio's Landscaping",
    "wof:placetype":"venue"
},
  "geometry": {"coordinates":[-74.76374800000001,40.887733],"type":"Point"}
}