{
  "type": "Feature",
  "properties": {
    "iso:country":"US",
    "sg:address":"500 Haddon Ave",
    "sg:city":"Collingswood",
    "sg:classifiers":[
        {
            "category":"Retail",
            "subcategory":"Repair Shop",
            "type":"Services"
        }
    ],
    "sg:phone":"+1 856 854 3117",
    "sg:postcode":"08108",
    "sg:province":"NJ",
    "sg:tags":[
        "sewing",
        "machines-service"
    ],
    "wof:name":"South Jersey Sewing Machine Repairs",
    "wof:placetype":"venue"
},
  "geometry": {"coordinates":[-75.07467699999999,39.918171],"type":"Point"}
}