{
  "type": "Feature",
  "properties": {
    "iso:country":"US",
    "sg:address":"999 Ocean Ave",
    "sg:city":"Sea Bright",
    "sg:classifiers":[
        {
            "category":"Organizations",
            "subcategory":"Community Association",
            "type":"Services"
        }
    ],
    "sg:phone":"+1 732 842 0245",
    "sg:postcode":"07760",
    "sg:province":"NJ",
    "sg:tags":[
        "club"
    ],
    "wof:name":"Sea Bright Beach Club",
    "wof:placetype":"venue"
},
  "geometry": {"coordinates":[-73.974211,40.374216],"type":"Point"}
}