{
  "type": "Feature",
  "properties": {
    "iso:country":"US",
    "sg:address":"17 Bunn Rd",
    "sg:city":"Hamburg",
    "sg:classifiers":[
        {
            "category":"Building & Trades",
            "subcategory":"Plumbing",
            "type":"Services"
        }
    ],
    "sg:phone":"+1 973 209 8812",
    "sg:postcode":"07419",
    "sg:province":"NJ",
    "sg:tags":[
        "conditioning",
        "air",
        "system",
        "contractor"
    ],
    "wof:name":"Jack's Heating & AC & REFRIG",
    "wof:placetype":"venue"
},
  "geometry": {"coordinates":[-74.613238,41.139061],"type":"Point"}
}