{
  "type": "Feature",
  "properties": {
    "addr:full":"15 Worth St South Hackensack NJ 07606",
    "addr:housenumber":"15",
    "addr:postcode":"07606",
    "addr:street":"Worth St",
    "iso:country":"US",
    "sg:address":"15 Worth St",
    "sg:city":"South Hackensack",
    "sg:classifiers":[
        {
            "category":"Retail",
            "subcategory":"Repair Shop",
            "type":"Services"
        }
    ],
    "sg:phone":"+1   ",
    "sg:postcode":"07606",
    "sg:province":"NJ",
    "wof:name":"Wtr Sales Corporation",
    "wof:placetype":"venue"
},
  "geometry": {"coordinates":[-74.049683,40.872497],"type":"Point"}
}