{
  "type": "Feature",
  "properties": {
    "addr:full":"23 Reese Ct Phillipsburg NJ 08865",
    "addr:housenumber":"23",
    "addr:postcode":"08865",
    "addr:street":"Reese Ct",
    "iso:country":"US",
    "sg:address":"23 Reese Ct",
    "sg:city":"Phillipsburg",
    "sg:classifiers":[
        {
            "category":"Professional",
            "subcategory":"Business Services",
            "type":"Services"
        }
    ],
    "sg:phone":"+1   ",
    "sg:postcode":"08865",
    "sg:province":"NJ",
    "sg:tags":[
        "sound"
    ],
    "wof:name":"Sounding Board",
    "wof:placetype":"venue"
},
  "geometry": {"coordinates":[-75.19765599999999,40.686811],"type":"Point"}
}