{
  "type": "Feature",
  "properties": {
    "addr:full":"81 State Rte 35 Keyport NJ 07735",
    "addr:housenumber":"81",
    "addr:postcode":"07735",
    "addr:street":"State Rte 35",
    "iso:country":"US",
    "sg:address":"81 State Rte 35",
    "sg:city":"Keyport",
    "sg:classifiers":[
        {
            "category":"Retail",
            "subcategory":"Auto Repair",
            "type":"Services"
        }
    ],
    "sg:phone":"+1 732 739 9376",
    "sg:postcode":"07735",
    "sg:province":"NJ",
    "sg:tags":[
        "repairing",
        "automobile"
    ],
    "wof:name":"Bayshore Auto Svc Inc",
    "wof:placetype":"venue"
},
  "geometry": {"coordinates":[-74.236242,40.448389],"type":"Point"}
}