{
  "type": "Feature",
  "properties": {
    "addr:full":"303 7th Ave Asbury Park NJ 07712",
    "addr:housenumber":"303",
    "addr:postcode":"07712",
    "addr:street":"7Th Ave Asbury",
    "iso:country":"US",
    "sg:address":"303 7th Ave",
    "sg:city":"Asbury Park",
    "sg:classifiers":[
        {
            "category":"Home & Garden",
            "subcategory":"Carpets & Floor Coverings",
            "type":"Retail Goods"
        }
    ],
    "sg:phone":"+1   ",
    "sg:postcode":"07712",
    "sg:province":"NJ",
    "sg:tags":[
        "installation"
    ],
    "wof:name":"Lennys Floor Covering",
    "wof:placetype":"venue"
},
  "geometry": {"coordinates":[-74.00280600000001,40.227895],"type":"Point"}
}