{
  "type": "Feature",
  "properties": {
    "iso:country":"US",
    "sg:address":"1 Garden State Plz",
    "sg:city":"Paramus",
    "sg:classifiers":[
        {
            "category":"Shopping",
            "subcategory":"Clothing, Apparel, & Fashions",
            "type":"Retail Goods"
        }
    ],
    "sg:phone":"+1 201 226 0122",
    "sg:postcode":"07652",
    "sg:province":"NJ",
    "sg:tags":[
        "men's",
        "clothing",
        "women's"
    ],
    "sg:website":"www.shoppuredenim.com",
    "wof:name":"Pure Boutique",
    "wof:placetype":"venue"
},
  "geometry": {"coordinates":[-74.076363,40.918116],"type":"Point"}
}