{
  "type": "Feature",
  "properties": {
    "addr:full":"172 US Hwy 206 Chester NJ 07930",
    "addr:housenumber":"172",
    "addr:postcode":"07930",
    "addr:street":"Us Hwy 206",
    "iso:country":"US",
    "sg:address":"172 US Hwy 206",
    "sg:city":"Chester",
    "sg:classifiers":[
        {
            "category":"Personal",
            "type":"Services"
        }
    ],
    "sg:phone":"+1 908 879 7762",
    "sg:postcode":"07930",
    "sg:province":"NJ",
    "sg:tags":[
        "consultant",
        "program",
        "health",
        "fitness"
    ],
    "wof:name":"Body Time",
    "wof:placetype":"venue"
},
  "geometry": {"coordinates":[-74.698235,40.783847],"type":"Point"}
}