{
  "type": "Feature",
  "properties": {
    "addr:full":"222 Dutch Neck Rd Hightstown NJ 08520",
    "addr:housenumber":"222",
    "addr:postcode":"08520",
    "addr:street":"Dutch Neck Rd",
    "iso:country":"US",
    "sg:address":"222 Dutch Neck Rd",
    "sg:city":"Hightstown",
    "sg:classifiers":[
        {
            "category":"Retail",
            "subcategory":"Self-service Laundry",
            "type":"Services"
        }
    ],
    "sg:phone":"+1 609 426 9595",
    "sg:postcode":"08520",
    "sg:province":"NJ",
    "wof:name":"Lucas Laundromat",
    "wof:placetype":"venue"
},
  "geometry": {"coordinates":[-74.549975,40.271253],"type":"Point"}
}