{
  "type": "Feature",
  "properties": {
    "iso:country":"US",
    "sg:address":"52 Milltown Rd",
    "sg:city":"Stockton",
    "sg:classifiers":[
        {
            "category":"Building & Trades",
            "subcategory":"Construction",
            "type":"Services"
        }
    ],
    "sg:phone":"+1 908 996 4456",
    "sg:postcode":"08559",
    "sg:province":"NJ",
    "sg:tags":[
        "house"
    ],
    "wof:name":"Woodchuck Construction",
    "wof:placetype":"venue"
},
  "geometry": {"coordinates":[-75.027159,40.450466],"type":"Point"}
}