{
  "type": "Feature",
  "properties": {
    "addr:full":"48 Durham St Pompton Lakes NJ 07442",
    "addr:housenumber":"48",
    "addr:postcode":"07442",
    "addr:street":"Durham St",
    "iso:country":"US",
    "sg:address":"48 Durham St",
    "sg:city":"Pompton Lakes",
    "sg:classifiers":[
        {
            "category":"Professional",
            "subcategory":"Business Services",
            "type":"Services"
        }
    ],
    "sg:phone":"+1   ",
    "sg:postcode":"07442",
    "sg:province":"NJ",
    "wof:name":"Pinnacle Home Inspection",
    "wof:placetype":"venue"
},
  "geometry": {"coordinates":[-74.27772400000001,41.011622],"type":"Point"}
}