{
  "type": "Feature",
  "properties": {
    "addr:full":"1345 Hurffville Rd Deptford NJ 08096",
    "addr:housenumber":"1345",
    "addr:postcode":"08096",
    "addr:street":"Hurffville Rd",
    "iso:country":"US",
    "sg:address":"1345 Hurffville Rd",
    "sg:city":"Deptford",
    "sg:classifiers":[
        {
            "category":"Recreation",
            "type":"Entertainment"
        }
    ],
    "sg:phone":"+1 856 227 7500",
    "sg:postcode":"08096",
    "sg:province":"NJ",
    "sg:tags":[
        "paint",
        "ball",
        "sport"
    ],
    "wof:name":"Paintball Thunder",
    "wof:placetype":"venue"
},
  "geometry": {"coordinates":[-75.090934,39.820207],"type":"Point"}
}