{
  "type": "Feature",
  "properties": {
    "addr:full":"7 Holmes Ter Freehold NJ 07728",
    "addr:housenumber":"7",
    "addr:postcode":"07728",
    "addr:street":"Holmes Ter",
    "iso:country":"US",
    "sg:address":"7 Holmes Ter",
    "sg:city":"Freehold",
    "sg:classifiers":[
        {
            "category":"Building & Trades",
            "subcategory":"Construction",
            "type":"Services"
        }
    ],
    "sg:phone":"+1 732 780 4558",
    "sg:postcode":"07728",
    "sg:province":"NJ",
    "sg:tags":[
        "house",
        "contractor"
    ],
    "wof:name":"John W Sauter Builders",
    "wof:placetype":"venue"
},
  "geometry": {"coordinates":[-74.28230000000001,40.266855],"type":"Point"}
}