{
  "type": "Feature",
  "properties": {
    "iso:country":"US",
    "sg:address":"301 Parish Dr",
    "sg:city":"Wayne",
    "sg:classifiers":[
        {
            "category":"Building & Trades",
            "subcategory":"Construction",
            "type":"Services"
        }
    ],
    "sg:phone":"+1 973 709 0779",
    "sg:postcode":"07470",
    "sg:province":"NJ",
    "sg:tags":[
        "painter"
    ],
    "wof:name":"Gikas Painting & Decorating",
    "wof:placetype":"venue"
},
  "geometry": {"coordinates":[-74.25273799999999,40.916337],"type":"Point"}
}