{
  "type": "Feature",
  "properties": {
    "addr:full":"405 State Rte 33 Manalapan NJ 07726",
    "addr:housenumber":"405",
    "addr:postcode":"07726",
    "addr:street":"State Rte 33",
    "iso:country":"US",
    "sg:address":"405 State Rte 33",
    "sg:city":"Manalapan",
    "sg:classifiers":[
        {
            "category":"Manufacturing",
            "subcategory":"Chemicals & Compounds",
            "type":"Manufacturing & Wholesale Goods"
        }
    ],
    "sg:phone":"+1 732 446 5676",
    "sg:postcode":"07726",
    "sg:province":"NJ",
    "sg:tags":[
        "gas"
    ],
    "wof:name":"Air Products & Chemicals Inc",
    "wof:placetype":"venue"
},
  "geometry": {"coordinates":[-74.390198,40.256937],"type":"Point"}
}