{
  "type": "Feature",
  "properties": {
    "addr:full":"216 Birchwood Rd Westwood NJ 07675",
    "addr:housenumber":"216",
    "addr:postcode":"07675",
    "addr:street":"Birchwood Rd",
    "iso:country":"US",
    "sg:address":"216 Birchwood Rd",
    "sg:city":"Westwood",
    "sg:classifiers":[
        {
            "category":"Building & Trades",
            "subcategory":"Cleaning & Sanitation",
            "type":"Services"
        }
    ],
    "sg:phone":"+1   ",
    "sg:postcode":"07675",
    "sg:province":"NJ",
    "sg:tags":[
        "maintenance"
    ],
    "wof:name":"J&C Marble Maintenance Inc",
    "wof:placetype":"venue"
},
  "geometry": {"coordinates":[-74.0029,41.008421],"type":"Point"}
}