{
  "type": "Feature",
  "properties": {
    "addr:full":"783 Roosevelt Ave Carteret NJ 07008",
    "addr:housenumber":"783",
    "addr:postcode":"07008",
    "addr:street":"Roosevelt Ave",
    "iso:country":"US",
    "sg:address":"783 Roosevelt Ave",
    "sg:city":"Carteret",
    "sg:classifiers":[
        {
            "category":"Restaurant",
            "type":"Food & Drink"
        }
    ],
    "sg:phone":"+1   ",
    "sg:postcode":"07008",
    "sg:province":"NJ",
    "sg:tags":[
        "eating"
    ],
    "wof:name":"Chinese Gourmet",
    "wof:placetype":"venue"
},
  "geometry": {"coordinates":[-74.227304,40.589207],"type":"Point"}
}