{
  "type": "Feature",
  "properties": {
    "addr:full":"194 Bradley Ave Bergenfield NJ 07621",
    "addr:housenumber":"194",
    "addr:postcode":"07621",
    "addr:street":"Bradley Ave",
    "iso:country":"US",
    "sg:address":"194 Bradley Ave",
    "sg:city":"Bergenfield",
    "sg:classifiers":[
        {
            "category":"Professional",
            "subcategory":"Engineering",
            "type":"Services"
        }
    ],
    "sg:phone":"+1 201 387 8022",
    "sg:postcode":"07621",
    "sg:province":"NJ",
    "sg:tags":[
        "engineer"
    ],
    "wof:name":"TML Co",
    "wof:placetype":"venue"
},
  "geometry": {"coordinates":[-73.98891500000001,40.929204],"type":"Point"}
}