{
  "type": "Feature",
  "properties": {
    "iso:country":"US",
    "sg:address":"335 US Hwy 9",
    "sg:city":"Lanoka Harbor",
    "sg:classifiers":[
        {
            "category":"Professional",
            "subcategory":"Accounting & Tax Preparation",
            "type":"Services"
        }
    ],
    "sg:phone":"+1   ",
    "sg:postcode":"08734",
    "sg:province":"NJ",
    "sg:tags":[
        "return"
    ],
    "wof:name":"Robbins H & R Block",
    "wof:placetype":"venue"
},
  "geometry": {"coordinates":[-74.18268399999999,39.851461],"type":"Point"}
}