{
  "type": "Feature",
  "properties": {
    "iso:country":"US",
    "sg:address":"5 Park St",
    "sg:city":"Bordentown",
    "sg:classifiers":[
        {
            "category":"Wholesale",
            "subcategory":"Vending Machines",
            "type":"Manufacturing & Wholesale Goods"
        }
    ],
    "sg:phone":"+1   ",
    "sg:postcode":"08505",
    "sg:province":"NJ",
    "sg:tags":[
        "operator"
    ],
    "wof:name":"White Dog Vending Co",
    "wof:placetype":"venue"
},
  "geometry": {"coordinates":[-74.71243,40.149351],"type":"Point"}
}