{
  "type": "Feature",
  "properties": {
    "iso:country":"US",
    "sg:address":"147 Elmora Ave",
    "sg:city":"Elizabeth",
    "sg:classifiers":[
        {
            "category":"Restaurant",
            "type":"Food & Drink"
        }
    ],
    "sg:phone":"+1 908 289 9093",
    "sg:postcode":"07202",
    "sg:province":"NJ",
    "sg:tags":[
        "bar"
    ],
    "wof:name":"Panda Gardens",
    "wof:placetype":"venue"
},
  "geometry": {"coordinates":[-74.23343,40.662304],"type":"Point"}
}