{
  "type": "Feature",
  "properties": {
    "addr:full":"75 E Browning Rd Bellmawr NJ 08031",
    "addr:housenumber":"75",
    "addr:postcode":"08031",
    "addr:street":"E Browning Rd",
    "iso:country":"US",
    "sg:address":"75 E Browning Rd",
    "sg:city":"Bellmawr",
    "sg:classifiers":[
        {
            "category":"Personal",
            "subcategory":"Barber",
            "type":"Services"
        }
    ],
    "sg:phone":"+1 856 931 0764",
    "sg:postcode":"08031",
    "sg:province":"NJ",
    "wof:name":"Joe's Barber Shop",
    "wof:placetype":"venue"
},
  "geometry": {"coordinates":[-75.077499,39.8666],"type":"Point"}
}