{
  "type": "Feature",
  "properties": {
    "addr:full":"8 3rd St Fair Lawn NJ 07410",
    "addr:housenumber":"8",
    "addr:postcode":"07410",
    "addr:street":"3Rd St",
    "iso:country":"US",
    "sg:address":"8 3rd St",
    "sg:city":"Fair Lawn",
    "sg:classifiers":[
        {
            "category":"Professional",
            "subcategory":"Management & Consulting",
            "type":"Services"
        }
    ],
    "sg:phone":"+1 201 794 0615",
    "sg:postcode":"07410",
    "sg:province":"NJ",
    "sg:tags":[
        "public",
        "relations"
    ],
    "wof:name":"Prp Networks Inc",
    "wof:placetype":"venue"
},
  "geometry": {"coordinates":[-74.135453,40.929851],"type":"Point"}
}