{
  "type": "Feature",
  "properties": {
    "iso:country":"US",
    "sg:address":"273 Egg Harbor Rd",
    "sg:city":"Sewell",
    "sg:classifiers":[
        {
            "category":"Restaurant",
            "type":"Food & Drink"
        }
    ],
    "sg:menulink":"http://www.allmenus.com/nj/washington/15217-johnnys-pizza/menu/",
    "sg:phone":"+1 856 256 9111",
    "sg:postcode":"08080",
    "sg:province":"NJ",
    "sg:tags":[
        "american",
        "italian",
        "pizza"
    ],
    "wof:name":"Johnny's Pizza",
    "wof:placetype":"venue"
},
  "geometry": {"coordinates":[-75.08819699999999,39.768425],"type":"Point"}
}