{
  "type": "Feature",
  "properties": {
    "iso:country":"US",
    "sg:address":"40 Riverview Ave",
    "sg:city":"Neptune",
    "sg:classifiers":[
        {
            "category":"Real Estate",
            "subcategory":"Real Estate Agent",
            "type":"Services"
        }
    ],
    "sg:phone":"+1 732 774 2207",
    "sg:postcode":"07753",
    "sg:province":"NJ",
    "sg:tags":[
        "inspection"
    ],
    "wof:name":"Jersey Central Home Inspection",
    "wof:placetype":"venue"
},
  "geometry": {"coordinates":[-74.02851,40.193632],"type":"Point"}
}