{
  "type": "Feature",
  "properties": {
    "iso:country":"US",
    "sg:address":"2444 Hamilton Ave",
    "sg:city":"Trenton",
    "sg:classifiers":[
        {
            "category":"Home & Garden",
            "subcategory":"Hardware",
            "type":"Retail Goods"
        }
    ],
    "sg:phone":"+1   ",
    "sg:postcode":"08619",
    "sg:province":"NJ",
    "sg:tags":[
        "repair",
        "merchandise"
    ],
    "wof:name":"Parkers Safe & Lock",
    "wof:placetype":"venue"
},
  "geometry": {"coordinates":[-74.70088199999999,40.232399],"type":"Point"}
}