{
  "type": "Feature",
  "properties": {
    "iso:country":"US",
    "sg:address":"290 Hoboken Ave",
    "sg:city":"Jersey City",
    "sg:classifiers":[
        {
            "category":"Banks & Credit Unions",
            "subcategory":"Investment Brokerage",
            "type":"Services"
        }
    ],
    "sg:phone":"+1   ",
    "sg:postcode":"07306",
    "sg:province":"NJ",
    "sg:tags":[
        "advisory"
    ],
    "wof:name":"Blue Print Investment",
    "wof:placetype":"venue"
},
  "geometry": {"coordinates":[-74.05294600000001,40.73218],"type":"Point"}
}