{
  "type": "Feature",
  "properties": {
    "iso:country":"US",
    "sg:address":"401 Market St",
    "sg:city":"Camden",
    "sg:classifiers":[
        {
            "category":"Health Services",
            "subcategory":"Health Practitioner",
            "type":"Services"
        }
    ],
    "sg:phone":"+1 856 635 0502",
    "sg:postcode":"08102",
    "sg:province":"NJ",
    "sg:tags":[
        "occupational",
        "therapist"
    ],
    "wof:name":"Occupational Training Center",
    "wof:placetype":"venue"
},
  "geometry": {"coordinates":[-75.12243700000001,39.945869],"type":"Point"}
}