{
  "type": "Feature",
  "properties": {
    "iso:country":"US",
    "sg:address":"36 Wall St",
    "sg:city":"Passaic",
    "sg:classifiers":[
        {
            "category":"Food & Beverages",
            "subcategory":"Groceries & Convenience Stores",
            "type":"Retail Goods"
        }
    ],
    "sg:phone":"+1 973 777 3403",
    "sg:postcode":"07055",
    "sg:province":"NJ",
    "sg:tags":[
        "grocer"
    ],
    "wof:name":"News Supermarket",
    "wof:placetype":"venue"
},
  "geometry": {"coordinates":[-74.111019,40.86373],"type":"Point"}
}