{
  "type": "Feature",
  "properties": {
    "addr:full":"173 Main St Hackettstown NJ 07840",
    "addr:housenumber":"173",
    "addr:postcode":"07840",
    "addr:street":"Main St",
    "iso:country":"US",
    "sg:address":"173 Main St",
    "sg:city":"Hackettstown",
    "sg:classifiers":[
        {
            "category":"Shopping",
            "subcategory":"Gifts & Souvenirs",
            "type":"Retail Goods"
        }
    ],
    "sg:phone":"+1 908 852 8035",
    "sg:postcode":"07840",
    "sg:province":"NJ",
    "sg:tags":[
        "party",
        "novelty",
        "favor",
        "supply"
    ],
    "wof:name":"Super Stuff Parts Supply",
    "wof:placetype":"venue"
},
  "geometry": {"coordinates":[-74.828788,40.853522],"type":"Point"}
}