{
  "type": "Feature",
  "properties": {
    "addr:full":"27 Brookside Ave Old Bridge NJ 08857",
    "addr:housenumber":"27",
    "addr:postcode":"08857",
    "addr:street":"Brookside Ave",
    "iso:country":"US",
    "sg:address":"27 Brookside Ave",
    "sg:city":"Old Bridge",
    "sg:classifiers":[
        {
            "category":"Organizations",
            "subcategory":"Religious Organization",
            "type":"Services"
        }
    ],
    "sg:phone":"+1   ",
    "sg:postcode":"08857",
    "sg:province":"NJ",
    "wof:name":"Polish Roman Catholic UNI",
    "wof:placetype":"venue"
},
  "geometry": {"coordinates":[-74.36281700000001,40.393726],"type":"Point"}
}