{
  "type": "Feature",
  "properties": {
    "addr:full":"35 Washington Ave Tenafly NJ 07670",
    "addr:housenumber":"35",
    "addr:postcode":"07670",
    "addr:street":"Washington Ave",
    "iso:country":"US",
    "sg:address":"35 Washington Ave",
    "sg:city":"Tenafly",
    "sg:classifiers":[
        {
            "category":"Food & Beverages",
            "subcategory":"Groceries & Convenience Stores",
            "type":"Retail Goods"
        }
    ],
    "sg:phone":"+1 201 541 1270",
    "sg:postcode":"07670",
    "sg:province":"NJ",
    "sg:tags":[
        "shop",
        "sandwich"
    ],
    "sg:website":"http://www.blimpie.com",
    "wof:name":"BLIMPIE Subs & Salads",
    "wof:placetype":"venue"
},
  "geometry": {"coordinates":[-73.966397,40.925507],"type":"Point"}
}