{
  "type": "Feature",
  "properties": {
    "iso:country":"US",
    "sg:address":"300 State Rt 17 S",
    "sg:city":"Lodi",
    "sg:classifiers":[
        {
            "category":"Professional",
            "subcategory":"Computer Services",
            "type":"Services"
        }
    ],
    "sg:phone":"+1 973 249 6666",
    "sg:postcode":"07644",
    "sg:province":"NJ",
    "sg:tags":[
        "repair"
    ],
    "sg:website":"www.smoothsolutions.com",
    "wof:name":"Smooth Solutions Inc",
    "wof:placetype":"venue"
},
  "geometry": {"coordinates":[-74.069603,40.877899],"type":"Point"}
}