{
  "type": "Feature",
  "properties": {
    "addr:full":"322 Farwood Rd Haddonfield NJ 08033",
    "addr:housenumber":"322",
    "addr:postcode":"08033",
    "addr:street":"Farwood Rd",
    "iso:country":"US",
    "sg:address":"322 Farwood Rd",
    "sg:city":"Haddonfield",
    "sg:classifiers":[
        {
            "category":"Professional",
            "subcategory":"Secretarial Services",
            "type":"Services"
        }
    ],
    "sg:phone":"+1   ",
    "sg:postcode":"08033",
    "sg:province":"NJ",
    "sg:tags":[
        "reporting"
    ],
    "wof:name":"Diane Omara Secretarial Servic",
    "wof:placetype":"venue"
},
  "geometry": {"coordinates":[-75.038725,39.911488],"type":"Point"}
}