{
  "type": "Feature",
  "properties": {
    "iso:country":"US",
    "sg:address":"106 Allen Rd",
    "sg:city":"Basking Ridge",
    "sg:classifiers":[
        {
            "category":"Professional",
            "type":"Services"
        }
    ],
    "sg:phone":"+1   ",
    "sg:postcode":"07920",
    "sg:province":"NJ",
    "wof:name":"Hcl Comnet Systems",
    "wof:placetype":"venue"
},
  "geometry": {"coordinates":[-74.586938,40.649838],"type":"Point"}
}