{
  "type": "Feature",
  "properties": {
    "iso:country":"US",
    "sg:address":"1 Overlook Rd",
    "sg:city":"Chatham",
    "sg:classifiers":[
        {
            "category":"Professional",
            "subcategory":"Computer Services",
            "type":"Services"
        }
    ],
    "sg:phone":"+1 973 408 9202",
    "sg:postcode":"07928",
    "sg:province":"NJ",
    "sg:tags":[
        "datum"
    ],
    "wof:name":"Produx",
    "wof:placetype":"venue"
},
  "geometry": {"coordinates":[-74.41410399999999,40.738946],"type":"Point"}
}