{
  "type": "Feature",
  "properties": {
    "iso:country":"US",
    "sg:address":"205 Long Branch Ave",
    "sg:city":"Long Branch",
    "sg:classifiers":[
        {
            "category":"Wholesale",
            "subcategory":"Electrical",
            "type":"Manufacturing & Wholesale Goods"
        }
    ],
    "sg:phone":"+1 732 870 0201",
    "sg:postcode":"07740",
    "sg:province":"NJ",
    "sg:tags":[
        "fire",
        "alarm",
        "system"
    ],
    "wof:name":"Allphase Security & Battle",
    "wof:placetype":"venue"
},
  "geometry": {"coordinates":[-73.984157,40.3129],"type":"Point"}
}