{
  "type": "Feature",
  "properties": {
    "addr:full":"253 Belle Mead Griggstwn Rd Belle Mead NJ 08502",
    "addr:housenumber":"253",
    "addr:postcode":"08502",
    "addr:street":"Belle Mead Griggstwn Rd",
    "iso:country":"US",
    "sg:address":"253 Belle Mead Griggstwn Rd",
    "sg:city":"Belle Mead",
    "sg:classifiers":[
        {
            "category":"Organizations",
            "subcategory":"Religious Organization",
            "type":"Services"
        }
    ],
    "sg:phone":"+1 908 359 0420",
    "sg:postcode":"08502",
    "sg:province":"NJ",
    "sg:tags":[
        "synagogue"
    ],
    "sg:website":"www.jccbm.org",
    "wof:name":"Jewish Community Ctr",
    "wof:placetype":"venue"
},
  "geometry": {"coordinates":[-74.64245,40.452223],"type":"Point"}
}