{
  "type": "Feature",
  "properties": {
    "addr:full":"450 Murray Hill Pkwy East Rutherford NJ 07073",
    "addr:housenumber":"450",
    "addr:postcode":"07073",
    "addr:street":"Murray Hill Pkwy",
    "iso:country":"US",
    "sg:address":"450 Murray Hill Pkwy",
    "sg:city":"East Rutherford",
    "sg:classifiers":[
        {
            "category":"Shopping",
            "subcategory":"Clothing, Apparel, & Fashions",
            "type":"Retail Goods"
        }
    ],
    "sg:phone":"+1 201 933 8111",
    "sg:postcode":"07073",
    "sg:province":"NJ",
    "sg:tags":[
        "clothing",
        "women's"
    ],
    "wof:name":"Metropolitan Manufacturing Inc",
    "wof:placetype":"venue"
},
  "geometry": {"coordinates":[-74.0933,40.8167],"type":"Point"}
}