{
  "type": "Feature",
  "properties": {
    "addr:full":"412 Pleasant Valley Way West Orange NJ 07052",
    "addr:housenumber":"412",
    "addr:postcode":"07052",
    "addr:street":"Pleasant Valley Way",
    "iso:country":"US",
    "sg:address":"412 Pleasant Valley Way",
    "sg:city":"West Orange",
    "sg:classifiers":[
        {
            "category":"Health Services",
            "subcategory":"Dentist",
            "type":"Services"
        }
    ],
    "sg:phone":"+1 973 731 2468",
    "sg:postcode":"07052",
    "sg:province":"NJ",
    "sg:tags":[
        "pediatric"
    ],
    "wof:name":"Rosenfeld Kimberly DMD",
    "wof:placetype":"venue"
},
  "geometry": {"coordinates":[-74.25962,40.811723],"type":"Point"}
}