{
  "type": "Feature",
  "properties": {
    "addr:full":"25 Burlington Rd Monroeville NJ 08343",
    "addr:housenumber":"25",
    "addr:postcode":"08343",
    "addr:street":"Burlington Rd",
    "iso:country":"US",
    "sg:address":"25 Burlington Rd",
    "sg:city":"Monroeville",
    "sg:classifiers":[
        {
            "category":"Farming",
            "subcategory":"Farm",
            "type":"Manufacturing & Wholesale Goods"
        }
    ],
    "sg:phone":"+1 856 358 8169",
    "sg:postcode":"08343",
    "sg:province":"NJ",
    "sg:tags":[
        "food",
        "covered",
        "crop"
    ],
    "wof:name":"Maurice Kernan Jr",
    "wof:placetype":"venue"
},
  "geometry": {"coordinates":[-75.201639,39.618855],"type":"Point"}
}