{
  "type": "Feature",
  "properties": {
    "addr:full":"200 Jockey Hollow Rd Bernardsville NJ 07924",
    "addr:housenumber":"200",
    "addr:postcode":"07924",
    "addr:street":"Jockey Hollow Rd",
    "iso:country":"US",
    "sg:address":"200 Jockey Hollow Rd",
    "sg:city":"Bernardsville",
    "sg:classifiers":[
        {
            "category":"Professional",
            "subcategory":"Management & Consulting",
            "type":"Services"
        }
    ],
    "sg:phone":"+1 908 204 1942",
    "sg:postcode":"07924",
    "sg:province":"NJ",
    "sg:tags":[
        "consultant"
    ],
    "wof:name":"Monica Oliver Consulting",
    "wof:placetype":"venue"
},
  "geometry": {"coordinates":[-74.55694099999999,40.754135],"type":"Point"}
}