{
  "type": "Feature",
  "properties": {
    "iso:country":"US",
    "sg:address":"86 Paterson Ave",
    "sg:city":"West Paterson",
    "sg:classifiers":[
        {
            "category":"Professional",
            "subcategory":"Art Services",
            "type":"Services"
        }
    ],
    "sg:phone":"+1 973 256 9060",
    "sg:postcode":"07424",
    "sg:province":"NJ",
    "sg:tags":[
        "photographer"
    ],
    "wof:name":"Gene Bowman Photography",
    "wof:placetype":"venue"
},
  "geometry": {"coordinates":[-74.22667800000001,40.881788],"type":"Point"}
}