{
  "type": "Feature",
  "properties": {
    "addr:full":"927 S 18th St Newark NJ 07108",
    "addr:housenumber":"927",
    "addr:postcode":"07108",
    "addr:street":"S 18Th St",
    "iso:country":"US",
    "sg:address":"927 S 18th St",
    "sg:city":"Newark",
    "sg:classifiers":[
        {
            "category":"Home & Garden",
            "subcategory":"Hardware",
            "type":"Retail Goods"
        }
    ],
    "sg:phone":"+1 973 372 7288",
    "sg:postcode":"07108",
    "sg:province":"NJ",
    "wof:name":"New American Hardware Salv Co",
    "wof:placetype":"venue"
},
  "geometry": {"coordinates":[-74.214844,40.724127],"type":"Point"}
}