{
  "type": "Feature",
  "properties": {
    "addr:full":"1041 Bloomfield St Hoboken NJ 07030",
    "addr:housenumber":"1041",
    "addr:postcode":"07030",
    "addr:street":"Bloomfield St",
    "iso:country":"US",
    "sg:address":"1041 Bloomfield St",
    "sg:city":"Hoboken",
    "sg:classifiers":[
        {
            "category":"Personal",
            "type":"Services"
        }
    ],
    "sg:phone":"+1   ",
    "sg:postcode":"07030",
    "sg:province":"NJ",
    "wof:name":"Shop Gotham Inc",
    "wof:placetype":"venue"
},
  "geometry": {"coordinates":[-74.027981,40.749454],"type":"Point"}
}