{
  "type": "Feature",
  "properties": {
    "addr:full":"57 State Rte 35 Neptune NJ 07753",
    "addr:housenumber":"57",
    "addr:postcode":"07753",
    "addr:street":"State Rte 35",
    "iso:country":"US",
    "sg:address":"57 State Rte 35",
    "sg:city":"Neptune",
    "sg:classifiers":[
        {
            "category":"Autos & Motor Vehicles",
            "subcategory":"Auto Supplies",
            "type":"Retail Goods"
        },
        {
            "category":"Wholesale",
            "subcategory":"Auto Parts",
            "type":"Manufacturing & Wholesale Goods"
        }
    ],
    "sg:phone":"+1 732 774 1222",
    "sg:postcode":"07753",
    "sg:province":"NJ",
    "sg:tags":[
        "automobile",
        "new",
        "p"
    ],
    "wof:name":"F & C Automotive Supply Inc",
    "wof:placetype":"venue"
},
  "geometry": {"coordinates":[-74.028746,40.198607],"type":"Point"}
}