{
  "type": "Feature",
  "properties": {
    "iso:country":"US",
    "sg:address":"209 Remsen Ave",
    "sg:city":"Avenel",
    "sg:classifiers":[
        {
            "category":"Manufacturing",
            "subcategory":"Food",
            "type":"Manufacturing & Wholesale Goods"
        }
    ],
    "sg:phone":"+1 732 634 7378",
    "sg:postcode":"07001",
    "sg:province":"NJ",
    "sg:tags":[
        "mfg"
    ],
    "wof:name":"A Little Something Sweet",
    "wof:placetype":"venue"
},
  "geometry": {"coordinates":[-74.28953,40.579999],"type":"Point"}
}