{
  "type": "Feature",
  "properties": {
    "addr:full":"140 Palmer Ave South Plainfield NJ 07080",
    "addr:housenumber":"140",
    "addr:postcode":"07080",
    "addr:street":"Palmer Ave",
    "iso:country":"US",
    "sg:address":"140 Palmer Ave",
    "sg:city":"South Plainfield",
    "sg:classifiers":[
        {
            "category":"Arts & Performance",
            "subcategory":"Theater",
            "type":"Entertainment"
        }
    ],
    "sg:phone":"+1 908 756 7030",
    "sg:postcode":"07080",
    "sg:province":"NJ",
    "sg:tags":[
        "group"
    ],
    "wof:name":"John Bundy Productions",
    "wof:placetype":"venue"
},
  "geometry": {"coordinates":[-74.42973000000001,40.596135],"type":"Point"}
}