{
  "type": "Feature",
  "properties": {
    "addr:full":"2796 Hooper Ave Brick NJ 08723",
    "addr:housenumber":"2796",
    "addr:postcode":"08723",
    "addr:street":"Hooper Ave",
    "iso:country":"US",
    "sg:address":"2796 Hooper Ave",
    "sg:city":"Brick",
    "sg:classifiers":[
        {
            "category":"Travel",
            "subcategory":"Travel Agent",
            "type":"Entertainment"
        }
    ],
    "sg:phone":"+1 732 920 3500",
    "sg:postcode":"08723",
    "sg:province":"NJ",
    "sg:tags":[
        "agency",
        "bureau"
    ],
    "sg:website":"www.libertytravel.com",
    "wof:name":"Liberty Travel Inc",
    "wof:placetype":"venue"
},
  "geometry": {"coordinates":[-74.136602,40.0576],"type":"Point"}
}