{
  "type": "Feature",
  "properties": {
    "addr:full":"28 Yard Ave Trenton NJ 08609",
    "addr:housenumber":"28",
    "addr:postcode":"08609",
    "addr:street":"Yard Ave",
    "iso:country":"US",
    "sg:address":"28 Yard Ave",
    "sg:city":"Trenton",
    "sg:classifiers":[
        {
            "category":"Government",
            "subcategory":"Office",
            "type":"Public Place"
        }
    ],
    "sg:phone":"+1 609 292 2508",
    "sg:postcode":"08609",
    "sg:province":"NJ",
    "sg:tags":[
        "state",
        "resource"
    ],
    "wof:name":"Workers Compensation",
    "wof:placetype":"venue"
},
  "geometry": {"coordinates":[-74.75394900000001,40.219647],"type":"Point"}
}