{
  "type": "Feature",
  "properties": {
    "addr:full":"265 Rte 10 East Hanover NJ 07936",
    "addr:housenumber":"265",
    "addr:postcode":"07936",
    "addr:street":"Rte 10",
    "iso:country":"US",
    "sg:address":"265 Rte 10",
    "sg:city":"East Hanover",
    "sg:classifiers":[
        {
            "category":"Personal",
            "subcategory":"Tanning Parlor",
            "type":"Services"
        }
    ],
    "sg:phone":"+1 973 884 9559",
    "sg:postcode":"07936",
    "sg:province":"NJ",
    "sg:website":"beachbumeasthanover.com",
    "wof:name":"Beach Bum Tanning & Airbrush Salon",
    "wof:placetype":"venue"
},
  "geometry": {"coordinates":[-74.37061799999999,40.806208],"type":"Point"}
}