{
  "type": "Feature",
  "properties": {
    "iso:country":"US",
    "sg:address":"35 Waterview Blvd",
    "sg:city":"Parsippany",
    "sg:classifiers":[
        {
            "category":"Professional",
            "subcategory":"Advertising",
            "type":"Services"
        }
    ],
    "sg:phone":"+1   ",
    "sg:postcode":"07054",
    "sg:province":"NJ",
    "sg:tags":[
        "full",
        "agency",
        "relations",
        "public"
    ],
    "wof:name":"R & J",
    "wof:placetype":"venue"
},
  "geometry": {"coordinates":[-74.428855,40.874988],"type":"Point"}
}