{
  "type": "Feature",
  "properties": {
    "iso:country":"US",
    "sg:address":"65 Lee Ave",
    "sg:city":"Perth Amboy",
    "sg:classifiers":[
        {
            "category":"Insurance",
            "subcategory":"Insurance Agent",
            "type":"Services"
        }
    ],
    "sg:phone":"+1   ",
    "sg:postcode":"08861",
    "sg:province":"NJ",
    "wof:name":"Scharff & Daughter Insurance A",
    "wof:placetype":"venue"
},
  "geometry": {"coordinates":[-74.29458200000001,40.526393],"type":"Point"}
}