{
  "type": "Feature",
  "properties": {
    "addr:full":"150 Sylvan Ave Englewood Cliffs NJ 07632",
    "addr:housenumber":"150",
    "addr:postcode":"07632",
    "addr:street":"Sylvan Ave",
    "iso:country":"US",
    "sg:address":"150 Sylvan Ave",
    "sg:city":"Englewood Cliffs",
    "sg:classifiers":[
        {
            "category":"Health Services",
            "subcategory":"Chiropractor",
            "type":"Services"
        }
    ],
    "sg:phone":"+1 201 894 0444",
    "sg:postcode":"07632",
    "sg:province":"NJ",
    "wof:name":"Meimaris Sports Chiropractic",
    "wof:placetype":"venue"
},
  "geometry": {"coordinates":[-73.95390999999999,40.872532],"type":"Point"}
}