{
  "type": "Feature",
  "properties": {
    "iso:country":"US",
    "sg:address":"1300 State Rte 35",
    "sg:city":"Middletown",
    "sg:classifiers":[
        {
            "category":"Restaurant",
            "type":"Food & Drink"
        }
    ],
    "sg:phone":"+1 732 671 8322",
    "sg:postcode":"07748",
    "sg:province":"NJ",
    "sg:tags":[
        "parlor",
        "ice",
        "cream"
    ],
    "wof:name":"Rita's Ice",
    "wof:placetype":"venue"
},
  "geometry": {"coordinates":[-74.11835600000001,40.39996],"type":"Point"}
}