{
  "type": "Feature",
  "properties": {
    "addr:full":"1161 Park Ave Plainfield NJ 07060",
    "addr:housenumber":"1161",
    "addr:postcode":"07060",
    "addr:street":"Park Ave",
    "iso:country":"US",
    "sg:address":"1161 Park Ave",
    "sg:city":"Plainfield",
    "sg:classifiers":[
        {
            "category":"Wholesale",
            "subcategory":"Chemicals & Plastics",
            "type":"Manufacturing & Wholesale Goods"
        }
    ],
    "sg:phone":"+1 908 757 4400",
    "sg:postcode":"07060",
    "sg:province":"NJ",
    "sg:tags":[
        "paint",
        "material"
    ],
    "wof:name":"Westdry Industries Inc",
    "wof:placetype":"venue"
},
  "geometry": {"coordinates":[-74.406938,40.608733],"type":"Point"}
}