{
  "type": "Feature",
  "properties": {
    "iso:country":"US",
    "sg:address":"345 Main St",
    "sg:city":"Newport",
    "sg:classifiers":[
        {
            "category":"Building & Trades",
            "subcategory":"Plumbing",
            "type":"Services"
        }
    ],
    "sg:phone":"+1 856 447 3919",
    "sg:postcode":"08345",
    "sg:province":"NJ",
    "sg:tags":[
        "heating",
        "contractor"
    ],
    "wof:name":"Mathis Heating & Air Cond",
    "wof:placetype":"venue"
},
  "geometry": {"coordinates":[-75.155823,39.290843],"type":"Point"}
}