{
  "type": "Feature",
  "properties": {
    "addr:full":"199 Pomeroy Rd Parsippany NJ 07054",
    "addr:housenumber":"199",
    "addr:postcode":"07054",
    "addr:street":"Pomeroy Rd",
    "iso:country":"US",
    "sg:address":"199 Pomeroy Rd",
    "sg:city":"Parsippany",
    "sg:classifiers":[
        {
            "category":"Travel",
            "subcategory":"Travel Agent",
            "type":"Entertainment"
        }
    ],
    "sg:phone":"+1 973 952 8938",
    "sg:postcode":"07054",
    "sg:province":"NJ",
    "sg:tags":[
        "agency"
    ],
    "wof:name":"American Express",
    "wof:placetype":"venue"
},
  "geometry": {"coordinates":[-74.420258,40.857191],"type":"Point"}
}