{
  "type": "Feature",
  "properties": {
    "iso:country":"US",
    "sg:address":"33 W State St",
    "sg:city":"Trenton",
    "sg:classifiers":[
        {
            "category":"Banks & Credit Unions",
            "subcategory":"Bank",
            "type":"Services"
        }
    ],
    "sg:phone":"+1   ",
    "sg:postcode":"08618",
    "sg:province":"NJ",
    "sg:tags":[
        "fed"
    ],
    "wof:name":"Sovereign Bank",
    "wof:placetype":"venue"
},
  "geometry": {"coordinates":[-74.768033,40.220506],"type":"Point"}
}