{
  "type": "Feature",
  "properties": {
    "iso:country":"US",
    "sg:address":"2094 Englishtown Rd",
    "sg:city":"Jamesburg",
    "sg:classifiers":[
        {
            "category":"Home & Garden",
            "subcategory":"Furniture",
            "type":"Retail Goods"
        }
    ],
    "sg:phone":"+1 732 446 2535",
    "sg:postcode":"08831",
    "sg:province":"NJ",
    "wof:name":"Oak Furniture Depot Inc",
    "wof:placetype":"venue"
},
  "geometry": {"coordinates":[-74.35728899999999,40.347012],"type":"Point"}
}