{
  "type": "Feature",
  "properties": {
    "iso:country":"US",
    "sg:address":"459 Maitland Ave",
    "sg:city":"Teaneck",
    "sg:classifiers":[
        {
            "category":"Social Services",
            "type":"Services"
        }
    ],
    "sg:phone":"+1 201 833 0333",
    "sg:postcode":"07666",
    "sg:province":"NJ",
    "sg:tags":[
        "counselor",
        "marriage",
        "family"
    ],
    "wof:name":"Harrison Products Corp",
    "wof:placetype":"venue"
},
  "geometry": {"coordinates":[-74.01297700000001,40.906277],"type":"Point"}
}