{
  "type": "Feature",
  "properties": {
    "addr:full":"46 S Orange Ave South Orange NJ 07079",
    "addr:housenumber":"46",
    "addr:postcode":"07079",
    "addr:street":"S Orange Ave",
    "iso:country":"US",
    "sg:address":"46 S Orange Ave",
    "sg:city":"South Orange",
    "sg:classifiers":[
        {
            "category":"Professional",
            "subcategory":"Business Services",
            "type":"Services"
        }
    ],
    "sg:phone":"+1   ",
    "sg:postcode":"07079",
    "sg:province":"NJ",
    "wof:name":"Kns Twine Inc",
    "wof:placetype":"venue"
},
  "geometry": {"coordinates":[-74.258078,40.745684],"type":"Point"}
}