{
  "type": "Feature",
  "properties": {
    "iso:country":"US",
    "sg:address":"2 Dedrick Pl",
    "sg:city":"West Caldwell",
    "sg:classifiers":[
        {
            "category":"Food & Beverages",
            "subcategory":"Meat & Fish",
            "type":"Retail Goods"
        }
    ],
    "sg:phone":"+1 973 575 9526",
    "sg:postcode":"07006",
    "sg:province":"NJ",
    "sg:tags":[
        "seafood",
        "market"
    ],
    "wof:name":"Freshpro",
    "wof:placetype":"venue"
},
  "geometry": {"coordinates":[-74.2938,40.8559],"type":"Point"}
}