{
  "type": "Feature",
  "properties": {
    "iso:country":"US",
    "sg:address":"55 W Shore Ave",
    "sg:city":"Dumont",
    "sg:classifiers":[
        {
            "category":"Recreation",
            "type":"Entertainment"
        }
    ],
    "sg:phone":"+1 201 384 6900",
    "sg:postcode":"07628",
    "sg:province":"NJ",
    "sg:tags":[
        "karate",
        "judo",
        "instr"
    ],
    "wof:name":"Master Nathan's Martial Arts",
    "wof:placetype":"venue"
},
  "geometry": {"coordinates":[-73.995013,40.944302],"type":"Point"}
}