{
  "type": "Feature",
  "properties": {
    "addr:full":"196 Hackensack St Wood-Ridge NJ 07075",
    "addr:housenumber":"196",
    "addr:postcode":"07075",
    "addr:street":"Hackensack St",
    "iso:country":"US",
    "sg:address":"196 Hackensack St",
    "sg:city":"Wood-Ridge",
    "sg:classifiers":[
        {
            "category":"Food & Beverages",
            "subcategory":"Groceries & Convenience Stores",
            "type":"Retail Goods"
        }
    ],
    "sg:phone":"+1   ",
    "sg:postcode":"07075",
    "sg:province":"NJ",
    "wof:name":"Abubuckr Inc",
    "wof:placetype":"venue"
},
  "geometry": {"coordinates":[-74.082588,40.846918],"type":"Point"}
}