{
  "type": "Feature",
  "properties": {
    "addr:full":"336 Montgomery St Jersey City NJ 07302",
    "addr:housenumber":"336",
    "addr:postcode":"07302",
    "addr:street":"Montgomery St",
    "iso:country":"US",
    "sg:address":"336 Montgomery St",
    "sg:city":"Jersey City",
    "sg:classifiers":[
        {
            "category":"Real Estate",
            "subcategory":"Real Estate Agent",
            "type":"Services"
        }
    ],
    "sg:phone":"+1 201 435 0333",
    "sg:postcode":"07302",
    "sg:province":"NJ",
    "sg:tags":[
        "management",
        "property"
    ],
    "wof:name":"Urban Home Ownership Corp",
    "wof:placetype":"venue"
},
  "geometry": {"coordinates":[-74.049797,40.719299],"type":"Point"}
}