{
  "type": "Feature",
  "properties": {
    "addr:full":"142 Harding Ave Clifton NJ 07011",
    "addr:housenumber":"142",
    "addr:postcode":"07011",
    "addr:street":"Harding Ave",
    "iso:country":"US",
    "sg:address":"142 Harding Ave",
    "sg:city":"Clifton",
    "sg:classifiers":[
        {
            "category":"Organizations",
            "subcategory":"Community Association",
            "type":"Services"
        }
    ],
    "sg:phone":"+1 973 478 3682",
    "sg:postcode":"07011",
    "sg:province":"NJ",
    "wof:name":"Order of Eastern Star of",
    "wof:placetype":"venue"
},
  "geometry": {"coordinates":[-74.14472600000001,40.875367],"type":"Point"}
}