{
  "type": "Feature",
  "properties": {
    "iso:country":"US",
    "sg:address":"394 Croshaw Rd",
    "sg:city":"Wrightstown",
    "sg:classifiers":[
        {
            "category":"Building & Trades",
            "subcategory":"Construction",
            "type":"Services"
        }
    ],
    "sg:phone":"+1 609 723 0418",
    "sg:postcode":"08562",
    "sg:province":"NJ",
    "sg:tags":[
        "house"
    ],
    "wof:name":"Windyhill Construction Co",
    "wof:placetype":"venue"
},
  "geometry": {"coordinates":[-74.612342,40.05047],"type":"Point"}
}