{
  "type": "Feature",
  "properties": {
    "iso:country":"US",
    "sg:address":"386 Chancellor Ave",
    "sg:city":"Newark",
    "sg:classifiers":[
        {
            "category":"Organizations",
            "subcategory":"Religious Organization",
            "type":"Services"
        }
    ],
    "sg:phone":"+1 973 923 3164",
    "sg:postcode":"07112",
    "sg:province":"NJ",
    "sg:tags":[
        "church"
    ],
    "wof:name":"Christ Temple Of Peace Dlvrnc",
    "wof:placetype":"venue"
},
  "geometry": {"coordinates":[-74.223902,40.710564],"type":"Point"}
}