{
  "type": "Feature",
  "properties": {
    "addr:full":"7 Cambridge Dr Annandale NJ 08801",
    "addr:housenumber":"7",
    "addr:postcode":"08801",
    "addr:street":"Cambridge Dr",
    "iso:country":"US",
    "sg:address":"7 Cambridge Dr",
    "sg:city":"Annandale",
    "sg:classifiers":[
        {
            "category":"Professional",
            "type":"Services"
        }
    ],
    "sg:phone":"+1   ",
    "sg:postcode":"08801",
    "sg:province":"NJ",
    "wof:name":"Cds Cambridge Corp",
    "wof:placetype":"venue"
},
  "geometry": {"coordinates":[-74.894423,40.611657],"type":"Point"}
}