{
  "type": "Feature",
  "properties": {
    "addr:full":"494 Demarest Ave Oradell NJ 07649",
    "addr:housenumber":"494",
    "addr:postcode":"07649",
    "addr:street":"Demarest Ave",
    "iso:country":"US",
    "sg:address":"494 Demarest Ave",
    "sg:city":"Oradell",
    "sg:classifiers":[
        {
            "category":"Manufacturing",
            "subcategory":"Paper Products",
            "type":"Manufacturing & Wholesale Goods"
        }
    ],
    "sg:phone":"+1 201 262 6022",
    "sg:postcode":"07649",
    "sg:province":"NJ",
    "sg:tags":[
        "manufacture",
        "corrugated",
        "design",
        "packaging"
    ],
    "wof:name":"Web Design Inc",
    "wof:placetype":"venue"
},
  "geometry": {"coordinates":[-74.025453,40.95779],"type":"Point"}
}