{
  "type": "Feature",
  "properties": {
    "addr:full":"246 W 6th Ave Roselle NJ 07203",
    "addr:housenumber":"246",
    "addr:postcode":"07203",
    "addr:street":"W 6Th Ave",
    "iso:country":"US",
    "sg:address":"246 W 6th Ave",
    "sg:city":"Roselle",
    "sg:classifiers":[
        {
            "category":"Professional",
            "subcategory":"Management & Consulting",
            "type":"Services"
        }
    ],
    "sg:phone":"+1 908 245 2950",
    "sg:postcode":"07203",
    "sg:province":"NJ",
    "sg:tags":[
        "business"
    ],
    "wof:name":"Daniel Schlabieg",
    "wof:placetype":"venue"
},
  "geometry": {"coordinates":[-74.266885,40.653373],"type":"Point"}
}