{
  "type": "Feature",
  "properties": {
    "iso:country":"US",
    "sg:address":"2232 E Broad St",
    "sg:city":"Millville",
    "sg:classifiers":[
        {
            "category":"Retail",
            "subcategory":"Auto Repair",
            "type":"Services"
        }
    ],
    "sg:phone":"+1   ",
    "sg:postcode":"08332",
    "sg:province":"NJ",
    "sg:tags":[
        "station",
        "gasoline",
        "general"
    ],
    "wof:name":"C & C Services",
    "wof:placetype":"venue"
},
  "geometry": {"coordinates":[-75.006827,39.407912],"type":"Point"}
}