{
  "type": "Feature",
  "properties": {
    "addr:full":"4005 Bergenline Ave Union City NJ 07087",
    "addr:housenumber":"4005",
    "addr:postcode":"07087",
    "addr:street":"Bergenline Ave",
    "iso:country":"US",
    "sg:address":"4005 Bergenline Ave",
    "sg:city":"Union City",
    "sg:classifiers":[
        {
            "category":"Travel",
            "subcategory":"Travel Agent",
            "type":"Entertainment"
        }
    ],
    "sg:phone":"+1 201 866 1212",
    "sg:postcode":"07087",
    "sg:province":"NJ",
    "sg:tags":[
        "ticket",
        "agency",
        "airline"
    ],
    "wof:name":"Perez Travel Svc",
    "wof:placetype":"venue"
},
  "geometry": {"coordinates":[-74.02555700000001,40.776941],"type":"Point"}
}