{
  "type": "Feature",
  "properties": {
    "addr:full":"28 Inlet Ter Belmar NJ 07719",
    "addr:housenumber":"28",
    "addr:postcode":"07719",
    "addr:street":"Inlet Ter",
    "iso:country":"US",
    "sg:address":"28 Inlet Ter",
    "sg:city":"Belmar",
    "sg:classifiers":[
        {
            "category":"Banks & Credit Unions",
            "subcategory":"Financial Services",
            "type":"Services"
        }
    ],
    "sg:phone":"+1   ",
    "sg:postcode":"07719",
    "sg:province":"NJ",
    "sg:tags":[
        "company",
        "holding"
    ],
    "wof:name":"Algos Pharmaceutical Corp",
    "wof:placetype":"venue"
},
  "geometry": {"coordinates":[-74.01484000000001,40.185767],"type":"Point"}
}