{
  "type": "Feature",
  "properties": {
    "iso:country":"US",
    "sg:address":"1 Hanford St",
    "sg:city":"Newark",
    "sg:classifiers":[
        {
            "category":"Building & Trades",
            "subcategory":"Construction",
            "type":"Services"
        }
    ],
    "sg:phone":"+1 973 824 2902",
    "sg:postcode":"07114",
    "sg:province":"NJ",
    "sg:tags":[
        "sewer",
        "contractor"
    ],
    "wof:name":"Judges Sewerage Drain Clg Svc",
    "wof:placetype":"venue"
},
  "geometry": {"coordinates":[-74.20388699999999,40.692854],"type":"Point"}
}