{
  "type": "Feature",
  "properties": {
    "addr:full":"120 Charlotte Pl Englewood Cliffs NJ 07632",
    "addr:housenumber":"120",
    "addr:postcode":"07632",
    "addr:street":"Charlotte Pl",
    "iso:country":"US",
    "sg:address":"120 Charlotte Pl",
    "sg:city":"Englewood Cliffs",
    "sg:classifiers":[
        {
            "category":"Professional",
            "type":"Services"
        }
    ],
    "sg:phone":"+1 212 488 7076",
    "sg:postcode":"07632",
    "sg:province":"NJ",
    "sg:tags":[
        "establishment"
    ],
    "wof:name":"Antaino & Chuang",
    "wof:placetype":"venue"
},
  "geometry": {"coordinates":[-73.954105,40.873156],"type":"Point"}
}