{
  "type": "Feature",
  "properties": {
    "addr:full":"556 Ocean Rd Spring Lake NJ 07762",
    "addr:housenumber":"556",
    "addr:postcode":"07762",
    "addr:street":"Ocean Rd",
    "iso:country":"US",
    "sg:address":"556 Ocean Rd",
    "sg:city":"Spring Lake",
    "sg:classifiers":[
        {
            "category":"Arts & Performance",
            "subcategory":"Theater",
            "type":"Entertainment"
        }
    ],
    "sg:phone":"+1 732 449 2854",
    "sg:postcode":"07762",
    "sg:province":"NJ",
    "sg:tags":[
        "karaoke"
    ],
    "wof:name":"KC Entertainment",
    "wof:placetype":"venue"
},
  "geometry": {"coordinates":[-74.03924600000001,40.143689],"type":"Point"}
}