{
  "type": "Feature",
  "properties": {
    "addr:full":"90 Moonachie Ave Moonachie NJ 07074",
    "addr:housenumber":"90",
    "addr:postcode":"07074",
    "addr:street":"Moonachie Ave",
    "iso:country":"US",
    "sg:address":"90 Moonachie Ave",
    "sg:city":"Moonachie",
    "sg:classifiers":[
        {
            "category":"Building & Trades",
            "subcategory":"Locksmith",
            "type":"Services"
        }
    ],
    "sg:phone":"+1 888 524 0307",
    "sg:postcode":"07074",
    "sg:province":"NJ",
    "sg:tags":[
        "key"
    ],
    "wof:name":"24 Emergency Locksmith",
    "wof:placetype":"venue"
},
  "geometry": {"coordinates":[-74.07276899999999,40.841088],"type":"Point"}
}