{
  "type": "Feature",
  "properties": {
    "iso:country":"US",
    "sg:address":"4010 Ivins Ave",
    "sg:city":"Egg Harbor Township",
    "sg:classifiers":[
        {
            "category":"Organizations",
            "subcategory":"Religious Organization",
            "type":"Services"
        }
    ],
    "sg:phone":"+1   ",
    "sg:postcode":"08234",
    "sg:province":"NJ",
    "wof:name":"Crown of Thorns Ministrie",
    "wof:placetype":"venue"
},
  "geometry": {"coordinates":[-74.613816,39.410651],"type":"Point"}
}