{
  "type": "Feature",
  "properties": {
    "iso:country":"US",
    "sg:address":"300 Central Ave",
    "sg:city":"Plainfield",
    "sg:classifiers":[
        {
            "category":"Real Estate",
            "subcategory":"Real Estate Operator",
            "type":"Services"
        }
    ],
    "sg:phone":"+1 908 753 6499",
    "sg:postcode":"07060",
    "sg:province":"NJ",
    "sg:tags":[
        "apartment"
    ],
    "wof:name":"Allen-Young Apartments",
    "wof:placetype":"venue"
},
  "geometry": {"coordinates":[-74.423255,40.614523],"type":"Point"}
}