{
  "type": "Feature",
  "properties": {
    "addr:full":"59 Chester St Clifton NJ 07011",
    "addr:housenumber":"59",
    "addr:postcode":"07011",
    "addr:street":"Chester St",
    "iso:country":"US",
    "sg:address":"59 Chester St",
    "sg:city":"Clifton",
    "sg:classifiers":[
        {
            "category":"Retail",
            "subcategory":"Repair Shop",
            "type":"Services"
        }
    ],
    "sg:phone":"+1 973 340 4003",
    "sg:postcode":"07011",
    "sg:province":"NJ",
    "sg:tags":[
        "air",
        "system",
        "conditioning"
    ],
    "wof:name":"Fresh Aircool Inc",
    "wof:placetype":"venue"
},
  "geometry": {"coordinates":[-74.14786100000001,40.884665],"type":"Point"}
}