{
  "type": "Feature",
  "properties": {
    "addr:full":"342 4th St Saddle Brook NJ 07663",
    "addr:housenumber":"342",
    "addr:postcode":"07663",
    "addr:street":"4Th St",
    "iso:country":"US",
    "sg:address":"342 4th St",
    "sg:city":"Saddle Brook",
    "sg:classifiers":[
        {
            "category":"Professional",
            "subcategory":"Management & Consulting",
            "type":"Services"
        }
    ],
    "sg:phone":"+1 973 253 1997",
    "sg:postcode":"07663",
    "sg:province":"NJ",
    "wof:name":"S & H Marketing",
    "wof:placetype":"venue"
},
  "geometry": {"coordinates":[-74.09775399999999,40.88645],"type":"Point"}
}