{
  "type": "Feature",
  "properties": {
    "addr:full":"122 Oweno Rd Mahwah NJ 07430",
    "addr:housenumber":"122",
    "addr:postcode":"07430",
    "addr:street":"Oweno Rd",
    "iso:country":"US",
    "sg:address":"122 Oweno Rd",
    "sg:city":"Mahwah",
    "sg:classifiers":[
        {
            "category":"Professional",
            "subcategory":"Computer Services",
            "type":"Services"
        }
    ],
    "sg:phone":"+1   ",
    "sg:postcode":"07430",
    "sg:province":"NJ",
    "sg:tags":[
        "programing",
        "custom"
    ],
    "wof:name":"Universal Computer Technology",
    "wof:placetype":"venue"
},
  "geometry": {"coordinates":[-74.13908000000001,41.085623],"type":"Point"}
}