{
  "type": "Feature",
  "properties": {
    "addr:full":"1056 Randolph Ave Rahway NJ 07065",
    "addr:housenumber":"1056",
    "addr:postcode":"07065",
    "addr:street":"Randolph Ave",
    "iso:country":"US",
    "sg:address":"1056 Randolph Ave",
    "sg:city":"Rahway",
    "sg:classifiers":[
        {
            "category":"Autos & Motor Vehicles",
            "subcategory":"Auto Supplies",
            "type":"Retail Goods"
        }
    ],
    "sg:phone":"+1   ",
    "sg:postcode":"07065",
    "sg:province":"NJ",
    "wof:name":"B & B Automotive Machine Svc",
    "wof:placetype":"venue"
},
  "geometry": {"coordinates":[-74.263797,40.596849],"type":"Point"}
}