{
  "type": "Feature",
  "properties": {
    "iso:country":"US",
    "sg:address":"1701 Nottingham Way",
    "sg:city":"Trenton",
    "sg:classifiers":[
        {
            "category":"Professional",
            "subcategory":"Business Services",
            "type":"Services"
        }
    ],
    "sg:phone":"+1 609 586 1188",
    "sg:postcode":"08619",
    "sg:province":"NJ",
    "sg:tags":[
        "notary"
    ],
    "wof:name":"Insurance Center Agency",
    "wof:placetype":"venue"
},
  "geometry": {"coordinates":[-74.713831,40.2327],"type":"Point"}
}