{
  "type": "Feature",
  "properties": {
    "iso:country":"US",
    "sg:address":"183 Anderson Ave",
    "sg:city":"Fairview",
    "sg:classifiers":[
        {
            "category":"Restaurant",
            "type":"Food & Drink"
        }
    ],
    "sg:phone":"+1   ",
    "sg:postcode":"07022",
    "sg:province":"NJ",
    "sg:tags":[
        "eating"
    ],
    "wof:name":"Pasta & Pizza Restaurant Inc",
    "wof:placetype":"venue"
},
  "geometry": {"coordinates":[-73.99609100000001,40.815222],"type":"Point"}
}