{
  "type": "Feature",
  "properties": {
    "iso:country":"US",
    "sg:address":"135 Bond St",
    "sg:city":"Bridgewater",
    "sg:classifiers":[
        {
            "category":"Restaurant",
            "type":"Food & Drink"
        }
    ],
    "sg:phone":"+1 908 725 7323",
    "sg:postcode":"08807",
    "sg:province":"NJ",
    "wof:name":"Davis Diner",
    "wof:placetype":"venue"
},
  "geometry": {"coordinates":[-74.628505,40.582701],"type":"Point"}
}