{
  "type": "Feature",
  "properties": {
    "addr:full":"396 White Horse Ave Trenton NJ 08610",
    "addr:housenumber":"396",
    "addr:postcode":"08610",
    "addr:street":"White Horse Ave",
    "iso:country":"US",
    "sg:address":"396 White Horse Ave",
    "sg:city":"Trenton",
    "sg:classifiers":[
        {
            "category":"Health Services",
            "subcategory":"Doctor",
            "type":"Services"
        }
    ],
    "sg:phone":"+1 609 585 4200",
    "sg:postcode":"08610",
    "sg:province":"NJ",
    "sg:tags":[
        "physician",
        "surgeon"
    ],
    "wof:name":"Susan Fuchs MD",
    "wof:placetype":"venue"
},
  "geometry": {"coordinates":[-74.70100600000001,40.195422],"type":"Point"}
}