{
  "type": "Feature",
  "properties": {
    "iso:country":"US",
    "sg:address":"1400 Berlin Rd",
    "sg:city":"Cherry Hill",
    "sg:classifiers":[
        {
            "category":"Autos & Motor Vehicles",
            "subcategory":"Auto Supplies",
            "type":"Retail Goods"
        }
    ],
    "sg:phone":"+1 856 354 9510",
    "sg:postcode":"08003",
    "sg:province":"NJ",
    "sg:tags":[
        "tire"
    ],
    "wof:name":"Trio Tire & Auto Svc Ctr",
    "wof:placetype":"venue"
},
  "geometry": {"coordinates":[-75.00693099999999,39.878319],"type":"Point"}
}