{
  "type": "Feature",
  "properties": {
    "iso:country":"US",
    "sg:address":"431 8th St",
    "sg:city":"Gloucester City",
    "sg:classifiers":[
        {
            "category":"Autos & Motor Vehicles",
            "subcategory":"Auto Supplies",
            "type":"Retail Goods"
        }
    ],
    "sg:phone":"+1 856 456 1115",
    "sg:postcode":"08030",
    "sg:province":"NJ",
    "sg:tags":[
        "automobile",
        "parts"
    ],
    "wof:name":"Patriot Auto Parts",
    "wof:placetype":"venue"
},
  "geometry": {"coordinates":[-75.12468699999999,39.88925],"type":"Point"}
}