{
  "type": "Feature",
  "properties": {
    "iso:country":"US",
    "sg:address":"2421 Long Beach Blvd",
    "sg:city":"Beach Haven",
    "sg:classifiers":[
        {
            "category":"Health Services",
            "subcategory":"Doctor",
            "type":"Services"
        }
    ],
    "sg:phone":"+1   ",
    "sg:postcode":"08008",
    "sg:province":"NJ",
    "wof:name":"J R Federici DMD",
    "wof:placetype":"venue"
},
  "geometry": {"coordinates":[-74.183673,39.639989],"type":"Point"}
}