{
  "type": "Feature",
  "properties": {
    "iso:country":"US",
    "sg:address":"177 Main St",
    "sg:city":"Fort Lee",
    "sg:classifiers":[
        {
            "category":"Banks & Credit Unions",
            "subcategory":"Investment Brokerage",
            "type":"Services"
        }
    ],
    "sg:phone":"+1   ",
    "sg:postcode":"07024",
    "sg:province":"NJ",
    "sg:tags":[
        "advisory"
    ],
    "wof:name":"KFM Inc",
    "wof:placetype":"venue"
},
  "geometry": {"coordinates":[-73.969476,40.851156],"type":"Point"}
}