{
  "type": "Feature",
  "properties": {
    "iso:country":"US",
    "sg:address":"8 Sylvan St",
    "sg:city":"Lincoln Park",
    "sg:classifiers":[
        {
            "category":"Wholesale",
            "subcategory":"Hardware",
            "type":"Manufacturing & Wholesale Goods"
        }
    ],
    "sg:phone":"+1 973 633 5213",
    "sg:postcode":"07035",
    "sg:province":"NJ",
    "sg:tags":[
        "plumbing"
    ],
    "wof:name":"Ascon",
    "wof:placetype":"venue"
},
  "geometry": {"coordinates":[-74.290342,40.922146],"type":"Point"}
}