{
  "type": "Feature",
  "properties": {
    "addr:full":"10 Spear St Metuchen NJ 08840",
    "addr:housenumber":"10",
    "addr:postcode":"08840",
    "addr:street":"Spear St",
    "iso:country":"US",
    "sg:address":"10 Spear St",
    "sg:city":"Metuchen",
    "sg:classifiers":[
        {
            "category":"Social Services",
            "subcategory":"Job Training",
            "type":"Services"
        }
    ],
    "sg:phone":"+1   ",
    "sg:postcode":"08840",
    "sg:province":"NJ",
    "wof:name":"Training Solutions",
    "wof:placetype":"venue"
},
  "geometry": {"coordinates":[-74.348297,40.541371],"type":"Point"}
}