{
  "type": "Feature",
  "properties": {
    "iso:country":"US",
    "sg:address":"24 Patriot Xing",
    "sg:city":"Rockaway",
    "sg:classifiers":[
        {
            "category":"Manufacturing",
            "subcategory":"Tools & Machinery",
            "type":"Manufacturing & Wholesale Goods"
        }
    ],
    "sg:phone":"+1 973 579 6509",
    "sg:postcode":"07866",
    "sg:province":"NJ",
    "sg:tags":[
        "machine",
        "shop"
    ],
    "wof:name":"Precision Parts Unlimited",
    "wof:placetype":"venue"
},
  "geometry": {"coordinates":[-74.552452,40.901768],"type":"Point"}
}