{
  "type": "Feature",
  "properties": {
    "addr:full":"34 Boundary Rd Marlboro NJ 07746",
    "addr:housenumber":"34",
    "addr:postcode":"07746",
    "addr:street":"Boundary Rd",
    "iso:country":"US",
    "sg:address":"34 Boundary Rd",
    "sg:city":"Marlboro",
    "sg:classifiers":[
        {
            "category":"Professional",
            "subcategory":"Management & Consulting",
            "type":"Services"
        }
    ],
    "sg:phone":"+1   ",
    "sg:postcode":"07746",
    "sg:province":"NJ",
    "sg:tags":[
        "business"
    ],
    "wof:name":"Gunning Clear Writing Inst",
    "wof:placetype":"venue"
},
  "geometry": {"coordinates":[-74.22255699999999,40.335205],"type":"Point"}
}