{
  "type": "Feature",
  "properties": {
    "addr:full":"74 Orion Rd Piscataway NJ 08854",
    "addr:housenumber":"74",
    "addr:postcode":"08854",
    "addr:street":"Orion Rd",
    "iso:country":"US",
    "sg:address":"74 Orion Rd",
    "sg:city":"Piscataway",
    "sg:classifiers":[
        {
            "category":"Professional",
            "type":"Services"
        }
    ],
    "sg:phone":"+1   ",
    "sg:postcode":"08854",
    "sg:province":"NJ",
    "wof:name":"Sylvia Bennett",
    "wof:placetype":"venue"
},
  "geometry": {"coordinates":[-74.417103,40.534617],"type":"Point"}
}