{
  "type": "Feature",
  "properties": {
    "iso:country":"US",
    "sg:address":"86 E Springtown Rd",
    "sg:city":"Long Valley",
    "sg:classifiers":[
        {
            "category":"Building & Trades",
            "subcategory":"Landscaping Services",
            "type":"Services"
        }
    ],
    "sg:phone":"+1 908 876 5484",
    "sg:postcode":"07853",
    "sg:province":"NJ",
    "wof:name":"Long Valley Lawn & Landscape",
    "wof:placetype":"venue"
},
  "geometry": {"coordinates":[-74.786345,40.804234],"type":"Point"}
}