{
  "type": "Feature",
  "properties": {
    "addr:full":"1000 State Rte 35 Middletown NJ 07748",
    "addr:housenumber":"1000",
    "addr:postcode":"07748",
    "addr:street":"State Rte 35",
    "iso:country":"US",
    "sg:address":"1000 State Rte 35",
    "sg:city":"Middletown",
    "sg:classifiers":[
        {
            "category":"Health Services",
            "subcategory":"Health Practitioner",
            "type":"Services"
        },
        {
            "category":"Professional",
            "subcategory":"Employment Agencies",
            "type":"Services"
        }
    ],
    "sg:phone":"+1 732 957 9600",
    "sg:postcode":"07748",
    "sg:province":"NJ",
    "sg:tags":[
        "nurse",
        "registry",
        "help",
        "supply"
    ],
    "wof:name":"Ultima Staffers & Nursing Care",
    "wof:placetype":"venue"
},
  "geometry": {"coordinates":[-74.107969,40.396618],"type":"Point"}
}