{
  "type": "Feature",
  "properties": {
    "addr:full":"681 Newman Springs Rd Lincroft NJ 07738",
    "addr:housenumber":"681",
    "addr:postcode":"07738",
    "addr:street":"Newman Springs Rd",
    "iso:country":"US",
    "sg:address":"681 Newman Springs Rd",
    "sg:city":"Lincroft",
    "sg:classifiers":[
        {
            "category":"Shopping",
            "subcategory":"Florist",
            "type":"Retail Goods"
        }
    ],
    "sg:phone":"+1 732 747 4664",
    "sg:postcode":"07738",
    "sg:province":"NJ",
    "sg:tags":[
        "supply"
    ],
    "sg:website":"www.branching.com",
    "wof:name":"Branching Out",
    "wof:placetype":"venue"
},
  "geometry": {"coordinates":[-74.117981,40.331431],"type":"Point"}
}