{
  "type": "Feature",
  "properties": {
    "addr:full":"1062 Old White Horse Pike Waterford Works NJ 08089",
    "addr:housenumber":"1062",
    "addr:postcode":"08089",
    "addr:street":"Old White Horse Pike",
    "iso:country":"US",
    "sg:address":"1062 Old White Horse Pike",
    "sg:city":"Waterford Works",
    "sg:classifiers":[
        {
            "category":"Building & Trades",
            "subcategory":"Construction",
            "type":"Services"
        }
    ],
    "sg:phone":"+1 856 768 0285",
    "sg:postcode":"08089",
    "sg:province":"NJ",
    "sg:tags":[
        "house"
    ],
    "wof:name":"M&M Home Improvement",
    "wof:placetype":"venue"
},
  "geometry": {"coordinates":[-74.854034,39.729418],"type":"Point"}
}