{
  "type": "Feature",
  "properties": {
    "iso:country":"US",
    "sg:address":"820 Main Ave",
    "sg:city":"Passaic",
    "sg:classifiers":[
        {
            "category":"Home & Garden",
            "subcategory":"Furniture",
            "type":"Retail Goods"
        }
    ],
    "sg:phone":"+1 973 574 0050",
    "sg:postcode":"07055",
    "sg:province":"NJ",
    "sg:tags":[
        "store"
    ],
    "wof:name":"U S Furniture & Mattress",
    "wof:placetype":"venue"
},
  "geometry": {"coordinates":[-74.130353,40.865631],"type":"Point"}
}