{
  "type": "Feature",
  "properties": {
    "addr:full":"3220 State Rte 42 Sicklerville NJ 08081",
    "addr:housenumber":"3220",
    "addr:postcode":"08081",
    "addr:street":"State Rte 42",
    "iso:country":"US",
    "sg:address":"3220 State Rte 42",
    "sg:city":"Sicklerville",
    "sg:classifiers":[
        {
            "category":"Retail",
            "subcategory":"Repair Shop",
            "type":"Services"
        }
    ],
    "sg:phone":"+1 856 629 9175",
    "sg:postcode":"08081",
    "sg:province":"NJ",
    "sg:tags":[
        "related"
    ],
    "wof:name":"Steve's Auto Repair",
    "wof:placetype":"venue"
},
  "geometry": {"coordinates":[-75.030304,39.72712],"type":"Point"}
}