{
  "type": "Feature",
  "properties": {
    "iso:country":"US",
    "sg:address":"2 Elizabeth Ave",
    "sg:city":"Livingston",
    "sg:classifiers":[
        {
            "category":"Building & Trades",
            "subcategory":"Landscaping Services",
            "type":"Services"
        }
    ],
    "sg:phone":"+1 973 992 2358",
    "sg:postcode":"07039",
    "sg:province":"NJ",
    "wof:name":"T and D Tree Company",
    "wof:placetype":"venue"
},
  "geometry": {"coordinates":[-74.32045599999999,40.796775],"type":"Point"}
}