{
  "type": "Feature",
  "properties": {
    "addr:full":"89 N Main St Medford NJ 08055",
    "addr:housenumber":"89",
    "addr:postcode":"08055",
    "addr:street":"N Main St",
    "iso:country":"US",
    "sg:address":"89 N Main St",
    "sg:city":"Medford",
    "sg:classifiers":[
        {
            "category":"Banks & Credit Unions",
            "subcategory":"Bank",
            "type":"Services"
        }
    ],
    "sg:phone":"+1 609 654 8833",
    "sg:postcode":"08055",
    "sg:province":"NJ",
    "sg:tags":[
        "loan",
        "real estate"
    ],
    "wof:name":"Novastar Home Mortgage",
    "wof:placetype":"venue"
},
  "geometry": {"coordinates":[-74.824123,39.90363],"type":"Point"}
}