{
  "type": "Feature",
  "properties": {
    "addr:full":"701 Haddonfield Berlin Rd Voorhees NJ 08043",
    "addr:housenumber":"701",
    "addr:postcode":"08043",
    "addr:street":"Haddonfield Berlin Rd",
    "iso:country":"US",
    "sg:address":"701 Haddonfield Berlin Rd",
    "sg:city":"Voorhees",
    "sg:classifiers":[
        {
            "category":"Home & Garden",
            "subcategory":"Furniture",
            "type":"Retail Goods"
        }
    ],
    "sg:phone":"+1   ",
    "sg:postcode":"08043",
    "sg:province":"NJ",
    "wof:name":"Mattress Giant Corporation",
    "wof:placetype":"venue"
},
  "geometry": {"coordinates":[-74.982314,39.853728],"type":"Point"}
}