{
  "type": "Feature",
  "properties": {
    "addr:full":"45 Main St Madison NJ 07940",
    "addr:housenumber":"45",
    "addr:postcode":"07940",
    "addr:street":"Main St",
    "iso:country":"US",
    "sg:address":"45 Main St",
    "sg:city":"Madison",
    "sg:classifiers":[
        {
            "category":"Food & Beverages",
            "subcategory":"Bakery",
            "type":"Retail Goods"
        }
    ],
    "sg:phone":"+1 973 301 9888",
    "sg:postcode":"07940",
    "sg:province":"NJ",
    "sg:tags":[
        "bagel"
    ],
    "wof:name":"Bagel Chateau of Madison",
    "wof:placetype":"venue"
},
  "geometry": {"coordinates":[-74.41570299999999,40.759201],"type":"Point"}
}