{
  "type": "Feature",
  "properties": {
    "addr:full":"18 Main St Eatontown NJ 07724",
    "addr:housenumber":"18",
    "addr:postcode":"07724",
    "addr:street":"Main St",
    "iso:country":"US",
    "sg:address":"18 Main St",
    "sg:city":"Eatontown",
    "sg:classifiers":[
        {
            "category":"Personal",
            "subcategory":"Beauty Salon",
            "type":"Services"
        }
    ],
    "sg:phone":"+1 732 542 8183",
    "sg:postcode":"07724",
    "sg:province":"NJ",
    "sg:tags":[
        "shop"
    ],
    "wof:name":"Eatontown Hair Plus",
    "wof:placetype":"venue"
},
  "geometry": {"coordinates":[-74.059321,40.303801],"type":"Point"}
}