{
  "type": "Feature",
  "properties": {
    "iso:country":"US",
    "sg:address":"116 Millburn Ave",
    "sg:city":"Millburn",
    "sg:classifiers":[
        {
            "category":"Health Services",
            "subcategory":"Doctor",
            "type":"Services"
        }
    ],
    "sg:phone":"+1 973 376 3622",
    "sg:postcode":"07041",
    "sg:province":"NJ",
    "sg:tags":[
        "physician",
        "medical",
        "surgeon"
    ],
    "wof:name":"Yvonne LI MD",
    "wof:placetype":"venue"
},
  "geometry": {"coordinates":[-74.28915600000001,40.721883],"type":"Point"}
}