{
  "type": "Feature",
  "properties": {
    "addr:full":"374 Drakestown Rd Long Valley NJ 07853",
    "addr:housenumber":"374",
    "addr:postcode":"07853",
    "addr:street":"Drakestown Rd",
    "iso:country":"US",
    "sg:address":"374 Drakestown Rd",
    "sg:city":"Long Valley",
    "sg:classifiers":[
        {
            "category":"Professional",
            "subcategory":"Computer Services",
            "type":"Services"
        }
    ],
    "sg:phone":"+1   ",
    "sg:postcode":"07853",
    "sg:province":"NJ",
    "sg:tags":[
        "repair",
        "fiber",
        "maintenance",
        "cable",
        "optic"
    ],
    "wof:name":"Advanced Cmmnctions Engrg Svcs",
    "wof:placetype":"venue"
},
  "geometry": {"coordinates":[-74.756018,40.828981],"type":"Point"}
}