{
  "type": "Feature",
  "properties": {
    "addr:full":"230 9th St Jersey City NJ 07302",
    "addr:housenumber":"230",
    "addr:postcode":"07302",
    "addr:street":"9Th St",
    "iso:country":"US",
    "sg:address":"230 9th St",
    "sg:city":"Jersey City",
    "sg:classifiers":[
        {
            "category":"Manufacturing",
            "subcategory":"Textiles",
            "type":"Manufacturing & Wholesale Goods"
        }
    ],
    "sg:phone":"+1 201 653 0177",
    "sg:postcode":"07302",
    "sg:province":"NJ",
    "sg:tags":[
        "mill",
        "narrow",
        "fabric"
    ],
    "wof:name":"Lace Matters Inc",
    "wof:placetype":"venue"
},
  "geometry": {"coordinates":[-74.043831,40.728326],"type":"Point"}
}