{
  "type": "Feature",
  "properties": {
    "iso:country":"US",
    "sg:address":"82 Pompton Ave",
    "sg:city":"Cedar Grove",
    "sg:classifiers":[
        {
            "category":"Restaurant",
            "type":"Food & Drink"
        }
    ],
    "sg:phone":"+1 973 239 2900",
    "sg:postcode":"07009",
    "sg:province":"NJ",
    "sg:tags":[
        "diner"
    ],
    "wof:name":"Pilgrim Diner Restaurant",
    "wof:placetype":"venue"
},
  "geometry": {"coordinates":[-74.22689800000001,40.835201],"type":"Point"}
}