{
  "type": "Feature",
  "properties": {
    "addr:full":"99 Midvale Rd Mountain Lakes NJ 07046",
    "addr:housenumber":"99",
    "addr:postcode":"07046",
    "addr:street":"Midvale Rd",
    "iso:country":"US",
    "sg:address":"99 Midvale Rd",
    "sg:city":"Mountain Lakes",
    "sg:classifiers":[
        {
            "category":"Restaurant",
            "type":"Food & Drink"
        }
    ],
    "sg:phone":"+1 973 335 5330",
    "sg:postcode":"07046",
    "sg:province":"NJ",
    "wof:name":"Station Restaurant At Mountain",
    "wof:placetype":"venue"
},
  "geometry": {"coordinates":[-74.43429999999999,40.885565],"type":"Point"}
}