{
  "type": "Feature",
  "properties": {
    "iso:country":"US",
    "sg:address":"750 Willets Point Rd",
    "sg:city":"Marmora",
    "sg:classifiers":[
        {
            "category":"Building & Trades",
            "subcategory":"Cleaning & Sanitation",
            "type":"Services"
        }
    ],
    "sg:phone":"+1 609 827 5011",
    "sg:postcode":"08223",
    "sg:province":"NJ",
    "sg:tags":[
        "janitor"
    ],
    "wof:name":"Durham Cleaning Svc",
    "wof:placetype":"venue"
},
  "geometry": {"coordinates":[-74.674454,39.278626],"type":"Point"}
}