{
  "type": "Feature",
  "properties": {
    "iso:country":"US",
    "sg:address":"1300 Central Ave",
    "sg:city":"Wildwood",
    "sg:classifiers":[
        {
            "category":"Organizations",
            "subcategory":"Religious Organization",
            "type":"Services"
        }
    ],
    "sg:phone":"+1   ",
    "sg:postcode":"08260",
    "sg:province":"NJ",
    "wof:name":"Joe Mathis Rev",
    "wof:placetype":"venue"
},
  "geometry": {"coordinates":[-74.800146,39.000265],"type":"Point"}
}