{
  "type": "Feature",
  "properties": {
    "addr:full":"500 E Landis Ave Vineland NJ 08360",
    "addr:housenumber":"500",
    "addr:postcode":"08360",
    "addr:street":"E Landis Ave",
    "iso:country":"US",
    "sg:address":"500 E Landis Ave",
    "sg:city":"Vineland",
    "sg:classifiers":[
        {
            "category":"Government",
            "subcategory":"Office",
            "type":"Public Place"
        }
    ],
    "sg:phone":"+1 856 691 2214",
    "sg:postcode":"08360",
    "sg:province":"NJ",
    "sg:tags":[
        "armed",
        "force",
        "recruiting"
    ],
    "wof:name":"US Army Recruiting",
    "wof:placetype":"venue"
},
  "geometry": {"coordinates":[-75.023449,39.486061],"type":"Point"}
}