{
  "type": "Feature",
  "properties": {
    "addr:full":"2109 New Albany Rd Riverton NJ 08077",
    "addr:housenumber":"2109",
    "addr:postcode":"08077",
    "addr:street":"New Albany Rd",
    "iso:country":"US",
    "sg:address":"2109 New Albany Rd",
    "sg:city":"Riverton",
    "sg:classifiers":[
        {
            "category":"Building & Trades",
            "subcategory":"Landscaping Services",
            "type":"Services"
        }
    ],
    "sg:phone":"+1 856 786 1708",
    "sg:postcode":"08077",
    "sg:province":"NJ",
    "sg:tags":[
        "landscape"
    ],
    "wof:name":"Full Circle Landscaping",
    "wof:placetype":"venue"
},
  "geometry": {"coordinates":[-74.973168,40.007171],"type":"Point"}
}