{
  "type": "Feature",
  "properties": {
    "addr:full":"2 Loyalist Ct Marlton NJ 08053",
    "addr:housenumber":"2",
    "addr:postcode":"08053",
    "addr:street":"Loyalist Ct",
    "iso:country":"US",
    "sg:address":"2 Loyalist Ct",
    "sg:city":"Marlton",
    "sg:classifiers":[
        {
            "category":"Professional",
            "subcategory":"Business Services",
            "type":"Services"
        }
    ],
    "sg:phone":"+1   ",
    "sg:postcode":"08053",
    "sg:province":"NJ",
    "wof:name":"Integral Capital Mgt Corp",
    "wof:placetype":"venue"
},
  "geometry": {"coordinates":[-74.895236,39.875204],"type":"Point"}
}