{
  "type": "Feature",
  "properties": {
    "iso:country":"US",
    "sg:address":"537 Hamilton Ave",
    "sg:city":"Trenton",
    "sg:classifiers":[
        {
            "category":"Shopping",
            "subcategory":"Music",
            "type":"Retail Goods"
        }
    ],
    "sg:phone":"+1 609 695 0035",
    "sg:postcode":"08609",
    "sg:province":"NJ",
    "sg:tags":[
        "compact",
        "used",
        "tapes",
        "records",
        "vintage",
        "record",
        "disc",
        "tape",
        "cd's"
    ],
    "wof:name":"Disco Hit",
    "wof:placetype":"venue"
},
  "geometry": {"coordinates":[-74.743742,40.216836],"type":"Point"}
}