{
  "type": "Feature",
  "properties": {
    "addr:full":"25 Country Oaks Rd Lebanon NJ 08833",
    "addr:housenumber":"25",
    "addr:postcode":"08833",
    "addr:street":"Country Oaks Rd",
    "iso:country":"US",
    "sg:address":"25 Country Oaks Rd",
    "sg:city":"Lebanon",
    "sg:classifiers":[
        {
            "category":"Banks & Credit Unions",
            "subcategory":"Investment Brokerage",
            "type":"Services"
        }
    ],
    "sg:phone":"+1   ",
    "sg:postcode":"08833",
    "sg:province":"NJ",
    "sg:tags":[
        "advisory"
    ],
    "wof:name":"William F Bergs Financial & In",
    "wof:placetype":"venue"
},
  "geometry": {"coordinates":[-74.85382,40.588001],"type":"Point"}
}