{
  "type": "Feature",
  "properties": {
    "iso:country":"US",
    "sg:address":"52 Maple Ave",
    "sg:city":"Morristown",
    "sg:classifiers":[
        {
            "category":"Health Services",
            "subcategory":"Doctor",
            "type":"Services"
        }
    ],
    "sg:phone":"+1 973 538 2055",
    "sg:postcode":"07960",
    "sg:province":"NJ",
    "sg:tags":[
        "medical"
    ],
    "wof:name":"Philip Werner MD",
    "wof:placetype":"venue"
},
  "geometry": {"coordinates":[-74.479439,40.793025],"type":"Point"}
}