{
  "type": "Feature",
  "properties": {
    "addr:full":"311 W Cuthbert Blvd Collingswood NJ 08108",
    "addr:housenumber":"311",
    "addr:postcode":"08108",
    "addr:street":"W Cuthbert Blvd",
    "iso:country":"US",
    "sg:address":"311 W Cuthbert Blvd",
    "sg:city":"Collingswood",
    "sg:classifiers":[
        {
            "category":"Professional",
            "subcategory":"Accounting & Tax Preparation",
            "type":"Services"
        }
    ],
    "sg:phone":"+1   ",
    "sg:postcode":"08108",
    "sg:province":"NJ",
    "sg:tags":[
        "return"
    ],
    "wof:name":"Tax Solutions Inc",
    "wof:placetype":"venue"
},
  "geometry": {"coordinates":[-75.059561,39.908409],"type":"Point"}
}