{
  "type": "Feature",
  "properties": {
    "addr:full":"7 E Wilson St Middlesex NJ 08846",
    "addr:housenumber":"7",
    "addr:postcode":"08846",
    "addr:street":"E Wilson St",
    "iso:country":"US",
    "sg:address":"7 E Wilson St",
    "sg:city":"Middlesex",
    "sg:classifiers":[
        {
            "category":"Building & Trades",
            "subcategory":"Construction",
            "type":"Services"
        }
    ],
    "sg:phone":"+1 732 469 3360",
    "sg:postcode":"08846",
    "sg:province":"NJ",
    "sg:tags":[
        "house"
    ],
    "wof:name":"J&M Carpentry",
    "wof:placetype":"venue"
},
  "geometry": {"coordinates":[-74.501846,40.582108],"type":"Point"}
}