{
  "type": "Feature",
  "properties": {
    "iso:country":"US",
    "sg:address":"45 E Madison Ave",
    "sg:city":"Clifton",
    "sg:classifiers":[
        {
            "category":"Personal",
            "type":"Services"
        }
    ],
    "sg:phone":"+1 973 894 3641",
    "sg:postcode":"07011",
    "sg:province":"NJ",
    "sg:tags":[
        "mover"
    ],
    "wof:name":"Global Vanline Movin",
    "wof:placetype":"venue"
},
  "geometry": {"coordinates":[-74.13494900000001,40.87504],"type":"Point"}
}