{
  "type": "Feature",
  "properties": {
    "addr:full":"982 Summit Ave Jersey City NJ 07307",
    "addr:housenumber":"982",
    "addr:postcode":"07307",
    "addr:street":"Summit Ave",
    "iso:country":"US",
    "sg:address":"982 Summit Ave",
    "sg:city":"Jersey City",
    "sg:classifiers":[
        {
            "category":"Social Services",
            "type":"Services"
        }
    ],
    "sg:phone":"+1   ",
    "sg:postcode":"07307",
    "sg:province":"NJ",
    "wof:name":"Project Hugs",
    "wof:placetype":"venue"
},
  "geometry": {"coordinates":[-74.05084100000001,40.748093],"type":"Point"}
}