{
  "type": "Feature",
  "properties": {
    "addr:full":"1465 State Rte 31 Clinton NJ 08809",
    "addr:housenumber":"1465",
    "addr:postcode":"08809",
    "addr:street":"State Rte 31",
    "iso:country":"US",
    "sg:address":"1465 State Rte 31",
    "sg:city":"Clinton",
    "sg:classifiers":[
        {
            "category":"Health Services",
            "subcategory":"Doctor",
            "type":"Services"
        }
    ],
    "sg:phone":"+1 908 730 7778",
    "sg:postcode":"08809",
    "sg:province":"NJ",
    "sg:tags":[
        "physician",
        "surgeon"
    ],
    "wof:name":"Allergy Asthma & Sinus Ctr",
    "wof:placetype":"venue"
},
  "geometry": {"coordinates":[-74.896547,40.641079],"type":"Point"}
}