{
  "type": "Feature",
  "properties": {
    "addr:full":"1028 Laura St Elizabeth NJ 07201",
    "addr:housenumber":"1028",
    "addr:postcode":"07201",
    "addr:street":"Laura St",
    "iso:country":"US",
    "sg:address":"1028 Laura St",
    "sg:city":"Elizabeth",
    "sg:classifiers":[
        {
            "category":"Personal",
            "type":"Services"
        }
    ],
    "sg:phone":"+1   ",
    "sg:postcode":"07201",
    "sg:province":"NJ",
    "wof:name":"ACS Creations",
    "wof:placetype":"venue"
},
  "geometry": {"coordinates":[-74.202708,40.671346],"type":"Point"}
}