{
  "type": "Feature",
  "properties": {
    "addr:full":"4 Phillips Ln Roseland NJ 07068",
    "addr:housenumber":"4",
    "addr:postcode":"07068",
    "addr:street":"Phillips Ln",
    "iso:country":"US",
    "sg:address":"4 Phillips Ln",
    "sg:city":"Roseland",
    "sg:classifiers":[
        {
            "category":"Travel",
            "subcategory":"Travel Agent",
            "type":"Entertainment"
        }
    ],
    "sg:phone":"+1 973 228 4706",
    "sg:postcode":"07068",
    "sg:province":"NJ",
    "sg:tags":[
        "agency"
    ],
    "wof:name":"Fredericks Travel Consultants",
    "wof:placetype":"venue"
},
  "geometry": {"coordinates":[-74.317764,40.827555],"type":"Point"}
}