{
  "type": "Feature",
  "properties": {
    "addr:full":"212 Briar Heath Ln Clark NJ 07066",
    "addr:housenumber":"212",
    "addr:postcode":"07066",
    "addr:street":"Briar Heath Ln",
    "iso:country":"US",
    "sg:address":"212 Briar Heath Ln",
    "sg:city":"Clark",
    "sg:classifiers":[
        {
            "category":"Building & Trades",
            "subcategory":"Plumbing",
            "type":"Services"
        }
    ],
    "sg:phone":"+1 732 574 3565",
    "sg:postcode":"07066",
    "sg:province":"NJ",
    "sg:tags":[
        "contractor"
    ],
    "wof:name":"Framan Mechanical Inc",
    "wof:placetype":"venue"
},
  "geometry": {"coordinates":[-74.332295,40.607298],"type":"Point"}
}