{
  "type": "Feature",
  "properties": {
    "iso:country":"US",
    "sg:address":"81 E 39th St",
    "sg:city":"Paterson",
    "sg:classifiers":[
        {
            "category":"Social Services",
            "subcategory":"Adult Care",
            "type":"Services"
        }
    ],
    "sg:phone":"+1   ",
    "sg:postcode":"07514",
    "sg:province":"NJ",
    "sg:tags":[
        "orphanage"
    ],
    "wof:name":"Kilbarchan Home For Children",
    "wof:placetype":"venue"
},
  "geometry": {"coordinates":[-74.135796,40.919775],"type":"Point"}
}