{
  "type": "Feature",
  "properties": {
    "iso:country":"US",
    "sg:address":"484 E 24th St",
    "sg:city":"Paterson",
    "sg:classifiers":[
        {
            "category":"Social Services",
            "subcategory":"Child Care",
            "type":"Services"
        }
    ],
    "sg:phone":"+1 973 345 0992",
    "sg:postcode":"07514",
    "sg:province":"NJ",
    "sg:tags":[
        "day"
    ],
    "wof:name":"First Steps Day Care Center",
    "wof:placetype":"venue"
},
  "geometry": {"coordinates":[-74.1493,40.923401],"type":"Point"}
}