{
  "type": "Feature",
  "properties": {
    "iso:country":"US",
    "sg:address":"668 Main Ave",
    "sg:city":"Passaic",
    "sg:classifiers":[
        {
            "category":"Wholesale",
            "subcategory":"Machinery & Supplies",
            "type":"Manufacturing & Wholesale Goods"
        }
    ],
    "sg:phone":"+1 973 594 0099",
    "sg:postcode":"07055",
    "sg:province":"NJ",
    "sg:tags":[
        "equipment",
        "establishment"
    ],
    "wof:name":"Jazz Beauty Supply",
    "wof:placetype":"venue"
},
  "geometry": {"coordinates":[-74.12634199999999,40.861073],"type":"Point"}
}