{
  "type": "Feature",
  "properties": {
    "iso:country":"US",
    "sg:address":"46 Milltown Rd",
    "sg:city":"Stockton",
    "sg:classifiers":[
        {
            "category":"Professional",
            "subcategory":"Lawyer & Legal Services",
            "type":"Services"
        }
    ],
    "sg:phone":"+1 609 394 7917",
    "sg:postcode":"08559",
    "sg:province":"NJ",
    "sg:tags":[
        "attorney"
    ],
    "wof:name":"Nicholas Mancini",
    "wof:placetype":"venue"
},
  "geometry": {"coordinates":[-75.019081,40.455198],"type":"Point"}
}