{
  "type": "Feature",
  "properties": {
    "iso:country":"US",
    "sg:address":"17 James St Ste 4",
    "sg:city":"Bloomfield",
    "sg:classifiers":[
        {
            "category":"Building & Trades",
            "subcategory":"Cleaning & Sanitation",
            "type":"Services"
        }
    ],
    "sg:phone":"+1 973 748 4761",
    "sg:postcode":"07003",
    "sg:province":"NJ",
    "sg:tags":[
        "home"
    ],
    "sg:website":"www.barbarashomecare.com",
    "wof:name":"Barbara's Homecare Inc",
    "wof:placetype":"venue"
},
  "geometry": {"coordinates":[-74.192342,40.806133],"type":"Point"}
}