{
  "type": "Feature",
  "properties": {
    "addr:full":"248 Main St Lincoln Park NJ 07035",
    "addr:housenumber":"248",
    "addr:postcode":"07035",
    "addr:street":"Main St",
    "iso:country":"US",
    "sg:address":"248 Main St",
    "sg:city":"Lincoln Park",
    "sg:classifiers":[
        {
            "category":"Deli",
            "type":"Food & Drink"
        }
    ],
    "sg:phone":"+1 973 628 0630",
    "sg:postcode":"07035",
    "sg:province":"NJ",
    "wof:name":"Linda's Deli",
    "wof:placetype":"venue"
},
  "geometry": {"coordinates":[-74.304901,40.9231],"type":"Point"}
}