{
  "type": "Feature",
  "properties": {
    "iso:country":"US",
    "sg:address":"1068 White Horse Ave",
    "sg:city":"Trenton",
    "sg:classifiers":[
        {
            "category":"Restaurant",
            "type":"Food & Drink"
        }
    ],
    "sg:phone":"+1 609 585 3829",
    "sg:postcode":"08610",
    "sg:province":"NJ",
    "sg:tags":[
        "pizza"
    ],
    "wof:name":"Brother's Pizzeria",
    "wof:placetype":"venue"
},
  "geometry": {"coordinates":[-74.69612499999999,40.204551],"type":"Point"}
}