{
  "type": "Feature",
  "properties": {
    "iso:country":"US",
    "sg:address":"1275 Bloomfield Ave",
    "sg:city":"Fairfield",
    "sg:classifiers":[
        {
            "category":"Professional",
            "subcategory":"Research",
            "type":"Services"
        }
    ],
    "sg:phone":"+1 845 267 4102",
    "sg:postcode":"07004",
    "sg:province":"NJ",
    "sg:tags":[
        "environmental",
        "ecological"
    ],
    "wof:name":"Environmental Products & Svc",
    "wof:placetype":"venue"
},
  "geometry": {"coordinates":[-74.318907,40.858492],"type":"Point"}
}