{
  "type": "Feature",
  "properties": {
    "iso:country":"US",
    "sg:address":"18 Devins Ln",
    "sg:city":"Pleasantville",
    "sg:classifiers":[
        {
            "category":"Utilities",
            "subcategory":"Fuel Oil & Lpg",
            "type":"Services"
        }
    ],
    "sg:phone":"+1 609 641 4520",
    "sg:postcode":"08232",
    "sg:province":"NJ",
    "sg:tags":[
        "heating"
    ],
    "wof:name":"Ken Adams Oil Service Inc",
    "wof:placetype":"venue"
},
  "geometry": {"coordinates":[-74.539565,39.396346],"type":"Point"}
}