{
  "type": "Feature",
  "properties": {
    "iso:country":"US",
    "sg:address":"632 Burt Rd",
    "sg:city":"Runnemede",
    "sg:classifiers":[
        {
            "category":"Professional",
            "type":"Services"
        }
    ],
    "sg:phone":"+1   ",
    "sg:postcode":"08078",
    "sg:province":"NJ",
    "wof:name":"Slivinski K Aldn",
    "wof:placetype":"venue"
},
  "geometry": {"coordinates":[-75.08869300000001,39.848568],"type":"Point"}
}