{
  "type": "Feature",
  "properties": {
    "addr:full":"38 Grandin Dr Flemington NJ 08822",
    "addr:housenumber":"38",
    "addr:postcode":"08822",
    "addr:street":"Grandin Dr",
    "iso:country":"US",
    "sg:address":"38 Grandin Dr",
    "sg:city":"Flemington",
    "sg:classifiers":[
        {
            "category":"Shopping",
            "subcategory":"Music",
            "type":"Retail Goods"
        }
    ],
    "sg:phone":"+1   ",
    "sg:postcode":"08822",
    "sg:province":"NJ",
    "wof:name":"Edward M Hermann Jr",
    "wof:placetype":"venue"
},
  "geometry": {"coordinates":[-74.86724,40.524863],"type":"Point"}
}