{
  "type": "Feature",
  "properties": {
    "iso:country":"US",
    "sg:address":"11 Jacob Arnold Rd",
    "sg:city":"Morristown",
    "sg:classifiers":[
        {
            "category":"Wholesale",
            "subcategory":"Home Furnishings",
            "type":"Manufacturing & Wholesale Goods"
        },
        {
            "category":"Home & Garden",
            "subcategory":"Home Furnishings",
            "type":"Retail Goods"
        }
    ],
    "sg:phone":"+1 973 292 6525",
    "sg:postcode":"07960",
    "sg:province":"NJ",
    "sg:tags":[
        "tapestry"
    ],
    "wof:name":"Chanteclaire Collections",
    "wof:placetype":"venue"
},
  "geometry": {"coordinates":[-74.529842,40.813015],"type":"Point"}
}