{
  "type": "Feature",
  "properties": {
    "iso:country":"US",
    "sg:address":"255 Washington Pl",
    "sg:city":"Paramus",
    "sg:classifiers":[
        {
            "category":"Manufacturing",
            "subcategory":"Printing",
            "type":"Manufacturing & Wholesale Goods"
        }
    ],
    "sg:phone":"+1 201 599 2085",
    "sg:postcode":"07652",
    "sg:province":"NJ",
    "sg:tags":[
        "periodical"
    ],
    "wof:name":"Golden China Monthly",
    "wof:placetype":"venue"
},
  "geometry": {"coordinates":[-74.05185899999999,40.946443],"type":"Point"}
}