{
  "type": "Feature",
  "properties": {
    "addr:full":"617 Kingman Ave Vineland NJ 08360",
    "addr:housenumber":"617",
    "addr:postcode":"08360",
    "addr:street":"Kingman Ave",
    "iso:country":"US",
    "sg:address":"617 Kingman Ave",
    "sg:city":"Vineland",
    "sg:classifiers":[
        {
            "category":"Building & Trades",
            "subcategory":"Plumbing",
            "type":"Services"
        }
    ],
    "sg:phone":"+1 856 690 9692",
    "sg:postcode":"08360",
    "sg:province":"NJ",
    "sg:tags":[
        "contractor"
    ],
    "wof:name":"Rj Mechanical LLC",
    "wof:placetype":"venue"
},
  "geometry": {"coordinates":[-75.035089,39.507477],"type":"Point"}
}