{
  "type": "Feature",
  "properties": {
    "iso:country":"US",
    "sg:address":"95 New Bridge Rd",
    "sg:city":"Bergenfield",
    "sg:classifiers":[
        {
            "category":"Personal",
            "subcategory":"Beauty Salon",
            "type":"Services"
        }
    ],
    "sg:phone":"+1 201 385 8990",
    "sg:postcode":"07621",
    "sg:province":"NJ",
    "sg:tags":[
        "shop"
    ],
    "wof:name":"Studio II Hair & Nails",
    "wof:placetype":"venue"
},
  "geometry": {"coordinates":[-74.00123000000001,40.914148],"type":"Point"}
}