{
  "type": "Feature",
  "properties": {
    "addr:full":"206 Keats Ave Toms River NJ 08753",
    "addr:housenumber":"206",
    "addr:postcode":"08753",
    "addr:street":"Keats Ave",
    "iso:country":"US",
    "sg:address":"206 Keats Ave",
    "sg:city":"Toms River",
    "sg:classifiers":[
        {
            "category":"Building & Trades",
            "subcategory":"Construction",
            "type":"Services"
        }
    ],
    "sg:phone":"+1 732 288 9163",
    "sg:postcode":"08753",
    "sg:province":"NJ",
    "sg:tags":[
        "carpentry",
        "contractor"
    ],
    "wof:name":"Polozzo Construction Inc",
    "wof:placetype":"venue"
},
  "geometry": {"coordinates":[-74.162279,39.951499],"type":"Point"}
}