{
  "type": "Feature",
  "properties": {
    "iso:country":"US",
    "sg:address":"295 Atlantic City Blvd",
    "sg:city":"Bayville",
    "sg:classifiers":[
        {
            "category":"Banks & Credit Unions",
            "subcategory":"Financial Services",
            "type":"Services"
        }
    ],
    "sg:phone":"+1   ",
    "sg:postcode":"08721",
    "sg:province":"NJ",
    "sg:tags":[
        "realtor"
    ],
    "wof:name":"Bay Coast Realty",
    "wof:placetype":"venue"
},
  "geometry": {"coordinates":[-74.163033,39.921094],"type":"Point"}
}