{
  "type": "Feature",
  "properties": {
    "addr:full":"18 Connecticut St Cranford NJ 07016",
    "addr:housenumber":"18",
    "addr:postcode":"07016",
    "addr:street":"Connecticut St",
    "iso:country":"US",
    "sg:address":"18 Connecticut St",
    "sg:city":"Cranford",
    "sg:classifiers":[
        {
            "category":"Professional",
            "subcategory":"Management & Consulting",
            "type":"Services"
        }
    ],
    "sg:phone":"+1   ",
    "sg:postcode":"07016",
    "sg:province":"NJ",
    "sg:tags":[
        "retail",
        "direct",
        "sales"
    ],
    "wof:name":"Lesko Care LLC",
    "wof:placetype":"venue"
},
  "geometry": {"coordinates":[-74.314583,40.642428],"type":"Point"}
}