{
  "type": "Feature",
  "properties": {
    "addr:full":"45 Meadowbrook Rd Chatham NJ 07928",
    "addr:housenumber":"45",
    "addr:postcode":"07928",
    "addr:street":"Meadowbrook Rd",
    "iso:country":"US",
    "sg:address":"45 Meadowbrook Rd",
    "sg:city":"Chatham",
    "sg:classifiers":[
        {
            "category":"Professional",
            "type":"Services"
        }
    ],
    "sg:phone":"+1   ",
    "sg:postcode":"07928",
    "sg:province":"NJ",
    "wof:name":"Five Star Importers LLC",
    "wof:placetype":"venue"
},
  "geometry": {"coordinates":[-74.39552500000001,40.740016],"type":"Point"}
}