{
  "type": "Feature",
  "properties": {
    "iso:country":"US",
    "sg:address":"506 61st St",
    "sg:city":"West New York",
    "sg:classifiers":[
        {
            "category":"Personal",
            "subcategory":"Beauty Salon",
            "type":"Services"
        }
    ],
    "sg:phone":"+1 201 854 4504",
    "sg:postcode":"07093",
    "sg:province":"NJ",
    "sg:tags":[
        "nail",
        "manicuring"
    ],
    "wof:name":"Diego's Unisex",
    "wof:placetype":"venue"
},
  "geometry": {"coordinates":[-74.0158,40.790001],"type":"Point"}
}