{
  "type": "Feature",
  "properties": {
    "iso:country":"US",
    "sg:address":"10 Old Milford Ln",
    "sg:city":"West Milford",
    "sg:classifiers":[
        {
            "category":"Building & Trades",
            "subcategory":"Construction",
            "type":"Services"
        }
    ],
    "sg:phone":"+1 973 697 2545",
    "sg:postcode":"07480",
    "sg:province":"NJ",
    "sg:tags":[
        "contractor"
    ],
    "wof:name":"Home-Tech Repair Contr Inc",
    "wof:placetype":"venue"
},
  "geometry": {"coordinates":[-74.40607199999999,41.102707],"type":"Point"}
}