{
  "type": "Feature",
  "properties": {
    "iso:country":"US",
    "sg:address":"6 Brunswick Woods Dr",
    "sg:city":"East Brunswick",
    "sg:classifiers":[
        {
            "category":"Professional",
            "subcategory":"Computer Services",
            "type":"Services"
        }
    ],
    "sg:phone":"+1 732 254 4562",
    "sg:postcode":"08816",
    "sg:province":"NJ",
    "sg:tags":[
        "related"
    ],
    "wof:name":"Ahlers Technologies",
    "wof:placetype":"venue"
},
  "geometry": {"coordinates":[-74.389709,40.420905],"type":"Point"}
}