{
  "type": "Feature",
  "properties": {
    "addr:full":"297 Kinderkamack Rd Oradell NJ 07649",
    "addr:housenumber":"297",
    "addr:postcode":"07649",
    "addr:street":"Kinderkamack Rd",
    "iso:country":"US",
    "sg:address":"297 Kinderkamack Rd",
    "sg:city":"Oradell",
    "sg:classifiers":[
        {
            "category":"Shopping",
            "subcategory":"Computers & Home Electronics",
            "type":"Retail Goods"
        }
    ],
    "sg:phone":"+1 201 236 0189",
    "sg:postcode":"07649",
    "sg:province":"NJ",
    "sg:tags":[
        "software"
    ],
    "wof:name":"Client Server Stragegies",
    "wof:placetype":"venue"
},
  "geometry": {"coordinates":[-74.03232,40.950637],"type":"Point"}
}