{
  "type": "Feature",
  "properties": {
    "iso:country":"US",
    "sg:address":"9 Caldwell Ct",
    "sg:city":"Basking Ridge",
    "sg:classifiers":[
        {
            "category":"Professional",
            "subcategory":"Lawyer & Legal Services",
            "type":"Services"
        }
    ],
    "sg:phone":"+1 908 304 0008",
    "sg:postcode":"07920",
    "sg:province":"NJ",
    "sg:tags":[
        "attorney"
    ],
    "wof:name":"Jonathan B Behrins",
    "wof:placetype":"venue"
},
  "geometry": {"coordinates":[-74.603686,40.655147],"type":"Point"}
}