{
  "type": "Feature",
  "properties": {
    "addr:full":"552 W Union Ave Bound Brook NJ 08805",
    "addr:housenumber":"552",
    "addr:postcode":"08805",
    "addr:street":"W Union Ave",
    "iso:country":"US",
    "sg:address":"552 W Union Ave",
    "sg:city":"Bound Brook",
    "sg:classifiers":[
        {
            "category":"Restaurant",
            "type":"Food & Drink"
        }
    ],
    "sg:menulink":"http://www.allmenus.com/nj/bound-brook/19049-joeys-grill/menu/",
    "sg:phone":"+1 732 469 4007",
    "sg:postcode":"08805",
    "sg:province":"NJ",
    "sg:tags":[
        "italian"
    ],
    "wof:name":"Joey's Grill",
    "wof:placetype":"venue"
},
  "geometry": {"coordinates":[-74.550016,40.56797],"type":"Point"}
}