{
  "type": "Feature",
  "properties": {
    "iso:country":"US",
    "sg:address":"5 Sicomac Rd",
    "sg:city":"Haledon",
    "sg:classifiers":[
        {
            "category":"Restaurant",
            "type":"Food & Drink"
        }
    ],
    "sg:phone":"+1   ",
    "sg:postcode":"07508",
    "sg:province":"NJ",
    "sg:tags":[
        "catering"
    ],
    "wof:name":"Meals For Kids",
    "wof:placetype":"venue"
},
  "geometry": {"coordinates":[-74.19076099999999,40.973295],"type":"Point"}
}