{
  "type": "Feature",
  "properties": {
    "iso:country":"US",
    "sg:address":"351 E Cos Cob Dr",
    "sg:city":"Absecon",
    "sg:classifiers":[
        {
            "category":"Professional",
            "type":"Services"
        }
    ],
    "sg:phone":"+1   ",
    "sg:postcode":"08205",
    "sg:province":"NJ",
    "wof:name":"APT Preparation Service",
    "wof:placetype":"venue"
},
  "geometry": {"coordinates":[-74.492115,39.494913],"type":"Point"}
}