{
  "type": "Feature",
  "properties": {
    "iso:country":"US",
    "sg:address":"403 King George Rd",
    "sg:city":"Basking Ridge",
    "sg:classifiers":[
        {
            "category":"Professional",
            "subcategory":"Lawyer & Legal Services",
            "type":"Services"
        }
    ],
    "sg:phone":"+1 908 647 9300",
    "sg:postcode":"07920",
    "sg:province":"NJ",
    "sg:tags":[
        "attorney"
    ],
    "wof:name":"Reppert & Kelly",
    "wof:placetype":"venue"
},
  "geometry": {"coordinates":[-74.52386199999999,40.649446],"type":"Point"}
}