{
  "type": "Feature",
  "properties": {
    "addr:full":"US Hwy 1 & Industrial Ln N Linden NJ 07036",
    "addr:postcode":"07036",
    "addr:street":"Us Hwy 1 & Industrial Ln N",
    "iso:country":"US",
    "sg:address":"US Hwy 1 & Industrial Ln N",
    "sg:city":"Linden",
    "sg:classifiers":[
        {
            "category":"Restaurant",
            "type":"Food & Drink"
        },
        {
            "category":"Food & Beverages",
            "subcategory":"Bakery",
            "type":"Retail Goods"
        }
    ],
    "sg:phone":"+1 908 862 0245",
    "sg:postcode":"07036",
    "sg:province":"NJ",
    "sg:tags":[
        "sandwich",
        "diner"
    ],
    "wof:name":"US 1 Diner",
    "wof:placetype":"venue"
},
  "geometry": {"coordinates":[-74.24009,40.630157],"type":"Point"}
}