{
  "type": "Feature",
  "properties": {
    "addr:full":"869 Broad St Newark NJ 07102",
    "addr:housenumber":"869",
    "addr:postcode":"07102",
    "addr:street":"Broad St",
    "iso:country":"US",
    "sg:address":"869 Broad St",
    "sg:city":"Newark",
    "sg:classifiers":[
        {
            "category":"Shopping",
            "subcategory":"Clothing, Apparel, & Fashions",
            "type":"Retail Goods"
        }
    ],
    "sg:phone":"+1   ",
    "sg:postcode":"07102",
    "sg:province":"NJ",
    "wof:name":"Three Stars",
    "wof:placetype":"venue"
},
  "geometry": {"coordinates":[-74.173547,40.733298],"type":"Point"}
}