{
  "type": "Feature",
  "properties": {
    "iso:country":"US",
    "sg:address":"8400 Atlantic Ave",
    "sg:city":"Wildwood Crest",
    "sg:classifiers":[
        {
            "category":"Travel",
            "subcategory":"Hotels & Motels",
            "type":"Entertainment"
        }
    ],
    "sg:phone":"+1 609 522 1002",
    "sg:postcode":"08260",
    "sg:province":"NJ",
    "sg:website":"www.lavita.com",
    "wof:name":"LA Vita Motel",
    "wof:placetype":"venue"
},
  "geometry": {"coordinates":[-74.842688,38.963857],"type":"Point"}
}