{
  "type": "Feature",
  "properties": {
    "iso:country":"US",
    "sg:address":"541 Lincoln St",
    "sg:city":"Carlstadt",
    "sg:classifiers":[
        {
            "category":"Retail",
            "subcategory":"Repair Shop",
            "type":"Services"
        }
    ],
    "sg:phone":"+1   ",
    "sg:postcode":"07072",
    "sg:province":"NJ",
    "wof:name":"Carlstadt Cycle",
    "wof:placetype":"venue"
},
  "geometry": {"coordinates":[-74.096512,40.84368],"type":"Point"}
}