{
  "type": "Feature",
  "properties": {
    "iso:country":"US",
    "sg:address":"348 Pompton Ave",
    "sg:city":"Cedar Grove",
    "sg:classifiers":[
        {
            "category":"Shopping",
            "type":"Retail Goods"
        }
    ],
    "sg:phone":"+1 973 239 1441",
    "sg:postcode":"07009",
    "sg:province":"NJ",
    "sg:tags":[
        "art",
        "gallery",
        "dealer"
    ],
    "wof:name":"Main Street Gallery",
    "wof:placetype":"venue"
},
  "geometry": {"coordinates":[-74.228312,40.844077],"type":"Point"}
}