{
  "type": "Feature",
  "properties": {
    "iso:country":"US",
    "sg:address":"1900 State Rte 35",
    "sg:city":"Middletown",
    "sg:classifiers":[
        {
            "category":"Retail",
            "subcategory":"Auto Repair",
            "type":"Services"
        }
    ],
    "sg:phone":"+1 732 671 0299",
    "sg:postcode":"07748",
    "sg:province":"NJ",
    "sg:tags":[
        "repairing",
        "automobile"
    ],
    "wof:name":"Mr Good Lube 10 Minute Oil Inc",
    "wof:placetype":"venue"
},
  "geometry": {"coordinates":[-74.13064199999999,40.408001],"type":"Point"}
}