{
  "type": "Feature",
  "properties": {
    "iso:country":"US",
    "sg:address":"134 Monmouth St",
    "sg:city":"Red Bank",
    "sg:classifiers":[
        {
            "category":"Food & Beverages",
            "subcategory":"Fruits & Vegetables",
            "type":"Retail Goods"
        }
    ],
    "sg:phone":"+1 732 747 0508",
    "sg:postcode":"07701",
    "sg:province":"NJ",
    "sg:tags":[
        "produce"
    ],
    "wof:name":"Victory Market",
    "wof:placetype":"venue"
},
  "geometry": {"coordinates":[-74.072428,40.349062],"type":"Point"}
}