{
  "type": "Feature",
  "properties": {
    "addr:full":"29 Polkville Rd Columbia NJ 07832",
    "addr:housenumber":"29",
    "addr:postcode":"07832",
    "addr:street":"Polkville Rd",
    "iso:country":"US",
    "sg:address":"29 Polkville Rd",
    "sg:city":"Columbia",
    "sg:classifiers":[
        {
            "category":"Manufacturing",
            "subcategory":"Tools & Machinery",
            "type":"Manufacturing & Wholesale Goods"
        }
    ],
    "sg:phone":"+1 908 362 6573",
    "sg:postcode":"07832",
    "sg:province":"NJ",
    "sg:tags":[
        "machine",
        "shop"
    ],
    "wof:name":"Specialized Machining Svc",
    "wof:placetype":"venue"
},
  "geometry": {"coordinates":[-75.027106,40.95777],"type":"Point"}
}