{
  "type": "Feature",
  "properties": {
    "iso:country":"US",
    "sg:address":"6 Sussex Ave",
    "sg:city":"Beach Haven",
    "sg:classifiers":[
        {
            "category":"Professional",
            "subcategory":"Management & Consulting",
            "type":"Services"
        }
    ],
    "sg:phone":"+1   ",
    "sg:postcode":"08008",
    "sg:province":"NJ",
    "sg:tags":[
        "firm"
    ],
    "wof:name":"Moore Group Inc",
    "wof:placetype":"venue"
},
  "geometry": {"coordinates":[-74.137747,39.702019],"type":"Point"}
}