{
  "type": "Feature",
  "properties": {
    "addr:full":"320 Viviney St Elmwood Park NJ 07407",
    "addr:housenumber":"320",
    "addr:postcode":"07407",
    "addr:street":"Viviney St",
    "iso:country":"US",
    "sg:address":"320 Viviney St",
    "sg:city":"Elmwood Park",
    "sg:classifiers":[
        {
            "category":"Professional",
            "type":"Services"
        }
    ],
    "sg:phone":"+1   ",
    "sg:postcode":"07407",
    "sg:province":"NJ",
    "wof:name":"Electricom Co",
    "wof:placetype":"venue"
},
  "geometry": {"coordinates":[-74.12462600000001,40.905927],"type":"Point"}
}