{
  "type": "Feature",
  "properties": {
    "addr:full":"2500 S Broadway Camden NJ 08104",
    "addr:housenumber":"2500",
    "addr:postcode":"08104",
    "addr:street":"S Broadway",
    "iso:country":"US",
    "sg:address":"2500 S Broadway",
    "sg:city":"Camden",
    "sg:classifiers":[
        {
            "category":"Structure",
            "subcategory":"Warehouse",
            "type":"Public Place"
        },
        {
            "category":"Retail",
            "subcategory":"Storage",
            "type":"Services"
        }
    ],
    "sg:phone":"+1 856 963 9270",
    "sg:postcode":"08104",
    "sg:province":"NJ",
    "sg:tags":[
        "self",
        "warehouses-merchandise"
    ],
    "wof:name":"Federal Street Warehousing & D",
    "wof:placetype":"venue"
},
  "geometry": {"coordinates":[-75.11994199999999,39.91267],"type":"Point"}
}