{
  "type": "Feature",
  "properties": {
    "iso:country":"US",
    "sg:address":"4682 Springfield Ave",
    "sg:city":"Merchantville",
    "sg:classifiers":[
        {
            "category":"Wholesale",
            "subcategory":"Vending Machines",
            "type":"Manufacturing & Wholesale Goods"
        }
    ],
    "sg:phone":"+1   ",
    "sg:postcode":"08109",
    "sg:province":"NJ",
    "sg:tags":[
        "operator"
    ],
    "wof:name":"Link Vending",
    "wof:placetype":"venue"
},
  "geometry": {"coordinates":[-75.055376,39.946602],"type":"Point"}
}