{
  "type": "Feature",
  "properties": {
    "addr:full":"61 State Rte 34 South Amboy NJ 08879",
    "addr:housenumber":"61",
    "addr:postcode":"08879",
    "addr:street":"State Rte 34",
    "iso:country":"US",
    "sg:address":"61 State Rte 34",
    "sg:city":"South Amboy",
    "sg:classifiers":[
        {
            "category":"Retail",
            "subcategory":"Laundry & Dry Cleaning",
            "type":"Services"
        }
    ],
    "sg:phone":"+1 732 721 5400",
    "sg:postcode":"08879",
    "sg:province":"NJ",
    "sg:tags":[
        "cleaners"
    ],
    "wof:name":"Madison Dry Cleaners",
    "wof:placetype":"venue"
},
  "geometry": {"coordinates":[-74.29473,40.428334],"type":"Point"}
}