{
  "type": "Feature",
  "properties": {
    "iso:country":"US",
    "sg:address":"16 Beekman Pl",
    "sg:city":"Cherry Hill",
    "sg:classifiers":[
        {
            "category":"Professional",
            "subcategory":"Management & Consulting",
            "type":"Services"
        }
    ],
    "sg:phone":"+1   ",
    "sg:postcode":"08002",
    "sg:province":"NJ",
    "sg:tags":[
        "business"
    ],
    "wof:name":"Mobil Fleet",
    "wof:placetype":"venue"
},
  "geometry": {"coordinates":[-75.010887,39.937104],"type":"Point"}
}