{
  "type": "Feature",
  "properties": {
    "addr:full":"127 Pershing Rd Brooklawn NJ 08030",
    "addr:housenumber":"127",
    "addr:postcode":"08030",
    "addr:street":"Pershing Rd",
    "iso:country":"US",
    "sg:address":"127 Pershing Rd",
    "sg:city":"Brooklawn",
    "sg:classifiers":[
        {
            "category":"Building & Trades",
            "subcategory":"Construction",
            "type":"Services"
        }
    ],
    "sg:phone":"+1 856 456 5588",
    "sg:postcode":"08030",
    "sg:province":"NJ",
    "sg:tags":[
        "contractor"
    ],
    "wof:name":"Anthony Franchi Contractors and Materials Co",
    "wof:placetype":"venue"
},
  "geometry": {"coordinates":[-75.126552,39.881889],"type":"Point"}
}