{
  "type": "Feature",
  "properties": {
    "addr:full":"72 Hamburg Tpke Riverdale NJ 07457",
    "addr:housenumber":"72",
    "addr:postcode":"07457",
    "addr:street":"Hamburg Tpke",
    "iso:country":"US",
    "sg:address":"72 Hamburg Tpke",
    "sg:city":"Riverdale",
    "sg:classifiers":[
        {
            "category":"Health Services",
            "subcategory":"Doctor",
            "type":"Services"
        }
    ],
    "sg:phone":"+1   ",
    "sg:postcode":"07457",
    "sg:province":"NJ",
    "sg:tags":[
        "medical"
    ],
    "sg:website":"www.valleyhealth.com",
    "wof:name":"Valley Health Medical Group",
    "wof:placetype":"venue"
},
  "geometry": {"coordinates":[-74.304866,40.99839],"type":"Point"}
}