{
  "type": "Feature",
  "properties": {
    "iso:country":"US",
    "sg:address":"1210 Ocean Ave",
    "sg:city":"Lakewood",
    "sg:classifiers":[
        {
            "category":"Autos & Motor Vehicles",
            "subcategory":"Automobile Sales",
            "type":"Retail Goods"
        }
    ],
    "sg:phone":"+1 732 370 8800",
    "sg:postcode":"08701",
    "sg:province":"NJ",
    "sg:tags":[
        "car",
        "dealer"
    ],
    "sg:website":"www.futureclassicsnj.com",
    "wof:name":"Future Classics",
    "wof:placetype":"venue"
},
  "geometry": {"coordinates":[-74.16678,40.082233],"type":"Point"}
}