{
  "type": "Feature",
  "properties": {
    "addr:full":"490 E Main St Denville NJ 07834",
    "addr:housenumber":"490",
    "addr:postcode":"07834",
    "addr:street":"E Main St",
    "iso:country":"US",
    "sg:address":"490 E Main St",
    "sg:city":"Denville",
    "sg:classifiers":[
        {
            "category":"Personal",
            "type":"Services"
        }
    ],
    "sg:phone":"+1 973 664 0809",
    "sg:postcode":"07834",
    "sg:province":"NJ",
    "sg:tags":[
        "therapist",
        "massage"
    ],
    "wof:name":"Spring Health Spa",
    "wof:placetype":"venue"
},
  "geometry": {"coordinates":[-74.47999900000001,40.878778],"type":"Point"}
}