{
  "type": "Feature",
  "properties": {
    "iso:country":"US",
    "sg:address":"1 Palmer Ln",
    "sg:city":"Manalapan",
    "sg:classifiers":[
        {
            "category":"Real Estate",
            "subcategory":"Real Estate Agent",
            "type":"Services"
        }
    ],
    "sg:phone":"+1 732 786 8844",
    "sg:postcode":"07726",
    "sg:province":"NJ",
    "wof:name":"Galloping Hills At Millstone",
    "wof:placetype":"venue"
},
  "geometry": {"coordinates":[-74.35469999999999,40.294066],"type":"Point"}
}