{
  "type": "Feature",
  "properties": {
    "addr:full":"342 Grant Ave Middlesex NJ 08846",
    "addr:housenumber":"342",
    "addr:postcode":"08846",
    "addr:street":"Grant Ave",
    "iso:country":"US",
    "sg:address":"342 Grant Ave",
    "sg:city":"Middlesex",
    "sg:classifiers":[
        {
            "category":"Building & Trades",
            "subcategory":"Construction",
            "type":"Services"
        }
    ],
    "sg:phone":"+1 732 469 2801",
    "sg:postcode":"08846",
    "sg:province":"NJ",
    "sg:tags":[
        "house"
    ],
    "wof:name":"Daisey Construction Inc",
    "wof:placetype":"venue"
},
  "geometry": {"coordinates":[-74.51468300000001,40.570716],"type":"Point"}
}