{
  "type": "Feature",
  "properties": {
    "addr:full":"1469 Nottingham Way Trenton NJ 08609",
    "addr:housenumber":"1469",
    "addr:postcode":"08609",
    "addr:street":"Nottingham Way",
    "iso:country":"US",
    "sg:address":"1469 Nottingham Way",
    "sg:city":"Trenton",
    "sg:classifiers":[
        {
            "category":"Food & Beverages",
            "subcategory":"Groceries & Convenience Stores",
            "type":"Retail Goods"
        }
    ],
    "sg:phone":"+1 609 586 2929",
    "sg:postcode":"08609",
    "sg:province":"NJ",
    "wof:name":"Express Food Market",
    "wof:placetype":"venue"
},
  "geometry": {"coordinates":[-74.722173,40.232026],"type":"Point"}
}