{
  "type": "Feature",
  "properties": {
    "iso:country":"US",
    "sg:address":"9 Northfield Dr",
    "sg:city":"Sussex",
    "sg:classifiers":[
        {
            "category":"Professional",
            "subcategory":"Engineering",
            "type":"Services"
        }
    ],
    "sg:phone":"+1 973 702 1848",
    "sg:postcode":"07461",
    "sg:province":"NJ",
    "wof:name":"Constant Trading & Contracting",
    "wof:placetype":"venue"
},
  "geometry": {"coordinates":[-74.658835,41.224842],"type":"Point"}
}