{
  "type": "Feature",
  "properties": {
    "addr:full":"58 Wallington Ave Wallington NJ 07057",
    "addr:housenumber":"58",
    "addr:postcode":"07057",
    "addr:street":"Wallington Ave",
    "iso:country":"US",
    "sg:address":"58 Wallington Ave",
    "sg:city":"Wallington",
    "sg:classifiers":[
        {
            "category":"Personal",
            "type":"Services"
        }
    ],
    "sg:phone":"+1 973 249 1818",
    "sg:postcode":"07057",
    "sg:province":"NJ",
    "sg:tags":[
        "contracting",
        "contractor"
    ],
    "wof:name":"Brahma Construction Corp",
    "wof:placetype":"venue"
},
  "geometry": {"coordinates":[-74.1157,40.857601],"type":"Point"}
}