{
  "type": "Feature",
  "properties": {
    "iso:country":"US",
    "sg:address":"1 Nottingham Cir",
    "sg:city":"Princeton",
    "sg:classifiers":[
        {
            "category":"Professional",
            "subcategory":"Business Services",
            "type":"Services"
        }
    ],
    "sg:phone":"+1   ",
    "sg:postcode":"08540",
    "sg:province":"NJ",
    "wof:name":"Richard J Schwartz Sales Inc",
    "wof:placetype":"venue"
},
  "geometry": {"coordinates":[-74.66157200000001,40.319174],"type":"Point"}
}