{
  "type": "Feature",
  "properties": {
    "addr:full":"1667 State Rte 27 Edison NJ 08817",
    "addr:housenumber":"1667",
    "addr:postcode":"08817",
    "addr:street":"State Rte 27",
    "iso:country":"US",
    "sg:address":"1667 State Rte 27",
    "sg:city":"Edison",
    "sg:classifiers":[
        {
            "category":"Personal",
            "subcategory":"Beauty Salon",
            "type":"Services"
        }
    ],
    "sg:phone":"+1 732 548 5424",
    "sg:postcode":"08817",
    "sg:province":"NJ",
    "sg:tags":[
        "barber"
    ],
    "wof:name":"Edison Barber Shop",
    "wof:placetype":"venue"
},
  "geometry": {"coordinates":[-74.409396,40.510337],"type":"Point"}
}