{
  "type": "Feature",
  "properties": {
    "iso:country":"US",
    "sg:address":"523 W End Ave",
    "sg:city":"Haddonfield",
    "sg:classifiers":[
        {
            "category":"Shopping",
            "subcategory":"Gifts & Souvenirs",
            "type":"Retail Goods"
        }
    ],
    "sg:phone":"+1   ",
    "sg:postcode":"08033",
    "sg:province":"NJ",
    "wof:name":"Big Sky",
    "wof:placetype":"venue"
},
  "geometry": {"coordinates":[-75.047236,39.900275],"type":"Point"}
}