{
  "type": "Feature",
  "properties": {
    "addr:full":"36 Cleveland St Bergenfield NJ 07621",
    "addr:housenumber":"36",
    "addr:postcode":"07621",
    "addr:street":"Cleveland St",
    "iso:country":"US",
    "sg:address":"36 Cleveland St",
    "sg:city":"Bergenfield",
    "sg:classifiers":[
        {
            "category":"Professional",
            "subcategory":"Art Services",
            "type":"Services"
        }
    ],
    "sg:phone":"+1   ",
    "sg:postcode":"07621",
    "sg:province":"NJ",
    "sg:tags":[
        "graphic",
        "design",
        "computer"
    ],
    "wof:name":"Medianet Inc",
    "wof:placetype":"venue"
},
  "geometry": {"coordinates":[-73.99981099999999,40.930007],"type":"Point"}
}