{
  "type": "Feature",
  "properties": {
    "iso:country":"US",
    "sg:address":"1359 S Main Rd",
    "sg:city":"Vineland",
    "sg:classifiers":[
        {
            "category":"Travel",
            "subcategory":"Travel Agent",
            "type":"Entertainment"
        }
    ],
    "sg:phone":"+1 856 507 9110",
    "sg:postcode":"08360",
    "sg:province":"NJ",
    "sg:tags":[
        "agency",
        "bureau"
    ],
    "wof:name":"Magic Carpet Travels Inc",
    "wof:placetype":"venue"
},
  "geometry": {"coordinates":[-75.005196,39.467862],"type":"Point"}
}