{
  "type": "Feature",
  "properties": {
    "iso:country":"US",
    "sg:address":"59 Sandelwood Dr",
    "sg:city":"Clark",
    "sg:classifiers":[
        {
            "category":"Shopping",
            "type":"Retail Goods"
        }
    ],
    "sg:phone":"+1 732 388 8009",
    "sg:postcode":"07066",
    "sg:province":"NJ",
    "sg:tags":[
        "picture",
        "frame"
    ],
    "wof:name":"Final Touch Art & Framing",
    "wof:placetype":"venue"
},
  "geometry": {"coordinates":[-74.320266,40.614846],"type":"Point"}
}