{
  "type": "Feature",
  "properties": {
    "iso:country":"US",
    "sg:address":"4 Progress St",
    "sg:city":"Edison",
    "sg:classifiers":[
        {
            "category":"Personal",
            "type":"Services"
        }
    ],
    "sg:phone":"+1 908 222 0700",
    "sg:postcode":"08820",
    "sg:province":"NJ",
    "sg:tags":[
        "hair",
        "replacement"
    ],
    "wof:name":"International Hair Surgical Gp",
    "wof:placetype":"venue"
},
  "geometry": {"coordinates":[-74.357083,40.597525],"type":"Point"}
}