{
  "type": "Feature",
  "properties": {
    "iso:country":"US",
    "sg:address":"241 Harrison Ave",
    "sg:city":"Garfield",
    "sg:classifiers":[
        {
            "category":"Shopping",
            "subcategory":"Clothing, Apparel, & Fashions",
            "type":"Retail Goods"
        }
    ],
    "sg:phone":"+1 973 478 1370",
    "sg:postcode":"07026",
    "sg:province":"NJ",
    "sg:tags":[
        "accessory",
        "clothing",
        "women's"
    ],
    "sg:website":"www.thefigleafboutique.com",
    "wof:name":"The Fig Leaf",
    "wof:placetype":"venue"
},
  "geometry": {"coordinates":[-74.097837,40.874373],"type":"Point"}
}