{
  "type": "Feature",
  "properties": {
    "iso:country":"US",
    "sg:address":"660 E Bay Ave",
    "sg:city":"Manahawkin",
    "sg:classifiers":[
        {
            "category":"Travel",
            "subcategory":"Travel Agent",
            "type":"Entertainment"
        }
    ],
    "sg:phone":"+1 609 597 0800",
    "sg:postcode":"08050",
    "sg:province":"NJ",
    "sg:tags":[
        "agency"
    ],
    "wof:name":"Travel Emporium",
    "wof:placetype":"venue"
},
  "geometry": {"coordinates":[-74.23849,39.685805],"type":"Point"}
}