{
  "type": "Feature",
  "properties": {
    "iso:country":"US",
    "sg:address":"915 Glenview Rd",
    "sg:city":"Ridgewood",
    "sg:classifiers":[
        {
            "category":"Recreation",
            "type":"Entertainment"
        }
    ],
    "sg:phone":"+1   ",
    "sg:postcode":"07450",
    "sg:province":"NJ",
    "sg:tags":[
        "club",
        "membership",
        "sport"
    ],
    "wof:name":"Upper Ridgewood Tennis Club",
    "wof:placetype":"venue"
},
  "geometry": {"coordinates":[-74.12232299999999,41.00523],"type":"Point"}
}