{
  "type": "Feature",
  "properties": {
    "iso:country":"US",
    "sg:address":"48 Lafayette Ave",
    "sg:city":"Voorhees",
    "sg:classifiers":[
        {
            "category":"Retail",
            "subcategory":"Animal Services",
            "type":"Services"
        }
    ],
    "sg:phone":"+1 856 767 6578",
    "sg:postcode":"08043",
    "sg:province":"NJ",
    "sg:tags":[
        "specialty"
    ],
    "wof:name":"Ashmen Akitas",
    "wof:placetype":"venue"
},
  "geometry": {"coordinates":[-74.93889799999999,39.818751],"type":"Point"}
}