{
  "type": "Feature",
  "properties": {
    "addr:full":"11 Mount Salem Rd Pittstown NJ 08867",
    "addr:housenumber":"11",
    "addr:postcode":"08867",
    "addr:street":"Mount Salem Rd",
    "iso:country":"US",
    "sg:address":"11 Mount Salem Rd",
    "sg:city":"Pittstown",
    "sg:classifiers":[
        {
            "category":"Building & Trades",
            "subcategory":"Construction",
            "type":"Services"
        }
    ],
    "sg:phone":"+1 908 730 5908",
    "sg:postcode":"08867",
    "sg:province":"NJ",
    "sg:tags":[
        "resurfacing",
        "laying",
        "refinishing",
        "floor"
    ],
    "wof:name":"Classic Wood Flooring",
    "wof:placetype":"venue"
},
  "geometry": {"coordinates":[-75.00357700000001,40.591367],"type":"Point"}
}