{
  "type": "Feature",
  "properties": {
    "addr:full":"877 Prospect St Glen Rock NJ 07452",
    "addr:housenumber":"877",
    "addr:postcode":"07452",
    "addr:street":"Prospect St",
    "iso:country":"US",
    "sg:address":"877 Prospect St",
    "sg:city":"Glen Rock",
    "sg:classifiers":[
        {
            "category":"Personal",
            "subcategory":"Beauty Salon",
            "type":"Services"
        }
    ],
    "sg:phone":"+1 201 445 2829",
    "sg:postcode":"07452",
    "sg:province":"NJ",
    "wof:name":"Bellezza Salon & Spa",
    "wof:placetype":"venue"
},
  "geometry": {"coordinates":[-74.108187,40.953773],"type":"Point"}
}