{
  "type": "Feature",
  "properties": {
    "iso:country":"US",
    "sg:address":"369 Main St",
    "sg:city":"Orange",
    "sg:classifiers":[
        {
            "category":"Education",
            "subcategory":"School",
            "type":"Public Place"
        }
    ],
    "sg:phone":"+1 973 675 6376",
    "sg:postcode":"07050",
    "sg:province":"NJ",
    "wof:name":"Main Street School",
    "wof:placetype":"venue"
},
  "geometry": {"coordinates":[-74.232584,40.773331],"type":"Point"}
}