{
  "type": "Feature",
  "properties": {
    "addr:full":"2780 John F Kennedy Blvd Jersey City NJ 07306",
    "addr:housenumber":"2780",
    "addr:postcode":"07306",
    "addr:street":"John F Kennedy Blvd",
    "iso:country":"US",
    "sg:address":"2780 John F Kennedy Blvd",
    "sg:city":"Jersey City",
    "sg:classifiers":[
        {
            "category":"Health Services",
            "subcategory":"Doctor",
            "type":"Services"
        }
    ],
    "sg:phone":"+1 201 239 7777",
    "sg:postcode":"07306",
    "sg:province":"NJ",
    "sg:tags":[
        "physician",
        "surgeon"
    ],
    "wof:name":"Mona Boulos MD",
    "wof:placetype":"venue"
},
  "geometry": {"coordinates":[-74.06819900000001,40.73059],"type":"Point"}
}