{
  "type": "Feature",
  "properties": {
    "iso:country":"US",
    "sg:address":"409 Halladay St",
    "sg:city":"Jersey City",
    "sg:classifiers":[
        {
            "category":"Social Services",
            "subcategory":"Child Care",
            "type":"Services"
        }
    ],
    "sg:phone":"+1 201 432 7645",
    "sg:postcode":"07304",
    "sg:province":"NJ",
    "wof:name":"Lafayette Park Day Care Ctr",
    "wof:placetype":"venue"
},
  "geometry": {"coordinates":[-74.059011,40.715025],"type":"Point"}
}