{
  "type": "Feature",
  "properties": {
    "iso:country":"US",
    "sg:address":"150 E Route 70",
    "sg:city":"Marlton",
    "sg:classifiers":[
        {
            "category":"Shopping",
            "subcategory":"Clothing, Apparel, & Fashions",
            "type":"Retail Goods"
        },
        {
            "category":"Shopping",
            "subcategory":"Department Store",
            "type":"Retail Goods"
        },
        {
            "category":"Shopping",
            "subcategory":"Discount & Variety Stores",
            "type":"Retail Goods"
        },
        {
            "category":"Shopping",
            "subcategory":"Mobile Phones",
            "type":"Retail Goods"
        },
        {
            "category":"Utilities",
            "subcategory":"Telephone",
            "type":"Services"
        },
        {
            "category":"Utilities",
            "subcategory":"Mobile Phone",
            "type":"Services"
        },
        {
            "category":"Food & Beverages",
            "subcategory":"Supermarket",
            "type":"Retail Goods"
        },
        {
            "category":"Professional",
            "subcategory":"Computer Services",
            "type":"Services"
        },
        {
            "category":"Shopping",
            "type":"Retail Goods"
        }
    ],
    "sg:phone":"+1 856 983 2100",
    "sg:postcode":"08053",
    "sg:province":"NJ",
    "sg:tags":[
        "super",
        "telecommunication",
        "supply",
        "communication",
        "system",
        "wireless",
        "equipment",
        "cellular",
        "clothing",
        "merchandise"
    ],
    "sg:website":"http://clickserve.dartsearch.net/link/click?lid=43000000308049899",
    "wof:name":"T-Mobile",
    "wof:placetype":"venue"
},
  "geometry": {"coordinates":[-74.908782,39.894074],"type":"Point"}
}