{
  "type": "Feature",
  "properties": {
    "addr:full":"100 S Mill Rd Vineland NJ 08360",
    "addr:housenumber":"100",
    "addr:postcode":"08360",
    "addr:street":"S Mill Rd",
    "iso:country":"US",
    "sg:address":"100 S Mill Rd",
    "sg:city":"Vineland",
    "sg:classifiers":[
        {
            "category":"Shopping",
            "subcategory":"Clothing, Apparel, & Fashions",
            "type":"Retail Goods"
        }
    ],
    "sg:phone":"+1   ",
    "sg:postcode":"08360",
    "sg:province":"NJ",
    "wof:name":"Victorias Secret",
    "wof:placetype":"venue"
},
  "geometry": {"coordinates":[-75.061798,39.485143],"type":"Point"}
}