{
  "type": "Feature",
  "properties": {
    "iso:country":"US",
    "sg:address":"233 W Market St",
    "sg:city":"Newark",
    "sg:classifiers":[
        {
            "category":"Professional",
            "subcategory":"Employment Agencies",
            "type":"Services"
        }
    ],
    "sg:phone":"+1 973 484 0300",
    "sg:postcode":"07103",
    "sg:province":"NJ",
    "sg:tags":[
        "temporary",
        "staffing"
    ],
    "wof:name":"Newsource Staffing Inc",
    "wof:placetype":"venue"
},
  "geometry": {"coordinates":[-74.186423,40.742896],"type":"Point"}
}