{
  "type": "Feature",
  "properties": {
    "addr:full":"238 N White Horse Pike Hammonton NJ 08037",
    "addr:housenumber":"238",
    "addr:postcode":"08037",
    "addr:street":"N White Horse Pike",
    "iso:country":"US",
    "sg:address":"238 N White Horse Pike",
    "sg:city":"Hammonton",
    "sg:classifiers":[
        {
            "category":"Shopping",
            "type":"Retail Goods"
        }
    ],
    "sg:phone":"+1 609 704 3113",
    "sg:postcode":"08037",
    "sg:province":"NJ",
    "sg:tags":[
        "hearing",
        "equipment",
        "supply",
        "impaired"
    ],
    "wof:name":"Garden State Hearing Aid Ctr",
    "wof:placetype":"venue"
},
  "geometry": {"coordinates":[-74.796876,39.652832],"type":"Point"}
}