{
  "type": "Feature",
  "properties": {
    "addr:full":"136 Green Grove Ave Keyport NJ 07735",
    "addr:housenumber":"136",
    "addr:postcode":"07735",
    "addr:street":"Green Grove Ave",
    "iso:country":"US",
    "sg:address":"136 Green Grove Ave",
    "sg:city":"Keyport",
    "sg:classifiers":[
        {
            "category":"Building & Trades",
            "subcategory":"Landscaping Services",
            "type":"Services"
        }
    ],
    "sg:phone":"+1 732 203 1688",
    "sg:postcode":"07735",
    "sg:province":"NJ",
    "sg:tags":[
        "consultant",
        "designer",
        "landscape"
    ],
    "wof:name":"Pv & Sons Landscaping",
    "wof:placetype":"venue"
},
  "geometry": {"coordinates":[-74.19059,40.431721],"type":"Point"}
}