{
  "type": "Feature",
  "properties": {
    "iso:country":"US",
    "sg:address":"917 E 27th St",
    "sg:city":"Paterson",
    "sg:classifiers":[
        {
            "category":"Manufacturing",
            "subcategory":"Printing",
            "type":"Manufacturing & Wholesale Goods"
        }
    ],
    "sg:phone":"+1 973 357 0099",
    "sg:postcode":"07513",
    "sg:province":"NJ",
    "sg:tags":[
        "printer"
    ],
    "wof:name":"Watermark Press",
    "wof:placetype":"venue"
},
  "geometry": {"coordinates":[-74.149883,40.907016],"type":"Point"}
}