{
  "type": "Feature",
  "properties": {
    "iso:country":"US",
    "sg:address":"241 Thomas St",
    "sg:city":"Newark",
    "sg:classifiers":[
        {
            "category":"Retail",
            "subcategory":"Auto Repair",
            "type":"Services"
        }
    ],
    "sg:phone":"+1 973 344 1877",
    "sg:postcode":"07114",
    "sg:province":"NJ",
    "sg:tags":[
        "repairing",
        "automobile"
    ],
    "wof:name":"Marmecar Auto Repairs",
    "wof:placetype":"venue"
},
  "geometry": {"coordinates":[-74.17040299999999,40.721001],"type":"Point"}
}