{
  "type": "Feature",
  "properties": {
    "iso:country":"US",
    "sg:address":"400 Kelby St",
    "sg:city":"Fort Lee",
    "sg:classifiers":[
        {
            "category":"Real Estate",
            "subcategory":"Real Estate Services",
            "type":"Services"
        }
    ],
    "sg:phone":"+1 201 302 9000",
    "sg:postcode":"07024",
    "sg:province":"NJ",
    "sg:tags":[
        "management",
        "property"
    ],
    "wof:name":"Avm Corporation",
    "wof:placetype":"venue"
},
  "geometry": {"coordinates":[-73.972702,40.856098],"type":"Point"}
}