{
  "type": "Feature",
  "properties": {
    "iso:country":"US",
    "sg:address":"4693 US Hwy 9",
    "sg:city":"Howell",
    "sg:classifiers":[
        {
            "category":"Health Services",
            "subcategory":"Health Practitioner",
            "type":"Services"
        }
    ],
    "sg:phone":"+1 732 866 3977",
    "sg:postcode":"07731",
    "sg:province":"NJ",
    "sg:tags":[
        "nutritionist"
    ],
    "wof:name":"Suzan Siegel",
    "wof:placetype":"venue"
},
  "geometry": {"coordinates":[-74.22465800000001,40.138339],"type":"Point"}
}