{
  "type": "Feature",
  "properties": {
    "iso:country":"US",
    "sg:address":"1318 Pacific Ave",
    "sg:city":"Atlantic City",
    "sg:classifiers":[
        {
            "category":"Food & Beverages",
            "subcategory":"Groceries & Convenience Stores",
            "type":"Retail Goods"
        }
    ],
    "sg:phone":"+1 609 345 0488",
    "sg:postcode":"08401",
    "sg:province":"NJ",
    "sg:tags":[
        "grocer"
    ],
    "wof:name":"New York's Finest Grocery-Deli",
    "wof:placetype":"venue"
},
  "geometry": {"coordinates":[-74.42576,39.361096],"type":"Point"}
}