{
  "type": "Feature",
  "properties": {
    "addr:full":"10 Stewart Pl Fairfield NJ 07004",
    "addr:housenumber":"10",
    "addr:postcode":"07004",
    "addr:street":"Stewart Pl",
    "iso:country":"US",
    "sg:address":"10 Stewart Pl",
    "sg:city":"Fairfield",
    "sg:classifiers":[
        {
            "category":"Professional",
            "subcategory":"Business Services",
            "type":"Services"
        }
    ],
    "sg:phone":"+1   ",
    "sg:postcode":"07004",
    "sg:province":"NJ",
    "sg:tags":[
        "trucking"
    ],
    "wof:name":"Retailers & Mfrs Dist Mkg Svc",
    "wof:placetype":"venue"
},
  "geometry": {"coordinates":[-74.31613400000001,40.871004],"type":"Point"}
}