{
  "type": "Feature",
  "properties": {
    "addr:full":"49 Hunter Rd S Haledon NJ 07508",
    "addr:housenumber":"49",
    "addr:postcode":"07508",
    "addr:street":"Hunter Rd",
    "iso:country":"US",
    "sg:address":"49 Hunter Rd S",
    "sg:city":"Haledon",
    "sg:classifiers":[
        {
            "category":"Professional",
            "subcategory":"Management & Consulting",
            "type":"Services"
        }
    ],
    "sg:phone":"+1   ",
    "sg:postcode":"07508",
    "sg:province":"NJ",
    "wof:name":"Law Computer Interface Inc",
    "wof:placetype":"venue"
},
  "geometry": {"coordinates":[-74.180758,40.967383],"type":"Point"}
}