{
  "type": "Feature",
  "properties": {
    "iso:country":"US",
    "sg:address":"1510 John F Kennedy Blvd",
    "sg:city":"Jersey City",
    "sg:classifiers":[
        {
            "category":"Organizations",
            "subcategory":"Religious Organization",
            "type":"Services"
        }
    ],
    "sg:phone":"+1 201 332 0970",
    "sg:postcode":"07305",
    "sg:province":"NJ",
    "sg:tags":[
        "church"
    ],
    "wof:name":"Cityline Church",
    "wof:placetype":"venue"
},
  "geometry": {"coordinates":[-74.101135,40.693374],"type":"Point"}
}