{
  "type": "Feature",
  "properties": {
    "addr:full":"875 Industrial Hwy Cinnaminson NJ 08077",
    "addr:housenumber":"875",
    "addr:postcode":"08077",
    "addr:street":"Industrial Hwy",
    "iso:country":"US",
    "sg:address":"875 Industrial Hwy",
    "sg:city":"Cinnaminson",
    "sg:classifiers":[
        {
            "category":"Wholesale",
            "subcategory":"Machinery & Supplies",
            "type":"Manufacturing & Wholesale Goods"
        }
    ],
    "sg:phone":"+1 856 786 8314",
    "sg:postcode":"08077",
    "sg:province":"NJ",
    "sg:tags":[
        "equipment",
        "labeling"
    ],
    "wof:name":"Slate Marketing Inc",
    "wof:placetype":"venue"
},
  "geometry": {"coordinates":[-74.998193,40.015459],"type":"Point"}
}