{
  "type": "Feature",
  "properties": {
    "iso:country":"US",
    "sg:address":"315 Roosevelt Ave",
    "sg:city":"Northfield",
    "sg:classifiers":[
        {
            "category":"Building & Trades",
            "subcategory":"Construction",
            "type":"Services"
        }
    ],
    "sg:phone":"+1 609 646 7537",
    "sg:postcode":"08225",
    "sg:province":"NJ",
    "sg:tags":[
        "house"
    ],
    "wof:name":"Block Brothers Builders",
    "wof:placetype":"venue"
},
  "geometry": {"coordinates":[-74.549854,39.375719],"type":"Point"}
}