{
  "type": "Feature",
  "properties": {
    "iso:country":"US",
    "sg:address":"75 Jewell St",
    "sg:city":"Garfield",
    "sg:classifiers":[
        {
            "category":"Food & Beverages",
            "subcategory":"Bakery",
            "type":"Retail Goods"
        }
    ],
    "sg:phone":"+1 973 772 7270",
    "sg:postcode":"07026",
    "sg:province":"NJ",
    "sg:tags":[
        "deli",
        "baker",
        "grocery"
    ],
    "wof:name":"Kohout Bakery",
    "wof:placetype":"venue"
},
  "geometry": {"coordinates":[-74.11930099999999,40.882801],"type":"Point"}
}