{
  "type": "Feature",
  "properties": {
    "addr:full":"220 Rivervale Rd Westwood NJ 07675",
    "addr:housenumber":"220",
    "addr:postcode":"07675",
    "addr:street":"Rivervale Rd",
    "iso:country":"US",
    "sg:address":"220 Rivervale Rd",
    "sg:city":"Westwood",
    "sg:classifiers":[
        {
            "category":"Professional",
            "subcategory":"Business Services",
            "type":"Services"
        }
    ],
    "sg:phone":"+1   ",
    "sg:postcode":"07675",
    "sg:province":"NJ",
    "wof:name":"Jed Enterprises No 1 LLC",
    "wof:placetype":"venue"
},
  "geometry": {"coordinates":[-74.00631300000001,40.995199],"type":"Point"}
}