{
  "type": "Feature",
  "properties": {
    "iso:country":"US",
    "sg:address":"48 Handy St",
    "sg:city":"New Brunswick",
    "sg:classifiers":[
        {
            "category":"Professional",
            "subcategory":"Business Services",
            "type":"Services"
        }
    ],
    "sg:phone":"+1   ",
    "sg:postcode":"08901",
    "sg:province":"NJ",
    "sg:tags":[
        "geological"
    ],
    "wof:name":"Ground Truth",
    "wof:placetype":"venue"
},
  "geometry": {"coordinates":[-74.442796,40.484185],"type":"Point"}
}