{
  "type": "Feature",
  "properties": {
    "iso:country":"US",
    "sg:address":"3 Regina Rd",
    "sg:city":"Morganville",
    "sg:classifiers":[
        {
            "category":"Professional",
            "subcategory":"Accounting & Tax Preparation",
            "type":"Services"
        }
    ],
    "sg:phone":"+1   ",
    "sg:postcode":"07751",
    "sg:province":"NJ",
    "wof:name":"Daniel Jelinsky",
    "wof:placetype":"venue"
},
  "geometry": {"coordinates":[-74.295421,40.329617],"type":"Point"}
}