{
  "type": "Feature",
  "properties": {
    "iso:country":"US",
    "sg:address":"832 E Saint Georges Ave",
    "sg:city":"Linden",
    "sg:classifiers":[
        {
            "category":"Building & Trades",
            "subcategory":"Construction",
            "type":"Services"
        }
    ],
    "sg:phone":"+1 908 925 2336",
    "sg:postcode":"07036",
    "sg:province":"NJ",
    "sg:tags":[
        "tile",
        "dealer"
    ],
    "wof:name":"Decorama Tile & Bath Outlets",
    "wof:placetype":"venue"
},
  "geometry": {"coordinates":[-74.25445000000001,40.644523],"type":"Point"}
}