{
  "type": "Feature",
  "properties": {
    "iso:country":"US",
    "sg:address":"1306 W Chicago Blvd",
    "sg:city":"Sea Girt",
    "sg:classifiers":[
        {
            "category":"Manufacturing",
            "subcategory":"Retail Goods",
            "type":"Manufacturing & Wholesale Goods"
        }
    ],
    "sg:phone":"+1 732 974 0174",
    "sg:postcode":"08750",
    "sg:province":"NJ",
    "sg:tags":[
        "product",
        "mfg"
    ],
    "wof:name":"Conhagen Industries Inc",
    "wof:placetype":"venue"
},
  "geometry": {"coordinates":[-74.0566,40.140063],"type":"Point"}
}