{
  "type": "Feature",
  "properties": {
    "addr:full":"36 Central Ave Clifton NJ 07011",
    "addr:housenumber":"36",
    "addr:postcode":"07011",
    "addr:street":"Central Ave",
    "iso:country":"US",
    "sg:address":"36 Central Ave",
    "sg:city":"Clifton",
    "sg:classifiers":[
        {
            "category":"Home & Garden",
            "subcategory":"Building Materials",
            "type":"Retail Goods"
        }
    ],
    "sg:phone":"+1   ",
    "sg:postcode":"07011",
    "sg:province":"NJ",
    "wof:name":"Cellar Doors By Schlipf",
    "wof:placetype":"venue"
},
  "geometry": {"coordinates":[-74.13267999999999,40.871919],"type":"Point"}
}