{
  "type": "Feature",
  "properties": {
    "iso:country":"US",
    "sg:address":"8 Commerce St",
    "sg:city":"Springfield",
    "sg:classifiers":[
        {
            "category":"Manufacturing",
            "subcategory":"Metals",
            "type":"Manufacturing & Wholesale Goods"
        }
    ],
    "sg:phone":"+1 973 379 4600",
    "sg:postcode":"07081",
    "sg:province":"NJ",
    "sg:tags":[
        "metalwork",
        "sheet",
        "fabric",
        "architectural",
        "mfg"
    ],
    "wof:name":"Springfield Metal Products Co",
    "wof:placetype":"venue"
},
  "geometry": {"coordinates":[-74.318153,40.690015],"type":"Point"}
}