{
  "type": "Feature",
  "properties": {
    "iso:country":"US",
    "sg:address":"34 Ridge Rd",
    "sg:city":"Budd Lake",
    "sg:classifiers":[
        {
            "category":"Professional",
            "subcategory":"Management & Consulting",
            "type":"Services"
        }
    ],
    "sg:phone":"+1   ",
    "sg:postcode":"07828",
    "sg:province":"NJ",
    "sg:tags":[
        "resource",
        "human"
    ],
    "wof:name":"Luminara LLC",
    "wof:placetype":"venue"
},
  "geometry": {"coordinates":[-74.765108,40.869912],"type":"Point"}
}