{
  "type": "Feature",
  "properties": {
    "addr:full":"52 Patriot Hill Dr Basking Ridge NJ 07920",
    "addr:housenumber":"52",
    "addr:postcode":"07920",
    "addr:street":"Patriot Hill Dr",
    "iso:country":"US",
    "sg:address":"52 Patriot Hill Dr",
    "sg:city":"Basking Ridge",
    "sg:classifiers":[
        {
            "category":"Professional",
            "subcategory":"Computer Services",
            "type":"Services"
        }
    ],
    "sg:phone":"+1 908 730 6317",
    "sg:postcode":"07920",
    "sg:province":"NJ",
    "sg:tags":[
        "consultant"
    ],
    "wof:name":"Connexion Inc",
    "wof:placetype":"venue"
},
  "geometry": {"coordinates":[-74.614464,40.651485],"type":"Point"}
}