{
  "type": "Feature",
  "properties": {
    "iso:country":"US",
    "sg:address":"1154 Boardwalk",
    "sg:city":"Ocean City",
    "sg:classifiers":[
        {
            "category":"Shopping",
            "type":"Retail Goods"
        }
    ],
    "sg:phone":"+1 609 390 8575",
    "sg:postcode":"08226",
    "sg:province":"NJ",
    "sg:tags":[
        "factory",
        "outlet"
    ],
    "wof:name":"Gener Xation",
    "wof:placetype":"venue"
},
  "geometry": {"coordinates":[-74.576837,39.273556],"type":"Point"}
}