{
  "type": "Feature",
  "properties": {
    "iso:country":"US",
    "sg:address":"350 Ramapo Valley Rd",
    "sg:city":"Oakland",
    "sg:classifiers":[
        {
            "category":"Shopping",
            "subcategory":"Optical Goods",
            "type":"Retail Goods"
        }
    ],
    "sg:phone":"+1 201 651 1212",
    "sg:postcode":"07436",
    "sg:province":"NJ",
    "sg:tags":[
        "optician"
    ],
    "wof:name":"Oakland Vision Ctr Inc",
    "wof:placetype":"venue"
},
  "geometry": {"coordinates":[-74.241674,41.024804],"type":"Point"}
}