{
  "type": "Feature",
  "properties": {
    "iso:country":"US",
    "sg:address":"183 South Ave",
    "sg:city":"Fanwood",
    "sg:classifiers":[
        {
            "category":"Retail",
            "subcategory":"Auto Repair",
            "type":"Services"
        }
    ],
    "sg:phone":"+1 908 322 3999",
    "sg:postcode":"07023",
    "sg:province":"NJ",
    "sg:tags":[
        "body",
        "automobile",
        "painting"
    ],
    "wof:name":"George Church Auto Inc",
    "wof:placetype":"venue"
},
  "geometry": {"coordinates":[-74.386942,40.638563],"type":"Point"}
}