{
  "type": "Feature",
  "properties": {
    "addr:full":"525 Ewingville Rd Trenton NJ 08638",
    "addr:housenumber":"525",
    "addr:postcode":"08638",
    "addr:street":"Ewingville Rd",
    "iso:country":"US",
    "sg:address":"525 Ewingville Rd",
    "sg:city":"Trenton",
    "sg:classifiers":[
        {
            "category":"Home & Garden",
            "subcategory":"Hardware",
            "type":"Retail Goods"
        }
    ],
    "sg:phone":"+1   ",
    "sg:postcode":"08638",
    "sg:province":"NJ",
    "wof:name":"Village Hardware",
    "wof:placetype":"venue"
},
  "geometry": {"coordinates":[-74.778768,40.27673],"type":"Point"}
}