{
  "type": "Feature",
  "properties": {
    "iso:country":"US",
    "sg:address":"269 Varick St",
    "sg:city":"Jersey City",
    "sg:classifiers":[
        {
            "category":"Personal",
            "subcategory":"Beauty Salon",
            "type":"Services"
        }
    ],
    "sg:phone":"+1 201 333 7773",
    "sg:postcode":"07302",
    "sg:province":"NJ",
    "wof:name":"Diamonds & Pearls Hair Crtns",
    "wof:placetype":"venue"
},
  "geometry": {"coordinates":[-74.049796,40.718365],"type":"Point"}
}