{
  "type": "Feature",
  "properties": {
    "addr:full":"6701 Kennedy Blvd E West New York NJ 07093",
    "addr:housenumber":"6701",
    "addr:postcode":"07093",
    "addr:street":"Kennedy Blvd E West",
    "iso:country":"US",
    "sg:address":"6701 Kennedy Blvd E",
    "sg:city":"West New York",
    "sg:classifiers":[
        {
            "category":"Professional",
            "subcategory":"Lawyer & Legal Services",
            "type":"Services"
        }
    ],
    "sg:phone":"+1 201 854 3072",
    "sg:postcode":"07093",
    "sg:province":"NJ",
    "wof:name":"Cohen Sheldon",
    "wof:placetype":"venue"
},
  "geometry": {"coordinates":[-74.002098,40.789501],"type":"Point"}
}