{
  "type": "Feature",
  "properties": {
    "addr:full":"653 US Highway 46 Fairfield NJ 07004",
    "addr:housenumber":"653",
    "addr:postcode":"07004",
    "addr:street":"Us Highway 46",
    "iso:country":"US",
    "sg:address":"653 US Highway 46",
    "sg:city":"Fairfield",
    "sg:classifiers":[
        {
            "category":"Shopping",
            "subcategory":"Jewelry",
            "type":"Retail Goods"
        }
    ],
    "sg:phone":"+1 973 808 0003",
    "sg:postcode":"07004",
    "sg:province":"NJ",
    "wof:name":"David's Sons Jewelry",
    "wof:placetype":"venue"
},
  "geometry": {"coordinates":[-74.267799,40.8922],"type":"Point"}
}