{
  "type": "Feature",
  "properties": {
    "addr:full":"333 Grand Ave Englewood NJ 07631",
    "addr:housenumber":"333",
    "addr:postcode":"07631",
    "addr:street":"Grand Ave",
    "iso:country":"US",
    "sg:address":"333 Grand Ave",
    "sg:city":"Englewood",
    "sg:classifiers":[
        {
            "category":"Health Services",
            "subcategory":"Nursing And Care Facility",
            "type":"Services"
        }
    ],
    "sg:phone":"+1 201 568 0900",
    "sg:postcode":"07631",
    "sg:province":"NJ",
    "sg:tags":[
        "home",
        "convalescent"
    ],
    "sg:website":"www.genesishcc.com",
    "wof:name":"Inglemoor Nursing & Rehab Ctr",
    "wof:placetype":"venue"
},
  "geometry": {"coordinates":[-73.97810200000001,40.881884],"type":"Point"}
}