{
  "type": "Feature",
  "properties": {
    "iso:country":"US",
    "sg:address":"33 Chub Way",
    "sg:city":"Somerville",
    "sg:classifiers":[
        {
            "category":"Professional",
            "subcategory":"Research",
            "type":"Services"
        }
    ],
    "sg:phone":"+1 908 218 9588",
    "sg:postcode":"08876",
    "sg:province":"NJ",
    "sg:tags":[
        "biological",
        "product",
        "physical",
        "commercial",
        "mfg"
    ],
    "wof:name":"Imclone Systems Incorporated",
    "wof:placetype":"venue"
},
  "geometry": {"coordinates":[-74.70965,40.555191],"type":"Point"}
}