{
  "type": "Feature",
  "properties": {
    "iso:country":"US",
    "sg:address":"231 E Main St",
    "sg:city":"Moorestown",
    "sg:classifiers":[
        {
            "category":"Building & Trades",
            "subcategory":"Landscaping Services",
            "type":"Services"
        }
    ],
    "sg:phone":"+1 856 222 9337",
    "sg:postcode":"08057",
    "sg:province":"NJ",
    "sg:tags":[
        "designer",
        "landscape"
    ],
    "wof:name":"Beechwood Landscape Arch",
    "wof:placetype":"venue"
},
  "geometry": {"coordinates":[-74.938602,39.966217],"type":"Point"}
}