{
  "type": "Feature",
  "properties": {
    "addr:full":"602 Valley Rd Montclair NJ 07043",
    "addr:housenumber":"602",
    "addr:postcode":"07043",
    "addr:street":"Valley Rd",
    "iso:country":"US",
    "sg:address":"602 Valley Rd",
    "sg:city":"Montclair",
    "sg:classifiers":[
        {
            "category":"Travel",
            "subcategory":"Travel Agent",
            "type":"Entertainment"
        }
    ],
    "sg:phone":"+1 973 744 0010",
    "sg:postcode":"07043",
    "sg:province":"NJ",
    "sg:tags":[
        "agency",
        "bureau"
    ],
    "wof:name":"World Wide Travel Bureau Inc",
    "wof:placetype":"venue"
},
  "geometry": {"coordinates":[-74.20820999999999,40.84234],"type":"Point"}
}