{
  "type": "Feature",
  "properties": {
    "addr:full":"54 Lenox Rd Summit NJ 07901",
    "addr:housenumber":"54",
    "addr:postcode":"07901",
    "addr:street":"Lenox Rd",
    "iso:country":"US",
    "sg:address":"54 Lenox Rd",
    "sg:city":"Summit",
    "sg:classifiers":[
        {
            "category":"Building & Trades",
            "subcategory":"Construction",
            "type":"Services"
        }
    ],
    "sg:phone":"+1 908 273 6644",
    "sg:postcode":"07901",
    "sg:province":"NJ",
    "sg:tags":[
        "contractor"
    ],
    "wof:name":"Solo A Mano",
    "wof:placetype":"venue"
},
  "geometry": {"coordinates":[-74.347905,40.718947],"type":"Point"}
}