{
  "type": "Feature",
  "properties": {
    "addr:full":"912 Haddonfield Rd Ste A Cherry Hill NJ 08002",
    "addr:housenumber":"912",
    "addr:postcode":"08002",
    "addr:street":"Haddonfield Rd Ste A",
    "iso:country":"US",
    "sg:address":"912 Haddonfield Rd Ste A",
    "sg:city":"Cherry Hill",
    "sg:classifiers":[
        {
            "category":"Retail",
            "subcategory":"Laundry & Dry Cleaning",
            "type":"Services"
        }
    ],
    "sg:phone":"+1 856 662 0170",
    "sg:postcode":"08002",
    "sg:province":"NJ",
    "wof:name":"Cleaners USA",
    "wof:placetype":"venue"
},
  "geometry": {"coordinates":[-75.03283500000001,39.92484],"type":"Point"}
}