{
  "type": "Feature",
  "properties": {
    "iso:country":"US",
    "sg:address":"221 State Rte 31",
    "sg:city":"Flemington",
    "sg:classifiers":[
        {
            "category":"Retail",
            "subcategory":"Auto Repair",
            "type":"Services"
        }
    ],
    "sg:phone":"+1 908 782 9322",
    "sg:postcode":"08822",
    "sg:province":"NJ",
    "sg:tags":[
        "repairing",
        "automobile"
    ],
    "wof:name":"Midas Auto Svc Experts",
    "wof:placetype":"venue"
},
  "geometry": {"coordinates":[-74.85763300000001,40.534511],"type":"Point"}
}