{
  "type": "Feature",
  "properties": {
    "addr:full":"7408 Tonnelle Ave North Bergen NJ 07047",
    "addr:housenumber":"7408",
    "addr:postcode":"07047",
    "addr:street":"Tonnelle Ave",
    "iso:country":"US",
    "sg:address":"7408 Tonnelle Ave",
    "sg:city":"North Bergen",
    "sg:classifiers":[
        {
            "category":"Shopping",
            "subcategory":"Tobacco",
            "type":"Retail Goods"
        }
    ],
    "sg:phone":"+1 201 943 8675",
    "sg:postcode":"07047",
    "sg:province":"NJ",
    "sg:tags":[
        "shop"
    ],
    "wof:name":"United Candy & Tobacco Co",
    "wof:placetype":"venue"
},
  "geometry": {"coordinates":[-74.01950100000001,40.803299],"type":"Point"}
}