{
  "type": "Feature",
  "properties": {
    "addr:full":"2 Haverford Ave Somerdale NJ 08083",
    "addr:housenumber":"2",
    "addr:postcode":"08083",
    "addr:street":"Haverford Ave",
    "iso:country":"US",
    "sg:address":"2 Haverford Ave",
    "sg:city":"Somerdale",
    "sg:classifiers":[
        {
            "category":"Retail",
            "subcategory":"Portrait Studio",
            "type":"Services"
        }
    ],
    "sg:phone":"+1   ",
    "sg:postcode":"08083",
    "sg:province":"NJ",
    "sg:tags":[
        "photo"
    ],
    "wof:name":"Pure Entertainment",
    "wof:placetype":"venue"
},
  "geometry": {"coordinates":[-75.011854,39.841536],"type":"Point"}
}