{
  "type": "Feature",
  "properties": {
    "addr:full":"124 Rolling Brook Dr Edison NJ 08820",
    "addr:housenumber":"124",
    "addr:postcode":"08820",
    "addr:street":"Rolling Brook Dr",
    "iso:country":"US",
    "sg:address":"124 Rolling Brook Dr",
    "sg:city":"Edison",
    "sg:classifiers":[
        {
            "category":"Professional",
            "subcategory":"Computer Services",
            "type":"Services"
        }
    ],
    "sg:phone":"+1 908 755 4040",
    "sg:postcode":"08820",
    "sg:province":"NJ",
    "sg:tags":[
        "programing",
        "custom"
    ],
    "wof:name":"Apex Consulting Services Inc",
    "wof:placetype":"venue"
},
  "geometry": {"coordinates":[-74.369095,40.591577],"type":"Point"}
}