{
  "type": "Feature",
  "properties": {
    "addr:full":"619 River Dr Elmwood Park NJ 07407",
    "addr:housenumber":"619",
    "addr:postcode":"07407",
    "addr:street":"River Dr",
    "iso:country":"US",
    "sg:address":"619 River Dr",
    "sg:city":"Elmwood Park",
    "sg:classifiers":[
        {
            "category":"Health Services",
            "subcategory":"Doctor",
            "type":"Services"
        }
    ],
    "sg:phone":"+1 201 703 2900",
    "sg:postcode":"07407",
    "sg:province":"NJ",
    "sg:tags":[
        "medical"
    ],
    "wof:name":"River Drive Surgery Center LLC",
    "wof:placetype":"venue"
},
  "geometry": {"coordinates":[-74.127002,40.901807],"type":"Point"}
}