{
  "type": "Feature",
  "properties": {
    "iso:country":"US",
    "sg:address":"664 Sunset Blvd",
    "sg:city":"Cape May",
    "sg:classifiers":[
        {
            "category":"Farming",
            "subcategory":"Nursery",
            "type":"Manufacturing & Wholesale Goods"
        }
    ],
    "sg:phone":"+1 609 898 1711",
    "sg:postcode":"08204",
    "sg:province":"NJ",
    "sg:tags":[
        "ornamental"
    ],
    "wof:name":"Cape May Cut Flowers",
    "wof:placetype":"venue"
},
  "geometry": {"coordinates":[-74.953103,38.940617],"type":"Point"}
}