{
  "type": "Feature",
  "properties": {
    "iso:country":"US",
    "sg:address":"519 41st St",
    "sg:city":"Union City",
    "sg:classifiers":[
        {
            "category":"Travel",
            "subcategory":"Travel Agent",
            "type":"Entertainment"
        }
    ],
    "sg:phone":"+1 201 348 0469",
    "sg:postcode":"07087",
    "sg:province":"NJ",
    "sg:tags":[
        "operator",
        "tour"
    ],
    "wof:name":"Celimar Tours Inc",
    "wof:placetype":"venue"
},
  "geometry": {"coordinates":[-74.027586,40.777776],"type":"Point"}
}