{
  "type": "Feature",
  "properties": {
    "addr:full":"5 Snowball Ln Trenton NJ 08619",
    "addr:housenumber":"5",
    "addr:postcode":"08619",
    "addr:street":"Snowball Ln",
    "iso:country":"US",
    "sg:address":"5 Snowball Ln",
    "sg:city":"Trenton",
    "sg:classifiers":[
        {
            "category":"Organizations",
            "subcategory":"Religious Organization",
            "type":"Services"
        }
    ],
    "sg:phone":"+1 609 890 8280",
    "sg:postcode":"08619",
    "sg:province":"NJ",
    "sg:tags":[
        "church"
    ],
    "wof:name":"Hamilton Bible Fellowship Inc",
    "wof:placetype":"venue"
},
  "geometry": {"coordinates":[-74.683627,40.223429],"type":"Point"}
}