{
  "type": "Feature",
  "properties": {
    "iso:country":"US",
    "sg:address":"284 Glenn Ave",
    "sg:city":"Trenton",
    "sg:classifiers":[
        {
            "category":"Social Services",
            "type":"Services"
        }
    ],
    "sg:phone":"+1 609 771 4094",
    "sg:postcode":"08648",
    "sg:province":"NJ",
    "wof:name":"Counseling Health Associates",
    "wof:placetype":"venue"
},
  "geometry": {"coordinates":[-74.721946,40.268467],"type":"Point"}
}