{
  "type": "Feature",
  "properties": {
    "addr:full":"541 White Horse Ave Trenton NJ 08610",
    "addr:housenumber":"541",
    "addr:postcode":"08610",
    "addr:street":"White Horse Ave",
    "iso:country":"US",
    "sg:address":"541 White Horse Ave",
    "sg:city":"Trenton",
    "sg:classifiers":[
        {
            "category":"Personal",
            "subcategory":"Beauty Salon",
            "type":"Services"
        },
        {
            "category":"Personal",
            "subcategory":"Barber",
            "type":"Services"
        }
    ],
    "sg:phone":"+1 609 585 4749",
    "sg:postcode":"08610",
    "sg:province":"NJ",
    "sg:tags":[
        "hair",
        "stylist"
    ],
    "sg:website":"http://www.positivethinkingmag.com",
    "wof:name":"Postively Hair",
    "wof:placetype":"venue"
},
  "geometry": {"coordinates":[-74.69982299999999,40.197551],"type":"Point"}
}