{
  "type": "Feature",
  "properties": {
    "addr:full":"135 Kinnelon Rd Kinnelon NJ 07405",
    "addr:housenumber":"135",
    "addr:postcode":"07405",
    "addr:street":"Kinnelon Rd",
    "iso:country":"US",
    "sg:address":"135 Kinnelon Rd",
    "sg:city":"Kinnelon",
    "sg:classifiers":[
        {
            "category":"Professional",
            "subcategory":"Business Services",
            "type":"Services"
        }
    ],
    "sg:phone":"+1 973 492 3450",
    "sg:postcode":"07405",
    "sg:province":"NJ",
    "sg:tags":[
        "fund",
        "promotion",
        "raising"
    ],
    "wof:name":"Elite Sampling & Promotion LLC",
    "wof:placetype":"venue"
},
  "geometry": {"coordinates":[-74.37878000000001,40.995709],"type":"Point"}
}