{
  "type": "Feature",
  "properties": {
    "iso:country":"US",
    "sg:address":"254 Livingston St",
    "sg:city":"Norwood",
    "sg:classifiers":[
        {
            "category":"Wholesale",
            "subcategory":"Apparel",
            "type":"Manufacturing & Wholesale Goods"
        }
    ],
    "sg:phone":"+1 201 768 9535",
    "sg:postcode":"07648",
    "sg:province":"NJ",
    "sg:tags":[
        "footwear"
    ],
    "wof:name":"Okabashi Brands Inc",
    "wof:placetype":"venue"
},
  "geometry": {"coordinates":[-73.958637,40.987413],"type":"Point"}
}