{
  "type": "Feature",
  "properties": {
    "iso:country":"US",
    "sg:address":"545 Dowd Ave",
    "sg:city":"Elizabeth",
    "sg:classifiers":[
        {
            "category":"Ferry",
            "type":"Transportation"
        }
    ],
    "sg:phone":"+1 908 629 9300",
    "sg:postcode":"07201",
    "sg:province":"NJ",
    "sg:tags":[
        "company",
        "steamship"
    ],
    "sg:website":"www.apa-intl.com",
    "wof:name":"APA Intl Corp",
    "wof:placetype":"venue"
},
  "geometry": {"coordinates":[-74.187332,40.665863],"type":"Point"}
}