{
  "type": "Feature",
  "properties": {
    "iso:country":"US",
    "sg:address":"51 Us Highway 1",
    "sg:city":"New Brunswick",
    "sg:classifiers":[
        {
            "category":"Restaurant",
            "type":"Food & Drink"
        }
    ],
    "sg:menulink":"http://www.allmenus.com/nj/new-brunswick/106703-on-the-border/menu/",
    "sg:phone":"+1 732 214 9400",
    "sg:postcode":"08901",
    "sg:province":"NJ",
    "sg:tags":[
        "mexican"
    ],
    "wof:name":"On The Border",
    "wof:placetype":"venue"
},
  "geometry": {"coordinates":[-74.42183,40.479652],"type":"Point"}
}