{
  "type": "Feature",
  "properties": {
    "iso:country":"US",
    "sg:address":"524 Eagle Rock Ave",
    "sg:city":"West Orange",
    "sg:classifiers":[
        {
            "category":"Social Services",
            "subcategory":"Child Care",
            "type":"Services"
        }
    ],
    "sg:phone":"+1 973 243 0628",
    "sg:postcode":"07052",
    "sg:province":"NJ",
    "sg:tags":[
        "day"
    ],
    "wof:name":"Childcare ABC Center",
    "wof:placetype":"venue"
},
  "geometry": {"coordinates":[-74.25294599999999,40.805701],"type":"Point"}
}