{
  "type": "Feature",
  "properties": {
    "iso:country":"US",
    "sg:address":"3404 Winder Dr",
    "sg:city":"Bridgewater",
    "sg:classifiers":[
        {
            "category":"Health Services",
            "subcategory":"Health Practitioner",
            "type":"Services"
        }
    ],
    "sg:phone":"+1 908 218 5592",
    "sg:postcode":"08807",
    "sg:province":"NJ",
    "sg:tags":[
        "nurse",
        "registry"
    ],
    "wof:name":"Affiliated Service Providers",
    "wof:placetype":"venue"
},
  "geometry": {"coordinates":[-74.667233,40.580623],"type":"Point"}
}