{
  "type": "Feature",
  "properties": {
    "addr:full":"50 E 31st St Paterson NJ 07514",
    "addr:housenumber":"50",
    "addr:postcode":"07514",
    "addr:street":"E 31St St",
    "iso:country":"US",
    "sg:address":"50 E 31st St",
    "sg:city":"Paterson",
    "sg:classifiers":[
        {
            "category":"Retail",
            "subcategory":"Auto Repair",
            "type":"Services"
        }
    ],
    "sg:phone":"+1 973 278 6226",
    "sg:postcode":"07514",
    "sg:province":"NJ",
    "sg:tags":[
        "body",
        "shop"
    ],
    "wof:name":"Maaco Auto Painting & Bodyworks",
    "wof:placetype":"venue"
},
  "geometry": {"coordinates":[-74.147598,40.922699],"type":"Point"}
}