{
  "type": "Feature",
  "properties": {
    "iso:country":"US",
    "sg:address":"711 E Main St",
    "sg:city":"Bridgewater",
    "sg:classifiers":[
        {
            "category":"Building & Trades",
            "subcategory":"Pest Control",
            "type":"Services"
        }
    ],
    "sg:phone":"+1 908 722 1133",
    "sg:postcode":"08807",
    "sg:province":"NJ",
    "wof:name":"Crystal Pest Control Co",
    "wof:placetype":"venue"
},
  "geometry": {"coordinates":[-74.572208,40.562462],"type":"Point"}
}