{
  "type": "Feature",
  "properties": {
    "iso:country":"US",
    "sg:address":"131 Palisade Rd",
    "sg:city":"Elizabeth",
    "sg:classifiers":[
        {
            "category":"Building & Trades",
            "subcategory":"Construction",
            "type":"Services"
        }
    ],
    "sg:phone":"+1 908 558 7995",
    "sg:postcode":"07208",
    "sg:province":"NJ",
    "sg:tags":[
        "carpentry",
        "contractor"
    ],
    "wof:name":"Fajardo Construction",
    "wof:placetype":"venue"
},
  "geometry": {"coordinates":[-74.240533,40.669429],"type":"Point"}
}