{
  "type": "Feature",
  "properties": {
    "addr:full":"89 Old Church Rd Monroe Township NJ 08831",
    "addr:housenumber":"89",
    "addr:postcode":"08831",
    "addr:street":"Old Church Rd",
    "iso:country":"US",
    "sg:address":"89 Old Church Rd",
    "sg:city":"Monroe Township",
    "sg:classifiers":[
        {
            "category":"Manufacturing",
            "subcategory":"Lumber",
            "type":"Manufacturing & Wholesale Goods"
        }
    ],
    "sg:phone":"+1 609 395 7528",
    "sg:postcode":"08831",
    "sg:province":"NJ",
    "sg:tags":[
        "operation",
        "timber",
        "tract"
    ],
    "wof:name":"Allen Christmas Tree Farm",
    "wof:placetype":"venue"
},
  "geometry": {"coordinates":[-74.463441,40.296224],"type":"Point"}
}