{
  "type": "Feature",
  "properties": {
    "addr:full":"40 Back Neck Rd Bridgeton NJ 08302",
    "addr:housenumber":"40",
    "addr:postcode":"08302",
    "addr:street":"Back Neck Rd",
    "iso:country":"US",
    "sg:address":"40 Back Neck Rd",
    "sg:city":"Bridgeton",
    "sg:classifiers":[
        {
            "category":"Home & Garden",
            "subcategory":"Garden Supply",
            "type":"Retail Goods"
        }
    ],
    "sg:phone":"+1   ",
    "sg:postcode":"08302",
    "sg:province":"NJ",
    "wof:name":"Blew Valley Farm",
    "wof:placetype":"venue"
},
  "geometry": {"coordinates":[-75.22681900000001,39.377737],"type":"Point"}
}