{
  "type": "Feature",
  "properties": {
    "iso:country":"US",
    "sg:address":"16 Marconi Ave",
    "sg:city":"Iselin",
    "sg:classifiers":[
        {
            "category":"Shopping",
            "subcategory":"Crafts & Fabrics",
            "type":"Retail Goods"
        }
    ],
    "sg:phone":"+1 732 283 4768",
    "sg:postcode":"08830",
    "sg:province":"NJ",
    "sg:tags":[
        "indian"
    ],
    "wof:name":"Sari-Emporium Inc",
    "wof:placetype":"venue"
},
  "geometry": {"coordinates":[-74.324544,40.573936],"type":"Point"}
}