{
  "type": "Feature",
  "properties": {
    "iso:country":"US",
    "sg:address":"100 State St",
    "sg:city":"Teaneck",
    "sg:classifiers":[
        {
            "category":"Health Services",
            "subcategory":"Podiatrist",
            "type":"Services"
        }
    ],
    "sg:phone":"+1   ",
    "sg:postcode":"07666",
    "sg:province":"NJ",
    "wof:name":"ARI Sytner Dr",
    "wof:placetype":"venue"
},
  "geometry": {"coordinates":[-74.00394,40.902733],"type":"Point"}
}