{
  "type": "Feature",
  "properties": {
    "addr:full":"20 Park Ave Morristown NJ 07960",
    "addr:housenumber":"20",
    "addr:postcode":"07960",
    "addr:street":"Park Ave",
    "iso:country":"US",
    "sg:address":"20 Park Ave",
    "sg:city":"Morristown",
    "sg:classifiers":[
        {
            "category":"Professional",
            "subcategory":"Lawyer & Legal Services",
            "type":"Services"
        }
    ],
    "sg:phone":"+1 973 267 5200",
    "sg:postcode":"07960",
    "sg:province":"NJ",
    "sg:tags":[
        "attorney"
    ],
    "wof:name":"Gail S Boertzel",
    "wof:placetype":"venue"
},
  "geometry": {"coordinates":[-74.434584,40.795334],"type":"Point"}
}