{
  "type": "Feature",
  "properties": {
    "iso:country":"US",
    "sg:address":"62 Flanders-Bartley Rd",
    "sg:city":"Flanders",
    "sg:classifiers":[
        {
            "category":"Manufacturing",
            "subcategory":"Tools & Machinery",
            "type":"Manufacturing & Wholesale Goods"
        }
    ],
    "sg:phone":"+1 973 927 2828",
    "sg:postcode":"07836",
    "sg:province":"NJ",
    "sg:tags":[
        "physician",
        "surgeon"
    ],
    "wof:name":"DPC Instrument Systems Div",
    "wof:placetype":"venue"
},
  "geometry": {"coordinates":[-74.716144,40.830719],"type":"Point"}
}