{
  "type": "Feature",
  "properties": {
    "iso:country":"US",
    "sg:address":"409 South St",
    "sg:city":"Elizabeth",
    "sg:classifiers":[
        {
            "category":"Shopping",
            "subcategory":"Used Merchandise",
            "type":"Retail Goods"
        },
        {
            "category":"Manufacturing",
            "subcategory":"Motor Vehicles & Parts",
            "type":"Manufacturing & Wholesale Goods"
        }
    ],
    "sg:phone":"+1 908 351 5858",
    "sg:postcode":"07202",
    "sg:province":"NJ",
    "sg:tags":[
        "automobile",
        "wrecker"
    ],
    "wof:name":"Abcar Autowreckers Inc",
    "wof:placetype":"venue"
},
  "geometry": {"coordinates":[-74.209394,40.658091],"type":"Point"}
}