{
  "type": "Feature",
  "properties": {
    "addr:full":"548 Mantua Pike Woodbury NJ 08096",
    "addr:housenumber":"548",
    "addr:postcode":"08096",
    "addr:street":"Mantua Pike",
    "iso:country":"US",
    "sg:address":"548 Mantua Pike",
    "sg:city":"Woodbury",
    "sg:classifiers":[
        {
            "category":"Autos & Motor Vehicles",
            "subcategory":"Fuel & Gas Station",
            "type":"Retail Goods"
        },
        {
            "category":"Autos & Motor Vehicles",
            "subcategory":"Automobile Sales",
            "type":"Retail Goods"
        },
        {
            "category":"Autos & Motor Vehicles",
            "subcategory":"Auto Supplies",
            "type":"Retail Goods"
        },
        {
            "category":"Retail",
            "subcategory":"Auto Repair",
            "type":"Services"
        }
    ],
    "sg:phone":"+1 856 381 0242",
    "sg:postcode":"08096",
    "sg:province":"NJ",
    "sg:tags":[
        "muffler",
        "brake",
        "sport",
        "system",
        "equipment",
        "lube",
        "electrical",
        "equipment-service",
        "performance",
        "racing",
        "wheel",
        "exhaust",
        "oil",
        "accessory",
        "servicing-automotive",
        "balancing",
        "axle",
        "wheels-aligning",
        "alignment-frame",
        "air conditioning",
        "car",
        "truck",
        "inspection"
    ],
    "sg:website":"http://www.tomtracker.com/redirect.cfm?bID=4837&hID=111353",
    "wof:name":"Meineke Car Care Center",
    "wof:placetype":"venue"
},
  "geometry": {"coordinates":[-75.15881899999999,39.828673],"type":"Point"}
}