{
  "type": "Feature",
  "properties": {
    "addr:full":"1310 Doughty Rd Egg Harbor Twp NJ 08234",
    "addr:housenumber":"1310",
    "addr:postcode":"08234",
    "addr:street":"Doughty Rd",
    "iso:country":"US",
    "sg:address":"1310 Doughty Rd",
    "sg:city":"Egg Harbor Twp",
    "sg:classifiers":[
        {
            "category":"Building & Trades",
            "subcategory":"Landscaping Services",
            "type":"Services"
        }
    ],
    "sg:phone":"+1 609 653 2197",
    "sg:postcode":"08234",
    "sg:province":"NJ",
    "sg:tags":[
        "landscape",
        "contractor"
    ],
    "sg:website":"www.freshcutlawncare.com",
    "wof:name":"Freshcut Lawncare & Landscpg",
    "wof:placetype":"venue"
},
  "geometry": {"coordinates":[-74.54123,39.415816],"type":"Point"}
}