{
  "type": "Feature",
  "properties": {
    "iso:country":"US",
    "sg:address":"21 Brookside Ter",
    "sg:city":"Clark",
    "sg:classifiers":[
        {
            "category":"Building & Trades",
            "subcategory":"Construction",
            "type":"Services"
        }
    ],
    "sg:phone":"+1 732 382 3118",
    "sg:postcode":"07066",
    "sg:province":"NJ",
    "sg:tags":[
        "house"
    ],
    "wof:name":"V Firetto Construction Co",
    "wof:placetype":"venue"
},
  "geometry": {"coordinates":[-74.33750499999999,40.608944],"type":"Point"}
}