{
  "type": "Feature",
  "properties": {
    "iso:country":"US",
    "sg:address":"453 State Rt 23",
    "sg:city":"Pompton Plains",
    "sg:classifiers":[
        {
            "category":"Arts & Performance",
            "subcategory":"Arts Center",
            "type":"Entertainment"
        }
    ],
    "sg:phone":"+1 973 839 0099",
    "sg:postcode":"07444",
    "sg:province":"NJ",
    "sg:tags":[
        "performing"
    ],
    "wof:name":"Performing Arts Academy",
    "wof:placetype":"venue"
},
  "geometry": {"coordinates":[-74.285599,40.9674],"type":"Point"}
}