{
  "type": "Feature",
  "properties": {
    "addr:full":"4711 Atlantic Ave Atlantic City NJ 08401",
    "addr:housenumber":"4711",
    "addr:postcode":"08401",
    "addr:street":"Atlantic Ave",
    "iso:country":"US",
    "sg:address":"4711 Atlantic Ave",
    "sg:city":"Atlantic City",
    "sg:classifiers":[
        {
            "category":"Health Services",
            "subcategory":"Doctor",
            "type":"Services"
        }
    ],
    "sg:phone":"+1 609 348 8100",
    "sg:postcode":"08401",
    "sg:province":"NJ",
    "sg:tags":[
        "medical"
    ],
    "wof:name":"Peter C Morse MD",
    "wof:placetype":"venue"
},
  "geometry": {"coordinates":[-74.46543,39.344525],"type":"Point"}
}