{
  "type": "Feature",
  "properties": {
    "addr:full":"1613 State Rte 88 Brick NJ 08724",
    "addr:housenumber":"1613",
    "addr:postcode":"08724",
    "addr:street":"State Rte 88",
    "iso:country":"US",
    "sg:address":"1613 State Rte 88",
    "sg:city":"Brick",
    "sg:classifiers":[
        {
            "category":"Building & Trades",
            "subcategory":"Landscaping Services",
            "type":"Services"
        }
    ],
    "sg:phone":"+1 732 785 3310",
    "sg:postcode":"08724",
    "sg:province":"NJ",
    "sg:tags":[
        "landscape",
        "contractor"
    ],
    "wof:name":"Images Property Mntnc Inc",
    "wof:placetype":"venue"
},
  "geometry": {"coordinates":[-74.136712,40.07826],"type":"Point"}
}