{
  "type": "Feature",
  "properties": {
    "addr:full":"202 Circle Ave Clifton NJ 07011",
    "addr:housenumber":"202",
    "addr:postcode":"07011",
    "addr:street":"Circle Ave",
    "iso:country":"US",
    "sg:address":"202 Circle Ave",
    "sg:city":"Clifton",
    "sg:classifiers":[
        {
            "category":"Wholesale",
            "subcategory":"Vending Machines",
            "type":"Manufacturing & Wholesale Goods"
        }
    ],
    "sg:phone":"+1 973 772 7500",
    "sg:postcode":"07011",
    "sg:province":"NJ",
    "sg:tags":[
        "machines-parts",
        "machines-wholesale",
        "manufacturer",
        "supply"
    ],
    "wof:name":"Avs East",
    "wof:placetype":"venue"
},
  "geometry": {"coordinates":[-74.16158,40.889056],"type":"Point"}
}