{
  "type": "Feature",
  "properties": {
    "addr:full":"123 E Main St Ste 4 Denville NJ 07834",
    "addr:housenumber":"123",
    "addr:postcode":"07834",
    "addr:street":"E Main St Ste 4",
    "iso:country":"US",
    "sg:address":"123 E Main St Ste 4",
    "sg:city":"Denville",
    "sg:classifiers":[
        {
            "category":"Shopping",
            "subcategory":"Pets & Pet Supplies",
            "type":"Retail Goods"
        }
    ],
    "sg:phone":"+1 973 625 2584",
    "sg:postcode":"07834",
    "sg:province":"NJ",
    "sg:tags":[
        "store"
    ],
    "wof:name":"Li'l Critters Aquarium and Pet Center",
    "wof:placetype":"venue"
},
  "geometry": {"coordinates":[-74.48027500000001,40.887488],"type":"Point"}
}