{
  "type": "Feature",
  "properties": {
    "iso:country":"US",
    "sg:address":"119 Engle St",
    "sg:city":"Tenafly",
    "sg:classifiers":[
        {
            "category":"Health Services",
            "subcategory":"Health Practitioner",
            "type":"Services"
        }
    ],
    "sg:phone":"+1 201 871 4366",
    "sg:postcode":"07670",
    "sg:province":"NJ",
    "wof:name":"Womancare",
    "wof:placetype":"venue"
},
  "geometry": {"coordinates":[-73.961535,40.916328],"type":"Point"}
}