{
  "type": "Feature",
  "properties": {
    "iso:country":"US",
    "sg:address":"7024 State Highway 70 N",
    "sg:city":"Pennsauken",
    "sg:classifiers":[
        {
            "category":"Retail",
            "subcategory":"Pet Boarding",
            "type":"Services"
        }
    ],
    "sg:phone":"+1 856 662 9692",
    "sg:postcode":"08110",
    "sg:province":"NJ",
    "sg:tags":[
        "boarding/pet",
        "sitting"
    ],
    "wof:name":"Petco",
    "wof:placetype":"venue"
},
  "geometry": {"coordinates":[-75.066498,39.962002],"type":"Point"}
}