{
  "type": "Feature",
  "properties": {
    "iso:country":"US",
    "sg:address":"99 Saint Andrews Blvd",
    "sg:city":"Clifton",
    "sg:classifiers":[
        {
            "category":"Education",
            "subcategory":"School",
            "type":"Public Place"
        }
    ],
    "sg:phone":"+1 973 470 2411",
    "sg:postcode":"07012",
    "sg:province":"NJ",
    "wof:name":"Clifton Elementary School 14",
    "wof:placetype":"venue"
},
  "geometry": {"coordinates":[-74.164526,40.855243],"type":"Point"}
}