{
  "type": "Feature",
  "properties": {
    "addr:full":"1010 Broad St Newark NJ 07102",
    "addr:housenumber":"1010",
    "addr:postcode":"07102",
    "addr:street":"Broad St",
    "iso:country":"US",
    "sg:address":"1010 Broad St",
    "sg:city":"Newark",
    "sg:classifiers":[
        {
            "category":"Wholesale",
            "subcategory":"Stationery",
            "type":"Manufacturing & Wholesale Goods"
        }
    ],
    "sg:phone":"+1 973 623 2440",
    "sg:postcode":"07102",
    "sg:province":"NJ",
    "sg:tags":[
        "supply"
    ],
    "wof:name":"Universal Stamp & Sty Co",
    "wof:placetype":"venue"
},
  "geometry": {"coordinates":[-74.176761,40.727568],"type":"Point"}
}