{
  "type": "Feature",
  "properties": {
    "addr:full":"907 Main St Belmar NJ 07719",
    "addr:housenumber":"907",
    "addr:postcode":"07719",
    "addr:street":"Main St",
    "iso:country":"US",
    "sg:address":"907 Main St",
    "sg:city":"Belmar",
    "sg:classifiers":[
        {
            "category":"Personal",
            "subcategory":"Beauty Salon",
            "type":"Services"
        }
    ],
    "sg:phone":"+1 732 681 8988",
    "sg:postcode":"07719",
    "sg:province":"NJ",
    "sg:tags":[
        "shop"
    ],
    "wof:name":"Terry's Hair & Nail Place",
    "wof:placetype":"venue"
},
  "geometry": {"coordinates":[-74.025372,40.180224],"type":"Point"}
}