{
  "type": "Feature",
  "properties": {
    "addr:full":"25 S Center St Orange NJ 07050",
    "addr:housenumber":"25",
    "addr:postcode":"07050",
    "addr:street":"S Center St",
    "iso:country":"US",
    "sg:address":"25 S Center St",
    "sg:city":"Orange",
    "sg:classifiers":[
        {
            "category":"Food & Beverages",
            "subcategory":"Meat & Fish",
            "type":"Retail Goods"
        }
    ],
    "sg:phone":"+1   ",
    "sg:postcode":"07050",
    "sg:province":"NJ",
    "wof:name":"Fishland",
    "wof:placetype":"venue"
},
  "geometry": {"coordinates":[-74.228774,40.771454],"type":"Point"}
}