{
  "type": "Feature",
  "properties": {
    "addr:full":"300 Observer Hwy Hoboken NJ 07030",
    "addr:housenumber":"300",
    "addr:postcode":"07030",
    "addr:street":"Observer Hwy",
    "iso:country":"US",
    "sg:address":"300 Observer Hwy",
    "sg:city":"Hoboken",
    "sg:classifiers":[
        {
            "category":"Restaurant",
            "type":"Food & Drink"
        }
    ],
    "sg:phone":"+1 201 418 0600",
    "sg:postcode":"07030",
    "sg:province":"NJ",
    "wof:name":"Positouch Point of Sale Systems",
    "wof:placetype":"venue"
},
  "geometry": {"coordinates":[-74.03608699999999,40.736535],"type":"Point"}
}