{
  "type": "Feature",
  "properties": {
    "addr:full":"222 Burnamwood Dr Mount Laurel NJ 08054",
    "addr:housenumber":"222",
    "addr:postcode":"08054",
    "addr:street":"Burnamwood Dr",
    "iso:country":"US",
    "sg:address":"222 Burnamwood Dr",
    "sg:city":"Mount Laurel",
    "sg:classifiers":[
        {
            "category":"Building & Trades",
            "subcategory":"Landscaping Services",
            "type":"Services"
        }
    ],
    "sg:phone":"+1 856 778 8774",
    "sg:postcode":"08054",
    "sg:province":"NJ",
    "wof:name":"Care and Tree Treemendous Lawn",
    "wof:placetype":"venue"
},
  "geometry": {"coordinates":[-74.880239,39.963333],"type":"Point"}
}