{
  "type": "Feature",
  "properties": {
    "addr:full":"225 West Ave Long Branch NJ 07740",
    "addr:housenumber":"225",
    "addr:postcode":"07740",
    "addr:street":"West Ave",
    "iso:country":"US",
    "sg:address":"225 West Ave",
    "sg:city":"Long Branch",
    "sg:classifiers":[
        {
            "category":"Retail",
            "subcategory":"Auto Repair",
            "type":"Services"
        }
    ],
    "sg:phone":"+1   ",
    "sg:postcode":"07740",
    "sg:province":"NJ",
    "sg:tags":[
        "shop",
        "collision",
        "towing"
    ],
    "wof:name":"Collision Repair By Damiano",
    "wof:placetype":"venue"
},
  "geometry": {"coordinates":[-73.989064,40.297097],"type":"Point"}
}