{
  "type": "Feature",
  "properties": {
    "addr:full":"253 E Washington Ave Washington NJ 07882",
    "addr:housenumber":"253",
    "addr:postcode":"07882",
    "addr:street":"E Washington Ave",
    "iso:country":"US",
    "sg:address":"253 E Washington Ave",
    "sg:city":"Washington",
    "sg:classifiers":[
        {
            "category":"Wholesale",
            "subcategory":"Medical Equipment & Supplies",
            "type":"Manufacturing & Wholesale Goods"
        },
        {
            "category":"Health Services",
            "subcategory":"Hospital",
            "type":"Services"
        }
    ],
    "sg:phone":"+1 908 835 0004",
    "sg:postcode":"07882",
    "sg:province":"NJ",
    "sg:tags":[
        "x-ray",
        "apparatus"
    ],
    "wof:name":"Mci Optonix Limited Liability Company",
    "wof:placetype":"venue"
},
  "geometry": {"coordinates":[-74.97022,40.760511],"type":"Point"}
}