{
  "type": "Feature",
  "properties": {
    "iso:country":"US",
    "sg:address":"1103 Maple Ave",
    "sg:city":"Vineland",
    "sg:classifiers":[
        {
            "category":"Professional",
            "subcategory":"Business Services",
            "type":"Services"
        }
    ],
    "sg:phone":"+1   ",
    "sg:postcode":"08360",
    "sg:province":"NJ",
    "wof:name":"Jr Property Group LLC",
    "wof:placetype":"venue"
},
  "geometry": {"coordinates":[-75.005171,39.493764],"type":"Point"}
}