{
  "type": "Feature",
  "properties": {
    "iso:country":"US",
    "sg:address":"27 Milton Ave",
    "sg:city":"Jersey City",
    "sg:classifiers":[
        {
            "category":"Shopping",
            "subcategory":"Beauty & Cosmetics",
            "type":"Retail Goods"
        }
    ],
    "sg:phone":"+1   ",
    "sg:postcode":"07307",
    "sg:province":"NJ",
    "sg:tags":[
        "supply"
    ],
    "wof:name":"Tinas Beauty Supply Inc",
    "wof:placetype":"venue"
},
  "geometry": {"coordinates":[-74.052853,40.748418],"type":"Point"}
}