{
  "type": "Feature",
  "properties": {
    "iso:country":"US",
    "sg:address":"15 Vaughan Dr",
    "sg:city":"Newark",
    "sg:classifiers":[
        {
            "category":"Professional",
            "subcategory":"Management & Consulting",
            "type":"Services"
        }
    ],
    "sg:phone":"+1   ",
    "sg:postcode":"07103",
    "sg:province":"NJ",
    "wof:name":"Tyron Financial Services",
    "wof:placetype":"venue"
},
  "geometry": {"coordinates":[-74.184034,40.739539],"type":"Point"}
}