{
  "type": "Feature",
  "properties": {
    "iso:country":"US",
    "sg:address":"48 Plz 9",
    "sg:city":"Englishtown",
    "sg:classifiers":[
        {
            "category":"Restaurant",
            "type":"Food & Drink"
        }
    ],
    "sg:phone":"+1   ",
    "sg:postcode":"07726",
    "sg:province":"NJ",
    "sg:tags":[
        "diner"
    ],
    "wof:name":"Manalapan Diner Inc",
    "wof:placetype":"venue"
},
  "geometry": {"coordinates":[-74.303438,40.298601],"type":"Point"}
}