{
  "type": "Feature",
  "properties": {
    "iso:country":"US",
    "sg:address":"24 Blvd A",
    "sg:city":"Elmwood Park",
    "sg:classifiers":[
        {
            "category":"Real Estate",
            "subcategory":"Real Estate Services",
            "type":"Services"
        },
        {
            "category":"Real Estate",
            "subcategory":"Real Estate Operator",
            "type":"Services"
        }
    ],
    "sg:phone":"+1 201 796 3555",
    "sg:postcode":"07407",
    "sg:province":"NJ",
    "sg:tags":[
        "apartment",
        "property",
        "management"
    ],
    "wof:name":"Elmwood Village",
    "wof:placetype":"venue"
},
  "geometry": {"coordinates":[-74.12256600000001,40.91434],"type":"Point"}
}