{
  "type": "Feature",
  "properties": {
    "addr:full":"33 S Broadway Fair Lawn NJ 07410",
    "addr:housenumber":"33",
    "addr:postcode":"07410",
    "addr:street":"S Broadway",
    "iso:country":"US",
    "sg:address":"33 S Broadway",
    "sg:city":"Fair Lawn",
    "sg:classifiers":[
        {
            "category":"Health Services",
            "subcategory":"Medical Lab",
            "type":"Services"
        }
    ],
    "sg:phone":"+1 201 796 8616",
    "sg:postcode":"07410",
    "sg:province":"NJ",
    "sg:tags":[
        "laboratory"
    ],
    "wof:name":"Quest Diagnotics",
    "wof:placetype":"venue"
},
  "geometry": {"coordinates":[-74.094081,40.92051],"type":"Point"}
}