{
  "type": "Feature",
  "properties": {
    "addr:full":"1806 State Rte 71 Spring Lake NJ 07762",
    "addr:housenumber":"1806",
    "addr:postcode":"07762",
    "addr:street":"State Rte 71",
    "iso:country":"US",
    "sg:address":"1806 State Rte 71",
    "sg:city":"Spring Lake",
    "sg:classifiers":[
        {
            "category":"Professional",
            "subcategory":"Accounting & Tax Preparation",
            "type":"Services"
        }
    ],
    "sg:phone":"+1 732 449 0902",
    "sg:postcode":"07762",
    "sg:province":"NJ",
    "sg:tags":[
        "accountant"
    ],
    "wof:name":"Hudy Mc Carthy & Deluca",
    "wof:placetype":"venue"
},
  "geometry": {"coordinates":[-74.035596,40.158252],"type":"Point"}
}