{
  "type": "Feature",
  "properties": {
    "iso:country":"US",
    "sg:address":"910 Kings Hwy",
    "sg:city":"Woodstown",
    "sg:classifiers":[
        {
            "category":"Wholesale",
            "subcategory":"Plants",
            "type":"Manufacturing & Wholesale Goods"
        }
    ],
    "sg:phone":"+1 856 769 2827",
    "sg:postcode":"08098",
    "sg:province":"NJ",
    "sg:tags":[
        "flower",
        "greenhouse"
    ],
    "wof:name":"Larosa Greenhouse LLP",
    "wof:placetype":"venue"
},
  "geometry": {"coordinates":[-75.368683,39.652048],"type":"Point"}
}