{
  "type": "Feature",
  "properties": {
    "iso:country":"US",
    "sg:address":"14 Columbus Pl",
    "sg:city":"Bound Brook",
    "sg:classifiers":[
        {
            "category":"Bars & Pubs",
            "type":"Food & Drink"
        },
        {
            "category":"Restaurant",
            "type":"Food & Drink"
        }
    ],
    "sg:phone":"+1 732 356 0899",
    "sg:postcode":"08805",
    "sg:province":"NJ",
    "sg:tags":[
        "drinking",
        "eating"
    ],
    "wof:name":"Stan's Chitch's Cafe",
    "wof:placetype":"venue"
},
  "geometry": {"coordinates":[-74.53745000000001,40.56153],"type":"Point"}
}