{
  "type": "Feature",
  "properties": {
    "iso:country":"US",
    "sg:address":"80 Bergen Ave",
    "sg:city":"Clifton",
    "sg:classifiers":[
        {
            "category":"Professional",
            "subcategory":"Credit Reporting & Collection",
            "type":"Services"
        }
    ],
    "sg:phone":"+1 973 340 5850",
    "sg:postcode":"07011",
    "sg:province":"NJ",
    "sg:tags":[
        "agency"
    ],
    "wof:name":"Advanced Collections Inc",
    "wof:placetype":"venue"
},
  "geometry": {"coordinates":[-74.13407599999999,40.883212],"type":"Point"}
}