{
  "type": "Feature",
  "properties": {
    "iso:country":"US",
    "sg:address":"35 Ewing Ave",
    "sg:city":"North Arlington",
    "sg:classifiers":[
        {
            "category":"Building & Trades",
            "subcategory":"Construction",
            "type":"Services"
        }
    ],
    "sg:phone":"+1 201 246 0500",
    "sg:postcode":"07031",
    "sg:province":"NJ",
    "sg:tags":[
        "painter"
    ],
    "wof:name":"Ram Maintenance",
    "wof:placetype":"venue"
},
  "geometry": {"coordinates":[-74.11840100000001,40.7952],"type":"Point"}
}