{
  "type": "Feature",
  "properties": {
    "iso:country":"US",
    "sg:address":"354 State St Ste 202",
    "sg:city":"Hackensack",
    "sg:classifiers":[
        {
            "category":"Banks & Credit Unions",
            "subcategory":"Investment Brokerage",
            "type":"Services"
        }
    ],
    "sg:phone":"+1 201 546 7111",
    "sg:postcode":"07601",
    "sg:province":"NJ",
    "sg:tags":[
        "investing"
    ],
    "wof:name":"Fidelis Securities",
    "wof:placetype":"venue"
},
  "geometry": {"coordinates":[-74.041662,40.889673],"type":"Point"}
}