{
  "type": "Feature",
  "properties": {
    "addr:full":"114 Lexington Ave Merchantville NJ 08109",
    "addr:housenumber":"114",
    "addr:postcode":"08109",
    "addr:street":"Lexington Ave",
    "iso:country":"US",
    "sg:address":"114 Lexington Ave",
    "sg:city":"Merchantville",
    "sg:classifiers":[
        {
            "category":"Building & Trades",
            "subcategory":"Plumbing",
            "type":"Services"
        }
    ],
    "sg:phone":"+1 856 662 7779",
    "sg:postcode":"08109",
    "sg:province":"NJ",
    "sg:tags":[
        "contractor"
    ],
    "wof:name":"Volkert Joseph Heating and AC",
    "wof:placetype":"venue"
},
  "geometry": {"coordinates":[-75.057124,39.947923],"type":"Point"}
}