{
  "type": "Feature",
  "properties": {
    "iso:country":"US",
    "sg:address":"202 Hawthorne Ave",
    "sg:city":"Newark",
    "sg:classifiers":[
        {
            "category":"Organizations",
            "subcategory":"Religious Organization",
            "type":"Services"
        }
    ],
    "sg:phone":"+1 973 297 0081",
    "sg:postcode":"07112",
    "sg:province":"NJ",
    "sg:tags":[
        "church"
    ],
    "sg:website":"www.udtministry.org",
    "wof:name":"United Deliverance Tabernacle",
    "wof:placetype":"venue"
},
  "geometry": {"coordinates":[-74.202152,40.715639],"type":"Point"}
}