{
  "type": "Feature",
  "properties": {
    "iso:country":"US",
    "sg:address":"442 Redwood Ave",
    "sg:city":"Woodbury Heights",
    "sg:classifiers":[
        {
            "category":"Building & Trades",
            "subcategory":"Construction",
            "type":"Services"
        }
    ],
    "sg:phone":"+1 856 845 2925",
    "sg:postcode":"08097",
    "sg:province":"NJ",
    "sg:tags":[
        "excavation",
        "contractor"
    ],
    "wof:name":"Roger Macmichael",
    "wof:placetype":"venue"
},
  "geometry": {"coordinates":[-75.15373599999999,39.823368],"type":"Point"}
}