{
  "type": "Feature",
  "properties": {
    "iso:country":"US",
    "sg:address":"314 Washington St",
    "sg:city":"Perth Amboy",
    "sg:classifiers":[
        {
            "category":"Professional",
            "subcategory":"Lawyer & Legal Services",
            "type":"Services"
        }
    ],
    "sg:phone":"+1 732 442 2001",
    "sg:postcode":"08861",
    "sg:province":"NJ",
    "wof:name":"Cameron Jose M Lawyer",
    "wof:placetype":"venue"
},
  "geometry": {"coordinates":[-74.27359800000001,40.5159],"type":"Point"}
}