{
  "type": "Feature",
  "properties": {
    "addr:full":"405 Hurffville Crosskeys Rd Sewell NJ 08080",
    "addr:housenumber":"405",
    "addr:postcode":"08080",
    "addr:street":"Hurffville Crosskeys Rd",
    "iso:country":"US",
    "sg:address":"405 Hurffville Crosskeys Rd",
    "sg:city":"Sewell",
    "sg:classifiers":[
        {
            "category":"Health Services",
            "subcategory":"Clinic",
            "type":"Services"
        },
        {
            "category":"Community Center",
            "type":"Public Place"
        },
        {
            "category":"Health Services",
            "subcategory":"Hospital",
            "type":"Services"
        }
    ],
    "sg:phone":"+1 856 256 7871",
    "sg:postcode":"08080",
    "sg:province":"NJ",
    "sg:tags":[
        "medical"
    ],
    "wof:name":"Kennedy University Hospital",
    "wof:placetype":"venue"
},
  "geometry": {"coordinates":[-75.060266,39.73096],"type":"Point"}
}