{
  "type": "Feature",
  "properties": {
    "addr:full":"8 Baron Ct Englishtown NJ 07726",
    "addr:housenumber":"8",
    "addr:postcode":"07726",
    "addr:street":"Baron Ct",
    "iso:country":"US",
    "sg:address":"8 Baron Ct",
    "sg:city":"Englishtown",
    "sg:classifiers":[
        {
            "category":"Health Services",
            "subcategory":"Medical Lab",
            "type":"Services"
        }
    ],
    "sg:phone":"+1 732 972 7880",
    "sg:postcode":"07726",
    "sg:province":"NJ",
    "sg:tags":[
        "laboratory"
    ],
    "wof:name":"F D Dental Lab Inc",
    "wof:placetype":"venue"
},
  "geometry": {"coordinates":[-74.322146,40.323646],"type":"Point"}
}