{
  "type": "Feature",
  "properties": {
    "addr:full":"1467 W Bay Ave Barnegat NJ 08005",
    "addr:housenumber":"1467",
    "addr:postcode":"08005",
    "addr:street":"W Bay Ave",
    "iso:country":"US",
    "sg:address":"1467 W Bay Ave",
    "sg:city":"Barnegat",
    "sg:classifiers":[
        {
            "category":"Building & Trades",
            "subcategory":"Construction",
            "type":"Services"
        }
    ],
    "sg:phone":"+1 609 698 1801",
    "sg:postcode":"08005",
    "sg:province":"NJ",
    "sg:tags":[
        "heavy",
        "farm",
        "excavation",
        "supply"
    ],
    "wof:name":"Total Building Services LLC",
    "wof:placetype":"venue"
},
  "geometry": {"coordinates":[-74.31366,39.772777],"type":"Point"}
}