{
  "type": "Feature",
  "properties": {
    "iso:country":"US",
    "sg:address":"201 Broadway",
    "sg:city":"Hillsdale",
    "sg:classifiers":[
        {
            "category":"Retail",
            "subcategory":"Veterinary Services",
            "type":"Services"
        }
    ],
    "sg:phone":"+1 201 358 6520",
    "sg:postcode":"07642",
    "sg:province":"NJ",
    "wof:name":"Hillsdale Animal Hospital",
    "wof:placetype":"venue"
},
  "geometry": {"coordinates":[-74.04125999999999,41.006467],"type":"Point"}
}