{
  "type": "Feature",
  "properties": {
    "addr:full":"702 Lyons Ave Irvington NJ 07111",
    "addr:housenumber":"702",
    "addr:postcode":"07111",
    "addr:street":"Lyons Ave",
    "iso:country":"US",
    "sg:address":"702 Lyons Ave",
    "sg:city":"Irvington",
    "sg:classifiers":[
        {
            "category":"Bars & Pubs",
            "type":"Food & Drink"
        },
        {
            "category":"Restaurant",
            "type":"Food & Drink"
        }
    ],
    "sg:phone":"+1 973 375 1221",
    "sg:postcode":"07111",
    "sg:province":"NJ",
    "sg:tags":[
        "drinking"
    ],
    "wof:name":"Marlo's Restaurant & Bar Inc",
    "wof:placetype":"venue"
},
  "geometry": {"coordinates":[-74.232056,40.721003],"type":"Point"}
}