{
  "type": "Feature",
  "properties": {
    "iso:country":"US",
    "sg:address":"105 Ferry St",
    "sg:city":"Newark",
    "sg:classifiers":[
        {
            "category":"Shopping",
            "subcategory":"Computers & Home Electronics",
            "type":"Retail Goods"
        }
    ],
    "sg:phone":"+1   ",
    "sg:postcode":"07105",
    "sg:province":"NJ",
    "wof:name":"Elite Electronics",
    "wof:placetype":"venue"
},
  "geometry": {"coordinates":[-74.16153799999999,40.731153],"type":"Point"}
}