{
  "type": "Feature",
  "properties": {
    "iso:country":"US",
    "sg:address":"53 4th St",
    "sg:city":"Hoboken",
    "sg:classifiers":[
        {
            "category":"Professional",
            "type":"Services"
        }
    ],
    "sg:phone":"+1   ",
    "sg:postcode":"07030",
    "sg:province":"NJ",
    "wof:name":"Nancy Colasurdo",
    "wof:placetype":"venue"
},
  "geometry": {"coordinates":[-74.02887699999999,40.741009],"type":"Point"}
}