{
  "type": "Feature",
  "properties": {
    "iso:country":"US",
    "sg:address":"29th & Dune Dr",
    "sg:city":"Avalon",
    "sg:classifiers":[
        {
            "category":"Real Estate",
            "subcategory":"Real Estate Services",
            "type":"Services"
        },
        {
            "category":"Banks & Credit Unions",
            "subcategory":"Investment Brokerage",
            "type":"Services"
        }
    ],
    "sg:phone":"+1 609 967 7800",
    "sg:postcode":"08202",
    "sg:province":"NJ",
    "sg:tags":[
        "investing",
        "management",
        "property"
    ],
    "wof:name":"A Lewis Purdy Real Estate Inc",
    "wof:placetype":"venue"
},
  "geometry": {"coordinates":[-74.7295,39.0919],"type":"Point"}
}