{
  "type": "Feature",
  "properties": {
    "addr:full":"898 Pioneer Dr Brick NJ 08724",
    "addr:housenumber":"898",
    "addr:postcode":"08724",
    "addr:street":"Pioneer Dr",
    "iso:country":"US",
    "sg:address":"898 Pioneer Dr",
    "sg:city":"Brick",
    "sg:classifiers":[
        {
            "category":"Building & Trades",
            "subcategory":"Construction",
            "type":"Services"
        }
    ],
    "sg:phone":"+1 732 785 2964",
    "sg:postcode":"08724",
    "sg:province":"NJ",
    "sg:tags":[
        "roofing",
        "contractor"
    ],
    "wof:name":"Demartino Construction Inc",
    "wof:placetype":"venue"
},
  "geometry": {"coordinates":[-74.128124,40.11552],"type":"Point"}
}