{
  "type": "Feature",
  "properties": {
    "iso:country":"US",
    "sg:address":"3 Apple Hill Ct",
    "sg:city":"Montvale",
    "sg:classifiers":[
        {
            "category":"Health Services",
            "subcategory":"Doctor",
            "type":"Services"
        }
    ],
    "sg:phone":"+1 201 802 9877",
    "sg:postcode":"07645",
    "sg:province":"NJ",
    "sg:tags":[
        "physician",
        "surgeon"
    ],
    "wof:name":"Mark M Golin MD",
    "wof:placetype":"venue"
},
  "geometry": {"coordinates":[-74.049098,41.060274],"type":"Point"}
}