{
  "type": "Feature",
  "properties": {
    "iso:country":"US",
    "sg:address":"53 Holly Oak Dr",
    "sg:city":"Voorhees",
    "sg:classifiers":[
        {
            "category":"Retail",
            "subcategory":"Animal Services",
            "type":"Services"
        }
    ],
    "sg:phone":"+1 856 772 1900",
    "sg:postcode":"08043",
    "sg:province":"NJ",
    "sg:tags":[
        "pet",
        "boarding",
        "sitting"
    ],
    "wof:name":"Home Alone Pet Svc",
    "wof:placetype":"venue"
},
  "geometry": {"coordinates":[-74.96336599999999,39.857171],"type":"Point"}
}