{
  "type": "Feature",
  "properties": {
    "iso:country":"US",
    "sg:address":"557 Ave A",
    "sg:city":"Bayonne",
    "sg:classifiers":[
        {
            "category":"Professional",
            "type":"Services"
        }
    ],
    "sg:phone":"+1   ",
    "sg:postcode":"07002",
    "sg:province":"NJ",
    "wof:name":"Primos Services Inc",
    "wof:placetype":"venue"
},
  "geometry": {"coordinates":[-74.12447299999999,40.667287],"type":"Point"}
}