{
  "type": "Feature",
  "properties": {
    "addr:full":"41 Jackson Ave Northfield NJ 08225",
    "addr:housenumber":"41",
    "addr:postcode":"08225",
    "addr:street":"Jackson Ave",
    "iso:country":"US",
    "sg:address":"41 Jackson Ave",
    "sg:city":"Northfield",
    "sg:classifiers":[
        {
            "category":"Professional",
            "subcategory":"Business Services",
            "type":"Services"
        }
    ],
    "sg:phone":"+1   ",
    "sg:postcode":"08225",
    "sg:province":"NJ",
    "wof:name":"Karen L Babb Interiors",
    "wof:placetype":"venue"
},
  "geometry": {"coordinates":[-74.544319,39.372935],"type":"Point"}
}