{
  "type": "Feature",
  "properties": {
    "iso:country":"US",
    "sg:address":"1091 Florence Columbus Rd",
    "sg:city":"Bordentown",
    "sg:classifiers":[
        {
            "category":"Farming",
            "subcategory":"Dairy Farm",
            "type":"Manufacturing & Wholesale Goods"
        }
    ],
    "sg:phone":"+1 609 499 0897",
    "sg:postcode":"08505",
    "sg:province":"NJ",
    "wof:name":"Clover Valley Farm Inc",
    "wof:placetype":"venue"
},
  "geometry": {"coordinates":[-74.76890899999999,40.091485],"type":"Point"}
}