{
  "type": "Feature",
  "properties": {
    "iso:country":"US",
    "sg:address":"1500 Broad St",
    "sg:city":"Bloomfield",
    "sg:classifiers":[
        {
            "category":"Organizations",
            "subcategory":"Labor Organization",
            "type":"Services"
        }
    ],
    "sg:phone":"+1 973 338 3777",
    "sg:postcode":"07003",
    "sg:province":"NJ",
    "sg:tags":[
        "union"
    ],
    "wof:name":"Iron Workers Local No 11",
    "wof:placetype":"venue"
},
  "geometry": {"coordinates":[-74.183812,40.840826],"type":"Point"}
}