{
  "type": "Feature",
  "properties": {
    "addr:full":"483 Middlesex Ave Metuchen NJ 08840",
    "addr:housenumber":"483",
    "addr:postcode":"08840",
    "addr:street":"Middlesex Ave",
    "iso:country":"US",
    "sg:address":"483 Middlesex Ave",
    "sg:city":"Metuchen",
    "sg:classifiers":[
        {
            "category":"Organizations",
            "subcategory":"Community Association",
            "type":"Services"
        }
    ],
    "sg:phone":"+1 732 321 9867",
    "sg:postcode":"08840",
    "sg:province":"NJ",
    "sg:tags":[
        "fraternal"
    ],
    "wof:name":"Masonic Lodge",
    "wof:placetype":"venue"
},
  "geometry": {"coordinates":[-74.36188900000001,40.544234],"type":"Point"}
}