{
  "type": "Feature",
  "properties": {
    "addr:full":"47 N Main St Flemington NJ 08822",
    "addr:housenumber":"47",
    "addr:postcode":"08822",
    "addr:street":"N Main St",
    "iso:country":"US",
    "sg:address":"47 N Main St",
    "sg:city":"Flemington",
    "sg:classifiers":[
        {
            "category":"Wholesale",
            "subcategory":"Electrical",
            "type":"Manufacturing & Wholesale Goods"
        }
    ],
    "sg:phone":"+1 908 237 9955",
    "sg:postcode":"08822",
    "sg:province":"NJ",
    "sg:tags":[
        "fixture",
        "lighting",
        "supply"
    ],
    "wof:name":"Billows Elc Sup of Haddon Hts",
    "wof:placetype":"venue"
},
  "geometry": {"coordinates":[-74.86246800000001,40.516112],"type":"Point"}
}