{
  "type": "Feature",
  "properties": {
    "addr:full":"440 Sicomac Ave Wyckoff NJ 07481",
    "addr:housenumber":"440",
    "addr:postcode":"07481",
    "addr:street":"Sicomac Ave",
    "iso:country":"US",
    "sg:address":"440 Sicomac Ave",
    "sg:city":"Wyckoff",
    "sg:classifiers":[
        {
            "category":"Food & Beverages",
            "subcategory":"Fruits & Vegetables",
            "type":"Retail Goods"
        }
    ],
    "sg:phone":"+1 201 891 8316",
    "sg:postcode":"07481",
    "sg:province":"NJ",
    "sg:tags":[
        "produce",
        "grower"
    ],
    "wof:name":"Russell Orchards Inc",
    "wof:placetype":"venue"
},
  "geometry": {"coordinates":[-74.179571,40.989391],"type":"Point"}
}