{
  "type": "Feature",
  "properties": {
    "addr:full":"48 Longview Ave Randolph NJ 07869",
    "addr:housenumber":"48",
    "addr:postcode":"07869",
    "addr:street":"Longview Ave",
    "iso:country":"US",
    "sg:address":"48 Longview Ave",
    "sg:city":"Randolph",
    "sg:classifiers":[
        {
            "category":"Professional",
            "subcategory":"Management & Consulting",
            "type":"Services"
        }
    ],
    "sg:phone":"+1 973 895 5016",
    "sg:postcode":"07869",
    "sg:province":"NJ",
    "sg:tags":[
        "consultant",
        "business"
    ],
    "wof:name":"Cygna Energy Svc",
    "wof:placetype":"venue"
},
  "geometry": {"coordinates":[-74.579937,40.839158],"type":"Point"}
}