{
  "type": "Feature",
  "properties": {
    "iso:country":"US",
    "sg:address":"44 Maple St",
    "sg:city":"Summit",
    "sg:classifiers":[
        {
            "category":"Personal",
            "subcategory":"Nail Salon",
            "type":"Services"
        }
    ],
    "sg:phone":"+1 908 273 0068",
    "sg:postcode":"07901",
    "sg:province":"NJ",
    "wof:name":"Jpm Nails",
    "wof:placetype":"venue"
},
  "geometry": {"coordinates":[-74.358808,40.717093],"type":"Point"}
}