{
  "type": "Feature",
  "properties": {
    "iso:country":"US",
    "sg:address":"31 Dayton St",
    "sg:city":"Elizabeth",
    "sg:classifiers":[
        {
            "category":"Banks & Credit Unions",
            "subcategory":"Bank",
            "type":"Services"
        }
    ],
    "sg:phone":"+1 908 289 2854",
    "sg:postcode":"07202",
    "sg:province":"NJ",
    "sg:tags":[
        "cashing",
        "check"
    ],
    "wof:name":"Mario Mendoza Checking Bus",
    "wof:placetype":"venue"
},
  "geometry": {"coordinates":[-74.232366,40.658319],"type":"Point"}
}