{
  "type": "Feature",
  "properties": {
    "iso:country":"US",
    "sg:address":"165 Dover Chester Rd",
    "sg:city":"Randolph",
    "sg:classifiers":[
        {
            "category":"Personal",
            "subcategory":"Beauty Salon",
            "type":"Services"
        }
    ],
    "sg:phone":"+1   ",
    "sg:postcode":"07869",
    "sg:province":"NJ",
    "sg:tags":[
        "nail"
    ],
    "wof:name":"Festive Fingers",
    "wof:placetype":"venue"
},
  "geometry": {"coordinates":[-74.599024,40.849337],"type":"Point"}
}