{
  "type": "Feature",
  "properties": {
    "addr:full":"422 Ave C Bayonne NJ 07002",
    "addr:housenumber":"422",
    "addr:postcode":"07002",
    "addr:street":"Ave C",
    "iso:country":"US",
    "sg:address":"422 Ave C",
    "sg:city":"Bayonne",
    "sg:classifiers":[
        {
            "category":"Personal",
            "subcategory":"Barber",
            "type":"Services"
        }
    ],
    "sg:phone":"+1 201 437 1398",
    "sg:postcode":"07002",
    "sg:province":"NJ",
    "wof:name":"Flora's Beauty Salon",
    "wof:placetype":"venue"
},
  "geometry": {"coordinates":[-74.123417,40.661556],"type":"Point"}
}