{
  "type": "Feature",
  "properties": {
    "iso:country":"US",
    "sg:address":"101 E Main St",
    "sg:city":"Little Falls",
    "sg:classifiers":[
        {
            "category":"Real Estate",
            "subcategory":"Real Estate Agent",
            "type":"Services"
        }
    ],
    "sg:phone":"+1 973 256 6644",
    "sg:postcode":"07424",
    "sg:province":"NJ",
    "wof:name":"Fairlawn Industries",
    "wof:placetype":"venue"
},
  "geometry": {"coordinates":[-74.22025600000001,40.878421],"type":"Point"}
}