{
  "type": "Feature",
  "properties": {
    "addr:full":"15 Main Ave Elmwood Park NJ 07407",
    "addr:housenumber":"15",
    "addr:postcode":"07407",
    "addr:street":"Main Ave",
    "iso:country":"US",
    "sg:address":"15 Main Ave",
    "sg:city":"Elmwood Park",
    "sg:classifiers":[
        {
            "category":"Building & Trades",
            "subcategory":"Construction",
            "type":"Services"
        }
    ],
    "sg:phone":"+1 201 797 1260",
    "sg:postcode":"07407",
    "sg:province":"NJ",
    "sg:tags":[
        "hanging",
        "contractor"
    ],
    "wof:name":"Veteran Painting",
    "wof:placetype":"venue"
},
  "geometry": {"coordinates":[-74.11441600000001,40.908891],"type":"Point"}
}