{
  "type": "Feature",
  "properties": {
    "iso:country":"US",
    "sg:address":"316 Ann St",
    "sg:city":"Randolph",
    "sg:classifiers":[
        {
            "category":"Professional",
            "subcategory":"Business Services",
            "type":"Services"
        }
    ],
    "sg:phone":"+1 973 659 9494",
    "sg:postcode":"07869",
    "sg:province":"NJ",
    "sg:tags":[
        "transcribing",
        "disc"
    ],
    "wof:name":"Metro Transcripts LLC",
    "wof:placetype":"venue"
},
  "geometry": {"coordinates":[-74.572097,40.874237],"type":"Point"}
}