{
  "type": "Feature",
  "properties": {
    "iso:country":"US",
    "sg:address":"14 Oak Ridge Ave",
    "sg:city":"Summit",
    "sg:classifiers":[
        {
            "category":"Health Services",
            "subcategory":"Doctor",
            "type":"Services"
        }
    ],
    "sg:phone":"+1 973 697 3311",
    "sg:postcode":"07901",
    "sg:province":"NJ",
    "sg:tags":[
        "medicine",
        "internal"
    ],
    "wof:name":"Asokan R MD",
    "wof:placetype":"venue"
},
  "geometry": {"coordinates":[-74.3545,40.7098],"type":"Point"}
}