{
  "type": "Feature",
  "properties": {
    "iso:country":"US",
    "sg:address":"22 Homestead Cir",
    "sg:city":"Marlboro",
    "sg:classifiers":[
        {
            "category":"Professional",
            "subcategory":"Management & Consulting",
            "type":"Services"
        }
    ],
    "sg:phone":"+1 732 536 2066",
    "sg:postcode":"07746",
    "sg:province":"NJ",
    "sg:tags":[
        "consultant"
    ],
    "wof:name":"K F M Associates Inc",
    "wof:placetype":"venue"
},
  "geometry": {"coordinates":[-74.274652,40.312342],"type":"Point"}
}