{
  "type": "Feature",
  "properties": {
    "addr:full":"62 Andrews Ct Freehold NJ 07728",
    "addr:housenumber":"62",
    "addr:postcode":"07728",
    "addr:street":"Andrews Ct",
    "iso:country":"US",
    "sg:address":"62 Andrews Ct",
    "sg:city":"Freehold",
    "sg:classifiers":[
        {
            "category":"Wholesale",
            "subcategory":"Sporting Goods",
            "type":"Manufacturing & Wholesale Goods"
        }
    ],
    "sg:phone":"+1 732 431 2731",
    "sg:postcode":"07728",
    "sg:province":"NJ",
    "sg:tags":[
        "product",
        "pool",
        "swimming"
    ],
    "wof:name":"East Coast Pool Products Inc",
    "wof:placetype":"venue"
},
  "geometry": {"coordinates":[-74.297487,40.21353],"type":"Point"}
}