{
  "type": "Feature",
  "properties": {
    "iso:country":"US",
    "sg:address":"1835 Burnet Ave",
    "sg:city":"Union",
    "sg:classifiers":[
        {
            "category":"Recreation",
            "type":"Entertainment"
        }
    ],
    "sg:phone":"+1 908 964 6786",
    "sg:postcode":"07083",
    "sg:province":"NJ",
    "sg:tags":[
        "parks"
    ],
    "wof:name":"Burnet Industrial Park",
    "wof:placetype":"venue"
},
  "geometry": {"coordinates":[-74.26845899999999,40.715714],"type":"Point"}
}