{
  "type": "Feature",
  "properties": {
    "addr:full":"445 State Rte 12 Flemington NJ 08822",
    "addr:housenumber":"445",
    "addr:postcode":"08822",
    "addr:street":"State Rte 12",
    "iso:country":"US",
    "sg:address":"445 State Rte 12",
    "sg:city":"Flemington",
    "sg:classifiers":[
        {
            "category":"Real Estate",
            "subcategory":"Real Estate Operator",
            "type":"Services"
        }
    ],
    "sg:phone":"+1   ",
    "sg:postcode":"08822",
    "sg:province":"NJ",
    "sg:tags":[
        "building",
        "apartment"
    ],
    "wof:name":"Reiner Apts Inc",
    "wof:placetype":"venue"
},
  "geometry": {"coordinates":[-74.908394,40.506161],"type":"Point"}
}