{
  "type": "Feature",
  "properties": {
    "addr:full":"2546 Nottingham Way Trenton NJ 08619",
    "addr:housenumber":"2546",
    "addr:postcode":"08619",
    "addr:street":"Nottingham Way",
    "iso:country":"US",
    "sg:address":"2546 Nottingham Way",
    "sg:city":"Trenton",
    "sg:classifiers":[
        {
            "category":"Building & Trades",
            "subcategory":"Electrical",
            "type":"Services"
        }
    ],
    "sg:phone":"+1 609 587 0251",
    "sg:postcode":"08619",
    "sg:province":"NJ",
    "sg:tags":[
        "electric",
        "contractor"
    ],
    "wof:name":"Modern Electrical Contractors",
    "wof:placetype":"venue"
},
  "geometry": {"coordinates":[-74.69386900000001,40.234786],"type":"Point"}
}