{
  "type": "Feature",
  "properties": {
    "addr:full":"357 Greenwood Ave Gloucester City NJ 08030",
    "addr:housenumber":"357",
    "addr:postcode":"08030",
    "addr:street":"Greenwood Ave",
    "iso:country":"US",
    "sg:address":"357 Greenwood Ave",
    "sg:city":"Gloucester City",
    "sg:classifiers":[
        {
            "category":"Professional",
            "type":"Services"
        }
    ],
    "sg:phone":"+1 856 742 0134",
    "sg:postcode":"08030",
    "sg:province":"NJ",
    "sg:tags":[
        "establishment"
    ],
    "wof:name":"Managed Benefit Systems",
    "wof:placetype":"venue"
},
  "geometry": {"coordinates":[-75.11035,39.887357],"type":"Point"}
}