{
  "type": "Feature",
  "properties": {
    "addr:full":"2681 Quakerbridge Rd Trenton NJ 08619",
    "addr:housenumber":"2681",
    "addr:postcode":"08619",
    "addr:street":"Quakerbridge Rd",
    "iso:country":"US",
    "sg:address":"2681 Quakerbridge Rd",
    "sg:city":"Trenton",
    "sg:classifiers":[
        {
            "category":"Professional",
            "subcategory":"Lawyer & Legal Services",
            "type":"Services"
        }
    ],
    "sg:phone":"+1   ",
    "sg:postcode":"08619",
    "sg:province":"NJ",
    "sg:tags":[
        "attorney"
    ],
    "wof:name":"Law Offces of Stnley H Needell",
    "wof:placetype":"venue"
},
  "geometry": {"coordinates":[-74.688106,40.237218],"type":"Point"}
}