{
  "type": "Feature",
  "properties": {
    "addr:full":"285 Passaic St Hackensack NJ 07601",
    "addr:housenumber":"285",
    "addr:postcode":"07601",
    "addr:street":"Passaic St",
    "iso:country":"US",
    "sg:address":"285 Passaic St",
    "sg:city":"Hackensack",
    "sg:classifiers":[
        {
            "category":"Personal",
            "type":"Services"
        }
    ],
    "sg:phone":"+1 973 594 4900",
    "sg:postcode":"07601",
    "sg:province":"NJ",
    "sg:tags":[
        "mover"
    ],
    "wof:name":"Prudential Van Lines",
    "wof:placetype":"venue"
},
  "geometry": {"coordinates":[-74.050088,40.895504],"type":"Point"}
}