{
  "type": "Feature",
  "properties": {
    "addr:full":"15 Smull Ave Caldwell NJ 07006",
    "addr:housenumber":"15",
    "addr:postcode":"07006",
    "addr:street":"Smull Ave",
    "iso:country":"US",
    "sg:address":"15 Smull Ave",
    "sg:city":"Caldwell",
    "sg:classifiers":[
        {
            "category":"Professional",
            "subcategory":"Lawyer & Legal Services",
            "type":"Services"
        }
    ],
    "sg:phone":"+1 973 226 1200",
    "sg:postcode":"07006",
    "sg:province":"NJ",
    "sg:tags":[
        "divorce",
        "law",
        "family"
    ],
    "wof:name":"Rochkind Mark",
    "wof:placetype":"venue"
},
  "geometry": {"coordinates":[-74.27562,40.840883],"type":"Point"}
}