{
  "type": "Feature",
  "properties": {
    "iso:country":"US",
    "sg:address":"62 Palmer St",
    "sg:city":"Passaic",
    "sg:classifiers":[
        {
            "category":"Social Services",
            "subcategory":"Child Care",
            "type":"Services"
        }
    ],
    "sg:phone":"+1 973 458 0390",
    "sg:postcode":"07055",
    "sg:province":"NJ",
    "sg:tags":[
        "day"
    ],
    "wof:name":"Debbie L Sturdivant",
    "wof:placetype":"venue"
},
  "geometry": {"coordinates":[-74.1259,40.844867],"type":"Point"}
}