{
  "type": "Feature",
  "properties": {
    "iso:country":"US",
    "sg:address":"10 Craydon St",
    "sg:city":"Morris Plains",
    "sg:classifiers":[
        {
            "category":"Professional",
            "subcategory":"Management & Consulting",
            "type":"Services"
        }
    ],
    "sg:phone":"+1 973 656 9677",
    "sg:postcode":"07950",
    "sg:province":"NJ",
    "sg:tags":[
        "fuel"
    ],
    "wof:name":"E S Research Mgmt",
    "wof:placetype":"venue"
},
  "geometry": {"coordinates":[-74.458179,40.85412],"type":"Point"}
}