{
  "type": "Feature",
  "properties": {
    "iso:country":"US",
    "sg:address":"894 Broadway",
    "sg:city":"Newark",
    "sg:classifiers":[
        {
            "category":"Local Transit",
            "type":"Transportation"
        }
    ],
    "sg:phone":"+1 973 484 9494",
    "sg:postcode":"07104",
    "sg:province":"NJ",
    "sg:tags":[
        "limousine"
    ],
    "sg:website":"www.classicmil.com",
    "wof:name":"Classic Milenio Dispatchin Svc",
    "wof:placetype":"venue"
},
  "geometry": {"coordinates":[-74.15545899999999,40.780082],"type":"Point"}
}