{
  "type": "Feature",
  "properties": {
    "addr:full":"17 Peachtree Ct Mullica Hill NJ 08062",
    "addr:housenumber":"17",
    "addr:postcode":"08062",
    "addr:street":"Peachtree Ct",
    "iso:country":"US",
    "sg:address":"17 Peachtree Ct",
    "sg:city":"Mullica Hill",
    "sg:classifiers":[
        {
            "category":"Shopping",
            "subcategory":"Clothing, Apparel, & Fashions",
            "type":"Retail Goods"
        }
    ],
    "sg:phone":"+1   ",
    "sg:postcode":"08062",
    "sg:province":"NJ",
    "wof:name":"Edge Wear",
    "wof:placetype":"venue"
},
  "geometry": {"coordinates":[-75.22365600000001,39.749202],"type":"Point"}
}