{
  "type": "Feature",
  "properties": {
    "iso:country":"US",
    "sg:address":"310 Hazelwood Ln",
    "sg:city":"Marlton",
    "sg:classifiers":[
        {
            "category":"Health Services",
            "subcategory":"Doctor",
            "type":"Services"
        }
    ],
    "sg:phone":"+1 609 923 7225",
    "sg:postcode":"08053",
    "sg:province":"NJ",
    "sg:tags":[
        "physician",
        "surgeon"
    ],
    "wof:name":"Leonard Garry MD",
    "wof:placetype":"venue"
},
  "geometry": {"coordinates":[-74.91610799999999,39.867163],"type":"Point"}
}