{
  "type": "Feature",
  "properties": {
    "addr:full":"714 Milford Warren Glen Rd Milford NJ 08848",
    "addr:housenumber":"714",
    "addr:postcode":"08848",
    "addr:street":"Milford Warren Glen Rd",
    "iso:country":"US",
    "sg:address":"714 Milford Warren Glen Rd",
    "sg:city":"Milford",
    "sg:classifiers":[
        {
            "category":"Education",
            "subcategory":"School",
            "type":"Public Place"
        }
    ],
    "sg:phone":"+1 908 995 2772",
    "sg:postcode":"08848",
    "sg:province":"NJ",
    "sg:website":"www.hts.k12.nj.us",
    "wof:name":"Holland Twp Board Of Education",
    "wof:placetype":"venue"
},
  "geometry": {"coordinates":[-75.116761,40.596211],"type":"Point"}
}