{
  "type": "Feature",
  "properties": {
    "iso:country":"US",
    "sg:address":"94 Silver Lake Ave",
    "sg:city":"Edison",
    "sg:classifiers":[
        {
            "category":"Shopping",
            "type":"Retail Goods"
        }
    ],
    "sg:phone":"+1   ",
    "sg:postcode":"08817",
    "sg:province":"NJ",
    "sg:tags":[
        "merchandise"
    ],
    "wof:name":"Mfinlaysportinggoodscom",
    "wof:placetype":"venue"
},
  "geometry": {"coordinates":[-74.40065,40.495954],"type":"Point"}
}