{
  "type": "Feature",
  "properties": {
    "iso:country":"US",
    "sg:address":"116 Millburn Ave Ste 211",
    "sg:city":"Millburn",
    "sg:classifiers":[
        {
            "category":"Health Services",
            "subcategory":"Doctor",
            "type":"Services"
        }
    ],
    "sg:phone":"+1 973 467 2500",
    "sg:postcode":"07041",
    "sg:province":"NJ",
    "wof:name":"Rosen Michael MD",
    "wof:placetype":"venue"
},
  "geometry": {"coordinates":[-74.28951000000001,40.72175],"type":"Point"}
}