{
  "type": "Feature",
  "properties": {
    "iso:country":"US",
    "sg:address":"637 Wesley Ave",
    "sg:city":"Ocean City",
    "sg:classifiers":[
        {
            "category":"Travel",
            "subcategory":"Hotels & Motels",
            "type":"Entertainment"
        }
    ],
    "sg:phone":"+1 609 391 9366",
    "sg:postcode":"08226",
    "sg:province":"NJ",
    "sg:tags":[
        "breakfast",
        "accommodation",
        "bed"
    ],
    "sg:website":"www.butterflybreeze.net",
    "wof:name":"Butterfly Breeze B & B",
    "wof:placetype":"venue"
},
  "geometry": {"coordinates":[-74.571528,39.280258],"type":"Point"}
}