{
  "type": "Feature",
  "properties": {
    "addr:full":"199 Heywood Ct Matawan NJ 07747",
    "addr:housenumber":"199",
    "addr:postcode":"07747",
    "addr:street":"Heywood Ct",
    "iso:country":"US",
    "sg:address":"199 Heywood Ct",
    "sg:city":"Matawan",
    "sg:classifiers":[
        {
            "category":"Professional",
            "subcategory":"Management & Consulting",
            "type":"Services"
        }
    ],
    "sg:phone":"+1   ",
    "sg:postcode":"07747",
    "sg:province":"NJ",
    "sg:tags":[
        "specializing",
        "business",
        "general"
    ],
    "wof:name":"Andrex Consulting Services",
    "wof:placetype":"venue"
},
  "geometry": {"coordinates":[-74.25800099999999,40.420918],"type":"Point"}
}