{
  "type": "Feature",
  "properties": {
    "iso:country":"US",
    "sg:address":"256 Main St",
    "sg:city":"Hackettstown",
    "sg:classifiers":[
        {
            "category":"Professional",
            "subcategory":"Lawyer & Legal Services",
            "type":"Services"
        }
    ],
    "sg:phone":"+1 908 852 9260",
    "sg:postcode":"07840",
    "sg:province":"NJ",
    "wof:name":"Robert A Russell",
    "wof:placetype":"venue"
},
  "geometry": {"coordinates":[-74.826598,40.851177],"type":"Point"}
}