{
  "type": "Feature",
  "properties": {
    "iso:country":"US",
    "sg:address":"250 Broadway",
    "sg:city":"Elmwood Park",
    "sg:classifiers":[
        {
            "category":"Home & Garden",
            "subcategory":"Household Appliances",
            "type":"Retail Goods"
        }
    ],
    "sg:phone":"+1   ",
    "sg:postcode":"07407",
    "sg:province":"NJ",
    "sg:tags":[
        "vacuum"
    ],
    "wof:name":"Kirby Vacuum Cleaners",
    "wof:placetype":"venue"
},
  "geometry": {"coordinates":[-74.119226,40.92066],"type":"Point"}
}