{
  "type": "Feature",
  "properties": {
    "addr:full":"80 Market St Kenilworth NJ 07033",
    "addr:housenumber":"80",
    "addr:postcode":"07033",
    "addr:street":"Market St",
    "iso:country":"US",
    "sg:address":"80 Market St",
    "sg:city":"Kenilworth",
    "sg:classifiers":[
        {
            "category":"Banks & Credit Unions",
            "subcategory":"Bank",
            "type":"Services"
        }
    ],
    "sg:phone":"+1 908 620 1069",
    "sg:postcode":"07033",
    "sg:province":"NJ",
    "wof:name":"Bank Of America",
    "wof:placetype":"venue"
},
  "geometry": {"coordinates":[-74.281807,40.675256],"type":"Point"}
}