{
  "type": "Feature",
  "properties": {
    "iso:country":"US",
    "sg:address":"22 Melrose Pl",
    "sg:city":"Montclair",
    "sg:classifiers":[
        {
            "category":"Arts & Performance",
            "subcategory":"Theater",
            "type":"Entertainment"
        }
    ],
    "sg:phone":"+1   ",
    "sg:postcode":"07042",
    "sg:province":"NJ",
    "sg:tags":[
        "musician"
    ],
    "wof:name":"James H McNeely",
    "wof:placetype":"venue"
},
  "geometry": {"coordinates":[-74.222617,40.805724],"type":"Point"}
}