{
  "type": "Feature",
  "properties": {
    "iso:country":"US",
    "sg:address":"711 N Main St",
    "sg:city":"Glassboro",
    "sg:classifiers":[
        {
            "category":"Social Services",
            "type":"Services"
        }
    ],
    "sg:phone":"+1   ",
    "sg:postcode":"08028",
    "sg:province":"NJ",
    "sg:tags":[
        "individual"
    ],
    "wof:name":"Fam Care",
    "wof:placetype":"venue"
},
  "geometry": {"coordinates":[-75.117012,39.71787],"type":"Point"}
}