{
  "type": "Feature",
  "properties": {
    "iso:country":"US",
    "sg:address":"1200 S Clinton Ave",
    "sg:city":"Trenton",
    "sg:classifiers":[
        {
            "category":"Restaurant",
            "type":"Food & Drink"
        }
    ],
    "sg:phone":"+1 609 393 1616",
    "sg:postcode":"08611",
    "sg:province":"NJ",
    "wof:name":"Castillo's Pizzeria-Restaurant",
    "wof:placetype":"venue"
},
  "geometry": {"coordinates":[-74.742683,40.205725],"type":"Point"}
}