{
  "type": "Feature",
  "properties": {
    "iso:country":"US",
    "sg:address":"2827 Westfield Ave",
    "sg:city":"Camden",
    "sg:classifiers":[
        {
            "category":"Health Services",
            "subcategory":"Doctor",
            "type":"Services"
        }
    ],
    "sg:phone":"+1 856 964 6400",
    "sg:postcode":"08105",
    "sg:province":"NJ",
    "sg:tags":[
        "physician",
        "family",
        "medical",
        "practice",
        "surgeons",
        "medicine"
    ],
    "wof:name":"Patel Ashokkumar B MD",
    "wof:placetype":"venue"
},
  "geometry": {"coordinates":[-75.08580000000001,39.947498],"type":"Point"}
}