{
  "type": "Feature",
  "properties": {
    "iso:country":"US",
    "sg:address":"103 Logan Ln",
    "sg:city":"Bridgeport",
    "sg:classifiers":[
        {
            "category":"Building & Trades",
            "subcategory":"Construction",
            "type":"Services"
        }
    ],
    "sg:phone":"+1 856 467 0242",
    "sg:postcode":"08014",
    "sg:province":"NJ",
    "sg:tags":[
        "general",
        "contractor"
    ],
    "wof:name":"BRP Svc",
    "wof:placetype":"venue"
},
  "geometry": {"coordinates":[-75.34902099999999,39.800368],"type":"Point"}
}