{
  "type": "Feature",
  "properties": {
    "addr:full":"403 Bloomfield Dr West Berlin NJ 08091",
    "addr:housenumber":"403",
    "addr:postcode":"08091",
    "addr:street":"Bloomfield Dr",
    "iso:country":"US",
    "sg:address":"403 Bloomfield Dr",
    "sg:city":"West Berlin",
    "sg:classifiers":[
        {
            "category":"Real Estate",
            "subcategory":"Real Estate Operator",
            "type":"Services"
        }
    ],
    "sg:phone":"+1   ",
    "sg:postcode":"08091",
    "sg:province":"NJ",
    "sg:tags":[
        "mobile",
        "home",
        "site"
    ],
    "wof:name":"Executive Motor Home Rentals",
    "wof:placetype":"venue"
},
  "geometry": {"coordinates":[-74.926413,39.814757],"type":"Point"}
}