{
  "type": "Feature",
  "properties": {
    "addr:full":"9 Amackassin Rd Blairstown NJ 07825",
    "addr:housenumber":"9",
    "addr:postcode":"07825",
    "addr:street":"Amackassin Rd",
    "iso:country":"US",
    "sg:address":"9 Amackassin Rd",
    "sg:city":"Blairstown",
    "sg:classifiers":[
        {
            "category":"Insurance",
            "subcategory":"Insurance Agent",
            "type":"Services"
        }
    ],
    "sg:phone":"+1   ",
    "sg:postcode":"07825",
    "sg:province":"NJ",
    "wof:name":"Henry M Bell",
    "wof:placetype":"venue"
},
  "geometry": {"coordinates":[-75.003326,40.986659],"type":"Point"}
}