{
  "type": "Feature",
  "properties": {
    "iso:country":"US",
    "sg:address":"130 Washington Ave",
    "sg:city":"Westwood",
    "sg:classifiers":[
        {
            "category":"Professional",
            "type":"Services"
        }
    ],
    "sg:phone":"+1   ",
    "sg:postcode":"07675",
    "sg:province":"NJ",
    "wof:name":"Bermuda Strokes",
    "wof:placetype":"venue"
},
  "geometry": {"coordinates":[-74.03746,40.992515],"type":"Point"}
}