{
  "type": "Feature",
  "properties": {
    "iso:country":"US",
    "sg:address":"227 Main Ave",
    "sg:city":"Passaic",
    "sg:classifiers":[
        {
            "category":"Restaurant",
            "type":"Food & Drink"
        }
    ],
    "sg:phone":"+1   ",
    "sg:postcode":"07055",
    "sg:province":"NJ",
    "sg:tags":[
        "eating"
    ],
    "wof:name":"Chop Sticks Passaic LLC",
    "wof:placetype":"venue"
},
  "geometry": {"coordinates":[-74.12680899999999,40.846632],"type":"Point"}
}