{
  "type": "Feature",
  "properties": {
    "addr:full":"20 E Main St Ramsey NJ 07446",
    "addr:housenumber":"20",
    "addr:postcode":"07446",
    "addr:street":"E Main St",
    "iso:country":"US",
    "sg:address":"20 E Main St",
    "sg:city":"Ramsey",
    "sg:classifiers":[
        {
            "category":"Home & Garden",
            "subcategory":"Home Furnishings",
            "type":"Retail Goods"
        }
    ],
    "sg:phone":"+1 201 327 4900",
    "sg:postcode":"07446",
    "sg:province":"NJ",
    "sg:tags":[
        "curtain",
        "made",
        "fabric",
        "drapery"
    ],
    "sg:website":"http://www.totalwindowwallfashions.com",
    "wof:name":"Total Window & Wall Fashion",
    "wof:placetype":"venue"
},
  "geometry": {"coordinates":[-74.141554,41.057315],"type":"Point"}
}