{
  "type": "Feature",
  "properties": {
    "iso:country":"US",
    "sg:address":"419 State Rte 31",
    "sg:city":"Washington",
    "sg:classifiers":[
        {
            "category":"Autos & Motor Vehicles",
            "subcategory":"Automobile Sales",
            "type":"Retail Goods"
        }
    ],
    "sg:phone":"+1 908 689 7860",
    "sg:postcode":"07882",
    "sg:province":"NJ",
    "sg:tags":[
        "car",
        "dealer"
    ],
    "wof:name":"Main Autorama",
    "wof:placetype":"venue"
},
  "geometry": {"coordinates":[-74.97550699999999,40.779681],"type":"Point"}
}