{
  "type": "Feature",
  "properties": {
    "addr:full":"300 Lakeside Blvd Hopatcong NJ 07843",
    "addr:housenumber":"300",
    "addr:postcode":"07843",
    "addr:street":"Lakeside Blvd",
    "iso:country":"US",
    "sg:address":"300 Lakeside Blvd",
    "sg:city":"Hopatcong",
    "sg:classifiers":[
        {
            "category":"Restaurant",
            "type":"Food & Drink"
        }
    ],
    "sg:phone":"+1 973 663 1075",
    "sg:postcode":"07843",
    "sg:province":"NJ",
    "wof:name":"Northwood Restaurant & Lounge",
    "wof:placetype":"venue"
},
  "geometry": {"coordinates":[-74.655081,40.932196],"type":"Point"}
}