{
  "type": "Feature",
  "properties": {
    "addr:full":"40 Lincoln Ave Livingston NJ 07039",
    "addr:housenumber":"40",
    "addr:postcode":"07039",
    "addr:street":"Lincoln Ave",
    "iso:country":"US",
    "sg:address":"40 Lincoln Ave",
    "sg:city":"Livingston",
    "sg:classifiers":[
        {
            "category":"Professional",
            "subcategory":"Accounting & Tax Preparation",
            "type":"Services"
        }
    ],
    "sg:phone":"+1 973 992 6886",
    "sg:postcode":"07039",
    "sg:province":"NJ",
    "sg:tags":[
        "accountant"
    ],
    "wof:name":"Bornstein Paul D CPA",
    "wof:placetype":"venue"
},
  "geometry": {"coordinates":[-74.318703,40.800999],"type":"Point"}
}