{
  "type": "Feature",
  "properties": {
    "addr:full":"1080 Stelton Rd Piscataway NJ 08854",
    "addr:housenumber":"1080",
    "addr:postcode":"08854",
    "addr:street":"Stelton Rd",
    "iso:country":"US",
    "sg:address":"1080 Stelton Rd",
    "sg:city":"Piscataway",
    "sg:classifiers":[
        {
            "category":"Real Estate",
            "subcategory":"Real Estate Agent",
            "type":"Services"
        }
    ],
    "sg:phone":"+1   ",
    "sg:postcode":"08854",
    "sg:province":"NJ",
    "sg:tags":[
        "management",
        "commercial",
        "agency"
    ],
    "wof:name":"Ksp Partnership",
    "wof:placetype":"venue"
},
  "geometry": {"coordinates":[-74.427965,40.547053],"type":"Point"}
}