{
  "type": "Feature",
  "properties": {
    "iso:country":"US",
    "sg:address":"525 E Brown St",
    "sg:city":"Trenton",
    "sg:classifiers":[
        {
            "category":"Food & Beverages",
            "subcategory":"Specialty",
            "type":"Retail Goods"
        }
    ],
    "sg:phone":"+1 609 396 5455",
    "sg:postcode":"08610",
    "sg:province":"NJ",
    "sg:tags":[
        "herb"
    ],
    "wof:name":"Terra Mama",
    "wof:placetype":"venue"
},
  "geometry": {"coordinates":[-74.733873,40.207603],"type":"Point"}
}