{
  "type": "Feature",
  "properties": {
    "addr:full":"717 Undercliff Ave Edgewater NJ 07020",
    "addr:housenumber":"717",
    "addr:postcode":"07020",
    "addr:street":"Undercliff Ave",
    "iso:country":"US",
    "sg:address":"717 Undercliff Ave",
    "sg:city":"Edgewater",
    "sg:classifiers":[
        {
            "category":"Professional",
            "subcategory":"Business Services",
            "type":"Services"
        }
    ],
    "sg:phone":"+1   ",
    "sg:postcode":"07020",
    "sg:province":"NJ",
    "wof:name":"Pacific Group Inc",
    "wof:placetype":"venue"
},
  "geometry": {"coordinates":[-73.9716,40.839558],"type":"Point"}
}