{
  "type": "Feature",
  "properties": {
    "iso:country":"US",
    "sg:address":"1628 Oak Tree Rd",
    "sg:city":"Edison",
    "sg:classifiers":[
        {
            "category":"Health Services",
            "subcategory":"Health Practitioner",
            "type":"Services"
        }
    ],
    "sg:phone":"+1 732 494 6192",
    "sg:postcode":"08820",
    "sg:province":"NJ",
    "sg:tags":[
        "therapist",
        "physical"
    ],
    "wof:name":"Nirvana Hypnthrputic Bdy Wks",
    "wof:placetype":"venue"
},
  "geometry": {"coordinates":[-74.33869300000001,40.57301],"type":"Point"}
}