{
  "type": "Feature",
  "properties": {
    "iso:country":"US",
    "sg:address":"45 Boudinot St",
    "sg:city":"Trenton",
    "sg:classifiers":[
        {
            "category":"Building & Trades",
            "subcategory":"Plumbing",
            "type":"Services"
        }
    ],
    "sg:phone":"+1 609 393 4478",
    "sg:postcode":"08618",
    "sg:province":"NJ",
    "sg:tags":[
        "sheet",
        "metal",
        "mfg"
    ],
    "wof:name":"LA Bella Sheet Metal",
    "wof:placetype":"venue"
},
  "geometry": {"coordinates":[-74.78280700000001,40.229409],"type":"Point"}
}