{
  "type": "Feature",
  "properties": {
    "addr:full":"276 Broad Ave Leonia NJ 07605",
    "addr:housenumber":"276",
    "addr:postcode":"07605",
    "addr:street":"Broad Ave",
    "iso:country":"US",
    "sg:address":"276 Broad Ave",
    "sg:city":"Leonia",
    "sg:classifiers":[
        {
            "category":"Freight",
            "type":"Transportation"
        }
    ],
    "sg:phone":"+1 201 592 0289",
    "sg:postcode":"07605",
    "sg:province":"NJ",
    "sg:tags":[
        "trucking"
    ],
    "wof:name":"Zeta Transport Inc",
    "wof:placetype":"venue"
},
  "geometry": {"coordinates":[-73.989227,40.859914],"type":"Point"}
}