{
  "type": "Feature",
  "properties": {
    "addr:full":"39 Lindley Ave Tenafly NJ 07670",
    "addr:housenumber":"39",
    "addr:postcode":"07670",
    "addr:street":"Lindley Ave",
    "iso:country":"US",
    "sg:address":"39 Lindley Ave",
    "sg:city":"Tenafly",
    "sg:classifiers":[
        {
            "category":"Building & Trades",
            "subcategory":"Pest Control",
            "type":"Services"
        }
    ],
    "sg:phone":"+1 201 569 8689",
    "sg:postcode":"07670",
    "sg:province":"NJ",
    "sg:tags":[
        "insecticide"
    ],
    "wof:name":"Pioneer Pest Control",
    "wof:placetype":"venue"
},
  "geometry": {"coordinates":[-73.969893,40.916491],"type":"Point"}
}