{
  "type": "Feature",
  "properties": {
    "iso:country":"US",
    "sg:address":"8 Kenneth Rd",
    "sg:city":"Montclair",
    "sg:classifiers":[
        {
            "category":"Professional",
            "subcategory":"Research",
            "type":"Services"
        }
    ],
    "sg:phone":"+1 973 746 3415",
    "sg:postcode":"07043",
    "sg:province":"NJ",
    "sg:tags":[
        "development",
        "laboratory"
    ],
    "wof:name":"Richard C Brogle Assoc",
    "wof:placetype":"venue"
},
  "geometry": {"coordinates":[-74.192802,40.847364],"type":"Point"}
}