{
  "type": "Feature",
  "properties": {
    "addr:full":"3115 Madison Ave Toms River NJ 08753",
    "addr:housenumber":"3115",
    "addr:postcode":"08753",
    "addr:street":"Madison Ave",
    "iso:country":"US",
    "sg:address":"3115 Madison Ave",
    "sg:city":"Toms River",
    "sg:classifiers":[
        {
            "category":"Professional",
            "subcategory":"Management & Consulting",
            "type":"Services"
        }
    ],
    "sg:phone":"+1   ",
    "sg:postcode":"08753",
    "sg:province":"NJ",
    "sg:tags":[
        "electronics"
    ],
    "wof:name":"Sunshine Electronics",
    "wof:placetype":"venue"
},
  "geometry": {"coordinates":[-74.123237,39.952053],"type":"Point"}
}