{
  "type": "Feature",
  "properties": {
    "addr:full":"6 Rutgers Pl Montclair NJ 07043",
    "addr:housenumber":"6",
    "addr:postcode":"07043",
    "addr:street":"Rutgers Pl",
    "iso:country":"US",
    "sg:address":"6 Rutgers Pl",
    "sg:city":"Montclair",
    "sg:classifiers":[
        {
            "category":"Professional",
            "type":"Services"
        }
    ],
    "sg:phone":"+1 973 744 8489",
    "sg:postcode":"07043",
    "sg:province":"NJ",
    "sg:tags":[
        "arts",
        "artist"
    ],
    "wof:name":"Toni Lyn's Artistry",
    "wof:placetype":"venue"
},
  "geometry": {"coordinates":[-74.18482899999999,40.848559],"type":"Point"}
}