{
  "type": "Feature",
  "properties": {
    "addr:full":"53 Oldwick Rd Oldwick NJ 08889",
    "addr:housenumber":"53",
    "addr:postcode":"08889",
    "addr:street":"Oldwick Rd",
    "iso:country":"US",
    "sg:address":"53 Oldwick Rd",
    "sg:city":"Oldwick",
    "sg:classifiers":[
        {
            "category":"Shopping",
            "subcategory":"Bicycles & Sporting Goods",
            "type":"Retail Goods"
        }
    ],
    "sg:phone":"+1 908 439 2526",
    "sg:postcode":"08889",
    "sg:province":"NJ",
    "sg:tags":[
        "horse",
        "furnishing"
    ],
    "wof:name":"Copper Creek Tack Shop",
    "wof:placetype":"venue"
},
  "geometry": {"coordinates":[-74.762534,40.639796],"type":"Point"}
}