{
  "type": "Feature",
  "properties": {
    "iso:country":"US",
    "sg:address":"639 Mrtn Lthr Kng Jr",
    "sg:city":"Newark",
    "sg:classifiers":[
        {
            "category":"Food & Beverages",
            "subcategory":"Groceries & Convenience Stores",
            "type":"Retail Goods"
        }
    ],
    "sg:phone":"+1 973 242 3313",
    "sg:postcode":"07102",
    "sg:province":"NJ",
    "wof:name":"New Way Inc",
    "wof:placetype":"venue"
},
  "geometry": {"coordinates":[-74.18180099999999,40.731098],"type":"Point"}
}