{
  "type": "Feature",
  "properties": {
    "iso:country":"US",
    "sg:address":"27 W Shore Trl",
    "sg:city":"Sparta",
    "sg:classifiers":[
        {
            "category":"Health Services",
            "subcategory":"Dentist",
            "type":"Services"
        }
    ],
    "sg:phone":"+1 973 512 4647",
    "sg:postcode":"07871",
    "sg:province":"NJ",
    "sg:tags":[
        "dentists-oral",
        "dentists-cosmetic",
        "maxillofacial",
        "denture",
        "dentists-prosthodontists",
        "dentists-endodontists",
        "dentistry",
        "surgery"
    ],
    "sg:website":"http://spartadentist.com",
    "wof:name":"Michael T. Ward, DMD",
    "wof:placetype":"venue"
},
  "geometry": {"coordinates":[-74.642765,41.033202],"type":"Point"}
}