{
  "type": "Feature",
  "properties": {
    "iso:country":"US",
    "sg:address":"83 Morse Lake Rd",
    "sg:city":"Bloomingdale",
    "sg:classifiers":[
        {
            "category":"Building & Trades",
            "subcategory":"Plumbing",
            "type":"Services"
        }
    ],
    "sg:phone":"+1 973 838 3810",
    "sg:postcode":"07403",
    "sg:province":"NJ",
    "sg:tags":[
        "management",
        "energy",
        "system",
        "contractor",
        "heating",
        "conditioning",
        "air"
    ],
    "wof:name":"Commercial Energy Design Inc",
    "wof:placetype":"venue"
},
  "geometry": {"coordinates":[-74.31852499999999,41.021414],"type":"Point"}
}