{
  "type": "Feature",
  "properties": {
    "iso:country":"US",
    "sg:address":"1304 Opdyke Ave",
    "sg:city":"Asbury Park",
    "sg:classifiers":[
        {
            "category":"Building & Trades",
            "subcategory":"Landscaping Services",
            "type":"Services"
        }
    ],
    "sg:phone":"+1 732 774 5117",
    "sg:postcode":"07712",
    "sg:province":"NJ",
    "sg:tags":[
        "lawn",
        "maintenance",
        "grounds"
    ],
    "wof:name":"Cross Cut Lawn Care",
    "wof:placetype":"venue"
},
  "geometry": {"coordinates":[-74.026481,40.232015],"type":"Point"}
}