{
  "type": "Feature",
  "properties": {
    "addr:full":"3 Orange Pl West Orange NJ 07052",
    "addr:housenumber":"3",
    "addr:postcode":"07052",
    "addr:street":"Orange Pl",
    "iso:country":"US",
    "sg:address":"3 Orange Pl",
    "sg:city":"West Orange",
    "sg:classifiers":[
        {
            "category":"Professional",
            "subcategory":"Lawyer & Legal Services",
            "type":"Services"
        }
    ],
    "sg:phone":"+1 973 669 5916",
    "sg:postcode":"07052",
    "sg:province":"NJ",
    "sg:tags":[
        "attorney"
    ],
    "wof:name":"Martinez & Ritorto",
    "wof:placetype":"venue"
},
  "geometry": {"coordinates":[-74.232411,40.792522],"type":"Point"}
}