{
  "type": "Feature",
  "properties": {
    "addr:full":"1989 Delsea Dr Franklinville NJ 08322",
    "addr:housenumber":"1989",
    "addr:postcode":"08322",
    "addr:street":"Delsea Dr",
    "iso:country":"US",
    "sg:address":"1989 Delsea Dr",
    "sg:city":"Franklinville",
    "sg:classifiers":[
        {
            "category":"Building & Trades",
            "subcategory":"Construction",
            "type":"Services"
        }
    ],
    "sg:phone":"+1 856 694 9460",
    "sg:postcode":"08322",
    "sg:province":"NJ",
    "sg:tags":[
        "dry wall",
        "contractor"
    ],
    "sg:website":"www.vikingdrywall.com",
    "wof:name":"Viking Drywall Inc",
    "wof:placetype":"venue"
},
  "geometry": {"coordinates":[-75.07125000000001,39.606775],"type":"Point"}
}