{
  "type": "Feature",
  "properties": {
    "iso:country":"US",
    "sg:address":"601 Frank E Rodgers Blvd S",
    "sg:city":"Harrison",
    "sg:classifiers":[
        {
            "category":"Banks & Credit Unions",
            "subcategory":"Bank",
            "type":"Services"
        }
    ],
    "sg:phone":"+1   ",
    "sg:postcode":"07029",
    "sg:province":"NJ",
    "sg:tags":[
        "federal",
        "savings",
        "institution"
    ],
    "wof:name":"Kearny Federal Saving Bank",
    "wof:placetype":"venue"
},
  "geometry": {"coordinates":[-74.155777,40.740902],"type":"Point"}
}