{
  "type": "Feature",
  "properties": {
    "iso:country":"US",
    "sg:address":"2 N Hill Dr",
    "sg:city":"Mt Holly",
    "sg:classifiers":[
        {
            "category":"Professional",
            "subcategory":"Lawyer & Legal Services",
            "type":"Services"
        }
    ],
    "sg:phone":"+1 609 596 0066",
    "sg:postcode":"08060",
    "sg:province":"NJ",
    "sg:tags":[
        "attorney"
    ],
    "wof:name":"Monteverde Mc Alee Fitzpatrick",
    "wof:placetype":"venue"
},
  "geometry": {"coordinates":[-74.804678,39.982192],"type":"Point"}
}