{
  "type": "Feature",
  "properties": {
    "addr:full":"61 N Maple Ave Ridgewood NJ 07450",
    "addr:housenumber":"61",
    "addr:postcode":"07450",
    "addr:street":"N Maple Ave",
    "iso:country":"US",
    "sg:address":"61 N Maple Ave",
    "sg:city":"Ridgewood",
    "sg:classifiers":[
        {
            "category":"Professional",
            "type":"Services"
        }
    ],
    "sg:phone":"+1 201 444 2019",
    "sg:postcode":"07450",
    "sg:province":"NJ",
    "sg:tags":[
        "establishment"
    ],
    "wof:name":"Valley Emergency Room Assoc",
    "wof:placetype":"venue"
},
  "geometry": {"coordinates":[-74.112692,40.979966],"type":"Point"}
}