{
  "type": "Feature",
  "properties": {
    "iso:country":"US",
    "sg:address":"25 Harding Ave",
    "sg:city":"Edison",
    "sg:classifiers":[
        {
            "category":"Freight",
            "type":"Transportation"
        }
    ],
    "sg:phone":"+1 732 549 6683",
    "sg:postcode":"08820",
    "sg:province":"NJ",
    "sg:tags":[
        "mover"
    ],
    "wof:name":"Sterling Express Moving",
    "wof:placetype":"venue"
},
  "geometry": {"coordinates":[-74.379533,40.569731],"type":"Point"}
}