{
  "type": "Feature",
  "properties": {
    "addr:full":"43 Bowers St Jersey City NJ 07307",
    "addr:housenumber":"43",
    "addr:postcode":"07307",
    "addr:street":"Bowers St",
    "iso:country":"US",
    "sg:address":"43 Bowers St",
    "sg:city":"Jersey City",
    "sg:classifiers":[
        {
            "category":"Building & Trades",
            "subcategory":"Locksmith",
            "type":"Services"
        }
    ],
    "sg:phone":"+1 888 570 1069",
    "sg:postcode":"07307",
    "sg:province":"NJ",
    "sg:tags":[
        "key"
    ],
    "wof:name":"7 Day 24 Hour Emergency Locksmith",
    "wof:placetype":"venue"
},
  "geometry": {"coordinates":[-74.04420399999999,40.745682],"type":"Point"}
}