{
  "type": "Feature",
  "properties": {
    "addr:full":"83 Lackawanna Ave Wallington NJ 07057",
    "addr:housenumber":"83",
    "addr:postcode":"07057",
    "addr:street":"Lackawanna Ave",
    "iso:country":"US",
    "sg:address":"83 Lackawanna Ave",
    "sg:city":"Wallington",
    "sg:classifiers":[
        {
            "category":"Personal",
            "subcategory":"Beauty Salon",
            "type":"Services"
        }
    ],
    "sg:phone":"+1 201 438 9440",
    "sg:postcode":"07057",
    "sg:province":"NJ",
    "sg:tags":[
        "manicuring"
    ],
    "wof:name":"Fancy Fingers",
    "wof:placetype":"venue"
},
  "geometry": {"coordinates":[-74.09928499999999,40.850963],"type":"Point"}
}