{
  "type": "Feature",
  "properties": {
    "addr:full":"723 Livingston St Elizabeth NJ 07201",
    "addr:housenumber":"723",
    "addr:postcode":"07201",
    "addr:street":"Livingston St",
    "iso:country":"US",
    "sg:address":"723 Livingston St",
    "sg:city":"Elizabeth",
    "sg:classifiers":[
        {
            "category":"Restaurant",
            "type":"Food & Drink"
        }
    ],
    "sg:phone":"+1   ",
    "sg:postcode":"07201",
    "sg:province":"NJ",
    "sg:tags":[
        "eating"
    ],
    "wof:name":"Merchant Sub Diego Guerre",
    "wof:placetype":"venue"
},
  "geometry": {"coordinates":[-74.198251,40.660268],"type":"Point"}
}