{
  "type": "Feature",
  "properties": {
    "addr:full":"979 N Black Horse Pike Williamstown NJ 08094",
    "addr:housenumber":"979",
    "addr:postcode":"08094",
    "addr:street":"N Black Horse Pike",
    "iso:country":"US",
    "sg:address":"979 N Black Horse Pike",
    "sg:city":"Williamstown",
    "sg:classifiers":[
        {
            "category":"Health Services",
            "subcategory":"Doctor",
            "type":"Services"
        }
    ],
    "sg:phone":"+1 856 629 5151",
    "sg:postcode":"08094",
    "sg:province":"NJ",
    "wof:name":"Advocare",
    "wof:placetype":"venue"
},
  "geometry": {"coordinates":[-75.002033,39.698229],"type":"Point"}
}