{
  "type": "Feature",
  "properties": {
    "addr:full":"430 State Rte 31 Washington NJ 07882",
    "addr:housenumber":"430",
    "addr:postcode":"07882",
    "addr:street":"State Rte 31",
    "iso:country":"US",
    "sg:address":"430 State Rte 31",
    "sg:city":"Washington",
    "sg:classifiers":[
        {
            "category":"Building & Trades",
            "subcategory":"Electrical",
            "type":"Services"
        }
    ],
    "sg:phone":"+1 908 537 6376",
    "sg:postcode":"07882",
    "sg:province":"NJ",
    "sg:tags":[
        "electrical",
        "contractor"
    ],
    "wof:name":"John L Dorsch",
    "wof:placetype":"venue"
},
  "geometry": {"coordinates":[-74.976196,40.777488],"type":"Point"}
}