{
  "type": "Feature",
  "properties": {
    "addr:full":"1044 US Hwy 22 Mountainside NJ 07092",
    "addr:housenumber":"1044",
    "addr:postcode":"07092",
    "addr:street":"Us Hwy 22",
    "iso:country":"US",
    "sg:address":"1044 US Hwy 22",
    "sg:city":"Mountainside",
    "sg:classifiers":[
        {
            "category":"Education",
            "subcategory":"College",
            "type":"Public Place"
        }
    ],
    "sg:phone":"+1 908 654 7228",
    "sg:postcode":"07092",
    "sg:province":"NJ",
    "sg:tags":[
        "academic",
        "school"
    ],
    "wof:name":"Surviving College Admssns Tst",
    "wof:placetype":"venue"
},
  "geometry": {"coordinates":[-74.337816,40.683948],"type":"Point"}
}