{
  "type": "Feature",
  "properties": {
    "iso:country":"US",
    "sg:address":"339 Spring Ave",
    "sg:city":"Ridgewood",
    "sg:classifiers":[
        {
            "category":"Professional",
            "subcategory":"Management & Consulting",
            "type":"Services"
        }
    ],
    "sg:phone":"+1   ",
    "sg:postcode":"07450",
    "sg:province":"NJ",
    "sg:tags":[
        "business"
    ],
    "wof:name":"Lisa S Sands Consulting LI",
    "wof:placetype":"venue"
},
  "geometry": {"coordinates":[-74.115482,40.974902],"type":"Point"}
}