{
  "type": "Feature",
  "properties": {
    "addr:full":"258 Kearny Ave Kearny NJ 07032",
    "addr:housenumber":"258",
    "addr:postcode":"07032",
    "addr:street":"Kearny Ave",
    "iso:country":"US",
    "sg:address":"258 Kearny Ave",
    "sg:city":"Kearny",
    "sg:classifiers":[
        {
            "category":"Restaurant",
            "type":"Food & Drink"
        }
    ],
    "sg:menulink":"http://www.allmenus.com/nj/kearny/15776-mr-ninos-iii-family-resturant/menu/",
    "sg:phone":"+1 201 991 2333",
    "sg:postcode":"07032",
    "sg:province":"NJ",
    "sg:tags":[
        "italian"
    ],
    "wof:name":"Mr. Nino's III Family Resturant",
    "wof:placetype":"venue"
},
  "geometry": {"coordinates":[-74.151371,40.759935],"type":"Point"}
}