{
  "type": "Feature",
  "properties": {
    "addr:full":"10 Douglas Ct Trenton NJ 08690",
    "addr:housenumber":"10",
    "addr:postcode":"08690",
    "addr:street":"Douglas Ct",
    "iso:country":"US",
    "sg:address":"10 Douglas Ct",
    "sg:city":"Trenton",
    "sg:classifiers":[
        {
            "category":"Personal",
            "type":"Services"
        }
    ],
    "sg:phone":"+1   ",
    "sg:postcode":"08690",
    "sg:province":"NJ",
    "wof:name":"Ram Ips LLC",
    "wof:placetype":"venue"
},
  "geometry": {"coordinates":[-74.657639,40.213007],"type":"Point"}
}