{
  "type": "Feature",
  "properties": {
    "iso:country":"US",
    "sg:address":"426 Birch Pl",
    "sg:city":"Westfield",
    "sg:classifiers":[
        {
            "category":"Professional",
            "subcategory":"Business Services",
            "type":"Services"
        }
    ],
    "sg:phone":"+1   ",
    "sg:postcode":"07090",
    "sg:province":"NJ",
    "wof:name":"Birch Place Partners",
    "wof:placetype":"venue"
},
  "geometry": {"coordinates":[-74.363102,40.648712],"type":"Point"}
}