{
  "type": "Feature",
  "properties": {
    "addr:full":"25 Progress St Edison NJ 08820",
    "addr:housenumber":"25",
    "addr:postcode":"08820",
    "addr:street":"Progress St",
    "iso:country":"US",
    "sg:address":"25 Progress St",
    "sg:city":"Edison",
    "sg:classifiers":[
        {
            "category":"Wholesale",
            "subcategory":"Machinery & Supplies",
            "type":"Manufacturing & Wholesale Goods"
        }
    ],
    "sg:phone":"+1 908 561 8655",
    "sg:postcode":"08820",
    "sg:province":"NJ",
    "sg:tags":[
        "industrial"
    ],
    "wof:name":"A T Industrial Services Inc",
    "wof:placetype":"venue"
},
  "geometry": {"coordinates":[-74.358436,40.600589],"type":"Point"}
}