{
  "type": "Feature",
  "properties": {
    "addr:full":"1907 State Rte 35 Oakhurst NJ 07755",
    "addr:housenumber":"1907",
    "addr:postcode":"07755",
    "addr:street":"State Rte 35",
    "iso:country":"US",
    "sg:address":"1907 State Rte 35",
    "sg:city":"Oakhurst",
    "sg:classifiers":[
        {
            "category":"Health Services",
            "subcategory":"Doctor",
            "type":"Services"
        }
    ],
    "sg:phone":"+1 732 517 1146",
    "sg:postcode":"07755",
    "sg:province":"NJ",
    "sg:tags":[
        "physician",
        "surgeon"
    ],
    "sg:website":"www.shoregastro.com",
    "wof:name":"Shore Gastroenterology Assoc",
    "wof:placetype":"venue"
},
  "geometry": {"coordinates":[-74.0415,40.262841],"type":"Point"}
}