{
  "type": "Feature",
  "properties": {
    "iso:country":"US",
    "sg:address":"529 Bergen Blvd",
    "sg:city":"Ridgefield",
    "sg:classifiers":[
        {
            "category":"Manufacturing",
            "subcategory":"Wood Products",
            "type":"Manufacturing & Wholesale Goods"
        }
    ],
    "sg:phone":"+1 201 943 4090",
    "sg:postcode":"07657",
    "sg:province":"NJ",
    "sg:tags":[
        "mfg"
    ],
    "wof:name":"Barry Woodworking",
    "wof:placetype":"venue"
},
  "geometry": {"coordinates":[-73.996976,40.825149],"type":"Point"}
}