{
  "type": "Feature",
  "properties": {
    "addr:full":"903 Elizabeth Ave Elizabeth NJ 07201",
    "addr:housenumber":"903",
    "addr:postcode":"07201",
    "addr:street":"Elizabeth Ave",
    "iso:country":"US",
    "sg:address":"903 Elizabeth Ave",
    "sg:city":"Elizabeth",
    "sg:classifiers":[
        {
            "category":"Restaurant",
            "type":"Food & Drink"
        }
    ],
    "sg:phone":"+1 908 351 7766",
    "sg:postcode":"07201",
    "sg:province":"NJ",
    "sg:tags":[
        "eating"
    ],
    "wof:name":"Super Restaurant",
    "wof:placetype":"venue"
},
  "geometry": {"coordinates":[-74.205101,40.6595],"type":"Point"}
}