{
  "type": "Feature",
  "properties": {
    "iso:country":"US",
    "sg:address":"1210 Saint Georges Ave",
    "sg:city":"Avenel",
    "sg:classifiers":[
        {
            "category":"Insurance",
            "subcategory":"Insurance Agent",
            "type":"Services"
        }
    ],
    "sg:phone":"+1   ",
    "sg:postcode":"07001",
    "sg:province":"NJ",
    "wof:name":"National Independent Truckers",
    "wof:placetype":"venue"
},
  "geometry": {"coordinates":[-74.293902,40.580804],"type":"Point"}
}