{
  "type": "Feature",
  "properties": {
    "iso:country":"US",
    "sg:address":"63 Elberon Ave",
    "sg:city":"Hawthorne",
    "sg:classifiers":[
        {
            "category":"Professional",
            "type":"Services"
        }
    ],
    "sg:phone":"+1 973 636 7388",
    "sg:postcode":"07506",
    "sg:province":"NJ",
    "sg:tags":[
        "establishment"
    ],
    "wof:name":"Middle America",
    "wof:placetype":"venue"
},
  "geometry": {"coordinates":[-74.157802,40.94293],"type":"Point"}
}