{
  "type": "Feature",
  "properties": {
    "addr:full":"605 Ridge Rd North Arlington NJ 07031",
    "addr:housenumber":"605",
    "addr:postcode":"07031",
    "addr:street":"Ridge Rd North",
    "iso:country":"US",
    "sg:address":"605 Ridge Rd",
    "sg:city":"North Arlington",
    "sg:classifiers":[
        {
            "category":"Building & Trades",
            "subcategory":"Locksmith",
            "type":"Services"
        }
    ],
    "sg:phone":"+1 888 294 4772",
    "sg:postcode":"07031",
    "sg:province":"NJ",
    "sg:tags":[
        "key"
    ],
    "wof:name":"A 1 Emergency Locksmith",
    "wof:placetype":"venue"
},
  "geometry": {"coordinates":[-74.12650600000001,40.798072],"type":"Point"}
}