{
  "type": "Feature",
  "properties": {
    "iso:country":"US",
    "sg:address":"584 State Rte 38",
    "sg:city":"Maple Shade",
    "sg:classifiers":[
        {
            "category":"Restaurant",
            "type":"Food & Drink"
        }
    ],
    "sg:phone":"+1 856 222 1128",
    "sg:postcode":"08052",
    "sg:province":"NJ",
    "wof:name":"Posh Restaurant Inc",
    "wof:placetype":"venue"
},
  "geometry": {"coordinates":[-74.99977,39.941714],"type":"Point"}
}