{
  "type": "Feature",
  "properties": {
    "addr:full":"19 Roosevelt Ave Oak Ridge NJ 07438",
    "addr:housenumber":"19",
    "addr:postcode":"07438",
    "addr:street":"Roosevelt Ave",
    "iso:country":"US",
    "sg:address":"19 Roosevelt Ave",
    "sg:city":"Oak Ridge",
    "sg:classifiers":[
        {
            "category":"Real Estate",
            "subcategory":"Real Estate Agent",
            "type":"Services"
        }
    ],
    "sg:phone":"+1 973 697 9440",
    "sg:postcode":"07438",
    "sg:province":"NJ",
    "sg:tags":[
        "management"
    ],
    "wof:name":"Unilinear Investments Inc",
    "wof:placetype":"venue"
},
  "geometry": {"coordinates":[-74.533295,41.043975],"type":"Point"}
}