{
  "type": "Feature",
  "properties": {
    "iso:country":"US",
    "sg:address":"528 Berlin New Freedom Rd",
    "sg:city":"Berlin",
    "sg:classifiers":[
        {
            "category":"Freight",
            "type":"Transportation"
        }
    ],
    "sg:phone":"+1 856 768 3270",
    "sg:postcode":"08009",
    "sg:province":"NJ",
    "sg:tags":[
        "operator",
        "local",
        "trucking"
    ],
    "wof:name":"R N Trucking",
    "wof:placetype":"venue"
},
  "geometry": {"coordinates":[-74.92891400000001,39.77152],"type":"Point"}
}