{
  "type": "Feature",
  "properties": {
    "iso:country":"US",
    "sg:address":"1310 Ratzer Rd",
    "sg:city":"Wayne",
    "sg:classifiers":[
        {
            "category":"Education",
            "subcategory":"School",
            "type":"Public Place"
        }
    ],
    "sg:phone":"+1 973 633 3160",
    "sg:postcode":"07470",
    "sg:province":"NJ",
    "wof:name":"John F Kennedy School",
    "wof:placetype":"venue"
},
  "geometry": {"coordinates":[-74.221194,40.948153],"type":"Point"}
}