{
  "type": "Feature",
  "properties": {
    "addr:full":"997 Hillcrest Rd Ridgewood NJ 07450",
    "addr:housenumber":"997",
    "addr:postcode":"07450",
    "addr:street":"Hillcrest Rd",
    "iso:country":"US",
    "sg:address":"997 Hillcrest Rd",
    "sg:city":"Ridgewood",
    "sg:classifiers":[
        {
            "category":"Recreation",
            "type":"Entertainment"
        }
    ],
    "sg:phone":"+1 201 445 0403",
    "sg:postcode":"07450",
    "sg:province":"NJ",
    "wof:name":"Purple Canoe Productions Inc",
    "wof:placetype":"venue"
},
  "geometry": {"coordinates":[-74.126397,41.004329],"type":"Point"}
}