{
  "type": "Feature",
  "properties": {
    "addr:full":"249 E Front St Trenton NJ 08611",
    "addr:housenumber":"249",
    "addr:postcode":"08611",
    "addr:street":"E Front St",
    "iso:country":"US",
    "sg:address":"249 E Front St",
    "sg:city":"Trenton",
    "sg:classifiers":[
        {
            "category":"Professional",
            "subcategory":"Credit Reporting & Collection",
            "type":"Services"
        }
    ],
    "sg:phone":"+1 609 599 3257",
    "sg:postcode":"08611",
    "sg:province":"NJ",
    "sg:tags":[
        "agency"
    ],
    "wof:name":"United States Credit Co",
    "wof:placetype":"venue"
},
  "geometry": {"coordinates":[-74.759483,40.219102],"type":"Point"}
}