{
  "type": "Feature",
  "properties": {
    "iso:country":"US",
    "sg:address":"407 Essex St",
    "sg:city":"Millburn",
    "sg:classifiers":[
        {
            "category":"Professional",
            "subcategory":"Business Services",
            "type":"Services"
        }
    ],
    "sg:phone":"+1   ",
    "sg:postcode":"07041",
    "sg:province":"NJ",
    "wof:name":"Professional Appearances Inc",
    "wof:placetype":"venue"
},
  "geometry": {"coordinates":[-74.311986,40.723671],"type":"Point"}
}