{
  "type": "Feature",
  "properties": {
    "iso:country":"US",
    "sg:address":"225 North Ave",
    "sg:city":"Garwood",
    "sg:classifiers":[
        {
            "category":"Shopping",
            "subcategory":"Antiques",
            "type":"Retail Goods"
        }
    ],
    "sg:phone":"+1 908 233 7667",
    "sg:postcode":"07027",
    "sg:province":"NJ",
    "wof:name":"Classic Antiques",
    "wof:placetype":"venue"
},
  "geometry": {"coordinates":[-74.32060199999999,40.653801],"type":"Point"}
}