{
  "type": "Feature",
  "properties": {
    "addr:full":"34 Highland Ave Hazlet NJ 07730",
    "addr:housenumber":"34",
    "addr:postcode":"07730",
    "addr:street":"Highland Ave",
    "iso:country":"US",
    "sg:address":"34 Highland Ave",
    "sg:city":"Hazlet",
    "sg:classifiers":[
        {
            "category":"Wholesale",
            "subcategory":"Electrical",
            "type":"Manufacturing & Wholesale Goods"
        }
    ],
    "sg:phone":"+1 732 739 1212",
    "sg:postcode":"07730",
    "sg:province":"NJ",
    "sg:tags":[
        "alarm",
        "burglar",
        "system"
    ],
    "wof:name":"Zems Security Systems",
    "wof:placetype":"venue"
},
  "geometry": {"coordinates":[-74.18795,40.436838],"type":"Point"}
}