{
  "type": "Feature",
  "properties": {
    "iso:country":"US",
    "sg:address":"519 26th St",
    "sg:city":"Union City",
    "sg:classifiers":[
        {
            "category":"Health Services",
            "subcategory":"Medical Lab",
            "type":"Services"
        }
    ],
    "sg:phone":"+1 201 348 6677",
    "sg:postcode":"07087",
    "sg:province":"NJ",
    "sg:tags":[
        "laboratory"
    ],
    "wof:name":"A & B Dental Lab",
    "wof:placetype":"venue"
},
  "geometry": {"coordinates":[-74.032768,40.7692],"type":"Point"}
}