{
  "type": "Feature",
  "properties": {
    "addr:full":"10 Main Rd Montville NJ 07045",
    "addr:housenumber":"10",
    "addr:postcode":"07045",
    "addr:street":"Main Rd",
    "iso:country":"US",
    "sg:address":"10 Main Rd",
    "sg:city":"Montville",
    "sg:classifiers":[
        {
            "category":"Retail",
            "subcategory":"Repair Shop",
            "type":"Services"
        }
    ],
    "sg:phone":"+1 973 335 7516",
    "sg:postcode":"07045",
    "sg:province":"NJ",
    "sg:tags":[
        "lock",
        "locksmith"
    ],
    "wof:name":"J Eckert Locksmith",
    "wof:placetype":"venue"
},
  "geometry": {"coordinates":[-74.39118499999999,40.912444],"type":"Point"}
}