{
  "type": "Feature",
  "properties": {
    "iso:country":"US",
    "sg:address":"1710 N Olden Avenue Ext",
    "sg:city":"Ewing",
    "sg:classifiers":[
        {
            "category":"Autos & Motor Vehicles",
            "subcategory":"Automobile Sales",
            "type":"Retail Goods"
        },
        {
            "category":"Retail",
            "subcategory":"Auto Repair",
            "type":"Services"
        }
    ],
    "sg:phone":"+1 866 956 1601",
    "sg:postcode":"08638",
    "sg:province":"NJ",
    "sg:tags":[
        "repairing",
        "used",
        "supply",
        "automotive",
        "dealers-used",
        "car",
        "new",
        "cars-wholesale",
        "tune",
        "service-equipment"
    ],
    "sg:website":"http://www.colemankia.com",
    "wof:name":"Coleman Auto Group",
    "wof:placetype":"venue"
},
  "geometry": {"coordinates":[-74.76627000000001,40.246756],"type":"Point"}
}