{
  "type": "Feature",
  "properties": {
    "iso:country":"US",
    "sg:address":"2217 John F Kennedy Blvd",
    "sg:city":"Jersey City",
    "sg:classifiers":[
        {
            "category":"Organizations",
            "subcategory":"Religious Organization",
            "type":"Services"
        }
    ],
    "sg:phone":"+1 201 433 4152",
    "sg:postcode":"07304",
    "sg:province":"NJ",
    "sg:tags":[
        "church"
    ],
    "wof:name":"Our Lady Of Victories Church",
    "wof:placetype":"venue"
},
  "geometry": {"coordinates":[-74.082756,40.714566],"type":"Point"}
}