{
  "type": "Feature",
  "properties": {
    "iso:country":"US",
    "sg:address":"3 Struble Pl",
    "sg:city":"Sussex",
    "sg:classifiers":[
        {
            "category":"Building & Trades",
            "subcategory":"Landscaping Services",
            "type":"Services"
        }
    ],
    "sg:phone":"+1 973 702 1136",
    "sg:postcode":"07461",
    "sg:province":"NJ",
    "sg:tags":[
        "landscape",
        "contractor"
    ],
    "wof:name":"Win Lawn & Landscape Inc",
    "wof:placetype":"venue"
},
  "geometry": {"coordinates":[-74.64662,41.235851],"type":"Point"}
}