{
  "type": "Feature",
  "properties": {
    "addr:full":"384 Long Ave Hillside NJ 07205",
    "addr:housenumber":"384",
    "addr:postcode":"07205",
    "addr:street":"Long Ave",
    "iso:country":"US",
    "sg:address":"384 Long Ave",
    "sg:city":"Hillside",
    "sg:classifiers":[
        {
            "category":"Organizations",
            "subcategory":"Religious Organization",
            "type":"Services"
        }
    ],
    "sg:phone":"+1 908 994 0505",
    "sg:postcode":"07205",
    "sg:province":"NJ",
    "sg:tags":[
        "church"
    ],
    "wof:name":"Jesus Tabernacle AOG",
    "wof:placetype":"venue"
},
  "geometry": {"coordinates":[-74.23721500000001,40.698689],"type":"Point"}
}