{
  "type": "Feature",
  "properties": {
    "iso:country":"US",
    "sg:address":"835 State Rte 17",
    "sg:city":"Ramsey",
    "sg:classifiers":[
        {
            "category":"Shopping",
            "subcategory":"Bicycles & Sporting Goods",
            "type":"Retail Goods"
        }
    ],
    "sg:phone":"+1 201 327 8141",
    "sg:postcode":"07446",
    "sg:province":"NJ",
    "sg:tags":[
        "tackle",
        "equipment",
        "fishing",
        "camping"
    ],
    "wof:name":"Ramsey Outdoor Store Inc",
    "wof:placetype":"venue"
},
  "geometry": {"coordinates":[-74.12742799999999,41.063736],"type":"Point"}
}