{
  "type": "Feature",
  "properties": {
    "iso:country":"US",
    "sg:address":"31 Higgins Ave",
    "sg:city":"Clementon",
    "sg:classifiers":[
        {
            "category":"Government",
            "subcategory":"Office",
            "type":"Public Place"
        }
    ],
    "sg:phone":"+1   ",
    "sg:postcode":"08021",
    "sg:province":"NJ",
    "wof:name":"Jeffrey Mark Richards",
    "wof:placetype":"venue"
},
  "geometry": {"coordinates":[-74.978803,39.806216],"type":"Point"}
}