{
  "type": "Feature",
  "properties": {
    "addr:full":"258 Main St Paterson NJ 07505",
    "addr:housenumber":"258",
    "addr:postcode":"07505",
    "addr:street":"Main St",
    "iso:country":"US",
    "sg:address":"258 Main St",
    "sg:city":"Paterson",
    "sg:classifiers":[
        {
            "category":"Professional",
            "type":"Services"
        },
        {
            "category":"Restaurant",
            "type":"Food & Drink"
        }
    ],
    "sg:phone":"+1 973 684 2800",
    "sg:postcode":"07505",
    "sg:province":"NJ",
    "sg:tags":[
        "establishment"
    ],
    "wof:name":"Chic Chick",
    "wof:placetype":"venue"
},
  "geometry": {"coordinates":[-74.173405,40.91554],"type":"Point"}
}