{
  "type": "Feature",
  "properties": {
    "addr:full":"718 Glenside Dr Mantua NJ 08090",
    "addr:housenumber":"718",
    "addr:postcode":"08090",
    "addr:street":"Glenside Dr",
    "iso:country":"US",
    "sg:address":"718 Glenside Dr",
    "sg:city":"Mantua",
    "sg:classifiers":[
        {
            "category":"Professional",
            "type":"Services"
        }
    ],
    "sg:phone":"+1   ",
    "sg:postcode":"08090",
    "sg:province":"NJ",
    "sg:tags":[
        "musical",
        "composition"
    ],
    "wof:name":"Studiokraft",
    "wof:placetype":"venue"
},
  "geometry": {"coordinates":[-75.166465,39.799361],"type":"Point"}
}