{
  "type": "Feature",
  "properties": {
    "iso:country":"US",
    "sg:address":"75 Griers Ln",
    "sg:city":"Elmer",
    "sg:phone":"+1 856 358 8731",
    "sg:postcode":"08318",
    "sg:province":"NJ",
    "sg:tags":[
        "agricultural",
        "product"
    ],
    "wof:name":"Ivan L Garrison",
    "wof:placetype":"venue"
},
  "geometry": {"coordinates":[-75.211551,39.547146],"type":"Point"}
}