{
  "type": "Feature",
  "properties": {
    "iso:country":"US",
    "sg:address":"1209 State Rte 35",
    "sg:city":"Neptune City",
    "sg:classifiers":[
        {
            "category":"Professional",
            "subcategory":"Business Services",
            "type":"Services"
        }
    ],
    "sg:phone":"+1 732 531 7857",
    "sg:postcode":"07753",
    "sg:province":"NJ",
    "sg:tags":[
        "paging",
        "signaling"
    ],
    "wof:name":"Pager Plus",
    "wof:placetype":"venue"
},
  "geometry": {"coordinates":[-74.02525,40.190187],"type":"Point"}
}