{
  "type": "Feature",
  "properties": {
    "addr:full":"355 State Rte 17 Paramus NJ 07652",
    "addr:housenumber":"355",
    "addr:postcode":"07652",
    "addr:street":"State Rte 17",
    "iso:country":"US",
    "sg:address":"355 State Rte 17",
    "sg:city":"Paramus",
    "sg:classifiers":[
        {
            "category":"Shopping",
            "subcategory":"Gifts & Souvenirs",
            "type":"Retail Goods"
        }
    ],
    "sg:phone":"+1 201 368 1711",
    "sg:postcode":"07652",
    "sg:province":"NJ",
    "sg:tags":[
        "shop"
    ],
    "wof:name":"Amy's Hallmark",
    "wof:placetype":"venue"
},
  "geometry": {"coordinates":[-74.07082699999999,40.910561],"type":"Point"}
}