{
  "type": "Feature",
  "properties": {
    "addr:full":"1274 Kay Dr E Cherry Hill NJ 08034",
    "addr:housenumber":"1274",
    "addr:postcode":"08034",
    "addr:street":"Kay Dr E",
    "iso:country":"US",
    "sg:address":"1274 Kay Dr E",
    "sg:city":"Cherry Hill",
    "sg:classifiers":[
        {
            "category":"Real Estate",
            "subcategory":"Architect",
            "type":"Services"
        }
    ],
    "sg:phone":"+1 856 795 0046",
    "sg:postcode":"08034",
    "sg:province":"NJ",
    "wof:name":"Williamson Design",
    "wof:placetype":"venue"
},
  "geometry": {"coordinates":[-75.005082,39.900629],"type":"Point"}
}