{
  "type": "Feature",
  "properties": {
    "iso:country":"US",
    "sg:address":"4 Carroll Dr",
    "sg:city":"Hillsborough",
    "sg:classifiers":[
        {
            "category":"Professional",
            "subcategory":"Management & Consulting",
            "type":"Services"
        }
    ],
    "sg:phone":"+1   ",
    "sg:postcode":"08844",
    "sg:province":"NJ",
    "sg:tags":[
        "business"
    ],
    "wof:name":"Princeton Somerset Group Inc",
    "wof:placetype":"venue"
},
  "geometry": {"coordinates":[-74.683977,40.546451],"type":"Point"}
}