{
  "type": "Feature",
  "properties": {
    "iso:country":"US",
    "sg:address":"1432 Randolph Ave",
    "sg:city":"Avenel",
    "sg:classifiers":[
        {
            "category":"Manufacturing",
            "subcategory":"Electronics",
            "type":"Manufacturing & Wholesale Goods"
        }
    ],
    "sg:phone":"+1 732 381 0080",
    "sg:postcode":"07001",
    "sg:province":"NJ",
    "sg:tags":[
        "semiconductor",
        "related",
        "devices"
    ],
    "sg:website":"www.chelcogroup.com",
    "wof:name":"Chelco Group Of Co",
    "wof:placetype":"venue"
},
  "geometry": {"coordinates":[-74.25899,40.597363],"type":"Point"}
}