{
  "type": "Feature",
  "properties": {
    "addr:full":"643 Hanford Pl Westfield NJ 07090",
    "addr:housenumber":"643",
    "addr:postcode":"07090",
    "addr:street":"Hanford Pl",
    "iso:country":"US",
    "sg:address":"643 Hanford Pl",
    "sg:city":"Westfield",
    "sg:classifiers":[
        {
            "category":"Health Services",
            "subcategory":"Health Practitioner",
            "type":"Services"
        }
    ],
    "sg:phone":"+1 908 232 7778",
    "sg:postcode":"07090",
    "sg:province":"NJ",
    "wof:name":"Ronald Kelber PHD",
    "wof:placetype":"venue"
},
  "geometry": {"coordinates":[-74.36348700000001,40.653115],"type":"Point"}
}