{
  "type": "Feature",
  "properties": {
    "addr:full":"5 Winchester Ct Matawan NJ 07747",
    "addr:housenumber":"5",
    "addr:postcode":"07747",
    "addr:street":"Winchester Ct",
    "iso:country":"US",
    "sg:address":"5 Winchester Ct",
    "sg:city":"Matawan",
    "sg:classifiers":[
        {
            "category":"Professional",
            "subcategory":"Management & Consulting",
            "type":"Services"
        }
    ],
    "sg:phone":"+1   ",
    "sg:postcode":"07747",
    "sg:province":"NJ",
    "sg:tags":[
        "business"
    ],
    "wof:name":"B P Consulting",
    "wof:placetype":"venue"
},
  "geometry": {"coordinates":[-74.26275800000001,40.401052],"type":"Point"}
}