{
  "type": "Feature",
  "properties": {
    "iso:country":"US",
    "sg:address":"456 Nordhoff Pl",
    "sg:city":"Englewood",
    "sg:classifiers":[
        {
            "category":"Manufacturing",
            "subcategory":"Tools & Machinery",
            "type":"Manufacturing & Wholesale Goods"
        }
    ],
    "sg:phone":"+1 201 569 7300",
    "sg:postcode":"07631",
    "sg:province":"NJ",
    "sg:tags":[
        "fasteners-industrial"
    ],
    "sg:website":"http://www.ccmetal.com",
    "wof:name":"Amershoe Division",
    "wof:placetype":"venue"
},
  "geometry": {"coordinates":[-73.984087,40.881185],"type":"Point"}
}