{
  "type": "Feature",
  "properties": {
    "addr:full":"60 Franklin St Morristown NJ 07960",
    "addr:housenumber":"60",
    "addr:postcode":"07960",
    "addr:street":"Franklin St",
    "iso:country":"US",
    "sg:address":"60 Franklin St",
    "sg:city":"Morristown",
    "sg:classifiers":[
        {
            "category":"Health Services",
            "subcategory":"Doctor",
            "type":"Services"
        }
    ],
    "sg:phone":"+1 973 540 8484",
    "sg:postcode":"07960",
    "sg:province":"NJ",
    "sg:tags":[
        "physician",
        "surgeon"
    ],
    "wof:name":"John S Salaki MD",
    "wof:placetype":"venue"
},
  "geometry": {"coordinates":[-74.470608,40.791611],"type":"Point"}
}