{
  "type": "Feature",
  "properties": {
    "iso:country":"US",
    "sg:address":"3 Coatsbridge Dr",
    "sg:city":"Marlton",
    "sg:classifiers":[
        {
            "category":"Arena",
            "subcategory":"Sports Club",
            "type":"Entertainment"
        }
    ],
    "sg:phone":"+1 856 988 0768",
    "sg:postcode":"08053",
    "sg:province":"NJ",
    "wof:name":"Jake Haverstick Memorial",
    "wof:placetype":"venue"
},
  "geometry": {"coordinates":[-74.91502,39.872378],"type":"Point"}
}