{
  "type": "Feature",
  "properties": {
    "iso:country":"US",
    "sg:address":"78 Columbia Ave",
    "sg:city":"Cliffside Park",
    "sg:classifiers":[
        {
            "category":"Arts & Performance",
            "subcategory":"Theater",
            "type":"Entertainment"
        }
    ],
    "sg:phone":"+1   ",
    "sg:postcode":"07010",
    "sg:province":"NJ",
    "sg:tags":[
        "group"
    ],
    "wof:name":"Untouchable Entertainment",
    "wof:placetype":"venue"
},
  "geometry": {"coordinates":[-73.982113,40.823734],"type":"Point"}
}