{
  "type": "Feature",
  "properties": {
    "iso:country":"US",
    "sg:address":"313 Wedgewood Rd",
    "sg:city":"Morganville",
    "sg:classifiers":[
        {
            "category":"Professional",
            "subcategory":"Computer Services",
            "type":"Services"
        }
    ],
    "sg:phone":"+1   ",
    "sg:postcode":"07751",
    "sg:province":"NJ",
    "sg:tags":[
        "related"
    ],
    "wof:name":"Ashmi Computer Consulting",
    "wof:placetype":"venue"
},
  "geometry": {"coordinates":[-74.221018,40.379604],"type":"Point"}
}