{
  "type": "Feature",
  "properties": {
    "addr:full":"9 Quaint Ln Trenton NJ 08690",
    "addr:housenumber":"9",
    "addr:postcode":"08690",
    "addr:street":"Quaint Ln",
    "iso:country":"US",
    "sg:address":"9 Quaint Ln",
    "sg:city":"Trenton",
    "sg:classifiers":[
        {
            "category":"Banks & Credit Unions",
            "subcategory":"Financial Services",
            "type":"Services"
        }
    ],
    "sg:phone":"+1   ",
    "sg:postcode":"08690",
    "sg:province":"NJ",
    "sg:tags":[
        "investment",
        "closed"
    ],
    "wof:name":"Apollo Investments Inc",
    "wof:placetype":"venue"
},
  "geometry": {"coordinates":[-74.645827,40.216646],"type":"Point"}
}