{
  "type": "Feature",
  "properties": {
    "iso:country":"US",
    "sg:address":"600 Ave A",
    "sg:city":"Phillipsburg",
    "sg:classifiers":[
        {
            "category":"Insurance",
            "subcategory":"Insurance Agent",
            "type":"Services"
        }
    ],
    "sg:phone":"+1   ",
    "sg:postcode":"08865",
    "sg:province":"NJ",
    "sg:tags":[
        "real estate"
    ],
    "wof:name":"Budd Agency Inc",
    "wof:placetype":"venue"
},
  "geometry": {"coordinates":[-75.166698,40.699172],"type":"Point"}
}