{
  "type": "Feature",
  "properties": {
    "iso:country":"US",
    "sg:address":"918 E Clements Bridge Rd",
    "sg:city":"Runnemede",
    "sg:classifiers":[
        {
            "category":"Real Estate",
            "subcategory":"Real Estate Operator",
            "type":"Services"
        }
    ],
    "sg:phone":"+1 856 939 1200",
    "sg:postcode":"08078",
    "sg:province":"NJ",
    "sg:tags":[
        "apartment"
    ],
    "wof:name":"Presidential Court Apartments",
    "wof:placetype":"venue"
},
  "geometry": {"coordinates":[-75.0625,39.8568],"type":"Point"}
}