{
  "type": "Feature",
  "properties": {
    "iso:country":"US",
    "sg:address":"2726 Morris Ave",
    "sg:city":"Union",
    "sg:classifiers":[
        {
            "category":"Building & Trades",
            "subcategory":"Locksmith",
            "type":"Services"
        }
    ],
    "sg:phone":"+1 908 573 0385",
    "sg:postcode":"07083",
    "sg:province":"NJ",
    "sg:tags":[
        "key"
    ],
    "wof:name":"0 0 0 1 Emergency 0 Locksmith",
    "wof:placetype":"venue"
},
  "geometry": {"coordinates":[-74.296329,40.70509],"type":"Point"}
}