{
  "type": "Feature",
  "properties": {
    "addr:full":"505 Raritan Ave Highland Park NJ 08904",
    "addr:housenumber":"505",
    "addr:postcode":"08904",
    "addr:street":"Raritan Ave",
    "iso:country":"US",
    "sg:address":"505 Raritan Ave",
    "sg:city":"Highland Park",
    "sg:classifiers":[
        {
            "category":"Health Services",
            "subcategory":"Doctor",
            "type":"Services"
        }
    ],
    "sg:phone":"+1 732 339 9004",
    "sg:postcode":"08904",
    "sg:province":"NJ",
    "wof:name":"Lieblich Dena G Ltd LLC",
    "wof:placetype":"venue"
},
  "geometry": {"coordinates":[-74.42339800000001,40.500896],"type":"Point"}
}