{
  "type": "Feature",
  "properties": {
    "addr:full":"2 Sheppard Davis Rd Cedarville NJ 08311",
    "addr:housenumber":"2",
    "addr:postcode":"08311",
    "addr:street":"Sheppard Davis Rd",
    "iso:country":"US",
    "sg:address":"2 Sheppard Davis Rd",
    "sg:city":"Cedarville",
    "sg:classifiers":[
        {
            "category":"Social Services",
            "subcategory":"Adult Care",
            "type":"Services"
        }
    ],
    "sg:phone":"+1   ",
    "sg:postcode":"08311",
    "sg:province":"NJ",
    "sg:tags":[
        "residential"
    ],
    "wof:name":"Pats Place",
    "wof:placetype":"venue"
},
  "geometry": {"coordinates":[-75.212615,39.346152],"type":"Point"}
}