{
  "type": "Feature",
  "properties": {
    "addr:full":"151 State Rte 10 Succasunna NJ 07876",
    "addr:housenumber":"151",
    "addr:postcode":"07876",
    "addr:street":"State Rte 10",
    "iso:country":"US",
    "sg:address":"151 State Rte 10",
    "sg:city":"Succasunna",
    "sg:classifiers":[
        {
            "category":"Professional",
            "subcategory":"Lawyer & Legal Services",
            "type":"Services"
        }
    ],
    "sg:phone":"+1 973 598 1680",
    "sg:postcode":"07876",
    "sg:province":"NJ",
    "sg:tags":[
        "attorney"
    ],
    "wof:name":"Richard Kesselman LLC",
    "wof:placetype":"venue"
},
  "geometry": {"coordinates":[-74.638666,40.866868],"type":"Point"}
}