{
  "type": "Feature",
  "properties": {
    "iso:country":"US",
    "sg:address":"901 White Horse Pike",
    "sg:city":"Haddon Twp",
    "sg:classifiers":[
        {
            "category":"Restaurant",
            "type":"Food & Drink"
        }
    ],
    "sg:phone":"+1 856 858 1810",
    "sg:postcode":"08107",
    "sg:province":"NJ",
    "wof:name":"Leonetti's Pizzeria",
    "wof:placetype":"venue"
},
  "geometry": {"coordinates":[-75.07480700000001,39.899743],"type":"Point"}
}