{
  "type": "Feature",
  "properties": {
    "iso:country":"US",
    "sg:address":"95 Palsa Ave",
    "sg:city":"Elmwood Park",
    "sg:classifiers":[
        {
            "category":"Organizations",
            "subcategory":"Religious Organization",
            "type":"Services"
        }
    ],
    "sg:phone":"+1 201 794 1828",
    "sg:postcode":"07407",
    "sg:province":"NJ",
    "wof:name":"Roman Santos Rev",
    "wof:placetype":"venue"
},
  "geometry": {"coordinates":[-74.122803,40.895599],"type":"Point"}
}