{
  "type": "Feature",
  "properties": {
    "iso:country":"US",
    "sg:address":"99 Kingwood Stockton Rd",
    "sg:city":"Rosemont",
    "sg:classifiers":[
        {
            "category":"Insurance",
            "subcategory":"Insurance Agent",
            "type":"Services"
        }
    ],
    "sg:phone":"+1 609 397 7400",
    "sg:postcode":"08559",
    "sg:province":"NJ",
    "wof:name":"Brokerage Consulting",
    "wof:placetype":"venue"
},
  "geometry": {"coordinates":[-74.990043,40.427469],"type":"Point"}
}