{
  "type": "Feature",
  "properties": {
    "iso:country":"US",
    "sg:address":"623 Newman Springs Rd",
    "sg:city":"Lincroft",
    "sg:classifiers":[
        {
            "category":"Restaurant",
            "type":"Food & Drink"
        }
    ],
    "sg:menulink":"http://www.allmenus.com/nj/middletown/282072-manow-asian-bistro/menu/",
    "sg:phone":"+1 732 933 1688",
    "sg:postcode":"07738",
    "sg:province":"NJ",
    "sg:tags":[
        "thai",
        "asian"
    ],
    "wof:name":"MANOW ASIAN BISTRO",
    "wof:placetype":"venue"
},
  "geometry": {"coordinates":[-74.11862499999999,40.330986],"type":"Point"}
}