{
  "type": "Feature",
  "properties": {
    "addr:full":"515 State Route 27 Iselin NJ 08830",
    "addr:housenumber":"515",
    "addr:postcode":"08830",
    "addr:street":"State Route 27",
    "iso:country":"US",
    "sg:address":"515 State Route 27",
    "sg:city":"Iselin",
    "sg:classifiers":[
        {
            "category":"Health Services",
            "subcategory":"Doctor",
            "type":"Services"
        }
    ],
    "sg:phone":"+1 732 283 3850",
    "sg:postcode":"08830",
    "sg:province":"NJ",
    "sg:tags":[
        "obstetrician",
        "gynecologist"
    ],
    "wof:name":"Ghanekar R MD",
    "wof:placetype":"venue"
},
  "geometry": {"coordinates":[-74.317802,40.575699],"type":"Point"}
}