{
  "type": "Feature",
  "properties": {
    "iso:country":"US",
    "sg:address":"39 Main St",
    "sg:city":"Succasunna",
    "sg:classifiers":[
        {
            "category":"Personal",
            "subcategory":"Barber",
            "type":"Services"
        }
    ],
    "sg:phone":"+1 973 584 9070",
    "sg:postcode":"07876",
    "sg:province":"NJ",
    "sg:tags":[
        "shop"
    ],
    "wof:name":"Mike's Barber Shop",
    "wof:placetype":"venue"
},
  "geometry": {"coordinates":[-74.633477,40.86538],"type":"Point"}
}