{
  "type": "Feature",
  "properties": {
    "addr:full":"34 Sylvan Ter Wayne NJ 07470",
    "addr:housenumber":"34",
    "addr:postcode":"07470",
    "addr:street":"Sylvan Ter",
    "iso:country":"US",
    "sg:address":"34 Sylvan Ter",
    "sg:city":"Wayne",
    "sg:classifiers":[
        {
            "category":"Professional",
            "subcategory":"Engineering",
            "type":"Services"
        }
    ],
    "sg:phone":"+1   ",
    "sg:postcode":"07470",
    "sg:province":"NJ",
    "wof:name":"Amar - Construction Enginering",
    "wof:placetype":"venue"
},
  "geometry": {"coordinates":[-74.23156299999999,40.933273],"type":"Point"}
}