{
  "type": "Feature",
  "properties": {
    "addr:full":"12 Patton Dr Sayreville NJ 08872",
    "addr:housenumber":"12",
    "addr:postcode":"08872",
    "addr:street":"Patton Dr",
    "iso:country":"US",
    "sg:address":"12 Patton Dr",
    "sg:city":"Sayreville",
    "sg:classifiers":[
        {
            "category":"Utilities",
            "type":"Services"
        }
    ],
    "sg:phone":"+1 732 651 0810",
    "sg:postcode":"08872",
    "sg:province":"NJ",
    "sg:tags":[
        "sanitary"
    ],
    "wof:name":"Alpine Plowing Inc",
    "wof:placetype":"venue"
},
  "geometry": {"coordinates":[-74.36603599999999,40.460272],"type":"Point"}
}