{
  "type": "Feature",
  "properties": {
    "iso:country":"US",
    "sg:address":"15 S Orange Ave",
    "sg:city":"South Orange",
    "sg:classifiers":[
        {
            "category":"Real Estate",
            "subcategory":"Real Estate Agent",
            "type":"Services"
        }
    ],
    "sg:phone":"+1 973 762 0401",
    "sg:postcode":"07079",
    "sg:province":"NJ",
    "wof:name":"Joseph E Flood Realtors",
    "wof:placetype":"venue"
},
  "geometry": {"coordinates":[-74.25989,40.746429],"type":"Point"}
}