{
  "type": "Feature",
  "properties": {
    "addr:full":"35 Green Ln Succasunna NJ 07876",
    "addr:housenumber":"35",
    "addr:postcode":"07876",
    "addr:street":"Green Ln",
    "iso:country":"US",
    "sg:address":"35 Green Ln",
    "sg:city":"Succasunna",
    "sg:classifiers":[
        {
            "category":"Recreation",
            "type":"Entertainment"
        }
    ],
    "sg:phone":"+1 973 584 3287",
    "sg:postcode":"07876",
    "sg:province":"NJ",
    "sg:tags":[
        "club",
        "membership"
    ],
    "wof:name":"Shongum Club",
    "wof:placetype":"venue"
},
  "geometry": {"coordinates":[-74.62499099999999,40.868998],"type":"Point"}
}