{
  "type": "Feature",
  "properties": {
    "addr:full":"977 Valley Rd Ste 25 Gillette NJ 07933",
    "addr:housenumber":"977",
    "addr:postcode":"07933",
    "addr:street":"Valley Rd Ste 25",
    "iso:country":"US",
    "sg:address":"977 Valley Rd Ste 25",
    "sg:city":"Gillette",
    "sg:classifiers":[
        {
            "category":"Shopping",
            "subcategory":"Mobile Phones",
            "type":"Retail Goods"
        }
    ],
    "sg:phone":"+1 908 647 3606",
    "sg:postcode":"07933",
    "sg:province":"NJ",
    "sg:website":"www.radioshack.com",
    "wof:name":"Radioshack",
    "wof:placetype":"venue"
},
  "geometry": {"coordinates":[-74.476439,40.670754],"type":"Point"}
}