{
  "type": "Feature",
  "properties": {
    "addr:full":"202 Easton Ave New Brunswick NJ 08901",
    "addr:housenumber":"202",
    "addr:postcode":"08901",
    "addr:street":"Easton Ave",
    "iso:country":"US",
    "sg:address":"202 Easton Ave",
    "sg:city":"New Brunswick",
    "sg:classifiers":[
        {
            "category":"Deli",
            "type":"Food & Drink"
        },
        {
            "category":"Restaurant",
            "type":"Food & Drink"
        }
    ],
    "sg:menulink":"http://www.allmenus.com/nj/new-brunswick/254085-knights-deli/menu/",
    "sg:phone":"+1 732 846 1140",
    "sg:postcode":"08901",
    "sg:province":"NJ",
    "sg:tags":[
        "deli",
        "american",
        "sandwich",
        "salad"
    ],
    "wof:name":"Knight's Deli",
    "wof:placetype":"venue"
},
  "geometry": {"coordinates":[-74.45587,40.500533],"type":"Point"}
}