{
  "type": "Feature",
  "properties": {
    "addr:full":"25 Holly St Lakewood NJ 08701",
    "addr:housenumber":"25",
    "addr:postcode":"08701",
    "addr:street":"Holly St",
    "iso:country":"US",
    "sg:address":"25 Holly St",
    "sg:city":"Lakewood",
    "sg:classifiers":[
        {
            "category":"Retail",
            "subcategory":"Auto Repair",
            "type":"Services"
        }
    ],
    "sg:phone":"+1 732 367 0800",
    "sg:postcode":"08701",
    "sg:province":"NJ",
    "sg:tags":[
        "body",
        "automotive",
        "shop"
    ],
    "wof:name":"Sunshine Auto Body",
    "wof:placetype":"venue"
},
  "geometry": {"coordinates":[-74.198267,40.091573],"type":"Point"}
}