{
  "type": "Feature",
  "properties": {
    "addr:full":"1998 Valley Ave Scotch Plains NJ 07076",
    "addr:housenumber":"1998",
    "addr:postcode":"07076",
    "addr:street":"Valley Ave",
    "iso:country":"US",
    "sg:address":"1998 Valley Ave",
    "sg:city":"Scotch Plains",
    "sg:classifiers":[
        {
            "category":"Building & Trades",
            "subcategory":"Construction",
            "type":"Services"
        }
    ],
    "sg:phone":"+1 908 322 5106",
    "sg:postcode":"07076",
    "sg:province":"NJ",
    "sg:tags":[
        "contractor"
    ],
    "wof:name":"Dimonte Silvano Mason Contr",
    "wof:placetype":"venue"
},
  "geometry": {"coordinates":[-74.399845,40.655682],"type":"Point"}
}