{
  "type": "Feature",
  "properties": {
    "addr:full":"1123 Whitebridge Rd Millington NJ 07946",
    "addr:housenumber":"1123",
    "addr:postcode":"07946",
    "addr:street":"Whitebridge Rd",
    "iso:country":"US",
    "sg:address":"1123 Whitebridge Rd",
    "sg:city":"Millington",
    "sg:classifiers":[
        {
            "category":"Building & Trades",
            "subcategory":"Electrical",
            "type":"Services"
        }
    ],
    "sg:phone":"+1 908 647 2602",
    "sg:postcode":"07946",
    "sg:province":"NJ",
    "sg:tags":[
        "electrical",
        "contractor"
    ],
    "wof:name":"Cullen Electric Corp",
    "wof:placetype":"venue"
},
  "geometry": {"coordinates":[-74.486966,40.699912],"type":"Point"}
}