{
  "type": "Feature",
  "properties": {
    "iso:country":"US",
    "sg:address":"215 Nassau St",
    "sg:city":"Princeton",
    "sg:classifiers":[
        {
            "category":"Professional",
            "subcategory":"Business Services",
            "type":"Services"
        }
    ],
    "sg:phone":"+1 609 921 2827",
    "sg:postcode":"08542",
    "sg:province":"NJ",
    "wof:name":"Eastridge Design",
    "wof:placetype":"venue"
},
  "geometry": {"coordinates":[-74.653334,40.351479],"type":"Point"}
}