{
  "type": "Feature",
  "properties": {
    "iso:country":"US",
    "sg:address":"1254 US Highway 22",
    "sg:city":"Mountainside",
    "sg:classifiers":[
        {
            "category":"Autos & Motor Vehicles",
            "subcategory":"Automobile Sales",
            "type":"Retail Goods"
        }
    ],
    "sg:phone":"+1 908 687 5595",
    "sg:postcode":"07092",
    "sg:province":"NJ",
    "sg:tags":[
        "limo"
    ],
    "wof:name":"B & M Limousine",
    "wof:placetype":"venue"
},
  "geometry": {"coordinates":[-74.347397,40.6768],"type":"Point"}
}