{
  "type": "Feature",
  "properties": {
    "iso:country":"US",
    "sg:address":"479 74th St",
    "sg:city":"Brooklyn",
    "sg:classifiers":[
        {
            "category":"Wholesale",
            "subcategory":"Computers",
            "type":"Manufacturing & Wholesale Goods"
        }
    ],
    "sg:phone":"+1 718 833 5078",
    "sg:postcode":"11209",
    "sg:province":"NY",
    "wof:name":"Lucky Computer Online",
    "wof:placetype":"venue"
},
  "geometry": {"coordinates":[-74.284132,40.630743],"type":"Point"}
}