{
  "type": "Feature",
  "properties": {
    "addr:full":"326 Westfield Ave W Roselle Park NJ 07204",
    "addr:housenumber":"326",
    "addr:postcode":"07204",
    "addr:street":"Westfield Ave W",
    "iso:country":"US",
    "sg:address":"326 Westfield Ave W",
    "sg:city":"Roselle Park",
    "sg:classifiers":[
        {
            "category":"Manufacturing",
            "subcategory":"Printing",
            "type":"Manufacturing & Wholesale Goods"
        }
    ],
    "sg:phone":"+1 908 241 5540",
    "sg:postcode":"07204",
    "sg:province":"NJ",
    "sg:tags":[
        "printer"
    ],
    "wof:name":"Printfast",
    "wof:placetype":"venue"
},
  "geometry": {"coordinates":[-74.277198,40.659786],"type":"Point"}
}