{
  "type": "Feature",
  "properties": {
    "addr:full":"76 N Bridge St Somerville NJ 08876",
    "addr:housenumber":"76",
    "addr:postcode":"08876",
    "addr:street":"N Bridge St",
    "iso:country":"US",
    "sg:address":"76 N Bridge St",
    "sg:city":"Somerville",
    "sg:classifiers":[
        {
            "category":"Government",
            "subcategory":"Office",
            "type":"Public Place"
        }
    ],
    "sg:phone":"+1   ",
    "sg:postcode":"08876",
    "sg:province":"NJ",
    "sg:tags":[
        "legislative",
        "body"
    ],
    "wof:name":"District 16",
    "wof:placetype":"venue"
},
  "geometry": {"coordinates":[-74.610911,40.57058],"type":"Point"}
}