{
  "type": "Feature",
  "properties": {
    "addr:full":"110 N Black Horse Pike Williamstown NJ 08094",
    "addr:housenumber":"110",
    "addr:postcode":"08094",
    "addr:street":"N Black Horse Pike",
    "iso:country":"US",
    "sg:address":"110 N Black Horse Pike",
    "sg:city":"Williamstown",
    "sg:classifiers":[
        {
            "category":"Restaurant",
            "type":"Food & Drink"
        }
    ],
    "sg:menulink":"http://www.allmenus.com/nj/monroe/183627-kfc---kentucky-fried-chicken/menu/",
    "sg:phone":"+1 856 875 1812",
    "sg:postcode":"08094",
    "sg:province":"NJ",
    "sg:tags":[
        "american",
        "chicken"
    ],
    "wof:name":"KFC - Kentucky Fried Chicken",
    "wof:placetype":"venue"
},
  "geometry": {"coordinates":[-74.993864,39.690676],"type":"Point"}
}