{
  "type": "Feature",
  "properties": {
    "addr:full":"139 Haledon Ave Paterson NJ 07522",
    "addr:housenumber":"139",
    "addr:postcode":"07522",
    "addr:street":"Haledon Ave",
    "iso:country":"US",
    "sg:address":"139 Haledon Ave",
    "sg:city":"Paterson",
    "sg:classifiers":[
        {
            "category":"Health Services",
            "subcategory":"Doctor",
            "type":"Services"
        }
    ],
    "sg:phone":"+1 973 790 4747",
    "sg:postcode":"07522",
    "sg:province":"NJ",
    "sg:tags":[
        "dentist",
        "dental"
    ],
    "wof:name":"Dental Directions",
    "wof:placetype":"venue"
},
  "geometry": {"coordinates":[-74.173311,40.930529],"type":"Point"}
}