{
  "type": "Feature",
  "properties": {
    "iso:country":"US",
    "sg:address":"40 Sunshine Ln",
    "sg:city":"Edison",
    "sg:classifiers":[
        {
            "category":"Professional",
            "subcategory":"Computer Services",
            "type":"Services"
        }
    ],
    "sg:phone":"+1   ",
    "sg:postcode":"08820",
    "sg:province":"NJ",
    "sg:tags":[
        "development",
        "software"
    ],
    "wof:name":"Bnb Consulting Ltd",
    "wof:placetype":"venue"
},
  "geometry": {"coordinates":[-74.387586,40.557452],"type":"Point"}
}