{
  "type": "Feature",
  "properties": {
    "iso:country":"US",
    "sg:address":"2 Saddle Dr",
    "sg:city":"Saddle River",
    "sg:classifiers":[
        {
            "category":"Real Estate",
            "subcategory":"Real Estate Agent",
            "type":"Services"
        }
    ],
    "sg:phone":"+1   ",
    "sg:postcode":"07444",
    "sg:province":"NJ",
    "sg:tags":[
        "building",
        "opera",
        "nonresidential"
    ],
    "wof:name":"The Frassetto Companies",
    "wof:placetype":"venue"
},
  "geometry": {"coordinates":[-74.31070699999999,40.970717],"type":"Point"}
}