{
  "type": "Feature",
  "properties": {
    "addr:full":"Atlantic Ave & St Pu Wildwood NJ 08260",
    "addr:postcode":"08260",
    "addr:street":"Atlantic Ave & St",
    "iso:country":"US",
    "sg:address":"Atlantic Ave & St Pu",
    "sg:city":"Wildwood",
    "sg:classifiers":[
        {
            "category":"Travel",
            "subcategory":"Hotels & Motels",
            "type":"Entertainment"
        }
    ],
    "sg:phone":"+1 609 522 6400",
    "sg:postcode":"08260",
    "sg:province":"NJ",
    "sg:website":"www.carriagestopmotel.com",
    "wof:name":"Carriage Stop Motel the",
    "wof:placetype":"venue"
},
  "geometry": {"coordinates":[-74.821404,38.987701],"type":"Point"}
}