{
  "type": "Feature",
  "properties": {
    "iso:country":"US",
    "sg:address":"21 Autumn Ridge Dr",
    "sg:city":"Glassboro",
    "sg:classifiers":[
        {
            "category":"Professional",
            "subcategory":"Art Services",
            "type":"Services"
        }
    ],
    "sg:phone":"+1   ",
    "sg:postcode":"08028",
    "sg:province":"NJ",
    "sg:tags":[
        "commercial",
        "design"
    ],
    "wof:name":"Moonbyte Designs",
    "wof:placetype":"venue"
},
  "geometry": {"coordinates":[-75.112218,39.730485],"type":"Point"}
}