{
  "type": "Feature",
  "properties": {
    "iso:country":"US",
    "sg:address":"21 Allison Pl",
    "sg:city":"Egg Harbor Twp",
    "sg:classifiers":[
        {
            "category":"Professional",
            "subcategory":"Computer Services",
            "type":"Services"
        }
    ],
    "sg:phone":"+1 609 927 3243",
    "sg:postcode":"08234",
    "sg:province":"NJ",
    "sg:tags":[
        "repair"
    ],
    "wof:name":"PC Solutions",
    "wof:placetype":"venue"
},
  "geometry": {"coordinates":[-74.58737499999999,39.357498],"type":"Point"}
}