{
  "type": "Feature",
  "properties": {
    "iso:country":"US",
    "sg:address":"395 State Rt 17",
    "sg:city":"Mahwah",
    "sg:classifiers":[
        {
            "category":"Restaurant",
            "type":"Food & Drink"
        }
    ],
    "sg:menulink":"http://www.allmenus.com/nj/mahwah/94136-boston-market/menu/",
    "sg:phone":"+1 201 828 9399",
    "sg:postcode":"07430",
    "sg:province":"NJ",
    "sg:tags":[
        "barbecue",
        "american",
        "soup"
    ],
    "wof:name":"Boston Market",
    "wof:placetype":"venue"
},
  "geometry": {"coordinates":[-74.15208199999999,41.085576],"type":"Point"}
}