{
  "type": "Feature",
  "properties": {
    "iso:country":"US",
    "sg:address":"52 Sherman Ave",
    "sg:city":"Hawthorne",
    "sg:classifiers":[
        {
            "category":"Building & Trades",
            "subcategory":"Cleaning & Sanitation",
            "type":"Services"
        }
    ],
    "sg:phone":"+1   ",
    "sg:postcode":"07506",
    "sg:province":"NJ",
    "sg:tags":[
        "maintenance"
    ],
    "wof:name":"American Cleaning Services",
    "wof:placetype":"venue"
},
  "geometry": {"coordinates":[-74.143801,40.966085],"type":"Point"}
}