{
  "type": "Feature",
  "properties": {
    "iso:country":"US",
    "sg:address":"154 Lenox Ave",
    "sg:city":"New Milford",
    "sg:classifiers":[
        {
            "category":"Professional",
            "subcategory":"Management & Consulting",
            "type":"Services"
        }
    ],
    "sg:phone":"+1   ",
    "sg:postcode":"07646",
    "sg:province":"NJ",
    "wof:name":"Global Risk Solutions LLC",
    "wof:placetype":"venue"
},
  "geometry": {"coordinates":[-74.02110500000001,40.948157],"type":"Point"}
}