{
  "type": "Feature",
  "properties": {
    "addr:full":"25 Witherspoon St Princeton NJ 08542",
    "addr:housenumber":"25",
    "addr:postcode":"08542",
    "addr:street":"Witherspoon St",
    "iso:country":"US",
    "sg:address":"25 Witherspoon St",
    "sg:city":"Princeton",
    "sg:classifiers":[
        {
            "category":"Restaurant",
            "type":"Food & Drink"
        }
    ],
    "sg:menulink":"http://www.allmenus.com/nj/princeton/286364-la-mezzaluna/menu/",
    "sg:phone":"+1 609 688 8515",
    "sg:postcode":"08542",
    "sg:province":"NJ",
    "sg:tags":[
        "italian"
    ],
    "wof:name":"LA Mezzaluna",
    "wof:placetype":"venue"
},
  "geometry": {"coordinates":[-74.660107,40.350563],"type":"Point"}
}