{
  "type": "Feature",
  "properties": {
    "addr:full":"56 Spruce St Oakland NJ 07436",
    "addr:housenumber":"56",
    "addr:postcode":"07436",
    "addr:street":"Spruce St",
    "iso:country":"US",
    "sg:address":"56 Spruce St",
    "sg:city":"Oakland",
    "sg:classifiers":[
        {
            "category":"Wholesale",
            "subcategory":"Home Furnishings",
            "type":"Manufacturing & Wholesale Goods"
        }
    ],
    "sg:phone":"+1 201 337 3127",
    "sg:postcode":"07436",
    "sg:province":"NJ",
    "wof:name":"J B Fireplaces",
    "wof:placetype":"venue"
},
  "geometry": {"coordinates":[-74.25559699999999,41.019085],"type":"Point"}
}