{
  "type": "Feature",
  "properties": {
    "iso:country":"US",
    "sg:address":"930 N Delsea Dr",
    "sg:city":"Clayton",
    "sg:classifiers":[
        {
            "category":"Shopping",
            "subcategory":"Computers & Home Electronics",
            "type":"Retail Goods"
        },
        {
            "category":"Professional",
            "subcategory":"Computer Services",
            "type":"Services"
        }
    ],
    "sg:phone":"+1 856 307 0300",
    "sg:postcode":"08312",
    "sg:province":"NJ",
    "sg:tags":[
        "software",
        "programing",
        "custom"
    ],
    "wof:name":"Datamill Business Systems Inc",
    "wof:placetype":"venue"
},
  "geometry": {"coordinates":[-75.094921,39.669398],"type":"Point"}
}