{
  "type": "Feature",
  "properties": {
    "addr:full":"64 Academy St Belleville NJ 07109",
    "addr:housenumber":"64",
    "addr:postcode":"07109",
    "addr:street":"Academy St",
    "iso:country":"US",
    "sg:address":"64 Academy St",
    "sg:city":"Belleville",
    "sg:classifiers":[
        {
            "category":"Building & Trades",
            "subcategory":"Locksmith",
            "type":"Services"
        }
    ],
    "sg:phone":"+1 888 262 6721",
    "sg:postcode":"07109",
    "sg:province":"NJ",
    "sg:tags":[
        "key"
    ],
    "wof:name":"Anytime Anywhere Emergency Locksmith",
    "wof:placetype":"venue"
},
  "geometry": {"coordinates":[-74.15057899999999,40.788423],"type":"Point"}
}