{
  "type": "Feature",
  "properties": {
    "addr:full":"2 South Ave Fanwood NJ 07023",
    "addr:housenumber":"2",
    "addr:postcode":"07023",
    "addr:street":"South Ave",
    "iso:country":"US",
    "sg:address":"2 South Ave",
    "sg:city":"Fanwood",
    "sg:classifiers":[
        {
            "category":"Retail",
            "subcategory":"Auto Rental",
            "type":"Services"
        }
    ],
    "sg:phone":"+1 908 322 8280",
    "sg:postcode":"07023",
    "sg:province":"NJ",
    "sg:tags":[
        "renting",
        "truck",
        "leasing"
    ],
    "wof:name":"Penske Truck Rental",
    "wof:placetype":"venue"
},
  "geometry": {"coordinates":[-74.390799,40.636309],"type":"Point"}
}