{
  "type": "Feature",
  "properties": {
    "iso:country":"US",
    "sg:address":"21 White Horse Pike",
    "sg:city":"Chesilhurst",
    "sg:classifiers":[
        {
            "category":"Professional",
            "type":"Services"
        }
    ],
    "sg:phone":"+1 856 768 9086",
    "sg:postcode":"08089",
    "sg:province":"NJ",
    "sg:tags":[
        "establishment"
    ],
    "wof:name":"Delfino's",
    "wof:placetype":"venue"
},
  "geometry": {"coordinates":[-74.864476,39.729316],"type":"Point"}
}