{
  "type": "Feature",
  "properties": {
    "iso:country":"US",
    "sg:address":"16 Roderer Dr",
    "sg:city":"Raritan",
    "sg:classifiers":[
        {
            "category":"Professional",
            "type":"Services"
        }
    ],
    "sg:phone":"+1   ",
    "sg:postcode":"08869",
    "sg:province":"NJ",
    "wof:name":"Jaisai Inc",
    "wof:placetype":"venue"
},
  "geometry": {"coordinates":[-74.661197,40.579429],"type":"Point"}
}