{
  "type": "Feature",
  "properties": {
    "addr:full":"164 N County Line Rd Jackson NJ 08527",
    "addr:housenumber":"164",
    "addr:postcode":"08527",
    "addr:street":"N County Line Rd",
    "iso:country":"US",
    "sg:address":"164 N County Line Rd",
    "sg:city":"Jackson",
    "sg:classifiers":[
        {
            "category":"Building & Trades",
            "subcategory":"Electrical",
            "type":"Services"
        }
    ],
    "sg:phone":"+1   ",
    "sg:postcode":"08527",
    "sg:province":"NJ",
    "sg:tags":[
        "access",
        "installation",
        "sales",
        "integrated"
    ],
    "wof:name":"Rcs International",
    "wof:placetype":"venue"
},
  "geometry": {"coordinates":[-74.28601399999999,40.135397],"type":"Point"}
}