{
  "type": "Feature",
  "properties": {
    "addr:full":"1093 Magnolia Ave Elizabeth NJ 07201",
    "addr:housenumber":"1093",
    "addr:postcode":"07201",
    "addr:street":"Magnolia Ave",
    "iso:country":"US",
    "sg:address":"1093 Magnolia Ave",
    "sg:city":"Elizabeth",
    "sg:classifiers":[
        {
            "category":"Retail",
            "subcategory":"Auto Repair",
            "type":"Services"
        }
    ],
    "sg:phone":"+1 908 289 8805",
    "sg:postcode":"07201",
    "sg:province":"NJ",
    "sg:tags":[
        "repairing",
        "automobile"
    ],
    "wof:name":"Daphne Auto Repair",
    "wof:placetype":"venue"
},
  "geometry": {"coordinates":[-74.208697,40.668651],"type":"Point"}
}