{
  "type": "Feature",
  "properties": {
    "addr:full":"461 Watchung Ave Watchung NJ 07069",
    "addr:housenumber":"461",
    "addr:postcode":"07069",
    "addr:street":"Watchung Ave",
    "iso:country":"US",
    "sg:address":"461 Watchung Ave",
    "sg:city":"Watchung",
    "sg:classifiers":[
        {
            "category":"Professional",
            "subcategory":"Computer Services",
            "type":"Services"
        }
    ],
    "sg:phone":"+1   ",
    "sg:postcode":"07069",
    "sg:province":"NJ",
    "sg:tags":[
        "content",
        "educational",
        "software"
    ],
    "wof:name":"Penn Rhoads",
    "wof:placetype":"venue"
},
  "geometry": {"coordinates":[-74.44292900000001,40.6314],"type":"Point"}
}