{
  "type": "Feature",
  "properties": {
    "addr:full":"124 Francisco Ave Little Falls NJ 07424",
    "addr:housenumber":"124",
    "addr:postcode":"07424",
    "addr:street":"Francisco Ave",
    "iso:country":"US",
    "sg:address":"124 Francisco Ave",
    "sg:city":"Little Falls",
    "sg:classifiers":[
        {
            "category":"Building & Trades",
            "subcategory":"Construction",
            "type":"Services"
        }
    ],
    "sg:phone":"+1 973 812 0860",
    "sg:postcode":"07424",
    "sg:province":"NJ",
    "sg:tags":[
        "application",
        "specialty",
        "contractor"
    ],
    "wof:name":"John Harrington Associates",
    "wof:placetype":"venue"
},
  "geometry": {"coordinates":[-74.21177299999999,40.8696],"type":"Point"}
}