{
  "type": "Feature",
  "properties": {
    "addr:full":"1 Stonehenge Ct Jackson NJ 08527",
    "addr:housenumber":"1",
    "addr:postcode":"08527",
    "addr:street":"Stonehenge Ct",
    "iso:country":"US",
    "sg:address":"1 Stonehenge Ct",
    "sg:city":"Jackson",
    "sg:classifiers":[
        {
            "category":"Building & Trades",
            "subcategory":"Electrical",
            "type":"Services"
        }
    ],
    "sg:phone":"+1 732 833 8268",
    "sg:postcode":"08527",
    "sg:province":"NJ",
    "sg:tags":[
        "electrical",
        "contractor"
    ],
    "wof:name":"Alternative Electric",
    "wof:placetype":"venue"
},
  "geometry": {"coordinates":[-74.38642299999999,40.153856],"type":"Point"}
}