{
  "type": "Feature",
  "properties": {
    "iso:country":"US",
    "sg:address":"101 E Gloucester Pike",
    "sg:city":"Barrington",
    "sg:classifiers":[
        {
            "category":"Wholesale",
            "subcategory":"Medical Equipment & Supplies",
            "type":"Manufacturing & Wholesale Goods"
        },
        {
            "category":"Shopping",
            "subcategory":"Optical Goods",
            "type":"Retail Goods"
        },
        {
            "category":"Shopping",
            "subcategory":"Catalog Store",
            "type":"Retail Goods"
        }
    ],
    "sg:phone":"+1 856 547 3488",
    "sg:postcode":"08007",
    "sg:province":"NJ",
    "sg:tags":[
        "goods-wholesale",
        "binoculars",
        "machinery",
        "online",
        "mail",
        "order",
        "manufacturer"
    ],
    "sg:website":"http://www.edsci.com",
    "wof:name":"Edmund Optics, Inc.",
    "wof:placetype":"venue"
},
  "geometry": {"coordinates":[-75.051041,39.867012],"type":"Point"}
}