{
  "type": "Feature",
  "properties": {
    "addr:full":"63 Holly Hill Ter Vineland NJ 08360",
    "addr:housenumber":"63",
    "addr:postcode":"08360",
    "addr:street":"Holly Hill Ter",
    "iso:country":"US",
    "sg:address":"63 Holly Hill Ter",
    "sg:city":"Vineland",
    "sg:classifiers":[
        {
            "category":"Building & Trades",
            "subcategory":"Construction",
            "type":"Services"
        }
    ],
    "sg:phone":"+1 856 692 1960",
    "sg:postcode":"08360",
    "sg:province":"NJ",
    "sg:tags":[
        "house",
        "contractor"
    ],
    "wof:name":"Kelly Construction",
    "wof:placetype":"venue"
},
  "geometry": {"coordinates":[-75.04119799999999,39.481047],"type":"Point"}
}