{
  "type": "Feature",
  "properties": {
    "addr:full":"1 Schiverea Ave Freehold NJ 07728",
    "addr:housenumber":"1",
    "addr:postcode":"07728",
    "addr:street":"Schiverea Ave",
    "iso:country":"US",
    "sg:address":"1 Schiverea Ave",
    "sg:city":"Freehold",
    "sg:classifiers":[
        {
            "category":"Wholesale",
            "subcategory":"Machinery & Supplies",
            "type":"Manufacturing & Wholesale Goods"
        }
    ],
    "sg:phone":"+1 732 303 8369",
    "sg:postcode":"07728",
    "sg:province":"NJ",
    "sg:tags":[
        "equipment",
        "industrial"
    ],
    "wof:name":"J F L Associate Inc",
    "wof:placetype":"venue"
},
  "geometry": {"coordinates":[-74.265614,40.271665],"type":"Point"}
}