{
  "type": "Feature",
  "properties": {
    "addr:full":"955 Columbus Dr Teaneck NJ 07666",
    "addr:housenumber":"955",
    "addr:postcode":"07666",
    "addr:street":"Columbus Dr",
    "iso:country":"US",
    "sg:address":"955 Columbus Dr",
    "sg:city":"Teaneck",
    "sg:classifiers":[
        {
            "category":"Professional",
            "subcategory":"Management & Consulting",
            "type":"Services"
        }
    ],
    "sg:phone":"+1 201 833 0629",
    "sg:postcode":"07666",
    "sg:province":"NJ",
    "wof:name":"Godfrey Holder Consultants",
    "wof:placetype":"venue"
},
  "geometry": {"coordinates":[-73.994632,40.885015],"type":"Point"}
}