{
  "type": "Feature",
  "properties": {
    "iso:country":"US",
    "sg:address":"505 S Lenola Rd",
    "sg:city":"Moorestown",
    "sg:classifiers":[
        {
            "category":"Professional",
            "subcategory":"Lawyer & Legal Services",
            "type":"Services"
        }
    ],
    "sg:phone":"+1 856 235 4277",
    "sg:postcode":"08057",
    "sg:province":"NJ",
    "sg:tags":[
        "divorce",
        "attorney",
        "law",
        "adoption",
        "family"
    ],
    "wof:name":"Robertson Vincent L",
    "wof:placetype":"venue"
},
  "geometry": {"coordinates":[-74.968756,39.94561],"type":"Point"}
}