{
  "type": "Feature",
  "properties": {
    "iso:country":"US",
    "sg:address":"925 W Side Ave",
    "sg:city":"Jersey City",
    "sg:classifiers":[
        {
            "category":"Restaurant",
            "type":"Food & Drink"
        }
    ],
    "sg:phone":"+1 201 200 1771",
    "sg:postcode":"07306",
    "sg:province":"NJ",
    "sg:tags":[
        "banquet",
        "rooms"
    ],
    "wof:name":"Marbella Lounge",
    "wof:placetype":"venue"
},
  "geometry": {"coordinates":[-74.07283,40.73202],"type":"Point"}
}