{
  "type": "Feature",
  "properties": {
    "iso:country":"US",
    "sg:address":"307 Washington St",
    "sg:city":"Carlstadt",
    "sg:classifiers":[
        {
            "category":"Organizations",
            "subcategory":"Religious Organization",
            "type":"Services"
        }
    ],
    "sg:phone":"+1   ",
    "sg:postcode":"07072",
    "sg:province":"NJ",
    "wof:name":"Carlstadt Christian Assembly",
    "wof:placetype":"venue"
},
  "geometry": {"coordinates":[-74.097607,40.840415],"type":"Point"}
}