{
  "type": "Feature",
  "properties": {
    "iso:country":"US",
    "sg:address":"780 Seashore Rd",
    "sg:city":"Cape May",
    "sg:classifiers":[
        {
            "category":"Retail",
            "subcategory":"Funeral Services",
            "type":"Services"
        }
    ],
    "sg:phone":"+1 609 884 5130",
    "sg:postcode":"08204",
    "sg:province":"NJ",
    "sg:tags":[
        "cemetery"
    ],
    "sg:website":"www.oldbrickpresbyterian.com",
    "wof:name":"Cold Spring Presbyterian Cemetery",
    "wof:placetype":"venue"
},
  "geometry": {"coordinates":[-74.917198,38.973801],"type":"Point"}
}