{
  "type": "Feature",
  "properties": {
    "addr:full":"455 Diamond Spring Rd Denville NJ 07834",
    "addr:housenumber":"455",
    "addr:postcode":"07834",
    "addr:street":"Diamond Spring Rd",
    "iso:country":"US",
    "sg:address":"455 Diamond Spring Rd",
    "sg:city":"Denville",
    "sg:classifiers":[
        {
            "category":"Professional",
            "type":"Services"
        }
    ],
    "sg:phone":"+1   ",
    "sg:postcode":"07834",
    "sg:province":"NJ",
    "wof:name":"Cooks Pond LP",
    "wof:placetype":"venue"
},
  "geometry": {"coordinates":[-74.457415,40.911099],"type":"Point"}
}