{
  "type": "Feature",
  "properties": {
    "iso:country":"US",
    "sg:address":"902 Oak Tree Rd",
    "sg:city":"South Plainfield",
    "sg:classifiers":[
        {
            "category":"Professional",
            "subcategory":"Accounting & Tax Preparation",
            "type":"Services"
        }
    ],
    "sg:phone":"+1 908 668 0042",
    "sg:postcode":"07080",
    "sg:province":"NJ",
    "sg:tags":[
        "billing"
    ],
    "wof:name":"Advanced Billing Svc LLC",
    "wof:placetype":"venue"
},
  "geometry": {"coordinates":[-74.387021,40.577123],"type":"Point"}
}