{
  "type": "Feature",
  "properties": {
    "addr:full":"13 Main St Robbinsville NJ 08691",
    "addr:housenumber":"13",
    "addr:postcode":"08691",
    "addr:street":"Main St",
    "iso:country":"US",
    "sg:address":"13 Main St",
    "sg:city":"Robbinsville",
    "sg:classifiers":[
        {
            "category":"Wholesale",
            "subcategory":"Machinery & Supplies",
            "type":"Manufacturing & Wholesale Goods"
        }
    ],
    "sg:phone":"+1 609 259 9700",
    "sg:postcode":"08691",
    "sg:province":"NJ",
    "sg:tags":[
        "equipment",
        "chiropractor"
    ],
    "sg:website":"www.kmedsupplies.com",
    "wof:name":"K-Med Svc",
    "wof:placetype":"venue"
},
  "geometry": {"coordinates":[-74.625168,40.217238],"type":"Point"}
}