{
  "type": "Feature",
  "properties": {
    "iso:country":"US",
    "sg:address":"2666 US Hwy 130",
    "sg:city":"Cranbury",
    "sg:classifiers":[
        {
            "category":"Home & Garden",
            "subcategory":"Building Materials",
            "type":"Retail Goods"
        }
    ],
    "sg:phone":"+1 609 655 9100",
    "sg:postcode":"08512",
    "sg:province":"NJ",
    "sg:tags":[
        "door"
    ],
    "wof:name":"Hollow Metal Door & Metal Spec",
    "wof:placetype":"venue"
},
  "geometry": {"coordinates":[-74.508312,40.318348],"type":"Point"}
}