{
  "type": "Feature",
  "properties": {
    "addr:full":"87 S Main St Marlboro NJ 07746",
    "addr:housenumber":"87",
    "addr:postcode":"07746",
    "addr:street":"S Main St",
    "iso:country":"US",
    "sg:address":"87 S Main St",
    "sg:city":"Marlboro",
    "sg:classifiers":[
        {
            "category":"Sports & Exercise",
            "subcategory":"Gym",
            "type":"Entertainment"
        }
    ],
    "sg:phone":"+1 732 431 2233",
    "sg:postcode":"07746",
    "sg:province":"NJ",
    "sg:tags":[
        "fitness",
        "physical",
        "facility"
    ],
    "wof:name":"Slender Lady of Marlboro Inc",
    "wof:placetype":"venue"
},
  "geometry": {"coordinates":[-74.254508,40.299997],"type":"Point"}
}