{
  "type": "Feature",
  "properties": {
    "addr:full":"415 Totowa Rd Totowa NJ 07512",
    "addr:housenumber":"415",
    "addr:postcode":"07512",
    "addr:street":"Totowa Rd",
    "iso:country":"US",
    "sg:address":"415 Totowa Rd",
    "sg:city":"Totowa",
    "sg:classifiers":[
        {
            "category":"Health Services",
            "subcategory":"Optometrist",
            "type":"Services"
        }
    ],
    "sg:phone":"+1 973 595 0011",
    "sg:postcode":"07512",
    "sg:province":"NJ",
    "sg:tags":[
        "ophthalmologist"
    ],
    "sg:website":"www.searchmagnetlocal.com/show.p...",
    "wof:name":"Giliberti Eye Laser Center Totowa",
    "wof:placetype":"venue"
},
  "geometry": {"coordinates":[-74.212475,40.904711],"type":"Point"}
}