{
  "type": "Feature",
  "properties": {
    "addr:full":"2321 Atco Ave Atco NJ 08004",
    "addr:housenumber":"2321",
    "addr:postcode":"08004",
    "addr:street":"Atco Ave",
    "iso:country":"US",
    "sg:address":"2321 Atco Ave",
    "sg:city":"Atco",
    "sg:classifiers":[
        {
            "category":"Building & Trades",
            "subcategory":"Plumbing",
            "type":"Services"
        }
    ],
    "sg:phone":"+1 856 768 1620",
    "sg:postcode":"08004",
    "sg:province":"NJ",
    "sg:tags":[
        "contractor"
    ],
    "wof:name":"Trader Mechanical",
    "wof:placetype":"venue"
},
  "geometry": {"coordinates":[-74.880422,39.772764],"type":"Point"}
}