{
  "type": "Feature",
  "properties": {
    "addr:full":"23 Essex Ct Maywood NJ 07607",
    "addr:housenumber":"23",
    "addr:postcode":"07607",
    "addr:street":"Essex Ct",
    "iso:country":"US",
    "sg:address":"23 Essex Ct",
    "sg:city":"Maywood",
    "sg:classifiers":[
        {
            "category":"Professional",
            "type":"Services"
        }
    ],
    "sg:phone":"+1   ",
    "sg:postcode":"07607",
    "sg:province":"NJ",
    "wof:name":"Essex Gardens",
    "wof:placetype":"venue"
},
  "geometry": {"coordinates":[-74.066636,40.888963],"type":"Point"}
}