{
  "type": "Feature",
  "properties": {
    "addr:full":"823 S Orange Ave South Orange NJ 07079",
    "addr:housenumber":"823",
    "addr:postcode":"07079",
    "addr:street":"S Orange Ave",
    "iso:country":"US",
    "sg:address":"823 S Orange Ave",
    "sg:city":"South Orange",
    "sg:classifiers":[
        {
            "category":"Real Estate",
            "subcategory":"Real Estate Agent",
            "type":"Services"
        }
    ],
    "sg:phone":"+1 973 762 7300",
    "sg:postcode":"07079",
    "sg:province":"NJ",
    "wof:name":"Sharpe Realty",
    "wof:placetype":"venue"
},
  "geometry": {"coordinates":[-74.242,40.745835],"type":"Point"}
}