{
  "type": "Feature",
  "properties": {
    "iso:country":"US",
    "sg:address":"610 Main Ave",
    "sg:city":"Passaic",
    "sg:classifiers":[
        {
            "category":"Wholesale",
            "subcategory":"Machinery & Supplies",
            "type":"Manufacturing & Wholesale Goods"
        }
    ],
    "sg:phone":"+1 973 778 8338",
    "sg:postcode":"07055",
    "sg:province":"NJ",
    "sg:tags":[
        "equipment",
        "establishment"
    ],
    "wof:name":"Glory Beauty Supply Inc",
    "wof:placetype":"venue"
},
  "geometry": {"coordinates":[-74.123592,40.858502],"type":"Point"}
}