{
  "type": "Feature",
  "properties": {
    "addr:full":"95 Shongum Lake Rd Randolph NJ 07869",
    "addr:housenumber":"95",
    "addr:postcode":"07869",
    "addr:street":"Shongum Lake Rd",
    "iso:country":"US",
    "sg:address":"95 Shongum Lake Rd",
    "sg:city":"Randolph",
    "sg:classifiers":[
        {
            "category":"Recreation",
            "subcategory":"Water Park",
            "type":"Entertainment"
        },
        {
            "category":"Sports & Exercise",
            "subcategory":"Swimming Pool",
            "type":"Entertainment"
        }
    ],
    "sg:phone":"+1 973 361 8680",
    "sg:postcode":"07869",
    "sg:province":"NJ",
    "sg:tags":[
        "beach"
    ],
    "wof:name":"Shongum Lake",
    "wof:placetype":"venue"
},
  "geometry": {"coordinates":[-74.534649,40.845878],"type":"Point"}
}