{
  "type": "Feature",
  "properties": {
    "iso:country":"US",
    "sg:address":"432 Kearny Ave",
    "sg:city":"Kearny",
    "sg:classifiers":[
        {
            "category":"Personal",
            "type":"Services"
        }
    ],
    "sg:phone":"+1 201 991 4464",
    "sg:postcode":"07032",
    "sg:province":"NJ",
    "sg:tags":[
        "alteration",
        "sewing",
        "wear",
        "formal"
    ],
    "wof:name":"Ideal Tuxedos",
    "wof:placetype":"venue"
},
  "geometry": {"coordinates":[-74.14769699999999,40.765301],"type":"Point"}
}