{
  "type": "Feature",
  "properties": {
    "addr:full":"15 Lee Pl Paterson NJ 07505",
    "addr:housenumber":"15",
    "addr:postcode":"07505",
    "addr:street":"Lee Pl",
    "iso:country":"US",
    "sg:address":"15 Lee Pl",
    "sg:city":"Paterson",
    "sg:classifiers":[
        {
            "category":"Real Estate",
            "subcategory":"Real Estate Agent",
            "type":"Services"
        }
    ],
    "sg:phone":"+1   ",
    "sg:postcode":"07505",
    "sg:province":"NJ",
    "wof:name":"American Dream Home Realty",
    "wof:placetype":"venue"
},
  "geometry": {"coordinates":[-74.172301,40.913991],"type":"Point"}
}