{
  "type": "Feature",
  "properties": {
    "iso:country":"US",
    "sg:address":"1156 US Highway 46",
    "sg:city":"Little Falls",
    "sg:classifiers":[
        {
            "category":"Shopping",
            "subcategory":"Mobile Phones",
            "type":"Retail Goods"
        }
    ],
    "sg:phone":"+1 973 256 1575",
    "sg:postcode":"07424",
    "sg:province":"NJ",
    "sg:website":"t-mobile.com",
    "wof:name":"T-Mobile",
    "wof:placetype":"venue"
},
  "geometry": {"coordinates":[-74.21322000000001,40.884765],"type":"Point"}
}