{
  "type": "Feature",
  "properties": {
    "addr:full":"629 Abbington Dr Hightstown NJ 08520",
    "addr:housenumber":"629",
    "addr:postcode":"08520",
    "addr:street":"Abbington Dr",
    "iso:country":"US",
    "sg:address":"629 Abbington Dr",
    "sg:city":"Hightstown",
    "sg:classifiers":[
        {
            "category":"Shopping",
            "subcategory":"Pharmacy",
            "type":"Retail Goods"
        }
    ],
    "sg:phone":"+1   ",
    "sg:postcode":"08520",
    "sg:province":"NJ",
    "wof:name":"CVS",
    "wof:placetype":"venue"
},
  "geometry": {"coordinates":[-74.490032,40.266745],"type":"Point"}
}