{
  "type": "Feature",
  "properties": {
    "addr:full":"300 E Greentree Rd Marlton NJ 08053",
    "addr:housenumber":"300",
    "addr:postcode":"08053",
    "addr:street":"E Greentree Rd",
    "iso:country":"US",
    "sg:address":"300 E Greentree Rd",
    "sg:city":"Marlton",
    "sg:classifiers":[
        {
            "category":"Food & Beverages",
            "subcategory":"Groceries & Convenience Stores",
            "type":"Retail Goods"
        }
    ],
    "sg:phone":"+1 856 797 1112",
    "sg:postcode":"08053",
    "sg:province":"NJ",
    "sg:website":"www.7-eleven.com",
    "wof:name":"7-Eleven",
    "wof:placetype":"venue"
},
  "geometry": {"coordinates":[-74.919393,39.916529],"type":"Point"}
}