{
  "type": "Feature",
  "properties": {
    "iso:country":"US",
    "sg:address":"51 Afterglow Ave",
    "sg:city":"Verona",
    "sg:classifiers":[
        {
            "category":"Professional",
            "subcategory":"Management & Consulting",
            "type":"Services"
        }
    ],
    "sg:phone":"+1   ",
    "sg:postcode":"07044",
    "sg:province":"NJ",
    "sg:tags":[
        "consultant",
        "real estate"
    ],
    "wof:name":"Horizon Properties",
    "wof:placetype":"venue"
},
  "geometry": {"coordinates":[-74.23262099999999,40.820097],"type":"Point"}
}