{
  "type": "Feature",
  "properties": {
    "iso:country":"US",
    "sg:address":"85 Onondago Trl",
    "sg:city":"Medford",
    "sg:classifiers":[
        {
            "category":"Building & Trades",
            "subcategory":"Pest Control",
            "type":"Services"
        }
    ],
    "sg:phone":"+1 609 714 3185",
    "sg:postcode":"08055",
    "sg:province":"NJ",
    "wof:name":"Accu Pest Ltd Liability Co",
    "wof:placetype":"venue"
},
  "geometry": {"coordinates":[-74.815865,39.860094],"type":"Point"}
}