{
  "type": "Feature",
  "properties": {
    "addr:full":"30 Burgess Ave Spotswood NJ 08884",
    "addr:housenumber":"30",
    "addr:postcode":"08884",
    "addr:street":"Burgess Ave",
    "iso:country":"US",
    "sg:address":"30 Burgess Ave",
    "sg:city":"Spotswood",
    "sg:classifiers":[
        {
            "category":"Professional",
            "type":"Services"
        }
    ],
    "sg:phone":"+1   ",
    "sg:postcode":"08884",
    "sg:province":"NJ",
    "wof:name":"Barbara Peck",
    "wof:placetype":"venue"
},
  "geometry": {"coordinates":[-74.397007,40.391208],"type":"Point"}
}