{
  "type": "Feature",
  "properties": {
    "addr:full":"241 Cedar Knolls Rd Cedar Knolls NJ 07927",
    "addr:housenumber":"241",
    "addr:postcode":"07927",
    "addr:street":"Cedar Knolls Rd",
    "iso:country":"US",
    "sg:address":"241 Cedar Knolls Rd",
    "sg:city":"Cedar Knolls",
    "sg:classifiers":[
        {
            "category":"Professional",
            "subcategory":"Printing & Photocopies",
            "type":"Services"
        }
    ],
    "sg:phone":"+1 973 267 7200",
    "sg:postcode":"07927",
    "sg:province":"NJ",
    "wof:name":"V I P Copy & Printing Center",
    "wof:placetype":"venue"
},
  "geometry": {"coordinates":[-74.44650300000001,40.817299],"type":"Point"}
}