{
  "type": "Feature",
  "properties": {
    "addr:full":"3706 Church Rd Mount Laurel NJ 08054",
    "addr:housenumber":"3706",
    "addr:postcode":"08054",
    "addr:street":"Church Rd",
    "iso:country":"US",
    "sg:address":"3706 Church Rd",
    "sg:city":"Mount Laurel",
    "sg:classifiers":[
        {
            "category":"Health Services",
            "subcategory":"Nursing And Care Facility",
            "type":"Services"
        }
    ],
    "sg:phone":"+1   ",
    "sg:postcode":"08054",
    "sg:province":"NJ",
    "sg:tags":[
        "skilled"
    ],
    "wof:name":"Genesis",
    "wof:placetype":"venue"
},
  "geometry": {"coordinates":[-74.974807,39.929463],"type":"Point"}
}