{
  "type": "Feature",
  "properties": {
    "iso:country":"US",
    "sg:address":"17 Tamarack Rd",
    "sg:city":"Belvidere",
    "sg:classifiers":[
        {
            "category":"Professional",
            "type":"Services"
        }
    ],
    "sg:phone":"+1 908 453 4821",
    "sg:postcode":"07823",
    "sg:province":"NJ",
    "wof:name":"Dpv Adjustment Svc Inc",
    "wof:placetype":"venue"
},
  "geometry": {"coordinates":[-74.98783,40.83866],"type":"Point"}
}