{
  "type": "Feature",
  "properties": {
    "addr:full":"10 Progress St Union NJ 07083",
    "addr:housenumber":"10",
    "addr:postcode":"07083",
    "addr:street":"Progress St",
    "iso:country":"US",
    "sg:address":"10 Progress St",
    "sg:city":"Union",
    "sg:classifiers":[
        {
            "category":"Wholesale",
            "subcategory":"Electrical",
            "type":"Manufacturing & Wholesale Goods"
        }
    ],
    "sg:phone":"+1 908 277 0070",
    "sg:postcode":"07083",
    "sg:province":"NJ",
    "sg:tags":[
        "alarm",
        "burglar",
        "system"
    ],
    "sg:website":"www.bhsecurities.com",
    "wof:name":"B & H Security",
    "wof:placetype":"venue"
},
  "geometry": {"coordinates":[-74.300453,40.691431],"type":"Point"}
}