{
  "type": "Feature",
  "properties": {
    "addr:full":"573 Liberty Ave Jersey City NJ 07307",
    "addr:housenumber":"573",
    "addr:postcode":"07307",
    "addr:street":"Liberty Ave",
    "iso:country":"US",
    "sg:address":"573 Liberty Ave",
    "sg:city":"Jersey City",
    "sg:classifiers":[
        {
            "category":"Professional",
            "subcategory":"Management & Consulting",
            "type":"Services"
        }
    ],
    "sg:phone":"+1   ",
    "sg:postcode":"07307",
    "sg:province":"NJ",
    "wof:name":"Arch Consulting Inc",
    "wof:placetype":"venue"
},
  "geometry": {"coordinates":[-74.05136299999999,40.758165],"type":"Point"}
}