{
  "type": "Feature",
  "properties": {
    "addr:full":"57 Bruen St Newark NJ 07105",
    "addr:housenumber":"57",
    "addr:postcode":"07105",
    "addr:street":"Bruen St",
    "iso:country":"US",
    "sg:address":"57 Bruen St",
    "sg:city":"Newark",
    "sg:classifiers":[
        {
            "category":"Professional",
            "subcategory":"Advertising",
            "type":"Services"
        }
    ],
    "sg:phone":"+1 973 274 0052",
    "sg:postcode":"07105",
    "sg:province":"NJ",
    "sg:tags":[
        "counselor",
        "agency"
    ],
    "wof:name":"Nema Associates Inc",
    "wof:placetype":"venue"
},
  "geometry": {"coordinates":[-74.166118,40.731463],"type":"Point"}
}