{
  "type": "Feature",
  "properties": {
    "iso:country":"US",
    "sg:address":"1534 Pennington Rd",
    "sg:city":"Trenton",
    "sg:classifiers":[
        {
            "category":"Retail",
            "subcategory":"Funeral Services",
            "type":"Services"
        }
    ],
    "sg:phone":"+1 609 883 1400",
    "sg:postcode":"08618",
    "sg:province":"NJ",
    "sg:tags":[
        "director",
        "home"
    ],
    "wof:name":"Orland's Ewing Memorial Chapel",
    "wof:placetype":"venue"
},
  "geometry": {"coordinates":[-74.776572,40.251726],"type":"Point"}
}