{
  "type": "Feature",
  "properties": {
    "iso:country":"US",
    "sg:address":"214 California Trl",
    "sg:city":"Browns Mills",
    "sg:classifiers":[
        {
            "category":"Arts & Performance",
            "subcategory":"Theater",
            "type":"Entertainment"
        }
    ],
    "sg:phone":"+1 609 893 7000",
    "sg:postcode":"08015",
    "sg:province":"NJ",
    "sg:tags":[
        "magician"
    ],
    "wof:name":"B Happie Entertainment",
    "wof:placetype":"venue"
},
  "geometry": {"coordinates":[-74.567221,39.918302],"type":"Point"}
}