{
  "type": "Feature",
  "properties": {
    "addr:full":"752 Ridge Road Ter Butler NJ 07405",
    "addr:housenumber":"752",
    "addr:postcode":"07405",
    "addr:street":"Ridge Road Ter",
    "iso:country":"US",
    "sg:address":"752 Ridge Road Ter",
    "sg:city":"Butler",
    "sg:classifiers":[
        {
            "category":"Wholesale",
            "subcategory":"Office Equipment",
            "type":"Manufacturing & Wholesale Goods"
        }
    ],
    "sg:phone":"+1 973 838 5844",
    "sg:postcode":"07405",
    "sg:province":"NJ",
    "wof:name":"Arw Equipment Company",
    "wof:placetype":"venue"
},
  "geometry": {"coordinates":[-74.413787,41.016464],"type":"Point"}
}