{
  "type": "Feature",
  "properties": {
    "addr:full":"322 2nd St Jersey City NJ 07302",
    "addr:housenumber":"322",
    "addr:postcode":"07302",
    "addr:street":"2Nd St",
    "iso:country":"US",
    "sg:address":"322 2nd St",
    "sg:city":"Jersey City",
    "sg:classifiers":[
        {
            "category":"Bars & Pubs",
            "subcategory":"Dive Bar",
            "type":"Food & Drink"
        }
    ],
    "sg:phone":"+1 201 418 8585",
    "sg:postcode":"07302",
    "sg:province":"NJ",
    "wof:name":"Lucky 7",
    "wof:placetype":"venue"
},
  "geometry": {"coordinates":[-74.047416,40.722957],"type":"Point"}
}