{
  "type": "Feature",
  "properties": {
    "iso:country":"US",
    "sg:address":"319 Stout Ave",
    "sg:city":"Scotch Plains",
    "sg:classifiers":[
        {
            "category":"Building & Trades",
            "subcategory":"Plumbing",
            "type":"Services"
        }
    ],
    "sg:phone":"+1 908 322 6542",
    "sg:postcode":"07076",
    "sg:province":"NJ",
    "sg:tags":[
        "contractor"
    ],
    "wof:name":"D Natale Son Plbg Htg",
    "wof:placetype":"venue"
},
  "geometry": {"coordinates":[-74.39743300000001,40.654327],"type":"Point"}
}