{
  "type": "Feature",
  "properties": {
    "addr:full":"10 Dartmouth Ct Marlton NJ 08053",
    "addr:housenumber":"10",
    "addr:postcode":"08053",
    "addr:street":"Dartmouth Ct",
    "iso:country":"US",
    "sg:address":"10 Dartmouth Ct",
    "sg:city":"Marlton",
    "sg:classifiers":[
        {
            "category":"Retail",
            "subcategory":"Portrait Studio",
            "type":"Services"
        }
    ],
    "sg:phone":"+1   ",
    "sg:postcode":"08053",
    "sg:province":"NJ",
    "sg:tags":[
        "photo"
    ],
    "wof:name":"Mary Quinn Photography Inc",
    "wof:placetype":"venue"
},
  "geometry": {"coordinates":[-74.882954,39.856126],"type":"Point"}
}