{
  "type": "Feature",
  "properties": {
    "addr:full":"338 Union Hill Rd Englishtown NJ 07726",
    "addr:housenumber":"338",
    "addr:postcode":"07726",
    "addr:street":"Union Hill Rd",
    "iso:country":"US",
    "sg:address":"338 Union Hill Rd",
    "sg:city":"Englishtown",
    "sg:classifiers":[
        {
            "category":"Food & Beverages",
            "subcategory":"Groceries & Convenience Stores",
            "type":"Retail Goods"
        },
        {
            "category":"Restaurant",
            "type":"Food & Drink"
        }
    ],
    "sg:phone":"+1 732 536 4616",
    "sg:postcode":"07726",
    "sg:province":"NJ",
    "sg:tags":[
        "bakery",
        "delicatessen"
    ],
    "wof:name":"Bagel Time Deli Inc",
    "wof:placetype":"venue"
},
  "geometry": {"coordinates":[-74.32217900000001,40.335156],"type":"Point"}
}