{
  "type": "Feature",
  "properties": {
    "addr:full":"600 13th Ave Belmar NJ 07719",
    "addr:housenumber":"600",
    "addr:postcode":"07719",
    "addr:street":"13Th Ave",
    "iso:country":"US",
    "sg:address":"600 13th Ave",
    "sg:city":"Belmar",
    "sg:classifiers":[
        {
            "category":"Organizations",
            "subcategory":"Religious Organization",
            "type":"Services"
        }
    ],
    "sg:phone":"+1 732 681 0940",
    "sg:postcode":"07719",
    "sg:province":"NJ",
    "sg:tags":[
        "church"
    ],
    "wof:name":"Calvary Baptist Church Inc",
    "wof:placetype":"venue"
},
  "geometry": {"coordinates":[-74.02668199999999,40.176395],"type":"Point"}
}