{
  "type": "Feature",
  "properties": {
    "addr:full":"1 Riverside Sq Hackensack NJ 07601",
    "addr:housenumber":"1",
    "addr:postcode":"07601",
    "addr:street":"Riverside Sq",
    "iso:country":"US",
    "sg:address":"1 Riverside Sq",
    "sg:city":"Hackensack",
    "sg:classifiers":[
        {
            "category":"Restaurant",
            "type":"Food & Drink"
        }
    ],
    "sg:phone":"+1 201 487 1303",
    "sg:postcode":"07601",
    "sg:province":"NJ",
    "sg:website":"www.mortons.com",
    "wof:name":"Morton's of Chicago-the Steakhouse",
    "wof:placetype":"venue"
},
  "geometry": {"coordinates":[-74.032402,40.9086],"type":"Point"}
}