{
  "type": "Feature",
  "properties": {
    "addr:full":"375 State St Perth Amboy NJ 08861",
    "addr:housenumber":"375",
    "addr:postcode":"08861",
    "addr:street":"State St",
    "iso:country":"US",
    "sg:address":"375 State St",
    "sg:city":"Perth Amboy",
    "sg:classifiers":[
        {
            "category":"Building & Trades",
            "subcategory":"Construction",
            "type":"Services"
        }
    ],
    "sg:phone":"+1 732 442 2367",
    "sg:postcode":"08861",
    "sg:province":"NJ",
    "sg:tags":[
        "hanging",
        "contractor"
    ],
    "wof:name":"I C E Painter",
    "wof:placetype":"venue"
},
  "geometry": {"coordinates":[-74.26648400000001,40.511254],"type":"Point"}
}