{
  "type": "Feature",
  "properties": {
    "addr:full":"312 Frelinghuysen Ave Newark NJ 07114",
    "addr:housenumber":"312",
    "addr:postcode":"07114",
    "addr:street":"Frelinghuysen Ave",
    "iso:country":"US",
    "sg:address":"312 Frelinghuysen Ave",
    "sg:city":"Newark",
    "sg:classifiers":[
        {
            "category":"Government",
            "subcategory":"Jail",
            "type":"Public Place"
        }
    ],
    "sg:phone":"+1 973 273 2088",
    "sg:postcode":"07114",
    "sg:province":"NJ",
    "sg:tags":[
        "govt",
        "state",
        "institution"
    ],
    "wof:name":"Community Corrections Corp",
    "wof:placetype":"venue"
},
  "geometry": {"coordinates":[-74.19161,40.708794],"type":"Point"}
}