{
  "type": "Feature",
  "properties": {
    "addr:full":"127 Harrison Ave Westfield NJ 07090",
    "addr:housenumber":"127",
    "addr:postcode":"07090",
    "addr:street":"Harrison Ave",
    "iso:country":"US",
    "sg:address":"127 Harrison Ave",
    "sg:city":"Westfield",
    "sg:classifiers":[
        {
            "category":"Manufacturing",
            "subcategory":"Printing",
            "type":"Manufacturing & Wholesale Goods"
        }
    ],
    "sg:phone":"+1 908 233 0530",
    "sg:postcode":"07090",
    "sg:province":"NJ",
    "sg:tags":[
        "commercial"
    ],
    "wof:name":"Union County Letterpress",
    "wof:placetype":"venue"
},
  "geometry": {"coordinates":[-74.34562,40.657644],"type":"Point"}
}