{
  "type": "Feature",
  "properties": {
    "iso:country":"US",
    "sg:address":"100 Bauer Dr",
    "sg:city":"Oakland",
    "sg:classifiers":[
        {
            "category":"Recreation",
            "type":"Entertainment"
        }
    ],
    "sg:phone":"+1   ",
    "sg:postcode":"07436",
    "sg:province":"NJ",
    "sg:tags":[
        "club",
        "private"
    ],
    "wof:name":"Lakeside Trainers Club LLC",
    "wof:placetype":"venue"
},
  "geometry": {"coordinates":[-74.237312,41.009201],"type":"Point"}
}