{
  "type": "Feature",
  "properties": {
    "addr:full":"700 Nye Ave Irvington NJ 07111",
    "addr:housenumber":"700",
    "addr:postcode":"07111",
    "addr:street":"Nye Ave",
    "iso:country":"US",
    "sg:address":"700 Nye Ave",
    "sg:city":"Irvington",
    "sg:classifiers":[
        {
            "category":"Professional",
            "subcategory":"Lawyer & Legal Services",
            "type":"Services"
        }
    ],
    "sg:phone":"+1 973 375 6262",
    "sg:postcode":"07111",
    "sg:province":"NJ",
    "sg:tags":[
        "attorney"
    ],
    "wof:name":"Jonathan St Preux & Assoc",
    "wof:placetype":"venue"
},
  "geometry": {"coordinates":[-74.235798,40.725033],"type":"Point"}
}