{
  "type": "Feature",
  "properties": {
    "iso:country":"US",
    "sg:address":"102 Webster Dr",
    "sg:city":"Wayne",
    "sg:classifiers":[
        {
            "category":"Banks & Credit Unions",
            "subcategory":"Investment Brokerage",
            "type":"Services"
        }
    ],
    "sg:phone":"+1 973 696 5299",
    "sg:postcode":"07470",
    "sg:province":"NJ",
    "sg:tags":[
        "commodity",
        "contract"
    ],
    "wof:name":"U S Commodity Consultants",
    "wof:placetype":"venue"
},
  "geometry": {"coordinates":[-74.26261100000001,40.956863],"type":"Point"}
}