{
  "type": "Feature",
  "properties": {
    "addr:full":"55 Wanaque Ave Ste 13B Pompton Lakes NJ 07442",
    "addr:housenumber":"55",
    "addr:postcode":"07442",
    "addr:street":"Wanaque Ave Ste 13B",
    "iso:country":"US",
    "sg:address":"55 Wanaque Ave Ste 13B",
    "sg:city":"Pompton Lakes",
    "sg:classifiers":[
        {
            "category":"Home & Garden",
            "subcategory":"Hardware",
            "type":"Retail Goods"
        }
    ],
    "sg:phone":"+1 973 831 2501",
    "sg:postcode":"07442",
    "sg:province":"NJ",
    "sg:tags":[
        "store"
    ],
    "sg:website":"www.fergusonbrotherspaint.com/ge...",
    "wof:name":"Ferguson Brothers Paint & Supply",
    "wof:placetype":"venue"
},
  "geometry": {"coordinates":[-74.293052,41.007269],"type":"Point"}
}