{
  "type": "Feature",
  "properties": {
    "iso:country":"US",
    "sg:address":"17 Scott St",
    "sg:city":"Butler",
    "sg:classifiers":[
        {
            "category":"Professional",
            "subcategory":"Computer Services",
            "type":"Services"
        }
    ],
    "sg:phone":"+1 973 838 1961",
    "sg:postcode":"07405",
    "sg:province":"NJ",
    "sg:tags":[
        "processing",
        "datum"
    ],
    "wof:name":"Gemini Data Works",
    "wof:placetype":"venue"
},
  "geometry": {"coordinates":[-74.343425,40.997497],"type":"Point"}
}