{
  "type": "Feature",
  "properties": {
    "addr:full":"320 State Rte 10 Whippany NJ 07981",
    "addr:housenumber":"320",
    "addr:postcode":"07981",
    "addr:street":"State Rte 10",
    "iso:country":"US",
    "sg:address":"320 State Rte 10",
    "sg:city":"Whippany",
    "sg:classifiers":[
        {
            "category":"Home & Garden",
            "subcategory":"Furniture",
            "type":"Retail Goods"
        }
    ],
    "sg:phone":"+1   ",
    "sg:postcode":"07981",
    "sg:province":"NJ",
    "wof:name":"Dial A Mattress",
    "wof:placetype":"venue"
},
  "geometry": {"coordinates":[-74.401989,40.816857],"type":"Point"}
}