{
  "type": "Feature",
  "properties": {
    "iso:country":"US",
    "sg:address":"158 Dutch Lane Rd",
    "sg:city":"Marlboro",
    "sg:classifiers":[
        {
            "category":"Professional",
            "subcategory":"Advertising",
            "type":"Services"
        }
    ],
    "sg:phone":"+1 732 431 4488",
    "sg:postcode":"07746",
    "sg:province":"NJ",
    "sg:tags":[
        "agency"
    ],
    "wof:name":"RSM Marketing Inc of NJ",
    "wof:placetype":"venue"
},
  "geometry": {"coordinates":[-74.224161,40.300978],"type":"Point"}
}