{
  "type": "Feature",
  "properties": {
    "addr:full":"52 Eagle Rim Rd Upper Saddle Rvr NJ 07458",
    "addr:housenumber":"52",
    "addr:postcode":"07458",
    "addr:street":"Eagle Rim Rd Upper Saddle Rvr",
    "iso:country":"US",
    "sg:address":"52 Eagle Rim Rd",
    "sg:city":"Upper Saddle Rvr",
    "sg:classifiers":[
        {
            "category":"Shopping",
            "subcategory":"Computers & Home Electronics",
            "type":"Retail Goods"
        }
    ],
    "sg:phone":"+1 201 760 2322",
    "sg:postcode":"07458",
    "sg:province":"NJ",
    "sg:tags":[
        "equipment",
        "dealer"
    ],
    "wof:name":"Palomino Computer",
    "wof:placetype":"venue"
},
  "geometry": {"coordinates":[-74.106296,41.066697],"type":"Point"}
}