{
  "type": "Feature",
  "properties": {
    "addr:full":"300 E Evesham Rd Cherry Hill NJ 08003",
    "addr:housenumber":"300",
    "addr:postcode":"08003",
    "addr:street":"E Evesham Rd",
    "iso:country":"US",
    "sg:address":"300 E Evesham Rd",
    "sg:city":"Cherry Hill",
    "sg:classifiers":[
        {
            "category":"Shopping",
            "subcategory":"Bicycles & Sporting Goods",
            "type":"Retail Goods"
        }
    ],
    "sg:phone":"+1 856 428 1619",
    "sg:postcode":"08003",
    "sg:province":"NJ",
    "sg:tags":[
        "equipment",
        "clothing",
        "golf",
        "supply"
    ],
    "wof:name":"Dick Smith Jr's Golf Shop",
    "wof:placetype":"venue"
},
  "geometry": {"coordinates":[-74.97532699999999,39.860588],"type":"Point"}
}