{
  "type": "Feature",
  "properties": {
    "addr:full":"2 Lincoln Pl Garfield NJ 07026",
    "addr:housenumber":"2",
    "addr:postcode":"07026",
    "addr:street":"Lincoln Pl",
    "iso:country":"US",
    "sg:address":"2 Lincoln Pl",
    "sg:city":"Garfield",
    "sg:classifiers":[
        {
            "category":"Organizations",
            "subcategory":"Religious Organization",
            "type":"Services"
        }
    ],
    "sg:phone":"+1 973 472 3059",
    "sg:postcode":"07026",
    "sg:province":"NJ",
    "sg:tags":[
        "church"
    ],
    "wof:name":"Beth Israel Messianic Cngrgtn",
    "wof:placetype":"venue"
},
  "geometry": {"coordinates":[-74.102633,40.867374],"type":"Point"}
}