{
  "type": "Feature",
  "properties": {
    "iso:country":"US",
    "sg:address":"502 Springfield Ave",
    "sg:city":"Newark",
    "sg:classifiers":[
        {
            "category":"Personal",
            "subcategory":"Beauty Salon",
            "type":"Services"
        }
    ],
    "sg:phone":"+1 973 624 8600",
    "sg:postcode":"07103",
    "sg:province":"NJ",
    "wof:name":"Vizions Layerz",
    "wof:placetype":"venue"
},
  "geometry": {"coordinates":[-74.20285800000001,40.731901],"type":"Point"}
}