{
  "type": "Feature",
  "properties": {
    "addr:full":"511 E Gibbsboro Rd Clementon NJ 08021",
    "addr:housenumber":"511",
    "addr:postcode":"08021",
    "addr:street":"E Gibbsboro Rd",
    "iso:country":"US",
    "sg:address":"511 E Gibbsboro Rd",
    "sg:city":"Clementon",
    "sg:classifiers":[
        {
            "category":"Building & Trades",
            "subcategory":"Construction",
            "type":"Services"
        }
    ],
    "sg:phone":"+1 856 655 2639",
    "sg:postcode":"08021",
    "sg:province":"NJ",
    "sg:tags":[
        "contractor"
    ],
    "wof:name":"Alt Contracting & Home Rmdlg",
    "wof:placetype":"venue"
},
  "geometry": {"coordinates":[-74.98027399999999,39.818537],"type":"Point"}
}