{
  "type": "Feature",
  "properties": {
    "iso:country":"US",
    "sg:address":"138 E Bergen Pl",
    "sg:city":"Red Bank",
    "sg:classifiers":[
        {
            "category":"Social Services",
            "type":"Services"
        }
    ],
    "sg:phone":"+1 732 842 7177",
    "sg:postcode":"07701",
    "sg:province":"NJ",
    "wof:name":"Childrens Cultural Center At R",
    "wof:placetype":"venue"
},
  "geometry": {"coordinates":[-74.06382000000001,40.342395],"type":"Point"}
}