{
  "type": "Feature",
  "properties": {
    "iso:country":"US",
    "sg:address":"401 Mount Laurel Rd",
    "sg:city":"Mt Laurel",
    "sg:classifiers":[
        {
            "category":"Building & Trades",
            "subcategory":"Construction",
            "type":"Services"
        }
    ],
    "sg:phone":"+1 856 222 4226",
    "sg:postcode":"08054",
    "sg:province":"NJ",
    "sg:tags":[
        "concrete",
        "contractor"
    ],
    "wof:name":"Tycon Construction Co Inc",
    "wof:placetype":"venue"
},
  "geometry": {"coordinates":[-74.90069,39.94066],"type":"Point"}
}