{
  "type": "Feature",
  "properties": {
    "iso:country":"US",
    "sg:address":"287 Pompton Ave",
    "sg:city":"Verona",
    "sg:classifiers":[
        {
            "category":"Personal",
            "subcategory":"Beauty Salon",
            "type":"Services"
        }
    ],
    "sg:phone":"+1 973 239 3959",
    "sg:postcode":"07044",
    "sg:province":"NJ",
    "sg:tags":[
        "shop"
    ],
    "wof:name":"Mirrors Salon",
    "wof:placetype":"venue"
},
  "geometry": {"coordinates":[-74.22713299999999,40.833907],"type":"Point"}
}