{
  "type": "Feature",
  "properties": {
    "addr:full":"30 Broadway Pt Pleasant Bch NJ 08742",
    "addr:housenumber":"30",
    "addr:postcode":"08742",
    "addr:street":"Broadway Pt",
    "iso:country":"US",
    "sg:address":"30 Broadway",
    "sg:city":"Pt Pleasant Bch",
    "sg:classifiers":[
        {
            "category":"Autos & Motor Vehicles",
            "subcategory":"Boat Sales",
            "type":"Retail Goods"
        },
        {
            "category":"Recreation",
            "subcategory":"Marina",
            "type":"Entertainment"
        }
    ],
    "sg:phone":"+1 732 892 9787",
    "sg:postcode":"08742",
    "sg:province":"NJ",
    "sg:tags":[
        "dealer",
        "sales"
    ],
    "sg:website":"www.normak.com",
    "wof:name":"Ken's Landing",
    "wof:placetype":"venue"
},
  "geometry": {"coordinates":[-74.03683100000001,40.100463],"type":"Point"}
}