{
  "type": "Feature",
  "properties": {
    "iso:country":"US",
    "sg:address":"234 Stuyvesant Ave",
    "sg:city":"Lyndhurst",
    "sg:classifiers":[
        {
            "category":"Personal",
            "subcategory":"Barber",
            "type":"Services"
        }
    ],
    "sg:phone":"+1 201 933 7743",
    "sg:postcode":"07071",
    "sg:province":"NJ",
    "wof:name":"Prestige Barber Shop",
    "wof:placetype":"venue"
},
  "geometry": {"coordinates":[-74.12529600000001,40.815187],"type":"Point"}
}