{
  "type": "Feature",
  "properties": {
    "iso:country":"US",
    "sg:address":"209 Haddonfield Berlin Rd",
    "sg:city":"Voorhees",
    "sg:classifiers":[
        {
            "category":"Restaurant",
            "type":"Food & Drink"
        }
    ],
    "sg:menulink":"http://www.allmenus.com/nj/voorhees/194509-mcdonalds/menu/",
    "sg:phone":"+1 856 566 9670",
    "sg:postcode":"08043",
    "sg:province":"NJ",
    "sg:tags":[
        "burger",
        "american"
    ],
    "wof:name":"McDonald's",
    "wof:placetype":"venue"
},
  "geometry": {"coordinates":[-74.986718,39.857881],"type":"Point"}
}