{
  "type": "Feature",
  "properties": {
    "iso:country":"US",
    "sg:address":"384 Stockton St",
    "sg:city":"Hightstown",
    "sg:classifiers":[
        {
            "category":"Professional",
            "subcategory":"Business Services",
            "type":"Services"
        }
    ],
    "sg:phone":"+1   ",
    "sg:postcode":"08520",
    "sg:province":"NJ",
    "wof:name":"Foundation For Education",
    "wof:placetype":"venue"
},
  "geometry": {"coordinates":[-74.533224,40.271195],"type":"Point"}
}