{
  "type": "Feature",
  "properties": {
    "addr:full":"146 Katz Ave Paterson NJ 07502",
    "addr:housenumber":"146",
    "addr:postcode":"07502",
    "addr:street":"Katz Ave",
    "iso:country":"US",
    "sg:address":"146 Katz Ave",
    "sg:city":"Paterson",
    "sg:classifiers":[
        {
            "category":"Professional",
            "type":"Services"
        }
    ],
    "sg:phone":"+1   ",
    "sg:postcode":"07502",
    "sg:province":"NJ",
    "wof:name":"Professional Limosine Service",
    "wof:placetype":"venue"
},
  "geometry": {"coordinates":[-74.193969,40.929048],"type":"Point"}
}