{
  "type": "Feature",
  "properties": {
    "iso:country":"US",
    "sg:address":"2954 E Grant Ave",
    "sg:city":"Williamstown",
    "sg:classifiers":[
        {
            "category":"Shopping",
            "subcategory":"Musical Instruments",
            "type":"Retail Goods"
        }
    ],
    "sg:phone":"+1 856 728 7888",
    "sg:postcode":"08094",
    "sg:province":"NJ",
    "sg:tags":[
        "music",
        "dealer"
    ],
    "wof:name":"Classical Music Fund",
    "wof:placetype":"venue"
},
  "geometry": {"coordinates":[-74.999774,39.636215],"type":"Point"}
}