{
  "type": "Feature",
  "properties": {
    "addr:full":"11 Brunswick Woods Dr East Brunswick NJ 08816",
    "addr:housenumber":"11",
    "addr:postcode":"08816",
    "addr:street":"Brunswick Woods Dr",
    "iso:country":"US",
    "sg:address":"11 Brunswick Woods Dr",
    "sg:city":"East Brunswick",
    "sg:classifiers":[
        {
            "category":"Professional",
            "type":"Services"
        }
    ],
    "sg:phone":"+1   ",
    "sg:postcode":"08816",
    "sg:province":"NJ",
    "wof:name":"Liangs Cad Service",
    "wof:placetype":"venue"
},
  "geometry": {"coordinates":[-74.390028,40.421015],"type":"Point"}
}