{
  "type": "Feature",
  "properties": {
    "addr:full":"136 State Rte 72 Barnegat NJ 08005",
    "addr:housenumber":"136",
    "addr:postcode":"08005",
    "addr:street":"State Rte 72",
    "iso:country":"US",
    "sg:address":"136 State Rte 72",
    "sg:city":"Barnegat",
    "sg:classifiers":[
        {
            "category":"Professional",
            "subcategory":"Employment Agencies",
            "type":"Services"
        }
    ],
    "sg:phone":"+1   ",
    "sg:postcode":"08005",
    "sg:province":"NJ",
    "sg:tags":[
        "help",
        "supply"
    ],
    "wof:name":"Cimber Staffing Services",
    "wof:placetype":"venue"
},
  "geometry": {"coordinates":[-74.322475,39.766369],"type":"Point"}
}