{
  "type": "Feature",
  "properties": {
    "iso:country":"US",
    "sg:address":"472 Weston Canal Rd",
    "sg:city":"Somerset",
    "sg:classifiers":[
        {
            "category":"Banks & Credit Unions",
            "subcategory":"Bank",
            "type":"Services"
        }
    ],
    "sg:phone":"+1   ",
    "sg:postcode":"08873",
    "sg:province":"NJ",
    "sg:tags":[
        "federal"
    ],
    "wof:name":"PSE Federal Credit Union",
    "wof:placetype":"venue"
},
  "geometry": {"coordinates":[-74.556735,40.546793],"type":"Point"}
}